Workbook

Sheet Comparativa Clientes
A1: CODIAGRO – Ventas por cliente: 2025 vs 2026 (real a 30/09) vs estimación de cierre 2026
A2: Importes en € (Importe Neto). Estimación 2026 = Real ene-ago + Previsión sep-dic del fichero de presupuesto de los comerciales.
A4: Umbrales de valoración (editables): | C4: 'Alcanzable' si el crecimiento necesario en oct-dic vs oct-dic 2025 es ≤ | E4: 0.15
C5: 'Exigente' si es ≤ (por encima: 'Poco realista') | E5: 0.4
A7: Comercial | B7: País | C7: Cliente | D7: Clasificación cliente | E7: Ventas 2025 (año completo) | F7: Ventas ene-sep 2025 | G7: Ventas oct-dic 2025 | H7: Ventas 2026 ene-sep (real) | I7: Estimación cierre 2026 | J7: Crec. real ene-sep 26 vs 25 | K7: Crec. estimado 2026 vs 2025 | L7: Pendiente por vender oct-dic 2026 | M7: Crec. necesario oct-dic 26 vs oct-dic 25 | N7: % de la estimación ya vendido | O7: Valoración | P7: Estim. real ene-ago (ppto.) | Q7: Previsión sep-dic (ppto.)
A8: Alfonso | B8: ESPAÑA | C8: VILLALTA SATIVUM, S.L. | D8: Consolidado/estratégico | E8: 81222.08 | F8: 81222.08 | G8: =E8-F8 -> 0 | H8: 89256.34 | I8: =P8+Q8 -> 84614.46 | J8: =IF(F8<=0,"n/a",H8/F8-1) -> 0.098917191 | K8: =IF(E8<=0,"n/a",I8/E8-1) -> 0.041766722 | L8: =IF(I8=0,0,I8-H8) -> -4641.88 | M8: =IF(OR(I8=0,G8<=0),"n/a",L8/G8-1) -> n/a | N8: =IF(I8=0,"n/a",H8/I8) -> 1.0548592 | O8: =IF(I8=0,"Sin estimación",IF(L8<=0,"Ya cumplido",IF(G8<=0,"Sin base 2025",IF(M8<=$E$4,"Alcanzable",IF(M8<=$E$5,"Exigente","Poco realista"))))) -> Ya cumplido | P8: 82168.82 | Q8: 2445.64
A9: Alfonso | B9: ESPAÑA | C9: AGROVEYCA,S.L | D9: Consolidado/estratégico | E9: 61161.69 | F9: 55786.19 | G9: =E9-F9 -> 5375.5 | H9: 95156.6 | I9: =P9+Q9 -> 95686.19 | J9: =IF(F9<=0,"n/a",H9/F9-1) -> 0.70573757 | K9: =IF(E9<=0,"n/a",I9/E9-1) -> 0.56447917 | L9: =IF(I9=0,0,I9-H9) -> 529.59 | M9: =IF(OR(I9=0,G9<=0),"n/a",L9/G9-1) -> -0.90148079 | N9: =IF(I9=0,"n/a",H9/I9) -> 0.99446535 | O9: =IF(I9=0,"Sin estimación",IF(L9<=0,"Ya cumplido",IF(G9<=0,"Sin base 2025",IF(M9<=$E$4,"Alcanzable",IF(M9<=$E$5,"Exigente","Poco realista"))))) -> Alcanzable | P9: 91458.99 | Q9: 4227.2
A10: Alfonso | B10: ESPAÑA | C10: AGROCAMP CANET S.L. | D10: Baja aportación | E10: 46084.21 | F10: 38376.71 | G10: =E10-F10 -> 7707.5 | H10: 19627.92 | I10: =P10+Q10 -> 19442.04 | J10: =IF(F10<=0,"n/a",H10/F10-1) -> -0.48854605 | K10: =IF(E10<=0,"n/a",I10/E10-1) -> -0.57811927 | L10: =IF(I10=0,0,I10-H10) -> -185.88 | M10: =IF(OR(I10=0,G10<=0),"n/a",L10/G10-1) -> -1.0241168 | N10: =IF(I10=0,"n/a",H10/I10) -> 1.0095607 | O10: =IF(I10=0,"Sin estimación",IF(L10<=0,"Ya cumplido",IF(G10<=0,"Sin base 2025",IF(M10<=$E$4,"Alcanzable",IF(M10<=$E$5,"Exigente","Poco realista"))))) -> Ya cumplido | P10: 19442.04 | Q10: 0
A11: Alfonso | B11: ESPAÑA | C11: T.J AGRICULTURA S.L. | D11: Con potencial | E11: 39285.44 | F11: 39285.44 | G11: =E11-F11 -> 0 | H11: 26335.2 | I11: =P11+Q11 -> 22954.42 | J11: =IF(F11<=0,"n/a",H11/F11-1) -> -0.32964477 | K11: =IF(E11<=0,"n/a",I11/E11-1) -> -0.41570159 | L11: =IF(I11=0,0,I11-H11) -> -3380.78 | M11: =IF(OR(I11=0,G11<=0),"n/a",L11/G11-1) -> n/a | N11: =IF(I11=0,"n/a",H11/I11) -> 1.1472823 | O11: =IF(I11=0,"Sin estimación",IF(L11<=0,"Ya cumplido",IF(G11<=0,"Sin base 2025",IF(M11<=$E$4,"Alcanzable",IF(M11<=$E$5,"Exigente","Poco realista"))))) -> Ya cumplido | P11: 22954.42 | Q11: 0
A12: Alfonso | B12: ESPAÑA | C12: FRUITURE ADVISORS, S.L. | D12: Baja aportación | E12: 37301.37 | F12: 25851.37 | G12: =E12-F12 -> 11450 | H12: 15959.2 | I12: =P12+Q12 -> 15859.82 | J12: =IF(F12<=0,"n/a",H12/F12-1) -> -0.38265554 | K12: =IF(E12<=0,"n/a",I12/E12-1) -> -0.57481937 | L12: =IF(I12=0,0,I12-H12) -> -99.38 | M12: =IF(OR(I12=0,G12<=0),"n/a",L12/G12-1) -> -1.0086795 | N12: =IF(I12=0,"n/a",H12/I12) -> 1.0062661 | O12: =IF(I12=0,"Sin estimación",IF(L12<=0,"Ya cumplido",IF(G12<=0,"Sin base 2025",IF(M12<=$E$4,"Alcanzable",IF(M12<=$E$5,"Exigente","Poco realista"))))) -> Ya cumplido | P12: 15859.82 | Q12: 0
A13: Alfonso | B13: ESPAÑA | C13: AGROTÉCNICA DEL NORTE, S.L | D13: Con potencial | E13: 36343.99 | F13: 30841.99 | G13: =E13-F13 -> 5502 | H13: 41444.56 | I13: =P13+Q13 -> 36330.04 | J13: =IF(F13<=0,"n/a",H13/F13-1) -> 0.34377062 | K13: =IF(E13<=0,"n/a",I13/E13-1) -> -0.00038383238 | L13: =IF(I13=0,0,I13-H13) -> -5114.52 | M13: =IF(OR(I13=0,G13<=0),"n/a",L13/G13-1) -> -1.9295747 | N13: =IF(I13=0,"n/a",H13/I13) -> 1.1407794 | O13: =IF(I13=0,"Sin estimación",IF(L13<=0,"Ya cumplido",IF(G13<=0,"Sin base 2025",IF(M13<=$E$4,"Alcanzable",IF(M13<=$E$5,"Exigente","Poco realista"))))) -> Ya cumplido | P13: 36330.04 | Q13: 0
A14: Alfonso | B14: ESPAÑA | C14: AGRITEC MEDINA, S.L.U. | D14: Con potencial | E14: 29062.19 | F14: 28434.19 | G14: =E14-F14 -> 628 | H14: 18521.26 | I14: =P14+Q14 -> 18277.38 | J14: =IF(F14<=0,"n/a",H14/F14-1) -> -0.34862713 | K14: =IF(E14<=0,"n/a",I14/E14-1) -> -0.37109419 | L14: =IF(I14=0,0,I14-H14) -> -243.88 | M14: =IF(OR(I14=0,G14<=0),"n/a",L14/G14-1) -> -1.3883439 | N14: =IF(I14=0,"n/a",H14/I14) -> 1.0133433 | O14: =IF(I14=0,"Sin estimación",IF(L14<=0,"Ya cumplido",IF(G14<=0,"Sin base 2025",IF(M14<=$E$4,"Alcanzable",IF(M14<=$E$5,"Exigente","Poco realista"))))) -> Ya cumplido | P14: 18277.38 | Q14: 0
A15: Alfonso | B15: ESPAÑA | C15: BELLO ALIAGA ERNESTO | D15: Con potencial | E15: 22911.58 | F15: 22911.58 | G15: =E15-F15 -> 0 | H15: 19918.8 | I15: =P15+Q15 -> 19704.39 | J15: =IF(F15<=0,"n/a",H15/F15-1) -> -0.13062303 | K15: =IF(E15<=0,"n/a",I15/E15-1) -> -0.13998118 | L15: =IF(I15=0,0,I15-H15) -> -214.41 | M15: =IF(OR(I15=0,G15<=0),"n/a",L15/G15-1) -> n/a | N15: =IF(I15=0,"n/a",H15/I15) -> 1.0108813 | O15: =IF(I15=0,"Sin estimación",IF(L15<=0,"Ya cumplido",IF(G15<=0,"Sin base 2025",IF(M15<=$E$4,"Alcanzable",IF(M15<=$E$5,"Exigente","Poco realista"))))) -> Ya cumplido | P15: 19704.39 | Q15: 0
A16: Alfonso | B16: ESPAÑA | C16: CITAL, S.L. | D16: Con potencial | E16: 21930 | F16: 19606.8 | G16: =E16-F16 -> 2323.2 | H16: 19940.4 | I16: =P16+Q16 -> 19725.76 | J16: =IF(F16<=0,"n/a",H16/F16-1) -> 0.017014505 | K16: =IF(E16<=0,"n/a",I16/E16-1) -> -0.10051254 | L16: =IF(I16=0,0,I16-H16) -> -214.64 | M16: =IF(OR(I16=0,G16<=0),"n/a",L16/G16-1) -> -1.0923898 | N16: =IF(I16=0,"n/a",H16/I16) -> 1.0108812 | O16: =IF(I16=0,"Sin estimación",IF(L16<=0,"Ya cumplido",IF(G16<=0,"Sin base 2025",IF(M16<=$E$4,"Alcanzable",IF(M16<=$E$5,"Exigente","Poco realista"))))) -> Ya cumplido | P16: 19725.76 | Q16: 0
A17: Alfonso | B17: ESPAÑA | C17: BARDENAS COMERCIAL, S.L. | D17: Con potencial | E17: 18606 | F17: 18606 | G17: =E17-F17 -> 0 | H17: 34721 | I17: =P17+Q17 -> 32700.17 | J17: =IF(F17<=0,"n/a",H17/F17-1) -> 0.86611846 | K17: =IF(E17<=0,"n/a",I17/E17-1) -> 0.75750672 | L17: =IF(I17=0,0,I17-H17) -> -2020.83 | M17: =IF(OR(I17=0,G17<=0),"n/a",L17/G17-1) -> n/a | N17: =IF(I17=0,"n/a",H17/I17) -> 1.0617988 | O17: =IF(I17=0,"Sin estimación",IF(L17<=0,"Ya cumplido",IF(G17<=0,"Sin base 2025",IF(M17<=$E$4,"Alcanzable",IF(M17<=$E$5,"Exigente","Poco realista"))))) -> Ya cumplido | P17: 32700.17 | Q17: 0
A18: Alfonso | B18: ESPAÑA | C18: ASOC. HORTICULTORES DE VILLA DEL PRADO | D18: Con potencial | E18: 16179.01 | F18: 14214.81 | G18: =E18-F18 -> 1964.2 | H18: 16343.5 | I18: =P18+Q18 -> 15165.08 | J18: =IF(F18<=0,"n/a",H18/F18-1) -> 0.14975156 | K18: =IF(E18<=0,"n/a",I18/E18-1) -> -0.062669471 | L18: =IF(I18=0,0,I18-H18) -> -1178.42 | M18: =IF(OR(I18=0,G18<=0),"n/a",L18/G18-1) -> -1.5999491 | N18: =IF(I18=0,"n/a",H18/I18) -> 1.0777062 | O18: =IF(I18=0,"Sin estimación",IF(L18<=0,"Ya cumplido",IF(G18<=0,"Sin base 2025",IF(M18<=$E$4,"Alcanzable",IF(M18<=$E$5,"Exigente","Poco realista"))))) -> Ya cumplido | P18: 15165.08 | Q18: 0
A19: Alfonso | B19: ESPAÑA | C19: ACTIV. PRODUC. Y COMERC. LA VEGUILLA, SL | D19: Consolidado/estratégico | E19: 15343.2 | F19: 5020.8 | G19: =E19-F19 -> 10322.4 | H19: 34680.8 | I19: =P19+Q19 -> 41845.16 | J19: =IF(F19<=0,"n/a",H19/F19-1) -> 5.9074251 | K19: =IF(E19<=0,"n/a",I19/E19-1) -> 1.7272772 | L19: =IF(I19=0,0,I19-H19) -> 7164.36 | M19: =IF(OR(I19=0,G19<=0),"n/a",L19/G19-1) -> -0.30594048 | N19: =IF(I19=0,"n/a",H19/I19) -> 0.8287888 | O19: =IF(I19=0,"Sin estimación",IF(L19<=0,"Ya cumplido",IF(G19<=0,"Sin base 2025",IF(M19<=$E$4,"Alcanzable",IF(M19<=$E$5,"Exigente","Poco realista"))))) -> Alcanzable | P19: 27609.17 | Q19: 14235.99
... A121: Sin estimación | B121: España | C121: ALMENDRALIA IBÉRICA, S.L.U. | D121: Sin clasificar | E121: 0 | F121: 0 | G121: =E121-F121 -> 0 | H121: 1958 | I121: =P121+Q121 -> 0 | J121: =IF(F121<=0,"n/a",H121/F121-1) -> n/a | K121: =IF(E121<=0,"n/a",I121/E121-1) -> n/a | L121: =IF(I121=0,0,I121-H121) -> 0 | M121: =IF(OR(I121=0,G121<=0),"n/a",L121/G121-1) -> n/a | N121: =IF(I121=0,"n/a",H121/I121) -> n/a | O121: =IF(I121=0,"Sin estimación",IF(L121<=0,"Ya cumplido",IF(G121<=0,"Sin base 2025",IF(M121<=$E$4,"Alcanzable",IF(M121<=$E$5,"Exigente","Poco realista"))))) -> Sin estimación | P121: 0 | Q121: 0
A122: TOTAL | E122: =SUM(E8:E121) -> 13040886 | F122: =SUM(F8:F121) -> 11107207 | G122: =SUM(G8:G121) -> 1933679.2 | H122: =SUM(H8:H121) -> 12009097 | I122: =SUM(I8:I121) -> 15180000 | J122: =H122/F122-1 -> 0.081198637 | K122: =I122/E122-1 -> 0.16403134 | L122: =SUM(L8:L121) -> 3204478 | M122: =L122/G122-1 -> 0.6571922 | N122: =H122/I122 -> 0.7911131 | P122: =SUM(P8:P121) -> 11417132 | Q122: =SUM(Q8:Q121) -> 3762867.9
A124: Notas: texto azul = dato copiado de los ficheros origen; negro = fórmula. Ver hoja "Notas y supuestos".

Sheet Resumen por Comercial
A1: Resumen por comercial
A3: Comercial | B3: Nº clientes | C3: Ventas 2025 (año completo) | D3: Ventas ene-sep 2025 | E3: Ventas oct-dic 2025 | F3: Ventas 2026 ene-sep (real) | G3: Estimación cierre 2026 | H3: Crec. real ene-sep 26 vs 25 | I3: Crec. estimado 2026 vs 2025 | J3: Pendiente por vender oct-dic 2026 | K3: Crec. necesario oct-dic 26 vs oct-dic 25 | L3: % de la estimación ya vendido
A4: Alfonso | B4: =COUNTIF('Comparativa Clientes'!$A$8:$A$121,A4) -> 29 | C4: =SUMIFS('Comparativa Clientes'!$E$8:$E$121,'Comparativa Clientes'!$A$8:$A$121,$A4) -> 540189.25 | D4: =SUMIFS('Comparativa Clientes'!$F$8:$F$121,'Comparativa Clientes'!$A$8:$A$121,$A4) -> 471099.4 | E4: =SUMIFS('Comparativa Clientes'!$G$8:$G$121,'Comparativa Clientes'!$A$8:$A$121,$A4) -> 69089.85 | F4: =SUMIFS('Comparativa Clientes'!$H$8:$H$121,'Comparativa Clientes'!$A$8:$A$121,$A4) -> 549726.63 | G4: =SUMIFS('Comparativa Clientes'!$I$8:$I$121,'Comparativa Clientes'!$A$8:$A$121,$A4) -> 534219.3 | H4: =IF(D4<=0,"n/a",F4/D4-1) -> 0.16690157 | I4: =IF(OR(C4<=0,G4=0),"n/a",G4/C4-1) -> -0.01105159 | J4: =SUMIFS('Comparativa Clientes'!$L$8:$L$121,'Comparativa Clientes'!$A$8:$A$121,$A4) -> -15507.33 | K4: =IF(OR(E4<=0,G4=0),"n/a",J4/E4-1) -> -1.2244516 | L4: =IF(G4=0,"n/a",F4/G4) -> 1.029028
A5: García | B5: =COUNTIF('Comparativa Clientes'!$A$8:$A$121,A5) -> 23 | C5: =SUMIFS('Comparativa Clientes'!$E$8:$E$121,'Comparativa Clientes'!$A$8:$A$121,$A5) -> 4735620.6 | D5: =SUMIFS('Comparativa Clientes'!$F$8:$F$121,'Comparativa Clientes'!$A$8:$A$121,$A5) -> 4041949.2 | E5: =SUMIFS('Comparativa Clientes'!$G$8:$G$121,'Comparativa Clientes'!$A$8:$A$121,$A5) -> 693671.36 | F5: =SUMIFS('Comparativa Clientes'!$H$8:$H$121,'Comparativa Clientes'!$A$8:$A$121,$A5) -> 4785341.8 | G5: =SUMIFS('Comparativa Clientes'!$I$8:$I$121,'Comparativa Clientes'!$A$8:$A$121,$A5) -> 5792830.4 | H5: =IF(D5<=0,"n/a",F5/D5-1) -> 0.18391931 | I5: =IF(OR(C5<=0,G5=0),"n/a",G5/C5-1) -> 0.22324631 | J5: =SUMIFS('Comparativa Clientes'!$L$8:$L$121,'Comparativa Clientes'!$A$8:$A$121,$A5) -> 1007488.7 | K5: =IF(OR(E5<=0,G5=0),"n/a",J5/E5-1) -> 0.45240056 | L5: =IF(G5=0,"n/a",F5/G5) -> 0.82608007
A6: Irene | B6: =COUNTIF('Comparativa Clientes'!$A$8:$A$121,A6) -> 6 | C6: =SUMIFS('Comparativa Clientes'!$E$8:$E$121,'Comparativa Clientes'!$A$8:$A$121,$A6) -> 939712.68 | D6: =SUMIFS('Comparativa Clientes'!$F$8:$F$121,'Comparativa Clientes'!$A$8:$A$121,$A6) -> 628722.29 | E6: =SUMIFS('Comparativa Clientes'!$G$8:$G$121,'Comparativa Clientes'!$A$8:$A$121,$A6) -> 310990.39 | F6: =SUMIFS('Comparativa Clientes'!$H$8:$H$121,'Comparativa Clientes'!$A$8:$A$121,$A6) -> 796950.28 | G6: =SUMIFS('Comparativa Clientes'!$I$8:$I$121,'Comparativa Clientes'!$A$8:$A$121,$A6) -> 1071709.1 | H6: =IF(D6<=0,"n/a",F6/D6-1) -> 0.26757122 | I6: =IF(OR(C6<=0,G6=0),"n/a",G6/C6-1) -> 0.14046469 | J6: =SUMIFS('Comparativa Clientes'!$L$8:$L$121,'Comparativa Clientes'!$A$8:$A$121,$A6) -> 274758.85 | K6: =IF(OR(E6<=0,G6=0),"n/a",J6/E6-1) -> -0.11650373 | L6: =IF(G6=0,"n/a",F6/G6) -> 0.74362554
A7: Javier | B7: =COUNTIF('Comparativa Clientes'!$A$8:$A$121,A7) -> 5 | C7: =SUMIFS('Comparativa Clientes'!$E$8:$E$121,'Comparativa Clientes'!$A$8:$A$121,$A7) -> 1048148.9 | D7: =SUMIFS('Comparativa Clientes'!$F$8:$F$121,'Comparativa Clientes'!$A$8:$A$121,$A7) -> 882363.5 | E7: =SUMIFS('Comparativa Clientes'!$G$8:$G$121,'Comparativa Clientes'!$A$8:$A$121,$A7) -> 165785.41 | F7: =SUMIFS('Comparativa Clientes'!$H$8:$H$121,'Comparativa Clientes'!$A$8:$A$121,$A7) -> 803334.58 | G7: =SUMIFS('Comparativa Clientes'!$I$8:$I$121,'Comparativa Clientes'!$A$8:$A$121,$A7) -> 992147.64 | H7: =IF(D7<=0,"n/a",F7/D7-1) -> -0.089565038 | I7: =IF(OR(C7<=0,G7=0),"n/a",G7/C7-1) -> -0.053428735 | J7: =SUMIFS('Comparativa Clientes'!$L$8:$L$121,'Comparativa Clientes'!$A$8:$A$121,$A7) -> 188813.06 | K7: =IF(OR(E7<=0,G7=0),"n/a",J7/E7-1) -> 0.13890034 | L7: =IF(G7=0,"n/a",F7/G7) -> 0.80969258
A8: Mehmet | B8: =COUNTIF('Comparativa Clientes'!$A$8:$A$121,A8) -> 5 | C8: =SUMIFS('Comparativa Clientes'!$E$8:$E$121,'Comparativa Clientes'!$A$8:$A$121,$A8) -> 803702.98 | D8: =SUMIFS('Comparativa Clientes'!$F$8:$F$121,'Comparativa Clientes'!$A$8:$A$121,$A8) -> 783697.88 | E8: =SUMIFS('Comparativa Clientes'!$G$8:$G$121,'Comparativa Clientes'!$A$8:$A$121,$A8) -> 20005.1 | F8: =SUMIFS('Comparativa Clientes'!$H$8:$H$121,'Comparativa Clientes'!$A$8:$A$121,$A8) -> 1367890.8 | G8: =SUMIFS('Comparativa Clientes'!$I$8:$I$121,'Comparativa Clientes'!$A$8:$A$121,$A8) -> 1804250 | H8: =IF(D8<=0,"n/a",F8/D8-1) -> 0.7454313 | I8: =IF(OR(C8<=0,G8=0),"n/a",G8/C8-1) -> 1.2449213 | J8: =SUMIFS('Comparativa Clientes'!$L$8:$L$121,'Comparativa Clientes'!$A$8:$A$121,$A8) -> 436359.14 | K8: =IF(OR(E8<=0,G8=0),"n/a",J8/E8-1) -> 20.812395 | L8: =IF(G8=0,"n/a",F8/G8) -> 0.75814929
A9: Pedro | B9: =COUNTIF('Comparativa Clientes'!$A$8:$A$121,A9) -> 3 | C9: =SUMIFS('Comparativa Clientes'!$E$8:$E$121,'Comparativa Clientes'!$A$8:$A$121,$A9) -> 1350442 | D9: =SUMIFS('Comparativa Clientes'!$F$8:$F$121,'Comparativa Clientes'!$A$8:$A$121,$A9) -> 1123401.9 | E9: =SUMIFS('Comparativa Clientes'!$G$8:$G$121,'Comparativa Clientes'!$A$8:$A$121,$A9) -> 227040.1 | F9: =SUMIFS('Comparativa Clientes'!$H$8:$H$121,'Comparativa Clientes'!$A$8:$A$121,$A9) -> 979461.96 | G9: =SUMIFS('Comparativa Clientes'!$I$8:$I$121,'Comparativa Clientes'!$A$8:$A$121,$A9) -> 1227858.5 | H9: =IF(D9<=0,"n/a",F9/D9-1) -> -0.12812866 | I9: =IF(OR(C9<=0,G9=0),"n/a",G9/C9-1) -> -0.090772907 | J9: =SUMIFS('Comparativa Clientes'!$L$8:$L$121,'Comparativa Clientes'!$A$8:$A$121,$A9) -> 248396.53 | K9: =IF(OR(E9<=0,G9=0),"n/a",J9/E9-1) -> 0.094064573 | L9: =IF(G9=0,"n/a",F9/G9) -> 0.79769938
A10: Ricardo | B10: =COUNTIF('Comparativa Clientes'!$A$8:$A$121,A10) -> 10 | C10: =SUMIFS('Comparativa Clientes'!$E$8:$E$121,'Comparativa Clientes'!$A$8:$A$121,$A10) -> 3377873.9 | D10: =SUMIFS('Comparativa Clientes'!$F$8:$F$121,'Comparativa Clientes'!$A$8:$A$121,$A10) -> 2932346.7 | E10: =SUMIFS('Comparativa Clientes'!$G$8:$G$121,'Comparativa Clientes'!$A$8:$A$121,$A10) -> 445527.2 | F10: =SUMIFS('Comparativa Clientes'!$H$8:$H$121,'Comparativa Clientes'!$A$8:$A$121,$A10) -> 2692815.9 | G10: =SUMIFS('Comparativa Clientes'!$I$8:$I$121,'Comparativa Clientes'!$A$8:$A$121,$A10) -> 3756985 | H10: =IF(D10<=0,"n/a",F10/D10-1) -> -0.081685693 | I10: =IF(OR(C10<=0,G10=0),"n/a",G10/C10-1) -> 0.11223366 | J10: =SUMIFS('Comparativa Clientes'!$L$8:$L$121,'Comparativa Clientes'!$A$8:$A$121,$A10) -> 1064169.1 | K10: =IF(OR(E10<=0,G10=0),"n/a",J10/E10-1) -> 1.3885615 | L10: =IF(G10=0,"n/a",F10/G10) -> 0.71674917
A11: Sin estimación | B11: =COUNTIF('Comparativa Clientes'!$A$8:$A$121,A11) -> 33 | C11: =SUMIFS('Comparativa Clientes'!$E$8:$E$121,'Comparativa Clientes'!$A$8:$A$121,$A11) -> 245195.61 | D11: =SUMIFS('Comparativa Clientes'!$F$8:$F$121,'Comparativa Clientes'!$A$8:$A$121,$A11) -> 243625.85 | E11: =SUMIFS('Comparativa Clientes'!$G$8:$G$121,'Comparativa Clientes'!$A$8:$A$121,$A11) -> 1569.76 | F11: =SUMIFS('Comparativa Clientes'!$H$8:$H$121,'Comparativa Clientes'!$A$8:$A$121,$A11) -> 33574.9 | G11: =SUMIFS('Comparativa Clientes'!$I$8:$I$121,'Comparativa Clientes'!$A$8:$A$121,$A11) -> 0 | H11: =IF(D11<=0,"n/a",F11/D11-1) -> -0.86218663 | I11: =IF(OR(C11<=0,G11=0),"n/a",G11/C11-1) -> n/a | J11: =SUMIFS('Comparativa Clientes'!$L$8:$L$121,'Comparativa Clientes'!$A$8:$A$121,$A11) -> 0 | K11: =IF(OR(E11<=0,G11=0),"n/a",J11/E11-1) -> n/a | L11: =IF(G11=0,"n/a",F11/G11) -> n/a
A12: TOTAL | B12: =SUM(B4:B11) -> 114 | C12: =SUM(C4:C11) -> 13040886 | D12: =SUM(D4:D11) -> 11107207 | E12: =SUM(E4:E11) -> 1933679.2 | F12: =SUM(F4:F11) -> 12009097 | G12: =SUM(G4:G11) -> 15180000 | H12: =F12/D12-1 -> 0.081198637 | I12: =G12/C12-1 -> 0.16403134 | J12: =SUM(J4:J11) -> 3204478 | K12: =J12/E12-1 -> 0.6571922 | L12: =F12/G12 -> 0.7911131

Sheet Notas y supuestos
A1: Fuentes
A2: Ventas 2025 y 2026 | B2: Fichero "Ventas Septiembre 2026", hoja DATOS (Importe Neto), agregado por código de cliente. 2026 incluye periodos 1-9 (hasta 30/09/26).
A3: Estimación 2026 | B3: Fichero "Presupuesto Ventas 2027 Definitivo", hoja "Resumen por Cliente": columna "Real Ene-Ago 26 (€)" + "Prev Sep-Dic 26 (€)" (= TOTAL 2026, 15,18 M€). Se ha usado la estimación de CIERRE 2026, no el presupuesto 2027 (que está en ese mismo fichero pero no se incluye aquí).
A5: Criterios y supuestos
A6: Unificación de clientes | B6: HORTIFRUT - PERU y HORTIFRUT PERU (dos filas en el presupuesto) = un único cliente en ventas (cód. 430000275). EMPHYTON POULTSIDIS GEORGIOS y GEORGIOS POULTSIDIS = un único cliente en ventas (cód. 430000345): el real ene-ago del presupuesto (32.932 €) coincide con las ventas 2026 de ese código (33.290 €). Es una suposición razonable, conviene confirmarla.
A7: Clientes sin estimación | B7: Clientes con ventas en 2025/2026 que no aparecen en el fichero de presupuesto: se muestran al final con "Sin estimación". Los comerciales no les han asignado previsión.
A8: Excluido: SUSTAINABLE AGRO SOLUTIONS SAU | B8: Cód. 430000427: 463.517 € netos en 2026 (mayo, junio, sept.). Son servicios de formulación, envasado, packaging y materias primas (artículos "SAS"), no ventas de producto, y no figuran en el presupuesto. Se han excluido de la tabla para no distorsionar. Si se quieren incluir, las ventas 2026 sumarían 463.517 € más.
A9: Cuadre con el presupuesto | B9: El "Real ene-ago 26" del presupuesto difiere ~1% de las ventas del fichero de septiembre en la mayoría de clientes, con diferencias mayores en BORN AGROCHEMISTRY, SC MARCOSER, CODIMED, FITOXENT y otros. Aquí se compara siempre contra las ventas del fichero de septiembre; la estimación se toma tal cual la han dado los comerciales.
A10: Clientes con estimación pero sin ventas | B10: DOGA TARIM (vendió 282 k€ en 2025, 0 € en 2026; estimación sep-dic 92 k€) y APLICAMPO, entre otros.
A12: Cómo leer la valoración
A13: Crec. necesario oct-dic | B13: (Estimación 2026 − ventas ene-sep 2026) ÷ ventas oct-dic 2025 − 1. Indica cuánto más tienen que vender en el último trimestre que en el mismo trimestre de 2025 para cumplir la estimación.
A14: Valoración | B14: Ya cumplido / Alcanzable / Exigente / Poco realista según los umbrales editables de la hoja "Comparativa Clientes" (celdas E4 y E5, 15% y 40% por defecto: criterio orientativo, no una regla del negocio). "Sin base 2025": no vendieron en oct-dic 2025 y aún les queda por vender.
