Workbook
Name Datos: #REF!
Name Datos: #REF!

Sheet 2026
C2: RELLENAR | L2: RELLENAR | U2: RELLENAR | AD2: RELLENAR | AM2: RELLENAR | AV2: RELLENAR | BE2: RELLENAR | BN2: RELLENAR | BW2: RELLENAR | CF2: RELLENAR | CO2: RELLENAR | CX2: RELLENAR | DG2: RELLENAR
B3: MES | C3: 1 | K3: MES | L3: 2 | T3: MES | U3: 3 | AC3: MES | AD3: 4 | AL3: MES | AM3: 5 | AU3: MES | AV3: 6 | BD3: MES | BE3: 7 | BM3: MES | BN3: 8 | BV3: MES | BW3: 9 | CE3: MES | CF3: 10 | CN3: MES | CO3: 11 | CW3: MES | CX3: 12 | DF3: MES | DG3: 12 | DH3: YTD
B5: P&L Mensual | K5: P&L Mensual | T5: P&L Mensual | AC5: P&L Mensual | AL5: P&L Mensual | AU5: P&L Mensual | BD5: P&L Mensual | BM5: P&L Mensual | BV5: P&L Mensual | CE5: P&L Mensual | CN5: P&L Mensual | CW5: P&L Mensual | DF5: P&L YTD
E6: Variación | H6: Variación | N6: Variación | Q6: Variación | W6: Variación | Z6: Variación | AF6: Variación | AI6: Variación | AO6: Variación | AR6: Variación | AX6: Variación | BA6: Variación | BG6: Variación | BJ6: Variación | BP6: Variación | BS6: Variación | BY6: Variación | CB6: Variación | CH6: Variación | CK6: Variación | CQ6: Variación | CT6: Variación | CZ6: Variación | DC6: Variación | DI6: Variación | DL6: Variación
B7: € '000 | C7: 2026A | D7: 2025A | E7: EUR | F7: % | G7: 2026B | H7: EUR | I7: % | K7: € '000 | L7: 2026A | M7: 2025A | N7: EUR | O7: % | P7: 2026B | Q7: EUR | R7: % | T7: € '000 | U7: 2026A | V7: 2025A | W7: EUR | X7: % | Y7: 2026B | Z7: EUR | AA7: % | AC7: € '000 | AD7: 2026A | AE7: 2025A | AF7: EUR | AG7: % | AH7: 2026B | AI7: EUR | AJ7: % | AL7: € '000 | AM7: 2026A | AN7: 2025A | AO7: EUR | AP7: % | AQ7: 2026B | AR7: EUR | AS7: % | AU7: € '000 | AV7: 2026A | AW7: 2025A | AX7: EUR | AY7: % | AZ7: 2026B | BA7: EUR | BB7: % | BD7: € '000 | BE7: 2026A | BF7: 2025A | BG7: EUR | BH7: % | BI7: 2026B | BJ7: EUR | BK7: % | BM7: € '000 | BN7: 2026A | BO7: 2025A | BP7: EUR | BQ7: % | BR7: 2026B | BS7: EUR | BT7: % | BV7: € '000 | BW7: 2026A | BX7: 2025A | BY7: EUR | BZ7: % | CA7: 2026B | CB7: EUR | CC7: % | CE7: € '000 | CF7: 2026A | CG7: 2025A | CH7: EUR | CI7: % | CJ7: 2026B | CK7: EUR | CL7: % | CN7: € '000 | CO7: 2026A | CP7: 2025A | CQ7: EUR | CR7: % | CS7: 2026B | CT7: EUR | CU7: % | CW7: € '000 | CX7: 2026A | CY7: 2025A | CZ7: EUR | DA7: % | DB7: 2026B | DC7: EUR | DD7: % | DF7: € '000 | DG7: 2026A | DH7: 2025A | DI7: EUR | DJ7: % | DK7: 2026B | DL7: EUR | DM7: %
B8: Ventas | C8: 983.81713 | D8: 622.28714 | E8: 361.52999 | F8: 0.58096973 | G8: 805.69363 | H8: 178.1235 | I8: 0.22108094 | K8: Ventas | L8: 1470.4281 | M8: 1062.4411 | N8: 407.98706 | O8: 0.38400911 | P8: 1513.248 | Q8: -42.819833 | R8: -0.02829664 | T8: Ventas | U8: 1533.7894 | V8: 1795.147 | W8: -261.35762 | X8: -0.14559121 | Y8: 2302.2173 | Z8: -768.4279 | AA8: -0.33377731 | AC8: Ventas | AD8: 1462.1463 | AE8: 1534.3509 | AF8: -72.20461 | AG8: -0.047058734 | AH8: 1891.2553 | AI8: -429.10904 | AJ8: -0.22689112 | AL8: Ventas | AM8: 1925.9299 | AN8: 1483.9152 | AO8: 442.01472 | AP8: 0.29787061 | AQ8: 1636.9092 | AR8: 289.0207 | AS8: 0.17656489 | AU8: Ventas | AV8: 1962.2618 | AW8: 1760.942 | AX8: 201.31983 | AY8: 0.11432508 | AZ8: 2150.2566 | BA8: -187.99474 | BB8: -0.087428981 | BD8: Ventas | BE8: 1290.6542 | BF8: 1314.5645 | BG8: -23.91025 | BH8: -0.018188724 | BI8: 1348.021 | BJ8: -57.366798 | BK8: -0.042556308 | BM8: Ventas | BN8: 788.10515 | BO8: 664.49694 | BP8: 123.60821 | BQ8: 0.18601773 | BR8: 776.07561 | BS8: 12.029536 | BT8: 0.015500469 | BV8: Ventas | BW8: =(GETPIVOTDATA("sep-26 ",TABLA!$B$3,"Nivel 4","1.- Importe neto de la cifra de negocios"))/1000 -> 624.72488 | BX8: =VLOOKUP(BV8,'P&L Mensualitzada 2025'!$A$5:$N$25,$BW$3+1,0) -> 842.11579 | BY8: =BW8-BX8 -> -217.39091 | BZ8: =+IF(IFERROR(BW8/BX8-1,"-")<300%,IFERROR(BW8/BX8-1,"-"),"n.a.") -> -0.25814848 | CA8: =VLOOKUP(BV8,'Budget26 sin EI'!$B:$O,$BW$3+1,0) -> 1026.5685 | CB8: =BW8-CA8 -> -401.84361 | CC8: =+IF(IFERROR(BW8/CA8-1,"-")<300%,IFERROR(BW8/CA8-1,"-"),"n.a.") -> -0.39144355 | CE8: Ventas | CF8: =(GETPIVOTDATA("oct-26 ",TABLA!$B$3,"Nivel 4","1.- Importe neto de la cifra de negocios"))/1000 -> 912.05501 | CG8: =VLOOKUP(CE8,'P&L Mensualitzada 2025'!$A$5:$N$25,$CF$3+1,0) -> 699.58345 | CH8: =CF8-CG8 -> 212.47156 | CI8: =+IF(IFERROR(CF8/CG8-1,"-")<300%,IFERROR(CF8/CG8-1,"-"),"n.a.") -> 0.30371153 | CJ8: =VLOOKUP(CE8,'Budget26 sin EI'!$B:$O,$CF$3+1,0) -> 798.56718 | CK8: =CF8-CJ8 -> 113.48783 | CL8: =+IF(IFERROR(CF8/CJ8-1,"-")<300%,IFERROR(CF8/CJ8-1,"-"),"n.a.") -> 0.14211431 | CN8: Ventas | CO8: =(GETPIVOTDATA("nov-26 ",TABLA!$B$3,"Nivel 4","1.- Importe neto de la cifra de negocios"))/1000 -> 1225.3218 | CP8: =VLOOKUP(CN8,'P&L Mensualitzada 2025'!$A$5:$N$25,$CO$3+1,0) -> 749.69916 | CQ8: =CO8-CP8 -> 475.62262 | CR8: =+IF(IFERROR(CO8/CP8-1,"-")<300%,IFERROR(CO8/CP8-1,"-"),"n.a.") -> 0.63441797 | CS8: =VLOOKUP(CN8,'Budget26 sin EI'!$B:$O,$CO$3+1,0) -> 1030.243 | CT8: =CO8-CS8 -> 195.07877 | CU8: =+IF(IFERROR(CO8/CS8-1,"-")<300%,IFERROR(CO8/CS8-1,"-"),"n.a.") -> 0.18935219 | CW8: Ventas | CX8: =(GETPIVOTDATA("dic-26 ",TABLA!$B$3,"Nivel 4","1.- Importe neto de la cifra de negocios"))/1000 -> 1142.4074 | CY8: =VLOOKUP(CW8,'P&L Mensualitzada 2025'!$A$5:$N$25,$CX$3+1,0) -> 248.50601 | CZ8: =CX8-CY8 -> 893.90137 | DA8: =+IF(IFERROR(CX8/CY8-1,"-")<300%,IFERROR(CX8/CY8-1,"-"),"n.a.") -> n.a. | DB8: =VLOOKUP(CW8,'Budget26 sin EI'!$B:$O,$CX$3+1,0) -> 659.94465 | DC8: =CX8-DB8 -> 482.46273 | DD8: =+IF(IFERROR(CX8/DB8-1,"-")<300%,IFERROR(CX8/DB8-1,"-"),"n.a.") -> 0.73106544 | DF8: Ventas | DG8: =(GETPIVOTDATA("Total 2026 ",TABLA!$B$3,"Nivel 4","1.- Importe neto de la cifra de negocios"))/1000 -> 15180 | DH8: =VLOOKUP(DF8,'P&L Mensualitzada 2025'!$A$5:$N$25,$CX$3+2,0) -> 12778.049 | DI8: =DG8-DH8 -> 2401.9508 | DJ8: =+IF(IFERROR(DG8/DH8-1,"-")<300%,IFERROR(DG8/DH8-1,"-"),"n.a.") -> 0.18797477 | DK8: =VLOOKUP(DF8,'Budget26 sin EI'!$B:$O,$CX$3+2,0) -> 15939 | DL8: =DG8-DK8 -> -759 | DM8: =+IF(IFERROR(DG8/DK8-1,"-")<300%,IFERROR(DG8/DK8-1,"-"),"n.a.") -> -0.047619048
B9: COGS | C9: -502.66555 | D9: -518.09465 | E9: 15.4291 | F9: -0.029780466 | G9: -276.70291 | H9: -225.96264 | I9: 0.81662548 | K9: COGS | L9: -356.23716 | M9: -451.51496 | N9: 95.2778 | O9: -0.21101804 | P9: -519.70141 | Q9: 163.46425 | R9: -0.31453494 | T9: COGS | U9: -385.69993 | V9: -510.02511 | W9: 124.32518 | X9: -0.24376286 | Y9: -790.66062 | Z9: 404.96069 | AA9: -0.51218017 | AC9: COGS | AD9: -506.20309 | AE9: -440.06148 | AF9: -66.14161 | AG9: 0.15030084 | AH9: -649.52213 | AI9: 143.31904 | AJ9: -0.22065305 | AL9: COGS | AM9: -624.27234 | AN9: -669.88812 | AO9: 45.61578 | AP9: -0.068094625 | AQ9: -562.17093 | AR9: -62.10141 | AS9: 0.11046713 | AU9: COGS | AV9: -743.55859 | AW9: -248.36745 | AX9: -495.19114 | AY9: 1.9937844 | AZ9: -738.47207 | BA9: -5.0865197 | BB9: 0.0068878972 | BD9: COGS | BE9: -525.31503 | BF9: -330.56434 | BG9: -194.75069 | BH9: 0.58914609 | BI9: -462.95679 | BJ9: -62.35824 | BK9: 0.13469559 | BM9: COGS | BN9: -272.12023 | BO9: -99.2048 | BP9: -172.91543 | BQ9: 1.7430148 | BR9: -266.53106 | BS9: -5.5891689 | BT9: 0.020970047 | BV9: COGS | BW9: =(GETPIVOTDATA("sep-26 ",TABLA!$B$3,"Nivel 4","2.- Variación de existencias")+GETPIVOTDATA("sep-26 ",TABLA!$B$3,"Nivel 4","4.- Aprovisionamientos"))/1000 -> -202.31205 | BX9: =VLOOKUP(BV9,'P&L Mensualitzada 2025'!$A$5:$N$25,$BW$3+1,0) -> -265.37091 | BY9: =BW9-BX9 -> 63.05886 | BZ9: =+IF(IFERROR(BW9/BX9-1,"-")<300%,IFERROR(BW9/BX9-1,"-"),"n.a.") -> -0.23762537 | CA9: =VLOOKUP(BV9,'Budget26 sin EI'!$B:$O,$BW$3+1,0) -> -352.55893 | CB9: =BW9-CA9 -> 150.24688 | CC9: =+IF(IFERROR(BW9/CA9-1,"-")<300%,IFERROR(BW9/CA9-1,"-"),"n.a.") -> -0.42616104 | CE9: COGS | CF9: =(GETPIVOTDATA("oct-26 ",TABLA!$B$3,"Nivel 4","2.- Variación de existencias")+GETPIVOTDATA("oct-26 ",TABLA!$B$3,"Nivel 4","4.- Aprovisionamientos"))/1000 -> -302.10136 | CG9: =VLOOKUP(CE9,'P&L Mensualitzada 2025'!$A$5:$N$25,$CF$3+1,0) -> -361.07371 | CH9: =CF9-CG9 -> 58.97235 | CI9: =+IF(IFERROR(CF9/CG9-1,"-")<300%,IFERROR(CF9/CG9-1,"-"),"n.a.") -> -0.16332496 | CJ9: =VLOOKUP(CE9,'Budget26 sin EI'!$B:$O,$CF$3+1,0) -> -274.25544 | CK9: =CF9-CJ9 -> -27.84592 | CL9: =+IF(IFERROR(CF9/CJ9-1,"-")<300%,IFERROR(CF9/CJ9-1,"-"),"n.a.") -> 0.10153279 | CN9: COGS | CO9: =(GETPIVOTDATA("nov-26 ",TABLA!$B$3,"Nivel 4","2.- Variación de existencias")+GETPIVOTDATA("nov-26 ",TABLA!$B$3,"Nivel 4","4.- Aprovisionamientos"))/1000 -> -404.42328 | CP9: =VLOOKUP(CN9,'P&L Mensualitzada 2025'!$A$5:$N$25,$CO$3+1,0) -> -275.74654 | CQ9: =CO9-CP9 -> -128.67674 | CR9: =+IF(IFERROR(CO9/CP9-1,"-")<300%,IFERROR(CO9/CP9-1,"-"),"n.a.") -> 0.46664861 | CS9: =VLOOKUP(CN9,'Budget26 sin EI'!$B:$O,$CO$3+1,0) -> -353.82089 | CT9: =CO9-CS9 -> -50.602393 | CU9: =+IF(IFERROR(CO9/CS9-1,"-")<300%,IFERROR(CO9/CS9-1,"-"),"n.a.") -> 0.14301697 | CW9: COGS | CX9: =(GETPIVOTDATA("dic-26 ",TABLA!$B$3,"Nivel 4","2.- Variación de existencias")+GETPIVOTDATA("dic-26 ",TABLA!$B$3,"Nivel 4","4.- Aprovisionamientos"))/1000 -> -449.14533 | CY9: =VLOOKUP(CW9,'P&L Mensualitzada 2025'!$A$5:$N$25,$CX$3+1,0) -> -116.4287 | CZ9: =CX9-CY9 -> -332.71663 | DA9: =+IF(IFERROR(CX9/CY9-1,"-")<300%,IFERROR(CX9/CY9-1,"-"),"n.a.") -> 2.8576857 | DB9: =VLOOKUP(CW9,'Budget26 sin EI'!$B:$O,$CX$3+1,0) -> -226.64682 | DC9: =CX9-DB9 -> -222.49851 | DD9: =+IF(IFERROR(CX9/DB9-1,"-")<300%,IFERROR(CX9/DB9-1,"-"),"n.a.") -> 0.981697 | DF9: COGS | DG9: =(GETPIVOTDATA("Total 2026 ",TABLA!$B$3,"Nivel 4","2.- Variación de existencias")+GETPIVOTDATA("Total 2026 ",TABLA!$B$3,"Nivel 4","4.- Aprovisionamientos"))/1000 -> -5233.5328 | DH9: =VLOOKUP(DF9,'P&L Mensualitzada 2025'!$A$5:$N$25,$CX$3+2,0) -> -4286.3408 | DI9: =DG9-DH9 -> -947.19208 | DJ9: =+IF(IFERROR(DG9/DH9-1,"-")<300%,IFERROR(DG9/DH9-1,"-"),"n.a.") -> 0.22097918 | DK9: =VLOOKUP(DF9,'Budget26 sin EI'!$B:$O,$CX$3+2,0) -> -5474 | DL9: =DG9-DK9 -> 240.46715 | DM9: =+IF(IFERROR(DG9/DK9-1,"-")<300%,IFERROR(DG9/DK9-1,"-"),"n.a.") -> -0.043928963
B10: Gross Profit | C10: 481.15158 | D10: 104.19249 | E10: 376.95909 | F10: 3.6179104 | G10: 528.99072 | H10: -47.839142 | I10: -0.090434747 | K10: Gross Profit | L10: 1114.191 | M10: 610.92613 | N10: 503.26486 | O10: 0.82377367 | P10: 993.54657 | Q10: 120.64442 | R10: 0.12142804 | T10: Gross Profit | U10: 1148.0895 | V10: 1285.1219 | W10: -137.03244 | X10: -0.10662991 | Y10: 1511.5567 | Z10: -363.46721 | AA10: -0.24045887 | AC10: Gross Profit | AD10: 955.94319 | AE10: 1094.2894 | AF10: -138.34622 | AG10: -0.12642562 | AH10: 1241.7332 | AI10: -285.79 | AJ10: -0.23015411 | AL10: Gross Profit | AM10: 1301.6576 | AN10: 814.02707 | AO10: 487.6305 | AP10: 0.59903475 | AQ10: 1074.7383 | AR10: 226.91929 | AS10: 0.21113911 | AU10: Gross Profit | AV10: 1218.7032 | AW10: 1512.5746 | AX10: -293.87131 | AY10: -0.1942855 | AZ10: 1411.7845 | BA10: -193.08126 | BB10: -0.13676397 | BD10: Gross Profit | BE10: 765.3392 | BF10: 984.00014 | BG10: -218.66094 | BH10: -0.22221637 | BI10: 885.06424 | BJ10: -119.72504 | BK10: -0.13527271 | BM10: Gross Profit | BN10: 515.98492 | BO10: 565.29214 | BP10: -49.30722 | BQ10: -0.087224316 | BR10: 509.54455 | BS10: 6.4403674 | BT10: 0.012639459 | BV10: Gross Profit | BW10: =BW8+BW9 -> 422.41283 | BX10: =SUM(BX8:BX9) -> 576.74488 | BY10: =BW10-BX10 -> -154.33205 | BZ10: =+IF(IFERROR(BW10/BX10-1,"-")<300%,IFERROR(BW10/BX10-1,"-"),"n.a.") -> -0.26759154 | CA10: =SUM(CA8:CA9) -> 674.00956 | CB10: =BW10-CA10 -> -251.59673 | CC10: =+IF(IFERROR(BW10/CA10-1,"-")<300%,IFERROR(BW10/CA10-1,"-"),"n.a.") -> -0.37328362 | CE10: Gross Profit | CF10: =CF8+CF9 -> 609.95365 | CG10: =SUM(CG8:CG9) -> 338.50974 | CH10: =CF10-CG10 -> 271.44391 | CI10: =+IF(IFERROR(CF10/CG10-1,"-")<300%,IFERROR(CF10/CG10-1,"-"),"n.a.") -> 0.80187917 | CJ10: =SUM(CJ8:CJ9) -> 524.31174 | CK10: =CF10-CJ10 -> 85.641906 | CL10: =+IF(IFERROR(CF10/CJ10-1,"-")<300%,IFERROR(CF10/CJ10-1,"-"),"n.a.") -> 0.16334157 | CN10: Gross Profit | CO10: =CO8+CO9 -> 820.8985 | CP10: =SUM(CP8:CP9) -> 473.95262 | CQ10: =CO10-CP10 -> 346.94588 | CR10: =+IF(IFERROR(CO10/CP10-1,"-")<300%,IFERROR(CO10/CP10-1,"-"),"n.a.") -> 0.73202651 | CS10: =SUM(CS8:CS9) -> 676.42212 | CT10: =CO10-CS10 -> 144.47638 | CU10: =+IF(IFERROR(CO10/CS10-1,"-")<300%,IFERROR(CO10/CS10-1,"-"),"n.a.") -> 0.21358908 | CW10: Gross Profit | CX10: =CX8+CX9 -> 693.26205 | CY10: =SUM(CY8:CY9) -> 132.07731 | CZ10: =CX10-CY10 -> 561.18474 | DA10: =+IF(IFERROR(CX10/CY10-1,"-")<300%,IFERROR(CX10/CY10-1,"-"),"n.a.") -> n.a. | DB10: =SUM(DB8:DB9) -> 433.29783 | DC10: =CX10-DB10 -> 259.96422 | DD10: =+IF(IFERROR(CX10/DB10-1,"-")<300%,IFERROR(CX10/DB10-1,"-"),"n.a.") -> 0.59996659 | DF10: Gross Profit | DG10: =DG8+DG9 -> 9946.4672 | DH10: =SUM(DH8:DH9) -> 8491.7084 | DI10: =DG10-DH10 -> 1454.7587 | DJ10: =+IF(IFERROR(DG10/DH10-1,"-")<300%,IFERROR(DG10/DH10-1,"-"),"n.a.") -> 0.1713152 | DK10: =SUM(DK8:DK9) -> 10465 | DL10: =DG10-DK10 -> -518.53285 | DM10: =+IF(IFERROR(DG10/DK10-1,"-")<300%,IFERROR(DG10/DK10-1,"-"),"n.a.") -> -0.049549245
B11: % Gross Margin | C11: 0.48906607 | D11: 0.16743475 | G11: 0.6565656 | K11: % Gross Margin | L11: 0.75773236 | M11: 0.57502118 | P11: 0.6565656 | T11: % Gross Margin | U11: 0.74853136 | V11: 0.71588672 | Y11: 0.6565656 | AC11: % Gross Margin | AD11: 0.6537945 | AE11: 0.71319371 | AH11: 0.6565656 | AL11: % Gross Margin | AM11: 0.67585926 | AN11: 0.54856711 | AQ11: 0.6565656 | AU11: % Gross Margin | AV11: 0.62107065 | AW11: 0.85895762 | AZ11: 0.6565656 | BD11: % Gross Margin | BE11: 0.59298547 | BF11: 0.74853699 | BI11: 0.6565656 | BM11: % Gross Margin | BN11: 0.65471583 | BO11: 0.85070691 | BR11: 0.6565656 | BV11: % Gross Margin | BW11: =BW10/BW8 -> 0.67615817 | BX11: =BX10/BX8 -> 0.68487598 | CA11: =CA10/CA8 -> 0.6565656 | CE11: % Gross Margin | CF11: =CF10/CF8 -> 0.66876849 | CG11: =CG10/CG8 -> 0.48387328 | CJ11: =CJ10/CJ8 -> 0.6565656 | CN11: % Gross Margin | CO11: =CO10/CO8 -> 0.66994524 | CP11: =CP10/CP8 -> 0.63219041 | CS11: =CS10/CS8 -> 0.6565656 | CW11: % Gross Margin | CX11: =CX10/CX8 -> 0.60684311 | CY11: =CY10/CY8 -> 0.53148538 | DB11: =DB10/DB8 -> 0.65656692 | DF11: % Gross Margin | DG11: =DG10/DG8 -> 0.65523499 | DH11: =DH10/DH8 -> 0.66455437 | DK11: =DK10/DK8 -> 0.65656566
B13: Gastos de Personal | C13: -111.53201 | D13: 17.397715 | E13: -128.92973 | F13: -7.4107275 | G13: -138.431 | H13: 26.898993 | I13: -0.19431336 | K13: Gastos de Personal | L13: -142.9272 | M13: -169.90228 | N13: 26.97508 | O13: -0.1587682 | P13: -152.80201 | Q13: 9.8748135 | R13: -0.064624891 | T13: Gastos de Personal | U13: -146.23331 | V13: -215.24045 | W13: 69.00714 | X13: -0.32060489 | Y13: -268.64421 | Z13: 122.4109 | AA13: -0.45566178 | AC13: Gastos de Personal | AD13: -130.04767 | AE13: -145.05985 | AF13: 15.01218 | AG13: -0.10348956 | AH13: -157.32982 | AI13: 27.282153 | AJ13: -0.17340739 | AL13: Gastos de Personal | AM13: -134.99252 | AN13: -141.27428 | AO13: 6.28176 | AP13: -0.044464994 | AQ13: -157.32982 | AR13: 22.337303 | AS13: -0.14197755 | AU13: Gastos de Personal | AV13: -145.07228 | AW13: -98.245985 | AX13: -46.826295 | AY13: 0.47662299 | AZ13: -290.07649 | BA13: 145.00421 | BB13: -0.49988267 | BD13: Gastos de Personal | BE13: -153.53365 | BF13: -218.74298 | BG13: 65.20933 | BH13: -0.29810936 | BI13: -157.32982 | BJ13: 3.7961735 | BK13: -0.02412876 | BM13: Gastos de Personal | BN13: -152.63279 | BO13: -131.97477 | BP13: -20.65802 | BQ13: 0.15653007 | BR13: -162.96321 | BS13: 10.330416 | BT13: -0.063391092 | BV13: Gastos de Personal | BW13: =GETPIVOTDATA("sep-26 ",TABLA!$B$3,"Nivel 4","6.- Gastos de personal")/1000 -> -165.80399 | BX13: =VLOOKUP(BV13,'P&L Mensualitzada 2025'!$A$5:$N$25,$BW$3+1,0) -> -133.7212 | BY13: =BW13-BX13 -> -32.08279 | BZ13: =+IF(IFERROR(BW13/BX13-1,"-")<300%,IFERROR(BW13/BX13-1,"-"),"n.a.") -> 0.23992299 | CA13: =VLOOKUP(BV13,'Budget26 sin EI'!$B:$O,$BW$3+1,0) -> -174.23 | CB13: =BW13-CA13 -> 8.42601 | CC13: =+IF(IFERROR(BW13/CA13-1,"-")<300%,IFERROR(BW13/CA13-1,"-"),"n.a.") -> -0.048361419 | CE13: Gastos de Personal | CF13: =GETPIVOTDATA("oct-26 ",TABLA!$B$3,"Nivel 4","6.- Gastos de personal")/1000 -> -152.63279 | CG13: =VLOOKUP(CE13,'P&L Mensualitzada 2025'!$A$5:$N$25,$CF$3+1,0) -> -300.72411 | CH13: =CF13-CG13 -> 148.09132 | CI13: =+IF(IFERROR(CF13/CG13-1,"-")<300%,IFERROR(CF13/CG13-1,"-"),"n.a.") -> -0.49244911 | CJ13: =VLOOKUP(CE13,'Budget26 sin EI'!$B:$O,$CF$3+1,0) -> -174.23 | CK13: =CF13-CJ13 -> 21.59721 | CL13: =+IF(IFERROR(CF13/CJ13-1,"-")<300%,IFERROR(CF13/CJ13-1,"-"),"n.a.") -> -0.12395804 | CN13: Gastos de Personal | CO13: =GETPIVOTDATA("nov-26 ",TABLA!$B$3,"Nivel 4","6.- Gastos de personal")/1000 -> -152.63279 | CP13: =VLOOKUP(CN13,'P&L Mensualitzada 2025'!$A$5:$N$25,$CO$3+1,0) -> -153.08435 | CQ13: =CO13-CP13 -> 0.45156 | CR13: =+IF(IFERROR(CO13/CP13-1,"-")<300%,IFERROR(CO13/CP13-1,"-"),"n.a.") -> -0.0029497463 | CS13: =VLOOKUP(CN13,'Budget26 sin EI'!$B:$O,$CO$3+1,0) -> -174.23 | CT13: =CO13-CS13 -> 21.59721 | CU13: =+IF(IFERROR(CO13/CS13-1,"-")<300%,IFERROR(CO13/CS13-1,"-"),"n.a.") -> -0.12395804 | CW13: Gastos de Personal | CX13: =GETPIVOTDATA("dic-26 ",TABLA!$B$3,"Nivel 4","6.- Gastos de personal")/1000 -> -431.63279 | CY13: =VLOOKUP(CW13,'P&L Mensualitzada 2025'!$A$5:$N$25,$CX$3+1,0) -> -172.01862 | CZ13: =CX13-CY13 -> -259.61417 | DA13: =+IF(IFERROR(CX13/CY13-1,"-")<300%,IFERROR(CX13/CY13-1,"-"),"n.a.") -> 1.5092213 | DB13: =VLOOKUP(CW13,'Budget26 sin EI'!$B:$O,$CX$3+1,0) -> -306.97667 | DC13: =CX13-DB13 -> -124.65612 | DD13: =+IF(IFERROR(CX13/DB13-1,"-")<300%,IFERROR(CX13/DB13-1,"-"),"n.a.") -> 0.40607687 | DF13: Gastos de Personal | DG13: =GETPIVOTDATA("Total 2026 ",TABLA!$B$3,"Nivel 4","6.- Gastos de personal")/1000 -> -2006.5026 | DH13: =VLOOKUP(DF13,'P&L Mensualitzada 2025'!$A$5:$N$25,$CX$3+2,0) -> -1862.5912 | DI13: =DG13-DH13 -> -143.91143 | DJ13: =+IF(IFERROR(DG13/DH13-1,"-")<300%,IFERROR(DG13/DH13-1,"-"),"n.a.") -> 0.0772641 | DK13: =VLOOKUP(DF13,'Budget26 sin EI'!$B:$O,$CX$3+2,0) -> -2314.5731 | DL13: =DG13-DK13 -> 308.07047 | DM13: =+IF(IFERROR(DG13/DK13-1,"-")<300%,IFERROR(DG13/DK13-1,"-"),"n.a.") -> -0.13310034
B14: % of Revenue | C14: -0.11336661 | D14: 0.027957697 | G14: -0.17181593 | K14: % of Revenue | L14: -0.097201077 | M14: -0.15991689 | P14: -0.10097619 | T14: % of Revenue | U14: -0.095341192 | V14: -0.11990129 | Y14: -0.11668934 | AC14: % of Revenue | AD14: -0.088942995 | AE14: -0.09454151 | AH14: -0.08318804 | AL14: % of Revenue | AM14: -0.070092125 | AN14: -0.095203743 | AQ14: -0.096113958 | AU14: % of Revenue | AV14: -0.073931153 | AW14: -0.055791721 | AZ14: -0.1349032 | BD14: % of Revenue | BE14: -0.118958 | BF14: -0.16639958 | BI14: -0.1167117 | BM14: % of Revenue | BN14: -0.19367059 | BO14: -0.19860854 | BR14: -0.20998367 | BV14: % of Revenue | BW14: =BW13/BW8 -> -0.26540321 | BX14: =BX13/BX8 -> -0.15879194 | CA14: =CA13/CA8 -> -0.16972078 | CE14: % of Revenue | CF14: =CF13/CF8 -> -0.16735042 | CG14: =CG13/CG8 -> -0.42986167 | CJ14: =CJ13/CJ8 -> -0.21817826 | CN14: % of Revenue | CO14: =CO13/CO8 -> -0.12456548 | CP14: =CP13/CP8 -> -0.20419437 | CS14: =CS13/CS8 -> -0.16911544 | CW14: % of Revenue | CX14: =CX13/CX8 -> -0.37782738 | CY14: =CY13/CY8 -> -0.69221111 | DB14: =DB13/DB8 -> -0.46515517 | DF14: % of Revenue | DG14: =DG13/DG8 -> -0.13218067 | DH14: =DH13/DH8 -> -0.14576491 | DK14: =DK13/DK8 -> -0.14521445
B16: Otros Ingresos Operativos | C16: 0 | D16: 0 | E16: 0 | F16: n.a. | G16: 0 | H16: 0 | I16: n.a. | K16: Otros Ingresos Operativos | L16: 0 | M16: 0.23944 | N16: -0.23944 | O16: -1 | P16: 0 | Q16: 0 | R16: n.a. | T16: Otros Ingresos Operativos | U16: 0 | V16: 0 | W16: 0 | X16: n.a. | Y16: 0 | Z16: 0 | AA16: n.a. | AC16: Otros Ingresos Operativos | AD16: 0.75075 | AE16: 0 | AF16: 0.75075 | AG16: n.a. | AH16: 0 | AI16: 0.75075 | AJ16: n.a. | AL16: Otros Ingresos Operativos | AM16: 25.14075 | AN16: 0.43575 | AO16: 24.705 | AP16: n.a. | AQ16: 0 | AR16: 25.14075 | AS16: n.a. | AU16: Otros Ingresos Operativos | AV16: 22.9776 | AW16: 0.11769 | AX16: 22.85991 | AY16: n.a. | AZ16: 0 | BA16: 22.9776 | BB16: n.a. | BD16: Otros Ingresos Operativos | BE16: 11.02724 | BF16: 0 | BG16: 11.02724 | BH16: n.a. | BI16: 0 | BJ16: 11.02724 | BK16: n.a. | BM16: Otros Ingresos Operativos | BN16: 11.429 | BO16: 0 | BP16: 11.429 | BQ16: n.a. | BR16: 0 | BS16: 11.429 | BT16: n.a. | BV16: Otros Ingresos Operativos | BW16: =GETPIVOTDATA("sep-26 ",TABLA!$B$3,"Nivel 4","5.- Otros ingresos de explotación")/1000 -> 9.613 | BX16: =VLOOKUP(BV16,'P&L Mensualitzada 2025'!$A$5:$N$25,$BW$3+1,0) -> 0 | BY16: =BW16-BX16 -> 9.613 | BZ16: =+IF(IFERROR(BW16/BX16-1,"-")<300%,IFERROR(BW16/BX16-1,"-"),"n.a.") -> n.a. | CA16: =VLOOKUP(BV16,'Budget26 sin EI'!$B:$O,$BW$3+1,0) -> 0 | CB16: =BW16-CA16 -> 9.613 | CC16: =+IF(IFERROR(BW16/CA16-1,"-")<300%,IFERROR(BW16/CA16-1,"-"),"n.a.") -> n.a. | CE16: Otros Ingresos Operativos | CF16: =GETPIVOTDATA("oct-26 ",TABLA!$B$3,"Nivel 4","5.- Otros ingresos de explotación")/1000 -> 21.379 | CG16: =VLOOKUP(CE16,'P&L Mensualitzada 2025'!$A$5:$N$25,$CF$3+1,0) -> 1.80096 | CH16: =CF16-CG16 -> 19.57804 | CI16: =+IF(IFERROR(CF16/CG16-1,"-")<300%,IFERROR(CF16/CG16-1,"-"),"n.a.") -> n.a. | CJ16: =VLOOKUP(CE16,'Budget26 sin EI'!$B:$O,$CF$3+1,0) -> 0 | CK16: =CF16-CJ16 -> 21.379 | CL16: =+IF(IFERROR(CF16/CJ16-1,"-")<300%,IFERROR(CF16/CJ16-1,"-"),"n.a.") -> n.a. | CN16: Otros Ingresos Operativos | CO16: =GETPIVOTDATA("nov-26 ",TABLA!$B$3,"Nivel 4","5.- Otros ingresos de explotación")/1000 -> 32.454 | CP16: =VLOOKUP(CN16,'P&L Mensualitzada 2025'!$A$5:$N$25,$CO$3+1,0) -> 0 | CQ16: =CO16-CP16 -> 32.454 | CR16: =+IF(IFERROR(CO16/CP16-1,"-")<300%,IFERROR(CO16/CP16-1,"-"),"n.a.") -> n.a. | CS16: =VLOOKUP(CN16,'Budget26 sin EI'!$B:$O,$CO$3+1,0) -> 0 | CT16: =CO16-CS16 -> 32.454 | CU16: =+IF(IFERROR(CO16/CS16-1,"-")<300%,IFERROR(CO16/CS16-1,"-"),"n.a.") -> n.a. | CW16: Otros Ingresos Operativos | CX16: =GETPIVOTDATA("dic-26 ",TABLA!$B$3,"Nivel 4","5.- Otros ingresos de explotación")/1000 -> 27.15 | CY16: =VLOOKUP(CW16,'P&L Mensualitzada 2025'!$A$5:$N$25,$CX$3+1,0) -> 47.20436 | CZ16: =CX16-CY16 -> -20.05436 | DA16: =+IF(IFERROR(CX16/CY16-1,"-")<300%,IFERROR(CX16/CY16-1,"-"),"n.a.") -> -0.42484126 | DB16: =VLOOKUP(CW16,'Budget26 sin EI'!$B:$O,$CX$3+1,0) -> 0 | DC16: =CX16-DB16 -> 27.15 | DD16: =+IF(IFERROR(CX16/DB16-1,"-")<300%,IFERROR(CX16/DB16-1,"-"),"n.a.") -> n.a. | DF16: Otros Ingresos Operativos | DG16: =GETPIVOTDATA("Total 2026 ",TABLA!$B$3,"Nivel 4","5.- Otros ingresos de explotación")/1000 -> 168.56134 | DH16: =VLOOKUP(DF16,'P&L Mensualitzada 2025'!$A$5:$N$25,$CX$3+2,0) -> 49.7982 | DI16: =DG16-DH16 -> 118.76314 | DJ16: =+IF(IFERROR(DG16/DH16-1,"-")<300%,IFERROR(DG16/DH16-1,"-"),"n.a.") -> 2.3848882 | DK16: =VLOOKUP(DF16,'Budget26 sin EI'!$B:$O,$CX$3+2,0) -> 0 | DL16: =DG16-DK16 -> 168.56134 | DM16: =+IF(IFERROR(DG16/DK16-1,"-")<300%,IFERROR(DG16/DK16-1,"-"),"n.a.") -> n.a.
B17: Otros Gastos Operativos | C17: -103.45176 | D17: -83.04566 | E17: -20.4061 | F17: 0.24572145 | G17: -183.33533 | H17: 79.883569 | I17: -0.43572382 | K17: Otros Gastos Operativos | L17: -62.49888 | M17: -74.84982 | N17: 12.35094 | O17: -0.16500962 | P17: -133.85532 | Q17: 71.356439 | R17: -0.53308632 | T17: Otros Gastos Operativos | U17: -110.60627 | V17: -105.74077 | W17: -4.8655 | X17: 0.046013472 | Y17: -128.94532 | Z17: 18.339049 | AA17: -0.14222346 | AC17: Otros Gastos Operativos | AD17: -107.70665 | AE17: -91.37805 | AF17: -16.3286 | AG17: 0.1786928 | AH17: -131.89532 | AI17: 24.188669 | AJ17: -0.18339293 | AL17: Otros Gastos Operativos | AM17: -123.39208 | AN17: -108.29459 | AO17: -15.09749 | AP17: 0.1394113 | AQ17: -126.94533 | AR17: 3.5532492 | AS17: -0.027990389 | AU17: Otros Gastos Operativos | AV17: -175.01376 | AW17: -116.04261 | AX17: -58.97115 | AY17: 0.50818531 | AZ17: -160.19533 | BA17: -14.818431 | BB17: 0.092502265 | BD17: Otros Gastos Operativos | BE17: -161.05174 | BF17: -102.38971 | BG17: -58.662034 | BH17: 0.572929 | BI17: -152.80333 | BJ17: -8.2484151 | BK17: 0.053980598 | BM17: Otros Gastos Operativos | BN17: -130.06066 | BO17: -68.70525 | BP17: -61.355411 | BQ17: 0.89302362 | BR17: -117.79333 | BS17: -12.267332 | BT17: 0.10414284 | BV17: Otros Gastos Operativos | BW17: =GETPIVOTDATA("sep-26 ",TABLA!$B$3,"Nivel 4","7.- Otros gastos de explotación")/1000 -> -108.09534 | BX17: =VLOOKUP(BV17,'P&L Mensualitzada 2025'!$A$5:$N$25,$BW$3+1,0) -> -73.91279 | BY17: =BW17-BX17 -> -34.18255 | BZ17: =+IF(IFERROR(BW17/BX17-1,"-")<300%,IFERROR(BW17/BX17-1,"-"),"n.a.") -> 0.46247138 | CA17: =VLOOKUP(BV17,'Budget26 sin EI'!$B:$O,$BW$3+1,0) -> -120.05333 | CB17: =BW17-CA17 -> 11.957989 | CC17: =+IF(IFERROR(BW17/CA17-1,"-")<300%,IFERROR(BW17/CA17-1,"-"),"n.a.") -> -0.099605644 | CE17: Otros Gastos Operativos | CF17: =GETPIVOTDATA("oct-26 ",TABLA!$B$3,"Nivel 4","7.- Otros gastos de explotación")/1000 -> -149.47019 | CG17: =VLOOKUP(CE17,'P&L Mensualitzada 2025'!$A$5:$N$25,$CF$3+1,0) -> -122.16905 | CH17: =CF17-CG17 -> -27.30114 | CI17: =+IF(IFERROR(CF17/CG17-1,"-")<300%,IFERROR(CF17/CG17-1,"-"),"n.a.") -> 0.22347018 | CJ17: =VLOOKUP(CE17,'Budget26 sin EI'!$B:$O,$CF$3+1,0) -> -144.84269 | CK17: =CF17-CJ17 -> -4.6275008 | CL17: =+IF(IFERROR(CF17/CJ17-1,"-")<300%,IFERROR(CF17/CJ17-1,"-"),"n.a.") -> 0.03194846 | CN17: Otros Gastos Operativos | CO17: =GETPIVOTDATA("nov-26 ",TABLA!$B$3,"Nivel 4","7.- Otros gastos de explotación")/1000 -> -162.36942 | CP17: =VLOOKUP(CN17,'P&L Mensualitzada 2025'!$A$5:$N$25,$CO$3+1,0) -> -68.32762 | CQ17: =CO17-CP17 -> -94.0418 | CR17: =+IF(IFERROR(CO17/CP17-1,"-")<300%,IFERROR(CO17/CP17-1,"-"),"n.a.") -> 1.3763365 | CS17: =VLOOKUP(CN17,'Budget26 sin EI'!$B:$O,$CO$3+1,0) -> -148.99269 | CT17: =CO17-CS17 -> -13.376731 | CU17: =+IF(IFERROR(CO17/CS17-1,"-")<300%,IFERROR(CO17/CS17-1,"-"),"n.a.") -> 0.089781122 | CW17: Otros Gastos Operativos | CX17: =GETPIVOTDATA("dic-26 ",TABLA!$B$3,"Nivel 4","7.- Otros gastos de explotación")/1000 -> -277.59629 | CY17: =VLOOKUP(CW17,'P&L Mensualitzada 2025'!$A$5:$N$25,$CX$3+1,0) -> -239.07332 | CZ17: =CX17-CY17 -> -38.52297 | DA17: =+IF(IFERROR(CX17/CY17-1,"-")<300%,IFERROR(CX17/CY17-1,"-"),"n.a.") -> 0.16113454 | DB17: =VLOOKUP(CW17,'Budget26 sin EI'!$B:$O,$CX$3+1,0) -> -180.34269 | DC17: =CX17-DB17 -> -97.253601 | DD17: =+IF(IFERROR(CX17/DB17-1,"-")<300%,IFERROR(CX17/DB17-1,"-"),"n.a.") -> 0.5392711 | DF17: Otros Gastos Operativos | DG17: =GETPIVOTDATA("Total 2026 ",TABLA!$B$3,"Nivel 4","7.- Otros gastos de explotación")/1000 -> -1684.026 | DH17: =VLOOKUP(DF17,'P&L Mensualitzada 2025'!$A$5:$N$25,$CX$3+2,0) -> -1253.9292 | DI17: =DG17-DH17 -> -430.09679 | DJ17: =+IF(IFERROR(DG17/DH17-1,"-")<300%,IFERROR(DG17/DH17-1,"-"),"n.a.") -> 0.34299925 | DK17: =VLOOKUP(DF17,'Budget26 sin EI'!$B:$O,$CX$3+2,0) -> -1730 | DL17: =DG17-DK17 -> 45.973975 | DM17: =+IF(IFERROR(DG17/DK17-1,"-")<300%,IFERROR(DG17/DK17-1,"-"),"n.a.") -> -0.026574552
B18: Operating Expenses | C18: -103.45176 | D18: -83.04566 | E18: -20.4061 | F18: 0.24572145 | G18: -183.33533 | H18: 79.883569 | I18: -0.43572382 | K18: Operating Expenses | L18: -62.49888 | M18: -74.61038 | N18: 12.1115 | O18: -0.16232996 | P18: -133.85532 | Q18: 71.356439 | R18: -0.53308632 | T18: Operating Expenses | U18: -110.60627 | V18: -105.74077 | W18: -4.8655 | X18: 0.046013472 | Y18: -128.94532 | Z18: 18.339049 | AA18: -0.14222346 | AC18: Operating Expenses | AD18: -106.9559 | AE18: -91.37805 | AF18: -15.57785 | AG18: 0.17047694 | AH18: -131.89532 | AI18: 24.939419 | AJ18: -0.18908494 | AL18: Operating Expenses | AM18: -98.25133 | AN18: -107.85884 | AO18: 9.60751 | AP18: -0.08907485 | AQ18: -126.94533 | AR18: 28.693999 | AS18: -0.2260343 | AU18: Operating Expenses | AV18: -152.03616 | AW18: -115.92492 | AX18: -36.11124 | AY18: 0.31150541 | AZ18: -160.19533 | BA18: 8.1591692 | BB18: -0.050932628 | BD18: Operating Expenses | BE18: -150.0245 | BF18: -102.38971 | BG18: -47.634794 | BH18: 0.46523029 | BI18: -152.80333 | BJ18: 2.7788249 | BK18: -0.018185631 | BM18: Operating Expenses | BN18: -118.63166 | BO18: -68.70525 | BP18: -49.926411 | BQ18: 0.72667534 | BR18: -117.79333 | BS18: -0.83833187 | BT18: 0.0071169724 | BV18: Operating Expenses | BW18: =SUM(BW16:BW17) -> -98.48234 | BX18: =SUM(BX16:BX17) -> -73.91279 | BY18: =BW18-BX18 -> -24.56955 | BZ18: =+IF(IFERROR(BW18/BX18-1,"-")<300%,IFERROR(BW18/BX18-1,"-"),"n.a.") -> 0.3324127 | CA18: =SUM(CA16:CA17) -> -120.05333 | CB18: =BW18-CA18 -> 21.570989 | CC18: =+IF(IFERROR(BW18/CA18-1,"-")<300%,IFERROR(BW18/CA18-1,"-"),"n.a.") -> -0.17967839 | CE18: Operating Expenses | CF18: =SUM(CF16:CF17) -> -128.09119 | CG18: =SUM(CG16:CG17) -> -120.36809 | CH18: =CF18-CG18 -> -7.7231 | CI18: =+IF(IFERROR(CF18/CG18-1,"-")<300%,IFERROR(CF18/CG18-1,"-"),"n.a.") -> 0.064162354 | CJ18: =SUM(CJ16:CJ17) -> -144.84269 | CK18: =CF18-CJ18 -> 16.751499 | CL18: =+IF(IFERROR(CF18/CJ18-1,"-")<300%,IFERROR(CF18/CJ18-1,"-"),"n.a.") -> -0.11565305 | CN18: Operating Expenses | CO18: =SUM(CO16:CO17) -> -129.91542 | CP18: =SUM(CP16:CP17) -> -68.32762 | CQ18: =CO18-CP18 -> -61.5878 | CR18: =+IF(IFERROR(CO18/CP18-1,"-")<300%,IFERROR(CO18/CP18-1,"-"),"n.a.") -> 0.90136024 | CS18: =SUM(CS16:CS17) -> -148.99269 | CT18: =CO18-CS18 -> 19.077269 | CU18: =+IF(IFERROR(CO18/CS18-1,"-")<300%,IFERROR(CO18/CS18-1,"-"),"n.a.") -> -0.12804165 | CW18: Operating Expenses | CX18: =SUM(CX16:CX17) -> -250.44629 | CY18: =SUM(CY16:CY17) -> -191.86896 | CZ18: =CX18-CY18 -> -58.57733 | DA18: =+IF(IFERROR(CX18/CY18-1,"-")<300%,IFERROR(CX18/CY18-1,"-"),"n.a.") -> 0.30529863 | DB18: =SUM(DB16:DB17) -> -180.34269 | DC18: =CX18-DB18 -> -70.103601 | DD18: =+IF(IFERROR(CX18/DB18-1,"-")<300%,IFERROR(CX18/DB18-1,"-"),"n.a.") -> 0.38872438 | DF18: Operating Expenses | DG18: =SUM(DG16:DG17) -> -1515.4647 | DH18: =SUM(DH16:DH17) -> -1204.131 | DI18: =DG18-DH18 -> -311.33365 | DJ18: =+IF(IFERROR(DG18/DH18-1,"-")<300%,IFERROR(DG18/DH18-1,"-"),"n.a.") -> 0.25855462 | DK18: =SUM(DK16:DK17) -> -1730 | DL18: =DG18-DK18 -> 214.53531 | DM18: =+IF(IFERROR(DG18/DK18-1,"-")<300%,IFERROR(DG18/DK18-1,"-"),"n.a.") -> -0.12400885
B19: % of Revenue | C19: -0.10515344 | D19: -0.13345232 | G19: -0.22754968 | K19: % of Revenue | L19: -0.042503865 | M19: -0.070225428 | P19: -0.08845564 | T19: % of Revenue | U19: -0.072113075 | V19: -0.058903682 | Y19: -0.056009187 | AC19: % of Revenue | AD19: -0.073149931 | AE19: -0.059554858 | AH19: -0.069739563 | AL19: % of Revenue | AM19: -0.051015008 | AN19: -0.072685313 | AQ19: -0.077551845 | AU19: % of Revenue | AV19: -0.077480058 | AW19: -0.065831197 | AZ19: -0.074500565 | BD19: % of Revenue | BE19: -0.11623911 | BF19: -0.077888694 | BI19: -0.11335382 | BM19: % of Revenue | BN19: -0.15052771 | BO19: -0.10339438 | BR19: -0.15178074 | BV19: % of Revenue | BW19: =BW18/BW8 -> -0.15764114 | BX19: =BX18/BX8 -> -0.087770341 | CA19: =CA18/CA8 -> -0.11694624 | CE19: % of Revenue | CF19: =CF18/CF8 -> -0.1404424 | CG19: =CG18/CG8 -> -0.1720568 | CJ19: =CJ18/CJ8 -> -0.18137821 | CN19: % of Revenue | CO19: =CO18/CO8 -> -0.10602555 | CP19: =CP18/CP8 -> -0.091140051 | CS19: =CS18/CS8 -> -0.14461898 | CW19: % of Revenue | CX19: =CX18/CX8 -> -0.21922678 | CY19: =CY18/CY8 -> -0.77208982 | DB19: =DB18/DB8 -> -0.27326941 | DF19: % of Revenue | DG19: =DG18/DG8 -> -0.099832983 | DH19: =DH18/DH8 -> -0.094234341 | DK19: =DK18/DK8 -> -0.1085388
B20: Gastos Fijos | C20: -214.98377 | D20: -65.647945 | E20: -149.33583 | F20: 2.2747982 | G20: -321.76633 | H20: 106.78256 | I20: -0.33186369 | K20: Gastos Fijos | L20: -205.42608 | M20: -244.51266 | N20: 39.08658 | O20: -0.15985504 | P20: -286.65733 | Q20: 81.231253 | R20: -0.28337406 | T20: Gastos Fijos | U20: -256.83958 | V20: -320.98122 | W20: 64.14164 | X20: -0.19982988 | Y20: -397.58953 | Z20: 140.74995 | AA20: -0.35400819 | AC20: Gastos Fijos | AD20: -237.00357 | AE20: -236.4379 | AF20: -0.56567 | AG20: 0.0023924675 | AH20: -289.22514 | AI20: 52.221573 | AJ20: -0.18055682 | AL20: Gastos Fijos | AM20: -233.24385 | AN20: -249.13312 | AO20: 15.88927 | AP20: -0.063778232 | AQ20: -284.27515 | AR20: 51.031303 | AS20: -0.17951376 | AU20: Gastos Fijos | AV20: -297.10844 | AW20: -214.1709 | AX20: -82.937535 | AY20: 0.38724931 | AZ20: -450.27182 | BA20: 153.16338 | BB20: -0.3401576 | BD20: Gastos Fijos | BE20: -303.55815 | BF20: -321.13269 | BG20: 17.574536 | BH20: -0.054726711 | BI20: -310.13315 | BJ20: 6.5749984 | BK20: -0.021200566 | BM20: Gastos Fijos | BN20: -271.26445 | BO20: -200.68002 | BP20: -70.584431 | BQ20: 0.35172625 | BR20: -280.75653 | BS20: 9.4920837 | BT20: -0.03380895 | BV20: Gastos Fijos | BW20: =BW18+BW13 -> -264.28633 | BX20: =BX18+BX13 -> -207.63399 | BY20: =BW20-BX20 -> -56.65234 | BZ20: =+IF(IFERROR(BW20/BX20-1,"-")<300%,IFERROR(BW20/BX20-1,"-"),"n.a.") -> 0.27284714 | CA20: =CA18+CA13 -> -294.28333 | CB20: =BW20-CA20 -> 29.996999 | CC20: =+IF(IFERROR(BW20/CA20-1,"-")<300%,IFERROR(BW20/CA20-1,"-"),"n.a.") -> -0.10193238 | CE20: Gastos Fijos | CF20: =CF18+CF13 -> -280.72398 | CG20: =CG18+CG13 -> -421.0922 | CH20: =CF20-CG20 -> 140.36822 | CI20: =+IF(IFERROR(CF20/CG20-1,"-")<300%,IFERROR(CF20/CG20-1,"-"),"n.a.") -> -0.3333432 | CJ20: =CJ18+CJ13 -> -319.07269 | CK20: =CF20-CJ20 -> 38.348709 | CL20: =+IF(IFERROR(CF20/CJ20-1,"-")<300%,IFERROR(CF20/CJ20-1,"-"),"n.a.") -> -0.120188 | CN20: Gastos Fijos | CO20: =CO18+CO13 -> -282.54821 | CP20: =CP18+CP13 -> -221.41197 | CQ20: =CO20-CP20 -> -61.13624 | CR20: =+IF(IFERROR(CO20/CP20-1,"-")<300%,IFERROR(CO20/CP20-1,"-"),"n.a.") -> 0.27611985 | CS20: =CS18+CS13 -> -323.22269 | CT20: =CO20-CS20 -> 40.674479 | CU20: =+IF(IFERROR(CO20/CS20-1,"-")<300%,IFERROR(CO20/CS20-1,"-"),"n.a.") -> -0.12584042 | CW20: Gastos Fijos | CX20: =CX18+CX13 -> -682.07908 | CY20: =CY18+CY13 -> -363.88758 | CZ20: =CX20-CY20 -> -318.1915 | DA20: =+IF(IFERROR(CX20/CY20-1,"-")<300%,IFERROR(CX20/CY20-1,"-"),"n.a.") -> 0.87442253 | DB20: =DB18+DB13 -> -487.31936 | DC20: =CX20-DB20 -> -194.75972 | DD20: =+IF(IFERROR(CX20/DB20-1,"-")<300%,IFERROR(CX20/DB20-1,"-"),"n.a.") -> 0.39965522 | DF20: Gastos Fijos | DG20: =DG18+DG13 -> -3521.9673 | DH20: =DH18+DH13 -> -3066.7222 | DI20: =DG20-DH20 -> -455.24508 | DJ20: =+IF(IFERROR(DG20/DH20-1,"-")<300%,IFERROR(DG20/DH20-1,"-"),"n.a.") -> 0.14844679 | DK20: =DK18+DK13 -> -4044.5731 | DL20: =DG20-DK20 -> 522.60578 | DM20: =+IF(IFERROR(DG20/DK20-1,"-")<300%,IFERROR(DG20/DK20-1,"-"),"n.a.") -> -0.12921161
B21: % of Revenue | C21: -0.21852005 | D21: -0.10549462 | G21: -0.39936562 | K21: % of Revenue | L21: -0.13970494 | M21: -0.23014232 | P21: -0.18943183 | T21: % of Revenue | U21: -0.16745427 | V21: -0.17880498 | Y21: -0.17269852 | AC21: % of Revenue | AD21: -0.16209293 | AE21: -0.15409637 | AH21: -0.1529276 | AL21: % of Revenue | AM21: -0.12110713 | AN21: -0.16788906 | AQ21: -0.1736658 | AU21: % of Revenue | AV21: -0.15141121 | AW21: -0.12162292 | AZ21: -0.20940376 | BD21: % of Revenue | BE21: -0.23519712 | BF21: -0.24428828 | BI21: -0.23006552 | BM21: % of Revenue | BN21: -0.3441983 | BO21: -0.30200293 | BR21: -0.36176441 | BV21: % of Revenue | BW21: =BW20/BW8 -> -0.42304435 | BX21: =BX20/BX8 -> -0.24656228 | CA21: =CA20/CA8 -> -0.28666702 | CE21: % of Revenue | CF21: =CF20/CF8 -> -0.30779282 | CG21: =CG20/CG8 -> -0.60191847 | CJ21: =CJ20/CJ8 -> -0.39955648 | CN21: % of Revenue | CO21: =CO20/CO8 -> -0.23059103 | CP21: =CP20/CP8 -> -0.29533442 | CS21: =CS20/CS8 -> -0.31373442 | CW21: % of Revenue | CX21: =CX20/CX8 -> -0.59705416 | CY21: =CY20/CY8 -> -1.4643009 | DB21: =DB20/DB8 -> -0.73842458 | DF21: % of Revenue | DG21: =DG20/DG8 -> -0.23201365 | DH21: =DH20/DH8 -> -0.23999925 | DK21: =DK20/DK8 -> -0.25375325
B22: Adjusted EBITDA | C22: 266.16781 | D22: 38.544545 | E22: 227.62326 | F22: 5.9054599 | G22: 207.22439 | H22: 58.943421 | I22: 0.28444249 | K22: Adjusted EBITDA | L22: 908.76491 | M22: 366.41347 | N22: 542.35144 | O22: 1.4801624 | P22: 706.88924 | Q22: 201.87567 | R22: 0.28558317 | T22: Adjusted EBITDA | U22: 891.2499 | V22: 964.1407 | W22: -72.8908 | X22: -0.075601829 | Y22: 1113.9672 | Z22: -222.71726 | AA22: -0.19993162 | AC22: Adjusted EBITDA | AD22: 718.93962 | AE22: 857.85151 | AF22: -138.91189 | AG22: -0.16192999 | AH22: 952.50805 | AI22: -233.56843 | AJ22: -0.24521412 | AL22: Adjusted EBITDA | AM22: 1068.4137 | AN22: 564.89395 | AO22: 503.51977 | AP22: 0.89135274 | AQ22: 790.46313 | AR22: 277.95059 | AS22: 0.35163005 | AU22: Adjusted EBITDA | AV22: 921.5948 | AW22: 1298.4036 | AX22: -376.80885 | AY22: -0.29020932 | AZ22: 961.51268 | BA22: -39.91788 | BB22: -0.041515709 | BD22: Adjusted EBITDA | BE22: 461.78105 | BF22: 662.86745 | BG22: -201.0864 | BH22: -0.30335839 | BI22: 574.93109 | BJ22: -113.15004 | BK22: -0.19680626 | BM22: Adjusted EBITDA | BN22: 244.72047 | BO22: 364.61212 | BP22: -119.89165 | BQ22: -0.32881971 | BR22: 228.78802 | BS22: 15.932451 | BT22: 0.069638486 | BV22: Adjusted EBITDA | BW22: =BW10+BW20 -> 158.1265 | BX22: =BX10+BX20 -> 369.11089 | BY22: =BW22-BX22 -> -210.98439 | BZ22: =+IF(IFERROR(BW22/BX22-1,"-")<300%,IFERROR(BW22/BX22-1,"-"),"n.a.") -> -0.57160164 | CA22: =CA10+CA20 -> 379.72623 | CB22: =BW22-CA22 -> -221.59973 | CC22: =+IF(IFERROR(BW22/CA22-1,"-")<300%,IFERROR(BW22/CA22-1,"-"),"n.a.") -> -0.58357762 | CE22: Adjusted EBITDA | CF22: =CF10+CF20 -> 329.22967 | CG22: =CG10+CG20 -> -82.58246 | CH22: =CF22-CG22 -> 411.81213 | CI22: =+IF(IFERROR(CF22/CG22-1,"-")<300%,IFERROR(CF22/CG22-1,"-"),"n.a.") -> -4.9866779 | CJ22: =CJ10+CJ20 -> 205.23905 | CK22: =CF22-CJ22 -> 123.99062 | CL22: =+IF(IFERROR(CF22/CJ22-1,"-")<300%,IFERROR(CF22/CJ22-1,"-"),"n.a.") -> 0.60412778 | CN22: Adjusted EBITDA | CO22: =CO10+CO20 -> 538.35029 | CP22: =CP10+CP20 -> 252.54065 | CQ22: =CO22-CP22 -> 285.80964 | CR22: =+IF(IFERROR(CO22/CP22-1,"-")<300%,IFERROR(CO22/CP22-1,"-"),"n.a.") -> 1.1317372 | CS22: =CS10+CS20 -> 353.19943 | CT22: =CO22-CS22 -> 185.15086 | CU22: =+IF(IFERROR(CO22/CS22-1,"-")<300%,IFERROR(CO22/CS22-1,"-"),"n.a.") -> 0.52421052 | CW22: Adjusted EBITDA | CX22: =CX10+CX20 -> 11.18297 | CY22: =CY10+CY20 -> -231.81027 | CZ22: =CX22-CY22 -> 242.99324 | DA22: =+IF(IFERROR(CX22/CY22-1,"-")<300%,IFERROR(CX22/CY22-1,"-"),"n.a.") -> -1.0482419 | DB22: =DB10+DB20 -> -54.021526 | DC22: =CX22-DB22 -> 65.204496 | DD22: =+IF(IFERROR(CX22/DB22-1,"-")<300%,IFERROR(CX22/DB22-1,"-"),"n.a.") -> -1.2070095 | DF22: Adjusted EBITDA | DG22: =DG10+DG20 -> 6424.4999 | DH22: =DH10+DH20 -> 5424.9862 | DI22: =DG22-DH22 -> 999.51367 | DJ22: =+IF(IFERROR(DG22/DH22-1,"-")<300%,IFERROR(DG22/DH22-1,"-"),"n.a.") -> 0.18424262 | DK22: =DK10+DK20 -> 6420.4269 | DL22: =DG22-DK22 -> 4.0729318 | DM22: =+IF(IFERROR(DG22/DK22-1,"-")<300%,IFERROR(DG22/DK22-1,"-"),"n.a.") -> 0.00063437087
B23: % Adj. EBITDA Margin | C23: 0.27054602 | D23: 0.061940128 | G23: 0.25719999 | K23: % Adj. EBITDA Margin | L23: 0.61802742 | M23: 0.34487886 | P23: 0.46713377 | T23: % Adj. EBITDA Margin | U23: 0.5810771 | V23: 0.53708175 | X23: 0.081915562 | Y23: 0.48386708 | AC23: % Adj. EBITDA Margin | AD23: 0.49170157 | AE23: 0.55909735 | AG23: -0.1205439 | AH23: 0.503638 | AL23: % Adj. EBITDA Margin | AM23: 0.55475213 | AN23: 0.38067806 | AP23: 0.45727373 | AQ23: 0.4828998 | AU23: % Adj. EBITDA Margin | AV23: 0.46965944 | AW23: 0.7373347 | AY23: -0.36303087 | AZ23: 0.44716184 | BD23: % Adj. EBITDA Margin | BE23: 0.35778835 | BF23: 0.50424872 | BH23: -0.29045263 | BI23: 0.42650009 | BM23: % Adj. EBITDA Margin | BN23: 0.31051754 | BO23: 0.54870399 | BQ23: -0.43408916 | BR23: 0.29480119 | BV23: % Adj. EBITDA Margin | BW23: =BW22/BW8 -> 0.25311382 | BX23: =BX22/BX8 -> 0.4383137 | BZ23: =+IF(IFERROR(BW23/BX23-1,"-")<300%,IFERROR(BW23/BX23-1,"-"),"n.a.") -> -0.42252816 | CA23: =CA22/CA8 -> 0.36989858 | CE23: % Adj. EBITDA Margin | CF23: =CF22/CF8 -> 0.36097567 | CG23: =CG22/CG8 -> -0.11804519 | CI23: =+IF(IFERROR(CF23/CG23-1,"-")<300%,IFERROR(CF23/CG23-1,"-"),"n.a.") -> -4.0579448 | CJ23: =CJ22/CJ8 -> 0.25700913 | CN23: % Adj. EBITDA Margin | CO23: =CO22/CO8 -> 0.43935422 | CP23: =CP22/CP8 -> 0.33685599 | CR23: =+IF(IFERROR(CO23/CP23-1,"-")<300%,IFERROR(CO23/CP23-1,"-"),"n.a.") -> 0.30427908 | CS23: =CS22/CS8 -> 0.34283119 | CW23: % Adj. EBITDA Margin | CX23: =CX22/CX8 -> 0.0097889511 | CY23: =CY22/CY8 -> -0.93281555 | DA23: =+IF(IFERROR(CX23/CY23-1,"-")<300%,IFERROR(CX23/CY23-1,"-"),"n.a.") -> -1.010494 | DB23: =DB22/DB8 -> -0.081857662 | DF23: % Adj. EBITDA Margin | DG23: =DG22/DG8 -> 0.42322134 | DH23: =DH22/DH8 -> 0.42455512 | DJ23: =+IF(IFERROR(DG23/DH23-1,"-")<300%,IFERROR(DG23/DH23-1,"-"),"n.a.") -> -0.003141605 | DK23: =DK22/DK8 -> 0.40281241
B25: D&A | C25: -19.13287 | D25: 0 | E25: -19.13287 | F25: n.a. | G25: -20.833333 | H25: 1.700463 | I25: -0.081622225 | K25: D&A | L25: -19.13287 | M25: 0 | N25: -19.13287 | O25: n.a. | P25: -20.833333 | Q25: 1.700463 | R25: -0.081622225 | T25: D&A | U25: -18.90355 | V25: 0 | W25: -18.90355 | X25: n.a. | Y25: -20.833333 | Z25: 1.929783 | AA25: -0.092629585 | AC25: D&A | AD25: -18.90355 | AE25: 0 | AF25: -18.90355 | AG25: n.a. | AH25: -20.833333 | AI25: 1.929783 | AJ25: -0.092629585 | AL25: D&A | AM25: -19.18968 | AN25: 0 | AO25: -19.18968 | AP25: n.a. | AQ25: -20.833333 | AR25: 1.643653 | AS25: -0.078895345 | AU25: D&A | AV25: -19.06025 | AW25: 0 | AX25: -19.06025 | AY25: n.a. | AZ25: -20.833333 | BA25: 1.773083 | BB25: -0.085107985 | BD25: D&A | BE25: -19.22529 | BF25: 0 | BG25: -19.22529 | BH25: n.a. | BI25: -20.833333 | BJ25: 1.608043 | BK25: -0.077186065 | BM25: D&A | BN25: -19.22529 | BO25: 0 | BP25: -19.22529 | BQ25: n.a. | BR25: -20.833333 | BS25: 1.608043 | BT25: -0.077186065 | BV25: D&A | BW25: =GETPIVOTDATA("sep-26 ",TABLA!$B$3,"Nivel 4","8.- Amortización del inmovilizado")/1000 -> -19.34267 | BX25: =VLOOKUP(BV25,'P&L Mensualitzada 2025'!$A$5:$N$25,$BW$3+1,0) -> 0 | BY25: =BW25-BX25 -> -19.34267 | BZ25: =+IF(IFERROR(BW25/BX25-1,"-")<300%,IFERROR(BW25/BX25-1,"-"),"n.a.") -> n.a. | CA25: =VLOOKUP(BV25,'Budget26 sin EI'!$B:$O,$BW$3+1,0) -> -20.833333 | CB25: =BW25-CA25 -> 1.490663 | CC25: =+IF(IFERROR(BW25/CA25-1,"-")<300%,IFERROR(BW25/CA25-1,"-"),"n.a.") -> -0.071551825 | CE25: D&A | CF25: =GETPIVOTDATA("oct-26 ",TABLA!$B$3,"Nivel 4","8.- Amortización del inmovilizado")/1000 -> -19.22535 | CG25: =VLOOKUP(CE25,'P&L Mensualitzada 2025'!$A$5:$N$25,$CF$3+1,0) -> -194.71201 | CH25: =CF25-CG25 -> 175.48666 | CI25: =+IF(IFERROR(CF25/CG25-1,"-")<300%,IFERROR(CF25/CG25-1,"-"),"n.a.") -> -0.90126264 | CJ25: =VLOOKUP(CE25,'Budget26 sin EI'!$B:$O,$CF$3+1,0) -> -20.833333 | CK25: =CF25-CJ25 -> 1.607983 | CL25: =+IF(IFERROR(CF25/CJ25-1,"-")<300%,IFERROR(CF25/CJ25-1,"-"),"n.a.") -> -0.077183185 | CN25: D&A | CO25: =GETPIVOTDATA("nov-26 ",TABLA!$B$3,"Nivel 4","8.- Amortización del inmovilizado")/1000 -> -19.22535 | CP25: =VLOOKUP(CN25,'P&L Mensualitzada 2025'!$A$5:$N$25,$CO$3+1,0) -> -19.4712 | CQ25: =CO25-CP25 -> 0.24585 | CR25: =+IF(IFERROR(CO25/CP25-1,"-")<300%,IFERROR(CO25/CP25-1,"-"),"n.a.") -> -0.01262634 | CS25: =VLOOKUP(CN25,'Budget26 sin EI'!$B:$O,$CO$3+1,0) -> -20.833333 | CT25: =CO25-CS25 -> 1.607983 | CU25: =+IF(IFERROR(CO25/CS25-1,"-")<300%,IFERROR(CO25/CS25-1,"-"),"n.a.") -> -0.077183185 | CW25: D&A | CX25: =GETPIVOTDATA("dic-26 ",TABLA!$B$3,"Nivel 4","8.- Amortización del inmovilizado")/1000 -> -19.22535 | CY25: =VLOOKUP(CW25,'P&L Mensualitzada 2025'!$A$5:$N$25,$CX$3+1,0) -> -34.07237 | CZ25: =CX25-CY25 -> 14.84702 | DA25: =+IF(IFERROR(CX25/CY25-1,"-")<300%,IFERROR(CX25/CY25-1,"-"),"n.a.") -> -0.43574955 | DB25: =VLOOKUP(CW25,'Budget26 sin EI'!$B:$O,$CX$3+1,0) -> -20.833333 | DC25: =CX25-DB25 -> 1.607983 | DD25: =+IF(IFERROR(CX25/DB25-1,"-")<300%,IFERROR(CX25/DB25-1,"-"),"n.a.") -> -0.077183185 | DF25: D&A | DG25: =GETPIVOTDATA("Total 2026 ",TABLA!$B$3,"Nivel 4","8.- Amortización del inmovilizado")/1000 -> -229.67475 | DH25: =VLOOKUP(DF25,'P&L Mensualitzada 2025'!$A$5:$N$25,$CX$3+2,0) -> -248.25558 | DI25: =DG25-DH25 -> 18.58083 | DJ25: =+IF(IFERROR(DG25/DH25-1,"-")<300%,IFERROR(DG25/DH25-1,"-"),"n.a.") -> -0.074845568 | DK25: =VLOOKUP(DF25,'Budget26 sin EI'!$B:$O,$CX$3+2,0) -> -250 | DL25: =DG25-DK25 -> 20.325246 | DM25: =+IF(IFERROR(DG25/DK25-1,"-")<300%,IFERROR(DG25/DK25-1,"-"),"n.a.") -> -0.081300985
B26: Other Gains/Losses | C26: 3.06527 | D26: 0.92147 | E26: 2.1438 | F26: 2.3265 | G26: 0 | H26: 3.06527 | I26: n.a. | K26: Other Gains/Losses | L26: 2e-05 | M26: 0.03183 | N26: -0.03181 | O26: -0.99937166 | P26: 0 | Q26: 2e-05 | R26: n.a. | T26: Other Gains/Losses | U26: 1.99986 | V26: -1e-05 | W26: 1.99987 | X26: n.a. | Y26: 0 | Z26: 1.99986 | AA26: n.a. | AC26: Other Gains/Losses | AD26: 1.02426 | AE26: 2e-05 | AF26: 1.02424 | AG26: n.a. | AH26: 0 | AI26: 1.02426 | AJ26: n.a. | AL26: Other Gains/Losses | AM26: 0 | AN26: 0.00031 | AO26: -0.00031 | AP26: n.a. | AQ26: 0 | AR26: 0 | AS26: n.a. | AU26: Other Gains/Losses | AV26: 0 | AW26: 0.00228 | AX26: -0.00228 | AY26: n.a. | AZ26: 0 | BA26: 0 | BB26: n.a. | BD26: Other Gains/Losses | BE26: -0.08803 | BF26: 0.00357 | BG26: -0.0916 | BH26: n.a. | BI26: 0 | BJ26: -0.08803 | BK26: n.a. | BM26: Other Gains/Losses | BN26: -0.01 | BO26: 0.47301 | BP26: -0.48301 | BQ26: n.a. | BR26: 0 | BS26: -0.01 | BT26: n.a. | BV26: Other Gains/Losses | BW26: =GETPIVOTDATA("sep-26 ",TABLA!$B$3,"Nivel 4","13.- Otros resultados")+GETPIVOTDATA("ago-26 ",TABLA!$B$3,"Nivel 4","11.- Deterioro y resultado por enajenaciones del inmovilizado")/1000 -> 0.2 | BX26: =VLOOKUP(BV26,'P&L Mensualitzada 2025'!$A$5:$N$25,$BW$3+1,0) -> -0.04064 | BY26: =BW26-BX26 -> 0.24064 | BZ26: n.a. | CA26: =VLOOKUP(BV26,'Budget26 sin EI'!$B:$O,$BW$3+1,0) -> 0 | CB26: =BW26-CA26 -> 0.2 | CC26: =+IF(IFERROR(BW26/CA26-1,"-")<300%,IFERROR(BW26/CA26-1,"-"),"n.a.") -> n.a. | CE26: Other Gains/Losses | CF26: =GETPIVOTDATA("oct-26 ",TABLA!$B$3,"Nivel 4","13.- Otros resultados")+GETPIVOTDATA("ago-26 ",TABLA!$B$3,"Nivel 4","11.- Deterioro y resultado por enajenaciones del inmovilizado")/1000 -> 0 | CG26: =VLOOKUP(CE26,'P&L Mensualitzada 2025'!$A$5:$N$25,$CF$3+1,0) -> 0.81001 | CH26: =CF26-CG26 -> -0.81001 | CI26: n.a. | CJ26: =VLOOKUP(CE26,'Budget26 sin EI'!$B:$O,$CF$3+1,0) -> 0 | CK26: =CF26-CJ26 -> 0 | CL26: =+IF(IFERROR(CF26/CJ26-1,"-")<300%,IFERROR(CF26/CJ26-1,"-"),"n.a.") -> n.a. | CN26: Other Gains/Losses | CO26: =GETPIVOTDATA("nov-26 ",TABLA!$B$3,"Nivel 4","13.- Otros resultados")+GETPIVOTDATA("ago-26 ",TABLA!$B$3,"Nivel 4","11.- Deterioro y resultado por enajenaciones del inmovilizado")/1000 -> 0 | CP26: =VLOOKUP(CN26,'P&L Mensualitzada 2025'!$A$5:$N$25,$CO$3+1,0) -> 0.00443 | CQ26: =CO26-CP26 -> -0.00443 | CR26: n.a. | CS26: =VLOOKUP(CN26,'Budget26 sin EI'!$B:$O,$CO$3+1,0) -> 0 | CT26: =CO26-CS26 -> 0 | CU26: =+IF(IFERROR(CO26/CS26-1,"-")<300%,IFERROR(CO26/CS26-1,"-"),"n.a.") -> n.a. | CW26: Other Gains/Losses | CX26: =GETPIVOTDATA("dic-26 ",TABLA!$B$3,"Nivel 4","13.- Otros resultados")+GETPIVOTDATA("ago-26 ",TABLA!$B$3,"Nivel 4","11.- Deterioro y resultado por enajenaciones del inmovilizado")/1000 -> 0 | CY26: =VLOOKUP(CW26,'P&L Mensualitzada 2025'!$A$5:$N$25,$CX$3+1,0) -> 0.15045 | CZ26: =CX26-CY26 -> -0.15045 | DA26: n.a. | DB26: =VLOOKUP(CW26,'Budget26 sin EI'!$B:$O,$CX$3+1,0) -> 0 | DC26: =CX26-DB26 -> 0 | DD26: =+IF(IFERROR(CX26/DB26-1,"-")<300%,IFERROR(CX26/DB26-1,"-"),"n.a.") -> n.a. | DF26: Other Gains/Losses | DG26: =(GETPIVOTDATA("Total 2026 ",TABLA!$B$3,"Nivel 4","13.- Otros resultados")+GETPIVOTDATA("Total 2026 ",TABLA!$B$3,"Nivel 4","11.- Deterioro y resultado por enajenaciones del inmovilizado"))/1000 -> 5.99994 | DH26: =VLOOKUP(DF26,'P&L Mensualitzada 2025'!$A$5:$N$25,$CX$3+2,0) -> 2.35673 | DI26: =DG26-DH26 -> 3.64321 | DJ26: n.a. | DK26: =VLOOKUP(DF26,'Budget26 sin EI'!$B:$O,$CX$3+2,0) -> 0 | DL26: =DG26-DK26 -> 5.99994 | DM26: =+IF(IFERROR(DG26/DK26-1,"-")<300%,IFERROR(DG26/DK26-1,"-"),"n.a.") -> n.a.
B27: Adjusted EBIT | C27: 250.10021 | D27: 39.466015 | E27: 210.63419 | F27: 5.3371032 | G27: 186.39106 | H27: 63.709154 | I27: 0.3418037 | K27: Adjusted EBIT | L27: 889.63206 | M27: 366.4453 | N27: 523.18676 | O27: 1.4277349 | P27: 686.05591 | Q27: 203.57615 | R27: 0.29673406 | T27: Adjusted EBIT | U27: 874.34621 | V27: 964.14069 | W27: -89.79448 | X27: -0.093134208 | Y27: 1093.1338 | Z27: -218.78762 | AA27: -0.20014715 | AC27: Adjusted EBIT | AD27: 701.06033 | AE27: 857.85153 | AF27: -156.7912 | AG27: -0.18277195 | AH27: 931.67471 | AI27: -230.61438 | AJ27: -0.24752672 | AL27: Adjusted EBIT | AM27: 1049.224 | AN27: 564.89426 | AO27: 484.32978 | AP27: 0.85738131 | AQ27: 769.6298 | AR27: 279.59424 | AS27: 0.36328407 | AU27: Adjusted EBIT | AV27: 902.53455 | AW27: 1298.4059 | AX27: -395.87138 | AY27: -0.3048903 | AZ27: 940.67935 | BA27: -38.144797 | BB27: -0.040550265 | BD27: Adjusted EBIT | BE27: 442.46773 | BF27: 662.87102 | BG27: -220.40329 | BH27: -0.33249801 | BI27: 554.09775 | BJ27: -111.63003 | BK27: -0.2014627 | BM27: Adjusted EBIT | BN27: 225.48518 | BO27: 365.08513 | BP27: -139.59995 | BQ27: -0.38237644 | BR27: 207.95468 | BS27: 17.530494 | BT27: 0.084299587 | BV27: Adjusted EBIT | BW27: =BW22+BW25+BW26 -> 138.98383 | BX27: =BX22+BX25+BX26 -> 369.07025 | BY27: =BW27-BX27 -> -230.08642 | BZ27: =+IF(IFERROR(BW27/BX27-1,"-")<300%,IFERROR(BW27/BX27-1,"-"),"n.a.") -> -0.62342175 | CA27: =CA22+CA25+CA26 -> 358.8929 | CB27: =BW27-CA27 -> -219.90907 | CC27: =+IF(IFERROR(BW27/CA27-1,"-")<300%,IFERROR(BW27/CA27-1,"-"),"n.a.") -> -0.61274288 | CE27: Adjusted EBIT | CF27: =CF22+CF25+CF26 -> 310.00432 | CG27: =CG22+CG25+CG26 -> -276.48446 | CH27: =CF27-CG27 -> 586.48878 | CI27: =+IF(IFERROR(CF27/CG27-1,"-")<300%,IFERROR(CF27/CG27-1,"-"),"n.a.") -> -2.121236 | CJ27: =CJ22+CJ25+CJ26 -> 184.40572 | CK27: =CF27-CJ27 -> 125.5986 | CL27: =+IF(IFERROR(CF27/CJ27-1,"-")<300%,IFERROR(CF27/CJ27-1,"-"),"n.a.") -> 0.68109925 | CN27: Adjusted EBIT | CO27: =CO22+CO25+CO26 -> 519.12494 | CP27: =CP22+CP25+CP26 -> 233.07388 | CQ27: =CO27-CP27 -> 286.05106 | CR27: =+IF(IFERROR(CO27/CP27-1,"-")<300%,IFERROR(CO27/CP27-1,"-"),"n.a.") -> 1.2272978 | CS27: =CS22+CS25+CS26 -> 332.3661 | CT27: =CO27-CS27 -> 186.75884 | CU27: =+IF(IFERROR(CO27/CS27-1,"-")<300%,IFERROR(CO27/CS27-1,"-"),"n.a.") -> 0.56190701 | CW27: Adjusted EBIT | CX27: =CX22+CX25+CX26 -> -8.04238 | CY27: =CY22+CY25+CY26 -> -265.73219 | CZ27: =CX27-CY27 -> 257.68981 | DA27: =+IF(IFERROR(CX27/CY27-1,"-")<300%,IFERROR(CX27/CY27-1,"-"),"n.a.") -> -0.96973502 | DB27: =DB22+DB25+DB26 -> -74.854859 | DC27: =CX27-DB27 -> 66.812479 | DD27: =+IF(IFERROR(CX27/DB27-1,"-")<300%,IFERROR(CX27/DB27-1,"-"),"n.a.") -> -0.89256035 | DF27: Adjusted EBIT | DG27: =DG22+DG25+DG26 -> 6200.8251 | DH27: =DH22+DH25+DH26 -> 5179.0874 | DI27: =DG27-DH27 -> 1021.7377 | DJ27: =+IF(IFERROR(DG27/DH27-1,"-")<300%,IFERROR(DG27/DH27-1,"-"),"n.a.") -> 0.19728142 | DK27: =DK22+DK25+DK26 -> 6170.4269 | DL27: =DG27-DK27 -> 30.398118 | DM27: =+IF(IFERROR(DG27/DK27-1,"-")<300%,IFERROR(DG27/DK27-1,"-"),"n.a.") -> 0.0049264205
B28: % EBIT Margin | C28: 0.25421412 | D28: 0.063420907 | G28: 0.23134235 | K28: % EBIT Margin | L28: 0.60501566 | M28: 0.34490882 | P28: 0.45336648 | T28: % EBIT Margin | U28: 0.57005623 | V28: 0.53708174 | Y28: 0.47481783 | AC28: % EBIT Margin | AD28: 0.47947346 | AE28: 0.55909736 | AH28: 0.49262239 | AL28: % EBIT Margin | AM28: 0.54478828 | AN28: 0.38067827 | AQ28: 0.47017256 | AU28: % EBIT Margin | AV28: 0.45994604 | AW28: 0.737336 | AZ28: 0.43747307 | BD28: % EBIT Margin | BE28: 0.34282437 | BF28: 0.50425143 | BI28: 0.41104533 | BM28: % EBIT Margin | BN28: 0.28611053 | BO28: 0.54941582 | BR28: 0.26795673 | BV28: % EBIT Margin | BW28: =BW27/BW8 -> 0.22247206 | BX28: =BX27/BX8 -> 0.43826544 | CA28: =CA27/CA8 -> 0.34960443 | CE28: % EBIT Margin | CF28: =CF27/CF8 -> 0.33989652 | CG28: =CG27/CG8 -> -0.39521298 | CJ28: =CJ27/CJ8 -> 0.23092074 | CN28: % EBIT Margin | CO28: =CO27/CO8 -> 0.42366417 | CP28: =CP27/CP8 -> 0.31088988 | CS28: =CS27/CS8 -> 0.32260942 | CW28: % EBIT Margin | CX28: =CX27/CX8 -> -0.007039853 | CY28: =CY27/CY8 -> -1.069319 | DB28: =DB27/DB8 -> -0.11342597 | DF28: % EBIT Margin | DG28: =DG27/DG8 -> 0.4084865 | DH28: =DH27/DH8 -> 0.40531127 | DK28: =DK27/DK8 -> 0.38712761
BM31: P&L YTD Actual
BP32: Variación | BS32: Variación
BM33: € '000 | BN33: 2026A | BO33: 2025A | BP33: EUR | BQ33: % | BR33: 2026B | BS33: EUR | BT33: %
BM34: Ventas | BN34: 11417.132 | BO34: 10238.145 | BP34: 1178.9873 | BQ34: 0.11515634 | BR34: 12423.677 | BS34: -1006.5446 | BT34: -0.081018253 | BW34: -0.036197428
BM35: COGS | BN35: -3916.0719 | BO35: -3267.7209 | BP35: -648.35101 | BQ35: 0.19841077 | BR35: -4266.7179 | BS35: 350.64599 | BT35: -0.082181668
BM36: Gross Profit | BN36: 7501.0602 | BO36: 6970.4239 | BP36: 530.63632 | BQ36: 0.076126837 | BR36: 8156.9587 | BS36: -655.89858 | BT36: -0.080409697 | CW36: =CX8*BW34 -> -41.352208
BM37: % Gross Margin | BN37: 0.65700038 | BO37: 0.6808288 | BR37: 0.6565656 | CN37: =BW34*CO8 -> -44.353496
BW38: =BW34*625 -> -22.623392 | CE38: =BW34*CF8 -> -33.014045
BM39: Gastos de Personal | BN39: -1116.9714 | BO39: -1103.0429 | BP39: -13.92855 | BQ39: 0.012627388 | BR39: -1484.9064 | BS39: 367.93496 | BT39: -0.24778327
BM40: % of Revenue | BN40: -0.097832925 | BO40: -0.10773855 | BR40: -0.1195223
BM42: Otros Ingresos Operativos | BN42: 71.32534 | BO42: 0.79288 | BP42: 70.53246 | BQ42: n.a. | BR42: 0 | BS42: 71.32534 | BT42: n.a.
BM43: Otros Gastos Operativos | BN43: -973.78181 | BO43: -750.44646 | BP43: -223.33535 | BQ43: 0.2976033 | BR43: -1135.7686 | BS43: 161.9868 | BT43: -0.14262306
BM44: Operating Expenses | BN44: -902.45647 | BO44: -749.65358 | BP44: -152.80289 | BQ44: 0.20383133 | BR44: -1135.7686 | BS44: 233.31214 | BT44: -0.20542225
BM45: % of Revenue | BN45: -0.079044059 | BO45: -0.073221623 | BR45: -0.091419685
BM46: Gastos Fijos | BN46: -2019.4279 | BO46: -1852.6965 | BP46: -166.73144 | BQ46: 0.08999393 | BR46: -2620.675 | BS46: 601.2471 | BT46: -0.22942452
BM47: % of Revenue | BN47: -0.17687698 | BO47: -0.18096017 | BR47: -0.21094198
BM48: Adjusted EBITDA | BN48: 5481.6323 | BO48: 5117.7274 | BP48: 363.90488 | BQ48: 0.071106735 | BR48: 5536.2838 | BS48: -54.651478 | BT48: -0.0098715096
BM49: % Adj. EBITDA Margin | BN49: 0.4801234 | BO49: 0.49986863 | BQ49: -0.039500838 | BR49: 0.44562362
BM51: D&A | BN51: -152.77335 | BO51: 0 | BP51: -152.77335 | BQ51: n.a. | BR51: -166.66666 | BS51: 13.893314 | BT51: -0.083359885
BM52: Other Gains/Losses | BN52: 5.99138 | BO52: 1.43248 | BP52: 4.5589 | BQ52: n.a. | BR52: 0 | BS52: 5.99138 | BT52: n.a.
BM53: Adjusted EBIT | BN53: 5334.8503 | BO53: 5119.1599 | BP53: 215.69043 | BQ53: 0.042133952 | BR53: 5369.6171 | BS53: -34.766784 | BT53: -0.0064747232
BM54: % EBIT Margin | BN54: 0.46726711 | BO54: 0.50000855 | BR54: 0.43220837

Sheet TABLA
B1: Periodo | C1: 2026
B3: Detalle sin Ajustar | C3: ene-26 | D3: feb-26 | E3: mar-26 | F3: abr-26 | G3: may-26 | H3: jun-26 | I3: jul-26 | J3: ago-26 | K3: sep-26 | L3: oct-26 | M3: nov-26 | N3: dic-26 | O3: Total 2026
B4: 1.- Importe neto de la cifra de negocios | C4: 983817.13 | D4: 1470428.1 | E4: 1533789.4 | F4: 1462146.3 | G4: 1925929.9 | H4: 1962261.8 | I4: 1290654.2 | J4: 788105.15 | K4: 624724.88 | L4: 912055.01 | M4: 1225321.8 | N4: 1142407.4 | O4: 15180000
B5: 2.- Variación de existencias | C5: -84878.08 | D5: 50005.57 | E5: 83552.77 | F5: 8645.2 | G5: -30291.1 | H5: -90104.87 | I5: -6292.63 | J5: 6734.64 | K5: -109366.49 | L5: 0 | M5: 0 | N5: 0 | O5: -62628.5
B6: 4.- Aprovisionamientos | C6: -417787.47 | D6: -406242.73 | E6: -469252.7 | F6: -514848.29 | G6: -593981.24 | H6: -653453.72 | I6: -519022.4 | J6: -278854.87 | K6: -92945.56 | L6: -302101.36 | M6: -404423.28 | N6: -449145.33 | O6: -5170904.3
B7: 6.- Gastos de personal | C7: -111532.01 | D7: -142927.2 | E7: -146233.31 | F7: -130047.67 | G7: -134992.52 | H7: -145072.28 | I7: -153533.65 | J7: -152632.79 | K7: -165803.99 | L7: -152632.79 | M7: -152632.79 | N7: -431632.79 | O7: -2006502.6
B8: 5.- Otros ingresos de explotación | C8: 0 | D8: 0 | E8: 0 | F8: 750.75 | G8: 25140.75 | H8: 22977.6 | I8: 11027.24 | J8: 11429 | K8: 9613 | L8: 21379 | M8: 32454 | N8: 27150 | O8: 168561.34
B9: 7.- Otros gastos de explotación | C9: -103451.76 | D9: -62498.88 | E9: -110606.27 | F9: -107706.65 | G9: -123392.08 | H9: -175013.76 | I9: -161051.74 | J9: -130060.66 | K9: -108095.34 | L9: -149470.19 | M9: -162369.42 | N9: -277596.29 | O9: -1684026
B10: 11.- Deterioro y resultado por enajenaciones del inmovilizado | C10: 0 | D10: 0 | E10: 2000 | F10: 0 | G10: 0 | H10: 0 | I10: 0 | J10: 0 | K10: 0 | L10: 0 | M10: 0 | N10: 0 | O10: 2000
B11: 8.- Amortización del inmovilizado | C11: -19132.87 | D11: -19132.87 | E11: -18903.55 | F11: -18903.55 | G11: -19189.68 | H11: -19060.25 | I11: -19225.29 | J11: -19225.29 | K11: -19342.67 | L11: -19225.35 | M11: -19225.35 | N11: -19225.35 | O11: -229674.75
B12: 13.- Otros resultados | C12: 3065.27 | D12: 0.02 | E12: -0.14 | F12: 1024.26 | G12: -1.43 | H12: 0 | I12: -88.03 | J12: -0.01 | K12: 0.2 | L12: 0 | M12: 0 | N12: 0 | O12: 3999.94
B13: 15.- Gastos financieros | C13: -52.82 | D13: 0 | E13: -79.37 | F13: -24483.47 | G13: -38651.64 | H13: -78497.33 | I13: -32604.18 | J13: -19768.43 | K13: -8347.1 | L13: -24579.01 | M13: -33042.67 | N13: -35674.22 | O13: -300408.35
B14: 17.- Diferencias de cambio | C14: 0 | D14: 78.79 | E14: 15.51 | F14: 0 | G14: 2879.75 | H14: 1665.7 | I14: 604.76 | J14: 0 | K14: 0 | L14: 0 | M14: 0 | N14: 0 | O14: 5244.51
B15: 14.- Ingresos financieros | C15: 0 | D15: 0 | E15: 0 | F15: 0 | G15: 0 | H15: 4495.93 | I15: 0 | J15: 0 | K15: 0 | L15: 0 | M15: 0 | N15: 0 | O15: 4495.93
B16: Total general | C16: 250047.39 | D16: 889710.85 | E16: 874282.35 | F16: 676576.86 | G16: 1013450.7 | H16: 830198.85 | I16: 410468.31 | J16: 205726.74 | K16: 130436.93 | L16: 285425.31 | M16: 486082.27 | N16: -43716.6 | O16: 5910157.2
B17: EBITDA | C17: =+SUM(C4:C9) -> 266167.81 | D17: =+SUM(D4:D9) -> 908764.91 | E17: =+SUM(E4:E9) -> 891249.9 | F17: =+SUM(F4:F9) -> 718939.62 | G17: =+SUM(G4:G9) -> 1068413.7 | H17: =+SUM(H4:H9) -> 921594.8 | I17: =+SUM(I4:I9) -> 461781.05 | J17: =+SUM(J4:J9) -> 244720.47 | ... O17: =+SUM(O4:O9) -> 6424499.9
B18: EBITDA % | C18: =C17/C4 -> 0.27054602 | D18: =D17/D4 -> 0.61802742 | E18: =E17/E4 -> 0.5810771 | F18: =F17/F4 -> 0.49170157 | G18: =G17/G4 -> 0.55475213 | H18: =H17/H4 -> 0.46965944 | I18: =I17/I4 -> 0.35778835 | J18: =J17/J4 -> 0.31051754 | ... O18: =O17/O4 -> 0.42322134
N19: Check | O19: =SUM(C16:N16)-O16 -> 98532.82

Sheet PL Mensual 2026
K2: =SUBTOTAL(9,K4:K216) -> 250047.39 | L2: =SUBTOTAL(9,L4:L216) -> 889710.85 | M2: =SUBTOTAL(9,M4:M216) -> 874282.35 | N2: =SUBTOTAL(9,N4:N216) -> 676576.86 | O2: =SUBTOTAL(9,O4:O2028) -> 1013450.7 | P2: =SUBTOTAL(9,P4:P2028) -> 830198.85 | Q2: =SUBTOTAL(9,Q4:Q2097) -> 410468.31 | R2: =SUBTOTAL(9,R4:R2016) -> 205726.74 | S2: =SUBTOTAL(9,S4:S216) -> 130436.93 | T2: =SUBTOTAL(9,T4:T216) -> 285425.31 | U2: =SUBTOTAL(9,U4:U216) -> 486082.27 | V2: =SUBTOTAL(9,V4:V216) -> -43716.6 | W2: =SUBTOTAL(9,W4:W2037) -> 6008690
B3: Periodo | C3: Empresa | D3: Nivel 1 | E3: Nivel 2 | F3: Nivel 3 | G3: Nivel 4 | H3: Nivel 5 | I3: Cuenta | J3: Grupo Ext Item | K3: 46023 | L3: 46054 | M3: 46082 | N3: 46113 | O3: 46143 | P3: 46174 | Q3: 46204 | R3: 46235 | S3: 46266 | T3: 46296 | U3: 46327 | V3: 46357 | W3: Total 2026
B4: 2026 | C4: Codiagro | D4: RESULTADO DEL EJERCICIO | E4: RESULTADO ANTES DE IMPUESTOS | F4: RESULTADO DE LA EXPLOTACION | G4: 1.- Importe neto de la cifra de negocios | H4: (700) Ventas | I4: 700000000 - Ventas de mercaderías | J4: - | K4: 993280.49 | L4: 1607538 | M4: 1536177.9 | N4: 1217250.4 | O4: 2029267 | P4: 2009948.7 | Q4: 1288443.6 | R4: 802410.56 | S4: =IFERROR(VLOOKUP(I4,'[1]PL Mensual 2026'!$I:$S,11,0),0) -> 632880.07 | T4: 910333.55 | U4: 1223802.8 | V4: 1321267.5 | W4: =SUM(K4:V4) -> 15572601 | X4: Presupuesto de Ventas 2026 ajustado para cuadrar la Cifra Neta de Negocios en 15.180.000,00 € exactos tras considerar la provisión anual de rappels (333k€) y gestión de envases. | AA4: =VLOOKUP(I4,'[2]BBDD P&L'!$J:$AK,28,0) -> 15572601 | AB4: =W4-AA4 -> 0
B5: 2026 | C5: Codiagro | D5: RESULTADO DEL EJERCICIO | E5: RESULTADO ANTES DE IMPUESTOS | F5: RESULTADO DE LA EXPLOTACION | G5: 1.- Importe neto de la cifra de negocios | H5: (700) Ventas | I5: 700000001 - VENTA MERCADERIAS POR ANTICIPO | J5: - | K5: 0 | L5: 0 | M5: 0 | N5: 106250.17 | O5: -106250.17 | P5: 0 | Q5: 0 | R5: 0 | S5: =IFERROR(VLOOKUP(I5,'[1]PL Mensual 2026'!$I:$S,11,0),0) -> 0 | T5: 0 | U5: 0 | V5: 0 | W5: =SUM(K5:V5) -> 0 | X5: Cuenta sin saldo en el ejercicio. Sin previsión de movimientos. | AA5: =VLOOKUP(I5,'[2]BBDD P&L'!$J:$AK,28,0) -> 0 | AB5: =W5-AA5 -> 0
B6: 2026 | C6: Codiagro | D6: RESULTADO DEL EJERCICIO | E6: RESULTADO ANTES DE IMPUESTOS | F6: RESULTADO DE LA EXPLOTACION | G6: 1.- Importe neto de la cifra de negocios | H6: (700) Ventas | I6: 700000624 - VENTA POR TRANSP. REP. AL CLIENTE | J6: - | K6: 17921.38 | L6: 12025.38 | M6: 8455.55 | N6: 0 | O6: 0 | P6: 0 | Q6: 0 | R6: 0 | S6: =IFERROR(VLOOKUP(I6,'[1]PL Mensual 2026'!$I:$S,11,0),0) -> - | T6: 0 | U6: 0 | V6: 0 | W6: =SUM(K6:V6) -> 38402.31 | X6: Partida puntual / no recurrente en el periodo enero-agosto. Sin movimiento adicional proyectado para el último cuatrimestre. | AA6: =VLOOKUP(I6,'[2]BBDD P&L'!$J:$AK,28,0) -> 38402.31 | AB6: =W6-AA6 -> 0
B7: 2026 | C7: Codiagro | D7: RESULTADO DEL EJERCICIO | E7: RESULTADO ANTES DE IMPUESTOS | F7: RESULTADO DE LA EXPLOTACION | G7: 5.- Otros ingresos de explotación | H7: (700) Ventas | I7: 700001624 - VENTA POR TRANSPORTE REP. AL CLIENTE DEFINITIVO | J7: - | K7: 0 | L7: 0 | M7: 0 | N7: 750.75 | O7: 25140.75 | P7: 22977.6 | Q7: 11027.24 | R7: 11429 | S7: =IFERROR(VLOOKUP(I7,'[1]PL Mensual 2026'!$I:$S,11,0),0) -> 9613 | T7: 21379 | U7: 32454 | V7: 27150 | W7: =SUM(K7:V7) -> 161921.34 | X7: Según presupuesto de transporte 2026: repercusión íntegra de fletes y transporte de exportación al cliente (efecto neto neutro con 624000002). | AA7: =VLOOKUP(I7,'[2]BBDD P&L'!$J:$AK,28,0) -> 161170.59 | AB7: =W7-AA7 -> 750.75
B8: 2026 | C8: Codiagro | D8: RESULTADO DEL EJERCICIO | E8: RESULTADO ANTES DE IMPUESTOS | F8: RESULTADO DE LA EXPLOTACION | G8: 1.- Importe neto de la cifra de negocios | H8: (700) Ventas | I8: 700000769 - INGRESOS POR RETRASOS DE COBRO Y ACTUALIZACION | J8: - | K8: 5635.79 | L8: 202.81 | M8: 178.05 | N8: 0 | O8: 0 | P8: 0 | Q8: 0 | R8: 0 | S8: =IFERROR(VLOOKUP(I8,'[1]PL Mensual 2026'!$I:$S,11,0),0) -> - | T8: 0 | U8: 0 | V8: 0 | W8: =SUM(K8:V8) -> 6016.65 | X8: Partida puntual / no recurrente en el periodo enero-agosto. Sin movimiento adicional proyectado para el último cuatrimestre. | AA8: =VLOOKUP(I8,'[2]BBDD P&L'!$J:$AK,28,0) -> 6016.65 | AB8: =W8-AA8 -> 0
B9: 2026 | C9: Codiagro | D9: RESULTADO DEL EJERCICIO | E9: RESULTADO ANTES DE IMPUESTOS | F9: RESULTADO DE LA EXPLOTACION | G9: 1.- Importe neto de la cifra de negocios | H9: (702) Ventas de productos semiterminados | I9: 702000000 - Ventas de productos semiterminados | J9: - | K9: 0 | L9: 0 | M9: 0 | N9: 51164.86 | O9: 0 | P9: 0 | Q9: 0 | R9: 0 | T9: 0 | U9: 0 | V9: 0 | W9: =SUM(K9:V9) -> 51164.86 | X9: Partida puntual / no recurrente en el periodo enero-agosto. Sin movimiento adicional proyectado para el último cuatrimestre. | AA9: =VLOOKUP(I9,'[2]BBDD P&L'!$J:$AK,28,0) -> 228488.33 | AB9: =W9-AA9 -> -177323.47
B10: 2026 | C10: Codiagro | D10: RESULTADO DEL EJERCICIO | E10: RESULTADO ANTES DE IMPUESTOS | F10: RESULTADO DE LA EXPLOTACION | G10: 1.- Importe neto de la cifra de negocios | H10: (703) Ventas por subproductos y residuos | I10: 703000000 - Ventas de subproductos y residuos | J10: - | K10: 0 | L10: 0 | M10: 26.26 | N10: 0 | O10: 0 | P10: 0 | Q10: 0 | R10: 0 | S10: =IFERROR(VLOOKUP(I10,'[1]PL Mensual 2026'!$I:$S,11,0),0) -> 2751.2 | T10: 0 | U10: 0 | V10: 0 | W10: =SUM(K10:V10) -> 2777.46 | X10: Partida puntual / no recurrente en el periodo enero-agosto. Sin movimiento adicional proyectado para el último cuatrimestre. | AA10: =VLOOKUP(I10,'[2]BBDD P&L'!$J:$AK,28,0) -> 2777.46 | AB10: =W10-AA10 -> 0
B11: 2026 | C11: Codiagro | D11: RESULTADO DEL EJERCICIO | E11: RESULTADO ANTES DE IMPUESTOS | F11: RESULTADO DE LA EXPLOTACION | G11: 1.- Importe neto de la cifra de negocios | H11: (704) Venta de envases y embalajes | I11: 704000000 - Ventas de envases y embalajes | J11: - | K11: 0 | L11: 4500 | M11: 13500 | N11: 35533.66 | O11: 0 | P11: 0 | Q11: 0 | R11: 0 | S11: =IFERROR(VLOOKUP(I11,'[1]PL Mensual 2026'!$I:$S,11,0),0)+'[1]PL Mensual 2026'!$S$220 -> 15.47 | T11: 0 | U11: 0 | V11: 0 | W11: =SUM(K11:V11) -> 53549.13 | X11: Partida puntual / no recurrente en el periodo enero-agosto. Sin movimiento adicional proyectado para el último cuatrimestre. | AA11: =VLOOKUP(I11,'[2]BBDD P&L'!$J:$AK,28,0) -> 134467.12 | AB11: =W11-AA11 -> -80917.99
B12: 2026 | C12: Codiagro | D12: RESULTADO DEL EJERCICIO | E12: RESULTADO ANTES DE IMPUESTOS | F12: RESULTADO DE LA EXPLOTACION | G12: 1.- Importe neto de la cifra de negocios | H12: (705) Prestación de servicios | I12: 705000000 - Prestaciones de servicios | J12: - | K12: 0 | L12: 0 | M12: 0 | N12: 48700.8 | O12: 0 | P12: 0 | Q12: 0 | R12: 0 | S12: 0 | T12: 0 | U12: 0 | V12: 0 | W12: =SUM(K12:V12) -> 48700.8 | X12: Partida puntual / no recurrente en el periodo enero-agosto. Sin movimiento adicional proyectado para el último cuatrimestre. | AA12: =VLOOKUP(I12,'[2]BBDD P&L'!$J:$AK,28,0) -> 213934.6 | AB12: =W12-AA12 -> -165233.8
B13: 2026 | C13: Codiagro | D13: RESULTADO DEL EJERCICIO | E13: RESULTADO ANTES DE IMPUESTOS | F13: RESULTADO DE LA EXPLOTACION | G13: 1.- Importe neto de la cifra de negocios | H13: (705) Prestación de servicios | I13: 705000001 - INGRESO POR GESTIÓN DE ENVASES | J13: - | K13: 1295.63 | L13: 6097.12 | M13: -1420.15 | N13: 3246.37 | O13: 2913.09 | P13: 2313.16 | Q13: 2210.59 | R13: 1694.59 | S13: =IFERROR(VLOOKUP(I13,'[1]PL Mensual 2026'!$I:$S,11,0),0) -> 1405.89 | T13: 1721.46 | U13: 1519.01 | V13: 5378.56 | W13: =SUM(K13:V13) -> 28375.32 | X13: Modelo de gestión de envases (Envases y transportes.xlsx): histórico 2025 ajustado por +12,35% en unidades y +4,5% en tarifas (factor 1,1685). | AA13: =VLOOKUP(I13,'[2]BBDD P&L'!$J:$AK,28,0) -> 16243.26 | AB13: =W13-AA13 -> 12132.06
B14: 2026 | C14: Codiagro | D14: RESULTADO DEL EJERCICIO | E14: RESULTADO ANTES DE IMPUESTOS | F14: RESULTADO DE LA EXPLOTACION | G14: 1.- Importe neto de la cifra de negocios | H14: (706) Dto. s/vtas p.p. | I14: 706000000 - Dtos. ventas por pronto pago mercaderías | J14: - | K14: -34316.16 | L14: -77173.86 | M14: -22849.78 | N14: 0 | O14: 0 | P14: 0 | Q14: 0 | R14: 0 | S14: =IFERROR(VLOOKUP(I14,'[1]PL Mensual 2026'!$I:$S,11,0),0) -> - | T14: 0 | U14: 0 | V14: 0 | W14: =SUM(K14:V14) -> -134339.8 | X14: Partida puntual / no recurrente en el periodo enero-agosto. Sin movimiento adicional proyectado para el último cuatrimestre. | AA14: =VLOOKUP(I14,'[2]BBDD P&L'!$J:$AK,28,0) -> -134339.8 | AB14: =W14-AA14 -> 0
B15: 2026 | C15: Codiagro | D15: RESULTADO DEL EJERCICIO | E15: RESULTADO ANTES DE IMPUESTOS | F15: RESULTADO DE LA EXPLOTACION | G15: 1.- Importe neto de la cifra de negocios | H15: (709) Bonificaciones s/ventas | I15: 709000000 - «Rappels» ventas de mercaderías | J15: - | K15: 0 | L15: 0 | M15: -278.38 | N15: 0 | O15: 0 | P15: 0 | Q15: 0 | R15: 0 | S15: =IFERROR(VLOOKUP(I15,'[1]PL Mensual 2026'!$I:$S,11,0),0) -> - | T15: 0 | U15: 0 | V15: 0 | W15: =SUM(K15:V15) -> -278.38 | X15: Partida puntual / no recurrente en el periodo enero-agosto. Sin movimiento adicional proyectado para el último cuatrimestre. | AA15: =VLOOKUP(I15,'[2]BBDD P&L'!$J:$AK,28,0) -> -278.38 | AB15: =W15-AA15 -> 0
B16: 2026 | C16: Codiagro | D16: RESULTADO DEL EJERCICIO | E16: RESULTADO ANTES DE IMPUESTOS | F16: RESULTADO DE LA EXPLOTACION | G16: 1.- Importe neto de la cifra de negocios | H16: (709) Bonificaciones s/ventas | I16: 709000001 - PROVISION RAPPELS | J16: - | K16: 0 | L16: -82761.28 | M16: 0 | N16: 0 | O16: 0 | P16: -50000 | Q16: 0 | R16: -16000 | S16: =IFERROR(VLOOKUP(I16,'[1]PL Mensual 2026'!$I:$S,11,0),0) -> -12327.75 | T16: 0 | U16: 0 | V16: -184238.72 | W16: =SUM(K16:V16) -> -345327.75 | X16: Provisión por rappels comerciales ajustada para alcanzar el objetivo anual exacto de 333.000,00 € (-148.761,28 € reales Ene-Ago + -184.238,72 € provisión Dic). | AA16: =VLOOKUP(I16,'[2]BBDD P&L'!$J:$AK,28,0) -> -345327.75 | AB16: =W16-AA16 -> 0
B17: 2026 | C17: Codiagro | D17: RESULTADO DEL EJERCICIO | E17: RESULTADO ANTES DE IMPUESTOS | F17: RESULTADO DE LA EXPLOTACION | G17: 11.- Deterioro y resultado por enajenaciones del inmovilizado | H17: (771) Beneficios procedentes IM | I17: 771000000 - Beneficios del inmovilizado material | J17: - | K17: 0 | L17: 0 | M17: 2000 | N17: 0 | O17: 0 | P17: 0 | Q17: 0 | R17: 0 | S17: =IFERROR(VLOOKUP(I17,'[1]PL Mensual 2026'!$I:$S,11,0),0) -> - | T17: 0 | U17: 0 | V17: 0 | W17: =SUM(K17:V17) -> 2000 | X17: Partida puntual / no recurrente en el periodo enero-agosto. Sin movimiento adicional proyectado para el último cuatrimestre. | AA17: =VLOOKUP(I17,'[2]BBDD P&L'!$J:$AK,28,0) -> 2000 | AB17: =W17-AA17 -> 0
B18: 2026 | C18: Codiagro | D18: RESULTADO DEL EJERCICIO | E18: RESULTADO ANTES DE IMPUESTOS | F18: RESULTADO DE LA EXPLOTACION | G18: 13.- Otros resultados | H18: (678) Gastos excepcionales PGC 2008 | I18: 678000000 - Gastos excepcionales | J18: - | K18: -0.2 | L18: 0 | M18: -0.14 | N18: -93.18 | O18: -1.43 | P18: 0 | Q18: -88.03 | R18: -0.02 | S18: =IFERROR(VLOOKUP(I18,'[1]PL Mensual 2026'!$I:$S,11,0),0) -> - | T18: 0 | U18: 0 | V18: 0 | W18: =SUM(K18:V18) -> -183 | X18: Partida puntual / no recurrente en el periodo enero-agosto. Sin movimiento adicional proyectado para el último cuatrimestre. | AA18: =VLOOKUP(I18,'[2]BBDD P&L'!$J:$AK,28,0) -> -181.57 | AB18: =W18-AA18 -> -1.43
B19: 2026 | C19: Codiagro | D19: RESULTADO DEL EJERCICIO | E19: RESULTADO ANTES DE IMPUESTOS | F19: RESULTADO DE LA EXPLOTACION | G19: 13.- Otros resultados | H19: (778) Ingresos excepcionales PGC 2008 | I19: 778000000 - Ingresos excepcionales | J19: - | K19: 3065.47 | L19: 0.02 | M19: 0 | N19: 1117.44 | O19: 0 | P19: 0 | Q19: 0 | R19: 0.01 | S19: =IFERROR(VLOOKUP(I19,'[1]PL Mensual 2026'!$I:$S,11,0),0) -> 0.2 | T19: 0 | U19: 0 | V19: 0 | W19: =SUM(K19:V19) -> 4183.14 | X19: Partida puntual / no recurrente en el periodo enero-agosto. Sin movimiento adicional proyectado para el último cuatrimestre. | AA19: =VLOOKUP(I19,'[2]BBDD P&L'!$J:$AK,28,0) -> 4183.14 | AB19: =W19-AA19 -> 0
B20: 2026 | C20: Codiagro | D20: RESULTADO DEL EJERCICIO | E20: RESULTADO ANTES DE IMPUESTOS | F20: RESULTADO DE LA EXPLOTACION | G20: 2.- Variación de existencias | H20: (711) Variación de existencias de productos semiterminados | I20: 711000000 - Variación existencias de prod. semiterminados | J20: - | K20: 1191.85 | L20: -20400.17 | M20: -3284.66 | N20: 15429.21 | O20: 4436.02 | P20: -12387.42 | Q20: -48438.2 | R20: 27557.62 | S20: =IFERROR(VLOOKUP(I20,'[1]PL Mensual 2026'!$I:$S,11,0),0) -> -30979.93 | T20: 0 | U20: 0 | V20: 0 | W20: =SUM(K20:V20) -> -66875.68 | X20: Ajuste previsional de variación de existencias para regularización de inventarios a cierre de ejercicio. | AA20: =VLOOKUP(I20,'[2]BBDD P&L'!$J:$AK,28,0) -> -64247.93 | AB20: =W20-AA20 -> -2627.75
B21: 2026 | C21: Codiagro | D21: RESULTADO DEL EJERCICIO | E21: RESULTADO ANTES DE IMPUESTOS | F21: RESULTADO DE LA EXPLOTACION | G21: 2.- Variación de existencias | H21: (712) Variación de existencias producto terminado | I21: 712000000 - Variación existencias de prod. terminados | J21: - | K21: -86069.93 | L21: 70405.74 | M21: 86837.43 | N21: -6784.01 | O21: -34727.12 | P21: -77717.45 | Q21: 42145.57 | R21: -20822.98 | S21: =IFERROR(VLOOKUP(I21,'[1]PL Mensual 2026'!$I:$S,11,0),0) -> -78386.56 | T21: 0 | U21: 0 | V21: 0 | W21: =SUM(K21:V21) -> -105119.31 | X21: Ajuste previsional de variación de existencias para regularización de inventarios a cierre de ejercicio. | AA21: =VLOOKUP(I21,'[2]BBDD P&L'!$J:$AK,28,0) -> -105119.31 | AB21: =W21-AA21 -> 0
B22: 2026 | C22: Codiagro | D22: RESULTADO DEL EJERCICIO | E22: RESULTADO ANTES DE IMPUESTOS | F22: RESULTADO DE LA EXPLOTACION | G22: 4.- Aprovisionamientos | H22: (601) Compras de materias primas | I22: 601000000 - Compras de materias primas | J22: - | K22: -372155.73 | L22: -457091.9 | M22: -457890.87 | N22: -391545.47 | O22: -423709.63 | P22: -393937.01 | Q22: -362186.44 | R22: -189242.44 | S22: =IFERROR(VLOOKUP(I22,'[1]PL Mensual 2026'!$I:$S,11,0),0) -> -91631.27 | T22: -235336.47 | U22: -316373.51 | V22: -341569.79 | W22: =SUM(K22:V22) -> -4032670.5 | X22: Coste variable directo: volumen según presupuesto ajustado (ratio histórico 25,85% s/ventas sin incremento de inflación en 2026; la inflación del +4,5% se aplica solo en 2027). | AA22: =VLOOKUP(I22,'[2]BBDD P&L'!$J:$AK,28,0) -> -3971184.7 | AB22: =W22-AA22 -> -61485.87
B23: 2026 | C23: Codiagro | D23: RESULTADO DEL EJERCICIO | E23: RESULTADO ANTES DE IMPUESTOS | F23: RESULTADO DE LA EXPLOTACION | G23: 4.- Aprovisionamientos | H23: (601) Compras de materias primas | I23: 601000001 - COMPRAS MAT. PRIMAS INTRACOMUNITARIAS | S23: =IFERROR(VLOOKUP(I23,'[1]PL Mensual 2026'!$I:$S,11,0),0) -> -108150 | W23: =SUM(K23:V23) -> -108150 | AA23: =VLOOKUP(I23,'[2]BBDD P&L'!$J:$AK,28,0) -> -499990 | AB23: =W23-AA23 -> 391840
B24: 2026 | C24: Codiagro | D24: RESULTADO DEL EJERCICIO | E24: RESULTADO ANTES DE IMPUESTOS | F24: RESULTADO DE LA EXPLOTACION | G24: 4.- Aprovisionamientos | H24: (602) Compras de otros aprovisionamientos | I24: 602000001 - COMPRA DE ENVASES Y EMBALAJES | J24: - | K24: -103817.84 | L24: -62983.5 | M24: -55812.27 | N24: -92652.34 | O24: -30193.15 | P24: -119472.15 | Q24: -145291.05 | R24: -8606.04 | S24: =IFERROR(VLOOKUP(I24,'[1]PL Mensual 2026'!$I:$S,11,0),0) -> -48494.97 | T24: -49053 | U24: -65944.18 | V24: -71196.03 | W24: =SUM(K24:V24) -> -853516.52 | X24: Coste variable por envases y embalajes: incluye saldo de junio traspasado de la 602000000 (-30.306,17 €). Estimación unificada según ratio histórico 5,39% s/ventas ajustadas (sin inflación en 2026; aplicable en 2027). | AA24: =VLOOKUP(I24,'[2]BBDD P&L'!$J:$AK,28,0) -> -1035493.8 | AB24: =W24-AA24 -> 181977.29
B25: 2026 | C25: Codiagro | D25: RESULTADO DEL EJERCICIO | E25: RESULTADO ANTES DE IMPUESTOS | F25: RESULTADO DE LA EXPLOTACION | G25: 4.- Aprovisionamientos | H25: (602) Compras de otros aprovisionamientos | I25: 602000000 - Compras de otros aprovisionamientos | J25: - | K25: 0 | L25: 0 | M25: 0 | N25: 0 | O25: 0 | P25: 0 | Q25: 0 | R25: 0 | S25: =IFERROR(VLOOKUP(I25,'[1]PL Mensual 2026'!$I:$S,11,0),0) -> 30306.17 | T25: 0 | U25: 0 | V25: 0 | W25: =SUM(K25:V25) -> 30306.17 | X25: Cuenta fusionada con 602000001. Su saldo real de junio (-30.306,17 €) se ha traspasado a la 602000001. Sin previsión en sep-dic ni en 2027. | AA25: =VLOOKUP(I25,'[2]BBDD P&L'!$J:$AK,28,0) -> 0 | AB25: =W25-AA25 -> 30306.17
B26: 2026 | C26: Codiagro | D26: RESULTADO DEL EJERCICIO | E26: RESULTADO ANTES DE IMPUESTOS | F26: RESULTADO DE LA EXPLOTACION | G26: 4.- Aprovisionamientos | H26: (602) Compras de otros aprovisionamientos | I26: 602000002 - COMPRA DE ETIQUETAS | J26: - | K26: -12617.31 | L26: -5458.67 | M26: -15267.33 | N26: -9307.32 | O26: -2784.91 | P26: -5867.49 | Q26: -10270.19 | R26: -2886.68 | S26: =IFERROR(VLOOKUP(I26,'[1]PL Mensual 2026'!$I:$S,11,0),0) -> - | T26: -4974.16 | U26: -6687 | V26: -7219.56 | W26: =SUM(K26:V26) -> -83340.62 | X26: Coste variable de etiquetas: ratio s/ventas ajustadas sin ajuste de precios de imprenta por inflación en 2026 (solo en 2027). | AA26: =VLOOKUP(I26,'[2]BBDD P&L'!$J:$AK,28,0) -> -83340.62 | AB26: =W26-AA26 -> 0
B27: 2026 | C27: Codiagro | D27: RESULTADO DEL EJERCICIO | E27: RESULTADO ANTES DE IMPUESTOS | F27: RESULTADO DE LA EXPLOTACION | G27: 4.- Aprovisionamientos | H27: (602) Compras de otros aprovisionamientos | I27: 602000003 - COMPRA DE PALETS | J27: - | K27: -7425.6 | L27: -3712.8 | M27: -4331.6 | N27: -12608.05 | O27: -17326.4 | P27: -12994.8 | Q27: -4331.6 | R27: -4331.6 | S27: =IFERROR(VLOOKUP(I27,'[1]PL Mensual 2026'!$I:$S,11,0),0) -> -1856.4 | T27: -5174.53 | U27: -6956.35 | V27: -7510.36 | W27: =SUM(K27:V27) -> -88560.09 | X27: Coste variable de palets: ratio s/ventas ajustadas sin inflación de suministros logísticos en 2026 (aplicable en 2027). | AA27: =VLOOKUP(I27,'[2]BBDD P&L'!$J:$AK,28,0) -> -88560.09 | AB27: =W27-AA27 -> 0
B28: 2026 | C28: Codiagro | D28: RESULTADO DEL EJERCICIO | E28: RESULTADO ANTES DE IMPUESTOS | F28: RESULTADO DE LA EXPLOTACION | G28: 4.- Aprovisionamientos | H28: (602) Compras de otros aprovisionamientos | I28: 602000004 - COMPRA MATERIAL DE LIMPIEZA | J28: - | K28: -131.92 | L28: 0 | M28: 0 | N28: 0 | O28: 0 | P28: 0 | Q28: 0 | R28: 0 | S28: =IFERROR(VLOOKUP(I28,'[1]PL Mensual 2026'!$I:$S,11,0),0) -> -130.42 | T28: -131.92 | U28: -131.92 | V28: -131.92 | W28: =SUM(K28:V28) -> -658.1 | X28: Coste operativo menor de planta: proyección basada en el promedio mensual histórico de reposición. | AA28: =VLOOKUP(I28,'[2]BBDD P&L'!$J:$AK,28,0) -> -658.1 | AB28: =W28-AA28 -> 0
B29: 2026 | C29: Codiagro | D29: RESULTADO DEL EJERCICIO | E29: RESULTADO ANTES DE IMPUESTOS | F29: RESULTADO DE LA EXPLOTACION | G29: 4.- Aprovisionamientos | H29: (602) Compras de otros aprovisionamientos | I29: 602000005 - COMPRA MATERIAL DE OFICINA | J29: - | K29: -95.3 | L29: -136 | M29: 0 | N29: -380.75 | O29: 0 | P29: 0 | Q29: 0 | R29: 0 | S29: =IFERROR(VLOOKUP(I29,'[1]PL Mensual 2026'!$I:$S,11,0),0) -> - | T29: -204.02 | U29: -204.02 | V29: -204.02 | W29: =SUM(K29:V29) -> -1224.11 | X29: Coste operativo menor de planta: proyección basada en el promedio mensual histórico de reposición. | AA29: =VLOOKUP(I29,'[2]BBDD P&L'!$J:$AK,28,0) -> -1224.11 | AB29: =W29-AA29 -> 0
B30: 2026 | C30: Codiagro | D30: RESULTADO DEL EJERCICIO | E30: RESULTADO ANTES DE IMPUESTOS | F30: RESULTADO DE LA EXPLOTACION | G30: 4.- Aprovisionamientos | H30: (602) Compras de otros aprovisionamientos | I30: 602000006 - COMPRA TAPONES DE ENVASES | J30: - | K30: -3578.65 | L30: 0 | M30: -5949 | N30: -5353 | O30: 0 | P30: -3337.38 | Q30: -5826.6 | R30: -1108.8 | S30: =IFERROR(VLOOKUP(I30,'[1]PL Mensual 2026'!$I:$S,11,0),0) -> - | T30: -2030.04 | U30: -2729.08 | V30: -2946.43 | W30: =SUM(K30:V30) -> -32858.98 | X30: Coste variable directamente proporcional al número de unidades/tapones envasados (0,22% s/ventas ajustadas). | AA30: =VLOOKUP(I30,'[2]BBDD P&L'!$J:$AK,28,0) -> -32858.98 | AB30: =W30-AA30 -> 0
B31: 2026 | C31: Codiagro | D31: RESULTADO DEL EJERCICIO | E31: RESULTADO ANTES DE IMPUESTOS | F31: RESULTADO DE LA EXPLOTACION | G31: 4.- Aprovisionamientos | H31: (602) Compras de otros aprovisionamientos | I31: 602000007 - COMPRAS LABORATORIO | J31: - | K31: 0 | L31: 0 | M31: 0 | N31: 0 | O31: 0 | P31: 0 | Q31: 0 | R31: 0 | S31: =IFERROR(VLOOKUP(I31,'[1]PL Mensual 2026'!$I:$S,11,0),0) -> 0 | T31: 0 | U31: 0 | V31: 0 | W31: =SUM(K31:V31) -> 0 | X31: Cuenta inactiva / sin saldo en el ejercicio. Sin previsión de movimientos. | AA31: =VLOOKUP(I31,'[2]BBDD P&L'!$J:$AK,28,0) -> 0 | AB31: =W31-AA31 -> 0
B32: 2026 | C32: Codiagro | D32: RESULTADO DEL EJERCICIO | E32: RESULTADO ANTES DE IMPUESTOS | F32: RESULTADO DE LA EXPLOTACION | G32: 4.- Aprovisionamientos | H32: (602) Compras de otros aprovisionamientos | I32: 602000008 - RESPUESTOS PLANTA | J32: - | K32: 0 | L32: 0 | M32: 0 | N32: 0 | O32: 0 | P32: 0 | Q32: 0 | R32: 0 | S32: =IFERROR(VLOOKUP(I32,'[1]PL Mensual 2026'!$I:$S,11,0),0) -> -509.99 | T32: 0 | U32: 0 | V32: 0 | W32: =SUM(K32:V32) -> -509.99 | X32: Cuenta inactiva / sin saldo en el ejercicio. Sin previsión de movimientos. | AA32: =VLOOKUP(I32,'[2]BBDD P&L'!$J:$AK,28,0) -> -509.99 | AB32: =W32-AA32 -> 0
B33: 2026 | C33: Codiagro | D33: RESULTADO DEL EJERCICIO | E33: RESULTADO ANTES DE IMPUESTOS | F33: RESULTADO DE LA EXPLOTACION | G33: 4.- Aprovisionamientos | H33: (602) Compras de otros aprovisionamientos | I33: 602000010 - COMPRA RIBBON | J33: - | K33: 0 | L33: 0 | M33: 0 | N33: 0 | O33: 0 | P33: 0 | Q33: 0 | R33: 0 | S33: =IFERROR(VLOOKUP(I33,'[1]PL Mensual 2026'!$I:$S,11,0),0) -> 0 | T33: 0 | U33: 0 | V33: 0 | W33: =SUM(K33:V33) -> 0 | X33: Cuenta inactiva / sin saldo en el ejercicio. Sin previsión de movimientos. | AA33: =VLOOKUP(I33,'[2]BBDD P&L'!$J:$AK,28,0) -> 0 | AB33: =W33-AA33 -> 0
B34: 2026 | C34: Codiagro | D34: RESULTADO DEL EJERCICIO | E34: RESULTADO ANTES DE IMPUESTOS | F34: RESULTADO DE LA EXPLOTACION | G34: 4.- Aprovisionamientos | H34: (602) Compras de otros aprovisionamientos | I34: 602000011 - COMPRAS VARIAS PLANTA | J34: - | K34: 0 | L34: -1575 | M34: 0 | N34: 0 | O34: 0 | P34: -1735.41 | Q34: -175.92 | R34: -371.23 | S34: =IFERROR(VLOOKUP(I34,'[1]PL Mensual 2026'!$I:$S,11,0),0) -> -125.1 | T34: -964.39 | U34: -964.39 | V34: -964.39 | W34: =SUM(K34:V34) -> -6875.83 | X34: Coste operativo menor de planta: proyección basada en el promedio mensual histórico de reposición. | AA34: =VLOOKUP(I34,'[2]BBDD P&L'!$J:$AK,28,0) -> -6875.83 | AB34: =W34-AA34 -> 0
B35: 2026 | C35: Codiagro | D35: RESULTADO DEL EJERCICIO | E35: RESULTADO ANTES DE IMPUESTOS | F35: RESULTADO DE LA EXPLOTACION | G35: 4.- Aprovisionamientos | H35: (602) Compras de otros aprovisionamientos | I35: 602000012 - REPUESTOS INFORMATICOS | J35: - | K35: 0 | L35: -1887.21 | M35: 0 | N35: 0 | O35: 0 | P35: 0 | Q35: -1232.05 | R35: 0 | S35: =IFERROR(VLOOKUP(I35,'[1]PL Mensual 2026'!$I:$S,11,0),0) -> - | T35: -1559.63 | U35: -1559.63 | V35: -1559.63 | W35: =SUM(K35:V35) -> -7798.15 | X35: Coste operativo menor de planta: proyección basada en el promedio mensual histórico de reposición. | AA35: =VLOOKUP(I35,'[2]BBDD P&L'!$J:$AK,28,0) -> -7798.15 | AB35: =W35-AA35 -> 0
B36: 2026 | C36: Codiagro | D36: RESULTADO DEL EJERCICIO | E36: RESULTADO ANTES DE IMPUESTOS | F36: RESULTADO DE LA EXPLOTACION | G36: 4.- Aprovisionamientos | H36: (602) Compras de otros aprovisionamientos | I36: 602000013 - COMPRA TINTA INPRESORA ETIQUETAS | J36: - | K36: -157 | L36: -2350.16 | M36: 0 | N36: -2676.19 | O36: -480.84 | P36: -2604.97 | Q36: -2809.41 | R36: -2557.66 | S36: =IFERROR(VLOOKUP(I36,'[1]PL Mensual 2026'!$I:$S,11,0),0) -> -2381.09 | T36: -2490 | U36: -2690 | V36: -2690 | W36: =SUM(K36:V36) -> -23887.32 | X36: Coste semi-variable de consumibles de marcaje y codificación en planta vinculado al volumen de producción envasado. | AA36: =VLOOKUP(I36,'[2]BBDD P&L'!$J:$AK,28,0) -> -23887.32 | AB36: =W36-AA36 -> 0
B37: 2026 | C37: Codiagro | D37: RESULTADO DEL EJERCICIO | E37: RESULTADO ANTES DE IMPUESTOS | F37: RESULTADO DE LA EXPLOTACION | G37: 4.- Aprovisionamientos | H37: (602) Compras de otros aprovisionamientos | I37: 602000100 - ENVASES Y EMBALAJES A DEVOLVER | J37: - | K37: -1200.4 | L37: -562 | M37: -363 | N37: 67 | O37: 1124 | P37: -1708 | Q37: 1360 | R37: 0 | S37: =IFERROR(VLOOKUP(I37,'[1]PL Mensual 2026'!$I:$S,11,0),0)+1188 -> 4089 | T37: -183.2 | U37: -183.2 | V37: -183.2 | W37: =SUM(K37:V37) -> 2257 | X37: Coste operativo menor de planta: proyección basada en el promedio mensual histórico de reposición. | AA37: =VLOOKUP(I37,'[2]BBDD P&L'!$J:$AK,28,0) -> 2257 | AB37: =W37-AA37 -> 0
B38: 2026 | C38: Codiagro | D38: RESULTADO DEL EJERCICIO | E38: RESULTADO ANTES DE IMPUESTOS | F38: RESULTADO DE LA EXPLOTACION | G38: 4.- Aprovisionamientos | H38: (607) Trabajos realizados por otras empresas | I38: 607000000 - Trabajos realizados por otras empresas | J38: - | K38: -4010 | L38: -8438.96 | M38: -10901.61 | N38: -20866.93 | O38: -3540 | P38: 0.72 | Q38: -3900 | R38: -6131.31 | S38: =IFERROR(VLOOKUP(I38,'[1]PL Mensual 2026'!$I:$S,11,0),0)+4717.08 -> -21488.9 | T38: 0 | U38: 0 | V38: -7970 | W38: =SUM(K38:V38) -> -87246.99 | X38: Coste variable de subcontratación fabril: eliminadas previsiones de sep a nov, dejando únicamente diciembre (-7.970,00 €) por refuerzo a cierre de ejercicio según indicación. | AA38: =VLOOKUP(I38,'[2]BBDD P&L'!$J:$AK,28,0) -> -206582.86 | AB38: =W38-AA38 -> 119335.87
B39: 2026 | C39: Codiagro | D39: RESULTADO DEL EJERCICIO | E39: RESULTADO ANTES DE IMPUESTOS | F39: RESULTADO DE LA EXPLOTACION | G39: 4.- Aprovisionamientos | H39: (611) Variación de existencias de materias primas | I39: 611000000 - Variación de existencias de materias primas | J39: - | K39: 25970.74 | L39: 149437.84 | M39: 81262.98 | N39: -23562.66 | O39: -43504.89 | P39: -145710 | Q39: 649.67 | R39: -59037.03 | S39: =IFERROR(VLOOKUP(I39,'[1]PL Mensual 2026'!$I:$S,11,0),0) -> 168480.81 | T39: 0 | U39: 0 | V39: -15000 | W39: =SUM(K39:V39) -> 138987.46 | X39: Ajuste previsional de variación de existencias para regularización de inventarios a cierre de ejercicio. | AA39: =VLOOKUP(I39,'[2]BBDD P&L'!$J:$AK,28,0) -> 138987.46 | AB39: =W39-AA39 -> 0
B40: 2026 | C40: Codiagro | D40: RESULTADO DEL EJERCICIO | E40: RESULTADO ANTES DE IMPUESTOS | F40: RESULTADO DE LA EXPLOTACION | G40: 4.- Aprovisionamientos | H40: (612) Variación de existencias envases/etiquetas | I40: 612000000 - Variación de existencias otros aprovisionamientos | J40: - | K40: 61431.54 | L40: -11484.37 | M40: 0 | N40: 44037.42 | O40: -73565.42 | P40: 33912.77 | Q40: 14991.19 | R40: -4582.08 | S40: =IFERROR(VLOOKUP(I40,'[1]PL Mensual 2026'!$I:$S,11,0),0) -> -21053.4 | T40: 0 | U40: 0 | V40: 10000 | W40: =SUM(K40:V40) -> 53687.65 | X40: Ajuste previsional de variación de existencias para regularización de inventarios a cierre de ejercicio. | AA40: =VLOOKUP(I40,'[2]BBDD P&L'!$J:$AK,28,0) -> 53687.65 | AB40: =W40-AA40 -> 0
B41: 2026 | C41: Codiagro | D41: RESULTADO DEL EJERCICIO | E41: RESULTADO ANTES DE IMPUESTOS | F41: RESULTADO DE LA EXPLOTACION | G41: 5.- Otros ingresos de explotación | H41: (759) Otros ingresos de gestión | I41: 759000000 - Ingresos por servicios diversos | J41: - | K41: 0 | L41: 0 | M41: 0 | N41: 0 | O41: 0 | P41: 0 | Q41: 0 | R41: 0 | S41: =IFERROR(VLOOKUP(I41,'[1]PL Mensual 2026'!$I:$S,11,0),0) -> 0 | T41: 0 | U41: 0 | V41: 0 | W41: =SUM(K41:V41) -> 0 | X41: Cuenta inactiva / sin saldo en el ejercicio. Sin previsión de movimientos. | AA41: =VLOOKUP(I41,'[2]BBDD P&L'!$J:$AK,28,0) -> 0 | AB41: =W41-AA41 -> 0
B42: 2026 | C42: Codiagro | D42: RESULTADO DEL EJERCICIO | E42: RESULTADO ANTES DE IMPUESTOS | F42: RESULTADO DE LA EXPLOTACION | G42: 6.- Gastos de personal | H42: (640) Sueldos y salarios | I42: 640000000 - Sueldos y salarios | J42: - | K42: -84814.92 | L42: -115852.5 | M42: -111568.08 | N42: -100687.82 | O42: -104048.18 | P42: -114103.58 | Q42: -121813.59 | R42: -128060.74 | S42: =IFERROR(VLOOKUP(I42,'[1]PL Mensual 2026'!$I:$S,11,0),0) -> -131094.27 | T42: -128060.74 | U42: -128060.74 | V42: -407060.74 | W42: =SUM(K42:V42) -> -1675225.9 | X42: Base salarial mensual fija igual a agosto (-128.060,74 €/mes) + 279.000,00 € adicionales en diciembre por devengo de Paga Extraordinaria de Navidad e incentivos anuales. | AA42: =VLOOKUP(I42,'[2]BBDD P&L'!$J:$AK,28,0) -> -1747364.7 | AB42: =W42-AA42 -> 72138.79
B43: 2026 | C43: Codiagro | D43: RESULTADO DEL EJERCICIO | E43: RESULTADO ANTES DE IMPUESTOS | F43: RESULTADO DE LA EXPLOTACION | G43: 6.- Gastos de personal | H43: (642) Seguridad social a cargo empresa | I43: 642000000 - Seguridad Social a cargo empresa | J43: - | K43: -26717.09 | L43: -27074.7 | M43: -32042.23 | N43: -29359.85 | O43: -30856.34 | P43: -30968.7 | Q43: -31720.06 | R43: -24572.05 | S43: =IFERROR(VLOOKUP(I43,'[1]PL Mensual 2026'!$I:$S,11,0),0) -> -34709.72 | T43: -24572.05 | U43: -24572.05 | V43: -24572.05 | W43: =SUM(K43:V43) -> -341736.89 | X43: Cotizaciones a la Seguridad Social mensuales fijas iguales a agosto (-24.572,05 €/mes). | AA43: =VLOOKUP(I43,'[2]BBDD P&L'!$J:$AK,28,0) -> -353869.07 | AB43: =W43-AA43 -> 12132.18
B44: 2026 | C44: Codiagro | D44: RESULTADO DEL EJERCICIO | E44: RESULTADO ANTES DE IMPUESTOS | F44: RESULTADO DE LA EXPLOTACION | G44: 6.- Gastos de personal | H44: (649) Otros gastos sociales | I44: 649000000 - Otros gastos sociales | J44: - | K44: 0 | L44: 0 | M44: 0 | N44: 0 | O44: 0 | P44: 0 | Q44: 0 | R44: 0 | S44: =IFERROR(VLOOKUP(I44,'[1]PL Mensual 2026'!$I:$S,11,0),0) -> 0 | T44: 0 | U44: 0 | V44: 0 | W44: =SUM(K44:V44) -> 0 | X44: Cuenta inactiva / sin saldo en el ejercicio. Sin previsión de movimientos. | AA44: =VLOOKUP(I44,'[2]BBDD P&L'!$J:$AK,28,0) -> 0 | AB44: =W44-AA44 -> 0
B45: 2026 | C45: Codiagro | D45: RESULTADO DEL EJERCICIO | E45: RESULTADO ANTES DE IMPUESTOS | F45: RESULTADO DE LA EXPLOTACION | G45: 6.- Gastos de personal | H45: (649) Otros gastos sociales | I45: 649000001 - GASTOS COMERCIALES NIEVES RUIZ | J45: - | K45: 0 | L45: 0 | M45: 0 | N45: 0 | O45: 0 | P45: 0 | Q45: 0 | R45: 0 | S45: =IFERROR(VLOOKUP(I45,'[1]PL Mensual 2026'!$I:$S,11,0),0) -> 0 | T45: 0 | U45: 0 | V45: 0 | W45: =SUM(K45:V45) -> 0 | X45: Cuenta inactiva / sin saldo en el ejercicio. Sin previsión de movimientos. | AA45: =VLOOKUP(I45,'[2]BBDD P&L'!$J:$AK,28,0) -> 0 | AB45: =W45-AA45 -> 0
B46: 2026 | C46: Codiagro | D46: RESULTADO DEL EJERCICIO | E46: RESULTADO ANTES DE IMPUESTOS | F46: RESULTADO DE LA EXPLOTACION | G46: 6.- Gastos de personal | H46: (649) Otros gastos sociales | I46: 649000002 - GASTOS EMPR. ANTONIO ANDREU | J46: - | K46: 0 | L46: 0 | M46: 0 | N46: 0 | O46: 0 | P46: 0 | Q46: 0 | R46: 0 | S46: =IFERROR(VLOOKUP(I46,'[1]PL Mensual 2026'!$I:$S,11,0),0) -> 0 | T46: 0 | U46: 0 | V46: 0 | W46: =SUM(K46:V46) -> 0 | X46: Cuenta inactiva / sin saldo en el ejercicio. Sin previsión de movimientos. | AA46: =VLOOKUP(I46,'[2]BBDD P&L'!$J:$AK,28,0) -> 0 | AB46: =W46-AA46 -> 0
B47: 2026 | C47: Codiagro | D47: RESULTADO DEL EJERCICIO | E47: RESULTADO ANTES DE IMPUESTOS | F47: RESULTADO DE LA EXPLOTACION | G47: 6.- Gastos de personal | H47: (649) Otros gastos sociales | I47: 649000004 - GASTOS COMERCIALES RICARDO PEREZ | J47: - | K47: 0 | L47: 0 | M47: 0 | N47: 0 | O47: 0 | P47: 0 | Q47: 0 | R47: 0 | S47: =IFERROR(VLOOKUP(I47,'[1]PL Mensual 2026'!$I:$S,11,0),0) -> 0 | T47: 0 | U47: 0 | V47: 0 | W47: =SUM(K47:V47) -> 0 | X47: Cuenta inactiva / sin saldo en el ejercicio. Sin previsión de movimientos. | AA47: =VLOOKUP(I47,'[2]BBDD P&L'!$J:$AK,28,0) -> 0 | AB47: =W47-AA47 -> 0
B48: 2026 | C48: Codiagro | D48: RESULTADO DEL EJERCICIO | E48: RESULTADO ANTES DE IMPUESTOS | F48: RESULTADO DE LA EXPLOTACION | G48: 6.- Gastos de personal | H48: (649) Otros gastos sociales | I48: 649000007 - GASTOS COMERCIALES J.PAREDES | J48: - | K48: 0 | L48: 0 | M48: 0 | N48: 0 | O48: 0 | P48: 0 | Q48: 0 | R48: 0 | S48: =IFERROR(VLOOKUP(I48,'[1]PL Mensual 2026'!$I:$S,11,0),0) -> 0 | T48: 0 | U48: 0 | V48: 0 | W48: =SUM(K48:V48) -> 0 | X48: Cuenta inactiva / sin saldo en el ejercicio. Sin previsión de movimientos. | AA48: =VLOOKUP(I48,'[2]BBDD P&L'!$J:$AK,28,0) -> 0 | AB48: =W48-AA48 -> 0
B49: 2026 | C49: Codiagro | D49: RESULTADO DEL EJERCICIO | E49: RESULTADO ANTES DE IMPUESTOS | F49: RESULTADO DE LA EXPLOTACION | G49: 6.- Gastos de personal | H49: (649) Otros gastos sociales | I49: 649000009 - GASTOS COMERCIALES J.A. GARCIA | J49: - | K49: 0 | L49: 0 | M49: 0 | N49: 0 | O49: 0 | P49: 0 | Q49: 0 | R49: 0 | S49: =IFERROR(VLOOKUP(I49,'[1]PL Mensual 2026'!$I:$S,11,0),0) -> 0 | T49: 0 | U49: 0 | V49: 0 | W49: =SUM(K49:V49) -> 0 | X49: Cuenta inactiva / sin saldo en el ejercicio. Sin previsión de movimientos. | AA49: =VLOOKUP(I49,'[2]BBDD P&L'!$J:$AK,28,0) -> 0 | AB49: =W49-AA49 -> 0
B50: 2026 | C50: Codiagro | D50: RESULTADO DEL EJERCICIO | E50: RESULTADO ANTES DE IMPUESTOS | F50: RESULTADO DE LA EXPLOTACION | G50: 6.- Gastos de personal | H50: (649) Otros gastos sociales | I50: 649000010 - GASTOS EMP. CURRO | J50: - | K50: 0 | L50: 0 | M50: 0 | N50: 0 | O50: 0 | P50: 0 | Q50: 0 | R50: 0 | S50: =IFERROR(VLOOKUP(I50,'[1]PL Mensual 2026'!$I:$S,11,0),0) -> 0 | T50: 0 | U50: 0 | V50: 0 | W50: =SUM(K50:V50) -> 0 | X50: Cuenta inactiva / sin saldo en el ejercicio. Sin previsión de movimientos. | AA50: =VLOOKUP(I50,'[2]BBDD P&L'!$J:$AK,28,0) -> 0 | AB50: =W50-AA50 -> 0
... B81: 2026 | C81: Codiagro | D81: RESULTADO DEL EJERCICIO | E81: RESULTADO ANTES DE IMPUESTOS | F81: RESULTADO DE LA EXPLOTACION | G81: 7.- Otros gastos de explotación | H81: (621) Arrendamientos y cánones | I81: 621000045 - ALQUILER RENTING 3421-NJT PERE | J81: - | K81: -634.77 | L81: -1093.22 | M81: -1093.22 | N81: -1093.22 | O81: -1208.01 | P81: -1208.01 | Q81: -1208.01 | R81: -1208.01 | S81: =IFERROR(VLOOKUP(I81,'[1]PL Mensual 2026'!$I:$S,11,0),0) -> -1208.01 | T81: -1093.31 | U81: -1093.31 | V81: -1093.31 | W81: =SUM(K81:V81) -> -13234.41 | X81: Coste fijo mensual según contratos vigentes de renting de vehículos y maquinaria auxiliar. | AA81: =VLOOKUP(I81,'[2]BBDD P&L'!$J:$AK,28,0) -> -13234.41 | AB81: =W81-AA81 -> 0
B82: 2026 | C82: Codiagro | D82: RESULTADO DEL EJERCICIO | E82: RESULTADO ANTES DE IMPUESTOS | F82: RESULTADO DE LA EXPLOTACION | G82: 7.- Otros gastos de explotación | H82: (621) Arrendamientos y cánones | I82: 621000046 - ALQUILER CARRETILLAS | J82: - | K82: 0 | L82: 0 | M82: 0 | N82: -381.67 | O82: 0 | P82: -845.33 | Q82: -742 | R82: -742 | S82: =IFERROR(VLOOKUP(I82,'[1]PL Mensual 2026'!$I:$S,11,0),0)+665 -> -742 | T82: -677.75 | U82: -677.75 | V82: -677.75 | W82: =SUM(K82:V82) -> -5486.25 | X82: Coste fijo mensual según contratos vigentes de renting de vehículos y maquinaria auxiliar. | AA82: =VLOOKUP(I82,'[2]BBDD P&L'!$J:$AK,28,0) -> -8146.25 | AB82: =W82-AA82 -> 2660
B83: 2026 | C83: Codiagro | D83: RESULTADO DEL EJERCICIO | E83: RESULTADO ANTES DE IMPUESTOS | F83: RESULTADO DE LA EXPLOTACION | G83: 7.- Otros gastos de explotación | H83: (622) Reparación/conservación/mantenimiento | I83: 622000001 - REPAR. EQUIPOS INFORM. Y FOTOCOPIADORAS | J83: - | K83: -1621.56 | L83: -815.7 | M83: -136.16 | N83: -218 | O83: 0 | P83: -790.66 | Q83: 0 | R83: 0 | S83: =IFERROR(VLOOKUP(I83,'[1]PL Mensual 2026'!$I:$S,11,0),0) -> -3275.52 | T83: -716.42 | U83: -716.42 | V83: -716.42 | W83: =SUM(K83:V83) -> -9006.86 | X83: Coste semi-variable: mantenimiento preventivo y correctivo de planta según promedio mensual histórico (sin incremento de inflación en 2026; la inflación del +4,5% se aplica solo en 2027). | AA83: =VLOOKUP(I83,'[2]BBDD P&L'!$J:$AK,28,0) -> -9006.86 | AB83: =W83-AA83 -> 0
B84: 2026 | C84: Codiagro | D84: RESULTADO DEL EJERCICIO | E84: RESULTADO ANTES DE IMPUESTOS | F84: RESULTADO DE LA EXPLOTACION | G84: 7.- Otros gastos de explotación | H84: (622) Reparación/conservación/mantenimiento | I84: 622000004 - REP. Y CONSERV. CARRETILLA ELECTRICA | J84: - | K84: 0 | L84: 0 | M84: -1006.36 | N84: 0 | O84: 0 | P84: -979.23 | Q84: 0 | R84: -115.48 | S84: =IFERROR(VLOOKUP(I84,'[1]PL Mensual 2026'!$I:$S,11,0),0) -> - | T84: -700.36 | U84: -700.36 | V84: -700.36 | W84: =SUM(K84:V84) -> -4202.15 | X84: Coste semi-variable: mantenimiento preventivo y correctivo de planta según promedio mensual histórico (sin incremento de inflación en 2026; la inflación del +4,5% se aplica solo en 2027). | AA84: =VLOOKUP(I84,'[2]BBDD P&L'!$J:$AK,28,0) -> -4202.15 | AB84: =W84-AA84 -> 0
B85: 2026 | C85: Codiagro | D85: RESULTADO DEL EJERCICIO | E85: RESULTADO ANTES DE IMPUESTOS | F85: RESULTADO DE LA EXPLOTACION | G85: 7.- Otros gastos de explotación | H85: (622) Reparación/conservación/mantenimiento | I85: 622000005 - REP. Y MANT. EQUIPOS SEGURIDAD | J85: - | K85: 0 | L85: -73.72 | M85: 0 | N85: -13.33 | O85: -183.66 | P85: 0 | Q85: -196.99 | R85: 0 | S85: =IFERROR(VLOOKUP(I85,'[1]PL Mensual 2026'!$I:$S,11,0),0) -> - | T85: -116.92 | U85: -116.92 | V85: -116.92 | W85: =SUM(K85:V85) -> -818.46 | X85: Coste semi-variable: mantenimiento preventivo y correctivo de planta según promedio mensual histórico (sin incremento de inflación en 2026; la inflación del +4,5% se aplica solo en 2027). | AA85: =VLOOKUP(I85,'[2]BBDD P&L'!$J:$AK,28,0) -> -818.46 | AB85: =W85-AA85 -> 0
B86: 2026 | C86: Codiagro | D86: RESULTADO DEL EJERCICIO | E86: RESULTADO ANTES DE IMPUESTOS | F86: RESULTADO DE LA EXPLOTACION | G86: 7.- Otros gastos de explotación | H86: (622) Reparación/conservación/mantenimiento | I86: 622000006 - REP. Y MANT. INSTALACIONES VARIAS | J86: - | K86: 0 | L86: -1833.95 | M86: -468.78 | N86: -344 | O86: 0 | P86: -1900.59 | Q86: -2274.92 | R86: 0 | S86: =IFERROR(VLOOKUP(I86,'[1]PL Mensual 2026'!$I:$S,11,0),0) -> -877.14 | T86: -3193 | U86: -1250 | V86: -525 | W86: =SUM(K86:V86) -> -12667.38 | X86: Según presupuesto de mantenimiento 2026: compresores de aire (1.693 € Sep y Oct), carretillas, caldera e inspecciones reglamentarias APQ y Antiincendios (1.500 € Oct). | AA86: =VLOOKUP(I86,'[2]BBDD P&L'!$J:$AK,28,0) -> -12667.38 | AB86: =W86-AA86 -> 0
B87: 2026 | C87: Codiagro | D87: RESULTADO DEL EJERCICIO | E87: RESULTADO ANTES DE IMPUESTOS | F87: RESULTADO DE LA EXPLOTACION | G87: 7.- Otros gastos de explotación | H87: (622) Reparación/conservación/mantenimiento | I87: 622000007 - REP. Y MANT. HYUNDAI 0377CJG | J87: - | K87: 0 | L87: 0 | M87: -238.88 | N87: 0 | O87: 0 | P87: 0 | Q87: 0 | R87: 0 | S87: =IFERROR(VLOOKUP(I87,'[1]PL Mensual 2026'!$I:$S,11,0),0) -> - | T87: -238.88 | U87: -238.88 | V87: -238.88 | W87: =SUM(K87:V87) -> -955.52 | X87: Coste semi-variable: mantenimiento preventivo y correctivo de planta según promedio mensual histórico (sin incremento de inflación en 2026; la inflación del +4,5% se aplica solo en 2027). | AA87: =VLOOKUP(I87,'[2]BBDD P&L'!$J:$AK,28,0) -> -955.52 | AB87: =W87-AA87 -> 0
B88: 2026 | C88: Codiagro | D88: RESULTADO DEL EJERCICIO | E88: RESULTADO ANTES DE IMPUESTOS | F88: RESULTADO DE LA EXPLOTACION | G88: 7.- Otros gastos de explotación | H88: (622) Reparación/conservación/mantenimiento | I88: 622000008 - REP. Y MANT. MAQUINA BARREDORA | J88: - | K88: 0 | L88: 0 | M88: 0 | N88: -350.75 | O88: 0 | P88: 0 | Q88: -634.91 | R88: 0 | S88: =IFERROR(VLOOKUP(I88,'[1]PL Mensual 2026'!$I:$S,11,0),0) -> -591.76 | T88: -492.83 | U88: -492.83 | V88: -492.83 | W88: =SUM(K88:V88) -> -3055.91 | X88: Coste semi-variable: mantenimiento preventivo y correctivo de planta según promedio mensual histórico (sin incremento de inflación en 2026; la inflación del +4,5% se aplica solo en 2027). | AA88: =VLOOKUP(I88,'[2]BBDD P&L'!$J:$AK,28,0) -> -3055.91 | AB88: =W88-AA88 -> 0
B89: 2026 | C89: Codiagro | D89: RESULTADO DEL EJERCICIO | E89: RESULTADO ANTES DE IMPUESTOS | F89: RESULTADO DE LA EXPLOTACION | G89: 7.- Otros gastos de explotación | H89: (622) Reparación/conservación/mantenimiento | I89: 622000009 - REP. Y MANT. FURGONETA 2589CRJ | J89: - | K89: 0 | L89: 0 | M89: 0 | N89: 0 | O89: 0 | P89: 0 | Q89: 0 | R89: 0 | S89: =IFERROR(VLOOKUP(I89,'[1]PL Mensual 2026'!$I:$S,11,0),0) -> 0 | T89: 0 | U89: 0 | V89: 0 | W89: =SUM(K89:V89) -> 0 | X89: Coste semi-variable: mantenimiento preventivo y correctivo de planta según promedio mensual histórico (sin incremento de inflación en 2026; la inflación del +4,5% se aplica solo en 2027). | AA89: =VLOOKUP(I89,'[2]BBDD P&L'!$J:$AK,28,0) -> 0 | AB89: =W89-AA89 -> 0
B90: 2026 | C90: Codiagro | D90: RESULTADO DEL EJERCICIO | E90: RESULTADO ANTES DE IMPUESTOS | F90: RESULTADO DE LA EXPLOTACION | G90: 7.- Otros gastos de explotación | H90: (622) Reparación/conservación/mantenimiento | I90: 622000012 - LIMPIEZA OFICINAS, LABORATORIO Y VESTUARIOS | J90: - | K90: -585 | L90: 0 | M90: -1101.6 | N90: -495 | O90: 0 | P90: -1566.9 | Q90: -642.6 | R90: -977.98 | S90: =IFERROR(VLOOKUP(I90,'[1]PL Mensual 2026'!$I:$S,11,0),0) -> -734.1 | T90: -894.85 | U90: -894.85 | V90: -894.85 | W90: =SUM(K90:V90) -> -8787.73 | X90: Coste semi-variable: mantenimiento preventivo y correctivo de planta según promedio mensual histórico (sin incremento de inflación en 2026; la inflación del +4,5% se aplica solo en 2027). | AA90: =VLOOKUP(I90,'[2]BBDD P&L'!$J:$AK,28,0) -> -8787.73 | AB90: =W90-AA90 -> 0
B91: 2026 | C91: Codiagro | D91: RESULTADO DEL EJERCICIO | E91: RESULTADO ANTES DE IMPUESTOS | F91: RESULTADO DE LA EXPLOTACION | G91: 7.- Otros gastos de explotación | H91: (622) Reparación/conservación/mantenimiento | I91: 622010000 - MANTENIMIENTO | J91: - | K91: 0 | L91: 0 | M91: 0 | N91: 0 | O91: 0 | P91: 0 | Q91: -1409.04 | R91: 0 | S91: =IFERROR(VLOOKUP(I91,'[1]PL Mensual 2026'!$I:$S,11,0),0) -> 0 | T91: -1409.04 | U91: -1409.04 | V91: -1409.04 | W91: =SUM(K91:V91) -> -5636.16 | X91: Coste semi-variable: mantenimiento preventivo y correctivo de planta según promedio mensual histórico (sin incremento de inflación en 2026; la inflación del +4,5% se aplica solo en 2027). | AA91: =VLOOKUP(I91,'[2]BBDD P&L'!$J:$AK,28,0) -> -5636.16 | AB91: =W91-AA91 -> 0
B92: 2026 | C92: Codiagro | D92: RESULTADO DEL EJERCICIO | E92: RESULTADO ANTES DE IMPUESTOS | F92: RESULTADO DE LA EXPLOTACION | G92: 7.- Otros gastos de explotación | H92: (622) Reparación/conservación/mantenimiento | I92: 622010001 - MANTENIMIENTO REPUESTO COMPRA AMAZON | J92: - | K92: 0 | L92: 0 | M92: 0 | N92: 0 | O92: 0 | P92: 0 | Q92: 0 | R92: 0 | S92: =IFERROR(VLOOKUP(I92,'[1]PL Mensual 2026'!$I:$S,11,0),0) -> 0 | T92: 0 | U92: 0 | V92: 0 | W92: =SUM(K92:V92) -> 0 | X92: Coste semi-variable: mantenimiento preventivo y correctivo de planta según promedio mensual histórico (sin incremento de inflación en 2026; la inflación del +4,5% se aplica solo en 2027). | AA92: =VLOOKUP(I92,'[2]BBDD P&L'!$J:$AK,28,0) -> 0 | AB92: =W92-AA92 -> 0
B93: 2026 | C93: Codiagro | D93: RESULTADO DEL EJERCICIO | E93: RESULTADO ANTES DE IMPUESTOS | F93: RESULTADO DE LA EXPLOTACION | G93: 7.- Otros gastos de explotación | H93: (622) Reparación/conservación/mantenimiento | I93: 622010200 - ALCAPLANT | J93: - | K93: -1342.54 | L93: -586 | M93: -2280 | N93: 0 | O93: -942.88 | P93: -354.5 | Q93: -9441.85 | R93: -1983.69 | S93: =IFERROR(VLOOKUP(I93,'[1]PL Mensual 2026'!$I:$S,11,0),0) -> -1288.62 | T93: -3000 | U93: 0 | V93: 0 | W93: =SUM(K93:V93) -> -21220.08 | X93: Según presupuesto de mantenimiento 2026: molinos Alcaplant (3.000 € en Oct) y robot paletizado (800 € en Sep). | AA93: =VLOOKUP(I93,'[2]BBDD P&L'!$J:$AK,28,0) -> -21220.08 | AB93: =W93-AA93 -> 0
B94: 2026 | C94: Codiagro | D94: RESULTADO DEL EJERCICIO | E94: RESULTADO ANTES DE IMPUESTOS | F94: RESULTADO DE LA EXPLOTACION | G94: 7.- Otros gastos de explotación | H94: (622) Reparación/conservación/mantenimiento | I94: 622010201 - REPARACIONES ALCAPLANT | J94: - | K94: -667.12 | L94: 0 | M94: 0 | N94: 0 | O94: 0 | P94: -4282.05 | Q94: -5230 | R94: -5848.16 | S94: =IFERROR(VLOOKUP(I94,'[1]PL Mensual 2026'!$I:$S,11,0),0) -> - | T94: -4006.83 | U94: -4006.83 | V94: -4006.83 | W94: =SUM(K94:V94) -> -28047.82 | X94: Coste semi-variable: mantenimiento preventivo y correctivo de planta según promedio mensual histórico (sin incremento de inflación en 2026; la inflación del +4,5% se aplica solo en 2027). | AA94: =VLOOKUP(I94,'[2]BBDD P&L'!$J:$AK,28,0) -> -28047.82 | AB94: =W94-AA94 -> 0
... B143: 2026 | C143: Codiagro | D143: RESULTADO DEL EJERCICIO | E143: RESULTADO ANTES DE IMPUESTOS | F143: RESULTADO DE LA EXPLOTACION | G143: 7.- Otros gastos de explotación | H143: (627) Publicidad | I143: 627000001 - GTOS. PUBLICIDAD EN INTERNET | J143: - | K143: 0 | L143: 0 | M143: 0 | N143: 0 | O143: 0 | P143: 0 | Q143: 0 | R143: 0 | S143: =IFERROR(VLOOKUP(I143,'[1]PL Mensual 2026'!$I:$S,11,0),0) -> -875.65 | T143: 0 | U143: 0 | V143: 0 | W143: =SUM(K143:V143) -> -875.65 | X143: Cuenta sin saldo en el ejercicio. Sin previsión de movimientos. | AA143: =VLOOKUP(I143,'[2]BBDD P&L'!$J:$AK,28,0) -> -875.65 | AB143: =W143-AA143 -> 0
B144: 2026 | C144: Codiagro | D144: RESULTADO DEL EJERCICIO | E144: RESULTADO ANTES DE IMPUESTOS | F144: RESULTADO DE LA EXPLOTACION | G144: 7.- Otros gastos de explotación | H144: (627) Publicidad | I144: 627000003 - PATROCINIOS VARIOS | S144: =IFERROR(VLOOKUP(I144,'[1]PL Mensual 2026'!$I:$S,11,0),0) -> -1700 | W144: =SUM(K144:V144) -> -1700 | AA144: =VLOOKUP(I144,'[2]BBDD P&L'!$J:$AK,28,0) -> -1700 | AB144: =W144-AA144 -> 0
B145: 2026 | C145: Codiagro | D145: RESULTADO DEL EJERCICIO | E145: RESULTADO ANTES DE IMPUESTOS | F145: RESULTADO DE LA EXPLOTACION | G145: 7.- Otros gastos de explotación | H145: (627) Publicidad | I145: 627000004 - RELACIONES PUBLICAS | J145: - | K145: 0 | L145: 0 | M145: 0 | N145: 0 | O145: 0 | P145: 0 | Q145: 0 | R145: -214.6 | S145: =IFERROR(VLOOKUP(I145,'[1]PL Mensual 2026'!$I:$S,11,0),0) -> -347.59 | T145: -321.9 | U145: -214.6 | V145: -214.6 | W145: =SUM(K145:V145) -> -1313.29 | X145: Gasto comercial y marketing: promedio mensual con refuerzo en octubre por ferias agrícolas de otoño. | AA145: =VLOOKUP(I145,'[2]BBDD P&L'!$J:$AK,28,0) -> -1313.29 | AB145: =W145-AA145 -> 0
B146: 2026 | C146: Codiagro | D146: RESULTADO DEL EJERCICIO | E146: RESULTADO ANTES DE IMPUESTOS | F146: RESULTADO DE LA EXPLOTACION | G146: 7.- Otros gastos de explotación | H146: (627) Publicidad | I146: 627000005 - INVITACIONES CLIENTES | J146: - | K146: 0 | L146: 0 | M146: 0 | N146: 0 | O146: 0 | P146: 0 | Q146: -407 | R146: 0 | S146: =IFERROR(VLOOKUP(I146,'[1]PL Mensual 2026'!$I:$S,11,0),0) -> -1261.92 | T146: -610.5 | U146: -407 | V146: -407 | W146: =SUM(K146:V146) -> -3093.42 | X146: Gasto comercial y marketing: promedio mensual con refuerzo en octubre por ferias agrícolas de otoño. | AA146: =VLOOKUP(I146,'[2]BBDD P&L'!$J:$AK,28,0) -> -3093.42 | AB146: =W146-AA146 -> 0
B147: 2026 | C147: Codiagro | D147: RESULTADO DEL EJERCICIO | E147: RESULTADO ANTES DE IMPUESTOS | F147: RESULTADO DE LA EXPLOTACION | G147: 7.- Otros gastos de explotación | H147: (627) Publicidad | I147: 627000006 - PUBLICIDAD CATALOGOS Y FOLLETOS | J147: - | K147: -27.52 | L147: 0 | M147: 0 | N147: 0 | O147: -170.36 | P147: 0 | Q147: 0 | R147: 0 | S147: =IFERROR(VLOOKUP(I147,'[1]PL Mensual 2026'!$I:$S,11,0),0) -> - | T147: -148.41 | U147: -98.94 | V147: -98.94 | W147: =SUM(K147:V147) -> -544.17 | X147: Gasto comercial y marketing: promedio mensual con refuerzo en octubre por ferias agrícolas de otoño. | AA147: =VLOOKUP(I147,'[2]BBDD P&L'!$J:$AK,28,0) -> -544.17 | AB147: =W147-AA147 -> 0
B148: 2026 | C148: Codiagro | D148: RESULTADO DEL EJERCICIO | E148: RESULTADO ANTES DE IMPUESTOS | F148: RESULTADO DE LA EXPLOTACION | G148: 7.- Otros gastos de explotación | H148: (627) Publicidad | I148: 627000007 - FERIAS | J148: - | K148: 0 | L148: 0 | M148: 0 | N148: -308.46 | O148: 0 | P148: 0 | Q148: 0 | R148: 0 | S148: =IFERROR(VLOOKUP(I148,'[1]PL Mensual 2026'!$I:$S,11,0),0) -> -559.72 | T148: -462.69 | U148: -308.46 | V148: -308.46 | W148: =SUM(K148:V148) -> -1947.79 | X148: Gasto comercial y marketing: promedio mensual con refuerzo en octubre por ferias agrícolas de otoño. | AA148: =VLOOKUP(I148,'[2]BBDD P&L'!$J:$AK,28,0) -> -1947.79 | AB148: =W148-AA148 -> 0
B149: 2026 | C149: Codiagro | D149: RESULTADO DEL EJERCICIO | E149: RESULTADO ANTES DE IMPUESTOS | F149: RESULTADO DE LA EXPLOTACION | G149: 7.- Otros gastos de explotación | H149: (627) Publicidad | I149: 627000008 - MARKETING | J149: - | K149: 0 | L149: 0 | M149: -1568.58 | N149: -4485 | O149: -55 | P149: -3000 | Q149: 0 | R149: 0 | S149: =IFERROR(VLOOKUP(I149,'[1]PL Mensual 2026'!$I:$S,11,0),0) -> -2679.5 | T149: 0 | U149: 0 | V149: 0 | W149: =SUM(K149:V149) -> -11788.08 | X149: Gastos de marketing: eliminadas las partidas de sep a dic del 2026. Para 2027 pendiente de adjuntar el plan de marketing. | AA149: =VLOOKUP(I149,'[2]BBDD P&L'!$J:$AK,28,0) -> -11788.08 | AB149: =W149-AA149 -> 0
B150: 2026 | C150: Codiagro | D150: RESULTADO DEL EJERCICIO | E150: RESULTADO ANTES DE IMPUESTOS | F150: RESULTADO DE LA EXPLOTACION | G150: 7.- Otros gastos de explotación | H150: (627) Publicidad | I150: 627000009 - ARTICULOS PUBLICIDAD | J150: - | K150: 0 | L150: 0 | M150: 0 | N150: 0 | O150: -3208.9 | P150: -438 | Q150: -9082.9 | R150: -3164.3 | S150: =IFERROR(VLOOKUP(I150,'[1]PL Mensual 2026'!$I:$S,11,0),0) -> - | T150: -4500 | U150: -2000 | V150: -2000 | W150: =SUM(K150:V150) -> -24394.1 | X150: Gasto comercial estratégico con estacionalidad: refuerzo en octubre por ferias agrícolas (Fruit Attraction) y catálogos. | AA150: =VLOOKUP(I150,'[2]BBDD P&L'!$J:$AK,28,0) -> -24394.1 | AB150: =W150-AA150 -> 0
B151: 2026 | C151: Codiagro | D151: RESULTADO DEL EJERCICIO | E151: RESULTADO ANTES DE IMPUESTOS | F151: RESULTADO DE LA EXPLOTACION | G151: 7.- Otros gastos de explotación | H151: (627) Publicidad | I151: 627000010 - RELACIONES PUBLICAS TEC. CLIENTES | J151: - | K151: 0 | L151: 0 | M151: -826.76 | N151: 0 | O151: 0 | P151: 0 | Q151: 0 | R151: 0 | S151: =IFERROR(VLOOKUP(I151,'[1]PL Mensual 2026'!$I:$S,11,0),0) -> - | T151: -1240.14 | U151: -826.76 | V151: -826.76 | W151: =SUM(K151:V151) -> -3720.42 | X151: Gasto comercial y marketing: promedio mensual con refuerzo en octubre por ferias agrícolas de otoño. | AA151: =VLOOKUP(I151,'[2]BBDD P&L'!$J:$AK,28,0) -> -3720.42 | AB151: =W151-AA151 -> 0
B152: 2026 | C152: Codiagro | D152: RESULTADO DEL EJERCICIO | E152: RESULTADO ANTES DE IMPUESTOS | F152: RESULTADO DE LA EXPLOTACION | G152: 7.- Otros gastos de explotación | H152: (628) Suministros | I152: 628000001 - SUMINISTROS INFORMATICOS | J152: - | K152: 0 | L152: 0 | M152: 0 | N152: 0 | O152: 0 | P152: -489 | Q152: 0 | R152: 0 | S152: =IFERROR(VLOOKUP(I152,'[1]PL Mensual 2026'!$I:$S,11,0),0) -> - | T152: -489 | U152: -489 | V152: -489 | W152: =SUM(K152:V152) -> -1956 | X152: Proyección basada en el promedio mensual histórico de actividad. | AA152: =VLOOKUP(I152,'[2]BBDD P&L'!$J:$AK,28,0) -> -1956 | AB152: =W152-AA152 -> 0
B153: 2026 | C153: Codiagro | D153: RESULTADO DEL EJERCICIO | E153: RESULTADO ANTES DE IMPUESTOS | F153: RESULTADO DE LA EXPLOTACION | G153: 7.- Otros gastos de explotación | H153: (628) Suministros | I153: 628000002 - SUMINISTROS ELECTRICIDAD | J153: - | K153: -4457.07 | L153: -4192.18 | M153: 0 | N153: -8417.9 | O153: -1115.2 | P153: -7205.31 | Q153: -3014.4754 | R153: -1350.4331 | S153: =IFERROR(VLOOKUP(I153,'[1]PL Mensual 2026'!$I:$S,11,0),0)+77.3 -> -1947.15 | T153: -3790 | U153: -4190 | V153: -4390 | W153: =SUM(K153:V153) -> -44069.719 | X153: Coste semi-variable: término fijo de potencia contratada + consumo eléctrico de reactores y envasado proporcional a la producción. | AA153: =VLOOKUP(I153,'[2]BBDD P&L'!$J:$AK,28,0) -> -50086.17 | AB153: =W153-AA153 -> 6016.4514
B154: 2026 | C154: Codiagro | D154: RESULTADO DEL EJERCICIO | E154: RESULTADO ANTES DE IMPUESTOS | F154: RESULTADO DE LA EXPLOTACION | G154: 7.- Otros gastos de explotación | H154: (628) Suministros | I154: 628000003 - SUMINISTROS AGUA | J154: - | K154: -1170.76 | L154: 0 | M154: 0 | N154: -1209.46 | O154: 0 | P154: 0 | Q154: -1927.6 | R154: 0 | S154: =IFERROR(VLOOKUP(I154,'[1]PL Mensual 2026'!$I:$S,11,0),0) -> - | T154: -1435.94 | U154: -1435.94 | V154: -1435.94 | W154: =SUM(K154:V154) -> -8615.64 | X154: Proyección basada en el promedio mensual histórico de actividad. | AA154: =VLOOKUP(I154,'[2]BBDD P&L'!$J:$AK,28,0) -> -8615.64 | AB154: =W154-AA154 -> 0
B155: 2026 | C155: Codiagro | D155: RESULTADO DEL EJERCICIO | E155: RESULTADO ANTES DE IMPUESTOS | F155: RESULTADO DE LA EXPLOTACION | G155: 7.- Otros gastos de explotación | H155: (628) Suministros | I155: 628000004 - SUMINISTROS TELEFONIA E INTERNET | J155: - | K155: -697.53 | L155: -707.86 | M155: -721.07 | N155: -752.94 | O155: -259.61 | P155: -1232.48 | Q155: -761.55 | R155: -853 | S155: =IFERROR(VLOOKUP(I155,'[1]PL Mensual 2026'!$I:$S,11,0),0) -> -464.2 | T155: -400 | U155: -700 | V155: -900 | W155: =SUM(K155:V155) -> -8450.24 | X155: Coste semi-variable estacional: climatización de instalaciones y caldera durante meses fríos. | AA155: =VLOOKUP(I155,'[2]BBDD P&L'!$J:$AK,28,0) -> -8450.24 | AB155: =W155-AA155 -> 0
B156: 2026 | C156: Codiagro | D156: RESULTADO DEL EJERCICIO | E156: RESULTADO ANTES DE IMPUESTOS | F156: RESULTADO DE LA EXPLOTACION | G156: 7.- Otros gastos de explotación | H156: (628) Suministros | I156: 628000005 - SUMINISTROS GASOLEO | J156: - | K156: 0 | L156: 0 | M156: 0 | N156: 0 | O156: -1891.22 | P156: 0 | Q156: 0 | R156: -1496.33 | S156: =IFERROR(VLOOKUP(I156,'[1]PL Mensual 2026'!$I:$S,11,0),0) -> - | T156: -1693.78 | U156: -1693.78 | V156: -1693.78 | W156: =SUM(K156:V156) -> -8468.89 | X156: Proyección basada en el promedio mensual histórico de actividad. | AA156: =VLOOKUP(I156,'[2]BBDD P&L'!$J:$AK,28,0) -> -8468.89 | AB156: =W156-AA156 -> 0
B157: 2026 | C157: Codiagro | D157: RESULTADO DEL EJERCICIO | E157: RESULTADO ANTES DE IMPUESTOS | F157: RESULTADO DE LA EXPLOTACION | G157: 7.- Otros gastos de explotación | H157: (629) Otros servicios | I157: 629000001 - HOSPEDAJE WEB | J157: - | K157: -396 | L157: 0 | M157: 0 | N157: 0 | O157: 0 | P157: -30 | Q157: 0 | R157: 0 | S157: =IFERROR(VLOOKUP(I157,'[1]PL Mensual 2026'!$I:$S,11,0),0) -> - | T157: -213 | U157: -213 | V157: -213 | W157: =SUM(K157:V157) -> -1065 | X157: Coste operativo general de estructura y servicios de oficinas/fábrica (promedio histórico). | AA157: =VLOOKUP(I157,'[2]BBDD P&L'!$J:$AK,28,0) -> -1065 | AB157: =W157-AA157 -> 0
B158: 2026 | C158: Codiagro | D158: RESULTADO DEL EJERCICIO | E158: RESULTADO ANTES DE IMPUESTOS | F158: RESULTADO DE LA EXPLOTACION | G158: 7.- Otros gastos de explotación | H158: (629) Otros servicios | I158: 629000002 - OTROS GASTOS | J158: - | K158: -194.68 | L158: -108 | M158: -1186.24 | N158: -80.59 | O158: -277.84 | P158: -254.03 | Q158: -4498.18 | R158: -986.98 | S158: =IFERROR(VLOOKUP(I158,'[1]PL Mensual 2026'!$I:$S,11,0),0) -> -1007.61 | T158: 0 | U158: -1940 | V158: -976 | W158: =SUM(K158:V158) -> -11510.15 | X158: Según presupuesto de regulatory 2026: declaración 3T (1.940 €) y regularización anual (976 €) SCRAP envases agrarios AEVAE. | AA158: =VLOOKUP(I158,'[2]BBDD P&L'!$J:$AK,28,0) -> -11510.15 | AB158: =W158-AA158 -> 0
B159: 2026 | C159: Codiagro | D159: RESULTADO DEL EJERCICIO | E159: RESULTADO ANTES DE IMPUESTOS | F159: RESULTADO DE LA EXPLOTACION | G159: 7.- Otros gastos de explotación | H159: (629) Otros servicios | I159: 629000003 - SUSCRIPCIONES A REVISTAS Y PERIODICOS | J159: - | K159: -460.58 | L159: 0 | M159: 0 | N159: 0 | O159: 0 | P159: 0 | Q159: 0 | R159: 0 | S159: =IFERROR(VLOOKUP(I159,'[1]PL Mensual 2026'!$I:$S,11,0),0) -> - | T159: -460.58 | U159: -460.58 | V159: -460.58 | W159: =SUM(K159:V159) -> -1842.32 | X159: Coste operativo general de estructura y servicios de oficinas/fábrica (promedio histórico). | AA159: =VLOOKUP(I159,'[2]BBDD P&L'!$J:$AK,28,0) -> -1842.32 | AB159: =W159-AA159 -> 0
B160: 2026 | C160: Codiagro | D160: RESULTADO DEL EJERCICIO | E160: RESULTADO ANTES DE IMPUESTOS | F160: RESULTADO DE LA EXPLOTACION | G160: 7.- Otros gastos de explotación | H160: (629) Otros servicios | I160: 629000004 - GTOS. SERV. VIGILANCIA | J160: - | K160: -73.72 | L160: 0 | M160: -73.72 | N160: -73.72 | O160: -75.94 | P160: -75.94 | Q160: -75.94 | R160: -75.94 | S160: =IFERROR(VLOOKUP(I160,'[1]PL Mensual 2026'!$I:$S,11,0),0) -> -75.94 | T160: -74.99 | U160: -74.99 | V160: -74.99 | W160: =SUM(K160:V160) -> -825.83 | X160: Coste operativo general de estructura y servicios de oficinas/fábrica (promedio histórico). | AA160: =VLOOKUP(I160,'[2]BBDD P&L'!$J:$AK,28,0) -> -825.83 | AB160: =W160-AA160 -> 0
B161: 2026 | C161: Codiagro | D161: RESULTADO DEL EJERCICIO | E161: RESULTADO ANTES DE IMPUESTOS | F161: RESULTADO DE LA EXPLOTACION | G161: 7.- Otros gastos de explotación | H161: (629) Otros servicios | I161: 629000005 - GTOS. ANALISIS LABORATORIOS | J161: - | K161: -87.98 | L161: 0 | M161: 0 | N161: -2772 | O161: 36.18 | P161: 0 | Q161: 0 | R161: 0 | S161: =IFERROR(VLOOKUP(I161,'[1]PL Mensual 2026'!$I:$S,11,0),0) -> - | T161: -941.27 | U161: -941.27 | V161: -941.27 | W161: =SUM(K161:V161) -> -5647.61 | X161: Coste operativo general de estructura y servicios de oficinas/fábrica (promedio histórico). | AA161: =VLOOKUP(I161,'[2]BBDD P&L'!$J:$AK,28,0) -> -5647.61 | AB161: =W161-AA161 -> 0
B162: 2026 | C162: Codiagro | D162: RESULTADO DEL EJERCICIO | E162: RESULTADO ANTES DE IMPUESTOS | F162: RESULTADO DE LA EXPLOTACION | G162: 7.- Otros gastos de explotación | H162: (629) Otros servicios | I162: 629000006 - GASTOS CORREOS | J162: - | K162: -48 | L162: 0 | M162: 0 | N162: 0 | O162: -144 | P162: 0 | Q162: 0 | R162: 0 | S162: =IFERROR(VLOOKUP(I162,'[1]PL Mensual 2026'!$I:$S,11,0),0) -> - | T162: -96 | U162: -96 | V162: -96 | W162: =SUM(K162:V162) -> -480 | X162: Coste operativo general de estructura y servicios de oficinas/fábrica (promedio histórico). | AA162: =VLOOKUP(I162,'[2]BBDD P&L'!$J:$AK,28,0) -> -480 | AB162: =W162-AA162 -> 0
B163: 2026 | C163: Codiagro | D163: RESULTADO DEL EJERCICIO | E163: RESULTADO ANTES DE IMPUESTOS | F163: RESULTADO DE LA EXPLOTACION | G163: 7.- Otros gastos de explotación | H163: (629) Otros servicios | I163: 629000007 - GASTOS RETIRADA DE RESIDUOS | J163: - | K163: -7569.69 | L163: 1670.07 | M163: -1388.15 | N163: -1276.52 | O163: -545.45 | P163: -1758.33 | Q163: -11469.319 | R163: 667.67211 | S163: =IFERROR(VLOOKUP(I163,'[1]PL Mensual 2026'!$I:$S,11,0),0)+233.86 -> -5890.87 | T163: -4500 | U163: -4500 | V163: -4500 | W163: =SUM(K163:V163) -> -41060.587 | X163: Según presupuesto de regulatory 2026: retirada y gestión de residuos industriales (4.500 €/mes en Oct, Nov, Dic). | AA163: =VLOOKUP(I163,'[2]BBDD P&L'!$J:$AK,28,0) -> -42741.53 | AB163: =W163-AA163 -> 1680.9433
B164: 2026 | C164: Codiagro | D164: RESULTADO DEL EJERCICIO | E164: RESULTADO ANTES DE IMPUESTOS | F164: RESULTADO DE LA EXPLOTACION | G164: 7.- Otros gastos de explotación | H164: (629) Otros servicios | I164: 629000008 - CUOTAS ASOCIACIONES | J164: - | K164: -1148.29 | L164: 0 | M164: -600 | N164: -945 | O164: 0 | P164: 0 | Q164: -514 | R164: 0 | S164: =IFERROR(VLOOKUP(I164,'[1]PL Mensual 2026'!$I:$S,11,0),0) -> - | T164: -801.82 | U164: -801.82 | V164: -801.82 | W164: =SUM(K164:V164) -> -5612.75 | X164: Coste operativo general de estructura y servicios de oficinas/fábrica (promedio histórico). | AA164: =VLOOKUP(I164,'[2]BBDD P&L'!$J:$AK,28,0) -> -5612.75 | AB164: =W164-AA164 -> 0
B165: 2026 | C165: Codiagro | D165: RESULTADO DEL EJERCICIO | E165: RESULTADO ANTES DE IMPUESTOS | F165: RESULTADO DE LA EXPLOTACION | G165: 7.- Otros gastos de explotación | H165: (629) Otros servicios | I165: 629000009 - SANCIONES Y MULTAS | J165: - | K165: 0 | L165: 0 | M165: 0 | N165: 0 | O165: 0 | P165: 0 | Q165: -90 | R165: 0 | S165: =IFERROR(VLOOKUP(I165,'[1]PL Mensual 2026'!$I:$S,11,0),0) -> -130 | T165: -90 | U165: -90 | V165: -90 | W165: =SUM(K165:V165) -> -490 | X165: Coste operativo general de estructura y servicios de oficinas/fábrica (promedio histórico). | AA165: =VLOOKUP(I165,'[2]BBDD P&L'!$J:$AK,28,0) -> -490 | AB165: =W165-AA165 -> 0
B166: 2026 | C166: Codiagro | D166: RESULTADO DEL EJERCICIO | E166: RESULTADO ANTES DE IMPUESTOS | F166: RESULTADO DE LA EXPLOTACION | G166: 7.- Otros gastos de explotación | H166: (629) Otros servicios | I166: 629000010 - GASTOS COMERCIALES | J166: - | K166: -1233.23 | L166: 0 | M166: 29.06 | N166: 46.51 | O166: 29.06 | P166: 0 | Q166: -2125.27 | R166: -1663.31 | S166: =IFERROR(VLOOKUP(I166,'[1]PL Mensual 2026'!$I:$S,11,0),0) -> -3215.9 | T166: -819.53 | U166: -819.53 | V166: -819.53 | W166: =SUM(K166:V166) -> -10591.67 | X166: Coste operativo general de estructura y servicios de oficinas/fábrica (promedio histórico). | AA166: =VLOOKUP(I166,'[2]BBDD P&L'!$J:$AK,28,0) -> -10591.67 | AB166: =W166-AA166 -> 0
B167: 2026 | C167: Codiagro | D167: RESULTADO DEL EJERCICIO | E167: RESULTADO ANTES DE IMPUESTOS | F167: RESULTADO DE LA EXPLOTACION | G167: 7.- Otros gastos de explotación | H167: (629) Otros servicios | I167: 629000011 - EPIS PERSONAL | J167: - | K167: -425 | L167: 0 | M167: 0 | N167: -35.25 | O167: -425 | P167: 0 | Q167: 0 | R167: 0 | S167: =IFERROR(VLOOKUP(I167,'[1]PL Mensual 2026'!$I:$S,11,0),0) -> -1958.39 | T167: -295.08 | U167: -295.08 | V167: -295.08 | W167: =SUM(K167:V167) -> -3728.88 | X167: Coste operativo general de estructura y servicios de oficinas/fábrica (promedio histórico). | AA167: =VLOOKUP(I167,'[2]BBDD P&L'!$J:$AK,28,0) -> -3728.88 | AB167: =W167-AA167 -> 0
B168: 2026 | C168: Codiagro | D168: RESULTADO DEL EJERCICIO | E168: RESULTADO ANTES DE IMPUESTOS | F168: RESULTADO DE LA EXPLOTACION | G168: 7.- Otros gastos de explotación | H168: (629) Otros servicios | I168: 629000012 - GASTOS VARIOS PERSONAL | J168: - | K168: -808.04 | L168: -2163.44 | M168: -2173.63 | N168: -237.86 | O168: -2671.84 | P168: -503.74 | Q168: -1117.86 | R168: -932.8 | S168: =IFERROR(VLOOKUP(I168,'[1]PL Mensual 2026'!$I:$S,11,0),0) -> -619.43 | T168: -1326.15 | U168: -1326.15 | V168: -1326.15 | W168: =SUM(K168:V168) -> -15207.09 | X168: Coste operativo general de estructura y servicios de oficinas/fábrica (promedio histórico). | AA168: =VLOOKUP(I168,'[2]BBDD P&L'!$J:$AK,28,0) -> -15207.09 | AB168: =W168-AA168 -> 0
B169: 2026 | C169: Codiagro | D169: RESULTADO DEL EJERCICIO | E169: RESULTADO ANTES DE IMPUESTOS | F169: RESULTADO DE LA EXPLOTACION | G169: 7.- Otros gastos de explotación | H169: (629) Otros servicios | I169: 629000013 - FORMACION NO BONIFICADA | J169: - | K169: 0 | L169: 0 | M169: -400 | N169: 0 | O169: -625.2 | P169: 0 | Q169: 0 | R169: -4513.8 | S169: =IFERROR(VLOOKUP(I169,'[1]PL Mensual 2026'!$I:$S,11,0),0) -> - | T169: -1846.33 | U169: -1846.33 | V169: -1846.33 | W169: =SUM(K169:V169) -> -11077.99 | X169: Coste operativo general de estructura y servicios de oficinas/fábrica (promedio histórico). | AA169: =VLOOKUP(I169,'[2]BBDD P&L'!$J:$AK,28,0) -> -11077.99 | AB169: =W169-AA169 -> 0
B170: 2026 | C170: Codiagro | D170: RESULTADO DEL EJERCICIO | E170: RESULTADO ANTES DE IMPUESTOS | F170: RESULTADO DE LA EXPLOTACION | G170: 7.- Otros gastos de explotación | H170: (629) Otros servicios | I170: 629000014 - ROPA LABORAL | J170: - | K170: 0 | L170: -351.4 | M170: 0 | N170: 0 | O170: 0 | P170: 0 | Q170: -98.8 | R170: -340 | S170: =IFERROR(VLOOKUP(I170,'[1]PL Mensual 2026'!$I:$S,11,0),0) -> -277.03 | T170: -263.4 | U170: -263.4 | V170: -263.4 | W170: =SUM(K170:V170) -> -1857.43 | X170: Coste operativo general de estructura y servicios de oficinas/fábrica (promedio histórico). | AA170: =VLOOKUP(I170,'[2]BBDD P&L'!$J:$AK,28,0) -> -1857.43 | AB170: =W170-AA170 -> 0
B171: 2026 | C171: Codiagro | D171: RESULTADO DEL EJERCICIO | E171: RESULTADO ANTES DE IMPUESTOS | F171: RESULTADO DE LA EXPLOTACION | G171: 7.- Otros gastos de explotación | H171: (629) Otros servicios | I171: 629000015 MATERIAL DE OFICINA | J171: - | K171: 0 | L171: 0 | M171: 0 | N171: 0 | O171: 0 | P171: 0 | Q171: -206.45 | R171: -107.24 | S171: =IFERROR(VLOOKUP(I171,'[1]PL Mensual 2026'!$I:$S,11,0),0) -> -40.88 | T171: -156.84 | U171: -156.84 | V171: -156.84 | W171: =SUM(K171:V171) -> -825.09 | X171: Coste operativo general de estructura y servicios de oficinas/fábrica (promedio histórico). | AA171: =VLOOKUP(I171,'[2]BBDD P&L'!$J:$AK,28,0) -> -825.09 | AB171: =W171-AA171 -> 0
B172: 2026 | C172: Codiagro | D172: RESULTADO DEL EJERCICIO | E172: RESULTADO ANTES DE IMPUESTOS | F172: RESULTADO DE LA EXPLOTACION | G172: 7.- Otros gastos de explotación | H172: (629) Otros servicios | I172: 629000016 HERRAMIENTAS | J172: - | K172: 0 | L172: 0 | M172: 0 | N172: 0 | O172: 0 | P172: 0 | Q172: 0 | R172: -500.03 | S172: =IFERROR(VLOOKUP(I172,'[1]PL Mensual 2026'!$I:$S,11,0),0) -> - | T172: -500.03 | U172: -500.03 | V172: -500.03 | W172: =SUM(K172:V172) -> -2000.12 | X172: Coste operativo general de estructura y servicios de oficinas/fábrica (promedio histórico). | AA172: =VLOOKUP(I172,'[2]BBDD P&L'!$J:$AK,28,0) -> -2000.12 | AB172: =W172-AA172 -> 0
B173: 2026 | C173: Codiagro | D173: RESULTADO DEL EJERCICIO | E173: RESULTADO ANTES DE IMPUESTOS | F173: RESULTADO DE LA EXPLOTACION | G173: 7.- Otros gastos de explotación | H173: (629) Otros servicios | I173: 629100001 - GASTOS COMERCIALES PERE PORTA | J173: - | K173: -1325.34 | L173: -2819.19 | M173: -1737.88 | N173: -1506.87 | O173: -2533.93 | P173: -5047.35 | Q173: -6591.35 | R173: -2380.04 | S173: =IFERROR(VLOOKUP(I173,'[1]PL Mensual 2026'!$I:$S,11,0),0) -> -2431.82 | T173: -3200 | U173: -3200 | V173: -3500 | W173: =SUM(K173:V173) -> -36273.77 | X173: Gastos comerciales de viaje, kilometraje y dietas vinculados a visitas y prospección de clientes. | AA173: =VLOOKUP(I173,'[2]BBDD P&L'!$J:$AK,28,0) -> -36273.77 | AB173: =W173-AA173 -> 0
B174: 2026 | C174: Codiagro | D174: RESULTADO DEL EJERCICIO | E174: RESULTADO ANTES DE IMPUESTOS | F174: RESULTADO DE LA EXPLOTACION | G174: 7.- Otros gastos de explotación | H174: (629) Otros servicios | I174: 629100002 - GASTOS RICARDO PEREZ-SANTAMARINA | J174: - | K174: -3865.16 | L174: 34.2 | M174: -1710.02 | N174: -532.08 | O174: -2522.26 | P174: -4633.35 | Q174: -2854.53 | R174: -1290.01 | S174: =IFERROR(VLOOKUP(I174,'[1]PL Mensual 2026'!$I:$S,11,0),0) -> -315.52 | T174: -2300 | U174: -2300 | V174: -2500 | W174: =SUM(K174:V174) -> -24788.73 | X174: Gastos comerciales de viaje, representación y prospección comercial en zona asignada. | AA174: =VLOOKUP(I174,'[2]BBDD P&L'!$J:$AK,28,0) -> -24788.73 | AB174: =W174-AA174 -> 0
B175: 2026 | C175: Codiagro | D175: RESULTADO DEL EJERCICIO | E175: RESULTADO ANTES DE IMPUESTOS | F175: RESULTADO DE LA EXPLOTACION | G175: 7.- Otros gastos de explotación | H175: (629) Otros servicios | I175: 629100003 - GASTOS JAVIER PAREDES | J175: - | K175: -557.43 | L175: -1592.89 | M175: -800.56 | N175: -929.26 | O175: -1786.27 | P175: -936.54 | Q175: -759.39 | R175: -1377.28 | S175: =IFERROR(VLOOKUP(I175,'[1]PL Mensual 2026'!$I:$S,11,0),0) -> -1722.71 | T175: -1092.45 | U175: -1092.45 | V175: -1092.45 | W175: =SUM(K175:V175) -> -13739.68 | X175: Coste operativo general de estructura y servicios de oficinas/fábrica (promedio histórico). | AA175: =VLOOKUP(I175,'[2]BBDD P&L'!$J:$AK,28,0) -> -13739.68 | AB175: =W175-AA175 -> 0
... B206: 2026 | C206: Codiagro | D206: RESULTADO DEL EJERCICIO | E206: RESULTADO ANTES DE IMPUESTOS | F206: RESULTADO FINANCIERO | G206: 14.- Ingresos financieros | H206: (769) Otros ingresos financieros | I206: 769000000 - Otros ingresos financieros | J206: - | K206: 0 | L206: 0 | M206: 0 | N206: 0 | O206: 0 | P206: 4495.93 | Q206: 0 | R206: 0 | S206: =IFERROR(VLOOKUP(I206,'[1]PL Mensual 2026'!$I:$S,11,0),0) -> - | T206: 0 | U206: 0 | V206: 0 | W206: =SUM(K206:V206) -> 4495.93 | X206: Otros ingresos financieros: partida no recurrente de junio; sin saldos estimados de sep a dic 2026 ni en 2027. | AA206: =VLOOKUP(I206,'[2]BBDD P&L'!$J:$AK,28,0) -> 4495.93 | AB206: =W206-AA206 -> 0
AA207: =VLOOKUP(I207,'[2]BBDD P&L'!$J:$AK,28,0) -> #N/A
AA208: =VLOOKUP(I208,'[2]BBDD P&L'!$J:$AK,28,0) -> #N/A
AA209: =VLOOKUP(I209,'[2]BBDD P&L'!$J:$AK,28,0) -> #N/A
...

Sheet Ginger
A1: Cuenta | B1: Grupo Ext Item | C1: 46023 | D1: 46054 | E1: 46082 | F1: 46113 | G1: 46143 | H1: Comprobación | I1: Dif
A2: 700000000 - Ventas de mercaderías | B2: - | G2: 2029267 | H2: =VLOOKUP(A2,'PL Mensual 2026'!I:O,7,0) -> 2029267 | I2: =G2-H2 -> 0
A3: 700000001 - VENTA MERCADERIAS POR ANTICIPO | B3: - | G3: -106250.17 | H3: =VLOOKUP(A3,'PL Mensual 2026'!I:O,7,0) -> -106250.17 | I3: =G3-H3 -> 0
A4: 700000624 - VENTA POR TRANSP. REP. AL CLIENTE | B4: - | G4: - | H4: =VLOOKUP(A4,'PL Mensual 2026'!I:O,7,0) -> 0
A5: 700000769 - INGRESOS POR RETRASOS DE COBRO Y ACTUALIZACION | B5: - | G5: - | H5: =VLOOKUP(A5,'PL Mensual 2026'!I:O,7,0) -> 0
A6: 700001624 - VENTA POR TRANSPORTE REP. AL CLIENTE DEFINITIVO | B6: - | G6: 25140.75 | H6: =VLOOKUP(A6,'PL Mensual 2026'!I:O,7,0) -> 25140.75 | I6: =G6-H6 -> 0
A7: 702000000 - Ventas de productos semiterminados | B7: - | G7: 101865.8 | H7: =VLOOKUP(A7,'PL Mensual 2026'!I:O,7,0) -> 0 | I7: =G7-H7 -> 101865.8
A8: 703000000 - Ventas de subproductos y residuos | B8: - | G8: - | H8: =VLOOKUP(A8,'PL Mensual 2026'!I:O,7,0) -> 0
A9: 704000000 - Ventas de envases y embalajes | B9: - | G9: 80917.99 | H9: =VLOOKUP(A9,'PL Mensual 2026'!I:O,7,0) -> 0 | I9: =G9-H9 -> 80917.99
A10: 705000000 - Prestaciones de servicios | B10: - | G10: 111557.6 | H10: =VLOOKUP(A10,'PL Mensual 2026'!I:O,7,0) -> 0 | I10: =G10-H10 -> 111557.6
A11: - - | B11: Maquila | G11: -111557.6 | H11: =VLOOKUP(A11,'PL Mensual 2026'!I:O,7,0) -> #N/A | I11: =G11-H11 -> #N/A
A12: 705000001 - INGRESO POR GESTIÓN DE ENVASES | B12: - | G12: 2913.09 | H12: =VLOOKUP(A12,'PL Mensual 2026'!I:O,7,0) -> 2913.09 | I12: =G12-H12 -> 0
A13: 706000000 - Dtos. ventas por pronto pago mercaderías | B13: - | G13: - | H13: =VLOOKUP(A13,'PL Mensual 2026'!I:O,7,0) -> 0
A14: 706000001 - DESCUENTO POR PRONTO PAGO DEFINITIVO | B14: - | G14: -38633.95 | H14: =VLOOKUP(A14,'PL Mensual 2026'!I:O,7,0) -> -38633.95 | I14: =G14-H14 -> 0
A15: 709000000 - «Rappels» ventas de mercaderías | B15: - | G15: - | H15: =VLOOKUP(A15,'PL Mensual 2026'!I:O,7,0) -> 0
A16: 709000001 - PROVISION RAPPELS | B16: - | G16: - | H16: =VLOOKUP(A16,'PL Mensual 2026'!I:O,7,0) -> 0
A17: 709001500 - RAPPEL BONIFICACIONES POR PMK DEFINITIVO | B17: - | G17: -1350 | H17: =VLOOKUP(A17,'PL Mensual 2026'!I:O,7,0) -> -1350 | I17: =G17-H17 -> 0
A18: 711000000 - Variación existencias de prod. semiterminados | B18: - | G18: 4436.02 | H18: =VLOOKUP(A18,'PL Mensual 2026'!I:O,7,0) -> 4436.02 | I18: =G18-H18 -> 0
A19: 712000000 - Variación existencias de prod. terminados | B19: - | G19: -34727.12 | H19: =VLOOKUP(A19,'PL Mensual 2026'!I:O,7,0) -> -34727.12 | I19: =G19-H19 -> 0
A20: 601000000 - Compras de materias primas | B20: - | G20: -417425.43 | H20: =VLOOKUP(A20,'PL Mensual 2026'!I:O,7,0) -> -423709.63 | I20: =G20-H20 -> 6284.2
A21: 601000001 - COMPRAS MAT. PRIMAS INTRACOMUNITARIAS | B21: - | G21: -108150 | H21: =VLOOKUP(A21,'PL Mensual 2026'!I:O,7,0) -> 0 | I21: =G21-H21 -> -108150
A22: 602000001 - COMPRA DE ENVASES Y EMBALAJES | B22: - | G22: -111111.14 | H22: =VLOOKUP(A22,'PL Mensual 2026'!I:O,7,0) -> -30193.15 | I22: =G22-H22 -> -80917.99
A23: 602000002 - COMPRA DE ETIQUETAS | B23: - | G23: -2784.91 | H23: =VLOOKUP(A23,'PL Mensual 2026'!I:O,7,0) -> -2784.91 | I23: =G23-H23 -> 0
A24: 602000003 - COMPRA DE PALETS | B24: - | G24: -17326.4 | H24: =VLOOKUP(A24,'PL Mensual 2026'!I:O,7,0) -> -17326.4 | I24: =G24-H24 -> 0
A25: 602000004 - COMPRA MATERIAL DE LIMPIEZA | B25: - | G25: - | H25: =VLOOKUP(A25,'PL Mensual 2026'!I:O,7,0) -> 0
A26: 602000005 - COMPRA MATERIAL DE OFICINA | B26: - | G26: - | H26: =VLOOKUP(A26,'PL Mensual 2026'!I:O,7,0) -> 0
A27: 602000006 - COMPRA TAPONES DE ENVASES | B27: - | G27: - | H27: =VLOOKUP(A27,'PL Mensual 2026'!I:O,7,0) -> 0
A28: 602000011 - COMPRAS VARIAS PLANTA | B28: - | G28: - | H28: =VLOOKUP(A28,'PL Mensual 2026'!I:O,7,0) -> 0
A29: 602000012 - REPUESTOS INFORMATICOS | B29: - | G29: - | H29: =VLOOKUP(A29,'PL Mensual 2026'!I:O,7,0) -> 0
A30: 602000013 - COMPRA TINTA INPRESORA ETIQUETAS | B30: - | G30: -480.84 | H30: =VLOOKUP(A30,'PL Mensual 2026'!I:O,7,0) -> -480.84 | I30: =G30-H30 -> 0
A31: 602000100 - ENVASES Y EMBALAJES A DEVOLVER | B31: - | G31: 1124 | H31: =VLOOKUP(A31,'PL Mensual 2026'!I:O,7,0) -> 1124 | I31: =G31-H31 -> 0
A32: 607000000 - Trabajos realizados por otras empresas | B32: - | G32: -32102.71 | H32: =VLOOKUP(A32,'PL Mensual 2026'!I:O,7,0) -> -3540 | I32: =G32-H32 -> -28562.71
A33: - - | B33: Maquila | G33: 28562.71 | H33: =VLOOKUP(A33,'PL Mensual 2026'!I:O,7,0) -> #N/A | I33: =G33-H33 -> #N/A
A34: 611000000 - Variación de existencias de materias primas | B34: - | G34: -43504.89 | H34: =VLOOKUP(A34,'PL Mensual 2026'!I:O,7,0) -> -43504.89 | I34: =G34-H34 -> 0
A35: 612000000 - Variación de existencias otros aprovisionamientos | B35: - | G35: -73565.42 | H35: =VLOOKUP(A35,'PL Mensual 2026'!I:O,7,0) -> -73565.42 | I35: =G35-H35 -> 0
A36: 640000000 - Sueldos y salarios | B36: - | G36: -104048.18 | H36: =VLOOKUP(A36,'PL Mensual 2026'!I:O,7,0) -> -104048.18 | I36: =G36-H36 -> 0
A37: 641000000 - Indemnizaciones | B37: - | G37: - | H37: =VLOOKUP(A37,'PL Mensual 2026'!I:O,7,0) -> #N/A
A38: 642000000 - Seguridad Social a cargo empresa | B38: - | G38: -30856.34 | H38: =VLOOKUP(A38,'PL Mensual 2026'!I:O,7,0) -> -30856.34 | I38: =G38-H38 -> 0
A39: 649000100 - GTOS. CURSOS PERSONAL | B39: - | G39: -88 | H39: =VLOOKUP(A39,'PL Mensual 2026'!I:O,7,0) -> -88 | I39: =G39-H39 -> 0
A40: 620000002 - COMPRAS LABORATORIO | B40: - | G40: -487.47 | H40: =VLOOKUP(A40,'PL Mensual 2026'!I:O,7,0) -> -487.47 | I40: =G40-H40 -> 0
A41: 620000003 - SUMINISTROS LABORATORIO | B41: - | G41: -1464.58 | H41: =VLOOKUP(A41,'PL Mensual 2026'!I:O,7,0) -> -1464.58 | I41: =G41-H41 -> 0
A42: 620000004 - GTOS. ANALISIS LABORATORIOS | B42: - | G42: -1476.12 | H42: =VLOOKUP(A42,'PL Mensual 2026'!I:O,7,0) -> -1476.12 | I42: =G42-H42 -> 0
A43: 621000001 - ALQUILER OFICINA CARTAGENA | B43: - | G43: -192 | H43: =VLOOKUP(A43,'PL Mensual 2026'!I:O,7,0) -> -192 | I43: =G43-H43 -> 0
A44: 621000014 - ALQUILER MURANO | B44: - | G44: -15421.92 | H44: =VLOOKUP(A44,'PL Mensual 2026'!I:O,7,0) -> -15421.92 | I44: =G44-H44 -> 0
A45: 621000024 - ALQUILER RENTING 2255KXN ANTONIO | B45: - | G45: - | H45: =VLOOKUP(A45,'PL Mensual 2026'!I:O,7,0) -> 0
A46: 621000026 - ALQUILER RENTING 9319LCL CURRO | B46: - | G46: - | H46: =VLOOKUP(A46,'PL Mensual 2026'!I:O,7,0) -> 0
A47: 621000031 - ALQUILER RENTING KONICA-MINOLTA Y KYOCERA | B47: - | G47: -338 | H47: =VLOOKUP(A47,'PL Mensual 2026'!I:O,7,0) -> -338 | I47: =G47-H47 -> 0
A48: 621000032 - ALQUILER RENTING 6665-LVK JOSE JUAN | B48: - | G48: -443.49 | H48: =VLOOKUP(A48,'PL Mensual 2026'!I:O,7,0) -> -443.49 | I48: =G48-H48 -> 0
A49: 621000033 - ALQUILER RENTING 2612-MBY ANTONIO | B49: - | G49: -399.42 | H49: =VLOOKUP(A49,'PL Mensual 2026'!I:O,7,0) -> -399.42 | I49: =G49-H49 -> 0
A50: 621000034 - ALQUILER RENTING 3108-LZM NIEVES | B50: - | G50: - | H50: =VLOOKUP(A50,'PL Mensual 2026'!I:O,7,0) -> 0
A51: 621000037 - CARRETILLA STILL ELEKTROSTAPLER 516213H00521 | B51: - | G51: -200 | H51: =VLOOKUP(A51,'PL Mensual 2026'!I:O,7,0) -> -200 | I51: =G51-H51 -> 0
A52: 621000038 - CARRETILLA STILL ELEKTROSTAPLER 516223J00123 | B52: - | G52: -200.22 | H52: =VLOOKUP(A52,'PL Mensual 2026'!I:O,7,0) -> -200.22 | I52: =G52-H52 -> 0
A53: 621000039 - ALQUILER RENTING 5043-MWW CURRO | B53: - | G53: - | H53: =VLOOKUP(A53,'PL Mensual 2026'!I:O,7,0) -> 0
A54: 621000040 - ALQUILER RENTING 8917-MZT JAVIER | B54: - | G54: -1172.14 | H54: =VLOOKUP(A54,'PL Mensual 2026'!I:O,7,0) -> -1172.14 | I54: =G54-H54 -> 0
A55: 621000041 - ALQUILER RENTING 8929-MZT RICARDO | B55: - | G55: -1015.21 | H55: =VLOOKUP(A55,'PL Mensual 2026'!I:O,7,0) -> -1015.21 | I55: =G55-H55 -> 0
A56: 621000042 - ALQUILER RENTING 4946-NFH GARCIA | B56: - | G56: -677.53 | H56: =VLOOKUP(A56,'PL Mensual 2026'!I:O,7,0) -> -677.53 | I56: =G56-H56 -> 0
A57: 621000044 - ALQUILER COMPRESOR DE TORNILLO 37KW KAESER BSD 75C | B57: - | G57: -1600 | H57: =VLOOKUP(A57,'PL Mensual 2026'!I:O,7,0) -> -1600 | I57: =G57-H57 -> 0
A58: 621000045 - ALQUILER RENTING 3421-NJT PERE | B58: - | G58: -1208.01 | H58: =VLOOKUP(A58,'PL Mensual 2026'!I:O,7,0) -> -1208.01 | I58: =G58-H58 -> 0
A59: 621000046 - ALQUILER CARRETILLAS | B59: - | G59: -665 | H59: =VLOOKUP(A59,'PL Mensual 2026'!I:O,7,0) -> 0 | I59: =G59-H59 -> -665
A60: - - | B60: Maquila | G60: 665 | H60: =VLOOKUP(A60,'PL Mensual 2026'!I:O,7,0) -> #N/A | I60: =G60-H60 -> #N/A
A61: 622000001 - REPAR. EQUIPOS INFORM. Y FOTOCOPIADORAS | B61: - | G61: - | H61: =VLOOKUP(A61,'PL Mensual 2026'!I:O,7,0) -> 0
A62: 622000004 - REP. Y CONSERV. CARRETILLA ELECTRICA | B62: - | G62: - | H62: =VLOOKUP(A62,'PL Mensual 2026'!I:O,7,0) -> 0
A63: 622000005 - REP. Y MANT. EQUIPOS SEGURIDAD | B63: - | G63: -183.66 | H63: =VLOOKUP(A63,'PL Mensual 2026'!I:O,7,0) -> -183.66 | I63: =G63-H63 -> 0
A64: 622000006 - REP. Y MANT. INSTALACIONES VARIAS | B64: - | G64: - | H64: =VLOOKUP(A64,'PL Mensual 2026'!I:O,7,0) -> 0
A65: 622000007 - REP. Y MANT. HYUNDAI 0377CJG | B65: - | G65: - | H65: =VLOOKUP(A65,'PL Mensual 2026'!I:O,7,0) -> 0
A66: 622000008 - REP. Y MANT. MAQUINA BARREDORA | B66: - | G66: - | H66: =VLOOKUP(A66,'PL Mensual 2026'!I:O,7,0) -> 0
A67: 622000012 - LIMPIEZA OFICINAS, LABORATORIO Y VESTUARIOS | B67: - | G67: - | H67: =VLOOKUP(A67,'PL Mensual 2026'!I:O,7,0) -> 0
A68: 622010200 - ALCAPLANT | B68: - | G68: -942.88 | H68: =VLOOKUP(A68,'PL Mensual 2026'!I:O,7,0) -> -942.88 | I68: =G68-H68 -> 0
A69: 622010201 - REPARACIONES ALCAPLANT | B69: - | G69: - | H69: =VLOOKUP(A69,'PL Mensual 2026'!I:O,7,0) -> 0
A70: 622010300 - SOLIDOS | B70: - | G70: - | H70: =VLOOKUP(A70,'PL Mensual 2026'!I:O,7,0) -> 0
A71: 622010400 - LIQUIDOS | B71: - | G71: -1092.45 | H71: =VLOOKUP(A71,'PL Mensual 2026'!I:O,7,0) -> -1092.45 | I71: =G71-H71 -> 0
A72: 622010500 - REPUESTOS MANT. VARIOS | B72: - | G72: -799.04 | H72: =VLOOKUP(A72,'PL Mensual 2026'!I:O,7,0) -> -799.04 | I72: =G72-H72 -> 0
A73: 622010501 - REP. MANT. FONTANERIA | B73: - | G73: - | H73: =VLOOKUP(A73,'PL Mensual 2026'!I:O,7,0) -> 0
A74: 623000001 - SERV. PROF. INDEPENDIENTES | B74: - | G74: -21698 | H74: =VLOOKUP(A74,'PL Mensual 2026'!I:O,7,0) -> -21698 | I74: =G74-H74 -> 0
A75: 623000002 - SERVICIOS CONTABLES Y FINANCIEROS | B75: - | G75: -2891.19 | H75: =VLOOKUP(A75,'PL Mensual 2026'!I:O,7,0) -> -2891.19 | I75: =G75-H75 -> 0
A76: 623000003 - SERV. NOTARIOS, REGISTROS, LEGAL | B76: - | G76: -2271.24 | H76: =VLOOKUP(A76,'PL Mensual 2026'!I:O,7,0) -> -2271.24 | I76: =G76-H76 -> 0
A77: 623000004 - GTOS. BCS. OKO | B77: - | G77: -1574.71 | H77: =VLOOKUP(A77,'PL Mensual 2026'!I:O,7,0) -> -1574.71 | I77: =G77-H77 -> 0
A78: 623000005 - SERVICIOS PREST. CAMARA COMERCIO | B78: - | G78: -429 | H78: =VLOOKUP(A78,'PL Mensual 2026'!I:O,7,0) -> -429 | I78: =G78-H78 -> 0
A79: 623100002 - GASTOS MAURICIO ALISTE | B79: - | G79: -4225.22 | H79: =VLOOKUP(A79,'PL Mensual 2026'!I:O,7,0) -> -4225.22 | I79: =G79-H79 -> 0
A80: 623100006 - GASTOS Y SERVICIOS AGRICOLA DEL JUCAR | B80: - | G80: -141.55 | H80: =VLOOKUP(A80,'PL Mensual 2026'!I:O,7,0) -> -141.55 | I80: =G80-H80 -> 0
A81: 623100007 - GASTOS Y SUELDO MEHMET CILOGLU | B81: - | G81: - | H81: =VLOOKUP(A81,'PL Mensual 2026'!I:O,7,0) -> 0
A82: 623100008 - COMISIONES KAMAL KEHAL | B82: - | G82: -3398.55 | H82: =VLOOKUP(A82,'PL Mensual 2026'!I:O,7,0) -> -3398.55 | I82: =G82-H82 -> 0
A83: 623200001 - GASTOS MARCAS EN ESPAÑA | B83: - | G83: -377.56 | H83: =VLOOKUP(A83,'PL Mensual 2026'!I:O,7,0) -> -377.56 | I83: =G83-H83 -> 0
A84: 623200006 - MARCAS UNION EUROPEA | B84: - | G84: - | H84: =VLOOKUP(A84,'PL Mensual 2026'!I:O,7,0) -> 0
A85: 623200008 - GASTOS MARCAS EGIPTO | B85: - | G85: -53.14 | H85: =VLOOKUP(A85,'PL Mensual 2026'!I:O,7,0) -> -53.14 | I85: =G85-H85 -> 0
A86: 623200009 - GASTOS MARCAS MARRUECOS | B86: - | G86: - | H86: =VLOOKUP(A86,'PL Mensual 2026'!I:O,7,0) -> 0
A87: 623200010 - GASTOS MARCAS TURQUIA | B87: - | G87: - | H87: =VLOOKUP(A87,'PL Mensual 2026'!I:O,7,0) -> 0
A88: 623200011 - GASTOS MARCAS COLOMBIA | B88: - | G88: -53.12 | H88: =VLOOKUP(A88,'PL Mensual 2026'!I:O,7,0) -> -53.12 | I88: =G88-H88 -> 0
A89: 623200016 - GASTOS MARCAS ECUADOR | B89: - | G89: - | H89: =VLOOKUP(A89,'PL Mensual 2026'!I:O,7,0) -> 0
A90: 623200020 - GASTOS MARCAS TUNEZ | B90: - | G90: - | H90: =VLOOKUP(A90,'PL Mensual 2026'!I:O,7,0) -> 0
A91: 623200022 - GASTOS MARCAS BOLIVIA | B91: - | G91: - | H91: =VLOOKUP(A91,'PL Mensual 2026'!I:O,7,0) -> 0
A92: 623200023 - GASTOS MARCAS ARGELIA | B92: - | G92: -53.12 | H92: =VLOOKUP(A92,'PL Mensual 2026'!I:O,7,0) -> -53.12 | I92: =G92-H92 -> 0
A93: 623200024 - GASTOS MARCAS INTERNACIONALES | B93: - | G93: - | H93: =VLOOKUP(A93,'PL Mensual 2026'!I:O,7,0) -> 0
A94: 623200029 - GASTOS MARCAS GEORGIA | B94: - | G94: - | H94: =VLOOKUP(A94,'PL Mensual 2026'!I:O,7,0) -> 0
A95: 623200030 - GASTOS MARCAS AZERBAIYAN | B95: - | G95: -53.12 | H95: =VLOOKUP(A95,'PL Mensual 2026'!I:O,7,0) -> -53.12 | I95: =G95-H95 -> 0
A96: 624000001 - TRANSPORTES NACIONAL | B96: - | G96: -17966.84 | H96: =VLOOKUP(A96,'PL Mensual 2026'!I:O,7,0) -> -17966.84 | I96: =G96-H96 -> 0
A97: 624000002 - TRANSPORTE INTERNACIONAL | B97: - | G97: -951.38 | H97: =VLOOKUP(A97,'PL Mensual 2026'!I:O,7,0) -> -951.38 | I97: =G97-H97 -> 0
A98: 624000003 - TRANSPORTES CANARIAS | B98: - | G98: -6790.44 | H98: =VLOOKUP(A98,'PL Mensual 2026'!I:O,7,0) -> -6790.44 | I98: =G98-H98 -> 0
A99: 624000004 - GTOS. FLETE REP. AL CLIENTE | B99: - | G99: - | H99: =VLOOKUP(A99,'PL Mensual 2026'!I:O,7,0) -> 0
A100: 624000005 - TTE. PAQUETERIA | B100: - | G100: - | H100: =VLOOKUP(A100,'PL Mensual 2026'!I:O,7,0) -> 0
...

Sheet Extraitems 2026
B1: EXTRAITEMS
B2: 2026
B4: 1 | C4: 2 | D4: 3 | E4: 4 | F4: 5 | G4: 6 | H4: 7 | I4: 8 | J4: 9 | K4: 10 | L4: 11 | M4: 12
B5: ENERO | C5: FEBRERO | D5: MARZO | E5: ABRIL | F5: MAYO | G5: JUNIO | H5: JULIO | I5: AGOSTO | J5: SEPTIEMBRE | K5: OCTUBRE | L5: NOVIEMBRE | M5: DICIEMBRE
B6: 26.2017 | C6: 40.07489 | D6: 29.27336 | E6: 0

Sheet Ext Items 2026
N1: =SUM(N3:N2300) -> -100248.99
A2: Fecha de contabilización | B2: Mes report | C2: Empresa | D2: Grupo EI | E2: Factura | F2: Nivel 1 | G2: Nivel 2 | H2: Nivel 3 | I2: Nivel 4 | J2: Nivel 5 | K2: Cuenta contable | L2: Acreedor/Proveedor | M2: Detalle | N2: Importe € | O2: Comentarios
A3: 46053 | B3: 1 | C3: Codiagro | D3: Personal | F3: RESULTADO DEL EJERCICIO | G3: RESULTADO ANTES DE IMPUESTOS | H3: RESULTADO DE LA EXPLOTACION | I3: 6.- Gastos de personal | J3: (640) Sueldos y salarios | K3: - | N3: 7934.82 | O3: NIEVES RUIZ CESPEDES
A4: 46053 | B4: 1 | C4: Codiagro | D4: Personal | F4: RESULTADO DEL EJERCICIO | G4: RESULTADO ANTES DE IMPUESTOS | H4: RESULTADO DE LA EXPLOTACION | I4: 6.- Gastos de personal | J4: (642) Seguridad social a cargo empresa | K4: - | N4: 1693.8 | O4: NIEVES RUIZ CESPEDES
A5: 46053 | B5: 1 | C5: Codiagro | D5: Personal | F5: RESULTADO DEL EJERCICIO | G5: RESULTADO ANTES DE IMPUESTOS | H5: RESULTADO DE LA EXPLOTACION | I5: 6.- Gastos de personal | J5: (640) Sueldos y salarios | K5: - | N5: 2166.76 | O5: FRANCISCO LAGOSTENA DE GUZMAN
A6: 46053 | B6: 1 | C6: Codiagro | D6: Personal | F6: RESULTADO DEL EJERCICIO | G6: RESULTADO ANTES DE IMPUESTOS | H6: RESULTADO DE LA EXPLOTACION | I6: 6.- Gastos de personal | J6: (642) Seguridad social a cargo empresa | K6: - | N6: 911.41 | O6: FRANCISCO LAGOSTENA DE GUZMAN
A7: 46053 | B7: 1 | C7: Codiagro | D7: Personal | F7: RESULTADO DEL EJERCICIO | G7: RESULTADO ANTES DE IMPUESTOS | H7: RESULTADO DE LA EXPLOTACION | I7: 6.- Gastos de personal | J7: (640) Sueldos y salarios | K7: - | N7: 4444.21 | O7: RAUL AMELA MELIA
A8: 46053 | B8: 1 | C8: Codiagro | D8: Personal | F8: RESULTADO DEL EJERCICIO | G8: RESULTADO ANTES DE IMPUESTOS | H8: RESULTADO DE LA EXPLOTACION | I8: 6.- Gastos de personal | J8: (642) Seguridad social a cargo empresa | K8: - | N8: 1720.91 | O8: RAUL AMELA MELIA
A9: 46053 | B9: 1 | C9: Codiagro | D9: Personal | F9: RESULTADO DEL EJERCICIO | G9: RESULTADO ANTES DE IMPUESTOS | H9: RESULTADO DE LA EXPLOTACION | I9: 6.- Gastos de personal | J9: (640) Sueldos y salarios | K9: - | N9: 5593.98 | O9: CARLOS BARREDA MAS
A10: 46053 | B10: 1 | C10: Codiagro | D10: Personal | F10: RESULTADO DEL EJERCICIO | G10: RESULTADO ANTES DE IMPUESTOS | H10: RESULTADO DE LA EXPLOTACION | I10: 6.- Gastos de personal | J10: (642) Seguridad social a cargo empresa | K10: - | N10: 1735.81 | O10: CARLOS BARREDA MAS
A11: 46081 | B11: 2 | C11: Codiagro | D11: Personal | F11: RESULTADO DEL EJERCICIO | G11: RESULTADO ANTES DE IMPUESTOS | H11: RESULTADO DE LA EXPLOTACION | I11: 6.- Gastos de personal | J11: (640) Sueldos y salarios | K11: - | N11: 9273.34 | O11: NIEVES RUIZ CESPEDES
A12: 46081 | B12: 2 | C12: Codiagro | D12: Personal | F12: RESULTADO DEL EJERCICIO | G12: RESULTADO ANTES DE IMPUESTOS | H12: RESULTADO DE LA EXPLOTACION | I12: 6.- Gastos de personal | J12: (642) Seguridad social a cargo empresa | K12: - | N12: 1774.57 | O12: NIEVES RUIZ CESPEDES
A13: 46081 | B13: 2 | C13: Codiagro | D13: Personal | F13: RESULTADO DEL EJERCICIO | G13: RESULTADO ANTES DE IMPUESTOS | H13: RESULTADO DE LA EXPLOTACION | I13: 6.- Gastos de personal | J13: (640) Sueldos y salarios | K13: - | N13: 3414.13 | O13: FRANCISCO LAGOSTENA DE GUZMAN
A14: 46081 | B14: 2 | C14: Codiagro | D14: Personal | F14: RESULTADO DEL EJERCICIO | G14: RESULTADO ANTES DE IMPUESTOS | H14: RESULTADO DE LA EXPLOTACION | I14: 6.- Gastos de personal | J14: (642) Seguridad social a cargo empresa | K14: - | N14: 838.96 | O14: FRANCISCO LAGOSTENA DE GUZMAN
... A59: 46265 | B59: 8 | C59: Codiagro | D59: INDIVIDUAL-Ext Item Codiagro-SAS | F59: RESULTADO DEL EJERCICIO | G59: RESULTADO ANTES DE IMPUESTOS | H59: RESULTADO DE LA EXPLOTACION | I59: 4.- Aprovisionamientos | J59: (602) Compras de otros aprovisionamientos | K59: 602000001 - COMPRA DE ENVASES Y EMBALAJES | N59: 59572.72 | O59: Packing repercutido

Sheet Ext Items Budget
L1: =SUBTOTAL(9,L3:L52) -> 174.42694
A2: Ext Item/Cap | B2: Empresa | C2: Normalización | D2: Nivel 1 | E2: Nivel 2 | F2: Nivel 3 | G2: Nivel 4 | H2: Nivel 5 | I2: Cuenta | J2: Mes | K2: Importe EUR | L2: Importe EUR ('000) | M2: Comentarios | N2: Grupo EI
B3: Codiagro | C3: Gastos de personal | D3: RESULTADO DEL EJERCICIO | E3: RESULTADO ANTES DE IMPUESTOS | F3: RESULTADO DE LA EXPLOTACION | G3: 6.- Gastos de personal | H3: (640) Sueldos y salarios | J3: 1 | K3: 9918.52 | L3: =+K3/1000 -> 9.91852 | M3: NIEVES RUIZ CESPEDES | N3: Personal
B4: Codiagro | C4: Gastos de personal | D4: RESULTADO DEL EJERCICIO | E4: RESULTADO ANTES DE IMPUESTOS | F4: RESULTADO DE LA EXPLOTACION | G4: 6.- Gastos de personal | H4: (642) Seguridad social a cargo empresa | J4: 1 | K4: 6612.34 | L4: =+K4/1000 -> 6.61234 | M4: NIEVES RUIZ CESPEDES | N4: Personal
B5: Codiagro | C5: Gastos de personal | D5: RESULTADO DEL EJERCICIO | E5: RESULTADO ANTES DE IMPUESTOS | F5: RESULTADO DE LA EXPLOTACION | G5: 6.- Gastos de personal | H5: (640) Sueldos y salarios | J5: 2 | K5: 1295.91 | L5: =+K5/1000 -> 1.29591 | M5: NIEVES RUIZ CESPEDES | N5: Personal
B6: Codiagro | C6: Gastos de personal | D6: RESULTADO DEL EJERCICIO | E6: RESULTADO ANTES DE IMPUESTOS | F6: RESULTADO DE LA EXPLOTACION | G6: 6.- Gastos de personal | H6: (642) Seguridad social a cargo empresa | J6: 2 | K6: 863.94 | L6: =+K6/1000 -> 0.86394 | M6: NIEVES RUIZ CESPEDES | N6: Personal
B7: Codiagro | C7: Gastos de personal | D7: RESULTADO DEL EJERCICIO | E7: RESULTADO ANTES DE IMPUESTOS | F7: RESULTADO DE LA EXPLOTACION | G7: 6.- Gastos de personal | H7: (640) Sueldos y salarios | J7: 1 | K7: 1708.45 | L7: =+K7/1000 -> 1.70845 | M7: FRANCISCO LAGOSTENA DE GUZMAN | N7: Personal
B8: Codiagro | C8: Gastos de personal | D8: RESULTADO DEL EJERCICIO | E8: RESULTADO ANTES DE IMPUESTOS | F8: RESULTADO DE LA EXPLOTACION | G8: 6.- Gastos de personal | H8: (642) Seguridad social a cargo empresa | J8: 1 | K8: 659.51 | L8: =+K8/1000 -> 0.65951 | M8: FRANCISCO LAGOSTENA DE GUZMAN | N8: Personal
B9: Codiagro | C9: Gastos de personal | D9: RESULTADO DEL EJERCICIO | E9: RESULTADO ANTES DE IMPUESTOS | F9: RESULTADO DE LA EXPLOTACION | G9: 6.- Gastos de personal | H9: (640) Sueldos y salarios | J9: 2 | K9: 1708.45 | L9: =+K9/1000 -> 1.70845 | M9: FRANCISCO LAGOSTENA DE GUZMAN | N9: Personal
B10: Codiagro | C10: Gastos de personal | D10: RESULTADO DEL EJERCICIO | E10: RESULTADO ANTES DE IMPUESTOS | F10: RESULTADO DE LA EXPLOTACION | G10: 6.- Gastos de personal | H10: (642) Seguridad social a cargo empresa | J10: 2 | K10: 659.51 | L10: =+K10/1000 -> 0.65951 | M10: FRANCISCO LAGOSTENA DE GUZMAN | N10: Personal
B11: Codiagro | C11: Gastos de personal | D11: RESULTADO DEL EJERCICIO | E11: RESULTADO ANTES DE IMPUESTOS | F11: RESULTADO DE LA EXPLOTACION | G11: 6.- Gastos de personal | H11: (640) Sueldos y salarios | J11: 3 | K11: 1708.45 | L11: =+K11/1000 -> 1.70845 | M11: FRANCISCO LAGOSTENA DE GUZMAN | N11: Personal
B12: Codiagro | C12: Gastos de personal | D12: RESULTADO DEL EJERCICIO | E12: RESULTADO ANTES DE IMPUESTOS | F12: RESULTADO DE LA EXPLOTACION | G12: 6.- Gastos de personal | H12: (642) Seguridad social a cargo empresa | J12: 3 | K12: 659.51 | L12: =+K12/1000 -> 0.65951 | M12: FRANCISCO LAGOSTENA DE GUZMAN | N12: Personal
B13: Codiagro | C13: Gastos de personal | D13: RESULTADO DEL EJERCICIO | E13: RESULTADO ANTES DE IMPUESTOS | F13: RESULTADO DE LA EXPLOTACION | G13: 6.- Gastos de personal | H13: (641) Indemnizaciones | J13: 3 | K13: 19064.32 | L13: =+K13/1000 -> 19.06432 | M13: FRANCISCO LAGOSTENA DE GUZMAN | N13: Indemnizaciones
B14: Codiagro | C14: Gastos de personal | D14: RESULTADO DEL EJERCICIO | E14: RESULTADO ANTES DE IMPUESTOS | F14: RESULTADO DE LA EXPLOTACION | G14: 6.- Gastos de personal | H14: (640) Sueldos y salarios | J14: 1 | K14: 5700.18 | L14: =+K14/1000 -> 5.70018 | M14: RAUL AMELA MELIA | N14: Personal
... B45: Codiagro | C45: Gastos de personal | D45: RESULTADO DEL EJERCICIO | E45: RESULTADO ANTES DE IMPUESTOS | F45: RESULTADO DE LA EXPLOTACION | G45: 6.- Gastos de personal | H45: (642) Seguridad social a cargo empresa | J45: 8 | K45: 950.61913 | L45: =+K45/1000 -> 0.95061913 | M45: CARLOS BARREDA MAS | N45: Personal

Sheet Ext Items 2025
P1: Mes report | Q1: (Todas)
B2: Fecha de contabilización | C2: Mes report | D2: Empresa | E2: Concepto | F2: Factura | G2: Cuenta contable | H2: Normalización | I2: Nivel 4 | J2: Acreedor/Proveedor | K2: Detalle | L2: Importe | M2: Importe ('000)
B3: 45667 | C3: =MONTH(B3) -> 1 | D3: CODIAGRO | E3: Indemnizaciones | G3: 641000007 | H3: Gastos de personal | K3: INDEMNIZACION MIGUEL BELLES | L3: 112732.33 | M3: 112.73233 | P3: Etiquetas de fila | Q3: Suma de Importe ('000)
B4: 45734 | C4: =MONTH(B4) -> 3 | D4: CODIAGRO | E4: Costes Transacción | F4: 440FVN25000044 | G4: 623000001 | H4: Otros Gastos Operativos | J4: AUREN CORPORATE | K4: Asesoramiento | L4: 14111.19 | M4: 14.11119 | P4: Costes Transacción | Q4: 161.05205
B5: 45744 | C5: =MONTH(B5) -> 3 | D5: CODIAGRO | E5: Costes Transacción | F5: 440FVN25000048 | G5: 623000001 | H5: Otros Gastos Operativos | J5: AUREN CORPORATE | K5: Asesoramiento | L5: 4000 | M5: 4 | P5: Gastos periodos anteriores | Q5: 134.19399
B6: 45776 | C6: =MONTH(B6) -> 4 | D6: CODIAGRO | E6: Costes Transacción | F6: 440FVN25000070 | G6: 623000001 | H6: Otros Gastos Operativos | J6: AUREN CORPORATE | K6: Asesoramiento | L6: 4297.23 | M6: 4.29723 | P6: Gastos Representación | Q6: 48.99744
B7: 45805 | C7: =MONTH(B7) -> 5 | D7: CODIAGRO | E7: Costes Transacción | F7: 440FVN25000094 | G7: 623000001 | H7: Otros Gastos Operativos | J7: AUREN CORPORATE | K7: Asesoramiento | L7: 4000 | M7: 4 | P7: Indemnizaciones | Q7: 112.73233
B8: 45838 | C8: =MONTH(B8) -> 6 | D8: CODIAGRO | E8: Costes Transacción | F8: 440FVN25000118 | G8: 623000001 | H8: Otros Gastos Operativos | J8: AUREN CORPORATE | K8: Asesoramiento | L8: 4000 | M8: 4 | P8: TICS | Q8: 1.8
B9: 45866 | C9: =MONTH(B9) -> 7 | D9: CODIAGRO | E9: Costes Transacción | F9: 440FVN25000150 | G9: 623000001 | H9: Otros Gastos Operativos | J9: AUREN CORPORATE | K9: Asesoramiento | L9: 4589.25 | M9: 4.58925 | P9: Gastos de personal | Q9: 310.01329
B10: 45901 | C10: =MONTH(B10) -> 9 | D10: CODIAGRO | E10: Costes Transacción | F10: 440FVN25000171 | G10: 623000001 | H10: Otros Gastos Operativos | J10: AUREN CORPORATE | K10: Asesoramiento | L10: 4000 | M10: 4 | P10: Rappel Dotra (cliente Egipto) 2024 | Q10: 139.50071
B11: 45929 | C11: =MONTH(B11) -> 9 | D11: CODIAGRO | E11: Costes Transacción | F11: 440FVN25000191 | G11: 623000001 | H11: Otros Gastos Operativos | J11: AUREN CORPORATE | K11: Asesoramiento | L11: 4054.38 | M11: 4.05438 | P11: Reparaciones extraordinarias | Q11: 50.39565
B12: 45875 | C12: =MONTH(B12) -> 8 | D12: CODIAGRO | E12: Gastos Representación | F12: 52/000095 | G12: 627000005 | H12: Otros Gastos Operativos | J12: VILLARREAL CLUB DE FUTBOL | K12: PALCO TEMPORADA | L12: 40493.75 | M12: 40.49375 | P12: Total general | Q12: 958.68546
B13: 45875 | C13: =MONTH(B13) -> 8 | D13: CODIAGRO | E13: Gastos Representación | F13: 52/000095 | G13: 634100000 | H13: Otros Gastos Operativos | J13: VILLARREAL CLUB DE FUTBOL | K13: IVA NO DEDUCIBLE del Palco | L13: 8503.69 | M13: 8.50369
B14: 45962 | C14: =MONTH(B14) -> 11 | D14: CODIAGRO | E14: Costes Transacción | F14: 3522900376 | G14: 623000001 | H14: Otros Gastos Operativos | J14: KPMG | K14: VENDOR DIU DILIGENCE | L14: 118000 | M14: 118
B15: 45993 | C15: =MONTH(B15) -> 12 | D15: CODIAGRO | E15: TICS | G15: 623000001 | H15: Otros Gastos Operativos | J15: INTRALINKS | K15: NUBE PARA LA DOCUMENTACION | L15: 1800 | M15: 1.8
B16: 45748 | C16: =MONTH(B16) -> 4 | D16: CODIAGRO | E16: Reparaciones extraordinarias | F16: 153/25 | G16: 622010201 | H16: Otros Gastos Operativos | J16: MAQUISEL SERVICIOS QUIMICOS, S.L.L. | K16: REPARACION ALCAPLANT CADA 6/7 AÑOS | L16: 11502.5 | M16: 11.5025
B17: 45748 | C17: =MONTH(B17) -> 4 | D17: CODIAGRO | E17: Reparaciones extraordinarias | F17: 154/25 | G17: 622010201 | H17: Otros Gastos Operativos | J17: MAQUISEL SERVICIOS QUIMICOS, S.L.L. | K17: REPARACION ALCAPLANT CADA 6/7 AÑOS | L17: 11049.5 | M17: 11.0495
B18: 45992 | C18: =MONTH(B18) -> 12 | D18: CODIAGRO | E18: Reparaciones extraordinarias | F18: 278/25 | G18: 622010201 | H18: Otros Gastos Operativos | J18: MAQUISEL SERVICIOS QUIMICOS, S.L.L. | K18: REPARACION ALCAPLANT CADA 6/7 AÑOS | L18: 12968 | M18: 12.968
B19: 45992 | C19: =MONTH(B19) -> 12 | D19: CODIAGRO | E19: Reparaciones extraordinarias | F19: 560/25 | G19: 622000006 | H19: Otros Gastos Operativos | J19: MAQUISEL SERVICIOS QUIMICOS, S.L.L. | L19: 4897 | M19: 4.897
B20: 45713 | C20: =MONTH(B20) -> 2 | D20: CODIAGRO | E20: Reparaciones extraordinarias | F20: 25000332 | G20: 622010200 | H20: Otros Gastos Operativos | J20: OLIVER & BATLLE, S.A. | K20: REPARACION ALCAPLANT CADA 6/7 AÑOS | L20: 9978.65 | M20: 9.97865
B21: 45721 | C21: =MONTH(B21) -> 3 | D21: CODIAGRO | E21: Gastos periodos anteriores | G21: 627000008 | H21: Otros Gastos Operativos | K21: Marketing 2024 Marcoser | L21: 8479.84 | M21: 8.47984
B22: 45677 | C22: =MONTH(B22) -> 1 | D22: CODIAGRO | E22: Gastos periodos anteriores | G22: 623100006 | H22: Otros Gastos Operativos | K22: Comisiones 2024 Alfonso (agricola Juncar) | L22: 21135 | M22: 21.135
B23: 45660 | C23: =MONTH(B23) -> 1 | D23: CODIAGRO | E23: Gastos periodos anteriores | G23: 623100007 | H23: Otros Gastos Operativos | K23: Comisiones 2024 Mehmet | L23: 18863.51 | M23: 18.86351
B24: 45692 | C24: =MONTH(B24) -> 2 | D24: CODIAGRO | E24: Gastos periodos anteriores | G24: 623100007 | H24: Otros Gastos Operativos | K24: Comisiones 2024 Mehmet | L24: 3423.3 | M24: 3.4233
B25: 45838 | C25: =MONTH(B25) -> 6 | D25: CODIAGRO | E25: Gastos de personal | G25: 640000000 | H25: Gastos de personal | K25: Importe Producción-Planta 2024 | L25: 26136.49 | M25: 26.13649
B26: 45930 | C26: =MONTH(B26) -> 9 | D26: CODIAGRO | E26: Gastos de personal | G26: 647000000 | H26: Gastos de personal | K26: Retribución consejo 2024 | L26: 65849.57 | M26: 65.84957
B27: 45827 | C27: =MONTH(B27) -> 6 | D27: CODIAGRO | E27: Gastos periodos anteriores | G27: 623000001 | H27: Otros Gastos Operativos | K27: Comisiones Eurofertil 2024 | L27: 10969.96 | M27: 10.96996
B28: 45740 | C28: =MONTH(B28) -> 3 | D28: CODIAGRO | E28: Gastos periodos anteriores | G28: 623000001 | H28: Otros Gastos Operativos | K28: Comisiones Eurofertil 2024,2023,2022 | L28: 50283.36 | M28: 50.28336
B29: 45775 | C29: =MONTH(B29) -> 4 | D29: CODIAGRO | E29: Rappel Dotra (cliente Egipto) 2024 | G29: 709000000 | H29: Ventas | K29: Rappel Dotra (cliente Egipto) 2024 | L29: 102533.02 | M29: 102.53302
B30: 45775 | C30: =MONTH(B30) -> 4 | D30: CODIAGRO | E30: Rappel Dotra (cliente Egipto) 2024 | G30: 709000000 | H30: Ventas | K30: Rappel Dotra (cliente Egipto) 2024 | L30: 36967.69 | M30: 36.96769
B31: 45716 | C31: =MONTH(B31) -> 2 | D31: CODIAGRO | E31: Gastos de personal | G31: 640000000 | H31: Gastos de personal | K31: Bonus 2024 | L31: 135000 | M31: 135
B32: 45665 | C32: =MONTH(B32) -> 1 | D32: CODIAGRO | E32: Gastos periodos anteriores | G32: 627000010 | H32: Otros Gastos Operativos | K32: Promoción 2023 Tecnicos Campo Egido | L32: 9175.46 | M32: 9.17546
... B35: 45838 | C35: =MONTH(B35) -> 6 | D35: CODIAGRO | E35: Gastos de personal | G35: 640000000 | H35: Gastos de personal | K35: Comisiones Comercial en nomina de periodo de junio a diciembre 2024 - Pendiente el asiento | L35: 41513.615 | M35: 41.513615

Sheet Cuenta Ok
A1: AGOSTO
A2: Cuenta | B2: SALDO
A3: 700000000 - Ventas de mercaderías | B3: 802410.56
A4: 700000001 - VENTA MERCADERIAS POR ANTICIPO | B4: 0
A5: 700000624 - VENTA POR TRANSP. REP. AL CLIENTE | B5: -
A6: 700001624 - VENTA POR TRANSPORTE REP. AL CLIENTE DEFINITIVO | B6: 11429
A7: 700000769 - INGRESOS POR RETRASOS DE COBRO Y ACTUALIZACION | B7: -
A8: 700000769 - INGRESOS POR RETRASOS DE COBRO Y ACTUALIZACION | B8: -
A9: 702000000 - Ventas de productos semiterminados | B9: 141074.4
A10: 703000000 - Ventas de subproductos y residuos | B10: -
A11: 704000000 - Ventas de envases y embalajes | B11: 59572.72
A12: 705000000 - Prestaciones de servicios | B12: 101520
A13: 705000001 - INGRESO POR GESTIÓN DE ENVASES | B13: 1694.59
A14: 706000000 - Dtos. ventas por pronto pago mercaderías | B14: -
A15: 709000000 - «Rappels» ventas de mercaderías | B15: -
A16: 709000001 - PROVISION RAPPELS | B16: -16000
A17: 771000000 - Beneficios del inmovilizado material | B17: -
A18: 678000000 - Gastos excepcionales | B18: -0.02
A19: 778000000 - Ingresos excepcionales | B19: 0.01
A20: 711000000 - Variación existencias de prod. semiterminados | B20: 27557.62
A21: 712000000 - Variación existencias de prod. terminados | B21: -20822.98
A22: 601000000 - Compras de materias primas | B22: -265516.84
A23: 601000001 - COMPRAS MAT. PRIMAS INTRACOMUNITARIAS | B23: -64800
A24: 602000001 - COMPRA DE ENVASES Y EMBALAJES | B24: -68178.76
A25: 602000000 - Compras de otros aprovisionamientos | B25: -
A26: 602000002 - COMPRA DE ETIQUETAS | B26: -2886.68
A27: 602000003 - COMPRA DE PALETS | B27: -4331.6
A28: 602000004 - COMPRA MATERIAL DE LIMPIEZA | B28: -
A29: 602000005 - COMPRA MATERIAL DE OFICINA | B29: -
A30: 602000006 - COMPRA TAPONES DE ENVASES | B30: -1108.8
A31: 602000007 - COMPRAS LABORATORIO | B31: 0
A32: 602000008 - RESPUESTOS PLANTA | B32: 0
A33: 602000010 - COMPRA RIBBON | B33: 0
A34: 602000011 - COMPRAS VARIAS PLANTA | B34: -371.23
A35: 602000012 - REPUESTOS INFORMATICOS | B35: -
A36: 602000013 - COMPRA TINTA INPRESORA ETIQUETAS | B36: -2557.66
A37: 602000100 - ENVASES Y EMBALAJES A DEVOLVER | B37: -
A38: 607000000 - Trabajos realizados por otras empresas | B38: -25856.5
A39: 611000000 - Variación de existencias de materias primas | B39: -59037.03
A40: 612000000 - Variación de existencias otros aprovisionamientos | B40: -4582.08
A41: 759000000 - Ingresos por servicios diversos | B41: 0
A42: 640000000 - Sueldos y salarios | B42: -128060.74
A43: 640000200 - GASTO POR E. TRAB. TEMPORAL | B43: 0
A44: 640000300 - PROVISION PAGAS EXTRAS | B44: 0
A45: 641000000 - Indemnizaciones | B45: -
A46: 641000007 - INDEMNIZACION MIGUEL BELLES | B46: 0
A47: 642000000 - Seguridad Social a cargo empresa | B47: -24572.05
A48: 649000000 - Otros gastos sociales | B48: 0
A49: 649000001 - GASTOS COMERCIALES NIEVES RUIZ | B49: 0
A50: 649000002 - GASTOS EMPR. ANTONIO ANDREU | B50: 0
A51: 649000004 - GASTOS COMERCIALES RICARDO PEREZ | B51: 0
A52: 649000007 - GASTOS COMERCIALES J.PAREDES | B52: 0
A53: 649000009 - GASTOS COMERCIALES J.A. GARCIA | B53: 0
A54: 649000010 - GASTOS EMP. CURRO | B54: 0
A55: 649000012 - GASTOS COMERCIALES IRENE GARCIA | B55: 0
A56: 649000100 - GTOS. CURSOS PERSONAL | B56: -
A57: 649000101 - GTOS. SEG. Y RIESGOS PERSONAL | B57: 0
A58: 649000102 - GASTOS ROPA UNIFORMES TRABAJADORES | B58: 0
A59: 649000103 - GASTOS COMBUSTIBLE TRAB. | B59: 0
A60: 649100001 - GTOS. COMIDAS TRAB. | B60: 0
A61: 649100002 - GASTOS TRAB. EMPRESA VARIOS | B61: 0
A62: 620000002 - COMPRAS LABORATORIO | B62: -
A63: 620000003 - SUMINISTROS LABORATORIO | B63: -399.98
A64: 620000004 - GTOS. ANALISIS LABORATORIOS | B64: -911.52
A65: 621000001 - ALQUILER OFICINA CARTAGENA | B65: -192
A66: 621000014 - ALQUILER MURANO | B66: -
A67: 621000023 - RENTING TRANSPALETA ELECTRICA DE PIE | B67: 0
A68: 621000024 - ALQUILER RENTING 2255KXN ANTONIO | B68: -
A69: 621000025 - ALQUILER RENTING 9128 LBT NIEVES | B69: 0
A70: 621000026 - ALQUILER RENTING 9319LCL CURRO | B70: -
A71: 621000030 - ALQUILER RENTING 1075-LSC GARCIA | B71: 0
A72: 621000031 - ALQUILER RENTING KONICA-MINOLTA Y KYOCERA | B72: -338
A73: 621000032 - ALQUILER RENTING 6665-LVK JOSE JUAN | B73: -
A74: 621000033 - ALQUILER RENTING 2612-MBY ANTONIO | B74: -399.42
A75: 621000034 - ALQUILER RENTING 3108-LZM NIEVES | B75: -1139.16
A76: 621000035 - ALQUILER RENTING 2142-MCS RICARDO | B76: 0
A77: 621000036 - ALQUILER RENTING 3277-MDX JAVIER | B77: 0
A78: 621000037 - CARRETILLA STILL ELEKTROSTAPLER 516213H00521 | B78: -400
A79: 621000038 - CARRETILLA STILL ELEKTROSTAPLER 516223J00123 | B79: -400.44
A80: 621000039 - ALQUILER RENTING 5043-MWW CURRO | B80: -
A81: 621000040 - ALQUILER RENTING 8917-MZT JAVIER | B81: -
A82: 621000041 - ALQUILER RENTING 8929-MZT RICARDO | B82: -
A83: 621000042 - ALQUILER RENTING 4946-NFH GARCIA | B83: -677.53
A84: 621000044 - ALQUILER COMPRESOR DE TORNILLO 37KW KAESER BSD 75C | B84: -1600
A85: 621000045 - ALQUILER RENTING 3421-NJT PERE | B85: -1208.01
A86: 621000046 - ALQUILER CARRETILLAS | B86: -1407
A87: 622000001 - REPAR. EQUIPOS INFORM. Y FOTOCOPIADORAS | B87: -
A88: 622000004 - REP. Y CONSERV. CARRETILLA ELECTRICA | B88: -115.48
A89: 622000005 - REP. Y MANT. EQUIPOS SEGURIDAD | B89: -
A90: 622000006 - REP. Y MANT. INSTALACIONES VARIAS | B90: -
A91: 622000007 - REP. Y MANT. HYUNDAI 0377CJG | B91: -
A92: 622000008 - REP. Y MANT. MAQUINA BARREDORA | B92: -
A93: 622000009 - REP. Y MANT. FURGONETA 2589CRJ | B93: 0
A94: 622000012 - LIMPIEZA OFICINAS, LABORATORIO Y VESTUARIOS | B94: -977.98
A95: 622010000 MANTENIMIENTO | B95: -
A96: 622010001 - MANTENIMIENTO REPUESTO COMPRA AMAZON | B96: 0
A97: 622010200 - ALCAPLANT | B97: -1983.69
A98: 622010201 - REPARACIONES ALCAPLANT | B98: -5848.16
A99: 622010300 - SOLIDOS | B99: -11965.55
A100: 622010400 - LIQUIDOS | B100: -288.39
...

Sheet P&L Mensualitzada 2025
A1: Sin Ext Item
A2: CODIAGRO
A4: € '000 | B4: Ene | C4: Feb | D4: Mar | E4: Abr | F4: May | G4: Jun | H4: Jul | I4: Ago | J4: Sep | K4: Oct | L4: Nov | M4: Dic | N4: 2025
A5: Ventas | B5: 622.28714 | C5: 1062.4411 | D5: 1795.147 | E5: 1534.3509 | F5: 1483.9152 | G5: 1760.942 | H5: 1314.5645 | I5: 664.49694 | J5: 842.11579 | K5: 699.58345 | L5: 749.69916 | M5: 248.50601 | N5: =SUM(B5:M5) -> 12778.049
A6: COGS | B6: -518.09465 | C6: -451.51496 | D6: -510.02511 | E6: -440.06148 | F6: -669.88812 | G6: -248.36745 | H6: -330.56434 | I6: -99.2048 | J6: -265.37091 | K6: -361.07371 | L6: -275.74654 | M6: -116.4287 | N6: =SUM(B6:M6) -> -4286.3408
A7: Gross Profit | B7: =SUM(B5:B6) -> 104.19249 | C7: =SUM(C5:C6) -> 610.92613 | D7: =SUM(D5:D6) -> 1285.1219 | E7: =SUM(E5:E6) -> 1094.2894 | F7: =SUM(F5:F6) -> 814.02707 | G7: =SUM(G5:G6) -> 1512.5746 | H7: =SUM(H5:H6) -> 984.00014 | I7: =SUM(I5:I6) -> 565.29214 | ... N7: =SUM(N5:N6) -> 8491.7084
A8: % Gross Margin | B8: =+B7/B5 -> 0.16743475 | C8: =+C7/C5 -> 0.57502118 | D8: =+D7/D5 -> 0.71588672 | E8: =+E7/E5 -> 0.71319371 | F8: =+F7/F5 -> 0.54856711 | G8: =+G7/G5 -> 0.85895762 | H8: =+H7/H5 -> 0.74853699 | I8: =+I7/I5 -> 0.85070691 | ... N8: =+N7/N5 -> 0.66455437
A10: Gastos de Personal | B10: 17.397715 | C10: -169.90228 | D10: -215.24045 | E10: -145.05985 | F10: -141.27428 | G10: -98.245985 | H10: -218.74298 | I10: -131.97477 | J10: -133.7212 | K10: -300.72411 | L10: -153.08435 | M10: -172.01862 | N10: =SUM(B10:M10) -> -1862.5912
A11: % of Revenue | B11: =+B10/B5 -> 0.027957697 | C11: =+C10/C5 -> -0.15991689 | D11: =+D10/D5 -> -0.11990129 | E11: =+E10/E5 -> -0.09454151 | F11: =+F10/F5 -> -0.095203743 | G11: =+G10/G5 -> -0.055791721 | H11: =+H10/H5 -> -0.16639958 | I11: =+I10/I5 -> -0.19860854 | ... N11: =+N10/N5 -> -0.14576491
A13: Otros Ingresos Operativos | B13: 0 | C13: 0.23944 | D13: 0 | E13: 0 | F13: 0.43575 | G13: 0.11769 | H13: 0 | I13: 0 | J13: 0 | K13: 1.80096 | L13: 0 | M13: 47.20436 | N13: =SUM(B13:M13) -> 49.7982
A14: Otros Gastos Operativos | B14: -83.04566 | C14: -74.84982 | D14: -105.74077 | E14: -91.37805 | F14: -108.29459 | G14: -116.04261 | H14: -102.38971 | I14: -68.70525 | J14: -73.91279 | K14: -122.16905 | L14: -68.32762 | M14: -239.07332 | N14: =SUM(B14:M14) -> -1253.9292
A15: Operating Expenses | B15: =SUM(B13:B14) -> -83.04566 | C15: =SUM(C13:C14) -> -74.61038 | D15: =SUM(D13:D14) -> -105.74077 | E15: =SUM(E13:E14) -> -91.37805 | F15: =SUM(F13:F14) -> -107.85884 | G15: =SUM(G13:G14) -> -115.92492 | H15: =SUM(H13:H14) -> -102.38971 | I15: =SUM(I13:I14) -> -68.70525 | ... N15: =SUM(N13:N14) -> -1204.131
A16: % of Revenue | B16: =+B15/B5 -> -0.13345232 | C16: =+C15/C5 -> -0.070225428 | D16: =+D15/D5 -> -0.058903682 | E16: =+E15/E5 -> -0.059554858 | F16: =+F15/F5 -> -0.072685313 | G16: =+G15/G5 -> -0.065831197 | H16: =+H15/H5 -> -0.077888694 | I16: =+I15/I5 -> -0.10339438 | ... N16: =+N15/N5 -> -0.094234341
A17: Gastos Fijos | B17: =+B15+B10 -> -65.647945 | C17: =+C15+C10 -> -244.51266 | D17: =+D15+D10 -> -320.98122 | E17: =+E15+E10 -> -236.4379 | F17: =+F15+F10 -> -249.13312 | G17: =+G15+G10 -> -214.1709 | H17: =+H15+H10 -> -321.13269 | I17: =+I15+I10 -> -200.68002 | ... N17: =+N15+N10 -> -3066.7222
A18: % of Revenue | B18: =+B17/B5 -> -0.10549462 | C18: =+C17/C5 -> -0.23014232 | D18: =+D17/D5 -> -0.17880498 | E18: =+E17/E5 -> -0.15409637 | F18: =+F17/F5 -> -0.16788906 | G18: =+G17/G5 -> -0.12162292 | H18: =+H17/H5 -> -0.24428828 | I18: =+I17/I5 -> -0.30200293 | ... N18: =+N17/N5 -> -0.23999925
A19: Adjusted EBITDA | B19: =+B7+B17 -> 38.544545 | C19: =+C7+C17 -> 366.41347 | D19: =+D7+D17 -> 964.1407 | E19: =+E7+E17 -> 857.85151 | F19: =+F7+F17 -> 564.89395 | G19: =+G7+G17 -> 1298.4036 | H19: =+H7+H17 -> 662.86745 | I19: =+I7+I17 -> 364.61212 | ... N19: =+N7+N17 -> 5424.9862
A20: % Adj. EBITDA Margin | B20: =+B19/B5 -> 0.061940128 | C20: =+C19/C5 -> 0.34487886 | D20: =+D19/D5 -> 0.53708175 | E20: =+E19/E5 -> 0.55909735 | F20: =+F19/F5 -> 0.38067806 | G20: =+G19/G5 -> 0.7373347 | H20: =+H19/H5 -> 0.50424872 | I20: =+I19/I5 -> 0.54870399 | ... N20: =+N19/N5 -> 0.42455512
A22: D&A | B22: 0 | C22: 0 | D22: 0 | E22: 0 | F22: 0 | G22: 0 | H22: 0 | I22: 0 | J22: 0 | K22: -194.71201 | L22: -19.4712 | M22: -34.07237 | N22: =SUM(B22:M22) -> -248.25558
A23: Other Gains/Losses | B23: 0.92147 | C23: 0.03183 | D23: -1e-05 | E23: 2e-05 | F23: 0.00031 | G23: 0.00228 | H23: 0.00357 | I23: 0.47301 | J23: -0.04064 | K23: 0.81001 | L23: 0.00443 | M23: 0.15045 | N23: =SUM(B23:M23) -> 2.35673
A24: Adjusted EBIT | B24: =+B19+B22+B23 -> 39.466015 | C24: =+C19+C22+C23 -> 366.4453 | D24: =+D19+D22+D23 -> 964.14069 | E24: =+E19+E22+E23 -> 857.85153 | F24: =+F19+F22+F23 -> 564.89426 | G24: =+G19+G22+G23 -> 1298.4059 | H24: =+H19+H22+H23 -> 662.87102 | I24: =+I19+I22+I23 -> 365.08513 | ... N24: =+N19+N22+N23 -> 5179.0874
A25: % EBIT Margin | B25: =+B24/B5 -> 0.063420907 | C25: =+C24/C5 -> 0.34490882 | D25: =+D24/D5 -> 0.53708174 | E25: =+E24/E5 -> 0.55909736 | F25: =+F24/F5 -> 0.38067827 | G25: =+G24/G5 -> 0.737336 | H25: =+H24/H5 -> 0.50425143 | I25: =+I24/I5 -> 0.54941582 | ... N25: =+N24/N5 -> 0.40531127
A29: Suma de Importe ('000) | B29: Etiquetas de columna
A30: Etiquetas de fila | B30: ENERO | C30: FEBRERO | D30: MARZO | E30: ABRIL | F30: MAYO | G30: JUNIO | H30: JULIO | I30: AGOSTO | J30: SEPTIEMBRE | K30: OCTUBRE | L30: NOVIEMBRE | M30: DICIEMBRE | N30: Total general
A31: Gastos de personal | B31: 112.73233 | N31: 112.73233
A32: Otros Gastos Operativos | C32: 9.97865 | D32: 18.11119 | E32: 26.84923 | F32: 4 | G32: 4 | H32: 4.58925 | I32: 48.99744 | J32: 8.05438 | K32: 0 | L32: 118 | M32: 19.665 | N32: 262.24514
A33: Total general | B33: 112.73233 | C33: 9.97865 | D33: 18.11119 | E33: 26.84923 | F33: 4 | G33: 4 | H33: 4.58925 | I33: 48.99744 | J33: 8.05438 | K33: 0 | L33: 118 | M33: 19.665 | N33: 374.97747

Sheet Budget26 sin EI
B2: Ene-26 - € '000 | C2: 1 | D2: 2 | E2: 3 | F2: 4 | G2: 5 | H2: 6 | I2: 7 | J2: 8 | K2: 9 | L2: 10 | M2: 11 | N2: 12 | O2: Total
B3: Ventas | C3: 805.69363 | D3: 1513.248 | E3: 2302.2173 | F3: 1891.2553 | G3: 1636.9092 | H3: 2150.2566 | I3: 1348.021 | J3: 776.07561 | K3: 1026.5685 | L3: 798.56718 | M3: 1030.243 | N3: 659.94465 | O3: 15939
B4: COGS | C4: -276.70291 | D4: -519.70141 | E4: -790.66062 | F4: -649.52213 | G4: -562.17093 | H4: -738.47207 | I4: -462.95679 | J4: -266.53106 | K4: -352.55893 | L4: -274.25544 | M4: -353.82089 | N4: -226.64682 | O4: -5474
B5: Gross Profit | C5: 528.99072 | D5: 993.54657 | E5: 1511.5567 | F5: 1241.7332 | G5: 1074.7383 | H5: 1411.7845 | I5: 885.06424 | J5: 509.54455 | K5: 674.00956 | L5: 524.31174 | M5: 676.42212 | N5: 433.29783 | O5: 10465
B6: % Gross Margin | C6: 0.6565656 | D6: 0.6565656 | E6: 0.6565656 | F6: 0.6565656 | G6: 0.6565656 | H6: 0.6565656 | I6: 0.6565656 | J6: 0.6565656 | K6: 0.6565656 | L6: 0.6565656 | M6: 0.6565656 | N6: 0.65656692 | O6: 0.65656566
B8: Gastos de Personal | C8: -138.431 | D8: -152.80201 | E8: -268.64421 | F8: -157.32982 | G8: -157.32982 | H8: -290.07649 | I8: -157.32982 | J8: -162.96321 | K8: -174.23 | L8: -174.23 | M8: -174.23 | N8: -306.97667 | O8: -2314.5731
C9: -0.17181593 | D9: -0.10097619 | E9: -0.11668934 | F9: -0.08318804 | G9: -0.096113958 | H9: -0.1349032 | I9: -0.1167117 | J9: -0.20998367 | K9: -0.16972078 | L9: -0.21817826 | M9: -0.16911544 | N9: -0.46515517 | O9: -0.14521445
B10: Otros Ingresos Operativos | C10: 0 | D10: 0 | E10: 0 | F10: 0 | G10: 0 | H10: 0 | I10: 0 | J10: 0 | K10: 0 | L10: 0 | M10: 0 | N10: 0 | O10: 0
B11: Otros Gastos Operativos | C11: -183.33533 | D11: -133.85532 | E11: -128.94532 | F11: -131.89532 | G11: -126.94533 | H11: -160.19533 | I11: -152.80333 | J11: -117.79333 | K11: -120.05333 | L11: -144.84269 | M11: -148.99269 | N11: -180.34269 | O11: -1730
B12: Operating Expenses | C12: -183.33533 | D12: -133.85532 | E12: -128.94532 | F12: -131.89532 | G12: -126.94533 | H12: -160.19533 | I12: -152.80333 | J12: -117.79333 | K12: -120.05333 | L12: -144.84269 | M12: -148.99269 | N12: -180.34269 | O12: -1730
C13: 0.22754968 | D13: 0.08845564 | E13: 0.056009187 | F13: 0.069739563 | G13: 0.077551845 | H13: 0.074500565 | I13: 0.11335382 | J13: 0.15178074 | K13: 0.11694624 | L13: 0.18137821 | M13: 0.14461898 | N13: 0.27326941 | O13: 0.1085388
B14: Adjusted EBITDA | C14: 207.22439 | D14: 706.88924 | E14: 1113.9672 | F14: 952.50805 | G14: 790.46313 | H14: 961.51268 | I14: 574.93109 | J14: 228.78802 | K14: 379.72623 | L14: 205.23905 | M14: 353.19943 | N14: -54.021526 | O14: 6420.4269
B15: % Adj. EBITDA Margin | C15: 0.25719999 | D15: 0.46713377 | E15: 0.48386708 | F15: 0.503638 | G15: 0.4828998 | H15: 0.44716184 | I15: 0.42650009 | J15: 0.29480119 | K15: 0.36989858 | L15: 0.25700913 | M15: 0.34283119 | N15: -0.081857662 | O15: 0.40281241
B17: D&A | C17: -20.833333 | D17: -20.833333 | E17: -20.833333 | F17: -20.833333 | G17: -20.833333 | H17: -20.833333 | I17: -20.833333 | J17: -20.833333 | K17: -20.833333 | L17: -20.833333 | M17: -20.833333 | N17: -20.833333 | O17: -250
B18: Other Gains/Losses | C18: 0 | D18: 0 | E18: 0 | F18: 0 | G18: 0 | H18: 0 | I18: 0 | J18: 0 | K18: 0 | L18: 0 | M18: 0 | N18: 0 | O18: 0
B19: EBIT | C19: 186.39106 | D19: 686.05591 | E19: 1093.1338 | F19: 931.67471 | G19: 769.6298 | H19: 940.67935 | I19: 554.09775 | J19: 207.95468 | K19: 358.8929 | L19: 184.40572 | M19: 332.3661 | N19: -74.854859 | O19: 6170.4269
B20: % EBIT Margin | C20: 0.23134235 | D20: 0.45336648 | E20: 0.47481783 | F20: 0.49262239 | G20: 0.47017256 | H20: 0.43747307 | I20: 0.41104533 | J20: 0.26795673 | K20: 0.34960443 | L20: 0.23092074 | M20: 0.32260942 | N20: -0.11342597 | O20: 0.38712761
