Workbook
Name Datos: #REF!
Name Datos: #REF!

Sheet 2026
B2: Seleccionar las formulas de P&L YTD Mes anterior y de P&L YTD Actual y cambiar la referencia al mes anterior
C4: RELLENAR | L4: RELLENAR | U4: RELLENAR | AD4: RELLENAR | AM4: RELLENAR
B5: MES | C5: 9 | K5: MES | L5: 10 | T5: MES | U5: 11 | AC5: MES | AD5: 12 | AL5: MES | AM5: 12
B7: P&L Mensual | K7: P&L Mensual | T7: P&L Mensual | AC7: P&L Mensual | AL7: P&L Mensual
E8: Variación | H8: Variación | N8: Variación | Q8: Variación | W8: Variación | Z8: Variación | AF8: Variación | AI8: Variación | AO8: Variación | AR8: Variación
B9: € '000 | C9: 2026A | D9: 2025A | E9: EUR | F9: % | G9: 2026B | H9: EUR | I9: % | K9: € '000 | L9: 2026A | M9: 2025A | N9: EUR | O9: % | P9: 2026B | Q9: EUR | R9: % | T9: € '000 | U9: 2026A | V9: 2025A | W9: EUR | X9: % | Y9: 2026B | Z9: EUR | AA9: % | AC9: € '000 | AD9: 2026A | AE9: 2025A | AF9: EUR | AG9: % | AH9: 2026B | AI9: EUR | AJ9: % | AL9: € '000 | AM9: 2026A | AN9: 2025A | AO9: EUR | AP9: % | AQ9: 2026B | AR9: EUR | AS9: %
B10: Ventas | C10: =(GETPIVOTDATA("sep-26 ",TABLA!$B$3,"Nivel 4","1.- Importe neto de la cifra de negocios"))/1000 -> 483.08374 | D10: =VLOOKUP(B10,'P&L Mensualitzada 2025'!$A$5:$N$25,$C$5+1,0) -> 842.11579 | E10: =C10-D10 -> -359.03205 | F10: =+IF(IFERROR(C10/D10-1,"-")<300%,IFERROR(C10/D10-1,"-"),"n.a.") -> -0.42634523 | G10: =VLOOKUP(B10,'Budget26 sin EI'!$B:$O,$C$5+1,0) -> 1026.5685 | H10: =C10-G10 -> -543.48475 | I10: =+IF(IFERROR(C10/G10-1,"-")<300%,IFERROR(C10/G10-1,"-"),"n.a.") -> -0.52941889 | K10: Ventas | L10: =(GETPIVOTDATA("oct-26 ",TABLA!$B$3,"Nivel 4","1.- Importe neto de la cifra de negocios"))/1000 -> 912.05501 | M10: =VLOOKUP(K10,'P&L Mensualitzada 2025'!$A$5:$N$25,$L$5+1,0) -> 699.58345 | N10: =L10-M10 -> 212.47156 | O10: =+IF(IFERROR(L10/M10-1,"-")<300%,IFERROR(L10/M10-1,"-"),"n.a.") -> 0.30371153 | P10: =VLOOKUP(K10,'Budget26 sin EI'!$B:$O,$L$5+1,0) -> 798.56718 | Q10: =L10-P10 -> 113.48783 | R10: =+IF(IFERROR(L10/P10-1,"-")<300%,IFERROR(L10/P10-1,"-"),"n.a.") -> 0.14211431 | T10: Ventas | U10: =(GETPIVOTDATA("nov-26 ",TABLA!$B$3,"Nivel 4","1.- Importe neto de la cifra de negocios"))/1000 -> 1225.3218 | V10: =VLOOKUP(T10,'P&L Mensualitzada 2025'!$A$5:$N$25,$U$5+1,0) -> 749.69916 | W10: =U10-V10 -> 475.62262 | X10: =+IF(IFERROR(U10/V10-1,"-")<300%,IFERROR(U10/V10-1,"-"),"n.a.") -> 0.63441797 | Y10: =VLOOKUP(T10,'Budget26 sin EI'!$B:$O,$U$5+1,0) -> 1030.243 | Z10: =U10-Y10 -> 195.07877 | AA10: =+IF(IFERROR(U10/Y10-1,"-")<300%,IFERROR(U10/Y10-1,"-"),"n.a.") -> 0.18935219 | AC10: Ventas | AD10: =(GETPIVOTDATA("dic-26 ",TABLA!$B$3,"Nivel 4","1.- Importe neto de la cifra de negocios"))/1000 -> 1142.4074 | AE10: =VLOOKUP(AC10,'P&L Mensualitzada 2025'!$A$5:$N$25,$AD$5+1,0) -> 248.50601 | AF10: =AD10-AE10 -> 893.90137 | AG10: =+IF(IFERROR(AD10/AE10-1,"-")<300%,IFERROR(AD10/AE10-1,"-"),"n.a.") -> n.a. | AH10: =VLOOKUP(AC10,'Budget26 sin EI'!$B:$O,$AD$5+1,0) -> 659.94465 | AI10: =AD10-AH10 -> 482.46273 | AJ10: =+IF(IFERROR(AD10/AH10-1,"-")<300%,IFERROR(AD10/AH10-1,"-"),"n.a.") -> 0.73106544 | AL10: Ventas | AM10: =(GETPIVOTDATA("Total 2026 ",TABLA!$B$3,"Nivel 4","1.- Importe neto de la cifra de negocios"))/1000 -> 15180 | AN10: =VLOOKUP(AL10,'P&L Mensualitzada 2025'!$A$5:$N$25,$AD$5+1,0) -> 248.50601 | AO10: =AM10-AN10 -> 14931.494 | AP10: =+IF(IFERROR(AM10/AN10-1,"-")<300%,IFERROR(AM10/AN10-1,"-"),"n.a.") -> n.a. | AQ10: =VLOOKUP(AL10,'Budget26 sin EI'!$B:$O,$AD$5+1,0) -> 659.94465 | AR10: =AM10-AQ10 -> 14520.055 | AS10: =+IF(IFERROR(AM10/AQ10-1,"-")<300%,IFERROR(AM10/AQ10-1,"-"),"n.a.") -> n.a.
B11: COGS | C11: -80 | D11: =VLOOKUP(B11,'P&L Mensualitzada 2025'!$A$5:$N$25,$C$5+1,0) -> -265.37091 | E11: =C11-D11 -> 185.37091 | F11: =+IF(IFERROR(C11/D11-1,"-")<300%,IFERROR(C11/D11-1,"-"),"n.a.") -> -0.69853516 | G11: =VLOOKUP(B11,'Budget26 sin EI'!$B:$O,$C$5+1,0) -> -352.55893 | H11: =C11-G11 -> 272.55893 | I11: =+IF(IFERROR(C11/G11-1,"-")<300%,IFERROR(C11/G11-1,"-"),"n.a.") -> -0.77308758 | K11: COGS | L11: =(GETPIVOTDATA("oct-26 ",TABLA!$B$3,"Nivel 4","2.- Variación de existencias")+GETPIVOTDATA("oct-26 ",TABLA!$B$3,"Nivel 4","4.- Aprovisionamientos"))/1000 -> -302.10136 | M11: =VLOOKUP(K11,'P&L Mensualitzada 2025'!$A$5:$N$25,$L$5+1,0) -> -361.07371 | N11: =L11-M11 -> 58.97235 | O11: =+IF(IFERROR(L11/M11-1,"-")<300%,IFERROR(L11/M11-1,"-"),"n.a.") -> -0.16332496 | P11: =VLOOKUP(K11,'Budget26 sin EI'!$B:$O,$L$5+1,0) -> -274.25544 | Q11: =L11-P11 -> -27.84592 | R11: =+IF(IFERROR(L11/P11-1,"-")<300%,IFERROR(L11/P11-1,"-"),"n.a.") -> 0.10153279 | T11: COGS | U11: =(GETPIVOTDATA("nov-26 ",TABLA!$B$3,"Nivel 4","2.- Variación de existencias")+GETPIVOTDATA("nov-26 ",TABLA!$B$3,"Nivel 4","4.- Aprovisionamientos"))/1000 -> -404.42328 | V11: =VLOOKUP(T11,'P&L Mensualitzada 2025'!$A$5:$N$25,$U$5+1,0) -> -275.74654 | W11: =U11-V11 -> -128.67674 | X11: =+IF(IFERROR(U11/V11-1,"-")<300%,IFERROR(U11/V11-1,"-"),"n.a.") -> 0.46664861 | Y11: =VLOOKUP(T11,'Budget26 sin EI'!$B:$O,$U$5+1,0) -> -353.82089 | Z11: =U11-Y11 -> -50.602393 | AA11: =+IF(IFERROR(U11/Y11-1,"-")<300%,IFERROR(U11/Y11-1,"-"),"n.a.") -> 0.14301697 | AC11: COGS | AD11: =(GETPIVOTDATA("dic-26 ",TABLA!$B$3,"Nivel 4","2.- Variación de existencias")+GETPIVOTDATA("dic-26 ",TABLA!$B$3,"Nivel 4","4.- Aprovisionamientos"))/1000 -> -449.14533 | AE11: =VLOOKUP(AC11,'P&L Mensualitzada 2025'!$A$5:$N$25,$AD$5+1,0) -> -116.4287 | AF11: =AD11-AE11 -> -332.71663 | AG11: =+IF(IFERROR(AD11/AE11-1,"-")<300%,IFERROR(AD11/AE11-1,"-"),"n.a.") -> 2.8576857 | AH11: =VLOOKUP(AC11,'Budget26 sin EI'!$B:$O,$AD$5+1,0) -> -226.64682 | AI11: =AD11-AH11 -> -222.49851 | AJ11: =+IF(IFERROR(AD11/AH11-1,"-")<300%,IFERROR(AD11/AH11-1,"-"),"n.a.") -> 0.981697 | AL11: COGS | AM11: =(GETPIVOTDATA("Total 2026 ",TABLA!$B$3,"Nivel 4","2.- Variación de existencias")+GETPIVOTDATA("Total 2026 ",TABLA!$B$3,"Nivel 4","4.- Aprovisionamientos"))/1000 -> -5233.5328 | AN11: =VLOOKUP(AL11,'P&L Mensualitzada 2025'!$A$5:$N$25,$AD$5+1,0) -> -116.4287 | AO11: =AM11-AN11 -> -5117.1041 | AP11: =+IF(IFERROR(AM11/AN11-1,"-")<300%,IFERROR(AM11/AN11-1,"-"),"n.a.") -> n.a. | AQ11: =VLOOKUP(AL11,'Budget26 sin EI'!$B:$O,$AD$5+1,0) -> -226.64682 | AR11: =AM11-AQ11 -> -5006.886 | AS11: =+IF(IFERROR(AM11/AQ11-1,"-")<300%,IFERROR(AM11/AQ11-1,"-"),"n.a.") -> n.a.
B12: Gross Profit | C12: =C10+C11 -> 403.08374 | D12: =SUM(D10:D11) -> 576.74488 | E12: =C12-D12 -> -173.66114 | F12: =+IF(IFERROR(C12/D12-1,"-")<300%,IFERROR(C12/D12-1,"-"),"n.a.") -> -0.30110565 | G12: =SUM(G10:G11) -> 674.00956 | H12: =C12-G12 -> -270.92582 | I12: =+IF(IFERROR(C12/G12-1,"-")<300%,IFERROR(C12/G12-1,"-"),"n.a.") -> -0.40196139 | K12: Gross Profit | L12: =L10+L11 -> 609.95365 | M12: =SUM(M10:M11) -> 338.50974 | N12: =L12-M12 -> 271.44391 | O12: =+IF(IFERROR(L12/M12-1,"-")<300%,IFERROR(L12/M12-1,"-"),"n.a.") -> 0.80187917 | P12: =SUM(P10:P11) -> 524.31174 | Q12: =L12-P12 -> 85.641906 | R12: =+IF(IFERROR(L12/P12-1,"-")<300%,IFERROR(L12/P12-1,"-"),"n.a.") -> 0.16334157 | T12: Gross Profit | U12: =U10+U11 -> 820.8985 | V12: =SUM(V10:V11) -> 473.95262 | W12: =U12-V12 -> 346.94588 | X12: =+IF(IFERROR(U12/V12-1,"-")<300%,IFERROR(U12/V12-1,"-"),"n.a.") -> 0.73202651 | Y12: =SUM(Y10:Y11) -> 676.42212 | Z12: =U12-Y12 -> 144.47638 | AA12: =+IF(IFERROR(U12/Y12-1,"-")<300%,IFERROR(U12/Y12-1,"-"),"n.a.") -> 0.21358908 | AC12: Gross Profit | AD12: =AD10+AD11 -> 693.26205 | AE12: =SUM(AE10:AE11) -> 132.07731 | AF12: =AD12-AE12 -> 561.18474 | AG12: =+IF(IFERROR(AD12/AE12-1,"-")<300%,IFERROR(AD12/AE12-1,"-"),"n.a.") -> n.a. | AH12: =SUM(AH10:AH11) -> 433.29783 | AI12: =AD12-AH12 -> 259.96422 | AJ12: =+IF(IFERROR(AD12/AH12-1,"-")<300%,IFERROR(AD12/AH12-1,"-"),"n.a.") -> 0.59996659 | AL12: Gross Profit | AM12: =AM10+AM11 -> 9946.4672 | AN12: =SUM(AN10:AN11) -> 132.07731 | AO12: =AM12-AN12 -> 9814.3898 | AP12: =+IF(IFERROR(AM12/AN12-1,"-")<300%,IFERROR(AM12/AN12-1,"-"),"n.a.") -> n.a. | AQ12: =SUM(AQ10:AQ11) -> 433.29783 | AR12: =AM12-AQ12 -> 9513.1693 | AS12: =+IF(IFERROR(AM12/AQ12-1,"-")<300%,IFERROR(AM12/AQ12-1,"-"),"n.a.") -> n.a.
B13: % Gross Margin | C13: =C12/C10 -> 0.83439724 | D13: =D12/D10 -> 0.68487598 | G13: =G12/G10 -> 0.6565656 | K13: % Gross Margin | L13: =L12/L10 -> 0.66876849 | M13: =M12/M10 -> 0.48387328 | P13: =P12/P10 -> 0.6565656 | T13: % Gross Margin | U13: =U12/U10 -> 0.66994524 | V13: =V12/V10 -> 0.63219041 | Y13: =Y12/Y10 -> 0.6565656 | AC13: % Gross Margin | AD13: =AD12/AD10 -> 0.60684311 | AE13: =AE12/AE10 -> 0.53148538 | AH13: =AH12/AH10 -> 0.65656692 | AL13: % Gross Margin | AM13: =AM12/AM10 -> 0.65523499 | AN13: =AN12/AN10 -> 0.53148538 | AQ13: =AQ12/AQ10 -> 0.65656692
B15: Gastos de Personal | C15: =GETPIVOTDATA("sep-26 ",TABLA!$B$3,"Nivel 4","6.- Gastos de personal")/1000 -> -152.63279 | D15: =VLOOKUP(B15,'P&L Mensualitzada 2025'!$A$5:$N$25,$C$5+1,0) -> -133.7212 | E15: =C15-D15 -> -18.91159 | F15: =+IF(IFERROR(C15/D15-1,"-")<300%,IFERROR(C15/D15-1,"-"),"n.a.") -> 0.14142552 | G15: =VLOOKUP(B15,'Budget26 sin EI'!$B:$O,$C$5+1,0) -> -174.23 | H15: =C15-G15 -> 21.59721 | I15: =+IF(IFERROR(C15/G15-1,"-")<300%,IFERROR(C15/G15-1,"-"),"n.a.") -> -0.12395804 | K15: Gastos de Personal | L15: =GETPIVOTDATA("oct-26 ",TABLA!$B$3,"Nivel 4","6.- Gastos de personal")/1000 -> -152.63279 | M15: =VLOOKUP(K15,'P&L Mensualitzada 2025'!$A$5:$N$25,$L$5+1,0) -> -300.72411 | N15: =L15-M15 -> 148.09132 | O15: =+IF(IFERROR(L15/M15-1,"-")<300%,IFERROR(L15/M15-1,"-"),"n.a.") -> -0.49244911 | P15: =VLOOKUP(K15,'Budget26 sin EI'!$B:$O,$L$5+1,0) -> -174.23 | Q15: =L15-P15 -> 21.59721 | R15: =+IF(IFERROR(L15/P15-1,"-")<300%,IFERROR(L15/P15-1,"-"),"n.a.") -> -0.12395804 | T15: Gastos de Personal | U15: =GETPIVOTDATA("nov-26 ",TABLA!$B$3,"Nivel 4","6.- Gastos de personal")/1000 -> -152.63279 | V15: =VLOOKUP(T15,'P&L Mensualitzada 2025'!$A$5:$N$25,$U$5+1,0) -> -153.08435 | W15: =U15-V15 -> 0.45156 | X15: =+IF(IFERROR(U15/V15-1,"-")<300%,IFERROR(U15/V15-1,"-"),"n.a.") -> -0.0029497463 | Y15: =VLOOKUP(T15,'Budget26 sin EI'!$B:$O,$U$5+1,0) -> -174.23 | Z15: =U15-Y15 -> 21.59721 | AA15: =+IF(IFERROR(U15/Y15-1,"-")<300%,IFERROR(U15/Y15-1,"-"),"n.a.") -> -0.12395804 | AC15: Gastos de Personal | AD15: =GETPIVOTDATA("dic-26 ",TABLA!$B$3,"Nivel 4","6.- Gastos de personal")/1000 -> -431.63279 | AE15: =VLOOKUP(AC15,'P&L Mensualitzada 2025'!$A$5:$N$25,$AD$5+1,0) -> -172.01862 | AF15: =AD15-AE15 -> -259.61417 | AG15: =+IF(IFERROR(AD15/AE15-1,"-")<300%,IFERROR(AD15/AE15-1,"-"),"n.a.") -> 1.5092213 | AH15: =VLOOKUP(AC15,'Budget26 sin EI'!$B:$O,$AD$5+1,0) -> -306.97667 | AI15: =AD15-AH15 -> -124.65612 | AJ15: =+IF(IFERROR(AD15/AH15-1,"-")<300%,IFERROR(AD15/AH15-1,"-"),"n.a.") -> 0.40607687 | AL15: Gastos de Personal | AM15: =GETPIVOTDATA("Total 2026 ",TABLA!$B$3,"Nivel 4","6.- Gastos de personal")/1000 -> -2006.5026 | AN15: =VLOOKUP(AL15,'P&L Mensualitzada 2025'!$A$5:$N$25,$AD$5+1,0) -> -172.01862 | AO15: =AM15-AN15 -> -1834.484 | AP15: =+IF(IFERROR(AM15/AN15-1,"-")<300%,IFERROR(AM15/AN15-1,"-"),"n.a.") -> n.a. | AQ15: =VLOOKUP(AL15,'Budget26 sin EI'!$B:$O,$AD$5+1,0) -> -306.97667 | AR15: =AM15-AQ15 -> -1699.5259 | AS15: =+IF(IFERROR(AM15/AQ15-1,"-")<300%,IFERROR(AM15/AQ15-1,"-"),"n.a.") -> n.a.
B16: % of Revenue | C16: =C15/C10 -> -0.31595514 | D16: =D15/D10 -> -0.15879194 | G16: =G15/G10 -> -0.16972078 | K16: % of Revenue | L16: =L15/L10 -> -0.16735042 | M16: =M15/M10 -> -0.42986167 | P16: =P15/P10 -> -0.21817826 | T16: % of Revenue | U16: =U15/U10 -> -0.12456548 | V16: =V15/V10 -> -0.20419437 | Y16: =Y15/Y10 -> -0.16911544 | AC16: % of Revenue | AD16: =AD15/AD10 -> -0.37782738 | AE16: =AE15/AE10 -> -0.69221111 | AH16: =AH15/AH10 -> -0.46515517 | AL16: % of Revenue | AM16: =AM15/AM10 -> -0.13218067 | AN16: =AN15/AN10 -> -0.69221111 | AQ16: =AQ15/AQ10 -> -0.46515517
B18: Otros Ingresos Operativos | C18: =GETPIVOTDATA("sep-26 ",TABLA!$B$3,"Nivel 4","5.- Otros ingresos de explotación")/1000 -> 5.2862 | D18: =VLOOKUP(B18,'P&L Mensualitzada 2025'!$A$5:$N$25,$C$5+1,0) -> 0 | E18: =C18-D18 -> 5.2862 | F18: =+IF(IFERROR(C18/D18-1,"-")<300%,IFERROR(C18/D18-1,"-"),"n.a.") -> n.a. | G18: =VLOOKUP(B18,'Budget26 sin EI'!$B:$O,$C$5+1,0) -> 0 | H18: =C18-G18 -> 5.2862 | I18: =+IF(IFERROR(C18/G18-1,"-")<300%,IFERROR(C18/G18-1,"-"),"n.a.") -> n.a. | K18: Otros Ingresos Operativos | L18: =GETPIVOTDATA("oct-26 ",TABLA!$B$3,"Nivel 4","5.- Otros ingresos de explotación")/1000 -> 10.01367 | M18: =VLOOKUP(K18,'P&L Mensualitzada 2025'!$A$5:$N$25,$L$5+1,0) -> 1.80096 | N18: =L18-M18 -> 8.21271 | O18: =+IF(IFERROR(L18/M18-1,"-")<300%,IFERROR(L18/M18-1,"-"),"n.a.") -> n.a. | P18: =VLOOKUP(K18,'Budget26 sin EI'!$B:$O,$L$5+1,0) -> 0 | Q18: =L18-P18 -> 10.01367 | R18: =+IF(IFERROR(L18/P18-1,"-")<300%,IFERROR(L18/P18-1,"-"),"n.a.") -> n.a. | T18: Otros Ingresos Operativos | U18: =GETPIVOTDATA("nov-26 ",TABLA!$B$3,"Nivel 4","5.- Otros ingresos de explotación")/1000 -> 13.46183 | V18: =VLOOKUP(T18,'P&L Mensualitzada 2025'!$A$5:$N$25,$U$5+1,0) -> 0 | W18: =U18-V18 -> 13.46183 | X18: =+IF(IFERROR(U18/V18-1,"-")<300%,IFERROR(U18/V18-1,"-"),"n.a.") -> n.a. | Y18: =VLOOKUP(T18,'Budget26 sin EI'!$B:$O,$U$5+1,0) -> 0 | Z18: =U18-Y18 -> 13.46183 | AA18: =+IF(IFERROR(U18/Y18-1,"-")<300%,IFERROR(U18/Y18-1,"-"),"n.a.") -> n.a. | AC18: Otros Ingresos Operativos | AD18: =GETPIVOTDATA("dic-26 ",TABLA!$B$3,"Nivel 4","5.- Otros ingresos de explotación")/1000 -> 14.53394 | AE18: =VLOOKUP(AC18,'P&L Mensualitzada 2025'!$A$5:$N$25,$AD$5+1,0) -> 47.20436 | AF18: =AD18-AE18 -> -32.67042 | AG18: =+IF(IFERROR(AD18/AE18-1,"-")<300%,IFERROR(AD18/AE18-1,"-"),"n.a.") -> -0.69210598 | AH18: =VLOOKUP(AC18,'Budget26 sin EI'!$B:$O,$AD$5+1,0) -> 0 | AI18: =AD18-AH18 -> 14.53394 | AJ18: =+IF(IFERROR(AD18/AH18-1,"-")<300%,IFERROR(AD18/AH18-1,"-"),"n.a.") -> n.a. | AL18: Otros Ingresos Operativos | AM18: =GETPIVOTDATA("Total 2026 ",TABLA!$B$3,"Nivel 4","5.- Otros ingresos de explotación")/1000 -> 114.62098 | AN18: =VLOOKUP(AL18,'P&L Mensualitzada 2025'!$A$5:$N$25,$AD$5+1,0) -> 47.20436 | AO18: =AM18-AN18 -> 67.41662 | AP18: =+IF(IFERROR(AM18/AN18-1,"-")<300%,IFERROR(AM18/AN18-1,"-"),"n.a.") -> 1.4281863 | AQ18: =VLOOKUP(AL18,'Budget26 sin EI'!$B:$O,$AD$5+1,0) -> 0 | AR18: =AM18-AQ18 -> 114.62098 | AS18: =+IF(IFERROR(AM18/AQ18-1,"-")<300%,IFERROR(AM18/AQ18-1,"-"),"n.a.") -> n.a.
B19: Otros Gastos Operativos | C19: =-100 -> -100 | D19: =VLOOKUP(B19,'P&L Mensualitzada 2025'!$A$5:$N$25,$C$5+1,0) -> -73.91279 | E19: =C19-D19 -> -26.08721 | F19: =+IF(IFERROR(C19/D19-1,"-")<300%,IFERROR(C19/D19-1,"-"),"n.a.") -> 0.35294582 | G19: =VLOOKUP(B19,'Budget26 sin EI'!$B:$O,$C$5+1,0) -> -120.05333 | H19: =C19-G19 -> 20.053329 | I19: =+IF(IFERROR(C19/G19-1,"-")<300%,IFERROR(C19/G19-1,"-"),"n.a.") -> -0.16703684 | K19: Otros Gastos Operativos | L19: =GETPIVOTDATA("oct-26 ",TABLA!$B$3,"Nivel 4","7.- Otros gastos de explotación")/1000 -> -141.64847 | M19: =VLOOKUP(K19,'P&L Mensualitzada 2025'!$A$5:$N$25,$L$5+1,0) -> -122.16905 | N19: =L19-M19 -> -19.47942 | O19: =+IF(IFERROR(L19/M19-1,"-")<300%,IFERROR(L19/M19-1,"-"),"n.a.") -> 0.15944644 | P19: =VLOOKUP(K19,'Budget26 sin EI'!$B:$O,$L$5+1,0) -> -144.84269 | Q19: =L19-P19 -> 3.1942192 | R19: =+IF(IFERROR(L19/P19-1,"-")<300%,IFERROR(L19/P19-1,"-"),"n.a.") -> -0.022053023 | T19: Otros Gastos Operativos | U19: =GETPIVOTDATA("nov-26 ",TABLA!$B$3,"Nivel 4","7.- Otros gastos de explotación")/1000 -> -149.83612 | V19: =VLOOKUP(T19,'P&L Mensualitzada 2025'!$A$5:$N$25,$U$5+1,0) -> -68.32762 | W19: =U19-V19 -> -81.5085 | X19: =+IF(IFERROR(U19/V19-1,"-")<300%,IFERROR(U19/V19-1,"-"),"n.a.") -> 1.1929071 | Y19: =VLOOKUP(T19,'Budget26 sin EI'!$B:$O,$U$5+1,0) -> -148.99269 | Z19: =U19-Y19 -> -0.84343084 | AA19: =+IF(IFERROR(U19/Y19-1,"-")<300%,IFERROR(U19/Y19-1,"-"),"n.a.") -> 0.0056608874 | AC19: Otros Gastos Operativos | AD19: =GETPIVOTDATA("dic-26 ",TABLA!$B$3,"Nivel 4","7.- Otros gastos de explotación")/1000 -> -291.51097 | AE19: =VLOOKUP(AC19,'P&L Mensualitzada 2025'!$A$5:$N$25,$AD$5+1,0) -> -239.07332 | AF19: =AD19-AE19 -> -52.43765 | AG19: =+IF(IFERROR(AD19/AE19-1,"-")<300%,IFERROR(AD19/AE19-1,"-"),"n.a.") -> 0.21933711 | AH19: =VLOOKUP(AC19,'Budget26 sin EI'!$B:$O,$AD$5+1,0) -> -180.34269 | AI19: =AD19-AH19 -> -111.16828 | AJ19: =+IF(IFERROR(AD19/AH19-1,"-")<300%,IFERROR(AD19/AH19-1,"-"),"n.a.") -> 0.61642799 | AL19: Otros Gastos Operativos | AM19: =GETPIVOTDATA("Total 2026 ",TABLA!$B$3,"Nivel 4","7.- Otros gastos de explotación")/1000 -> -1678.4074 | AN19: =VLOOKUP(AL19,'P&L Mensualitzada 2025'!$A$5:$N$25,$AD$5+1,0) -> -239.07332 | AO19: =AM19-AN19 -> -1439.3341 | AP19: =+IF(IFERROR(AM19/AN19-1,"-")<300%,IFERROR(AM19/AN19-1,"-"),"n.a.") -> n.a. | AQ19: =VLOOKUP(AL19,'Budget26 sin EI'!$B:$O,$AD$5+1,0) -> -180.34269 | AR19: =AM19-AQ19 -> -1498.0647 | AS19: =+IF(IFERROR(AM19/AQ19-1,"-")<300%,IFERROR(AM19/AQ19-1,"-"),"n.a.") -> n.a.
B20: Operating Expenses | C20: =SUM(C18:C19) -> -94.7138 | D20: =SUM(D18:D19) -> -73.91279 | E20: =C20-D20 -> -20.80101 | F20: =+IF(IFERROR(C20/D20-1,"-")<300%,IFERROR(C20/D20-1,"-"),"n.a.") -> 0.28142639 | G20: =SUM(G18:G19) -> -120.05333 | H20: =C20-G20 -> 25.339529 | I20: =+IF(IFERROR(C20/G20-1,"-")<300%,IFERROR(C20/G20-1,"-"),"n.a.") -> -0.21106894 | K20: Operating Expenses | L20: =SUM(L18:L19) -> -131.6348 | M20: =SUM(M18:M19) -> -120.36809 | N20: =L20-M20 -> -11.26671 | O20: =+IF(IFERROR(L20/M20-1,"-")<300%,IFERROR(L20/M20-1,"-"),"n.a.") -> 0.093602133 | P20: =SUM(P18:P19) -> -144.84269 | Q20: =L20-P20 -> 13.207889 | R20: =+IF(IFERROR(L20/P20-1,"-")<300%,IFERROR(L20/P20-1,"-"),"n.a.") -> -0.091187821 | T20: Operating Expenses | U20: =SUM(U18:U19) -> -136.37429 | V20: =SUM(V18:V19) -> -68.32762 | W20: =U20-V20 -> -68.04667 | X20: =+IF(IFERROR(U20/V20-1,"-")<300%,IFERROR(U20/V20-1,"-"),"n.a.") -> 0.99588819 | Y20: =SUM(Y18:Y19) -> -148.99269 | Z20: =U20-Y20 -> 12.618399 | AA20: =+IF(IFERROR(U20/Y20-1,"-")<300%,IFERROR(U20/Y20-1,"-"),"n.a.") -> -0.084691398 | AC20: Operating Expenses | AD20: =SUM(AD18:AD19) -> -276.97703 | AE20: =SUM(AE18:AE19) -> -191.86896 | AF20: =AD20-AE20 -> -85.10807 | AG20: =+IF(IFERROR(AD20/AE20-1,"-")<300%,IFERROR(AD20/AE20-1,"-"),"n.a.") -> 0.44357394 | AH20: =SUM(AH18:AH19) -> -180.34269 | AI20: =AD20-AH20 -> -96.634341 | AJ20: =+IF(IFERROR(AD20/AH20-1,"-")<300%,IFERROR(AD20/AH20-1,"-"),"n.a.") -> 0.53583731 | AL20: Operating Expenses | AM20: =SUM(AM18:AM19) -> -1563.7865 | AN20: =SUM(AN18:AN19) -> -191.86896 | AO20: =AM20-AN20 -> -1371.9175 | AP20: =+IF(IFERROR(AM20/AN20-1,"-")<300%,IFERROR(AM20/AN20-1,"-"),"n.a.") -> n.a. | AQ20: =SUM(AQ18:AQ19) -> -180.34269 | AR20: =AM20-AQ20 -> -1383.4438 | AS20: =+IF(IFERROR(AM20/AQ20-1,"-")<300%,IFERROR(AM20/AQ20-1,"-"),"n.a.") -> n.a.
B21: % of Revenue | C21: =C20/C10 -> -0.19606083 | D21: =D20/D10 -> -0.087770341 | G21: =G20/G10 -> -0.11694624 | K21: % of Revenue | L21: =L20/L10 -> -0.1443277 | M21: =M20/M10 -> -0.1720568 | P21: =P20/P10 -> -0.18137821 | T21: % of Revenue | U21: =U20/U10 -> -0.11129672 | V21: =V20/V10 -> -0.091140051 | Y21: =Y20/Y10 -> -0.14461898 | AC21: % of Revenue | AD21: =AD20/AD10 -> -0.24245032 | AE21: =AE20/AE10 -> -0.77208982 | AH21: =AH20/AH10 -> -0.27326941 | AL21: % of Revenue | AM21: =AM20/AM10 -> -0.10301624 | AN21: =AN20/AN10 -> -0.77208982 | AQ21: =AQ20/AQ10 -> -0.27326941
B22: Gastos Fijos | C22: =C20+C15 -> -247.34659 | D22: =D20+D15 -> -207.63399 | E22: =C22-D22 -> -39.7126 | F22: =+IF(IFERROR(C22/D22-1,"-")<300%,IFERROR(C22/D22-1,"-"),"n.a.") -> 0.19126252 | G22: =G20+G15 -> -294.28333 | H22: =C22-G22 -> 46.936739 | I22: =+IF(IFERROR(C22/G22-1,"-")<300%,IFERROR(C22/G22-1,"-"),"n.a.") -> -0.15949507 | K22: Gastos Fijos | L22: =L20+L15 -> -284.26759 | M22: =M20+M15 -> -421.0922 | N22: =L22-M22 -> 136.82461 | O22: =+IF(IFERROR(L22/M22-1,"-")<300%,IFERROR(L22/M22-1,"-"),"n.a.") -> -0.32492791 | P22: =P20+P15 -> -319.07269 | Q22: =L22-P22 -> 34.805099 | R22: =+IF(IFERROR(L22/P22-1,"-")<300%,IFERROR(L22/P22-1,"-"),"n.a.") -> -0.10908204 | T22: Gastos Fijos | U22: =U20+U15 -> -289.00708 | V22: =V20+V15 -> -221.41197 | W22: =U22-V22 -> -67.59511 | X22: =+IF(IFERROR(U22/V22-1,"-")<300%,IFERROR(U22/V22-1,"-"),"n.a.") -> 0.30529113 | Y22: =Y20+Y15 -> -323.22269 | Z22: =U22-Y22 -> 34.215609 | AA22: =+IF(IFERROR(U22/Y22-1,"-")<300%,IFERROR(U22/Y22-1,"-"),"n.a.") -> -0.1058577 | AC22: Gastos Fijos | AD22: =AD20+AD15 -> -708.60982 | AE22: =AE20+AE15 -> -363.88758 | AF22: =AD22-AE22 -> -344.72224 | AG22: =+IF(IFERROR(AD22/AE22-1,"-")<300%,IFERROR(AD22/AE22-1,"-"),"n.a.") -> 0.9473317 | AH22: =AH20+AH15 -> -487.31936 | AI22: =AD22-AH22 -> -221.29046 | AJ22: =+IF(IFERROR(AD22/AH22-1,"-")<300%,IFERROR(AD22/AH22-1,"-"),"n.a.") -> 0.45409742 | AL22: Gastos Fijos | AM22: =AM20+AM15 -> -3570.289 | AN22: =AN20+AN15 -> -363.88758 | AO22: =AM22-AN22 -> -3206.4015 | AP22: =+IF(IFERROR(AM22/AN22-1,"-")<300%,IFERROR(AM22/AN22-1,"-"),"n.a.") -> n.a. | AQ22: =AQ20+AQ15 -> -487.31936 | AR22: =AM22-AQ22 -> -3082.9697 | AS22: =+IF(IFERROR(AM22/AQ22-1,"-")<300%,IFERROR(AM22/AQ22-1,"-"),"n.a.") -> n.a.
B23: % of Revenue | C23: =C22/C10 -> -0.51201597 | D23: =D22/D10 -> -0.24656228 | G23: =G22/G10 -> -0.28666702 | K23: % of Revenue | L23: =L22/L10 -> -0.31167812 | M23: =M22/M10 -> -0.60191847 | P23: =P22/P10 -> -0.39955648 | T23: % of Revenue | U23: =U22/U10 -> -0.23586219 | V23: =V22/V10 -> -0.29533442 | Y23: =Y22/Y10 -> -0.31373442 | AC23: % of Revenue | AD23: =AD22/AD10 -> -0.6202777 | AE23: =AE22/AE10 -> -1.4643009 | AH23: =AH22/AH10 -> -0.73842458 | AL23: % of Revenue | AM23: =AM22/AM10 -> -0.23519691 | AN23: =AN22/AN10 -> -1.4643009 | AQ23: =AQ22/AQ10 -> -0.73842458
B24: Adjusted EBITDA | C24: =C12+C22 -> 155.73715 | D24: =D12+D22 -> 369.11089 | E24: =C24-D24 -> -213.37374 | F24: =+IF(IFERROR(C24/D24-1,"-")<300%,IFERROR(C24/D24-1,"-"),"n.a.") -> -0.5780749 | G24: =G12+G22 -> 379.72623 | H24: =C24-G24 -> -223.98908 | I24: =+IF(IFERROR(C24/G24-1,"-")<300%,IFERROR(C24/G24-1,"-"),"n.a.") -> -0.58986992 | K24: Adjusted EBITDA | L24: =L12+L22 -> 325.68606 | M24: =M12+M22 -> -82.58246 | N24: =L24-M24 -> 408.26852 | O24: =+IF(IFERROR(L24/M24-1,"-")<300%,IFERROR(L24/M24-1,"-"),"n.a.") -> -4.943768 | P24: =P12+P22 -> 205.23905 | Q24: =L24-P24 -> 120.44701 | R24: =+IF(IFERROR(L24/P24-1,"-")<300%,IFERROR(L24/P24-1,"-"),"n.a.") -> 0.58686201 | T24: Adjusted EBITDA | U24: =U12+U22 -> 531.89142 | V24: =V12+V22 -> 252.54065 | W24: =U24-V24 -> 279.35077 | X24: =+IF(IFERROR(U24/V24-1,"-")<300%,IFERROR(U24/V24-1,"-"),"n.a.") -> 1.1061616 | Y24: =Y12+Y22 -> 353.19943 | Z24: =U24-Y24 -> 178.69199 | AA24: =+IF(IFERROR(U24/Y24-1,"-")<300%,IFERROR(U24/Y24-1,"-"),"n.a.") -> 0.50592377 | AC24: Adjusted EBITDA | AD24: =AD12+AD22 -> -15.34777 | AE24: =AE12+AE22 -> -231.81027 | AF24: =AD24-AE24 -> 216.4625 | AG24: =+IF(IFERROR(AD24/AE24-1,"-")<300%,IFERROR(AD24/AE24-1,"-"),"n.a.") -> -0.93379167 | AH24: =AH12+AH22 -> -54.021526 | AI24: =AD24-AH24 -> 38.673756 | AJ24: =+IF(IFERROR(AD24/AH24-1,"-")<300%,IFERROR(AD24/AH24-1,"-"),"n.a.") -> -0.71589529 | AL24: Adjusted EBITDA | AM24: =AM12+AM22 -> 6376.1781 | AN24: =AN12+AN22 -> -231.81027 | AO24: =AM24-AN24 -> 6607.9884 | AP24: =+IF(IFERROR(AM24/AN24-1,"-")<300%,IFERROR(AM24/AN24-1,"-"),"n.a.") -> -28.506021 | AQ24: =AQ12+AQ22 -> -54.021526 | AR24: =AM24-AQ24 -> 6430.1996 | AS24: =+IF(IFERROR(AM24/AQ24-1,"-")<300%,IFERROR(AM24/AQ24-1,"-"),"n.a.") -> -119.03032
B25: % Adj. EBITDA Margin | C25: =C24/C10 -> 0.32238127 | D25: =D24/D10 -> 0.4383137 | F25: =+IF(IFERROR(C25/D25-1,"-")<300%,IFERROR(C25/D25-1,"-"),"n.a.") -> -0.26449648 | G25: =G24/G10 -> 0.36989858 | K25: % Adj. EBITDA Margin | L25: =L24/L10 -> 0.35709037 | M25: =M24/M10 -> -0.11804519 | O25: =+IF(IFERROR(L25/M25-1,"-")<300%,IFERROR(L25/M25-1,"-"),"n.a.") -> -4.0250311 | P25: =P24/P10 -> 0.25700913 | T25: % Adj. EBITDA Margin | U25: =U24/U10 -> 0.43408305 | V25: =V24/V10 -> 0.33685599 | X25: =+IF(IFERROR(U25/V25-1,"-")<300%,IFERROR(U25/V25-1,"-"),"n.a.") -> 0.28863096 | Y25: =Y24/Y10 -> 0.34283119 | AC25: % Adj. EBITDA Margin | AD25: =AD24/AD10 -> -0.013434586 | AE25: =AE24/AE10 -> -0.93281555 | AG25: =+IF(IFERROR(AD25/AE25-1,"-")<300%,IFERROR(AD25/AE25-1,"-"),"n.a.") -> -0.98559781 | AH25: =AH24/AH10 -> -0.081857662 | AL25: % Adj. EBITDA Margin | AM25: =AM24/AM10 -> 0.42003808 | AN25: =AN24/AN10 -> -0.93281555 | AP25: =+IF(IFERROR(AM25/AN25-1,"-")<300%,IFERROR(AM25/AN25-1,"-"),"n.a.") -> -1.4502906 | AQ25: =AQ24/AQ10 -> -0.081857662
B27: D&A | C27: =GETPIVOTDATA("sep-26 ",TABLA!$B$3,"Nivel 4","8.- Amortización del inmovilizado")/1000 -> -19.22535 | D27: =VLOOKUP(B27,'P&L Mensualitzada 2025'!$A$5:$N$25,$C$5+1,0) -> 0 | E27: =C27-D27 -> -19.22535 | F27: =+IF(IFERROR(C27/D27-1,"-")<300%,IFERROR(C27/D27-1,"-"),"n.a.") -> n.a. | G27: =VLOOKUP(B27,'Budget26 sin EI'!$B:$O,$C$5+1,0) -> -20.833333 | H27: =C27-G27 -> 1.607983 | I27: =+IF(IFERROR(C27/G27-1,"-")<300%,IFERROR(C27/G27-1,"-"),"n.a.") -> -0.077183185 | K27: D&A | L27: =GETPIVOTDATA("oct-26 ",TABLA!$B$3,"Nivel 4","8.- Amortización del inmovilizado")/1000 -> -19.22535 | M27: =VLOOKUP(K27,'P&L Mensualitzada 2025'!$A$5:$N$25,$L$5+1,0) -> -194.71201 | N27: =L27-M27 -> 175.48666 | O27: =+IF(IFERROR(L27/M27-1,"-")<300%,IFERROR(L27/M27-1,"-"),"n.a.") -> -0.90126264 | P27: =VLOOKUP(K27,'Budget26 sin EI'!$B:$O,$L$5+1,0) -> -20.833333 | Q27: =L27-P27 -> 1.607983 | R27: =+IF(IFERROR(L27/P27-1,"-")<300%,IFERROR(L27/P27-1,"-"),"n.a.") -> -0.077183185 | T27: D&A | U27: =GETPIVOTDATA("nov-26 ",TABLA!$B$3,"Nivel 4","8.- Amortización del inmovilizado")/1000 -> -19.22535 | V27: =VLOOKUP(T27,'P&L Mensualitzada 2025'!$A$5:$N$25,$U$5+1,0) -> -19.4712 | W27: =U27-V27 -> 0.24585 | X27: =+IF(IFERROR(U27/V27-1,"-")<300%,IFERROR(U27/V27-1,"-"),"n.a.") -> -0.01262634 | Y27: =VLOOKUP(T27,'Budget26 sin EI'!$B:$O,$U$5+1,0) -> -20.833333 | Z27: =U27-Y27 -> 1.607983 | AA27: =+IF(IFERROR(U27/Y27-1,"-")<300%,IFERROR(U27/Y27-1,"-"),"n.a.") -> -0.077183185 | AC27: D&A | AD27: =GETPIVOTDATA("dic-26 ",TABLA!$B$3,"Nivel 4","8.- Amortización del inmovilizado")/1000 -> -19.22535 | AE27: =VLOOKUP(AC27,'P&L Mensualitzada 2025'!$A$5:$N$25,$AD$5+1,0) -> -34.07237 | AF27: =AD27-AE27 -> 14.84702 | AG27: =+IF(IFERROR(AD27/AE27-1,"-")<300%,IFERROR(AD27/AE27-1,"-"),"n.a.") -> -0.43574955 | AH27: =VLOOKUP(AC27,'Budget26 sin EI'!$B:$O,$AD$5+1,0) -> -20.833333 | AI27: =AD27-AH27 -> 1.607983 | AJ27: =+IF(IFERROR(AD27/AH27-1,"-")<300%,IFERROR(AD27/AH27-1,"-"),"n.a.") -> -0.077183185 | AL27: D&A | AM27: =GETPIVOTDATA("Total 2026 ",TABLA!$B$3,"Nivel 4","8.- Amortización del inmovilizado")/1000 -> -229.67475 | AN27: =VLOOKUP(AL27,'P&L Mensualitzada 2025'!$A$5:$N$25,$AD$5+1,0) -> -34.07237 | AO27: =AM27-AN27 -> -195.60238 | AP27: =+IF(IFERROR(AM27/AN27-1,"-")<300%,IFERROR(AM27/AN27-1,"-"),"n.a.") -> n.a. | AQ27: =VLOOKUP(AL27,'Budget26 sin EI'!$B:$O,$AD$5+1,0) -> -20.833333 | AR27: =AM27-AQ27 -> -208.84142 | AS27: =+IF(IFERROR(AM27/AQ27-1,"-")<300%,IFERROR(AM27/AQ27-1,"-"),"n.a.") -> n.a.
B28: Other Gains/Losses | C28: =GETPIVOTDATA("sep-26 ",TABLA!$B$3,"Nivel 4","13.- Otros resultados")+GETPIVOTDATA("ago-26 ",TABLA!$B$3,"Nivel 4","11.- Deterioro y resultado por enajenaciones del inmovilizado")/1000 -> 0 | D28: =VLOOKUP(B28,'P&L Mensualitzada 2025'!$A$5:$N$25,$C$5+1,0) -> -0.04064 | E28: =C28-D28 -> 0.04064 | F28: n.a. | G28: =VLOOKUP(B28,'Budget26 sin EI'!$B:$O,$C$5+1,0) -> 0 | H28: =C28-G28 -> 0 | I28: =+IF(IFERROR(C28/G28-1,"-")<300%,IFERROR(C28/G28-1,"-"),"n.a.") -> n.a. | K28: Other Gains/Losses | L28: =GETPIVOTDATA("oct-26 ",TABLA!$B$3,"Nivel 4","13.- Otros resultados")+GETPIVOTDATA("ago-26 ",TABLA!$B$3,"Nivel 4","11.- Deterioro y resultado por enajenaciones del inmovilizado")/1000 -> 0 | M28: =VLOOKUP(K28,'P&L Mensualitzada 2025'!$A$5:$N$25,$L$5+1,0) -> 0.81001 | N28: =L28-M28 -> -0.81001 | O28: n.a. | P28: =VLOOKUP(K28,'Budget26 sin EI'!$B:$O,$L$5+1,0) -> 0 | Q28: =L28-P28 -> 0 | R28: =+IF(IFERROR(L28/P28-1,"-")<300%,IFERROR(L28/P28-1,"-"),"n.a.") -> n.a. | T28: Other Gains/Losses | U28: =GETPIVOTDATA("nov-26 ",TABLA!$B$3,"Nivel 4","13.- Otros resultados")+GETPIVOTDATA("ago-26 ",TABLA!$B$3,"Nivel 4","11.- Deterioro y resultado por enajenaciones del inmovilizado")/1000 -> 0 | V28: =VLOOKUP(T28,'P&L Mensualitzada 2025'!$A$5:$N$25,$U$5+1,0) -> 0.00443 | W28: =U28-V28 -> -0.00443 | X28: n.a. | Y28: =VLOOKUP(T28,'Budget26 sin EI'!$B:$O,$U$5+1,0) -> 0 | Z28: =U28-Y28 -> 0 | AA28: =+IF(IFERROR(U28/Y28-1,"-")<300%,IFERROR(U28/Y28-1,"-"),"n.a.") -> n.a. | AC28: Other Gains/Losses | AD28: =GETPIVOTDATA("dic-26 ",TABLA!$B$3,"Nivel 4","13.- Otros resultados")+GETPIVOTDATA("ago-26 ",TABLA!$B$3,"Nivel 4","11.- Deterioro y resultado por enajenaciones del inmovilizado")/1000 -> 0 | AE28: =VLOOKUP(AC28,'P&L Mensualitzada 2025'!$A$5:$N$25,$AD$5+1,0) -> 0.15045 | AF28: =AD28-AE28 -> -0.15045 | AG28: n.a. | AH28: =VLOOKUP(AC28,'Budget26 sin EI'!$B:$O,$AD$5+1,0) -> 0 | AI28: =AD28-AH28 -> 0 | AJ28: =+IF(IFERROR(AD28/AH28-1,"-")<300%,IFERROR(AD28/AH28-1,"-"),"n.a.") -> n.a. | AL28: Other Gains/Losses | AM28: =GETPIVOTDATA("Total 2026 ",TABLA!$B$3,"Nivel 4","13.- Otros resultados")/1000+GETPIVOTDATA("ago-26 ",TABLA!$B$3,"Nivel 4","11.- Deterioro y resultado por enajenaciones del inmovilizado")/1000 -> 3.99994 | AN28: =VLOOKUP(AL28,'P&L Mensualitzada 2025'!$A$5:$N$25,$AD$5+1,0) -> 0.15045 | AO28: =AM28-AN28 -> 3.84949 | AP28: n.a. | AQ28: =VLOOKUP(AL28,'Budget26 sin EI'!$B:$O,$AD$5+1,0) -> 0 | AR28: =AM28-AQ28 -> 3.99994 | AS28: =+IF(IFERROR(AM28/AQ28-1,"-")<300%,IFERROR(AM28/AQ28-1,"-"),"n.a.") -> n.a.
B29: Adjusted EBIT | C29: =C24+C27+C28 -> 136.5118 | D29: =D24+D27+D28 -> 369.07025 | E29: =C29-D29 -> -232.55845 | F29: =+IF(IFERROR(C29/D29-1,"-")<300%,IFERROR(C29/D29-1,"-"),"n.a.") -> -0.63011974 | G29: =G24+G27+G28 -> 358.8929 | H29: =C29-G29 -> -222.3811 | I29: =+IF(IFERROR(C29/G29-1,"-")<300%,IFERROR(C29/G29-1,"-"),"n.a.") -> -0.61963081 | K29: Adjusted EBIT | L29: =L24+L27+L28 -> 306.46071 | M29: =M24+M27+M28 -> -276.48446 | N29: =L29-M29 -> 582.94517 | O29: =+IF(IFERROR(L29/M29-1,"-")<300%,IFERROR(L29/M29-1,"-"),"n.a.") -> -2.1084193 | P29: =P24+P27+P28 -> 184.40572 | Q29: =L29-P29 -> 122.05499 | R29: =+IF(IFERROR(L29/P29-1,"-")<300%,IFERROR(L29/P29-1,"-"),"n.a.") -> 0.66188287 | T29: Adjusted EBIT | U29: =U24+U27+U28 -> 512.66607 | V29: =V24+V27+V28 -> 233.07388 | W29: =U29-V29 -> 279.59219 | X29: =+IF(IFERROR(U29/V29-1,"-")<300%,IFERROR(U29/V29-1,"-"),"n.a.") -> 1.1995861 | Y29: =Y24+Y27+Y28 -> 332.3661 | Z29: =U29-Y29 -> 180.29997 | AA29: =+IF(IFERROR(U29/Y29-1,"-")<300%,IFERROR(U29/Y29-1,"-"),"n.a.") -> 0.54247401 | AC29: Adjusted EBIT | AD29: =AD24+AD27+AD28 -> -34.57312 | AE29: =AE24+AE27+AE28 -> -265.73219 | AF29: =AD29-AE29 -> 231.15907 | AG29: =+IF(IFERROR(AD29/AE29-1,"-")<300%,IFERROR(AD29/AE29-1,"-"),"n.a.") -> -0.86989487 | AH29: =AH24+AH27+AH28 -> -74.854859 | AI29: =AD29-AH29 -> 40.281739 | AJ29: =+IF(IFERROR(AD29/AH29-1,"-")<300%,IFERROR(AD29/AH29-1,"-"),"n.a.") -> -0.53813125 | AL29: Adjusted EBIT | AM29: =AM24+AM27+AM28 -> 6150.5033 | AN29: =AN24+AN27+AN28 -> -265.73219 | AO29: =AM29-AN29 -> 6416.2355 | AP29: =+IF(IFERROR(AM29/AN29-1,"-")<300%,IFERROR(AM29/AN29-1,"-"),"n.a.") -> -24.145496 | AQ29: =AQ24+AQ27+AQ28 -> -74.854859 | AR29: =AM29-AQ29 -> 6225.3582 | AS29: =+IF(IFERROR(AM29/AQ29-1,"-")<300%,IFERROR(AM29/AQ29-1,"-"),"n.a.") -> -83.165718
B30: % EBIT Margin | C30: =C29/C10 -> 0.28258413 | D30: =D29/D10 -> 0.43826544 | G30: =G29/G10 -> 0.34960443 | K30: % EBIT Margin | L30: =L29/L10 -> 0.33601121 | M30: =M29/M10 -> -0.39521298 | P30: =P29/P10 -> 0.23092074 | T30: % EBIT Margin | U30: =U29/U10 -> 0.41839301 | V30: =V29/V10 -> 0.31088988 | Y30: =Y29/Y10 -> 0.32260942 | AC30: % EBIT Margin | AD30: =AD29/AD10 -> -0.03026339 | AE30: =AE29/AE10 -> -1.069319 | AH30: =AH29/AH10 -> -0.11342597 | AL30: % EBIT Margin | AM30: =AM29/AM10 -> 0.4051715 | AN30: =AN29/AN10 -> -1.069319 | AQ30: =AQ29/AQ10 -> -0.11342597

Sheet TABLA
B1: Periodo | C1: 2026
B3: Detalle sin Ajustar | C3: ene-26 | D3: feb-26 | E3: mar-26 | F3: abr-26 | G3: may-26 | H3: jun-26 | I3: jul-26 | J3: ago-26 | K3: sep-26 | L3: oct-26 | M3: nov-26 | N3: dic-26 | O3: Total 2026
B4: 1.- Importe neto de la cifra de negocios | C4: 983817.13 | D4: 1470428.1 | E4: 1533789.4 | F4: 1462146.3 | G4: 1925929.9 | H4: 1962261.8 | I4: 1290654.2 | J4: 788105.15 | K4: 483083.74 | L4: 912055.01 | M4: 1225321.8 | N4: 1142407.4 | O4: 15180000
B5: 2.- Variación de existencias | C5: -84878.08 | D5: 50005.57 | E5: 83552.77 | F5: 8645.2 | G5: -30291.1 | H5: -90104.87 | I5: -6292.63 | J5: 6734.64 | K5: 0 | L5: 0 | M5: 0 | N5: 0 | O5: -62628.5
B6: 4.- Aprovisionamientos | C6: -417787.47 | D6: -406242.73 | E6: -469252.7 | F6: -514848.29 | G6: -593981.24 | H6: -653453.72 | I6: -519022.4 | J6: -278854.87 | K6: -161790.96 | L6: -302101.36 | M6: -404423.28 | N6: -449145.33 | O6: -5170904.3
B7: 6.- Gastos de personal | C7: -111532.01 | D7: -142927.2 | E7: -146233.31 | F7: -130047.67 | G7: -134992.52 | H7: -145072.28 | I7: -153533.65 | J7: -152632.79 | K7: -152632.79 | L7: -152632.79 | M7: -152632.79 | N7: -431632.79 | O7: -2006502.6
B8: 5.- Otros ingresos de explotación | C8: 0 | D8: 0 | E8: 0 | F8: 750.75 | G8: 25140.75 | H8: 22977.6 | I8: 11027.24 | J8: 11429 | K8: 5286.2 | L8: 10013.67 | M8: 13461.83 | N8: 14533.94 | O8: 114620.98
B9: 7.- Otros gastos de explotación | C9: -103451.76 | D9: -62498.88 | E9: -110606.27 | F9: -107706.65 | G9: -123392.08 | H9: -175013.76 | I9: -161051.74 | J9: -130060.66 | K9: -121630.07 | L9: -141648.47 | M9: -149836.12 | N9: -291510.97 | O9: -1678407.4
B10: 11.- Deterioro y resultado por enajenaciones del inmovilizado | C10: 0 | D10: 0 | E10: 2000 | F10: 0 | G10: 0 | H10: 0 | I10: 0 | J10: 0 | K10: 0 | L10: 0 | M10: 0 | N10: 0 | O10: 2000
B11: 8.- Amortización del inmovilizado | C11: -19132.87 | D11: -19132.87 | E11: -18903.55 | F11: -18903.55 | G11: -19189.68 | H11: -19060.25 | I11: -19225.29 | J11: -19225.29 | K11: -19225.35 | L11: -19225.35 | M11: -19225.35 | N11: -19225.35 | O11: -229674.75
B12: 13.- Otros resultados | C12: 3065.27 | D12: 0.02 | E12: -0.14 | F12: 1024.26 | G12: -1.43 | H12: 0 | I12: -88.03 | J12: -0.01 | K12: 0 | L12: 0 | M12: 0 | N12: 0 | O12: 3999.94
B13: 15.- Gastos financieros | C13: -52.82 | D13: 0 | E13: -79.37 | F13: -24483.47 | G13: -38651.64 | H13: -78497.33 | I13: -32604.18 | J13: -19768.43 | K13: -12975.21 | L13: -24579.01 | M13: -33042.67 | N13: -35674.22 | O13: -300408.35
B14: 17.- Diferencias de cambio | C14: 0 | D14: 78.79 | E14: 15.51 | F14: 0 | G14: 2879.75 | H14: 1665.7 | I14: 604.76 | J14: 0 | K14: 0 | L14: 0 | M14: 0 | N14: 0 | O14: 5244.51
B15: 14.- Ingresos financieros | C15: 0 | D15: 0 | E15: 0 | F15: 0 | G15: 0 | H15: 4495.93 | I15: 0 | J15: 0 | K15: 0 | L15: 0 | M15: 0 | N15: 0 | O15: 4495.93
B16: Total general | C16: 250047.39 | D16: 889710.85 | E16: 874282.35 | F16: 676576.86 | G16: 1013450.7 | H16: 830198.85 | I16: 410468.31 | J16: 205726.74 | K16: 20115.56 | L16: 281881.7 | M16: 479623.4 | N16: -70247.34 | O16: 5861835.4
B17: EBITDA | C17: =+SUM(C4:C9) -> 266167.81 | D17: =+SUM(D4:D9) -> 908764.91 | E17: =+SUM(E4:E9) -> 891249.9 | F17: =+SUM(F4:F9) -> 718939.62 | G17: =+SUM(G4:G9) -> 1068413.7 | H17: =+SUM(H4:H9) -> 921594.8 | I17: =+SUM(I4:I9) -> 461781.05 | J17: =+SUM(J4:J9) -> 244720.47 | ... O17: =+SUM(O4:O9) -> 6376178.1
B18: EBITDA % | C18: =C17/C4 -> 0.27054602 | D18: =D17/D4 -> 0.61802742 | E18: =E17/E4 -> 0.5810771 | F18: =F17/F4 -> 0.49170157 | G18: =G17/G4 -> 0.55475213 | H18: =H17/H4 -> 0.46965944 | I18: =I17/I4 -> 0.35778835 | J18: =J17/J4 -> 0.31051754 | ... O18: =O17/O4 -> 0.42003808
N19: Check | O19: =SUM(C16:N16)-O16 -> 0

Sheet PL Mensual 2026
K2: =SUBTOTAL(9,K4:K215) -> 250047.39 | L2: =SUBTOTAL(9,L4:L215) -> 889710.85 | M2: =SUBTOTAL(9,M4:M215) -> 874282.35 | N2: =SUBTOTAL(9,N4:N215) -> 676576.86 | O2: =SUBTOTAL(9,O4:O2027) -> 1013450.7 | P2: =SUBTOTAL(9,P4:P2027) -> 830198.85 | Q2: =SUBTOTAL(9,Q4:Q2096) -> 410468.31 | R2: =SUBTOTAL(9,R4:R2015) -> 205726.74 | S2: =SUBTOTAL(9,S4:S215) -> 20115.56 | T2: =SUBTOTAL(9,T4:T215) -> 281881.7 | U2: =SUBTOTAL(9,U4:U215) -> 479623.4 | V2: =SUBTOTAL(9,V4:V215) -> -70247.34 | W2: =SUBTOTAL(9,W4:W2036) -> 5861835.4
B3: Periodo | C3: Empresa | D3: Nivel 1 | E3: Nivel 2 | F3: Nivel 3 | G3: Nivel 4 | H3: Nivel 5 | I3: Cuenta | J3: Grupo Ext Item | K3: 46023 | L3: 46054 | M3: 46082 | N3: 46113 | O3: 46143 | P3: 46174 | Q3: 46204 | R3: 46235 | S3: 46266 | T3: 46296 | U3: 46327 | V3: 46357 | W3: Total 2026
B4: 2026 | C4: Codiagro | D4: RESULTADO DEL EJERCICIO | E4: RESULTADO ANTES DE IMPUESTOS | F4: RESULTADO DE LA EXPLOTACION | G4: 1.- Importe neto de la cifra de negocios | H4: (700) Ventas | I4: 700000000 - Ventas de mercaderías | J4: - | K4: 993280.49 | L4: 1607538 | M4: 1536177.9 | N4: 1217250.4 | O4: 2029267 | P4: 2009948.7 | Q4: 1288443.6 | R4: 802410.56 | S4: 480563.3 | T4: 910333.55 | U4: 1223802.8 | V4: 1321267.5 | W4: 15420284 | X4: Presupuesto de Ventas 2026 ajustado para cuadrar la Cifra Neta de Negocios en 15.180.000,00 € exactos tras considerar la provisión anual de rappels (333k€) y gestión de envases.
B5: 2026 | C5: Codiagro | D5: RESULTADO DEL EJERCICIO | E5: RESULTADO ANTES DE IMPUESTOS | F5: RESULTADO DE LA EXPLOTACION | G5: 1.- Importe neto de la cifra de negocios | H5: (700) Ventas | I5: 700000001 - VENTA MERCADERIAS POR ANTICIPO | J5: - | K5: 0 | L5: 0 | M5: 0 | N5: 106250.17 | O5: -106250.17 | P5: - | Q5: 0 | R5: 0 | S5: 0 | T5: 0 | U5: 0 | V5: 0 | W5: 0 | X5: Cuenta sin saldo en el ejercicio. Sin previsión de movimientos.
B6: 2026 | C6: Codiagro | D6: RESULTADO DEL EJERCICIO | E6: RESULTADO ANTES DE IMPUESTOS | F6: RESULTADO DE LA EXPLOTACION | G6: 1.- Importe neto de la cifra de negocios | H6: (700) Ventas | I6: 700000624 - VENTA POR TRANSP. REP. AL CLIENTE | J6: - | K6: 17921.38 | L6: 12025.38 | M6: 8455.55 | N6: 0 | O6: 0 | P6: - | Q6: 0 | R6: 0 | S6: 0 | T6: 0 | U6: 0 | V6: 0 | W6: 38402.31 | X6: Partida puntual / no recurrente en el periodo enero-agosto. Sin movimiento adicional proyectado para el último cuatrimestre.
B7: 2026 | C7: Codiagro | D7: RESULTADO DEL EJERCICIO | E7: RESULTADO ANTES DE IMPUESTOS | F7: RESULTADO DE LA EXPLOTACION | G7: 5.- Otros ingresos de explotación | H7: (700) Ventas | I7: 700001624 - VENTA POR TRANSPORTE REP. AL CLIENTE DEFINITIVO | J7: - | K7: 0 | L7: 0 | M7: 0 | N7: 750.75 | O7: 25140.75 | P7: 22977.6 | Q7: 11027.24 | R7: 11429 | S7: 5286.2 | T7: 10013.67 | U7: 13461.83 | V7: 14533.94 | W7: 114620.98 | X7: Coste/Ingreso variable según volumen de ventas y fletes repercutidos al cliente (ratio histórico 1,10% s/ventas) + inflación de fletes.
B8: 2026 | C8: Codiagro | D8: RESULTADO DEL EJERCICIO | E8: RESULTADO ANTES DE IMPUESTOS | F8: RESULTADO DE LA EXPLOTACION | G8: 1.- Importe neto de la cifra de negocios | H8: (700) Ventas | I8: 700000769 - INGRESOS POR RETRASOS DE COBRO Y ACTUALIZACION | J8: - | K8: 5635.79 | L8: 202.81 | M8: 178.05 | N8: 0 | O8: - | P8: - | Q8: 0 | R8: 0 | S8: 0 | T8: 0 | U8: 0 | V8: 0 | W8: 6016.65 | X8: Partida puntual / no recurrente en el periodo enero-agosto. Sin movimiento adicional proyectado para el último cuatrimestre.
B9: 2026 | C9: Codiagro | D9: RESULTADO DEL EJERCICIO | E9: RESULTADO ANTES DE IMPUESTOS | F9: RESULTADO FINANCIERO | G9: 14.- Ingresos financieros | H9: (700) Ventas | I9: 700000769 - INGRESOS POR RETRASOS DE COBRO Y ACTUALIZACION | J9: - | K9: 0 | L9: 0 | M9: 0 | N9: 0 | O9: - | P9: - | Q9: 0 | R9: 0 | S9: 0 | T9: 0 | U9: 0 | V9: 0 | W9: 0 | X9: Cuenta sin saldo en el ejercicio. Sin previsión de movimientos.
B10: 2026 | C10: Codiagro | D10: RESULTADO DEL EJERCICIO | E10: RESULTADO ANTES DE IMPUESTOS | F10: RESULTADO DE LA EXPLOTACION | G10: 1.- Importe neto de la cifra de negocios | H10: (702) Ventas de productos semiterminados | I10: 702000000 - Ventas de productos semiterminados | J10: - | K10: 0 | L10: 0 | M10: 0 | N10: 51164.86 | R10: 0 | S10: 0 | T10: 0 | U10: 0 | V10: 0 | W10: 51164.86 | X10: Partida puntual / no recurrente en el periodo enero-agosto. Sin movimiento adicional proyectado para el último cuatrimestre.
B11: 2026 | C11: Codiagro | D11: RESULTADO DEL EJERCICIO | E11: RESULTADO ANTES DE IMPUESTOS | F11: RESULTADO DE LA EXPLOTACION | G11: 1.- Importe neto de la cifra de negocios | H11: (703) Ventas por subproductos y residuos | I11: 703000000 - Ventas de subproductos y residuos | J11: - | K11: 0 | L11: 0 | M11: 26.26 | N11: 0 | O11: - | P11: - | Q11: 0 | R11: 0 | S11: 0 | T11: 0 | U11: 0 | V11: 0 | W11: 26.26 | X11: Partida puntual / no recurrente en el periodo enero-agosto. Sin movimiento adicional proyectado para el último cuatrimestre.
B12: 2026 | C12: Codiagro | D12: RESULTADO DEL EJERCICIO | E12: RESULTADO ANTES DE IMPUESTOS | F12: RESULTADO DE LA EXPLOTACION | G12: 1.- Importe neto de la cifra de negocios | H12: (704) Venta de envases y embalajes | I12: 704000000 - Ventas de envases y embalajes | J12: - | K12: 0 | L12: 4500 | M12: 13500 | N12: 35533.66 | O12: 0 | P12: 0 | Q12: 0 | R12: 0 | S12: 0 | T12: 0 | U12: 0 | V12: 0 | W12: 53533.66 | X12: Partida puntual / no recurrente en el periodo enero-agosto. Sin movimiento adicional proyectado para el último cuatrimestre.
B13: 2026 | C13: Codiagro | D13: RESULTADO DEL EJERCICIO | E13: RESULTADO ANTES DE IMPUESTOS | F13: RESULTADO DE LA EXPLOTACION | G13: 1.- Importe neto de la cifra de negocios | H13: (705) Prestación de servicios | I13: 705000000 - Prestaciones de servicios | J13: - | K13: 0 | L13: 0 | M13: 0 | N13: 48700.8 | R13: 0 | S13: 0 | T13: 0 | U13: 0 | V13: 0 | W13: 48700.8 | X13: Partida puntual / no recurrente en el periodo enero-agosto. Sin movimiento adicional proyectado para el último cuatrimestre.
B14: 2026 | C14: Codiagro | D14: RESULTADO DEL EJERCICIO | E14: RESULTADO ANTES DE IMPUESTOS | F14: RESULTADO DE LA EXPLOTACION | G14: 1.- Importe neto de la cifra de negocios | H14: (705) Prestación de servicios | I14: 705000001 - INGRESO POR GESTIÓN DE ENVASES | J14: - | K14: 1295.63 | L14: 6097.12 | M14: -1420.15 | N14: 3246.37 | O14: 2913.09 | P14: 2313.16 | Q14: 2210.59 | R14: 1694.59 | S14: 2520.44 | T14: 1721.46 | U14: 1519.01 | V14: 5378.56 | W14: 29489.87 | X14: Modelo de gestión de envases (Envases y transportes.xlsx): histórico 2025 ajustado por +12,35% en unidades y +4,5% en tarifas (factor 1,1685).
B15: 2026 | C15: Codiagro | D15: RESULTADO DEL EJERCICIO | E15: RESULTADO ANTES DE IMPUESTOS | F15: RESULTADO DE LA EXPLOTACION | G15: 1.- Importe neto de la cifra de negocios | H15: (706) Dto. s/vtas p.p. | I15: 706000000 - Dtos. ventas por pronto pago mercaderías | J15: - | K15: -34316.16 | L15: -77173.86 | M15: -22849.78 | N15: 0 | O15: 0 | P15: - | Q15: 0 | R15: 0 | S15: 0 | T15: 0 | U15: 0 | V15: 0 | W15: -134339.8 | X15: Partida puntual / no recurrente en el periodo enero-agosto. Sin movimiento adicional proyectado para el último cuatrimestre.
B16: 2026 | C16: Codiagro | D16: RESULTADO DEL EJERCICIO | E16: RESULTADO ANTES DE IMPUESTOS | F16: RESULTADO DE LA EXPLOTACION | G16: 1.- Importe neto de la cifra de negocios | H16: (709) Bonificaciones s/ventas | I16: 709000000 - «Rappels» ventas de mercaderías | J16: - | K16: 0 | L16: 0 | M16: -278.38 | N16: 0 | O16: - | P16: - | Q16: 0 | R16: 0 | S16: 0 | T16: 0 | U16: 0 | V16: 0 | W16: -278.38 | X16: Partida puntual / no recurrente en el periodo enero-agosto. Sin movimiento adicional proyectado para el último cuatrimestre.
B17: 2026 | C17: Codiagro | D17: RESULTADO DEL EJERCICIO | E17: RESULTADO ANTES DE IMPUESTOS | F17: RESULTADO DE LA EXPLOTACION | G17: 1.- Importe neto de la cifra de negocios | H17: (709) Bonificaciones s/ventas | I17: 709000001 - PROVISION RAPPELS | J17: - | K17: 0 | L17: -82761.28 | M17: 0 | N17: 0 | O17: - | P17: -50000 | Q17: 0 | R17: -16000 | S17: 0 | T17: 0 | U17: 0 | V17: -184238.72 | W17: -333000 | X17: Provisión por rappels comerciales ajustada para alcanzar el objetivo anual exacto de 333.000,00 € (-148.761,28 € reales Ene-Ago + -184.238,72 € provisión Dic).
B18: 2026 | C18: Codiagro | D18: RESULTADO DEL EJERCICIO | E18: RESULTADO ANTES DE IMPUESTOS | F18: RESULTADO DE LA EXPLOTACION | G18: 11.- Deterioro y resultado por enajenaciones del inmovilizado | H18: (771) Beneficios procedentes IM | I18: 771000000 - Beneficios del inmovilizado material | J18: - | K18: 0 | L18: 0 | M18: 2000 | N18: 0 | O18: - | P18: - | Q18: 0 | R18: 0 | S18: 0 | T18: 0 | U18: 0 | V18: 0 | W18: 2000 | X18: Partida puntual / no recurrente en el periodo enero-agosto. Sin movimiento adicional proyectado para el último cuatrimestre.
B19: 2026 | C19: Codiagro | D19: RESULTADO DEL EJERCICIO | E19: RESULTADO ANTES DE IMPUESTOS | F19: RESULTADO DE LA EXPLOTACION | G19: 13.- Otros resultados | H19: (678) Gastos excepcionales PGC 2008 | I19: 678000000 - Gastos excepcionales | J19: - | K19: -0.2 | L19: 0 | M19: -0.14 | N19: -93.18 | O19: -1.43 | P19: - | Q19: -88.03 | R19: -0.02 | S19: 0 | T19: 0 | U19: 0 | V19: 0 | W19: -183 | X19: Partida puntual / no recurrente en el periodo enero-agosto. Sin movimiento adicional proyectado para el último cuatrimestre.
B20: 2026 | C20: Codiagro | D20: RESULTADO DEL EJERCICIO | E20: RESULTADO ANTES DE IMPUESTOS | F20: RESULTADO DE LA EXPLOTACION | G20: 13.- Otros resultados | H20: (778) Ingresos excepcionales PGC 2008 | I20: 778000000 - Ingresos excepcionales | J20: - | K20: 3065.47 | L20: 0.02 | M20: 0 | N20: 1117.44 | O20: - | P20: - | Q20: 0 | R20: 0.01 | S20: 0 | T20: 0 | U20: 0 | V20: 0 | W20: 4182.94 | X20: Partida puntual / no recurrente en el periodo enero-agosto. Sin movimiento adicional proyectado para el último cuatrimestre.
B21: 2026 | C21: Codiagro | D21: RESULTADO DEL EJERCICIO | E21: RESULTADO ANTES DE IMPUESTOS | F21: RESULTADO DE LA EXPLOTACION | G21: 2.- Variación de existencias | H21: (711) Variación de existencias de productos semiterminados | I21: 711000000 - Variación existencias de prod. semiterminados | J21: - | K21: 1191.85 | L21: -20400.17 | M21: -3284.66 | N21: 15429.21 | O21: 4436.02 | P21: -12387.42 | Q21: -48438.2 | R21: 27557.62 | S21: 0 | T21: 0 | U21: 0 | V21: 0 | W21: -35895.75 | X21: Ajuste previsional de variación de existencias para regularización de inventarios a cierre de ejercicio.
B22: 2026 | C22: Codiagro | D22: RESULTADO DEL EJERCICIO | E22: RESULTADO ANTES DE IMPUESTOS | F22: RESULTADO DE LA EXPLOTACION | G22: 2.- Variación de existencias | H22: (712) Variación de existencias producto terminado | I22: 712000000 - Variación existencias de prod. terminados | J22: - | K22: -86069.93 | L22: 70405.74 | M22: 86837.43 | N22: -6784.01 | O22: -34727.12 | P22: -77717.45 | Q22: 42145.57 | R22: -20822.98 | S22: 0 | T22: 0 | U22: 0 | V22: 0 | W22: -26732.75 | X22: Ajuste previsional de variación de existencias para regularización de inventarios a cierre de ejercicio.
B23: 2026 | C23: Codiagro | D23: RESULTADO DEL EJERCICIO | E23: RESULTADO ANTES DE IMPUESTOS | F23: RESULTADO DE LA EXPLOTACION | G23: 4.- Aprovisionamientos | H23: (601) Compras de materias primas | I23: 601000000 - Compras de materias primas | J23: - | K23: -372155.73 | L23: -457091.9 | M23: -457890.87 | N23: -391545.47 | O23: -423709.63 | P23: -393937.01 | Q23: -362186.44 | R23: -189242.44 | S23: -124233.67 | T23: -235336.47 | U23: -316373.51 | V23: -341569.79 | W23: -4065272.9 | X23: Coste variable directo: volumen según presupuesto ajustado (ratio histórico 25,85% s/ventas sin incremento de inflación en 2026; la inflación del +4,5% se aplica solo en 2027).
B24: 2026 | C24: Codiagro | D24: RESULTADO DEL EJERCICIO | E24: RESULTADO ANTES DE IMPUESTOS | F24: RESULTADO DE LA EXPLOTACION | G24: 4.- Aprovisionamientos | H24: (602) Compras de otros aprovisionamientos | I24: 602000001 - COMPRA DE ENVASES Y EMBALAJES | J24: - | K24: -103817.84 | L24: -62983.5 | M24: -55812.27 | N24: -92652.34 | O24: -30193.15 | P24: -119472.15 | Q24: -145291.05 | R24: -8606.04 | S24: -25894.98 | T24: -49053 | U24: -65944.18 | V24: -71196.03 | W24: -830916.53 | X24: Coste variable por envases y embalajes: incluye saldo de junio traspasado de la 602000000 (-30.306,17 €). Estimación unificada según ratio histórico 5,39% s/ventas ajustadas (sin inflación en 2026; aplicable en 2027).
B25: 2026 | C25: Codiagro | D25: RESULTADO DEL EJERCICIO | E25: RESULTADO ANTES DE IMPUESTOS | F25: RESULTADO DE LA EXPLOTACION | G25: 4.- Aprovisionamientos | H25: (602) Compras de otros aprovisionamientos | I25: 602000000 - Compras de otros aprovisionamientos | J25: - | P25: 0 | Q25: 0 | R25: 0 | S25: 0 | T25: 0 | U25: 0 | V25: 0 | W25: 0 | X25: Cuenta fusionada con 602000001. Su saldo real de junio (-30.306,17 €) se ha traspasado a la 602000001. Sin previsión en sep-dic ni en 2027.
B26: 2026 | C26: Codiagro | D26: RESULTADO DEL EJERCICIO | E26: RESULTADO ANTES DE IMPUESTOS | F26: RESULTADO DE LA EXPLOTACION | G26: 4.- Aprovisionamientos | H26: (602) Compras de otros aprovisionamientos | I26: 602000002 - COMPRA DE ETIQUETAS | J26: - | K26: -12617.31 | L26: -5458.67 | M26: -15267.33 | N26: -9307.32 | O26: -2784.91 | P26: -5867.49 | Q26: -10270.19 | R26: -2886.68 | S26: -2625.86 | T26: -4974.16 | U26: -6687 | V26: -7219.56 | W26: -85966.48 | X26: Coste variable de etiquetas: ratio s/ventas ajustadas sin ajuste de precios de imprenta por inflación en 2026 (solo en 2027).
B27: 2026 | C27: Codiagro | D27: RESULTADO DEL EJERCICIO | E27: RESULTADO ANTES DE IMPUESTOS | F27: RESULTADO DE LA EXPLOTACION | G27: 4.- Aprovisionamientos | H27: (602) Compras de otros aprovisionamientos | I27: 602000003 - COMPRA DE PALETS | J27: - | K27: -7425.6 | L27: -3712.8 | M27: -4331.6 | N27: -12608.05 | O27: -17326.4 | P27: -12994.8 | Q27: -4331.6 | R27: -4331.6 | S27: -2731.63 | T27: -5174.53 | U27: -6956.35 | V27: -7510.36 | W27: -89435.32 | X27: Coste variable de palets: ratio s/ventas ajustadas sin inflación de suministros logísticos en 2026 (aplicable en 2027).
B28: 2026 | C28: Codiagro | D28: RESULTADO DEL EJERCICIO | E28: RESULTADO ANTES DE IMPUESTOS | F28: RESULTADO DE LA EXPLOTACION | G28: 4.- Aprovisionamientos | H28: (602) Compras de otros aprovisionamientos | I28: 602000004 - COMPRA MATERIAL DE LIMPIEZA | J28: - | K28: -131.92 | L28: 0 | M28: 0 | N28: 0 | O28: - | P28: - | Q28: 0 | R28: 0 | S28: -131.92 | T28: -131.92 | U28: -131.92 | V28: -131.92 | W28: -659.6 | X28: Coste operativo menor de planta: proyección basada en el promedio mensual histórico de reposición.
B29: 2026 | C29: Codiagro | D29: RESULTADO DEL EJERCICIO | E29: RESULTADO ANTES DE IMPUESTOS | F29: RESULTADO DE LA EXPLOTACION | G29: 4.- Aprovisionamientos | H29: (602) Compras de otros aprovisionamientos | I29: 602000005 - COMPRA MATERIAL DE OFICINA | J29: - | K29: -95.3 | L29: -136 | M29: 0 | N29: -380.75 | O29: - | P29: - | Q29: 0 | R29: 0 | S29: -204.02 | T29: -204.02 | U29: -204.02 | V29: -204.02 | W29: -1428.13 | X29: Coste operativo menor de planta: proyección basada en el promedio mensual histórico de reposición.
B30: 2026 | C30: Codiagro | D30: RESULTADO DEL EJERCICIO | E30: RESULTADO ANTES DE IMPUESTOS | F30: RESULTADO DE LA EXPLOTACION | G30: 4.- Aprovisionamientos | H30: (602) Compras de otros aprovisionamientos | I30: 602000006 - COMPRA TAPONES DE ENVASES | J30: - | K30: -3578.65 | L30: 0 | M30: -5949 | N30: -5353 | O30: - | P30: -3337.38 | Q30: -5826.6 | R30: -1108.8 | S30: -1071.66 | T30: -2030.04 | U30: -2729.08 | V30: -2946.43 | W30: -33930.64 | X30: Coste variable directamente proporcional al número de unidades/tapones envasados (0,22% s/ventas ajustadas).
B31: 2026 | C31: Codiagro | D31: RESULTADO DEL EJERCICIO | E31: RESULTADO ANTES DE IMPUESTOS | F31: RESULTADO DE LA EXPLOTACION | G31: 4.- Aprovisionamientos | H31: (602) Compras de otros aprovisionamientos | I31: 602000007 - COMPRAS LABORATORIO | J31: - | K31: 0 | L31: 0 | M31: 0 | N31: 0 | O31: 0 | P31: - | Q31: 0 | R31: 0 | S31: 0 | T31: 0 | U31: 0 | V31: 0 | W31: 0 | X31: Cuenta inactiva / sin saldo en el ejercicio. Sin previsión de movimientos.
B32: 2026 | C32: Codiagro | D32: RESULTADO DEL EJERCICIO | E32: RESULTADO ANTES DE IMPUESTOS | F32: RESULTADO DE LA EXPLOTACION | G32: 4.- Aprovisionamientos | H32: (602) Compras de otros aprovisionamientos | I32: 602000008 - RESPUESTOS PLANTA | J32: - | K32: 0 | L32: 0 | M32: 0 | N32: 0 | O32: 0 | P32: - | Q32: 0 | R32: 0 | S32: 0 | T32: 0 | U32: 0 | V32: 0 | W32: 0 | X32: Cuenta inactiva / sin saldo en el ejercicio. Sin previsión de movimientos.
B33: 2026 | C33: Codiagro | D33: RESULTADO DEL EJERCICIO | E33: RESULTADO ANTES DE IMPUESTOS | F33: RESULTADO DE LA EXPLOTACION | G33: 4.- Aprovisionamientos | H33: (602) Compras de otros aprovisionamientos | I33: 602000010 - COMPRA RIBBON | J33: - | K33: 0 | L33: 0 | M33: 0 | N33: 0 | O33: 0 | P33: - | Q33: 0 | R33: 0 | S33: 0 | T33: 0 | U33: 0 | V33: 0 | W33: 0 | X33: Cuenta inactiva / sin saldo en el ejercicio. Sin previsión de movimientos.
B34: 2026 | C34: Codiagro | D34: RESULTADO DEL EJERCICIO | E34: RESULTADO ANTES DE IMPUESTOS | F34: RESULTADO DE LA EXPLOTACION | G34: 4.- Aprovisionamientos | H34: (602) Compras de otros aprovisionamientos | I34: 602000011 - COMPRAS VARIAS PLANTA | J34: - | K34: 0 | L34: -1575 | M34: 0 | N34: 0 | O34: - | P34: -1735.41 | Q34: -175.92 | R34: -371.23 | S34: -964.39 | T34: -964.39 | U34: -964.39 | V34: -964.39 | W34: -7715.12 | X34: Coste operativo menor de planta: proyección basada en el promedio mensual histórico de reposición.
B35: 2026 | C35: Codiagro | D35: RESULTADO DEL EJERCICIO | E35: RESULTADO ANTES DE IMPUESTOS | F35: RESULTADO DE LA EXPLOTACION | G35: 4.- Aprovisionamientos | H35: (602) Compras de otros aprovisionamientos | I35: 602000012 - REPUESTOS INFORMATICOS | J35: - | K35: 0 | L35: -1887.21 | M35: 0 | N35: 0 | O35: - | P35: - | Q35: -1232.05 | R35: 0 | S35: -1559.63 | T35: -1559.63 | U35: -1559.63 | V35: -1559.63 | W35: -9357.78 | X35: Coste operativo menor de planta: proyección basada en el promedio mensual histórico de reposición.
B36: 2026 | C36: Codiagro | D36: RESULTADO DEL EJERCICIO | E36: RESULTADO ANTES DE IMPUESTOS | F36: RESULTADO DE LA EXPLOTACION | G36: 4.- Aprovisionamientos | H36: (602) Compras de otros aprovisionamientos | I36: 602000013 - COMPRA TINTA INPRESORA ETIQUETAS | J36: - | K36: -157 | L36: -2350.16 | M36: 0 | N36: -2676.19 | O36: -480.84 | P36: -2604.97 | Q36: -2809.41 | R36: -2557.66 | S36: -2190 | T36: -2490 | U36: -2690 | V36: -2690 | W36: -23696.23 | X36: Coste semi-variable de consumibles de marcaje y codificación en planta vinculado al volumen de producción envasado.
B37: 2026 | C37: Codiagro | D37: RESULTADO DEL EJERCICIO | E37: RESULTADO ANTES DE IMPUESTOS | F37: RESULTADO DE LA EXPLOTACION | G37: 4.- Aprovisionamientos | H37: (602) Compras de otros aprovisionamientos | I37: 602000100 - ENVASES Y EMBALAJES A DEVOLVER | J37: - | K37: -1200.4 | L37: -562 | M37: -363 | N37: 67 | O37: 1124 | P37: -1708 | Q37: 1360 | R37: 0 | S37: -183.2 | T37: -183.2 | U37: -183.2 | V37: -183.2 | W37: -2015.2 | X37: Coste operativo menor de planta: proyección basada en el promedio mensual histórico de reposición.
B38: 2026 | C38: Codiagro | D38: RESULTADO DEL EJERCICIO | E38: RESULTADO ANTES DE IMPUESTOS | F38: RESULTADO DE LA EXPLOTACION | G38: 4.- Aprovisionamientos | H38: (607) Trabajos realizados por otras empresas | I38: 607000000 - Trabajos realizados por otras empresas | J38: - | K38: -4010 | L38: -8438.96 | M38: -10901.61 | N38: -20866.93 | O38: -3540 | P38: 0.72 | Q38: -3900 | R38: -6131.31 | S38: 0 | T38: 0 | U38: 0 | V38: -7970 | W38: -65758.09 | X38: Coste variable de subcontratación fabril: eliminadas previsiones de sep a nov, dejando únicamente diciembre (-7.970,00 €) por refuerzo a cierre de ejercicio según indicación.
B39: 2026 | C39: Codiagro | D39: RESULTADO DEL EJERCICIO | E39: RESULTADO ANTES DE IMPUESTOS | F39: RESULTADO DE LA EXPLOTACION | G39: 4.- Aprovisionamientos | H39: (611) Variación de existencias de materias primas | I39: 611000000 - Variación de existencias de materias primas | J39: - | K39: 25970.74 | L39: 149437.84 | M39: 81262.98 | N39: -23562.66 | O39: -43504.89 | P39: -145710 | Q39: 649.67 | R39: -59037.03 | S39: 0 | T39: 0 | U39: 0 | V39: -15000 | W39: -29493.35 | X39: Ajuste previsional de variación de existencias para regularización de inventarios a cierre de ejercicio.
B40: 2026 | C40: Codiagro | D40: RESULTADO DEL EJERCICIO | E40: RESULTADO ANTES DE IMPUESTOS | F40: RESULTADO DE LA EXPLOTACION | G40: 4.- Aprovisionamientos | H40: (612) Variación de existencias envases/etiquetas | I40: 612000000 - Variación de existencias otros aprovisionamientos | J40: - | K40: 61431.54 | L40: -11484.37 | M40: 0 | N40: 44037.42 | O40: -73565.42 | P40: 33912.77 | Q40: 14991.19 | R40: -4582.08 | S40: 0 | T40: 0 | U40: 0 | V40: 10000 | W40: 74741.05 | X40: Ajuste previsional de variación de existencias para regularización de inventarios a cierre de ejercicio.
B41: 2026 | C41: Codiagro | D41: RESULTADO DEL EJERCICIO | E41: RESULTADO ANTES DE IMPUESTOS | F41: RESULTADO DE LA EXPLOTACION | G41: 5.- Otros ingresos de explotación | H41: (759) Otros ingresos de gestión | I41: 759000000 - Ingresos por servicios diversos | J41: - | K41: 0 | L41: 0 | M41: 0 | N41: 0 | O41: 0 | P41: - | Q41: 0 | R41: 0 | S41: 0 | T41: 0 | U41: 0 | V41: 0 | W41: 0 | X41: Cuenta inactiva / sin saldo en el ejercicio. Sin previsión de movimientos.
B42: 2026 | C42: Codiagro | D42: RESULTADO DEL EJERCICIO | E42: RESULTADO ANTES DE IMPUESTOS | F42: RESULTADO DE LA EXPLOTACION | G42: 6.- Gastos de personal | H42: (640) Sueldos y salarios | I42: 640000000 - Sueldos y salarios | J42: - | K42: -84814.92 | L42: -115852.5 | M42: -111568.08 | N42: -100687.82 | O42: -104048.18 | P42: -114103.58 | Q42: -121813.59 | R42: -128060.74 | S42: -128060.74 | T42: -128060.74 | U42: -128060.74 | V42: -407060.74 | W42: -1672192.4 | X42: Base salarial mensual fija igual a agosto (-128.060,74 €/mes) + 279.000,00 € adicionales en diciembre por devengo de Paga Extraordinaria de Navidad e incentivos anuales.
B43: 2026 | C43: Codiagro | D43: RESULTADO DEL EJERCICIO | E43: RESULTADO ANTES DE IMPUESTOS | F43: RESULTADO DE LA EXPLOTACION | G43: 6.- Gastos de personal | H43: (642) Seguridad social a cargo empresa | I43: 642000000 - Seguridad Social a cargo empresa | J43: - | K43: -26717.09 | L43: -27074.7 | M43: -32042.23 | N43: -29359.85 | O43: -30856.34 | P43: -30968.7 | Q43: -31720.06 | R43: -24572.05 | S43: -24572.05 | T43: -24572.05 | U43: -24572.05 | V43: -24572.05 | W43: -331599.22 | X43: Cotizaciones a la Seguridad Social mensuales fijas iguales a agosto (-24.572,05 €/mes).
B44: 2026 | C44: Codiagro | D44: RESULTADO DEL EJERCICIO | E44: RESULTADO ANTES DE IMPUESTOS | F44: RESULTADO DE LA EXPLOTACION | G44: 6.- Gastos de personal | H44: (649) Otros gastos sociales | I44: 649000000 - Otros gastos sociales | J44: - | K44: 0 | L44: 0 | M44: 0 | N44: 0 | O44: 0 | P44: - | Q44: 0 | R44: 0 | S44: 0 | T44: 0 | U44: 0 | V44: 0 | W44: 0 | X44: Cuenta inactiva / sin saldo en el ejercicio. Sin previsión de movimientos.
B45: 2026 | C45: Codiagro | D45: RESULTADO DEL EJERCICIO | E45: RESULTADO ANTES DE IMPUESTOS | F45: RESULTADO DE LA EXPLOTACION | G45: 6.- Gastos de personal | H45: (649) Otros gastos sociales | I45: 649000001 - GASTOS COMERCIALES NIEVES RUIZ | J45: - | K45: 0 | L45: 0 | M45: 0 | N45: 0 | O45: 0 | P45: - | Q45: 0 | R45: 0 | S45: 0 | T45: 0 | U45: 0 | V45: 0 | W45: 0 | X45: Cuenta inactiva / sin saldo en el ejercicio. Sin previsión de movimientos.
B46: 2026 | C46: Codiagro | D46: RESULTADO DEL EJERCICIO | E46: RESULTADO ANTES DE IMPUESTOS | F46: RESULTADO DE LA EXPLOTACION | G46: 6.- Gastos de personal | H46: (649) Otros gastos sociales | I46: 649000002 - GASTOS EMPR. ANTONIO ANDREU | J46: - | K46: 0 | L46: 0 | M46: 0 | N46: 0 | O46: 0 | P46: - | Q46: 0 | R46: 0 | S46: 0 | T46: 0 | U46: 0 | V46: 0 | W46: 0 | X46: Cuenta inactiva / sin saldo en el ejercicio. Sin previsión de movimientos.
B47: 2026 | C47: Codiagro | D47: RESULTADO DEL EJERCICIO | E47: RESULTADO ANTES DE IMPUESTOS | F47: RESULTADO DE LA EXPLOTACION | G47: 6.- Gastos de personal | H47: (649) Otros gastos sociales | I47: 649000004 - GASTOS COMERCIALES RICARDO PEREZ | J47: - | K47: 0 | L47: 0 | M47: 0 | N47: 0 | O47: 0 | P47: - | Q47: 0 | R47: 0 | S47: 0 | T47: 0 | U47: 0 | V47: 0 | W47: 0 | X47: Cuenta inactiva / sin saldo en el ejercicio. Sin previsión de movimientos.
B48: 2026 | C48: Codiagro | D48: RESULTADO DEL EJERCICIO | E48: RESULTADO ANTES DE IMPUESTOS | F48: RESULTADO DE LA EXPLOTACION | G48: 6.- Gastos de personal | H48: (649) Otros gastos sociales | I48: 649000007 - GASTOS COMERCIALES J.PAREDES | J48: - | K48: 0 | L48: 0 | M48: 0 | N48: 0 | O48: 0 | P48: - | Q48: 0 | R48: 0 | S48: 0 | T48: 0 | U48: 0 | V48: 0 | W48: 0 | X48: Cuenta inactiva / sin saldo en el ejercicio. Sin previsión de movimientos.
B49: 2026 | C49: Codiagro | D49: RESULTADO DEL EJERCICIO | E49: RESULTADO ANTES DE IMPUESTOS | F49: RESULTADO DE LA EXPLOTACION | G49: 6.- Gastos de personal | H49: (649) Otros gastos sociales | I49: 649000009 - GASTOS COMERCIALES J.A. GARCIA | J49: - | K49: 0 | L49: 0 | M49: 0 | N49: 0 | O49: 0 | P49: - | Q49: 0 | R49: 0 | S49: 0 | T49: 0 | U49: 0 | V49: 0 | W49: 0 | X49: Cuenta inactiva / sin saldo en el ejercicio. Sin previsión de movimientos.
B50: 2026 | C50: Codiagro | D50: RESULTADO DEL EJERCICIO | E50: RESULTADO ANTES DE IMPUESTOS | F50: RESULTADO DE LA EXPLOTACION | G50: 6.- Gastos de personal | H50: (649) Otros gastos sociales | I50: 649000010 - GASTOS EMP. CURRO | J50: - | K50: 0 | L50: 0 | M50: 0 | N50: 0 | O50: 0 | P50: - | Q50: 0 | R50: 0 | S50: 0 | T50: 0 | U50: 0 | V50: 0 | W50: 0 | X50: Cuenta inactiva / sin saldo en el ejercicio. Sin previsión de movimientos.
B51: 2026 | C51: Codiagro | D51: RESULTADO DEL EJERCICIO | E51: RESULTADO ANTES DE IMPUESTOS | F51: RESULTADO DE LA EXPLOTACION | G51: 6.- Gastos de personal | H51: (649) Otros gastos sociales | I51: 649000012 - GASTOS COMERCIALES IRENE GARCIA | J51: - | K51: 0 | L51: 0 | M51: 0 | N51: 0 | O51: 0 | P51: - | Q51: 0 | R51: 0 | S51: 0 | T51: 0 | U51: 0 | V51: 0 | W51: 0 | X51: Cuenta inactiva / sin saldo en el ejercicio. Sin previsión de movimientos.
B52: 2026 | C52: Codiagro | D52: RESULTADO DEL EJERCICIO | E52: RESULTADO ANTES DE IMPUESTOS | F52: RESULTADO DE LA EXPLOTACION | G52: 6.- Gastos de personal | H52: (649) Otros gastos sociales | I52: 649000100 - GTOS. CURSOS PERSONAL | J52: - | K52: 0 | L52: 0 | M52: -2623 | N52: 0 | O52: -88 | P52: - | Q52: 0 | R52: 0 | S52: 0 | T52: 0 | U52: 0 | V52: 0 | W52: -2711 | X52: Sin dotación presupuestada en el último cuatrimestre.
B53: 2026 | C53: Codiagro | D53: RESULTADO DEL EJERCICIO | E53: RESULTADO ANTES DE IMPUESTOS | F53: RESULTADO DE LA EXPLOTACION | G53: 6.- Gastos de personal | H53: (649) Otros gastos sociales | I53: 649000101 - GTOS. SEG. Y RIESGOS PERSONAL | J53: - | K53: 0 | L53: 0 | M53: 0 | N53: 0 | O53: 0 | P53: - | Q53: 0 | R53: 0 | S53: 0 | T53: 0 | U53: 0 | V53: 0 | W53: 0 | X53: Cuenta inactiva / sin saldo en el ejercicio. Sin previsión de movimientos.
B54: 2026 | C54: Codiagro | D54: RESULTADO DEL EJERCICIO | E54: RESULTADO ANTES DE IMPUESTOS | F54: RESULTADO DE LA EXPLOTACION | G54: 6.- Gastos de personal | H54: (649) Otros gastos sociales | I54: 649000102 - GASTOS ROPA UNIFORMES TRABAJADORES | J54: - | K54: 0 | L54: 0 | M54: 0 | N54: 0 | O54: 0 | P54: - | Q54: 0 | R54: 0 | S54: 0 | T54: 0 | U54: 0 | V54: 0 | W54: 0 | X54: Cuenta inactiva / sin saldo en el ejercicio. Sin previsión de movimientos.
B55: 2026 | C55: Codiagro | D55: RESULTADO DEL EJERCICIO | E55: RESULTADO ANTES DE IMPUESTOS | F55: RESULTADO DE LA EXPLOTACION | G55: 6.- Gastos de personal | H55: (649) Otros gastos sociales | I55: 649000103 - GASTOS COMBUSTIBLE TRAB. | J55: - | K55: 0 | L55: 0 | M55: 0 | N55: 0 | O55: 0 | P55: - | Q55: 0 | R55: 0 | S55: 0 | T55: 0 | U55: 0 | V55: 0 | W55: 0 | X55: Cuenta inactiva / sin saldo en el ejercicio. Sin previsión de movimientos.
... B57: 2026 | C57: Codiagro | D57: RESULTADO DEL EJERCICIO | E57: RESULTADO ANTES DE IMPUESTOS | F57: RESULTADO DE LA EXPLOTACION | G57: 6.- Gastos de personal | H57: (649) Otros gastos sociales | I57: 649100002 - GASTOS TRAB. EMPRESA VARIOS | J57: - | K57: 0 | L57: 0 | M57: 0 | N57: 0 | O57: 0 | P57: - | Q57: 0 | R57: 0 | S57: 0 | T57: 0 | U57: 0 | V57: 0 | W57: 0 | X57: Cuenta inactiva / sin saldo en el ejercicio. Sin previsión de movimientos.
B58: 2026 | C58: Codiagro | D58: RESULTADO DEL EJERCICIO | E58: RESULTADO ANTES DE IMPUESTOS | F58: RESULTADO DE LA EXPLOTACION | G58: 7.- Otros gastos de explotación | H58: (620) Gastos de investigación y desarrollo | I58: 620000002 - COMPRAS LABORATORIO | J58: - | K58: 0 | L58: 0 | M58: -113.13 | N58: -87.6 | O58: -487.47 | P58: -697.81 | Q58: -226.47 | R58: 0 | S58: -322.5 | T58: -322.5 | U58: -322.5 | V58: -322.5 | W58: -2902.48 | X58: Coste estratégico de I+D: ensayos agronómicos de eficacia y desarrollo de bioestimulantes.
B59: 2026 | C59: Codiagro | D59: RESULTADO DEL EJERCICIO | E59: RESULTADO ANTES DE IMPUESTOS | F59: RESULTADO DE LA EXPLOTACION | G59: 7.- Otros gastos de explotación | H59: (620) Gastos de investigación y desarrollo | I59: 620000003 - SUMINISTROS LABORATORIO | J59: - | K59: -522.31 | L59: -356.17 | M59: 0 | N59: -1440.58 | O59: -1464.58 | P59: -752.24 | Q59: -752.24 | R59: -399.98 | S59: -812.59 | T59: -812.59 | U59: -812.59 | V59: -812.59 | W59: -8938.46 | X59: Coste estratégico de I+D: ensayos agronómicos de eficacia y desarrollo de bioestimulantes.
B60: 2026 | C60: Codiagro | D60: RESULTADO DEL EJERCICIO | E60: RESULTADO ANTES DE IMPUESTOS | F60: RESULTADO DE LA EXPLOTACION | G60: 7.- Otros gastos de explotación | H60: (620) Gastos de investigación y desarrollo | I60: 620000004 - GTOS. ANALISIS LABORATORIOS | J60: - | K60: -523.96 | L60: -1019.07 | M60: -1573.25 | N60: -41.5 | O60: -1476.12 | P60: -2389.01 | Q60: -1899.09 | R60: -911.52 | S60: -1229.19 | T60: -1229.19 | U60: -1229.19 | V60: -1229.19 | W60: -14750.28 | X60: Coste estratégico de I+D: ensayos agronómicos de eficacia y desarrollo de bioestimulantes.
B61: 2026 | C61: Codiagro | D61: RESULTADO DEL EJERCICIO | E61: RESULTADO ANTES DE IMPUESTOS | F61: RESULTADO DE LA EXPLOTACION | G61: 7.- Otros gastos de explotación | H61: (621) Arrendamientos y cánones | I61: 621000001 - ALQUILER OFICINA CARTAGENA | J61: - | K61: -192 | L61: -192 | M61: -192 | N61: -192 | O61: -192 | P61: -192 | Q61: -192 | R61: -192 | S61: -192 | T61: -192 | U61: -192 | V61: -192 | W61: -2304 | X61: Coste fijo mensual según contratos vigentes de renting de vehículos y maquinaria auxiliar.
B62: 2026 | C62: Codiagro | D62: RESULTADO DEL EJERCICIO | E62: RESULTADO ANTES DE IMPUESTOS | F62: RESULTADO DE LA EXPLOTACION | G62: 7.- Otros gastos de explotación | H62: (621) Arrendamientos y cánones | I62: 621000014 - ALQUILER MURANO | J62: - | O62: -15421.92 | P62: - | Q62: -6139.04 | R62: 0 | S62: 0 | T62: 0 | U62: 0 | V62: 0 | W62: -21560.96 | X62: Arrendamiento Murano: no hay más cuotas en 2026 (ya está todo pagado, eliminadas sep-dic). En 2027 poner la misma cantidad anual ajustada a la inflación (+4,5%).
B63: 2026 | C63: Codiagro | D63: RESULTADO DEL EJERCICIO | E63: RESULTADO ANTES DE IMPUESTOS | F63: RESULTADO DE LA EXPLOTACION | G63: 7.- Otros gastos de explotación | H63: (621) Arrendamientos y cánones | I63: 621000023 - RENTING TRANSPALETA ELECTRICA DE PIE | J63: - | K63: 0 | L63: 0 | M63: 0 | N63: 0 | O63: 0 | P63: - | Q63: 0 | R63: 0 | S63: 0 | T63: 0 | U63: 0 | V63: 0 | W63: 0 | X63: Cuenta sin saldo en el ejercicio. Sin previsión de movimientos.
B64: 2026 | C64: Codiagro | D64: RESULTADO DEL EJERCICIO | E64: RESULTADO ANTES DE IMPUESTOS | F64: RESULTADO DE LA EXPLOTACION | G64: 7.- Otros gastos de explotación | H64: (621) Arrendamientos y cánones | I64: 621000024 - ALQUILER RENTING 2255KXN ANTONIO | J64: - | K64: 0 | L64: -361.46 | M64: 0 | N64: -361.46 | O64: - | P64: - | Q64: 0 | R64: 0 | S64: -361.46 | T64: -361.46 | U64: -361.46 | V64: -361.46 | W64: -2168.76 | X64: Coste fijo mensual según contratos vigentes de renting de vehículos y maquinaria auxiliar.
B65: 2026 | C65: Codiagro | D65: RESULTADO DEL EJERCICIO | E65: RESULTADO ANTES DE IMPUESTOS | F65: RESULTADO DE LA EXPLOTACION | G65: 7.- Otros gastos de explotación | H65: (621) Arrendamientos y cánones | I65: 621000025 - ALQUILER RENTING 9128 LBT NIEVES | J65: - | K65: 0 | L65: 0 | M65: 0 | N65: 0 | O65: 0 | P65: - | Q65: 0 | R65: 0 | S65: 0 | T65: 0 | U65: 0 | V65: 0 | W65: 0 | X65: Cuenta sin saldo en el ejercicio. Sin previsión de movimientos.
B66: 2026 | C66: Codiagro | D66: RESULTADO DEL EJERCICIO | E66: RESULTADO ANTES DE IMPUESTOS | F66: RESULTADO DE LA EXPLOTACION | G66: 7.- Otros gastos de explotación | H66: (621) Arrendamientos y cánones | I66: 621000026 - ALQUILER RENTING 9319LCL CURRO | J66: - | K66: 0 | L66: 0 | M66: -369.97 | N66: -369.97 | O66: - | P66: - | Q66: 0 | R66: 0 | S66: -369.97 | T66: -369.97 | U66: -369.97 | V66: -369.97 | W66: -2219.82 | X66: Coste fijo mensual según contratos vigentes de renting de vehículos y maquinaria auxiliar.
B67: 2026 | C67: Codiagro | D67: RESULTADO DEL EJERCICIO | E67: RESULTADO ANTES DE IMPUESTOS | F67: RESULTADO DE LA EXPLOTACION | G67: 7.- Otros gastos de explotación | H67: (621) Arrendamientos y cánones | I67: 621000030 - ALQUILER RENTING 1075-LSC GARCIA | J67: - | K67: 0 | L67: 0 | M67: 0 | N67: 0 | O67: 0 | P67: - | Q67: 0 | R67: 0 | S67: 0 | T67: 0 | U67: 0 | V67: 0 | W67: 0 | X67: Cuenta sin saldo en el ejercicio. Sin previsión de movimientos.
B68: 2026 | C68: Codiagro | D68: RESULTADO DEL EJERCICIO | E68: RESULTADO ANTES DE IMPUESTOS | F68: RESULTADO DE LA EXPLOTACION | G68: 7.- Otros gastos de explotación | H68: (621) Arrendamientos y cánones | I68: 621000031 - ALQUILER RENTING KONICA-MINOLTA Y KYOCERA | J68: - | K68: -338 | L68: -338 | M68: -338 | N68: -338 | O68: -338 | P68: -338 | Q68: -338 | R68: -338 | S68: -338 | T68: -338 | U68: -338 | V68: -338 | W68: -4056 | X68: Coste fijo mensual según contratos vigentes de renting de vehículos y maquinaria auxiliar.
B69: 2026 | C69: Codiagro | D69: RESULTADO DEL EJERCICIO | E69: RESULTADO ANTES DE IMPUESTOS | F69: RESULTADO DE LA EXPLOTACION | G69: 7.- Otros gastos de explotación | H69: (621) Arrendamientos y cánones | I69: 621000032 - ALQUILER RENTING 6665-LVK JOSE JUAN | J69: - | K69: -349 | L69: -349 | M69: -349 | N69: 0 | O69: -443.49 | P69: -443.49 | Q69: -886.98 | R69: 0 | S69: -470.16 | T69: -470.16 | U69: -470.16 | V69: -470.16 | W69: -4701.6 | X69: Coste fijo mensual según contratos vigentes de renting de vehículos y maquinaria auxiliar.
B70: 2026 | C70: Codiagro | D70: RESULTADO DEL EJERCICIO | E70: RESULTADO ANTES DE IMPUESTOS | F70: RESULTADO DE LA EXPLOTACION | G70: 7.- Otros gastos de explotación | H70: (621) Arrendamientos y cánones | I70: 621000033 - ALQUILER RENTING 2612-MBY ANTONIO | J70: - | K70: -361.46 | L70: 0 | M70: -361.46 | N70: 0 | O70: -399.42 | P70: -399.42 | Q70: -149.15 | R70: -399.42 | S70: -345.06 | T70: -345.06 | U70: -345.06 | V70: -345.06 | W70: -3450.57 | X70: Coste fijo mensual según contratos vigentes de renting de vehículos y maquinaria auxiliar.
B71: 2026 | C71: Codiagro | D71: RESULTADO DEL EJERCICIO | E71: RESULTADO ANTES DE IMPUESTOS | F71: RESULTADO DE LA EXPLOTACION | G71: 7.- Otros gastos de explotación | H71: (621) Arrendamientos y cánones | I71: 621000034 - ALQUILER RENTING 3108-LZM NIEVES | J71: - | K71: -650.95 | L71: -650.95 | M71: 0 | N71: 0 | O71: - | P71: - | Q71: 0 | R71: -1139.16 | S71: -813.69 | T71: -813.69 | U71: -813.69 | V71: -813.69 | W71: -5695.82 | X71: Coste fijo mensual según contratos vigentes de renting de vehículos y maquinaria auxiliar.
B72: 2026 | C72: Codiagro | D72: RESULTADO DEL EJERCICIO | E72: RESULTADO ANTES DE IMPUESTOS | F72: RESULTADO DE LA EXPLOTACION | G72: 7.- Otros gastos de explotación | H72: (621) Arrendamientos y cánones | I72: 621000035 - ALQUILER RENTING 2142-MCS RICARDO | J72: - | K72: 0 | L72: 0 | M72: 0 | N72: 0 | O72: 0 | P72: - | Q72: 0 | R72: 0 | S72: 0 | T72: 0 | U72: 0 | V72: 0 | W72: 0 | X72: Cuenta sin saldo en el ejercicio. Sin previsión de movimientos.
B73: 2026 | C73: Codiagro | D73: RESULTADO DEL EJERCICIO | E73: RESULTADO ANTES DE IMPUESTOS | F73: RESULTADO DE LA EXPLOTACION | G73: 7.- Otros gastos de explotación | H73: (621) Arrendamientos y cánones | I73: 621000036 - ALQUILER RENTING 3277-MDX JAVIER | J73: - | K73: 0 | L73: 0 | M73: 0 | N73: 0 | O73: 0 | P73: - | Q73: 0 | R73: 0 | S73: 0 | T73: 0 | U73: 0 | V73: 0 | W73: 0 | X73: Cuenta sin saldo en el ejercicio. Sin previsión de movimientos.
B74: 2026 | C74: Codiagro | D74: RESULTADO DEL EJERCICIO | E74: RESULTADO ANTES DE IMPUESTOS | F74: RESULTADO DE LA EXPLOTACION | G74: 7.- Otros gastos de explotación | H74: (621) Arrendamientos y cánones | I74: 621000037 - CARRETILLA STILL ELEKTROSTAPLER 516213H00521 | J74: - | K74: -200 | L74: -200 | M74: -200 | N74: -200 | O74: -200 | P74: -200 | Q74: - | R74: -400 | S74: -228.57 | T74: -228.57 | U74: -228.57 | V74: -228.57 | W74: -2514.28 | X74: Coste fijo mensual según contratos vigentes de renting de vehículos y maquinaria auxiliar.
B75: 2026 | C75: Codiagro | D75: RESULTADO DEL EJERCICIO | E75: RESULTADO ANTES DE IMPUESTOS | F75: RESULTADO DE LA EXPLOTACION | G75: 7.- Otros gastos de explotación | H75: (621) Arrendamientos y cánones | I75: 621000038 - CARRETILLA STILL ELEKTROSTAPLER 516223J00123 | J75: - | K75: -200.22 | L75: -200.22 | M75: -200.22 | N75: -200.22 | O75: -200.22 | P75: -200.22 | Q75: - | R75: -400.44 | S75: -228.82 | T75: -228.82 | U75: -228.82 | V75: -228.82 | W75: -2517.04 | X75: Coste fijo mensual según contratos vigentes de renting de vehículos y maquinaria auxiliar.
B76: 2026 | C76: Codiagro | D76: RESULTADO DEL EJERCICIO | E76: RESULTADO ANTES DE IMPUESTOS | F76: RESULTADO DE LA EXPLOTACION | G76: 7.- Otros gastos de explotación | H76: (621) Arrendamientos y cánones | I76: 621000039 - ALQUILER RENTING 5043-MWW CURRO | J76: - | K76: -369.97 | L76: -369.97 | M76: -150 | N76: -1039.51 | O76: - | P76: - | Q76: 0 | R76: 0 | S76: -482.36 | T76: -482.36 | U76: -482.36 | V76: -482.36 | W76: -3858.89 | X76: Coste fijo mensual según contratos vigentes de renting de vehículos y maquinaria auxiliar.
B77: 2026 | C77: Codiagro | D77: RESULTADO DEL EJERCICIO | E77: RESULTADO ANTES DE IMPUESTOS | F77: RESULTADO DE LA EXPLOTACION | G77: 7.- Otros gastos de explotación | H77: (621) Arrendamientos y cánones | I77: 621000040 - ALQUILER RENTING 8917-MZT JAVIER | J77: - | K77: -1068.22 | L77: 0 | M77: -2136.44 | N77: -1068.22 | O77: -1172.14 | P77: - | Q77: -2344.3 | R77: 0 | S77: -1557.86 | T77: -1557.86 | U77: -1557.86 | V77: -1557.86 | W77: -14020.76 | X77: Coste fijo mensual según contratos vigentes de renting de vehículos y maquinaria auxiliar.
B78: 2026 | C78: Codiagro | D78: RESULTADO DEL EJERCICIO | E78: RESULTADO ANTES DE IMPUESTOS | F78: RESULTADO DE LA EXPLOTACION | G78: 7.- Otros gastos de explotación | H78: (621) Arrendamientos y cánones | I78: 621000041 - ALQUILER RENTING 8929-MZT RICARDO | J78: - | K78: -911.28 | L78: 0 | M78: -1822.56 | N78: -911.28 | O78: -1015.21 | P78: - | Q78: -2030.4 | R78: 0 | S78: -1338.15 | T78: -1338.15 | U78: -1338.15 | V78: -1338.15 | W78: -12043.33 | X78: Coste fijo mensual según contratos vigentes de renting de vehículos y maquinaria auxiliar.
B79: 2026 | C79: Codiagro | D79: RESULTADO DEL EJERCICIO | E79: RESULTADO ANTES DE IMPUESTOS | F79: RESULTADO DE LA EXPLOTACION | G79: 7.- Otros gastos de explotación | H79: (621) Arrendamientos y cánones | I79: 621000042 - ALQUILER RENTING 4946-NFH GARCIA | J79: - | K79: -613.16 | L79: -613.15 | M79: -613.15 | N79: -613.15 | O79: -677.53 | P79: -677.53 | Q79: -677.53 | R79: -677.53 | S79: -645.34 | T79: -645.34 | U79: -645.34 | V79: -645.34 | W79: -7744.09 | X79: Coste fijo mensual según contratos vigentes de renting de vehículos y maquinaria auxiliar.
B80: 2026 | C80: Codiagro | D80: RESULTADO DEL EJERCICIO | E80: RESULTADO ANTES DE IMPUESTOS | F80: RESULTADO DE LA EXPLOTACION | G80: 7.- Otros gastos de explotación | H80: (621) Arrendamientos y cánones | I80: 621000044 - ALQUILER COMPRESOR DE TORNILLO 37KW KAESER BSD 75C | J80: - | K80: -1600 | L80: -1600 | M80: -1600 | N80: -1600 | O80: -1600 | P80: -1600 | Q80: -1600 | R80: -1600 | S80: -1600 | T80: -1600 | U80: -1600 | V80: -1600 | W80: -19200 | X80: Coste fijo mensual según contratos vigentes de renting de vehículos y maquinaria auxiliar.
B81: 2026 | C81: Codiagro | D81: RESULTADO DEL EJERCICIO | E81: RESULTADO ANTES DE IMPUESTOS | F81: RESULTADO DE LA EXPLOTACION | G81: 7.- Otros gastos de explotación | H81: (621) Arrendamientos y cánones | I81: 621000045 - ALQUILER RENTING 3421-NJT PERE | J81: - | K81: -634.77 | L81: -1093.22 | M81: -1093.22 | N81: -1093.22 | O81: -1208.01 | P81: -1208.01 | Q81: -1208.01 | R81: -1208.01 | S81: -1093.31 | T81: -1093.31 | U81: -1093.31 | V81: -1093.31 | W81: -13119.71 | X81: Coste fijo mensual según contratos vigentes de renting de vehículos y maquinaria auxiliar.
B82: 2026 | C82: Codiagro | D82: RESULTADO DEL EJERCICIO | E82: RESULTADO ANTES DE IMPUESTOS | F82: RESULTADO DE LA EXPLOTACION | G82: 7.- Otros gastos de explotación | H82: (621) Arrendamientos y cánones | I82: 621000046 - ALQUILER CARRETILLAS | J82: - | K82: 0 | L82: 0 | M82: 0 | N82: -381.67 | O82: 0 | P82: -845.33 | Q82: -742 | R82: -742 | S82: -677.75 | T82: -677.75 | U82: -677.75 | V82: -677.75 | W82: -5422 | X82: Coste fijo mensual según contratos vigentes de renting de vehículos y maquinaria auxiliar.
B83: 2026 | C83: Codiagro | D83: RESULTADO DEL EJERCICIO | E83: RESULTADO ANTES DE IMPUESTOS | F83: RESULTADO DE LA EXPLOTACION | G83: 7.- Otros gastos de explotación | H83: (622) Reparación/conservación/mantenimiento | I83: 622000001 - REPAR. EQUIPOS INFORM. Y FOTOCOPIADORAS | J83: - | K83: -1621.56 | L83: -815.7 | M83: -136.16 | N83: -218 | O83: - | P83: -790.66 | Q83: - | R83: 0 | S83: -716.42 | T83: -716.42 | U83: -716.42 | V83: -716.42 | W83: -6447.76 | X83: Coste semi-variable: mantenimiento preventivo y correctivo de planta según promedio mensual histórico (sin incremento de inflación en 2026; la inflación del +4,5% se aplica solo en 2027).
B84: 2026 | C84: Codiagro | D84: RESULTADO DEL EJERCICIO | E84: RESULTADO ANTES DE IMPUESTOS | F84: RESULTADO DE LA EXPLOTACION | G84: 7.- Otros gastos de explotación | H84: (622) Reparación/conservación/mantenimiento | I84: 622000004 - REP. Y CONSERV. CARRETILLA ELECTRICA | J84: - | K84: 0 | L84: 0 | M84: -1006.36 | N84: 0 | O84: - | P84: -979.23 | Q84: - | R84: -115.48 | S84: -700.36 | T84: -700.36 | U84: -700.36 | V84: -700.36 | W84: -4902.51 | X84: Coste semi-variable: mantenimiento preventivo y correctivo de planta según promedio mensual histórico (sin incremento de inflación en 2026; la inflación del +4,5% se aplica solo en 2027).
B85: 2026 | C85: Codiagro | D85: RESULTADO DEL EJERCICIO | E85: RESULTADO ANTES DE IMPUESTOS | F85: RESULTADO DE LA EXPLOTACION | G85: 7.- Otros gastos de explotación | H85: (622) Reparación/conservación/mantenimiento | I85: 622000005 - REP. Y MANT. EQUIPOS SEGURIDAD | J85: - | K85: 0 | L85: -73.72 | M85: 0 | N85: -13.33 | O85: -183.66 | P85: - | Q85: -196.99 | R85: 0 | S85: -116.92 | T85: -116.92 | U85: -116.92 | V85: -116.92 | W85: -935.38 | X85: Coste semi-variable: mantenimiento preventivo y correctivo de planta según promedio mensual histórico (sin incremento de inflación en 2026; la inflación del +4,5% se aplica solo en 2027).
B86: 2026 | C86: Codiagro | D86: RESULTADO DEL EJERCICIO | E86: RESULTADO ANTES DE IMPUESTOS | F86: RESULTADO DE LA EXPLOTACION | G86: 7.- Otros gastos de explotación | H86: (622) Reparación/conservación/mantenimiento | I86: 622000006 - REP. Y MANT. INSTALACIONES VARIAS | J86: - | K86: 0 | L86: -1833.95 | M86: -468.78 | N86: -344 | O86: - | P86: -1900.59 | Q86: -2274.92 | R86: 0 | S86: -1364.45 | T86: -1364.45 | U86: -1364.45 | V86: -1364.45 | W86: -12280.04 | X86: Coste semi-variable: mantenimiento preventivo y correctivo de planta según promedio mensual histórico (sin incremento de inflación en 2026; la inflación del +4,5% se aplica solo en 2027).
B87: 2026 | C87: Codiagro | D87: RESULTADO DEL EJERCICIO | E87: RESULTADO ANTES DE IMPUESTOS | F87: RESULTADO DE LA EXPLOTACION | G87: 7.- Otros gastos de explotación | H87: (622) Reparación/conservación/mantenimiento | I87: 622000007 - REP. Y MANT. HYUNDAI 0377CJG | J87: - | K87: 0 | L87: 0 | M87: -238.88 | N87: 0 | O87: - | P87: - | Q87: 0 | R87: 0 | S87: -238.88 | T87: -238.88 | U87: -238.88 | V87: -238.88 | W87: -1194.4 | X87: Coste semi-variable: mantenimiento preventivo y correctivo de planta según promedio mensual histórico (sin incremento de inflación en 2026; la inflación del +4,5% se aplica solo en 2027).
B88: 2026 | C88: Codiagro | D88: RESULTADO DEL EJERCICIO | E88: RESULTADO ANTES DE IMPUESTOS | F88: RESULTADO DE LA EXPLOTACION | G88: 7.- Otros gastos de explotación | H88: (622) Reparación/conservación/mantenimiento | I88: 622000008 - REP. Y MANT. MAQUINA BARREDORA | J88: - | K88: 0 | L88: 0 | M88: 0 | N88: -350.75 | O88: - | P88: - | Q88: -634.91 | R88: 0 | S88: -492.83 | T88: -492.83 | U88: -492.83 | V88: -492.83 | W88: -2956.98 | X88: Coste semi-variable: mantenimiento preventivo y correctivo de planta según promedio mensual histórico (sin incremento de inflación en 2026; la inflación del +4,5% se aplica solo en 2027).
B89: 2026 | C89: Codiagro | D89: RESULTADO DEL EJERCICIO | E89: RESULTADO ANTES DE IMPUESTOS | F89: RESULTADO DE LA EXPLOTACION | G89: 7.- Otros gastos de explotación | H89: (622) Reparación/conservación/mantenimiento | I89: 622000009 - REP. Y MANT. FURGONETA 2589CRJ | J89: - | K89: 0 | L89: 0 | M89: 0 | N89: 0 | O89: 0 | P89: - | Q89: 0 | R89: 0 | S89: 0 | T89: 0 | U89: 0 | V89: 0 | W89: 0 | X89: Coste semi-variable: mantenimiento preventivo y correctivo de planta según promedio mensual histórico (sin incremento de inflación en 2026; la inflación del +4,5% se aplica solo en 2027).
B90: 2026 | C90: Codiagro | D90: RESULTADO DEL EJERCICIO | E90: RESULTADO ANTES DE IMPUESTOS | F90: RESULTADO DE LA EXPLOTACION | G90: 7.- Otros gastos de explotación | H90: (622) Reparación/conservación/mantenimiento | I90: 622000012 - LIMPIEZA OFICINAS, LABORATORIO Y VESTUARIOS | J90: - | K90: -585 | L90: 0 | M90: -1101.6 | N90: -495 | O90: - | P90: -1566.9 | Q90: -642.6 | R90: -977.98 | S90: -894.85 | T90: -894.85 | U90: -894.85 | V90: -894.85 | W90: -8948.48 | X90: Coste semi-variable: mantenimiento preventivo y correctivo de planta según promedio mensual histórico (sin incremento de inflación en 2026; la inflación del +4,5% se aplica solo en 2027).
B91: 2026 | C91: Codiagro | D91: RESULTADO DEL EJERCICIO | E91: RESULTADO ANTES DE IMPUESTOS | F91: RESULTADO DE LA EXPLOTACION | G91: 7.- Otros gastos de explotación | H91: (622) Reparación/conservación/mantenimiento | I91: 622010000 MANTENIMIENTO | J91: - | K91: 0 | L91: 0 | M91: 0 | N91: 0 | O91: 0 | P91: 0 | Q91: -1409.04 | R91: 0 | S91: -1409.04 | T91: -1409.04 | U91: -1409.04 | V91: -1409.04 | W91: -7045.2 | X91: Coste semi-variable: mantenimiento preventivo y correctivo de planta según promedio mensual histórico (sin incremento de inflación en 2026; la inflación del +4,5% se aplica solo en 2027).
B92: 2026 | C92: Codiagro | D92: RESULTADO DEL EJERCICIO | E92: RESULTADO ANTES DE IMPUESTOS | F92: RESULTADO DE LA EXPLOTACION | G92: 7.- Otros gastos de explotación | H92: (622) Reparación/conservación/mantenimiento | I92: 622010001 - MANTENIMIENTO REPUESTO COMPRA AMAZON | J92: - | K92: 0 | L92: 0 | M92: 0 | N92: 0 | O92: 0 | P92: - | Q92: 0 | R92: 0 | S92: 0 | T92: 0 | U92: 0 | V92: 0 | W92: 0 | X92: Coste semi-variable: mantenimiento preventivo y correctivo de planta según promedio mensual histórico (sin incremento de inflación en 2026; la inflación del +4,5% se aplica solo en 2027).
B93: 2026 | C93: Codiagro | D93: RESULTADO DEL EJERCICIO | E93: RESULTADO ANTES DE IMPUESTOS | F93: RESULTADO DE LA EXPLOTACION | G93: 7.- Otros gastos de explotación | H93: (622) Reparación/conservación/mantenimiento | I93: 622010200 - ALCAPLANT | J93: - | K93: -1342.54 | L93: -586 | M93: -2280 | N93: 0 | O93: -942.88 | P93: -354.5 | Q93: -9441.85 | R93: -1983.69 | S93: -2418.78 | T93: -2418.78 | U93: -2418.78 | V93: -2418.78 | W93: -26606.58 | X93: Coste semi-variable: mantenimiento preventivo y correctivo de planta según promedio mensual histórico (sin incremento de inflación en 2026; la inflación del +4,5% se aplica solo en 2027).
B94: 2026 | C94: Codiagro | D94: RESULTADO DEL EJERCICIO | E94: RESULTADO ANTES DE IMPUESTOS | F94: RESULTADO DE LA EXPLOTACION | G94: 7.- Otros gastos de explotación | H94: (622) Reparación/conservación/mantenimiento | I94: 622010201 - REPARACIONES ALCAPLANT | J94: - | K94: -667.12 | L94: 0 | M94: 0 | N94: 0 | O94: - | P94: -4282.05 | Q94: -5230 | R94: -5848.16 | S94: -4006.83 | T94: -4006.83 | U94: -4006.83 | V94: -4006.83 | W94: -32054.65 | X94: Coste semi-variable: mantenimiento preventivo y correctivo de planta según promedio mensual histórico (sin incremento de inflación en 2026; la inflación del +4,5% se aplica solo en 2027).
B95: 2026 | C95: Codiagro | D95: RESULTADO DEL EJERCICIO | E95: RESULTADO ANTES DE IMPUESTOS | F95: RESULTADO DE LA EXPLOTACION | G95: 7.- Otros gastos de explotación | H95: (622) Reparación/conservación/mantenimiento | I95: 622010300 - SOLIDOS | J95: - | K95: -617.42 | L95: 0 | M95: 0 | N95: 0 | O95: - | P95: -4467.02 | Q95: - | R95: -11965.55 | S95: -5683.33 | T95: -5683.33 | U95: -5683.33 | V95: -5683.33 | W95: -39783.31 | X95: Coste semi-variable: mantenimiento preventivo y correctivo de planta según promedio mensual histórico (sin incremento de inflación en 2026; la inflación del +4,5% se aplica solo en 2027).
B96: 2026 | C96: Codiagro | D96: RESULTADO DEL EJERCICIO | E96: RESULTADO ANTES DE IMPUESTOS | F96: RESULTADO DE LA EXPLOTACION | G96: 7.- Otros gastos de explotación | H96: (622) Reparación/conservación/mantenimiento | I96: 622010400 - LIQUIDOS | J96: - | K96: 0 | L96: 0 | M96: -1502.54 | N96: -55.82 | O96: -1092.45 | P96: -8017.35 | Q96: 5697.8 | R96: -288.39 | S96: -876.46 | T96: -876.46 | U96: -876.46 | V96: -876.46 | W96: -8764.59 | X96: Coste semi-variable: mantenimiento preventivo y correctivo de planta según promedio mensual histórico (sin incremento de inflación en 2026; la inflación del +4,5% se aplica solo en 2027).
B97: 2026 | C97: Codiagro | D97: RESULTADO DEL EJERCICIO | E97: RESULTADO ANTES DE IMPUESTOS | F97: RESULTADO DE LA EXPLOTACION | G97: 7.- Otros gastos de explotación | H97: (622) Reparación/conservación/mantenimiento | I97: 622010500 - REPUESTOS MANT. VARIOS | J97: - | K97: 0 | L97: -155.11 | M97: -1072.93 | N97: -2283.52 | O97: -799.04 | P97: -106.8 | Q97: - | R97: -108.17 | S97: -754.26 | T97: -754.26 | U97: -754.26 | V97: -754.26 | W97: -7542.61 | X97: Coste semi-variable: mantenimiento preventivo y correctivo de planta según promedio mensual histórico (sin incremento de inflación en 2026; la inflación del +4,5% se aplica solo en 2027).
B98: 2026 | C98: Codiagro | D98: RESULTADO DEL EJERCICIO | E98: RESULTADO ANTES DE IMPUESTOS | F98: RESULTADO DE LA EXPLOTACION | G98: 7.- Otros gastos de explotación | H98: (622) Reparación/conservación/mantenimiento | I98: 622010501 - REP. MANT. FONTANERIA | J98: - | K98: 0 | L98: -39.8 | M98: -227.04 | N98: 0 | O98: - | P98: -81.8 | Q98: - | R98: 0 | S98: -116.21 | T98: -116.21 | U98: -116.21 | V98: -116.21 | W98: -813.48 | X98: Coste semi-variable: mantenimiento preventivo y correctivo de planta según promedio mensual histórico (sin incremento de inflación en 2026; la inflación del +4,5% se aplica solo en 2027).
B99: 2026 | C99: Codiagro | D99: RESULTADO DEL EJERCICIO | E99: RESULTADO ANTES DE IMPUESTOS | F99: RESULTADO DE LA EXPLOTACION | G99: 7.- Otros gastos de explotación | H99: (623) Servicios profesionales independientes | I99: 623000001 - SERV. PROF. INDEPENDIENTES | J99: - | K99: -1902.37 | L99: -497 | M99: -5360.3 | N99: -10729 | O99: -21698 | P99: -2988 | Q99: -2584.62 | R99: -2853.02 | S99: -6000 | T99: -6000 | U99: -6000 | V99: -8000 | W99: -74612.31 | X99: Coste fijo de asesoramiento legal, técnico y fiscal, con refuerzo en diciembre por preparación del cierre y auditoría.
B100: 2026 | C100: Codiagro | D100: RESULTADO DEL EJERCICIO | E100: RESULTADO ANTES DE IMPUESTOS | F100: RESULTADO DE LA EXPLOTACION | G100: 7.- Otros gastos de explotación | H100: (623) Servicios profesionales independientes | I100: 623000002 - SERVICIOS CONTABLES Y FINANCIEROS | J100: - | K100: -1417.95 | L100: -1417.95 | M100: -5837.67 | N100: -2891.19 | O100: -2891.19 | P100: -2891.19 | Q100: -2891.19 | R100: -2148.24 | S100: -2800 | T100: -2800 | U100: -2800 | V100: -2800 | W100: -33586.57 | X100: Servicios contables y financieros externos: restablecido a -2.800,00 €/mes en 2026 según indicación. La reducción del 50% (-1.400,00 €/mes) se aplica únicamente en el ejercicio 2027.
B101: 2026 | C101: Codiagro | D101: RESULTADO DEL EJERCICIO | E101: RESULTADO ANTES DE IMPUESTOS | F101: RESULTADO DE LA EXPLOTACION | G101: 7.- Otros gastos de explotación | H101: (623) Servicios profesionales independientes | I101: 623000003 - SERV. NOTARIOS, REGISTROS, LEGAL | J101: - | K101: -548.32 | L101: -3007.86 | M101: -3805.86 | N101: -3053.37 | O101: -2271.24 | P101: -2271.24 | Q101: -736.62 | R101: 0 | S101: -1800 | T101: -2000 | U101: -2000 | V101: -2200 | W101: -23694.51 | X101: Gastos de registro de formulaciones, marcas y actos notariales.
B102: 2026 | C102: Codiagro | D102: RESULTADO DEL EJERCICIO | E102: RESULTADO ANTES DE IMPUESTOS | F102: RESULTADO DE LA EXPLOTACION | G102: 7.- Otros gastos de explotación | H102: (623) Servicios profesionales independientes | I102: 623000004 - GTOS. BCS. OKO | J102: - | K102: -971.47 | L102: 0 | M102: 0 | N102: 0 | O102: -1574.71 | P102: -1267.24 | Q102: - | R102: 0 | S102: -1271.14 | T102: -1271.14 | U102: -1271.14 | V102: -1271.14 | W102: -8897.98 | X102: Proyección basada en el promedio mensual histórico de actividad.
...

Sheet Ginger
A1: Cuenta | B1: Grupo Ext Item | C1: 46023 | D1: 46054 | E1: 46082 | F1: 46113 | G1: 46143 | H1: Comprobación | I1: Dif
A2: 700000000 - Ventas de mercaderías | B2: - | G2: 2029267 | H2: =VLOOKUP(A2,'PL Mensual 2026'!I:O,7,0) -> 2029267 | I2: =G2-H2 -> 0
A3: 700000001 - VENTA MERCADERIAS POR ANTICIPO | B3: - | G3: -106250.17 | H3: =VLOOKUP(A3,'PL Mensual 2026'!I:O,7,0) -> -106250.17 | I3: =G3-H3 -> 0
A4: 700000624 - VENTA POR TRANSP. REP. AL CLIENTE | B4: - | G4: - | H4: =VLOOKUP(A4,'PL Mensual 2026'!I:O,7,0) -> 0
A5: 700000769 - INGRESOS POR RETRASOS DE COBRO Y ACTUALIZACION | B5: - | G5: - | H5: =VLOOKUP(A5,'PL Mensual 2026'!I:O,7,0) -> -
A6: 700001624 - VENTA POR TRANSPORTE REP. AL CLIENTE DEFINITIVO | B6: - | G6: 25140.75 | H6: =VLOOKUP(A6,'PL Mensual 2026'!I:O,7,0) -> 25140.75 | I6: =G6-H6 -> 0
A7: 702000000 - Ventas de productos semiterminados | B7: - | G7: 101865.8 | H7: =VLOOKUP(A7,'PL Mensual 2026'!I:O,7,0) -> 0 | I7: =G7-H7 -> 101865.8
A8: 703000000 - Ventas de subproductos y residuos | B8: - | G8: - | H8: =VLOOKUP(A8,'PL Mensual 2026'!I:O,7,0) -> -
A9: 704000000 - Ventas de envases y embalajes | B9: - | G9: 80917.99 | H9: =VLOOKUP(A9,'PL Mensual 2026'!I:O,7,0) -> 0 | I9: =G9-H9 -> 80917.99
A10: 705000000 - Prestaciones de servicios | B10: - | G10: 111557.6 | H10: =VLOOKUP(A10,'PL Mensual 2026'!I:O,7,0) -> 0 | I10: =G10-H10 -> 111557.6
A11: - - | B11: Maquila | G11: -111557.6 | H11: =VLOOKUP(A11,'PL Mensual 2026'!I:O,7,0) -> #N/A | I11: =G11-H11 -> #N/A
A12: 705000001 - INGRESO POR GESTIÓN DE ENVASES | B12: - | G12: 2913.09 | H12: =VLOOKUP(A12,'PL Mensual 2026'!I:O,7,0) -> 2913.09 | I12: =G12-H12 -> 0
A13: 706000000 - Dtos. ventas por pronto pago mercaderías | B13: - | G13: - | H13: =VLOOKUP(A13,'PL Mensual 2026'!I:O,7,0) -> 0
A14: 706000001 - DESCUENTO POR PRONTO PAGO DEFINITIVO | B14: - | G14: -38633.95 | H14: =VLOOKUP(A14,'PL Mensual 2026'!I:O,7,0) -> -38633.95 | I14: =G14-H14 -> 0
A15: 709000000 - «Rappels» ventas de mercaderías | B15: - | G15: - | H15: =VLOOKUP(A15,'PL Mensual 2026'!I:O,7,0) -> -
A16: 709000001 - PROVISION RAPPELS | B16: - | G16: - | H16: =VLOOKUP(A16,'PL Mensual 2026'!I:O,7,0) -> -
A17: 709001500 - RAPPEL BONIFICACIONES POR PMK DEFINITIVO | B17: - | G17: -1350 | H17: =VLOOKUP(A17,'PL Mensual 2026'!I:O,7,0) -> -1350 | I17: =G17-H17 -> 0
A18: 711000000 - Variación existencias de prod. semiterminados | B18: - | G18: 4436.02 | H18: =VLOOKUP(A18,'PL Mensual 2026'!I:O,7,0) -> 4436.02 | I18: =G18-H18 -> 0
A19: 712000000 - Variación existencias de prod. terminados | B19: - | G19: -34727.12 | H19: =VLOOKUP(A19,'PL Mensual 2026'!I:O,7,0) -> -34727.12 | I19: =G19-H19 -> 0
A20: 601000000 - Compras de materias primas | B20: - | G20: -417425.43 | H20: =VLOOKUP(A20,'PL Mensual 2026'!I:O,7,0) -> -423709.63 | I20: =G20-H20 -> 6284.2
A21: 601000001 - COMPRAS MAT. PRIMAS INTRACOMUNITARIAS | B21: - | G21: -108150 | H21: =VLOOKUP(A21,'PL Mensual 2026'!I:O,7,0) -> #N/A | I21: =G21-H21 -> #N/A
A22: 602000001 - COMPRA DE ENVASES Y EMBALAJES | B22: - | G22: -111111.14 | H22: =VLOOKUP(A22,'PL Mensual 2026'!I:O,7,0) -> -30193.15 | I22: =G22-H22 -> -80917.99
A23: 602000002 - COMPRA DE ETIQUETAS | B23: - | G23: -2784.91 | H23: =VLOOKUP(A23,'PL Mensual 2026'!I:O,7,0) -> -2784.91 | I23: =G23-H23 -> 0
A24: 602000003 - COMPRA DE PALETS | B24: - | G24: -17326.4 | H24: =VLOOKUP(A24,'PL Mensual 2026'!I:O,7,0) -> -17326.4 | I24: =G24-H24 -> 0
A25: 602000004 - COMPRA MATERIAL DE LIMPIEZA | B25: - | G25: - | H25: =VLOOKUP(A25,'PL Mensual 2026'!I:O,7,0) -> -
A26: 602000005 - COMPRA MATERIAL DE OFICINA | B26: - | G26: - | H26: =VLOOKUP(A26,'PL Mensual 2026'!I:O,7,0) -> -
A27: 602000006 - COMPRA TAPONES DE ENVASES | B27: - | G27: - | H27: =VLOOKUP(A27,'PL Mensual 2026'!I:O,7,0) -> -
A28: 602000011 - COMPRAS VARIAS PLANTA | B28: - | G28: - | H28: =VLOOKUP(A28,'PL Mensual 2026'!I:O,7,0) -> -
A29: 602000012 - REPUESTOS INFORMATICOS | B29: - | G29: - | H29: =VLOOKUP(A29,'PL Mensual 2026'!I:O,7,0) -> -
A30: 602000013 - COMPRA TINTA INPRESORA ETIQUETAS | B30: - | G30: -480.84 | H30: =VLOOKUP(A30,'PL Mensual 2026'!I:O,7,0) -> -480.84 | I30: =G30-H30 -> 0
A31: 602000100 - ENVASES Y EMBALAJES A DEVOLVER | B31: - | G31: 1124 | H31: =VLOOKUP(A31,'PL Mensual 2026'!I:O,7,0) -> 1124 | I31: =G31-H31 -> 0
A32: 607000000 - Trabajos realizados por otras empresas | B32: - | G32: -32102.71 | H32: =VLOOKUP(A32,'PL Mensual 2026'!I:O,7,0) -> -3540 | I32: =G32-H32 -> -28562.71
A33: - - | B33: Maquila | G33: 28562.71 | H33: =VLOOKUP(A33,'PL Mensual 2026'!I:O,7,0) -> #N/A | I33: =G33-H33 -> #N/A
A34: 611000000 - Variación de existencias de materias primas | B34: - | G34: -43504.89 | H34: =VLOOKUP(A34,'PL Mensual 2026'!I:O,7,0) -> -43504.89 | I34: =G34-H34 -> 0
A35: 612000000 - Variación de existencias otros aprovisionamientos | B35: - | G35: -73565.42 | H35: =VLOOKUP(A35,'PL Mensual 2026'!I:O,7,0) -> -73565.42 | I35: =G35-H35 -> 0
A36: 640000000 - Sueldos y salarios | B36: - | G36: -104048.18 | H36: =VLOOKUP(A36,'PL Mensual 2026'!I:O,7,0) -> -104048.18 | I36: =G36-H36 -> 0
A37: 641000000 - Indemnizaciones | B37: - | G37: - | H37: =VLOOKUP(A37,'PL Mensual 2026'!I:O,7,0) -> #N/A
A38: 642000000 - Seguridad Social a cargo empresa | B38: - | G38: -30856.34 | H38: =VLOOKUP(A38,'PL Mensual 2026'!I:O,7,0) -> -30856.34 | I38: =G38-H38 -> 0
A39: 649000100 - GTOS. CURSOS PERSONAL | B39: - | G39: -88 | H39: =VLOOKUP(A39,'PL Mensual 2026'!I:O,7,0) -> -88 | I39: =G39-H39 -> 0
A40: 620000002 - COMPRAS LABORATORIO | B40: - | G40: -487.47 | H40: =VLOOKUP(A40,'PL Mensual 2026'!I:O,7,0) -> -487.47 | I40: =G40-H40 -> 0
A41: 620000003 - SUMINISTROS LABORATORIO | B41: - | G41: -1464.58 | H41: =VLOOKUP(A41,'PL Mensual 2026'!I:O,7,0) -> -1464.58 | I41: =G41-H41 -> 0
A42: 620000004 - GTOS. ANALISIS LABORATORIOS | B42: - | G42: -1476.12 | H42: =VLOOKUP(A42,'PL Mensual 2026'!I:O,7,0) -> -1476.12 | I42: =G42-H42 -> 0
A43: 621000001 - ALQUILER OFICINA CARTAGENA | B43: - | G43: -192 | H43: =VLOOKUP(A43,'PL Mensual 2026'!I:O,7,0) -> -192 | I43: =G43-H43 -> 0
A44: 621000014 - ALQUILER MURANO | B44: - | G44: -15421.92 | H44: =VLOOKUP(A44,'PL Mensual 2026'!I:O,7,0) -> -15421.92 | I44: =G44-H44 -> 0
A45: 621000024 - ALQUILER RENTING 2255KXN ANTONIO | B45: - | G45: - | H45: =VLOOKUP(A45,'PL Mensual 2026'!I:O,7,0) -> -
A46: 621000026 - ALQUILER RENTING 9319LCL CURRO | B46: - | G46: - | H46: =VLOOKUP(A46,'PL Mensual 2026'!I:O,7,0) -> -
A47: 621000031 - ALQUILER RENTING KONICA-MINOLTA Y KYOCERA | B47: - | G47: -338 | H47: =VLOOKUP(A47,'PL Mensual 2026'!I:O,7,0) -> -338 | I47: =G47-H47 -> 0
A48: 621000032 - ALQUILER RENTING 6665-LVK JOSE JUAN | B48: - | G48: -443.49 | H48: =VLOOKUP(A48,'PL Mensual 2026'!I:O,7,0) -> -443.49 | I48: =G48-H48 -> 0
A49: 621000033 - ALQUILER RENTING 2612-MBY ANTONIO | B49: - | G49: -399.42 | H49: =VLOOKUP(A49,'PL Mensual 2026'!I:O,7,0) -> -399.42 | I49: =G49-H49 -> 0
A50: 621000034 - ALQUILER RENTING 3108-LZM NIEVES | B50: - | G50: - | H50: =VLOOKUP(A50,'PL Mensual 2026'!I:O,7,0) -> -
A51: 621000037 - CARRETILLA STILL ELEKTROSTAPLER 516213H00521 | B51: - | G51: -200 | H51: =VLOOKUP(A51,'PL Mensual 2026'!I:O,7,0) -> -200 | I51: =G51-H51 -> 0
A52: 621000038 - CARRETILLA STILL ELEKTROSTAPLER 516223J00123 | B52: - | G52: -200.22 | H52: =VLOOKUP(A52,'PL Mensual 2026'!I:O,7,0) -> -200.22 | I52: =G52-H52 -> 0
A53: 621000039 - ALQUILER RENTING 5043-MWW CURRO | B53: - | G53: - | H53: =VLOOKUP(A53,'PL Mensual 2026'!I:O,7,0) -> -
A54: 621000040 - ALQUILER RENTING 8917-MZT JAVIER | B54: - | G54: -1172.14 | H54: =VLOOKUP(A54,'PL Mensual 2026'!I:O,7,0) -> -1172.14 | I54: =G54-H54 -> 0
A55: 621000041 - ALQUILER RENTING 8929-MZT RICARDO | B55: - | G55: -1015.21 | H55: =VLOOKUP(A55,'PL Mensual 2026'!I:O,7,0) -> -1015.21 | I55: =G55-H55 -> 0
A56: 621000042 - ALQUILER RENTING 4946-NFH GARCIA | B56: - | G56: -677.53 | H56: =VLOOKUP(A56,'PL Mensual 2026'!I:O,7,0) -> -677.53 | I56: =G56-H56 -> 0
A57: 621000044 - ALQUILER COMPRESOR DE TORNILLO 37KW KAESER BSD 75C | B57: - | G57: -1600 | H57: =VLOOKUP(A57,'PL Mensual 2026'!I:O,7,0) -> -1600 | I57: =G57-H57 -> 0
A58: 621000045 - ALQUILER RENTING 3421-NJT PERE | B58: - | G58: -1208.01 | H58: =VLOOKUP(A58,'PL Mensual 2026'!I:O,7,0) -> -1208.01 | I58: =G58-H58 -> 0
A59: 621000046 - ALQUILER CARRETILLAS | B59: - | G59: -665 | H59: =VLOOKUP(A59,'PL Mensual 2026'!I:O,7,0) -> 0 | I59: =G59-H59 -> -665
A60: - - | B60: Maquila | G60: 665 | H60: =VLOOKUP(A60,'PL Mensual 2026'!I:O,7,0) -> #N/A | I60: =G60-H60 -> #N/A
A61: 622000001 - REPAR. EQUIPOS INFORM. Y FOTOCOPIADORAS | B61: - | G61: - | H61: =VLOOKUP(A61,'PL Mensual 2026'!I:O,7,0) -> -
A62: 622000004 - REP. Y CONSERV. CARRETILLA ELECTRICA | B62: - | G62: - | H62: =VLOOKUP(A62,'PL Mensual 2026'!I:O,7,0) -> -
A63: 622000005 - REP. Y MANT. EQUIPOS SEGURIDAD | B63: - | G63: -183.66 | H63: =VLOOKUP(A63,'PL Mensual 2026'!I:O,7,0) -> -183.66 | I63: =G63-H63 -> 0
A64: 622000006 - REP. Y MANT. INSTALACIONES VARIAS | B64: - | G64: - | H64: =VLOOKUP(A64,'PL Mensual 2026'!I:O,7,0) -> -
A65: 622000007 - REP. Y MANT. HYUNDAI 0377CJG | B65: - | G65: - | H65: =VLOOKUP(A65,'PL Mensual 2026'!I:O,7,0) -> -
A66: 622000008 - REP. Y MANT. MAQUINA BARREDORA | B66: - | G66: - | H66: =VLOOKUP(A66,'PL Mensual 2026'!I:O,7,0) -> -
A67: 622000012 - LIMPIEZA OFICINAS, LABORATORIO Y VESTUARIOS | B67: - | G67: - | H67: =VLOOKUP(A67,'PL Mensual 2026'!I:O,7,0) -> -
A68: 622010200 - ALCAPLANT | B68: - | G68: -942.88 | H68: =VLOOKUP(A68,'PL Mensual 2026'!I:O,7,0) -> -942.88 | I68: =G68-H68 -> 0
A69: 622010201 - REPARACIONES ALCAPLANT | B69: - | G69: - | H69: =VLOOKUP(A69,'PL Mensual 2026'!I:O,7,0) -> -
A70: 622010300 - SOLIDOS | B70: - | G70: - | H70: =VLOOKUP(A70,'PL Mensual 2026'!I:O,7,0) -> -
A71: 622010400 - LIQUIDOS | B71: - | G71: -1092.45 | H71: =VLOOKUP(A71,'PL Mensual 2026'!I:O,7,0) -> -1092.45 | I71: =G71-H71 -> 0
A72: 622010500 - REPUESTOS MANT. VARIOS | B72: - | G72: -799.04 | H72: =VLOOKUP(A72,'PL Mensual 2026'!I:O,7,0) -> -799.04 | I72: =G72-H72 -> 0
A73: 622010501 - REP. MANT. FONTANERIA | B73: - | G73: - | H73: =VLOOKUP(A73,'PL Mensual 2026'!I:O,7,0) -> -
A74: 623000001 - SERV. PROF. INDEPENDIENTES | B74: - | G74: -21698 | H74: =VLOOKUP(A74,'PL Mensual 2026'!I:O,7,0) -> -21698 | I74: =G74-H74 -> 0
A75: 623000002 - SERVICIOS CONTABLES Y FINANCIEROS | B75: - | G75: -2891.19 | H75: =VLOOKUP(A75,'PL Mensual 2026'!I:O,7,0) -> -2891.19 | I75: =G75-H75 -> 0
A76: 623000003 - SERV. NOTARIOS, REGISTROS, LEGAL | B76: - | G76: -2271.24 | H76: =VLOOKUP(A76,'PL Mensual 2026'!I:O,7,0) -> -2271.24 | I76: =G76-H76 -> 0
A77: 623000004 - GTOS. BCS. OKO | B77: - | G77: -1574.71 | H77: =VLOOKUP(A77,'PL Mensual 2026'!I:O,7,0) -> -1574.71 | I77: =G77-H77 -> 0
A78: 623000005 - SERVICIOS PREST. CAMARA COMERCIO | B78: - | G78: -429 | H78: =VLOOKUP(A78,'PL Mensual 2026'!I:O,7,0) -> -429 | I78: =G78-H78 -> 0
A79: 623100002 - GASTOS MAURICIO ALISTE | B79: - | G79: -4225.22 | H79: =VLOOKUP(A79,'PL Mensual 2026'!I:O,7,0) -> -4225.22 | I79: =G79-H79 -> 0
A80: 623100006 - GASTOS Y SERVICIOS AGRICOLA DEL JUCAR | B80: - | G80: -141.55 | H80: =VLOOKUP(A80,'PL Mensual 2026'!I:O,7,0) -> -141.55 | I80: =G80-H80 -> 0
A81: 623100007 - GASTOS Y SUELDO MEHMET CILOGLU | B81: - | G81: - | H81: =VLOOKUP(A81,'PL Mensual 2026'!I:O,7,0) -> -
A82: 623100008 - COMISIONES KAMAL KEHAL | B82: - | G82: -3398.55 | H82: =VLOOKUP(A82,'PL Mensual 2026'!I:O,7,0) -> -3398.55 | I82: =G82-H82 -> 0
A83: 623200001 - GASTOS MARCAS EN ESPAÑA | B83: - | G83: -377.56 | H83: =VLOOKUP(A83,'PL Mensual 2026'!I:O,7,0) -> -377.56 | I83: =G83-H83 -> 0
A84: 623200006 - MARCAS UNION EUROPEA | B84: - | G84: - | H84: =VLOOKUP(A84,'PL Mensual 2026'!I:O,7,0) -> -
A85: 623200008 - GASTOS MARCAS EGIPTO | B85: - | G85: -53.14 | H85: =VLOOKUP(A85,'PL Mensual 2026'!I:O,7,0) -> -53.14 | I85: =G85-H85 -> 0
A86: 623200009 - GASTOS MARCAS MARRUECOS | B86: - | G86: - | H86: =VLOOKUP(A86,'PL Mensual 2026'!I:O,7,0) -> -
A87: 623200010 - GASTOS MARCAS TURQUIA | B87: - | G87: - | H87: =VLOOKUP(A87,'PL Mensual 2026'!I:O,7,0) -> -
A88: 623200011 - GASTOS MARCAS COLOMBIA | B88: - | G88: -53.12 | H88: =VLOOKUP(A88,'PL Mensual 2026'!I:O,7,0) -> -53.12 | I88: =G88-H88 -> 0
A89: 623200016 - GASTOS MARCAS ECUADOR | B89: - | G89: - | H89: =VLOOKUP(A89,'PL Mensual 2026'!I:O,7,0) -> -
A90: 623200020 - GASTOS MARCAS TUNEZ | B90: - | G90: - | H90: =VLOOKUP(A90,'PL Mensual 2026'!I:O,7,0) -> -
A91: 623200022 - GASTOS MARCAS BOLIVIA | B91: - | G91: - | H91: =VLOOKUP(A91,'PL Mensual 2026'!I:O,7,0) -> -
A92: 623200023 - GASTOS MARCAS ARGELIA | B92: - | G92: -53.12 | H92: =VLOOKUP(A92,'PL Mensual 2026'!I:O,7,0) -> -53.12 | I92: =G92-H92 -> 0
A93: 623200024 - GASTOS MARCAS INTERNACIONALES | B93: - | G93: - | H93: =VLOOKUP(A93,'PL Mensual 2026'!I:O,7,0) -> -
A94: 623200029 - GASTOS MARCAS GEORGIA | B94: - | G94: - | H94: =VLOOKUP(A94,'PL Mensual 2026'!I:O,7,0) -> -
A95: 623200030 - GASTOS MARCAS AZERBAIYAN | B95: - | G95: -53.12 | H95: =VLOOKUP(A95,'PL Mensual 2026'!I:O,7,0) -> -53.12 | I95: =G95-H95 -> 0
A96: 624000001 - TRANSPORTES NACIONAL | B96: - | G96: -17966.84 | H96: =VLOOKUP(A96,'PL Mensual 2026'!I:O,7,0) -> -17966.84 | I96: =G96-H96 -> 0
A97: 624000002 - TRANSPORTE INTERNACIONAL | B97: - | G97: -951.38 | H97: =VLOOKUP(A97,'PL Mensual 2026'!I:O,7,0) -> -951.38 | I97: =G97-H97 -> 0
A98: 624000003 - TRANSPORTES CANARIAS | B98: - | G98: -6790.44 | H98: =VLOOKUP(A98,'PL Mensual 2026'!I:O,7,0) -> -6790.44 | I98: =G98-H98 -> 0
A99: 624000004 - GTOS. FLETE REP. AL CLIENTE | B99: - | G99: - | H99: =VLOOKUP(A99,'PL Mensual 2026'!I:O,7,0) -> -
A100: 624000005 - TTE. PAQUETERIA | B100: - | G100: - | H100: =VLOOKUP(A100,'PL Mensual 2026'!I:O,7,0) -> -
...

Sheet Extraitems 2026
B1: EXTRAITEMS
B2: 2026
B4: 1 | C4: 2 | D4: 3 | E4: 4 | F4: 5 | G4: 6 | H4: 7 | I4: 8 | J4: 9 | K4: 10 | L4: 11 | M4: 12
B5: ENERO | C5: FEBRERO | D5: MARZO | E5: ABRIL | F5: MAYO | G5: JUNIO | H5: JULIO | I5: AGOSTO | J5: SEPTIEMBRE | K5: OCTUBRE | L5: NOVIEMBRE | M5: DICIEMBRE
B6: 26.2017 | C6: 40.07489 | D6: 29.27336 | E6: 0

Sheet Ext Items 2026
N1: =SUM(N3:N2300) -> -100248.99
A2: Fecha de contabilización | B2: Mes report | C2: Empresa | D2: Grupo EI | E2: Factura | F2: Nivel 1 | G2: Nivel 2 | H2: Nivel 3 | I2: Nivel 4 | J2: Nivel 5 | K2: Cuenta contable | L2: Acreedor/Proveedor | M2: Detalle | N2: Importe € | O2: Comentarios
A3: 46053 | B3: 1 | C3: Codiagro | D3: Personal | F3: RESULTADO DEL EJERCICIO | G3: RESULTADO ANTES DE IMPUESTOS | H3: RESULTADO DE LA EXPLOTACION | I3: 6.- Gastos de personal | J3: (640) Sueldos y salarios | K3: - | N3: 7934.82 | O3: NIEVES RUIZ CESPEDES
A4: 46053 | B4: 1 | C4: Codiagro | D4: Personal | F4: RESULTADO DEL EJERCICIO | G4: RESULTADO ANTES DE IMPUESTOS | H4: RESULTADO DE LA EXPLOTACION | I4: 6.- Gastos de personal | J4: (642) Seguridad social a cargo empresa | K4: - | N4: 1693.8 | O4: NIEVES RUIZ CESPEDES
A5: 46053 | B5: 1 | C5: Codiagro | D5: Personal | F5: RESULTADO DEL EJERCICIO | G5: RESULTADO ANTES DE IMPUESTOS | H5: RESULTADO DE LA EXPLOTACION | I5: 6.- Gastos de personal | J5: (640) Sueldos y salarios | K5: - | N5: 2166.76 | O5: FRANCISCO LAGOSTENA DE GUZMAN
A6: 46053 | B6: 1 | C6: Codiagro | D6: Personal | F6: RESULTADO DEL EJERCICIO | G6: RESULTADO ANTES DE IMPUESTOS | H6: RESULTADO DE LA EXPLOTACION | I6: 6.- Gastos de personal | J6: (642) Seguridad social a cargo empresa | K6: - | N6: 911.41 | O6: FRANCISCO LAGOSTENA DE GUZMAN
A7: 46053 | B7: 1 | C7: Codiagro | D7: Personal | F7: RESULTADO DEL EJERCICIO | G7: RESULTADO ANTES DE IMPUESTOS | H7: RESULTADO DE LA EXPLOTACION | I7: 6.- Gastos de personal | J7: (640) Sueldos y salarios | K7: - | N7: 4444.21 | O7: RAUL AMELA MELIA
A8: 46053 | B8: 1 | C8: Codiagro | D8: Personal | F8: RESULTADO DEL EJERCICIO | G8: RESULTADO ANTES DE IMPUESTOS | H8: RESULTADO DE LA EXPLOTACION | I8: 6.- Gastos de personal | J8: (642) Seguridad social a cargo empresa | K8: - | N8: 1720.91 | O8: RAUL AMELA MELIA
A9: 46053 | B9: 1 | C9: Codiagro | D9: Personal | F9: RESULTADO DEL EJERCICIO | G9: RESULTADO ANTES DE IMPUESTOS | H9: RESULTADO DE LA EXPLOTACION | I9: 6.- Gastos de personal | J9: (640) Sueldos y salarios | K9: - | N9: 5593.98 | O9: CARLOS BARREDA MAS
A10: 46053 | B10: 1 | C10: Codiagro | D10: Personal | F10: RESULTADO DEL EJERCICIO | G10: RESULTADO ANTES DE IMPUESTOS | H10: RESULTADO DE LA EXPLOTACION | I10: 6.- Gastos de personal | J10: (642) Seguridad social a cargo empresa | K10: - | N10: 1735.81 | O10: CARLOS BARREDA MAS
A11: 46081 | B11: 2 | C11: Codiagro | D11: Personal | F11: RESULTADO DEL EJERCICIO | G11: RESULTADO ANTES DE IMPUESTOS | H11: RESULTADO DE LA EXPLOTACION | I11: 6.- Gastos de personal | J11: (640) Sueldos y salarios | K11: - | N11: 9273.34 | O11: NIEVES RUIZ CESPEDES
A12: 46081 | B12: 2 | C12: Codiagro | D12: Personal | F12: RESULTADO DEL EJERCICIO | G12: RESULTADO ANTES DE IMPUESTOS | H12: RESULTADO DE LA EXPLOTACION | I12: 6.- Gastos de personal | J12: (642) Seguridad social a cargo empresa | K12: - | N12: 1774.57 | O12: NIEVES RUIZ CESPEDES
A13: 46081 | B13: 2 | C13: Codiagro | D13: Personal | F13: RESULTADO DEL EJERCICIO | G13: RESULTADO ANTES DE IMPUESTOS | H13: RESULTADO DE LA EXPLOTACION | I13: 6.- Gastos de personal | J13: (640) Sueldos y salarios | K13: - | N13: 3414.13 | O13: FRANCISCO LAGOSTENA DE GUZMAN
A14: 46081 | B14: 2 | C14: Codiagro | D14: Personal | F14: RESULTADO DEL EJERCICIO | G14: RESULTADO ANTES DE IMPUESTOS | H14: RESULTADO DE LA EXPLOTACION | I14: 6.- Gastos de personal | J14: (642) Seguridad social a cargo empresa | K14: - | N14: 838.96 | O14: FRANCISCO LAGOSTENA DE GUZMAN
... A59: 46265 | B59: 8 | C59: Codiagro | D59: INDIVIDUAL-Ext Item Codiagro-SAS | F59: RESULTADO DEL EJERCICIO | G59: RESULTADO ANTES DE IMPUESTOS | H59: RESULTADO DE LA EXPLOTACION | I59: 4.- Aprovisionamientos | J59: (602) Compras de otros aprovisionamientos | K59: 602000001 - COMPRA DE ENVASES Y EMBALAJES | N59: 59572.72 | O59: Packing repercutido

Sheet Ext Items Budget
L1: =SUBTOTAL(9,L3:L52) -> 174.42694
A2: Ext Item/Cap | B2: Empresa | C2: Normalización | D2: Nivel 1 | E2: Nivel 2 | F2: Nivel 3 | G2: Nivel 4 | H2: Nivel 5 | I2: Cuenta | J2: Mes | K2: Importe EUR | L2: Importe EUR ('000) | M2: Comentarios | N2: Grupo EI
B3: Codiagro | C3: Gastos de personal | D3: RESULTADO DEL EJERCICIO | E3: RESULTADO ANTES DE IMPUESTOS | F3: RESULTADO DE LA EXPLOTACION | G3: 6.- Gastos de personal | H3: (640) Sueldos y salarios | J3: 1 | K3: 9918.52 | L3: =+K3/1000 -> 9.91852 | M3: NIEVES RUIZ CESPEDES | N3: Personal
B4: Codiagro | C4: Gastos de personal | D4: RESULTADO DEL EJERCICIO | E4: RESULTADO ANTES DE IMPUESTOS | F4: RESULTADO DE LA EXPLOTACION | G4: 6.- Gastos de personal | H4: (642) Seguridad social a cargo empresa | J4: 1 | K4: 6612.34 | L4: =+K4/1000 -> 6.61234 | M4: NIEVES RUIZ CESPEDES | N4: Personal
B5: Codiagro | C5: Gastos de personal | D5: RESULTADO DEL EJERCICIO | E5: RESULTADO ANTES DE IMPUESTOS | F5: RESULTADO DE LA EXPLOTACION | G5: 6.- Gastos de personal | H5: (640) Sueldos y salarios | J5: 2 | K5: 1295.91 | L5: =+K5/1000 -> 1.29591 | M5: NIEVES RUIZ CESPEDES | N5: Personal
B6: Codiagro | C6: Gastos de personal | D6: RESULTADO DEL EJERCICIO | E6: RESULTADO ANTES DE IMPUESTOS | F6: RESULTADO DE LA EXPLOTACION | G6: 6.- Gastos de personal | H6: (642) Seguridad social a cargo empresa | J6: 2 | K6: 863.94 | L6: =+K6/1000 -> 0.86394 | M6: NIEVES RUIZ CESPEDES | N6: Personal
B7: Codiagro | C7: Gastos de personal | D7: RESULTADO DEL EJERCICIO | E7: RESULTADO ANTES DE IMPUESTOS | F7: RESULTADO DE LA EXPLOTACION | G7: 6.- Gastos de personal | H7: (640) Sueldos y salarios | J7: 1 | K7: 1708.45 | L7: =+K7/1000 -> 1.70845 | M7: FRANCISCO LAGOSTENA DE GUZMAN | N7: Personal
B8: Codiagro | C8: Gastos de personal | D8: RESULTADO DEL EJERCICIO | E8: RESULTADO ANTES DE IMPUESTOS | F8: RESULTADO DE LA EXPLOTACION | G8: 6.- Gastos de personal | H8: (642) Seguridad social a cargo empresa | J8: 1 | K8: 659.51 | L8: =+K8/1000 -> 0.65951 | M8: FRANCISCO LAGOSTENA DE GUZMAN | N8: Personal
B9: Codiagro | C9: Gastos de personal | D9: RESULTADO DEL EJERCICIO | E9: RESULTADO ANTES DE IMPUESTOS | F9: RESULTADO DE LA EXPLOTACION | G9: 6.- Gastos de personal | H9: (640) Sueldos y salarios | J9: 2 | K9: 1708.45 | L9: =+K9/1000 -> 1.70845 | M9: FRANCISCO LAGOSTENA DE GUZMAN | N9: Personal
B10: Codiagro | C10: Gastos de personal | D10: RESULTADO DEL EJERCICIO | E10: RESULTADO ANTES DE IMPUESTOS | F10: RESULTADO DE LA EXPLOTACION | G10: 6.- Gastos de personal | H10: (642) Seguridad social a cargo empresa | J10: 2 | K10: 659.51 | L10: =+K10/1000 -> 0.65951 | M10: FRANCISCO LAGOSTENA DE GUZMAN | N10: Personal
B11: Codiagro | C11: Gastos de personal | D11: RESULTADO DEL EJERCICIO | E11: RESULTADO ANTES DE IMPUESTOS | F11: RESULTADO DE LA EXPLOTACION | G11: 6.- Gastos de personal | H11: (640) Sueldos y salarios | J11: 3 | K11: 1708.45 | L11: =+K11/1000 -> 1.70845 | M11: FRANCISCO LAGOSTENA DE GUZMAN | N11: Personal
B12: Codiagro | C12: Gastos de personal | D12: RESULTADO DEL EJERCICIO | E12: RESULTADO ANTES DE IMPUESTOS | F12: RESULTADO DE LA EXPLOTACION | G12: 6.- Gastos de personal | H12: (642) Seguridad social a cargo empresa | J12: 3 | K12: 659.51 | L12: =+K12/1000 -> 0.65951 | M12: FRANCISCO LAGOSTENA DE GUZMAN | N12: Personal
B13: Codiagro | C13: Gastos de personal | D13: RESULTADO DEL EJERCICIO | E13: RESULTADO ANTES DE IMPUESTOS | F13: RESULTADO DE LA EXPLOTACION | G13: 6.- Gastos de personal | H13: (641) Indemnizaciones | J13: 3 | K13: 19064.32 | L13: =+K13/1000 -> 19.06432 | M13: FRANCISCO LAGOSTENA DE GUZMAN | N13: Indemnizaciones
B14: Codiagro | C14: Gastos de personal | D14: RESULTADO DEL EJERCICIO | E14: RESULTADO ANTES DE IMPUESTOS | F14: RESULTADO DE LA EXPLOTACION | G14: 6.- Gastos de personal | H14: (640) Sueldos y salarios | J14: 1 | K14: 5700.18 | L14: =+K14/1000 -> 5.70018 | M14: RAUL AMELA MELIA | N14: Personal
... B45: Codiagro | C45: Gastos de personal | D45: RESULTADO DEL EJERCICIO | E45: RESULTADO ANTES DE IMPUESTOS | F45: RESULTADO DE LA EXPLOTACION | G45: 6.- Gastos de personal | H45: (642) Seguridad social a cargo empresa | J45: 8 | K45: 950.61913 | L45: =+K45/1000 -> 0.95061913 | M45: CARLOS BARREDA MAS | N45: Personal

Sheet Ext Items 2025
P1: Mes report | Q1: (Todas)
B2: Fecha de contabilización | C2: Mes report | D2: Empresa | E2: Concepto | F2: Factura | G2: Cuenta contable | H2: Normalización | I2: Nivel 4 | J2: Acreedor/Proveedor | K2: Detalle | L2: Importe | M2: Importe ('000)
B3: 45667 | C3: =MONTH(B3) -> 1 | D3: CODIAGRO | E3: Indemnizaciones | G3: 641000007 | H3: Gastos de personal | K3: INDEMNIZACION MIGUEL BELLES | L3: 112732.33 | M3: 112.73233 | P3: Etiquetas de fila | Q3: Suma de Importe ('000)
B4: 45734 | C4: =MONTH(B4) -> 3 | D4: CODIAGRO | E4: Costes Transacción | F4: 440FVN25000044 | G4: 623000001 | H4: Otros Gastos Operativos | J4: AUREN CORPORATE | K4: Asesoramiento | L4: 14111.19 | M4: 14.11119 | P4: Costes Transacción | Q4: 161.05205
B5: 45744 | C5: =MONTH(B5) -> 3 | D5: CODIAGRO | E5: Costes Transacción | F5: 440FVN25000048 | G5: 623000001 | H5: Otros Gastos Operativos | J5: AUREN CORPORATE | K5: Asesoramiento | L5: 4000 | M5: 4 | P5: Gastos periodos anteriores | Q5: 134.19399
B6: 45776 | C6: =MONTH(B6) -> 4 | D6: CODIAGRO | E6: Costes Transacción | F6: 440FVN25000070 | G6: 623000001 | H6: Otros Gastos Operativos | J6: AUREN CORPORATE | K6: Asesoramiento | L6: 4297.23 | M6: 4.29723 | P6: Gastos Representación | Q6: 48.99744
B7: 45805 | C7: =MONTH(B7) -> 5 | D7: CODIAGRO | E7: Costes Transacción | F7: 440FVN25000094 | G7: 623000001 | H7: Otros Gastos Operativos | J7: AUREN CORPORATE | K7: Asesoramiento | L7: 4000 | M7: 4 | P7: Indemnizaciones | Q7: 112.73233
B8: 45838 | C8: =MONTH(B8) -> 6 | D8: CODIAGRO | E8: Costes Transacción | F8: 440FVN25000118 | G8: 623000001 | H8: Otros Gastos Operativos | J8: AUREN CORPORATE | K8: Asesoramiento | L8: 4000 | M8: 4 | P8: TICS | Q8: 1.8
B9: 45866 | C9: =MONTH(B9) -> 7 | D9: CODIAGRO | E9: Costes Transacción | F9: 440FVN25000150 | G9: 623000001 | H9: Otros Gastos Operativos | J9: AUREN CORPORATE | K9: Asesoramiento | L9: 4589.25 | M9: 4.58925 | P9: Gastos de personal | Q9: 310.01329
B10: 45901 | C10: =MONTH(B10) -> 9 | D10: CODIAGRO | E10: Costes Transacción | F10: 440FVN25000171 | G10: 623000001 | H10: Otros Gastos Operativos | J10: AUREN CORPORATE | K10: Asesoramiento | L10: 4000 | M10: 4 | P10: Rappel Dotra (cliente Egipto) 2024 | Q10: 139.50071
B11: 45929 | C11: =MONTH(B11) -> 9 | D11: CODIAGRO | E11: Costes Transacción | F11: 440FVN25000191 | G11: 623000001 | H11: Otros Gastos Operativos | J11: AUREN CORPORATE | K11: Asesoramiento | L11: 4054.38 | M11: 4.05438 | P11: Reparaciones extraordinarias | Q11: 50.39565
B12: 45875 | C12: =MONTH(B12) -> 8 | D12: CODIAGRO | E12: Gastos Representación | F12: 52/000095 | G12: 627000005 | H12: Otros Gastos Operativos | J12: VILLARREAL CLUB DE FUTBOL | K12: PALCO TEMPORADA | L12: 40493.75 | M12: 40.49375 | P12: Total general | Q12: 958.68546
B13: 45875 | C13: =MONTH(B13) -> 8 | D13: CODIAGRO | E13: Gastos Representación | F13: 52/000095 | G13: 634100000 | H13: Otros Gastos Operativos | J13: VILLARREAL CLUB DE FUTBOL | K13: IVA NO DEDUCIBLE del Palco | L13: 8503.69 | M13: 8.50369
B14: 45962 | C14: =MONTH(B14) -> 11 | D14: CODIAGRO | E14: Costes Transacción | F14: 3522900376 | G14: 623000001 | H14: Otros Gastos Operativos | J14: KPMG | K14: VENDOR DIU DILIGENCE | L14: 118000 | M14: 118
B15: 45993 | C15: =MONTH(B15) -> 12 | D15: CODIAGRO | E15: TICS | G15: 623000001 | H15: Otros Gastos Operativos | J15: INTRALINKS | K15: NUBE PARA LA DOCUMENTACION | L15: 1800 | M15: 1.8
B16: 45748 | C16: =MONTH(B16) -> 4 | D16: CODIAGRO | E16: Reparaciones extraordinarias | F16: 153/25 | G16: 622010201 | H16: Otros Gastos Operativos | J16: MAQUISEL SERVICIOS QUIMICOS, S.L.L. | K16: REPARACION ALCAPLANT CADA 6/7 AÑOS | L16: 11502.5 | M16: 11.5025
B17: 45748 | C17: =MONTH(B17) -> 4 | D17: CODIAGRO | E17: Reparaciones extraordinarias | F17: 154/25 | G17: 622010201 | H17: Otros Gastos Operativos | J17: MAQUISEL SERVICIOS QUIMICOS, S.L.L. | K17: REPARACION ALCAPLANT CADA 6/7 AÑOS | L17: 11049.5 | M17: 11.0495
B18: 45992 | C18: =MONTH(B18) -> 12 | D18: CODIAGRO | E18: Reparaciones extraordinarias | F18: 278/25 | G18: 622010201 | H18: Otros Gastos Operativos | J18: MAQUISEL SERVICIOS QUIMICOS, S.L.L. | K18: REPARACION ALCAPLANT CADA 6/7 AÑOS | L18: 12968 | M18: 12.968
B19: 45992 | C19: =MONTH(B19) -> 12 | D19: CODIAGRO | E19: Reparaciones extraordinarias | F19: 560/25 | G19: 622000006 | H19: Otros Gastos Operativos | J19: MAQUISEL SERVICIOS QUIMICOS, S.L.L. | L19: 4897 | M19: 4.897
B20: 45713 | C20: =MONTH(B20) -> 2 | D20: CODIAGRO | E20: Reparaciones extraordinarias | F20: 25000332 | G20: 622010200 | H20: Otros Gastos Operativos | J20: OLIVER & BATLLE, S.A. | K20: REPARACION ALCAPLANT CADA 6/7 AÑOS | L20: 9978.65 | M20: 9.97865
B21: 45721 | C21: =MONTH(B21) -> 3 | D21: CODIAGRO | E21: Gastos periodos anteriores | G21: 627000008 | H21: Otros Gastos Operativos | K21: Marketing 2024 Marcoser | L21: 8479.84 | M21: 8.47984
B22: 45677 | C22: =MONTH(B22) -> 1 | D22: CODIAGRO | E22: Gastos periodos anteriores | G22: 623100006 | H22: Otros Gastos Operativos | K22: Comisiones 2024 Alfonso (agricola Juncar) | L22: 21135 | M22: 21.135
B23: 45660 | C23: =MONTH(B23) -> 1 | D23: CODIAGRO | E23: Gastos periodos anteriores | G23: 623100007 | H23: Otros Gastos Operativos | K23: Comisiones 2024 Mehmet | L23: 18863.51 | M23: 18.86351
B24: 45692 | C24: =MONTH(B24) -> 2 | D24: CODIAGRO | E24: Gastos periodos anteriores | G24: 623100007 | H24: Otros Gastos Operativos | K24: Comisiones 2024 Mehmet | L24: 3423.3 | M24: 3.4233
B25: 45838 | C25: =MONTH(B25) -> 6 | D25: CODIAGRO | E25: Gastos de personal | G25: 640000000 | H25: Gastos de personal | K25: Importe Producción-Planta 2024 | L25: 26136.49 | M25: 26.13649
B26: 45930 | C26: =MONTH(B26) -> 9 | D26: CODIAGRO | E26: Gastos de personal | G26: 647000000 | H26: Gastos de personal | K26: Retribución consejo 2024 | L26: 65849.57 | M26: 65.84957
B27: 45827 | C27: =MONTH(B27) -> 6 | D27: CODIAGRO | E27: Gastos periodos anteriores | G27: 623000001 | H27: Otros Gastos Operativos | K27: Comisiones Eurofertil 2024 | L27: 10969.96 | M27: 10.96996
B28: 45740 | C28: =MONTH(B28) -> 3 | D28: CODIAGRO | E28: Gastos periodos anteriores | G28: 623000001 | H28: Otros Gastos Operativos | K28: Comisiones Eurofertil 2024,2023,2022 | L28: 50283.36 | M28: 50.28336
B29: 45775 | C29: =MONTH(B29) -> 4 | D29: CODIAGRO | E29: Rappel Dotra (cliente Egipto) 2024 | G29: 709000000 | H29: Ventas | K29: Rappel Dotra (cliente Egipto) 2024 | L29: 102533.02 | M29: 102.53302
B30: 45775 | C30: =MONTH(B30) -> 4 | D30: CODIAGRO | E30: Rappel Dotra (cliente Egipto) 2024 | G30: 709000000 | H30: Ventas | K30: Rappel Dotra (cliente Egipto) 2024 | L30: 36967.69 | M30: 36.96769
B31: 45716 | C31: =MONTH(B31) -> 2 | D31: CODIAGRO | E31: Gastos de personal | G31: 640000000 | H31: Gastos de personal | K31: Bonus 2024 | L31: 135000 | M31: 135
B32: 45665 | C32: =MONTH(B32) -> 1 | D32: CODIAGRO | E32: Gastos periodos anteriores | G32: 627000010 | H32: Otros Gastos Operativos | K32: Promoción 2023 Tecnicos Campo Egido | L32: 9175.46 | M32: 9.17546
... B35: 45838 | C35: =MONTH(B35) -> 6 | D35: CODIAGRO | E35: Gastos de personal | G35: 640000000 | H35: Gastos de personal | K35: Comisiones Comercial en nomina de periodo de junio a diciembre 2024 - Pendiente el asiento | L35: 41513.615 | M35: 41.513615

Sheet Cuenta Ok
A1: AGOSTO
A2: Cuenta | B2: SALDO
A3: 700000000 - Ventas de mercaderías | B3: 802410.56
A4: 700000001 - VENTA MERCADERIAS POR ANTICIPO | B4: 0
A5: 700000624 - VENTA POR TRANSP. REP. AL CLIENTE | B5: -
A6: 700001624 - VENTA POR TRANSPORTE REP. AL CLIENTE DEFINITIVO | B6: 11429
A7: 700000769 - INGRESOS POR RETRASOS DE COBRO Y ACTUALIZACION | B7: -
A8: 700000769 - INGRESOS POR RETRASOS DE COBRO Y ACTUALIZACION | B8: -
A9: 702000000 - Ventas de productos semiterminados | B9: 141074.4
A10: 703000000 - Ventas de subproductos y residuos | B10: -
A11: 704000000 - Ventas de envases y embalajes | B11: 59572.72
A12: 705000000 - Prestaciones de servicios | B12: 101520
A13: 705000001 - INGRESO POR GESTIÓN DE ENVASES | B13: 1694.59
A14: 706000000 - Dtos. ventas por pronto pago mercaderías | B14: -
A15: 709000000 - «Rappels» ventas de mercaderías | B15: -
A16: 709000001 - PROVISION RAPPELS | B16: -16000
A17: 771000000 - Beneficios del inmovilizado material | B17: -
A18: 678000000 - Gastos excepcionales | B18: -0.02
A19: 778000000 - Ingresos excepcionales | B19: 0.01
A20: 711000000 - Variación existencias de prod. semiterminados | B20: 27557.62
A21: 712000000 - Variación existencias de prod. terminados | B21: -20822.98
A22: 601000000 - Compras de materias primas | B22: -265516.84
A23: 601000001 - COMPRAS MAT. PRIMAS INTRACOMUNITARIAS | B23: -64800
A24: 602000001 - COMPRA DE ENVASES Y EMBALAJES | B24: -68178.76
A25: 602000000 - Compras de otros aprovisionamientos | B25: -
A26: 602000002 - COMPRA DE ETIQUETAS | B26: -2886.68
A27: 602000003 - COMPRA DE PALETS | B27: -4331.6
A28: 602000004 - COMPRA MATERIAL DE LIMPIEZA | B28: -
A29: 602000005 - COMPRA MATERIAL DE OFICINA | B29: -
A30: 602000006 - COMPRA TAPONES DE ENVASES | B30: -1108.8
A31: 602000007 - COMPRAS LABORATORIO | B31: 0
A32: 602000008 - RESPUESTOS PLANTA | B32: 0
A33: 602000010 - COMPRA RIBBON | B33: 0
A34: 602000011 - COMPRAS VARIAS PLANTA | B34: -371.23
A35: 602000012 - REPUESTOS INFORMATICOS | B35: -
A36: 602000013 - COMPRA TINTA INPRESORA ETIQUETAS | B36: -2557.66
A37: 602000100 - ENVASES Y EMBALAJES A DEVOLVER | B37: -
A38: 607000000 - Trabajos realizados por otras empresas | B38: -25856.5
A39: 611000000 - Variación de existencias de materias primas | B39: -59037.03
A40: 612000000 - Variación de existencias otros aprovisionamientos | B40: -4582.08
A41: 759000000 - Ingresos por servicios diversos | B41: 0
A42: 640000000 - Sueldos y salarios | B42: -128060.74
A43: 640000200 - GASTO POR E. TRAB. TEMPORAL | B43: 0
A44: 640000300 - PROVISION PAGAS EXTRAS | B44: 0
A45: 641000000 - Indemnizaciones | B45: -
A46: 641000007 - INDEMNIZACION MIGUEL BELLES | B46: 0
A47: 642000000 - Seguridad Social a cargo empresa | B47: -24572.05
A48: 649000000 - Otros gastos sociales | B48: 0
A49: 649000001 - GASTOS COMERCIALES NIEVES RUIZ | B49: 0
A50: 649000002 - GASTOS EMPR. ANTONIO ANDREU | B50: 0
A51: 649000004 - GASTOS COMERCIALES RICARDO PEREZ | B51: 0
A52: 649000007 - GASTOS COMERCIALES J.PAREDES | B52: 0
A53: 649000009 - GASTOS COMERCIALES J.A. GARCIA | B53: 0
A54: 649000010 - GASTOS EMP. CURRO | B54: 0
A55: 649000012 - GASTOS COMERCIALES IRENE GARCIA | B55: 0
A56: 649000100 - GTOS. CURSOS PERSONAL | B56: -
A57: 649000101 - GTOS. SEG. Y RIESGOS PERSONAL | B57: 0
A58: 649000102 - GASTOS ROPA UNIFORMES TRABAJADORES | B58: 0
A59: 649000103 - GASTOS COMBUSTIBLE TRAB. | B59: 0
A60: 649100001 - GTOS. COMIDAS TRAB. | B60: 0
A61: 649100002 - GASTOS TRAB. EMPRESA VARIOS | B61: 0
A62: 620000002 - COMPRAS LABORATORIO | B62: -
A63: 620000003 - SUMINISTROS LABORATORIO | B63: -399.98
A64: 620000004 - GTOS. ANALISIS LABORATORIOS | B64: -911.52
A65: 621000001 - ALQUILER OFICINA CARTAGENA | B65: -192
A66: 621000014 - ALQUILER MURANO | B66: -
A67: 621000023 - RENTING TRANSPALETA ELECTRICA DE PIE | B67: 0
A68: 621000024 - ALQUILER RENTING 2255KXN ANTONIO | B68: -
A69: 621000025 - ALQUILER RENTING 9128 LBT NIEVES | B69: 0
A70: 621000026 - ALQUILER RENTING 9319LCL CURRO | B70: -
A71: 621000030 - ALQUILER RENTING 1075-LSC GARCIA | B71: 0
A72: 621000031 - ALQUILER RENTING KONICA-MINOLTA Y KYOCERA | B72: -338
A73: 621000032 - ALQUILER RENTING 6665-LVK JOSE JUAN | B73: -
A74: 621000033 - ALQUILER RENTING 2612-MBY ANTONIO | B74: -399.42
A75: 621000034 - ALQUILER RENTING 3108-LZM NIEVES | B75: -1139.16
A76: 621000035 - ALQUILER RENTING 2142-MCS RICARDO | B76: 0
A77: 621000036 - ALQUILER RENTING 3277-MDX JAVIER | B77: 0
A78: 621000037 - CARRETILLA STILL ELEKTROSTAPLER 516213H00521 | B78: -400
A79: 621000038 - CARRETILLA STILL ELEKTROSTAPLER 516223J00123 | B79: -400.44
A80: 621000039 - ALQUILER RENTING 5043-MWW CURRO | B80: -
A81: 621000040 - ALQUILER RENTING 8917-MZT JAVIER | B81: -
A82: 621000041 - ALQUILER RENTING 8929-MZT RICARDO | B82: -
A83: 621000042 - ALQUILER RENTING 4946-NFH GARCIA | B83: -677.53
A84: 621000044 - ALQUILER COMPRESOR DE TORNILLO 37KW KAESER BSD 75C | B84: -1600
A85: 621000045 - ALQUILER RENTING 3421-NJT PERE | B85: -1208.01
A86: 621000046 - ALQUILER CARRETILLAS | B86: -1407
A87: 622000001 - REPAR. EQUIPOS INFORM. Y FOTOCOPIADORAS | B87: -
A88: 622000004 - REP. Y CONSERV. CARRETILLA ELECTRICA | B88: -115.48
A89: 622000005 - REP. Y MANT. EQUIPOS SEGURIDAD | B89: -
A90: 622000006 - REP. Y MANT. INSTALACIONES VARIAS | B90: -
A91: 622000007 - REP. Y MANT. HYUNDAI 0377CJG | B91: -
A92: 622000008 - REP. Y MANT. MAQUINA BARREDORA | B92: -
A93: 622000009 - REP. Y MANT. FURGONETA 2589CRJ | B93: 0
A94: 622000012 - LIMPIEZA OFICINAS, LABORATORIO Y VESTUARIOS | B94: -977.98
A95: 622010000 MANTENIMIENTO | B95: -
A96: 622010001 - MANTENIMIENTO REPUESTO COMPRA AMAZON | B96: 0
A97: 622010200 - ALCAPLANT | B97: -1983.69
A98: 622010201 - REPARACIONES ALCAPLANT | B98: -5848.16
A99: 622010300 - SOLIDOS | B99: -11965.55
A100: 622010400 - LIQUIDOS | B100: -288.39
...

Sheet P&L Mensualitzada 2025
A1: Sin Ext Item
A2: CODIAGRO
A4: € '000 | B4: Ene | C4: Feb | D4: Mar | E4: Abr | F4: May | G4: Jun | H4: Jul | I4: Ago | J4: Sep | K4: Oct | L4: Nov | M4: Dic | N4: 2025
A5: Ventas | B5: 622.28714 | C5: 1062.4411 | D5: 1795.147 | E5: 1534.3509 | F5: 1483.9152 | G5: 1760.942 | H5: 1314.5645 | I5: 664.49694 | J5: 842.11579 | K5: 699.58345 | L5: 749.69916 | M5: 248.50601 | N5: =SUM(B5:M5) -> 12778.049
A6: COGS | B6: -518.09465 | C6: -451.51496 | D6: -510.02511 | E6: -440.06148 | F6: -669.88812 | G6: -248.36745 | H6: -330.56434 | I6: -99.2048 | J6: -265.37091 | K6: -361.07371 | L6: -275.74654 | M6: -116.4287 | N6: =SUM(B6:M6) -> -4286.3408
A7: Gross Profit | B7: =SUM(B5:B6) -> 104.19249 | C7: =SUM(C5:C6) -> 610.92613 | D7: =SUM(D5:D6) -> 1285.1219 | E7: =SUM(E5:E6) -> 1094.2894 | F7: =SUM(F5:F6) -> 814.02707 | G7: =SUM(G5:G6) -> 1512.5746 | H7: =SUM(H5:H6) -> 984.00014 | I7: =SUM(I5:I6) -> 565.29214 | ... N7: =SUM(N5:N6) -> 8491.7084
A8: % Gross Margin | B8: =+B7/B5 -> 0.16743475 | C8: =+C7/C5 -> 0.57502118 | D8: =+D7/D5 -> 0.71588672 | E8: =+E7/E5 -> 0.71319371 | F8: =+F7/F5 -> 0.54856711 | G8: =+G7/G5 -> 0.85895762 | H8: =+H7/H5 -> 0.74853699 | I8: =+I7/I5 -> 0.85070691 | ... N8: =+N7/N5 -> 0.66455437
A10: Gastos de Personal | B10: 17.397715 | C10: -169.90228 | D10: -215.24045 | E10: -145.05985 | F10: -141.27428 | G10: -98.245985 | H10: -218.74298 | I10: -131.97477 | J10: -133.7212 | K10: -300.72411 | L10: -153.08435 | M10: -172.01862 | N10: =SUM(B10:M10) -> -1862.5912
A11: % of Revenue | B11: =+B10/B5 -> 0.027957697 | C11: =+C10/C5 -> -0.15991689 | D11: =+D10/D5 -> -0.11990129 | E11: =+E10/E5 -> -0.09454151 | F11: =+F10/F5 -> -0.095203743 | G11: =+G10/G5 -> -0.055791721 | H11: =+H10/H5 -> -0.16639958 | I11: =+I10/I5 -> -0.19860854 | ... N11: =+N10/N5 -> -0.14576491
A13: Otros Ingresos Operativos | B13: 0 | C13: 0.23944 | D13: 0 | E13: 0 | F13: 0.43575 | G13: 0.11769 | H13: 0 | I13: 0 | J13: 0 | K13: 1.80096 | L13: 0 | M13: 47.20436 | N13: =SUM(B13:M13) -> 49.7982
A14: Otros Gastos Operativos | B14: -83.04566 | C14: -74.84982 | D14: -105.74077 | E14: -91.37805 | F14: -108.29459 | G14: -116.04261 | H14: -102.38971 | I14: -68.70525 | J14: -73.91279 | K14: -122.16905 | L14: -68.32762 | M14: -239.07332 | N14: =SUM(B14:M14) -> -1253.9292
A15: Operating Expenses | B15: =SUM(B13:B14) -> -83.04566 | C15: =SUM(C13:C14) -> -74.61038 | D15: =SUM(D13:D14) -> -105.74077 | E15: =SUM(E13:E14) -> -91.37805 | F15: =SUM(F13:F14) -> -107.85884 | G15: =SUM(G13:G14) -> -115.92492 | H15: =SUM(H13:H14) -> -102.38971 | I15: =SUM(I13:I14) -> -68.70525 | ... N15: =SUM(N13:N14) -> -1204.131
A16: % of Revenue | B16: =+B15/B5 -> -0.13345232 | C16: =+C15/C5 -> -0.070225428 | D16: =+D15/D5 -> -0.058903682 | E16: =+E15/E5 -> -0.059554858 | F16: =+F15/F5 -> -0.072685313 | G16: =+G15/G5 -> -0.065831197 | H16: =+H15/H5 -> -0.077888694 | I16: =+I15/I5 -> -0.10339438 | ... N16: =+N15/N5 -> -0.094234341
A17: Gastos Fijos | B17: =+B15+B10 -> -65.647945 | C17: =+C15+C10 -> -244.51266 | D17: =+D15+D10 -> -320.98122 | E17: =+E15+E10 -> -236.4379 | F17: =+F15+F10 -> -249.13312 | G17: =+G15+G10 -> -214.1709 | H17: =+H15+H10 -> -321.13269 | I17: =+I15+I10 -> -200.68002 | ... N17: =+N15+N10 -> -3066.7222
A18: % of Revenue | B18: =+B17/B5 -> -0.10549462 | C18: =+C17/C5 -> -0.23014232 | D18: =+D17/D5 -> -0.17880498 | E18: =+E17/E5 -> -0.15409637 | F18: =+F17/F5 -> -0.16788906 | G18: =+G17/G5 -> -0.12162292 | H18: =+H17/H5 -> -0.24428828 | I18: =+I17/I5 -> -0.30200293 | ... N18: =+N17/N5 -> -0.23999925
A19: Adjusted EBITDA | B19: =+B7+B17 -> 38.544545 | C19: =+C7+C17 -> 366.41347 | D19: =+D7+D17 -> 964.1407 | E19: =+E7+E17 -> 857.85151 | F19: =+F7+F17 -> 564.89395 | G19: =+G7+G17 -> 1298.4036 | H19: =+H7+H17 -> 662.86745 | I19: =+I7+I17 -> 364.61212 | ... N19: =+N7+N17 -> 5424.9862
A20: % Adj. EBITDA Margin | B20: =+B19/B5 -> 0.061940128 | C20: =+C19/C5 -> 0.34487886 | D20: =+D19/D5 -> 0.53708175 | E20: =+E19/E5 -> 0.55909735 | F20: =+F19/F5 -> 0.38067806 | G20: =+G19/G5 -> 0.7373347 | H20: =+H19/H5 -> 0.50424872 | I20: =+I19/I5 -> 0.54870399 | ... N20: =+N19/N5 -> 0.42455512
A22: D&A | B22: 0 | C22: 0 | D22: 0 | E22: 0 | F22: 0 | G22: 0 | H22: 0 | I22: 0 | J22: 0 | K22: -194.71201 | L22: -19.4712 | M22: -34.07237 | N22: =SUM(B22:M22) -> -248.25558
A23: Other Gains/Losses | B23: 0.92147 | C23: 0.03183 | D23: -1e-05 | E23: 2e-05 | F23: 0.00031 | G23: 0.00228 | H23: 0.00357 | I23: 0.47301 | J23: -0.04064 | K23: 0.81001 | L23: 0.00443 | M23: 0.15045 | N23: =SUM(B23:M23) -> 2.35673
A24: Adjusted EBIT | B24: =+B19+B22+B23 -> 39.466015 | C24: =+C19+C22+C23 -> 366.4453 | D24: =+D19+D22+D23 -> 964.14069 | E24: =+E19+E22+E23 -> 857.85153 | F24: =+F19+F22+F23 -> 564.89426 | G24: =+G19+G22+G23 -> 1298.4059 | H24: =+H19+H22+H23 -> 662.87102 | I24: =+I19+I22+I23 -> 365.08513 | ... N24: =+N19+N22+N23 -> 5179.0874
A25: % EBIT Margin | B25: =+B24/B5 -> 0.063420907 | C25: =+C24/C5 -> 0.34490882 | D25: =+D24/D5 -> 0.53708174 | E25: =+E24/E5 -> 0.55909736 | F25: =+F24/F5 -> 0.38067827 | G25: =+G24/G5 -> 0.737336 | H25: =+H24/H5 -> 0.50425143 | I25: =+I24/I5 -> 0.54941582 | ... N25: =+N24/N5 -> 0.40531127
A29: Suma de Importe ('000) | B29: Etiquetas de columna
A30: Etiquetas de fila | B30: ENERO | C30: FEBRERO | D30: MARZO | E30: ABRIL | F30: MAYO | G30: JUNIO | H30: JULIO | I30: AGOSTO | J30: SEPTIEMBRE | K30: OCTUBRE | L30: NOVIEMBRE | M30: DICIEMBRE | N30: Total general
A31: Gastos de personal | B31: 112.73233 | N31: 112.73233
A32: Otros Gastos Operativos | C32: 9.97865 | D32: 18.11119 | E32: 26.84923 | F32: 4 | G32: 4 | H32: 4.58925 | I32: 48.99744 | J32: 8.05438 | K32: 0 | L32: 118 | M32: 19.665 | N32: 262.24514
A33: Total general | B33: 112.73233 | C33: 9.97865 | D33: 18.11119 | E33: 26.84923 | F33: 4 | G33: 4 | H33: 4.58925 | I33: 48.99744 | J33: 8.05438 | K33: 0 | L33: 118 | M33: 19.665 | N33: 374.97747

Sheet Budget26 sin EI
B2: Ene-26 - € '000 | C2: 1 | D2: 2 | E2: 3 | F2: 4 | G2: 5 | H2: 6 | I2: 7 | J2: 8 | K2: 9 | L2: 10 | M2: 11 | N2: 12 | O2: Total
B3: Ventas | C3: 805.69363 | D3: 1513.248 | E3: 2302.2173 | F3: 1891.2553 | G3: 1636.9092 | H3: 2150.2566 | I3: 1348.021 | J3: 776.07561 | K3: 1026.5685 | L3: 798.56718 | M3: 1030.243 | N3: 659.94465 | O3: 15939
B4: COGS | C4: -276.70291 | D4: -519.70141 | E4: -790.66062 | F4: -649.52213 | G4: -562.17093 | H4: -738.47207 | I4: -462.95679 | J4: -266.53106 | K4: -352.55893 | L4: -274.25544 | M4: -353.82089 | N4: -226.64682 | O4: -5474
B5: Gross Profit | C5: 528.99072 | D5: 993.54657 | E5: 1511.5567 | F5: 1241.7332 | G5: 1074.7383 | H5: 1411.7845 | I5: 885.06424 | J5: 509.54455 | K5: 674.00956 | L5: 524.31174 | M5: 676.42212 | N5: 433.29783 | O5: 10465
B6: % Gross Margin | C6: 0.6565656 | D6: 0.6565656 | E6: 0.6565656 | F6: 0.6565656 | G6: 0.6565656 | H6: 0.6565656 | I6: 0.6565656 | J6: 0.6565656 | K6: 0.6565656 | L6: 0.6565656 | M6: 0.6565656 | N6: 0.65656692 | O6: 0.65656566
B8: Gastos de Personal | C8: -138.431 | D8: -152.80201 | E8: -268.64421 | F8: -157.32982 | G8: -157.32982 | H8: -290.07649 | I8: -157.32982 | J8: -162.96321 | K8: -174.23 | L8: -174.23 | M8: -174.23 | N8: -306.97667 | O8: -2314.5731
C9: -0.17181593 | D9: -0.10097619 | E9: -0.11668934 | F9: -0.08318804 | G9: -0.096113958 | H9: -0.1349032 | I9: -0.1167117 | J9: -0.20998367 | K9: -0.16972078 | L9: -0.21817826 | M9: -0.16911544 | N9: -0.46515517 | O9: -0.14521445
B10: Otros Ingresos Operativos | C10: 0 | D10: 0 | E10: 0 | F10: 0 | G10: 0 | H10: 0 | I10: 0 | J10: 0 | K10: 0 | L10: 0 | M10: 0 | N10: 0 | O10: 0
B11: Otros Gastos Operativos | C11: -183.33533 | D11: -133.85532 | E11: -128.94532 | F11: -131.89532 | G11: -126.94533 | H11: -160.19533 | I11: -152.80333 | J11: -117.79333 | K11: -120.05333 | L11: -144.84269 | M11: -148.99269 | N11: -180.34269 | O11: -1730
B12: Operating Expenses | C12: -183.33533 | D12: -133.85532 | E12: -128.94532 | F12: -131.89532 | G12: -126.94533 | H12: -160.19533 | I12: -152.80333 | J12: -117.79333 | K12: -120.05333 | L12: -144.84269 | M12: -148.99269 | N12: -180.34269 | O12: -1730
C13: 0.22754968 | D13: 0.08845564 | E13: 0.056009187 | F13: 0.069739563 | G13: 0.077551845 | H13: 0.074500565 | I13: 0.11335382 | J13: 0.15178074 | K13: 0.11694624 | L13: 0.18137821 | M13: 0.14461898 | N13: 0.27326941 | O13: 0.1085388
B14: Adjusted EBITDA | C14: 207.22439 | D14: 706.88924 | E14: 1113.9672 | F14: 952.50805 | G14: 790.46313 | H14: 961.51268 | I14: 574.93109 | J14: 228.78802 | K14: 379.72623 | L14: 205.23905 | M14: 353.19943 | N14: -54.021526 | O14: 6420.4269
B15: % Adj. EBITDA Margin | C15: 0.25719999 | D15: 0.46713377 | E15: 0.48386708 | F15: 0.503638 | G15: 0.4828998 | H15: 0.44716184 | I15: 0.42650009 | J15: 0.29480119 | K15: 0.36989858 | L15: 0.25700913 | M15: 0.34283119 | N15: -0.081857662 | O15: 0.40281241
B17: D&A | C17: -20.833333 | D17: -20.833333 | E17: -20.833333 | F17: -20.833333 | G17: -20.833333 | H17: -20.833333 | I17: -20.833333 | J17: -20.833333 | K17: -20.833333 | L17: -20.833333 | M17: -20.833333 | N17: -20.833333 | O17: -250
B18: Other Gains/Losses | C18: 0 | D18: 0 | E18: 0 | F18: 0 | G18: 0 | H18: 0 | I18: 0 | J18: 0 | K18: 0 | L18: 0 | M18: 0 | N18: 0 | O18: 0
B19: EBIT | C19: 186.39106 | D19: 686.05591 | E19: 1093.1338 | F19: 931.67471 | G19: 769.6298 | H19: 940.67935 | I19: 554.09775 | J19: 207.95468 | K19: 358.8929 | L19: 184.40572 | M19: 332.3661 | N19: -74.854859 | O19: 6170.4269
B20: % EBIT Margin | C20: 0.23134235 | D20: 0.45336648 | E20: 0.47481783 | F20: 0.49262239 | G20: 0.47017256 | H20: 0.43747307 | I20: 0.41104533 | J20: 0.26795673 | K20: 0.34960443 | L20: 0.23092074 | M20: 0.32260942 | N20: -0.11342597 | O20: 0.38712761
