Workbook
Name Datos: #REF!

Sheet 2027
BV2: Seleccionar las formulas de P&L YTD Mes anterior y de P&L YTD Actual y cambiar la referencia al mes anterior
C4: RELLENAR | L4: RELLENAR | U4: RELLENAR | AD4: RELLENAR | AM4: RELLENAR | AV4: RELLENAR | BE4: RELLENAR | BN4: RELLENAR | BW4: RELLENAR | CF4: RELLENAR | CO4: RELLENAR | CX4: RELLENAR | DG4: RELLENAR
B5: MES | C5: 1 | K5: MES | L5: 2 | T5: MES | U5: 3 | AC5: MES | AD5: 4 | AL5: MES | AM5: 5 | AU5: MES | AV5: 6 | BD5: MES | BE5: 7 | BM5: MES | BN5: 8 | BV5: MES | BW5: 9 | CE5: MES | CF5: 10 | CN5: MES | CO5: 11 | CW5: MES | CX5: 12 | DF5: MES | DG5: 12 | DH5: YTD
B7: P&L Mensual | K7: P&L Mensual | T7: P&L Mensual | AC7: P&L Mensual | AL7: P&L Mensual | AU7: P&L Mensual | BD7: P&L Mensual | BM7: P&L Mensual | BV7: P&L Mensual | CE7: P&L Mensual | CN7: P&L Mensual | CW7: P&L Mensual | DF7: P&L YTD
E8: Variación | H8: Variación | N8: Variación | Q8: Variación | W8: Variación | Z8: Variación | AF8: Variación | AI8: Variación | AO8: Variación | AR8: Variación | AX8: Variación | BA8: Variación | BG8: Variación | BJ8: Variación | BP8: Variación | BS8: Variación | BY8: Variación | CB8: Variación | CH8: Variación | CK8: Variación | CQ8: Variación | CT8: Variación | CZ8: Variación | DC8: Variación | DI8: Variación | DL8: Variación
B9: € '000 | C9: 2027A | D9: 2026A | E9: EUR | F9: % | G9: 2027B | H9: EUR | I9: % | K9: € '000 | L9: 2027A | M9: 2026A | N9: EUR | O9: % | P9: 2027B | Q9: EUR | R9: % | T9: € '000 | U9: 2027A | V9: 2026A | W9: EUR | X9: % | Y9: 2027B | Z9: EUR | AA9: % | AC9: € '000 | AD9: 2027A | AE9: 2026A | AF9: EUR | AG9: % | AH9: 2027B | AI9: EUR | AJ9: % | AL9: € '000 | AM9: 2027A | AN9: 2026A | AO9: EUR | AP9: % | AQ9: 2027B | AR9: EUR | AS9: % | AU9: € '000 | AV9: 2027A | AW9: 2026A | AX9: EUR | AY9: % | AZ9: 2027B | BA9: EUR | BB9: % | BD9: € '000 | BE9: 2027A | BF9: 2026A | BG9: EUR | BH9: % | BI9: 2027B | BJ9: EUR | BK9: % | BM9: € '000 | BN9: 2027A | BO9: 2026A | BP9: EUR | BQ9: % | BR9: 2027B | BS9: EUR | BT9: % | BV9: € '000 | BW9: 2027A | BX9: 2026A | BY9: EUR | BZ9: % | CA9: 2027B | CB9: EUR | CC9: % | CE9: € '000 | CF9: 2027A | CG9: 2026A | CH9: EUR | CI9: % | CJ9: 2027B | CK9: EUR | CL9: % | CN9: € '000 | CO9: 2027A | CP9: 2026A | CQ9: EUR | CR9: % | CS9: 2027B | CT9: EUR | CU9: % | CW9: € '000 | CX9: 2027A | CY9: 2026A | CZ9: EUR | DA9: % | DB9: 2027B | DC9: EUR | DD9: % | DF9: € '000 | DG9: 2027A | DH9: 2026A | DI9: EUR | DJ9: % | DK9: 2027B | DL9: EUR | DM9: %
B10: Ventas | C10: =(GETPIVOTDATA("ene-27 ",TABLA!$B$3,"Nivel 4","1.- Importe neto de la cifra de negocios"))/1000 -> 1143.7325 | D10: 983.81713 | E10: =C10-D10 -> 159.91537 | F10: =+IF(IFERROR(C10/D10-1,"-")<300%,IFERROR(C10/D10-1,"-"),"n.a.") -> 0.16254583 | G10: =C10 -> 1143.7325 | H10: =C10-G10 -> 0 | I10: =+IF(IFERROR(C10/G10-1,"-")<300%,IFERROR(C10/G10-1,"-"),"n.a.") -> 0 | K10: Ventas | L10: =(GETPIVOTDATA("feb-27 ",TABLA!$B$3,"Nivel 4","1.- Importe neto de la cifra de negocios"))/1000 -> 1852.6413 | M10: 1470.4281 | N10: =L10-M10 -> 382.21312 | O10: =+IF(IFERROR(L10/M10-1,"-")<300%,IFERROR(L10/M10-1,"-"),"n.a.") -> 0.25993322 | P10: =L10 -> 1852.6413 | Q10: =L10-P10 -> 0 | R10: =+IF(IFERROR(L10/P10-1,"-")<300%,IFERROR(L10/P10-1,"-"),"n.a.") -> 0 | T10: Ventas | U10: =(GETPIVOTDATA("mar-27 ",TABLA!$B$3,"Nivel 4","1.- Importe neto de la cifra de negocios"))/1000 -> 1777.1341 | V10: 1533.7894 | W10: =U10-V10 -> 243.34469 | X10: =+IF(IFERROR(U10/V10-1,"-")<300%,IFERROR(U10/V10-1,"-"),"n.a.") -> 0.15865587 | Y10: =U10 -> 1777.1341 | Z10: =U10-Y10 -> 0 | AA10: =+IF(IFERROR(U10/Y10-1,"-")<300%,IFERROR(U10/Y10-1,"-"),"n.a.") -> 0 | AC10: Ventas | AD10: =(GETPIVOTDATA("abr-27 ",TABLA!$B$3,"Nivel 4","1.- Importe neto de la cifra de negocios"))/1000 -> 1430.7518 | AE10: 1462.1463 | AF10: =AD10-AE10 -> -31.39444 | AG10: =+IF(IFERROR(AD10/AE10-1,"-")<300%,IFERROR(AD10/AE10-1,"-"),"n.a.") -> -0.021471477 | AH10: =AD10 -> 1430.7518 | AI10: =AD10-AH10 -> 0 | AJ10: =+IF(IFERROR(AD10/AH10-1,"-")<300%,IFERROR(AD10/AH10-1,"-"),"n.a.") -> 0 | AL10: Ventas | AM10: =(GETPIVOTDATA("may-27 ",TABLA!$B$3,"Nivel 4","1.- Importe neto de la cifra de negocios"))/1000 -> 2349.0314 | AN10: 1925.9299 | AO10: =AM10-AN10 -> 423.10151 | AP10: =+IF(IFERROR(AM10/AN10-1,"-")<300%,IFERROR(AM10/AN10-1,"-"),"n.a.") -> 0.21968687 | AQ10: =AM10 -> 2349.0314 | AR10: =AM10-AQ10 -> 0 | AS10: =+IF(IFERROR(AM10/AQ10-1,"-")<300%,IFERROR(AM10/AQ10-1,"-"),"n.a.") -> 0 | AU10: Ventas | AV10: =GETPIVOTDATA("jun-27 ",TABLA!$B$3,"Nivel 4","1.- Importe neto de la cifra de negocios")/1000 -> 2329.4837 | AW10: 1962.2618 | AX10: =AV10-AW10 -> 367.22192 | AY10: =+IF(IFERROR(AV10/AW10-1,"-")<300%,IFERROR(AV10/AW10-1,"-"),"n.a.") -> 0.18714216 | AZ10: =AV10 -> 2329.4837 | BA10: =AV10-AZ10 -> 0 | BB10: =+IF(IFERROR(AV10/AZ10-1,"-")<300%,IFERROR(AV10/AZ10-1,"-"),"n.a.") -> 0 | BD10: Ventas | BE10: =(GETPIVOTDATA("jul-27 ",TABLA!$B$3,"Nivel 4","1.- Importe neto de la cifra de negocios"))/1000 -> 1477.9823 | BF10: 1290.6542 | BG10: =BE10-BF10 -> 187.32808 | BH10: =+IF(IFERROR(BE10/BF10-1,"-")<300%,IFERROR(BE10/BF10-1,"-"),"n.a.") -> 0.14514196 | BI10: =BE10 -> 1477.9823 | BJ10: =BE10-BI10 -> 0 | BK10: =+IF(IFERROR(BE10/BI10-1,"-")<300%,IFERROR(BE10/BI10-1,"-"),"n.a.") -> 0 | BM10: Ventas | BN10: =(GETPIVOTDATA("ago-27 ",TABLA!$B$3,"Nivel 4","1.- Importe neto de la cifra de negocios"))/1000 -> 943.22127 | BO10: 788.10515 | BP10: =BN10-BO10 -> 155.11612 | BQ10: =+IF(IFERROR(BN10/BO10-1,"-")<300%,IFERROR(BN10/BO10-1,"-"),"n.a.") -> 0.1968216 | BR10: =BN10 -> 943.22127 | BS10: =BN10-BR10 -> 0 | BT10: =+IF(IFERROR(BN10/BR10-1,"-")<300%,IFERROR(BN10/BR10-1,"-"),"n.a.") -> 0 | BV10: Ventas | BW10: =(GETPIVOTDATA("sep-27 ",TABLA!$B$3,"Nivel 4","1.- Importe neto de la cifra de negocios"))/1000 -> 547.89618 | BX10: 483.08374 | BY10: =BW10-BX10 -> 64.81244 | BZ10: =+IF(IFERROR(BW10/BX10-1,"-")<300%,IFERROR(BW10/BX10-1,"-"),"n.a.") -> 0.13416399 | CA10: =BW10 -> 547.89618 | CB10: =BW10-CA10 -> 0 | CC10: =+IF(IFERROR(BW10/CA10-1,"-")<300%,IFERROR(BW10/CA10-1,"-"),"n.a.") -> 0 | CE10: Ventas | CF10: =(GETPIVOTDATA("oct-27 ",TABLA!$B$3,"Nivel 4","1.- Importe neto de la cifra de negocios"))/1000 -> 916.29691 | CG10: 912.05501 | CH10: =CF10-CG10 -> 4.2419 | CI10: =+IF(IFERROR(CF10/CG10-1,"-")<300%,IFERROR(CF10/CG10-1,"-"),"n.a.") -> 0.0046509256 | CJ10: =CF10 -> 916.29691 | CK10: =CF10-CJ10 -> 0 | CL10: =+IF(IFERROR(CF10/CJ10-1,"-")<300%,IFERROR(CF10/CJ10-1,"-"),"n.a.") -> 0 | CN10: Ventas | CO10: =(GETPIVOTDATA("nov-27 ",TABLA!$B$3,"Nivel 4","1.- Importe neto de la cifra de negocios"))/1000 -> 1416.3668 | CP10: 1225.3218 | CQ10: =CO10-CP10 -> 191.04503 | CR10: =+IF(IFERROR(CO10/CP10-1,"-")<300%,IFERROR(CO10/CP10-1,"-"),"n.a.") -> 0.15591417 | CS10: =CO10 -> 1416.3668 | CT10: =CO10-CS10 -> 0 | CU10: =+IF(IFERROR(CO10/CS10-1,"-")<300%,IFERROR(CO10/CS10-1,"-"),"n.a.") -> 0 | CW10: Ventas | CX10: =(GETPIVOTDATA("dic-27 ",TABLA!$B$3,"Nivel 4","1.- Importe neto de la cifra de negocios"))/1000 -> 1553.6219 | CY10: 1142.4074 | CZ10: =CX10-CY10 -> 411.21455 | DA10: =+IF(IFERROR(CX10/CY10-1,"-")<300%,IFERROR(CX10/CY10-1,"-"),"n.a.") -> 0.35995439 | DB10: =CX10 -> 1553.6219 | DC10: =CX10-DB10 -> 0 | DD10: =+IF(IFERROR(CX10/DB10-1,"-")<300%,IFERROR(CX10/DB10-1,"-"),"n.a.") -> 0 | DF10: Ventas | DG10: =(GETPIVOTDATA("Total 2027 ",TABLA!$B$3,"Nivel 4","1.- Importe neto de la cifra de negocios"))/1000 -> 17738.16 | DH10: =CY10+CP10+CG10+BX10+BO10+BF10+AW10+AN10+AE10+V10+M10+D10 -> 15180 | DI10: =DG10-DH10 -> 2558.1603 | DJ10: =+IF(IFERROR(DG10/DH10-1,"-")<300%,IFERROR(DG10/DH10-1,"-"),"n.a.") -> 0.16852176 | DK10: =DG10 -> 17738.16 | DL10: =DG10-DK10 -> 0 | DM10: =+IF(IFERROR(DG10/DK10-1,"-")<300%,IFERROR(DG10/DK10-1,"-"),"n.a.") -> 0
B11: COGS | C11: =(GETPIVOTDATA("ene-27 ",TABLA!$B$3,"Nivel 4","2.- Variación de existencias")+GETPIVOTDATA("ene-27 ",TABLA!$B$3,"Nivel 4","4.- Aprovisionamientos"))/1000 -> -329.98443 | D11: -502.66555 | E11: =C11-D11 -> 172.68112 | F11: =+IF(IFERROR(C11/D11-1,"-")<300%,IFERROR(C11/D11-1,"-"),"n.a.") -> -0.34353084 | G11: =C11 -> -329.98443 | H11: =C11-G11 -> 0 | I11: =+IF(IFERROR(C11/G11-1,"-")<300%,IFERROR(C11/G11-1,"-"),"n.a.") -> 0 | K11: COGS | L11: =(GETPIVOTDATA("feb-27 ",TABLA!$B$3,"Nivel 4","2.- Variación de existencias")+GETPIVOTDATA("feb-27 ",TABLA!$B$3,"Nivel 4","4.- Aprovisionamientos"))/1000 -> -632.15977 | M11: -356.23716 | N11: =L11-M11 -> -275.92261 | O11: =+IF(IFERROR(L11/M11-1,"-")<300%,IFERROR(L11/M11-1,"-"),"n.a.") -> 0.77454752 | P11: =L11 -> -632.15977 | Q11: =L11-P11 -> 0 | R11: =+IF(IFERROR(L11/P11-1,"-")<300%,IFERROR(L11/P11-1,"-"),"n.a.") -> 0 | T11: COGS | U11: =(GETPIVOTDATA("mar-27 ",TABLA!$B$3,"Nivel 4","2.- Variación de existencias")+GETPIVOTDATA("mar-27 ",TABLA!$B$3,"Nivel 4","4.- Aprovisionamientos"))/1000 -> -664.98037 | V11: -385.69993 | W11: =U11-V11 -> -279.28044 | X11: =+IF(IFERROR(U11/V11-1,"-")<300%,IFERROR(U11/V11-1,"-"),"n.a.") -> 0.72408735 | Y11: =U11 -> -664.98037 | Z11: =U11-Y11 -> 0 | AA11: =+IF(IFERROR(U11/Y11-1,"-")<300%,IFERROR(U11/Y11-1,"-"),"n.a.") -> 0 | AC11: COGS | AD11: =(GETPIVOTDATA("abr-27 ",TABLA!$B$3,"Nivel 4","2.- Variación de existencias")+GETPIVOTDATA("abr-27 ",TABLA!$B$3,"Nivel 4","4.- Aprovisionamientos"))/1000 -> -517.76813 | AE11: -506.20309 | AF11: =AD11-AE11 -> -11.56504 | AG11: =+IF(IFERROR(AD11/AE11-1,"-")<300%,IFERROR(AD11/AE11-1,"-"),"n.a.") -> 0.02284664 | AH11: =AD11 -> -517.76813 | AI11: =AD11-AH11 -> 0 | AJ11: =+IF(IFERROR(AD11/AH11-1,"-")<300%,IFERROR(AD11/AH11-1,"-"),"n.a.") -> 0 | AL11: COGS | AM11: =(GETPIVOTDATA("may-27 ",TABLA!$B$3,"Nivel 4","2.- Variación de existencias")+GETPIVOTDATA("may-27 ",TABLA!$B$3,"Nivel 4","4.- Aprovisionamientos"))/1000 -> -838.0582 | AN11: -624.27234 | AO11: =AM11-AN11 -> -213.78586 | AP11: =+IF(IFERROR(AM11/AN11-1,"-")<300%,IFERROR(AM11/AN11-1,"-"),"n.a.") -> 0.34245608 | AQ11: =AM11 -> -838.0582 | AR11: =AM11-AQ11 -> 0 | AS11: =+IF(IFERROR(AM11/AQ11-1,"-")<300%,IFERROR(AM11/AQ11-1,"-"),"n.a.") -> 0 | AU11: COGS | AV11: =(GETPIVOTDATA("jun-27 ",TABLA!$B$3,"Nivel 4","2.- Variación de existencias")+GETPIVOTDATA("jun-27 ",TABLA!$B$3,"Nivel 4","4.- Aprovisionamientos"))/1000 -> -864.73897 | AW11: -743.55859 | AX11: =AV11-AW11 -> -121.18038 | AY11: =+IF(IFERROR(AV11/AW11-1,"-")<300%,IFERROR(AV11/AW11-1,"-"),"n.a.") -> 0.16297355 | AZ11: =AV11 -> -864.73897 | BA11: =AV11-AZ11 -> 0 | BB11: =+IF(IFERROR(AV11/AZ11-1,"-")<300%,IFERROR(AV11/AZ11-1,"-"),"n.a.") -> 0 | BD11: COGS | BE11: =(GETPIVOTDATA("jul-27 ",TABLA!$B$3,"Nivel 4","2.- Variación de existencias")+GETPIVOTDATA("jul-27 ",TABLA!$B$3,"Nivel 4","4.- Aprovisionamientos"))/1000 -> -562.0112 | BF11: -525.31503 | BG11: =BE11-BF11 -> -36.69617 | BH11: =+IF(IFERROR(BE11/BF11-1,"-")<300%,IFERROR(BE11/BF11-1,"-"),"n.a.") -> 0.069855549 | BI11: =BE11 -> -562.0112 | BJ11: =BE11-BI11 -> 0 | BK11: =+IF(IFERROR(BE11/BI11-1,"-")<300%,IFERROR(BE11/BI11-1,"-"),"n.a.") -> 0 | BM11: COGS | BN11: =(GETPIVOTDATA("ago-27 ",TABLA!$B$3,"Nivel 4","2.- Variación de existencias")+GETPIVOTDATA("ago-27 ",TABLA!$B$3,"Nivel 4","4.- Aprovisionamientos"))/1000 -> -339.95813 | BO11: -272.12023 | BP11: =BN11-BO11 -> -67.8379 | BQ11: =+IF(IFERROR(BN11/BO11-1,"-")<300%,IFERROR(BN11/BO11-1,"-"),"n.a.") -> 0.24929385 | BR11: =BN11 -> -339.95813 | BS11: =BN11-BR11 -> 0 | BT11: =+IF(IFERROR(BN11/BR11-1,"-")<300%,IFERROR(BN11/BR11-1,"-"),"n.a.") -> 0 | BV11: COGS | BW11: =(GETPIVOTDATA("sep-27 ",TABLA!$B$3,"Nivel 4","2.- Variación de existencias")+GETPIVOTDATA("sep-27 ",TABLA!$B$3,"Nivel 4","4.- Aprovisionamientos"))/1000 -> -210.01274 | BX11: -161.79096 | BY11: =BW11-BX11 -> -48.22178 | BZ11: =+IF(IFERROR(BW11/BX11-1,"-")<300%,IFERROR(BW11/BX11-1,"-"),"n.a.") -> 0.2980499 | CA11: =BW11 -> -210.01274 | CB11: =BW11-CA11 -> 0 | CC11: =+IF(IFERROR(BW11/CA11-1,"-")<300%,IFERROR(BW11/CA11-1,"-"),"n.a.") -> 0 | CE11: COGS | CF11: =(GETPIVOTDATA("oct-27 ",TABLA!$B$3,"Nivel 4","2.- Variación de existencias")+GETPIVOTDATA("oct-27 ",TABLA!$B$3,"Nivel 4","4.- Aprovisionamientos"))/1000 -> -342.59167 | CG11: -302.10136 | CH11: =CF11-CG11 -> -40.49031 | CI11: =+IF(IFERROR(CF11/CG11-1,"-")<300%,IFERROR(CF11/CG11-1,"-"),"n.a.") -> 0.13402889 | CJ11: =CF11 -> -342.59167 | CK11: =CF11-CJ11 -> 0 | CL11: =+IF(IFERROR(CF11/CJ11-1,"-")<300%,IFERROR(CF11/CJ11-1,"-"),"n.a.") -> 0 | CN11: COGS | CO11: =(GETPIVOTDATA("nov-27 ",TABLA!$B$3,"Nivel 4","2.- Variación de existencias")+GETPIVOTDATA("nov-27 ",TABLA!$B$3,"Nivel 4","4.- Aprovisionamientos"))/1000 -> -542.66987 | CP11: -404.42328 | CQ11: =CO11-CP11 -> -138.24659 | CR11: =+IF(IFERROR(CO11/CP11-1,"-")<300%,IFERROR(CO11/CP11-1,"-"),"n.a.") -> 0.34183638 | CS11: =CO11 -> -542.66987 | CT11: =CO11-CS11 -> 0 | CU11: =+IF(IFERROR(CO11/CS11-1,"-")<300%,IFERROR(CO11/CS11-1,"-"),"n.a.") -> 0 | CW11: COGS | CX11: =(GETPIVOTDATA("dic-27 ",TABLA!$B$3,"Nivel 4","2.- Variación de existencias")+GETPIVOTDATA("dic-27 ",TABLA!$B$3,"Nivel 4","4.- Aprovisionamientos"))/1000 -> -562.31302 | CY11: -449.14533 | CZ11: =CX11-CY11 -> -113.16769 | DA11: =+IF(IFERROR(CX11/CY11-1,"-")<300%,IFERROR(CX11/CY11-1,"-"),"n.a.") -> 0.2519623 | DB11: =CX11 -> -562.31302 | DC11: =CX11-DB11 -> 0 | DD11: =+IF(IFERROR(CX11/DB11-1,"-")<300%,IFERROR(CX11/DB11-1,"-"),"n.a.") -> 0 | DF11: COGS | DG11: =(GETPIVOTDATA("Total 2027 ",TABLA!$B$3,"Nivel 4","2.- Variación de existencias")+GETPIVOTDATA("Total 2027 ",TABLA!$B$3,"Nivel 4","4.- Aprovisionamientos"))/1000 -> -6407.2465 | DH11: =CY11+CP11+CG11+BX11+BO11+BF11+AW11+AN11+AE11+V11+M11+D11 -> -5233.5328 | DI11: =DG11-DH11 -> -1173.7136 | DJ11: =+IF(IFERROR(DG11/DH11-1,"-")<300%,IFERROR(DG11/DH11-1,"-"),"n.a.") -> 0.22426794 | DK11: =DG11 -> -6407.2465 | DL11: =DG11-DK11 -> 0 | DM11: =+IF(IFERROR(DG11/DK11-1,"-")<300%,IFERROR(DG11/DK11-1,"-"),"n.a.") -> 0
B12: Gross Profit | C12: =C10+C11 -> 813.74807 | D12: 481.15158 | E12: =C12-D12 -> 332.59649 | F12: =+IF(IFERROR(C12/D12-1,"-")<300%,IFERROR(C12/D12-1,"-"),"n.a.") -> 0.69125096 | G12: =SUM(G10:G11) -> 813.74807 | H12: =C12-G12 -> 0 | I12: =+IF(IFERROR(C12/G12-1,"-")<300%,IFERROR(C12/G12-1,"-"),"n.a.") -> 0 | K12: Gross Profit | L12: =L10+L11 -> 1220.4815 | M12: 1114.191 | N12: =L12-M12 -> 106.29051 | O12: =+IF(IFERROR(L12/M12-1,"-")<300%,IFERROR(L12/M12-1,"-"),"n.a.") -> 0.095397029 | P12: =SUM(P10:P11) -> 1220.4815 | Q12: =L12-P12 -> 0 | R12: =+IF(IFERROR(L12/P12-1,"-")<300%,IFERROR(L12/P12-1,"-"),"n.a.") -> 0 | T12: Gross Profit | U12: =U10+U11 -> 1112.1537 | V12: 1148.0895 | W12: =U12-V12 -> -35.93575 | X12: =+IF(IFERROR(U12/V12-1,"-")<300%,IFERROR(U12/V12-1,"-"),"n.a.") -> -0.031300478 | Y12: =SUM(Y10:Y11) -> 1112.1537 | Z12: =U12-Y12 -> 0 | AA12: =+IF(IFERROR(U12/Y12-1,"-")<300%,IFERROR(U12/Y12-1,"-"),"n.a.") -> 0 | AC12: Gross Profit | AD12: =AD10+AD11 -> 912.98371 | AE12: 955.94319 | AF12: =AD12-AE12 -> -42.95948 | AG12: =+IF(IFERROR(AD12/AE12-1,"-")<300%,IFERROR(AD12/AE12-1,"-"),"n.a.") -> -0.044939365 | AH12: =SUM(AH10:AH11) -> 912.98371 | AI12: =AD12-AH12 -> 0 | AJ12: =+IF(IFERROR(AD12/AH12-1,"-")<300%,IFERROR(AD12/AH12-1,"-"),"n.a.") -> 0 | AL12: Gross Profit | AM12: =AM10+AM11 -> 1510.9732 | AN12: 1301.6576 | AO12: =AM12-AN12 -> 209.31565 | AP12: =+IF(IFERROR(AM12/AN12-1,"-")<300%,IFERROR(AM12/AN12-1,"-"),"n.a.") -> 0.160807 | AQ12: =SUM(AQ10:AQ11) -> 1510.9732 | AR12: =AM12-AQ12 -> 0 | AS12: =+IF(IFERROR(AM12/AQ12-1,"-")<300%,IFERROR(AM12/AQ12-1,"-"),"n.a.") -> 0 | AU12: Gross Profit | AV12: =AV10+AV11 -> 1464.7448 | AW12: 1218.7032 | AX12: =AV12-AW12 -> 246.04154 | AY12: =+IF(IFERROR(AV12/AW12-1,"-")<300%,IFERROR(AV12/AW12-1,"-"),"n.a.") -> 0.20188798 | AZ12: =SUM(AZ10:AZ11) -> 1464.7448 | BA12: =AV12-AZ12 -> 0 | BB12: =+IF(IFERROR(AV12/AZ12-1,"-")<300%,IFERROR(AV12/AZ12-1,"-"),"n.a.") -> 0 | BD12: Gross Profit | BE12: =BE10+BE11 -> 915.97111 | BF12: 765.3392 | BG12: =BE12-BF12 -> 150.63191 | BH12: =+IF(IFERROR(BE12/BF12-1,"-")<300%,IFERROR(BE12/BF12-1,"-"),"n.a.") -> 0.19681719 | BI12: =SUM(BI10:BI11) -> 915.97111 | BJ12: =BE12-BI12 -> 0 | BK12: =+IF(IFERROR(BE12/BI12-1,"-")<300%,IFERROR(BE12/BI12-1,"-"),"n.a.") -> 0 | BM12: Gross Profit | BN12: =BN10+BN11 -> 603.26314 | BO12: 515.98492 | BP12: =BN12-BO12 -> 87.27822 | BQ12: =+IF(IFERROR(BN12/BO12-1,"-")<300%,IFERROR(BN12/BO12-1,"-"),"n.a.") -> 0.16914878 | BR12: =SUM(BR10:BR11) -> 603.26314 | BS12: =BN12-BR12 -> 0 | BT12: =+IF(IFERROR(BN12/BR12-1,"-")<300%,IFERROR(BN12/BR12-1,"-"),"n.a.") -> 0 | BV12: Gross Profit | BW12: =BW10+BW11 -> 337.88344 | BX12: 321.29278 | BY12: =BW12-BX12 -> 16.59066 | BZ12: =+IF(IFERROR(BW12/BX12-1,"-")<300%,IFERROR(BW12/BX12-1,"-"),"n.a.") -> 0.051637201 | CA12: =SUM(CA10:CA11) -> 337.88344 | CB12: =BW12-CA12 -> 0 | CC12: =+IF(IFERROR(BW12/CA12-1,"-")<300%,IFERROR(BW12/CA12-1,"-"),"n.a.") -> 0 | CE12: Gross Profit | CF12: =CF10+CF11 -> 573.70524 | CG12: 609.95365 | CH12: =CF12-CG12 -> -36.24841 | CI12: =+IF(IFERROR(CF12/CG12-1,"-")<300%,IFERROR(CF12/CG12-1,"-"),"n.a.") -> -0.059428139 | CJ12: =SUM(CJ10:CJ11) -> 573.70524 | CK12: =CF12-CJ12 -> 0 | CL12: =+IF(IFERROR(CF12/CJ12-1,"-")<300%,IFERROR(CF12/CJ12-1,"-"),"n.a.") -> 0 | CN12: Gross Profit | CO12: =CO10+CO11 -> 873.69694 | CP12: 820.8985 | CQ12: =CO12-CP12 -> 52.79844 | CR12: =+IF(IFERROR(CO12/CP12-1,"-")<300%,IFERROR(CO12/CP12-1,"-"),"n.a.") -> 0.064317866 | CS12: =SUM(CS10:CS11) -> 873.69694 | CT12: =CO12-CS12 -> 0 | CU12: =+IF(IFERROR(CO12/CS12-1,"-")<300%,IFERROR(CO12/CS12-1,"-"),"n.a.") -> 0 | CW12: Gross Profit | CX12: =CX10+CX11 -> 991.30891 | CY12: 693.26205 | CZ12: =CX12-CY12 -> 298.04686 | DA12: =+IF(IFERROR(CX12/CY12-1,"-")<300%,IFERROR(CX12/CY12-1,"-"),"n.a.") -> 0.42991948 | DB12: =SUM(DB10:DB11) -> 991.30891 | DC12: =CX12-DB12 -> 0 | DD12: =+IF(IFERROR(CX12/DB12-1,"-")<300%,IFERROR(CX12/DB12-1,"-"),"n.a.") -> 0 | DF12: Gross Profit | DG12: =DG10+DG11 -> 11330.914 | DH12: =DH10+DH11 -> 9946.4671 | DI12: =DG12-DH12 -> 1384.4466 | DJ12: =+IF(IFERROR(DG12/DH12-1,"-")<300%,IFERROR(DG12/DH12-1,"-"),"n.a.") -> 0.13918979 | DK12: =SUM(DK10:DK11) -> 11330.914 | DL12: =DG12-DK12 -> 0 | DM12: =+IF(IFERROR(DG12/DK12-1,"-")<300%,IFERROR(DG12/DK12-1,"-"),"n.a.") -> 0
B13: % Gross Margin | C13: =C12/C10 -> 0.71148461 | D13: 0.48906607 | G13: =G12/G10 -> 0.71148461 | K13: % Gross Margin | L13: =L12/L10 -> 0.65877918 | M13: 0.75773236 | P13: =P12/P10 -> 0.65877918 | T13: % Gross Margin | U13: =U12/U10 -> 0.62581306 | V13: 0.74853136 | Y13: =Y12/Y10 -> 0.62581306 | AC13: % Gross Margin | AD13: =AD12/AD10 -> 0.63811465 | AE13: 0.6537945 | AH13: =AH12/AH10 -> 0.63811465 | AL13: % Gross Margin | AM13: =AM12/AM10 -> 0.64323244 | AN13: 0.67585926 | AQ13: =AQ12/AQ10 -> 0.64323244 | AU13: % Gross Margin | AV13: =AV12/AV10 -> 0.62878515 | AW13: 0.62107065 | AZ13: =AZ12/AZ10 -> 0.62878515 | BD13: % Gross Margin | BE13: =BE12/BE10 -> 0.6197443 | BF13: 0.59298547 | BI13: =BI12/BI10 -> 0.6197443 | BM13: % Gross Margin | BN13: =BN12/BN10 -> 0.63957754 | BO13: 0.65471583 | BR13: =BR12/BR10 -> 0.63957754 | BV13: % Gross Margin | BW13: =BW12/BW10 -> 0.61669245 | BX13: 0.66508713 | CA13: =CA12/CA10 -> 0.61669245 | CE13: % Gross Margin | CF13: =CF12/CF10 -> 0.62611282 | CG13: 0.66876849 | CJ13: =CJ12/CJ10 -> 0.62611282 | CN13: % Gross Margin | CO13: =CO12/CO10 -> 0.61685782 | CP13: 0.66994524 | CS13: =CS12/CS10 -> 0.61685782 | CW13: % Gross Margin | CX13: =CX12/CX10 -> 0.63806315 | CY13: 0.60684311 | DB13: =DB12/DB10 -> 0.63806315 | DF13: % Gross Margin | DG13: =DG12/DG10 -> 0.63878743 | DH13: =DH12/DH10 -> 0.65523499 | DK13: =DK12/DK10 -> 0.63878743
B15: Gastos de Personal | C15: =GETPIVOTDATA("ene-27 ",TABLA!$B$3,"Nivel 4","6.- Gastos de personal")/1000 -> -162.38274 | D15: -111.53201 | E15: =C15-D15 -> -50.85073 | F15: =+IF(IFERROR(C15/D15-1,"-")<300%,IFERROR(C15/D15-1,"-"),"n.a.") -> 0.45592947 | G15: =C15 -> -162.38274 | H15: =C15-G15 -> 0 | I15: =+IF(IFERROR(C15/G15-1,"-")<300%,IFERROR(C15/G15-1,"-"),"n.a.") -> 0 | K15: Gastos de Personal | L15: =GETPIVOTDATA("feb-27 ",TABLA!$B$3,"Nivel 4","6.- Gastos de personal")/1000 -> -162.38274 | M15: -142.9272 | N15: =L15-M15 -> -19.45554 | O15: =+IF(IFERROR(L15/M15-1,"-")<300%,IFERROR(L15/M15-1,"-"),"n.a.") -> 0.13612203 | P15: =L15 -> -162.38274 | Q15: =L15-P15 -> 0 | R15: =+IF(IFERROR(L15/P15-1,"-")<300%,IFERROR(L15/P15-1,"-"),"n.a.") -> 0 | T15: Gastos de Personal | U15: =GETPIVOTDATA("mar-27 ",TABLA!$B$3,"Nivel 4","6.- Gastos de personal")/1000 -> -162.38274 | V15: -146.23331 | W15: =U15-V15 -> -16.14943 | X15: =+IF(IFERROR(U15/V15-1,"-")<300%,IFERROR(U15/V15-1,"-"),"n.a.") -> 0.11043606 | Y15: =U15 -> -162.38274 | Z15: =U15-Y15 -> 0 | AA15: =+IF(IFERROR(U15/Y15-1,"-")<300%,IFERROR(U15/Y15-1,"-"),"n.a.") -> 0 | AC15: Gastos de Personal | AD15: =GETPIVOTDATA("abr-27 ",TABLA!$B$3,"Nivel 4","6.- Gastos de personal")/1000 -> -162.38274 | AE15: -130.04767 | AF15: =AD15-AE15 -> -32.33507 | AG15: =+IF(IFERROR(AD15/AE15-1,"-")<300%,IFERROR(AD15/AE15-1,"-"),"n.a.") -> 0.24864013 | AH15: =AD15 -> -162.38274 | AI15: =AD15-AH15 -> 0 | AJ15: =+IF(IFERROR(AD15/AH15-1,"-")<300%,IFERROR(AD15/AH15-1,"-"),"n.a.") -> 0 | AL15: Gastos de Personal | AM15: =GETPIVOTDATA("may-27 ",TABLA!$B$3,"Nivel 4","6.- Gastos de personal")/1000 -> -162.38274 | AN15: -134.99252 | AO15: =AM15-AN15 -> -27.39022 | AP15: =+IF(IFERROR(AM15/AN15-1,"-")<300%,IFERROR(AM15/AN15-1,"-"),"n.a.") -> 0.20290176 | AQ15: =AM15 -> -162.38274 | AR15: =AM15-AQ15 -> 0 | AS15: =+IF(IFERROR(AM15/AQ15-1,"-")<300%,IFERROR(AM15/AQ15-1,"-"),"n.a.") -> 0 | AU15: Gastos de Personal | AV15: =GETPIVOTDATA("jun-27 ",TABLA!$B$3,"Nivel 4","6.- Gastos de personal")/1000 -> -162.38274 | AW15: -145.07228 | AX15: =AV15-AW15 -> -17.31046 | AY15: =+IF(IFERROR(AV15/AW15-1,"-")<300%,IFERROR(AV15/AW15-1,"-"),"n.a.") -> 0.119323 | AZ15: =AV15 -> -162.38274 | BA15: =AV15-AZ15 -> 0 | BB15: =+IF(IFERROR(AV15/AZ15-1,"-")<300%,IFERROR(AV15/AZ15-1,"-"),"n.a.") -> 0 | BD15: Gastos de Personal | BE15: =GETPIVOTDATA("jul-27 ",TABLA!$B$3,"Nivel 4","6.- Gastos de personal")/1000 -> -162.38274 | BF15: -153.53365 | BG15: =BE15-BF15 -> -8.84909 | BH15: =+IF(IFERROR(BE15/BF15-1,"-")<300%,IFERROR(BE15/BF15-1,"-"),"n.a.") -> 0.05763616 | BI15: =BE15 -> -162.38274 | BJ15: =BE15-BI15 -> 0 | BK15: =+IF(IFERROR(BE15/BI15-1,"-")<300%,IFERROR(BE15/BI15-1,"-"),"n.a.") -> 0 | BM15: Gastos de Personal | BN15: =GETPIVOTDATA("ago-27 ",TABLA!$B$3,"Nivel 4","6.- Gastos de personal")/1000 -> -162.38274 | BO15: -152.63279 | BP15: =BN15-BO15 -> -9.74995 | BQ15: =+IF(IFERROR(BN15/BO15-1,"-")<300%,IFERROR(BN15/BO15-1,"-"),"n.a.") -> 0.063878476 | BR15: =BN15 -> -162.38274 | BS15: =BN15-BR15 -> 0 | BT15: =+IF(IFERROR(BN15/BR15-1,"-")<300%,IFERROR(BN15/BR15-1,"-"),"n.a.") -> 0 | BV15: Gastos de Personal | BW15: =GETPIVOTDATA("sep-27 ",TABLA!$B$3,"Nivel 4","6.- Gastos de personal")/1000 -> -162.38274 | BX15: -152.63279 | BY15: =BW15-BX15 -> -9.74995 | BZ15: =+IF(IFERROR(BW15/BX15-1,"-")<300%,IFERROR(BW15/BX15-1,"-"),"n.a.") -> 0.063878476 | CA15: =BW15 -> -162.38274 | CB15: =BW15-CA15 -> 0 | CC15: =+IF(IFERROR(BW15/CA15-1,"-")<300%,IFERROR(BW15/CA15-1,"-"),"n.a.") -> 0 | CE15: Gastos de Personal | CF15: =GETPIVOTDATA("oct-27 ",TABLA!$B$3,"Nivel 4","6.- Gastos de personal")/1000 -> -162.38274 | CG15: -152.63279 | CH15: =CF15-CG15 -> -9.74995 | CI15: =+IF(IFERROR(CF15/CG15-1,"-")<300%,IFERROR(CF15/CG15-1,"-"),"n.a.") -> 0.063878476 | CJ15: =CF15 -> -162.38274 | CK15: =CF15-CJ15 -> 0 | CL15: =+IF(IFERROR(CF15/CJ15-1,"-")<300%,IFERROR(CF15/CJ15-1,"-"),"n.a.") -> 0 | CN15: Gastos de Personal | CO15: =GETPIVOTDATA("nov-27 ",TABLA!$B$3,"Nivel 4","6.- Gastos de personal")/1000 -> -163.38274 | CP15: -152.63279 | CQ15: =CO15-CP15 -> -10.74995 | CR15: =+IF(IFERROR(CO15/CP15-1,"-")<300%,IFERROR(CO15/CP15-1,"-"),"n.a.") -> 0.070430148 | CS15: =CO15 -> -163.38274 | CT15: =CO15-CS15 -> 0 | CU15: =+IF(IFERROR(CO15/CS15-1,"-")<300%,IFERROR(CO15/CS15-1,"-"),"n.a.") -> 0 | CW15: Gastos de Personal | CX15: =GETPIVOTDATA("dic-27 ",TABLA!$B$3,"Nivel 4","6.- Gastos de personal")/1000 -> -441.39946 | CY15: -431.63279 | CZ15: =CX15-CY15 -> -9.76667 | DA15: =+IF(IFERROR(CX15/CY15-1,"-")<300%,IFERROR(CX15/CY15-1,"-"),"n.a.") -> 0.022627266 | DB15: =CX15 -> -441.39946 | DC15: =CX15-DB15 -> 0 | DD15: =+IF(IFERROR(CX15/DB15-1,"-")<300%,IFERROR(CX15/DB15-1,"-"),"n.a.") -> 0 | DF15: Gastos de Personal | DG15: =GETPIVOTDATA("Total 2027 ",TABLA!$B$3,"Nivel 4","6.- Gastos de personal")/1000 -> -2228.6096 | DH15: =CY15+CP15+CG15+BX15+BO15+BF15+AW15+AN15+AE15+V15+M15+D15 -> -2006.5026 | DI15: =DG15-DH15 -> -222.10701 | DJ15: =+IF(IFERROR(DG15/DH15-1,"-")<300%,IFERROR(DG15/DH15-1,"-"),"n.a.") -> 0.11069361 | DK15: =DG15 -> -2228.6096 | DL15: =DG15-DK15 -> 0 | DM15: =+IF(IFERROR(DG15/DK15-1,"-")<300%,IFERROR(DG15/DK15-1,"-"),"n.a.") -> 0
B16: % of Revenue | C16: =C15/C10 -> -0.14197615 | D16: -0.11336661 | G16: =G15/G10 -> -0.14197615 | K16: % of Revenue | L16: =L15/L10 -> -0.087649316 | M16: -0.097201077 | P16: =P15/P10 -> -0.087649316 | T16: % of Revenue | U16: =U15/U10 -> -0.091373375 | V16: -0.095341192 | Y16: =Y15/Y10 -> -0.091373375 | AC16: % of Revenue | AD16: =AD15/AD10 -> -0.11349469 | AE16: -0.088942995 | AH16: =AH15/AH10 -> -0.11349469 | AL16: % of Revenue | AM16: =AM15/AM10 -> -0.06912753 | AN16: -0.070092125 | AQ16: =AQ15/AQ10 -> -0.06912753 | AU16: % of Revenue | AV16: =AV15/AV10 -> -0.069707608 | AW16: -0.073931153 | AZ16: =AZ15/AZ10 -> -0.069707608 | BD16: % of Revenue | BE16: =BE15/BE10 -> -0.10986785 | BF16: -0.118958 | BI16: =BI15/BI10 -> -0.10986785 | BM16: % of Revenue | BN16: =BN15/BN10 -> -0.17215763 | BO16: -0.19367059 | BR16: =BR15/BR10 -> -0.17215763 | BV16: % of Revenue | BW16: =BW15/BW10 -> -0.29637502 | BX16: -0.31595514 | CA16: =CA15/CA10 -> -0.29637502 | CE16: % of Revenue | CF16: =CF15/CF10 -> -0.17721629 | CG16: -0.16735042 | CJ16: =CJ15/CJ10 -> -0.17721629 | CN16: % of Revenue | CO16: =CO15/CO10 -> -0.11535341 | CP16: -0.12456548 | CS16: =CS15/CS10 -> -0.11535341 | CW16: % of Revenue | CX16: =CX15/CX10 -> -0.28410996 | CY16: -0.37782738 | DB16: =DB15/DB10 -> -0.28410996 | DF16: % of Revenue | DG16: =DG15/DG10 -> -0.12563928 | DH16: =DH15/DH10 -> -0.13218067 | DK16: =DK15/DK10 -> -0.12563928
B18: Otros Ingresos Operativos | C18: =GETPIVOTDATA("ene-27 ",TABLA!$B$3,"Nivel 4","5.- Otros ingresos de explotación")/1000 -> 29.8092 | D18: 0 | E18: =C18-D18 -> 29.8092 | F18: =+IF(IFERROR(C18/D18-1,"-")<300%,IFERROR(C18/D18-1,"-"),"n.a.") -> n.a. | G18: =C18 -> 29.8092 | H18: =C18-G18 -> 0 | I18: =+IF(IFERROR(C18/G18-1,"-")<300%,IFERROR(C18/G18-1,"-"),"n.a.") -> 0 | K18: Otros Ingresos Operativos | L18: =GETPIVOTDATA("feb-27 ",TABLA!$B$3,"Nivel 4","5.- Otros ingresos de explotación")/1000 -> 21.2467 | M18: 0 | N18: =L18-M18 -> 21.2467 | O18: =+IF(IFERROR(L18/M18-1,"-")<300%,IFERROR(L18/M18-1,"-"),"n.a.") -> n.a. | P18: =L18 -> 21.2467 | Q18: =L18-P18 -> 0 | R18: =+IF(IFERROR(L18/P18-1,"-")<300%,IFERROR(L18/P18-1,"-"),"n.a.") -> 0 | T18: Otros Ingresos Operativos | U18: =GETPIVOTDATA("mar-27 ",TABLA!$B$3,"Nivel 4","5.- Otros ingresos de explotación")/1000 -> 19.6383 | V18: 0 | W18: =U18-V18 -> 19.6383 | X18: =+IF(IFERROR(U18/V18-1,"-")<300%,IFERROR(U18/V18-1,"-"),"n.a.") -> n.a. | Y18: =U18 -> 19.6383 | Z18: =U18-Y18 -> 0 | AA18: =+IF(IFERROR(U18/Y18-1,"-")<300%,IFERROR(U18/Y18-1,"-"),"n.a.") -> 0 | AC18: Otros Ingresos Operativos | AD18: =GETPIVOTDATA("abr-27 ",TABLA!$B$3,"Nivel 4","5.- Otros ingresos de explotación")/1000 -> 8.0042 | AE18: 0.75075 | AF18: =AD18-AE18 -> 7.25345 | AG18: =+IF(IFERROR(AD18/AE18-1,"-")<300%,IFERROR(AD18/AE18-1,"-"),"n.a.") -> n.a. | AH18: =AD18 -> 8.0042 | AI18: =AD18-AH18 -> 0 | AJ18: =+IF(IFERROR(AD18/AH18-1,"-")<300%,IFERROR(AD18/AH18-1,"-"),"n.a.") -> 0 | AL18: Otros Ingresos Operativos | AM18: =GETPIVOTDATA("may-27 ",TABLA!$B$3,"Nivel 4","5.- Otros ingresos de explotación")/1000 -> 38.7188 | AN18: 25.14075 | AO18: =AM18-AN18 -> 13.57805 | AP18: =+IF(IFERROR(AM18/AN18-1,"-")<300%,IFERROR(AM18/AN18-1,"-"),"n.a.") -> 0.54008134 | AQ18: =AM18 -> 38.7188 | AR18: =AM18-AQ18 -> 0 | AS18: =+IF(IFERROR(AM18/AQ18-1,"-")<300%,IFERROR(AM18/AQ18-1,"-"),"n.a.") -> 0 | AU18: Otros Ingresos Operativos | AV18: =GETPIVOTDATA("jun-27 ",TABLA!$B$3,"Nivel 4","5.- Otros ingresos de explotación")/1000 -> 33.492 | AW18: 22.9776 | AX18: =AV18-AW18 -> 10.5144 | AY18: =+IF(IFERROR(AV18/AW18-1,"-")<300%,IFERROR(AV18/AW18-1,"-"),"n.a.") -> 0.45759348 | AZ18: =AV18 -> 33.492 | BA18: =AV18-AZ18 -> 0 | BB18: =+IF(IFERROR(AV18/AZ18-1,"-")<300%,IFERROR(AV18/AZ18-1,"-"),"n.a.") -> 0 | BD18: Otros Ingresos Operativos | BE18: =GETPIVOTDATA("jul-27 ",TABLA!$B$3,"Nivel 4","5.- Otros ingresos de explotación")/1000 -> 13.2128 | BF18: 11.02724 | BG18: =BE18-BF18 -> 2.18556 | BH18: =+IF(IFERROR(BE18/BF18-1,"-")<300%,IFERROR(BE18/BF18-1,"-"),"n.a.") -> 0.19819647 | BI18: =BE18 -> 13.2128 | BJ18: =BE18-BI18 -> 0 | BK18: =+IF(IFERROR(BE18/BI18-1,"-")<300%,IFERROR(BE18/BI18-1,"-"),"n.a.") -> 0 | BM18: Otros Ingresos Operativos | BN18: =GETPIVOTDATA("ago-27 ",TABLA!$B$3,"Nivel 4","5.- Otros ingresos de explotación")/1000 -> 18.5096 | BO18: 11.429 | BP18: =BN18-BO18 -> 7.0806 | BQ18: =+IF(IFERROR(BN18/BO18-1,"-")<300%,IFERROR(BN18/BO18-1,"-"),"n.a.") -> 0.61952927 | BR18: =BN18 -> 18.5096 | BS18: =BN18-BR18 -> 0 | BT18: =+IF(IFERROR(BN18/BR18-1,"-")<300%,IFERROR(BN18/BR18-1,"-"),"n.a.") -> 0 | BV18: Otros Ingresos Operativos | BW18: =GETPIVOTDATA("sep-27 ",TABLA!$B$3,"Nivel 4","5.- Otros ingresos de explotación")/1000 -> 24.1489 | BX18: 16.253 | BY18: =BW18-BX18 -> 7.8959 | BZ18: =+IF(IFERROR(BW18/BX18-1,"-")<300%,IFERROR(BW18/BX18-1,"-"),"n.a.") -> 0.48581185 | CA18: =BW18 -> 24.1489 | CB18: =BW18-CA18 -> 0 | CC18: =+IF(IFERROR(BW18/CA18-1,"-")<300%,IFERROR(BW18/CA18-1,"-"),"n.a.") -> 0 | CE18: Otros Ingresos Operativos | CF18: =GETPIVOTDATA("oct-27 ",TABLA!$B$3,"Nivel 4","5.- Otros ingresos de explotación")/1000 -> 23.4113 | CG18: 21.379 | CH18: =CF18-CG18 -> 2.0323 | CI18: =+IF(IFERROR(CF18/CG18-1,"-")<300%,IFERROR(CF18/CG18-1,"-"),"n.a.") -> 0.095060573 | CJ18: =CF18 -> 23.4113 | CK18: =CF18-CJ18 -> 0 | CL18: =+IF(IFERROR(CF18/CJ18-1,"-")<300%,IFERROR(CF18/CJ18-1,"-"),"n.a.") -> 0 | CN18: Otros Ingresos Operativos | CO18: =GETPIVOTDATA("nov-27 ",TABLA!$B$3,"Nivel 4","5.- Otros ingresos de explotación")/1000 -> 40.6507 | CP18: 32.454 | CQ18: =CO18-CP18 -> 8.1967 | CR18: =+IF(IFERROR(CO18/CP18-1,"-")<300%,IFERROR(CO18/CP18-1,"-"),"n.a.") -> 0.25256363 | CS18: =CO18 -> 40.6507 | CT18: =CO18-CS18 -> 0 | CU18: =+IF(IFERROR(CO18/CS18-1,"-")<300%,IFERROR(CO18/CS18-1,"-"),"n.a.") -> 0 | CW18: Otros Ingresos Operativos | CX18: =GETPIVOTDATA("dic-27 ",TABLA!$B$3,"Nivel 4","5.- Otros ingresos de explotación")/1000 -> 34.3808 | CY18: 27.15 | CZ18: =CX18-CY18 -> 7.2308 | DA18: =+IF(IFERROR(CX18/CY18-1,"-")<300%,IFERROR(CX18/CY18-1,"-"),"n.a.") -> 0.26632781 | DB18: =CX18 -> 34.3808 | DC18: =CX18-DB18 -> 0 | DD18: =+IF(IFERROR(CX18/DB18-1,"-")<300%,IFERROR(CX18/DB18-1,"-"),"n.a.") -> 0 | DF18: Otros Ingresos Operativos | DG18: =GETPIVOTDATA("Total 2027 ",TABLA!$B$3,"Nivel 4","5.- Otros ingresos de explotación")/1000 -> 305.2233 | DH18: =CY18+CP18+CG18+BX18+BO18+BF18+AW18+AN18+AE18+V18+M18+D18 -> 168.56134 | DI18: =DG18-DH18 -> 136.66196 | DJ18: =+IF(IFERROR(DG18/DH18-1,"-")<300%,IFERROR(DG18/DH18-1,"-"),"n.a.") -> 0.81075506 | DK18: =DG18 -> 305.2233 | DL18: =DG18-DK18 -> 0 | DM18: =+IF(IFERROR(DG18/DK18-1,"-")<300%,IFERROR(DG18/DK18-1,"-"),"n.a.") -> 0
B19: Otros Gastos Operativos | C19: =GETPIVOTDATA("ene-27 ",TABLA!$B$3,"Nivel 4","7.- Otros gastos de explotación")/1000 -> -162.8549 | D19: -103.45176 | E19: =C19-D19 -> -59.40314 | F19: =+IF(IFERROR(C19/D19-1,"-")<300%,IFERROR(C19/D19-1,"-"),"n.a.") -> 0.57421101 | G19: =C19 -> -162.8549 | H19: =C19-G19 -> 0 | I19: =+IF(IFERROR(C19/G19-1,"-")<300%,IFERROR(C19/G19-1,"-"),"n.a.") -> 0 | K19: Otros Gastos Operativos | L19: =GETPIVOTDATA("feb-27 ",TABLA!$B$3,"Nivel 4","7.- Otros gastos de explotación")/1000 -> -156.65463 | M19: -62.49888 | N19: =L19-M19 -> -94.15575 | O19: =+IF(IFERROR(L19/M19-1,"-")<300%,IFERROR(L19/M19-1,"-"),"n.a.") -> 1.506519 | P19: =L19 -> -156.65463 | Q19: =L19-P19 -> 0 | R19: =+IF(IFERROR(L19/P19-1,"-")<300%,IFERROR(L19/P19-1,"-"),"n.a.") -> 0 | T19: Otros Gastos Operativos | U19: =GETPIVOTDATA("mar-27 ",TABLA!$B$3,"Nivel 4","7.- Otros gastos de explotación")/1000 -> -161.54122 | V19: -110.60627 | W19: =U19-V19 -> -50.93495 | X19: =+IF(IFERROR(U19/V19-1,"-")<300%,IFERROR(U19/V19-1,"-"),"n.a.") -> 0.4605069 | Y19: =U19 -> -161.54122 | Z19: =U19-Y19 -> 0 | AA19: =+IF(IFERROR(U19/Y19-1,"-")<300%,IFERROR(U19/Y19-1,"-"),"n.a.") -> 0 | AC19: Otros Gastos Operativos | AD19: =GETPIVOTDATA("abr-27 ",TABLA!$B$3,"Nivel 4","7.- Otros gastos de explotación")/1000 -> -151.8867 | AE19: -107.70665 | AF19: =AD19-AE19 -> -44.18005 | AG19: =+IF(IFERROR(AD19/AE19-1,"-")<300%,IFERROR(AD19/AE19-1,"-"),"n.a.") -> 0.41018869 | AH19: =AD19 -> -151.8867 | AI19: =AD19-AH19 -> 0 | AJ19: =+IF(IFERROR(AD19/AH19-1,"-")<300%,IFERROR(AD19/AH19-1,"-"),"n.a.") -> 0 | AL19: Otros Gastos Operativos | AM19: =GETPIVOTDATA("may-27 ",TABLA!$B$3,"Nivel 4","7.- Otros gastos de explotación")/1000 -> -184.77671 | AN19: -123.39208 | AO19: =AM19-AN19 -> -61.38463 | AP19: =+IF(IFERROR(AM19/AN19-1,"-")<300%,IFERROR(AM19/AN19-1,"-"),"n.a.") -> 0.49747626 | AQ19: =AM19 -> -184.77671 | AR19: =AM19-AQ19 -> 0 | AS19: =+IF(IFERROR(AM19/AQ19-1,"-")<300%,IFERROR(AM19/AQ19-1,"-"),"n.a.") -> 0 | AU19: Otros Gastos Operativos | AV19: =GETPIVOTDATA("jun-27 ",TABLA!$B$3,"Nivel 4","7.- Otros gastos de explotación")/1000 -> -161.34468 | AW19: -175.01376 | AX19: =AV19-AW19 -> 13.66908 | AY19: =+IF(IFERROR(AV19/AW19-1,"-")<300%,IFERROR(AV19/AW19-1,"-"),"n.a.") -> -0.078102887 | AZ19: =AV19 -> -161.34468 | BA19: =AV19-AZ19 -> 0 | BB19: =+IF(IFERROR(AV19/AZ19-1,"-")<300%,IFERROR(AV19/AZ19-1,"-"),"n.a.") -> 0 | BD19: Otros Gastos Operativos | BE19: =GETPIVOTDATA("jul-27 ",TABLA!$B$3,"Nivel 4","7.- Otros gastos de explotación")/1000 -> -132.69654 | BF19: -161.05174 | BG19: =BE19-BF19 -> 28.355204 | BH19: =+IF(IFERROR(BE19/BF19-1,"-")<300%,IFERROR(BE19/BF19-1,"-"),"n.a.") -> -0.1760627 | BI19: =BE19 -> -132.69654 | BJ19: =BE19-BI19 -> 0 | BK19: =+IF(IFERROR(BE19/BI19-1,"-")<300%,IFERROR(BE19/BI19-1,"-"),"n.a.") -> 0 | BM19: Otros Gastos Operativos | BN19: =GETPIVOTDATA("ago-27 ",TABLA!$B$3,"Nivel 4","7.- Otros gastos de explotación")/1000 -> -131.76464 | BO19: -130.06066 | BP19: =BN19-BO19 -> -1.703979 | BQ19: =+IF(IFERROR(BN19/BO19-1,"-")<300%,IFERROR(BN19/BO19-1,"-"),"n.a.") -> 0.013101417 | BR19: =BN19 -> -131.76464 | BS19: =BN19-BR19 -> 0 | BT19: =+IF(IFERROR(BN19/BR19-1,"-")<300%,IFERROR(BN19/BR19-1,"-"),"n.a.") -> 0 | BV19: Otros Gastos Operativos | BW19: =GETPIVOTDATA("sep-27 ",TABLA!$B$3,"Nivel 4","7.- Otros gastos de explotación")/1000 -> -150.22285 | BX19: -120.80832 | BY19: =BW19-BX19 -> -29.41453 | BZ19: =+IF(IFERROR(BW19/BX19-1,"-")<300%,IFERROR(BW19/BX19-1,"-"),"n.a.") -> 0.243481 | CA19: =BW19 -> -150.22285 | CB19: =BW19-CA19 -> 0 | CC19: =+IF(IFERROR(BW19/CA19-1,"-")<300%,IFERROR(BW19/CA19-1,"-"),"n.a.") -> 0 | CE19: Otros Gastos Operativos | CF19: =GETPIVOTDATA("oct-27 ",TABLA!$B$3,"Nivel 4","7.- Otros gastos de explotación")/1000 -> -146.34194 | CG19: -149.47019 | CH19: =CF19-CG19 -> 3.12825 | CI19: =+IF(IFERROR(CF19/CG19-1,"-")<300%,IFERROR(CF19/CG19-1,"-"),"n.a.") -> -0.020928922 | CJ19: =CF19 -> -146.34194 | CK19: =CF19-CJ19 -> 0 | CL19: =+IF(IFERROR(CF19/CJ19-1,"-")<300%,IFERROR(CF19/CJ19-1,"-"),"n.a.") -> 0 | CN19: Otros Gastos Operativos | CO19: =GETPIVOTDATA("nov-27 ",TABLA!$B$3,"Nivel 4","7.- Otros gastos de explotación")/1000 -> -183.50703 | CP19: -162.36942 | CQ19: =CO19-CP19 -> -21.13761 | CR19: =+IF(IFERROR(CO19/CP19-1,"-")<300%,IFERROR(CO19/CP19-1,"-"),"n.a.") -> 0.13018221 | CS19: =CO19 -> -183.50703 | CT19: =CO19-CS19 -> 0 | CU19: =+IF(IFERROR(CO19/CS19-1,"-")<300%,IFERROR(CO19/CS19-1,"-"),"n.a.") -> 0 | CW19: Otros Gastos Operativos | CX19: =GETPIVOTDATA("dic-27 ",TABLA!$B$3,"Nivel 4","7.- Otros gastos de explotación")/1000 -> -286.91589 | CY19: -277.59629 | CZ19: =CX19-CY19 -> -9.3196 | DA19: =+IF(IFERROR(CX19/CY19-1,"-")<300%,IFERROR(CX19/CY19-1,"-"),"n.a.") -> 0.033572495 | DB19: =CX19 -> -286.91589 | DC19: =CX19-DB19 -> 0 | DD19: =+IF(IFERROR(CX19/DB19-1,"-")<300%,IFERROR(CX19/DB19-1,"-"),"n.a.") -> 0 | DF19: Otros Gastos Operativos | DG19: =GETPIVOTDATA("Total 2027 ",TABLA!$B$3,"Nivel 4","7.- Otros gastos de explotación")/1000 -> -2010.5077 | DH19: =CY19+CP19+CG19+BX19+BO19+BF19+AW19+AN19+AE19+V19+M19+D19 -> -1684.026 | DI19: =DG19-DH19 -> -326.4817 | DJ19: =+IF(IFERROR(DG19/DH19-1,"-")<300%,IFERROR(DG19/DH19-1,"-"),"n.a.") -> 0.19386975 | DK19: =DG19 -> -2010.5077 | DL19: =DG19-DK19 -> 0 | DM19: =+IF(IFERROR(DG19/DK19-1,"-")<300%,IFERROR(DG19/DK19-1,"-"),"n.a.") -> 0
B20: Operating Expenses | C20: =SUM(C18:C19) -> -133.0457 | D20: -103.45176 | E20: =C20-D20 -> -29.59394 | F20: =+IF(IFERROR(C20/D20-1,"-")<300%,IFERROR(C20/D20-1,"-"),"n.a.") -> 0.28606512 | G20: =SUM(G18:G19) -> -133.0457 | H20: =C20-G20 -> 0 | I20: =+IF(IFERROR(C20/G20-1,"-")<300%,IFERROR(C20/G20-1,"-"),"n.a.") -> 0 | K20: Operating Expenses | L20: =SUM(L18:L19) -> -135.40793 | M20: -62.49888 | N20: =L20-M20 -> -72.90905 | O20: =+IF(IFERROR(L20/M20-1,"-")<300%,IFERROR(L20/M20-1,"-"),"n.a.") -> 1.1665657 | P20: =SUM(P18:P19) -> -135.40793 | Q20: =L20-P20 -> 0 | R20: =+IF(IFERROR(L20/P20-1,"-")<300%,IFERROR(L20/P20-1,"-"),"n.a.") -> 0 | T20: Operating Expenses | U20: =SUM(U18:U19) -> -141.90292 | V20: -110.60627 | W20: =U20-V20 -> -31.29665 | X20: =+IF(IFERROR(U20/V20-1,"-")<300%,IFERROR(U20/V20-1,"-"),"n.a.") -> 0.28295548 | Y20: =SUM(Y18:Y19) -> -141.90292 | Z20: =U20-Y20 -> 0 | AA20: =+IF(IFERROR(U20/Y20-1,"-")<300%,IFERROR(U20/Y20-1,"-"),"n.a.") -> 0 | AC20: Operating Expenses | AD20: =SUM(AD18:AD19) -> -143.8825 | AE20: -106.9559 | AF20: =AD20-AE20 -> -36.9266 | AG20: =+IF(IFERROR(AD20/AE20-1,"-")<300%,IFERROR(AD20/AE20-1,"-"),"n.a.") -> 0.34525071 | AH20: =SUM(AH18:AH19) -> -143.8825 | AI20: =AD20-AH20 -> 0 | AJ20: =+IF(IFERROR(AD20/AH20-1,"-")<300%,IFERROR(AD20/AH20-1,"-"),"n.a.") -> 0 | AL20: Operating Expenses | AM20: =SUM(AM18:AM19) -> -146.05791 | AN20: -98.25133 | AO20: =AM20-AN20 -> -47.80658 | AP20: =+IF(IFERROR(AM20/AN20-1,"-")<300%,IFERROR(AM20/AN20-1,"-"),"n.a.") -> 0.48657438 | AQ20: =SUM(AQ18:AQ19) -> -146.05791 | AR20: =AM20-AQ20 -> 0 | AS20: =+IF(IFERROR(AM20/AQ20-1,"-")<300%,IFERROR(AM20/AQ20-1,"-"),"n.a.") -> 0 | AU20: Operating Expenses | AV20: =SUM(AV18:AV19) -> -127.85268 | AW20: -152.03616 | AX20: =AV20-AW20 -> 24.18348 | AY20: =+IF(IFERROR(AV20/AW20-1,"-")<300%,IFERROR(AV20/AW20-1,"-"),"n.a.") -> -0.159064 | AZ20: =SUM(AZ18:AZ19) -> -127.85268 | BA20: =AV20-AZ20 -> 0 | BB20: =+IF(IFERROR(AV20/AZ20-1,"-")<300%,IFERROR(AV20/AZ20-1,"-"),"n.a.") -> 0 | BD20: Operating Expenses | BE20: =SUM(BE18:BE19) -> -119.48374 | BF20: -150.0245 | BG20: =BE20-BF20 -> 30.540764 | BH20: =+IF(IFERROR(BE20/BF20-1,"-")<300%,IFERROR(BE20/BF20-1,"-"),"n.a.") -> -0.20357184 | BI20: =SUM(BI18:BI19) -> -119.48374 | BJ20: =BE20-BI20 -> 0 | BK20: =+IF(IFERROR(BE20/BI20-1,"-")<300%,IFERROR(BE20/BI20-1,"-"),"n.a.") -> 0 | BM20: Operating Expenses | BN20: =SUM(BN18:BN19) -> -113.25504 | BO20: -118.63166 | BP20: =BN20-BO20 -> 5.376621 | BQ20: =+IF(IFERROR(BN20/BO20-1,"-")<300%,IFERROR(BN20/BO20-1,"-"),"n.a.") -> -0.045321974 | BR20: =SUM(BR18:BR19) -> -113.25504 | BS20: =BN20-BR20 -> 0 | BT20: =+IF(IFERROR(BN20/BR20-1,"-")<300%,IFERROR(BN20/BR20-1,"-"),"n.a.") -> 0 | BV20: Operating Expenses | BW20: =SUM(BW18:BW19) -> -126.07395 | BX20: -104.55532 | BY20: =BW20-BX20 -> -21.51863 | BZ20: =+IF(IFERROR(BW20/BX20-1,"-")<300%,IFERROR(BW20/BX20-1,"-"),"n.a.") -> 0.20581095 | CA20: =SUM(CA18:CA19) -> -126.07395 | CB20: =BW20-CA20 -> 0 | CC20: =+IF(IFERROR(BW20/CA20-1,"-")<300%,IFERROR(BW20/CA20-1,"-"),"n.a.") -> 0 | CE20: Operating Expenses | CF20: =SUM(CF18:CF19) -> -122.93064 | CG20: -128.09119 | CH20: =CF20-CG20 -> 5.16055 | CI20: =+IF(IFERROR(CF20/CG20-1,"-")<300%,IFERROR(CF20/CG20-1,"-"),"n.a.") -> -0.040288095 | CJ20: =SUM(CJ18:CJ19) -> -122.93064 | CK20: =CF20-CJ20 -> 0 | CL20: =+IF(IFERROR(CF20/CJ20-1,"-")<300%,IFERROR(CF20/CJ20-1,"-"),"n.a.") -> 0 | CN20: Operating Expenses | CO20: =SUM(CO18:CO19) -> -142.85633 | CP20: -129.91542 | CQ20: =CO20-CP20 -> -12.94091 | CR20: =+IF(IFERROR(CO20/CP20-1,"-")<300%,IFERROR(CO20/CP20-1,"-"),"n.a.") -> 0.09961027 | CS20: =SUM(CS18:CS19) -> -142.85633 | CT20: =CO20-CS20 -> 0 | CU20: =+IF(IFERROR(CO20/CS20-1,"-")<300%,IFERROR(CO20/CS20-1,"-"),"n.a.") -> 0 | CW20: Operating Expenses | CX20: =SUM(CX18:CX19) -> -252.53509 | CY20: -250.44629 | CZ20: =CX20-CY20 -> -2.0888 | DA20: =+IF(IFERROR(CX20/CY20-1,"-")<300%,IFERROR(CX20/CY20-1,"-"),"n.a.") -> 0.0083403112 | DB20: =SUM(DB18:DB19) -> -252.53509 | DC20: =CX20-DB20 -> 0 | DD20: =+IF(IFERROR(CX20/DB20-1,"-")<300%,IFERROR(CX20/DB20-1,"-"),"n.a.") -> 0 | DF20: Operating Expenses | DG20: =SUM(DG18:DG19) -> -1705.2844 | DH20: =SUM(DH18:DH19) -> -1515.4647 | DI20: =DG20-DH20 -> -189.81974 | DJ20: =+IF(IFERROR(DG20/DH20-1,"-")<300%,IFERROR(DG20/DH20-1,"-"),"n.a.") -> 0.12525514 | DK20: =SUM(DK18:DK19) -> -1705.2844 | DL20: =DG20-DK20 -> 0 | DM20: =+IF(IFERROR(DG20/DK20-1,"-")<300%,IFERROR(DG20/DK20-1,"-"),"n.a.") -> 0
B21: % of Revenue | C21: =C20/C10 -> -0.11632589 | D21: -0.10515344 | G21: =G20/G10 -> -0.11632589 | K21: % of Revenue | L21: =L20/L10 -> -0.073089125 | M21: -0.042503865 | P21: =P20/P10 -> -0.073089125 | T21: % of Revenue | U21: =U20/U10 -> -0.079849303 | V21: -0.072113075 | Y21: =Y20/Y10 -> -0.079849303 | AC21: % of Revenue | AD21: =AD20/AD10 -> -0.10056426 | AE21: -0.073149931 | AH21: =AH20/AH10 -> -0.10056426 | AL21: % of Revenue | AM21: =AM20/AM10 -> -0.062177929 | AN21: -0.051015008 | AQ21: =AQ20/AQ10 -> -0.062177929 | AU21: % of Revenue | AV21: =AV20/AV10 -> -0.054884555 | AW21: -0.077480058 | AZ21: =AZ20/AZ10 -> -0.054884555 | BD21: % of Revenue | BE21: =BE20/BE10 -> -0.08084247 | BF21: -0.11623911 | BI21: =BI20/BI10 -> -0.08084247 | BM21: % of Revenue | BN21: =BN20/BN10 -> -0.12007261 | BO21: -0.15052771 | BR21: =BR20/BR10 -> -0.12007261 | BV21: % of Revenue | BW21: =BW20/BW10 -> -0.23010555 | BX21: -0.21643312 | CA21: =CA20/CA10 -> -0.23010555 | CE21: % of Revenue | CF21: =CF20/CF10 -> -0.13416027 | CG21: -0.1404424 | CJ21: =CJ20/CJ10 -> -0.13416027 | CN21: % of Revenue | CO21: =CO20/CO10 -> -0.10086111 | CP21: -0.10602555 | CS21: =CS20/CS10 -> -0.10086111 | CW21: % of Revenue | CX21: =CX20/CX10 -> -0.16254604 | CY21: -0.21922678 | DB21: =DB20/DB10 -> -0.16254604 | DF21: % of Revenue | DG21: =DG20/DG10 -> -0.096136488 | DH21: =DH20/DH10 -> -0.099832983 | DK21: =DK20/DK10 -> -0.096136488
B22: Gastos Fijos | C22: =C20+C15 -> -295.42844 | D22: -214.98377 | E22: =C22-D22 -> -80.44467 | F22: =+IF(IFERROR(C22/D22-1,"-")<300%,IFERROR(C22/D22-1,"-"),"n.a.") -> 0.3741895 | G22: =G20+G15 -> -295.42844 | H22: =C22-G22 -> 0 | I22: =+IF(IFERROR(C22/G22-1,"-")<300%,IFERROR(C22/G22-1,"-"),"n.a.") -> 0 | K22: Gastos Fijos | L22: =L20+L15 -> -297.79067 | M22: -205.42608 | N22: =L22-M22 -> -92.36459 | O22: =+IF(IFERROR(L22/M22-1,"-")<300%,IFERROR(L22/M22-1,"-"),"n.a.") -> 0.44962446 | P22: =P20+P15 -> -297.79067 | Q22: =L22-P22 -> 0 | R22: =+IF(IFERROR(L22/P22-1,"-")<300%,IFERROR(L22/P22-1,"-"),"n.a.") -> 0 | T22: Gastos Fijos | U22: =U20+U15 -> -304.28566 | V22: -256.83958 | W22: =U22-V22 -> -47.44608 | X22: =+IF(IFERROR(U22/V22-1,"-")<300%,IFERROR(U22/V22-1,"-"),"n.a.") -> 0.18473041 | Y22: =Y20+Y15 -> -304.28566 | Z22: =U22-Y22 -> 0 | AA22: =+IF(IFERROR(U22/Y22-1,"-")<300%,IFERROR(U22/Y22-1,"-"),"n.a.") -> 0 | AC22: Gastos Fijos | AD22: =AD20+AD15 -> -306.26524 | AE22: -237.00357 | AF22: =AD22-AE22 -> -69.26167 | AG22: =+IF(IFERROR(AD22/AE22-1,"-")<300%,IFERROR(AD22/AE22-1,"-"),"n.a.") -> 0.29223893 | AH22: =AH20+AH15 -> -306.26524 | AI22: =AD22-AH22 -> 0 | AJ22: =+IF(IFERROR(AD22/AH22-1,"-")<300%,IFERROR(AD22/AH22-1,"-"),"n.a.") -> 0 | AL22: Gastos Fijos | AM22: =AM20+AM15 -> -308.44065 | AN22: -233.24385 | AO22: =AM22-AN22 -> -75.1968 | AP22: =+IF(IFERROR(AM22/AN22-1,"-")<300%,IFERROR(AM22/AN22-1,"-"),"n.a.") -> 0.32239564 | AQ22: =AQ20+AQ15 -> -308.44065 | AR22: =AM22-AQ22 -> 0 | AS22: =+IF(IFERROR(AM22/AQ22-1,"-")<300%,IFERROR(AM22/AQ22-1,"-"),"n.a.") -> 0 | AU22: Gastos Fijos | AV22: =AV20+AV15 -> -290.23542 | AW22: -297.10844 | AX22: =AV22-AW22 -> 6.87302 | AY22: =+IF(IFERROR(AV22/AW22-1,"-")<300%,IFERROR(AV22/AW22-1,"-"),"n.a.") -> -0.023133035 | AZ22: =AZ20+AZ15 -> -290.23542 | BA22: =AV22-AZ22 -> 0 | BB22: =+IF(IFERROR(AV22/AZ22-1,"-")<300%,IFERROR(AV22/AZ22-1,"-"),"n.a.") -> 0 | BD22: Gastos Fijos | BE22: =BE20+BE15 -> -281.86648 | BF22: -303.55815 | BG22: =BE22-BF22 -> 21.691674 | BH22: =+IF(IFERROR(BE22/BF22-1,"-")<300%,IFERROR(BE22/BF22-1,"-"),"n.a.") -> -0.071458052 | BI22: =BI20+BI15 -> -281.86648 | BJ22: =BE22-BI22 -> 0 | BK22: =+IF(IFERROR(BE22/BI22-1,"-")<300%,IFERROR(BE22/BI22-1,"-"),"n.a.") -> 0 | BM22: Gastos Fijos | BN22: =BN20+BN15 -> -275.63778 | BO22: -271.26445 | BP22: =BN22-BO22 -> -4.373329 | BQ22: =+IF(IFERROR(BN22/BO22-1,"-")<300%,IFERROR(BN22/BO22-1,"-"),"n.a.") -> 0.016122013 | BR22: =BR20+BR15 -> -275.63778 | BS22: =BN22-BR22 -> 0 | BT22: =+IF(IFERROR(BN22/BR22-1,"-")<300%,IFERROR(BN22/BR22-1,"-"),"n.a.") -> 0 | BV22: Gastos Fijos | BW22: =BW20+BW15 -> -288.45669 | BX22: -257.18811 | BY22: =BW22-BX22 -> -31.26858 | BZ22: =+IF(IFERROR(BW22/BX22-1,"-")<300%,IFERROR(BW22/BX22-1,"-"),"n.a.") -> 0.12157864 | CA22: =CA20+CA15 -> -288.45669 | CB22: =BW22-CA22 -> 0 | CC22: =+IF(IFERROR(BW22/CA22-1,"-")<300%,IFERROR(BW22/CA22-1,"-"),"n.a.") -> 0 | CE22: Gastos Fijos | CF22: =CF20+CF15 -> -285.31338 | CG22: -280.72398 | CH22: =CF22-CG22 -> -4.5894 | CI22: =+IF(IFERROR(CF22/CG22-1,"-")<300%,IFERROR(CF22/CG22-1,"-"),"n.a.") -> 0.016348443 | CJ22: =CJ20+CJ15 -> -285.31338 | CK22: =CF22-CJ22 -> 0 | CL22: =+IF(IFERROR(CF22/CJ22-1,"-")<300%,IFERROR(CF22/CJ22-1,"-"),"n.a.") -> 0 | CN22: Gastos Fijos | CO22: =CO20+CO15 -> -306.23907 | CP22: -282.54821 | CQ22: =CO22-CP22 -> -23.69086 | CR22: =+IF(IFERROR(CO22/CP22-1,"-")<300%,IFERROR(CO22/CP22-1,"-"),"n.a.") -> 0.083847142 | CS22: =CS20+CS15 -> -306.23907 | CT22: =CO22-CS22 -> 0 | CU22: =+IF(IFERROR(CO22/CS22-1,"-")<300%,IFERROR(CO22/CS22-1,"-"),"n.a.") -> 0 | CW22: Gastos Fijos | CX22: =CX20+CX15 -> -693.93455 | CY22: -682.07908 | CZ22: =CX22-CY22 -> -11.85547 | DA22: =+IF(IFERROR(CX22/CY22-1,"-")<300%,IFERROR(CX22/CY22-1,"-"),"n.a.") -> 0.017381372 | DB22: =DB20+DB15 -> -693.93455 | DC22: =CX22-DB22 -> 0 | DD22: =+IF(IFERROR(CX22/DB22-1,"-")<300%,IFERROR(CX22/DB22-1,"-"),"n.a.") -> 0 | DF22: Gastos Fijos | DG22: =DG20+DG15 -> -3933.894 | DH22: =DH20+DH15 -> -3521.9673 | DI22: =DG22-DH22 -> -411.92675 | DJ22: =+IF(IFERROR(DG22/DH22-1,"-")<300%,IFERROR(DG22/DH22-1,"-"),"n.a.") -> 0.11695928 | DK22: =DK20+DK15 -> -3933.894 | DL22: =DG22-DK22 -> 0 | DM22: =+IF(IFERROR(DG22/DK22-1,"-")<300%,IFERROR(DG22/DK22-1,"-"),"n.a.") -> 0
B23: % of Revenue | C23: =C22/C10 -> -0.25830204 | D23: -0.21852005 | G23: =G22/G10 -> -0.25830204 | K23: % of Revenue | L23: =L22/L10 -> -0.16073844 | M23: -0.13970494 | P23: =P22/P10 -> -0.16073844 | T23: % of Revenue | U23: =U22/U10 -> -0.17122268 | V23: -0.16745427 | Y23: =Y22/Y10 -> -0.17122268 | AC23: % of Revenue | AD23: =AD22/AD10 -> -0.21405895 | AE23: -0.16209293 | AH23: =AH22/AH10 -> -0.21405895 | AL23: % of Revenue | AM23: =AM22/AM10 -> -0.13130546 | AN23: -0.12110713 | AQ23: =AQ22/AQ10 -> -0.13130546 | AU23: % of Revenue | AV23: =AV22/AV10 -> -0.12459216 | AW23: -0.15141121 | AZ23: =AZ22/AZ10 -> -0.12459216 | BD23: % of Revenue | BE23: =BE22/BE10 -> -0.19071032 | BF23: -0.23519712 | BI23: =BI22/BI10 -> -0.19071032 | BM23: % of Revenue | BN23: =BN22/BN10 -> -0.29223024 | BO23: -0.3441983 | BR23: =BR22/BR10 -> -0.29223024 | BV23: % of Revenue | BW23: =BW22/BW10 -> -0.52648056 | BX23: -0.53238826 | CA23: =CA22/CA10 -> -0.52648056 | CE23: % of Revenue | CF23: =CF22/CF10 -> -0.31137656 | CG23: -0.30779282 | CJ23: =CJ22/CJ10 -> -0.31137656 | CN23: % of Revenue | CO23: =CO22/CO10 -> -0.21621452 | CP23: -0.23059103 | CS23: =CS22/CS10 -> -0.21621452 | CW23: % of Revenue | CX23: =CX22/CX10 -> -0.446656 | CY23: -0.59705416 | DB23: =DB22/DB10 -> -0.446656 | DF23: % of Revenue | DG23: =DG22/DG10 -> -0.22177576 | DH23: =DH22/DH10 -> -0.23201365 | DK23: =DK22/DK10 -> -0.22177576
B24: Adjusted EBITDA | C24: =C12+C22 -> 518.31963 | D24: 266.16781 | E24: =C24-D24 -> 252.15182 | F24: =+IF(IFERROR(C24/D24-1,"-")<300%,IFERROR(C24/D24-1,"-"),"n.a.") -> 0.94734153 | G24: =G12+G22 -> 518.31963 | H24: =C24-G24 -> 0 | I24: =+IF(IFERROR(C24/G24-1,"-")<300%,IFERROR(C24/G24-1,"-"),"n.a.") -> 0 | K24: Adjusted EBITDA | L24: =L12+L22 -> 922.69083 | M24: 908.76491 | N24: =L24-M24 -> 13.92592 | O24: =+IF(IFERROR(L24/M24-1,"-")<300%,IFERROR(L24/M24-1,"-"),"n.a.") -> 0.015324007 | P24: =P12+P22 -> 922.69083 | Q24: =L24-P24 -> 0 | R24: =+IF(IFERROR(L24/P24-1,"-")<300%,IFERROR(L24/P24-1,"-"),"n.a.") -> 0 | T24: Adjusted EBITDA | U24: =U12+U22 -> 807.86807 | V24: 891.2499 | W24: =U24-V24 -> -83.38183 | X24: =+IF(IFERROR(U24/V24-1,"-")<300%,IFERROR(U24/V24-1,"-"),"n.a.") -> -0.093556061 | Y24: =Y12+Y22 -> 807.86807 | Z24: =U24-Y24 -> 0 | AA24: =+IF(IFERROR(U24/Y24-1,"-")<300%,IFERROR(U24/Y24-1,"-"),"n.a.") -> 0 | AC24: Adjusted EBITDA | AD24: =AD12+AD22 -> 606.71847 | AE24: 718.93962 | AF24: =AD24-AE24 -> -112.22115 | AG24: =+IF(IFERROR(AD24/AE24-1,"-")<300%,IFERROR(AD24/AE24-1,"-"),"n.a.") -> -0.15609259 | AH24: =AH12+AH22 -> 606.71847 | AI24: =AD24-AH24 -> 0 | AJ24: =+IF(IFERROR(AD24/AH24-1,"-")<300%,IFERROR(AD24/AH24-1,"-"),"n.a.") -> 0 | AL24: Adjusted EBITDA | AM24: =AM12+AM22 -> 1202.5326 | AN24: 1068.4137 | AO24: =AM24-AN24 -> 134.11885 | AP24: =+IF(IFERROR(AM24/AN24-1,"-")<300%,IFERROR(AM24/AN24-1,"-"),"n.a.") -> 0.12553082 | AQ24: =AQ12+AQ22 -> 1202.5326 | AR24: =AM24-AQ24 -> 0 | AS24: =+IF(IFERROR(AM24/AQ24-1,"-")<300%,IFERROR(AM24/AQ24-1,"-"),"n.a.") -> 0 | AU24: Adjusted EBITDA | AV24: =AV12+AV22 -> 1174.5094 | AW24: 921.5948 | AX24: =AV24-AW24 -> 252.91456 | AY24: =+IF(IFERROR(AV24/AW24-1,"-")<300%,IFERROR(AV24/AW24-1,"-"),"n.a.") -> 0.27443141 | AZ24: =AZ12+AZ22 -> 1174.5094 | BA24: =AV24-AZ24 -> 0 | BB24: =+IF(IFERROR(AV24/AZ24-1,"-")<300%,IFERROR(AV24/AZ24-1,"-"),"n.a.") -> 0 | BD24: Adjusted EBITDA | BE24: =BE12+BE22 -> 634.10463 | BF24: 461.78105 | BG24: =BE24-BF24 -> 172.32358 | BH24: =+IF(IFERROR(BE24/BF24-1,"-")<300%,IFERROR(BE24/BF24-1,"-"),"n.a.") -> 0.37317163 | BI24: =BI12+BI22 -> 634.10463 | BJ24: =BE24-BI24 -> 0 | BK24: =+IF(IFERROR(BE24/BI24-1,"-")<300%,IFERROR(BE24/BI24-1,"-"),"n.a.") -> 0 | BM24: Adjusted EBITDA | BN24: =BN12+BN22 -> 327.62536 | BO24: 244.72047 | BP24: =BN24-BO24 -> 82.904891 | BQ24: =+IF(IFERROR(BN24/BO24-1,"-")<300%,IFERROR(BN24/BO24-1,"-"),"n.a.") -> 0.33877383 | BR24: =BR12+BR22 -> 327.62536 | BS24: =BN24-BR24 -> 0 | BT24: =+IF(IFERROR(BN24/BR24-1,"-")<300%,IFERROR(BN24/BR24-1,"-"),"n.a.") -> 0 | BV24: Adjusted EBITDA | BW24: =BW12+BW22 -> 49.42675 | BX24: 64.10467 | BY24: =BW24-BX24 -> -14.67792 | BZ24: =+IF(IFERROR(BW24/BX24-1,"-")<300%,IFERROR(BW24/BX24-1,"-"),"n.a.") -> -0.22896803 | CA24: =CA12+CA22 -> 49.42675 | CB24: =BW24-CA24 -> 0 | CC24: =+IF(IFERROR(BW24/CA24-1,"-")<300%,IFERROR(BW24/CA24-1,"-"),"n.a.") -> 0 | CE24: Adjusted EBITDA | CF24: =CF12+CF22 -> 288.39186 | CG24: 329.22967 | CH24: =CF24-CG24 -> -40.83781 | CI24: =+IF(IFERROR(CF24/CG24-1,"-")<300%,IFERROR(CF24/CG24-1,"-"),"n.a.") -> -0.12404049 | CJ24: =CJ12+CJ22 -> 288.39186 | CK24: =CF24-CJ24 -> 0 | CL24: =+IF(IFERROR(CF24/CJ24-1,"-")<300%,IFERROR(CF24/CJ24-1,"-"),"n.a.") -> 0 | CN24: Adjusted EBITDA | CO24: =CO12+CO22 -> 567.45787 | CP24: 538.35029 | CQ24: =CO24-CP24 -> 29.10758 | CR24: =+IF(IFERROR(CO24/CP24-1,"-")<300%,IFERROR(CO24/CP24-1,"-"),"n.a.") -> 0.054068105 | CS24: =CS12+CS22 -> 567.45787 | CT24: =CO24-CS24 -> 0 | CU24: =+IF(IFERROR(CO24/CS24-1,"-")<300%,IFERROR(CO24/CS24-1,"-"),"n.a.") -> 0 | CW24: Adjusted EBITDA | CX24: =CX12+CX22 -> 297.37436 | CY24: 11.18297 | CZ24: =CX24-CY24 -> 286.19139 | DA24: =+IF(IFERROR(CX24/CY24-1,"-")<300%,IFERROR(CX24/CY24-1,"-"),"n.a.") -> n.a. | DB24: =DB12+DB22 -> 297.37436 | DC24: =CX24-DB24 -> 0 | DD24: =+IF(IFERROR(CX24/DB24-1,"-")<300%,IFERROR(CX24/DB24-1,"-"),"n.a.") -> 0 | DF24: Adjusted EBITDA | DG24: =DG12+DG22 -> 7397.0198 | DH24: =DH12+DH22 -> 6424.4999 | DI24: =DG24-DH24 -> 972.51989 | DJ24: =+IF(IFERROR(DG24/DH24-1,"-")<300%,IFERROR(DG24/DH24-1,"-"),"n.a.") -> 0.15137675 | DK24: =DK12+DK22 -> 7397.0198 | DL24: =DG24-DK24 -> 0 | DM24: =+IF(IFERROR(DG24/DK24-1,"-")<300%,IFERROR(DG24/DK24-1,"-"),"n.a.") -> 0
B25: % Adj. EBITDA Margin | C25: =C24/C10 -> 0.45318257 | D25: 0.27054602 | F25: =+IF(IFERROR(C25/D25-1,"-")<300%,IFERROR(C25/D25-1,"-"),"n.a.") -> 0.67506646 | G25: =G24/G10 -> 0.45318257 | K25: % Adj. EBITDA Margin | L25: =L24/L10 -> 0.49804074 | M25: 0.61802742 | O25: =+IF(IFERROR(L25/M25-1,"-")<300%,IFERROR(L25/M25-1,"-"),"n.a.") -> -0.19414458 | P25: =P24/P10 -> 0.49804074 | T25: % Adj. EBITDA Margin | U25: =U24/U10 -> 0.45459038 | V25: 0.5810771 | X25: =+IF(IFERROR(U25/V25-1,"-")<300%,IFERROR(U25/V25-1,"-"),"n.a.") -> -0.21767631 | Y25: =Y24/Y10 -> 0.45459038 | AC25: % Adj. EBITDA Margin | AD25: =AD24/AD10 -> 0.4240557 | AE25: 0.49170157 | AG25: =+IF(IFERROR(AD25/AE25-1,"-")<300%,IFERROR(AD25/AE25-1,"-"),"n.a.") -> -0.13757506 | AH25: =AH24/AH10 -> 0.4240557 | AL25: % Adj. EBITDA Margin | AM25: =AM24/AM10 -> 0.51192698 | AN25: 0.55475213 | AP25: =+IF(IFERROR(AM25/AN25-1,"-")<300%,IFERROR(AM25/AN25-1,"-"),"n.a.") -> -0.077196903 | AQ25: =AQ24/AQ10 -> 0.51192698 | AU25: % Adj. EBITDA Margin | AV25: =AV24/AV10 -> 0.50419298 | AW25: 0.46965944 | AY25: =+IF(IFERROR(AV25/AW25-1,"-")<300%,IFERROR(AV25/AW25-1,"-"),"n.a.") -> 0.073528892 | AZ25: =AZ24/AZ10 -> 0.50419298 | BD25: % Adj. EBITDA Margin | BE25: =BE24/BE10 -> 0.42903398 | BF25: 0.35778835 | BH25: =+IF(IFERROR(BE25/BF25-1,"-")<300%,IFERROR(BE25/BF25-1,"-"),"n.a.") -> 0.19912786 | BI25: =BI24/BI10 -> 0.42903398 | BM25: % Adj. EBITDA Margin | BN25: =BN24/BN10 -> 0.3473473 | BO25: 0.31051754 | BQ25: =+IF(IFERROR(BN25/BO25-1,"-")<300%,IFERROR(BN25/BO25-1,"-"),"n.a.") -> 0.11860767 | BR25: =BR24/BR10 -> 0.3473473 | BV25: % Adj. EBITDA Margin | BW25: =BW24/BW10 -> 0.09021189 | BX25: 0.13269888 | BZ25: =+IF(IFERROR(BW25/BX25-1,"-")<300%,IFERROR(BW25/BX25-1,"-"),"n.a.") -> -0.32017594 | CA25: =CA24/CA10 -> 0.09021189 | CE25: % Adj. EBITDA Margin | CF25: =CF24/CF10 -> 0.31473626 | CG25: 0.36097567 | CI25: =+IF(IFERROR(CF25/CG25-1,"-")<300%,IFERROR(CF25/CG25-1,"-"),"n.a.") -> -0.12809565 | CJ25: =CJ24/CJ10 -> 0.31473626 | CN25: % Adj. EBITDA Margin | CO25: =CO24/CO10 -> 0.4006433 | CP25: 0.43935422 | CR25: =+IF(IFERROR(CO25/CP25-1,"-")<300%,IFERROR(CO25/CP25-1,"-"),"n.a.") -> -0.088108675 | CS25: =CS24/CS10 -> 0.4006433 | CW25: % Adj. EBITDA Margin | CX25: =CX24/CX10 -> 0.19140716 | CY25: 0.0097889511 | DA25: =+IF(IFERROR(CX25/CY25-1,"-")<300%,IFERROR(CX25/CY25-1,"-"),"n.a.") -> n.a. | DB25: =DB24/DB10 -> 0.19140716 | DF25: % Adj. EBITDA Margin | DG25: =DG24/DG10 -> 0.41701167 | DH25: =DH24/DH10 -> 0.42322134 | DJ25: =+IF(IFERROR(DG25/DH25-1,"-")<300%,IFERROR(DG25/DH25-1,"-"),"n.a.") -> -0.014672395 | DK25: =DK24/DK10 -> 0.41701167
B27: D&A | C27: =GETPIVOTDATA("ene-27 ",TABLA!$B$3,"Nivel 4","8.- Amortización del inmovilizado")/1000 -> -19.22535 | D27: -19.13287 | E27: =C27-D27 -> -0.09248 | F27: =+IF(IFERROR(C27/D27-1,"-")<300%,IFERROR(C27/D27-1,"-"),"n.a.") -> 0.0048335665 | G27: =C27 -> -19.22535 | H27: =C27-G27 -> 0 | I27: =+IF(IFERROR(C27/G27-1,"-")<300%,IFERROR(C27/G27-1,"-"),"n.a.") -> 0 | K27: D&A | L27: =GETPIVOTDATA("feb-27 ",TABLA!$B$3,"Nivel 4","8.- Amortización del inmovilizado")/1000 -> -19.22535 | M27: -19.13287 | N27: =L27-M27 -> -0.09248 | O27: =+IF(IFERROR(L27/M27-1,"-")<300%,IFERROR(L27/M27-1,"-"),"n.a.") -> 0.0048335665 | P27: =L27 -> -19.22535 | Q27: =L27-P27 -> 0 | R27: =+IF(IFERROR(L27/P27-1,"-")<300%,IFERROR(L27/P27-1,"-"),"n.a.") -> 0 | T27: D&A | U27: =GETPIVOTDATA("mar-27 ",TABLA!$B$3,"Nivel 4","8.- Amortización del inmovilizado")/1000 -> -19.22535 | V27: -18.90355 | W27: =U27-V27 -> -0.3218 | X27: =+IF(IFERROR(U27/V27-1,"-")<300%,IFERROR(U27/V27-1,"-"),"n.a.") -> 0.017023258 | Y27: =U27 -> -19.22535 | Z27: =U27-Y27 -> 0 | AA27: =+IF(IFERROR(U27/Y27-1,"-")<300%,IFERROR(U27/Y27-1,"-"),"n.a.") -> 0 | AC27: D&A | AD27: =GETPIVOTDATA("abr-27 ",TABLA!$B$3,"Nivel 4","8.- Amortización del inmovilizado")/1000 -> -19.22535 | AE27: -18.90355 | AF27: =AD27-AE27 -> -0.3218 | AG27: =+IF(IFERROR(AD27/AE27-1,"-")<300%,IFERROR(AD27/AE27-1,"-"),"n.a.") -> 0.017023258 | AH27: =AD27 -> -19.22535 | AI27: =AD27-AH27 -> 0 | AJ27: =+IF(IFERROR(AD27/AH27-1,"-")<300%,IFERROR(AD27/AH27-1,"-"),"n.a.") -> 0 | AL27: D&A | AM27: =GETPIVOTDATA("may-27 ",TABLA!$B$3,"Nivel 4","8.- Amortización del inmovilizado")/1000 -> -19.22535 | AN27: -19.18968 | AO27: =AM27-AN27 -> -0.03567 | AP27: =+IF(IFERROR(AM27/AN27-1,"-")<300%,IFERROR(AM27/AN27-1,"-"),"n.a.") -> 0.0018588116 | AQ27: =AM27 -> -19.22535 | AR27: =AM27-AQ27 -> 0 | AS27: =+IF(IFERROR(AM27/AQ27-1,"-")<300%,IFERROR(AM27/AQ27-1,"-"),"n.a.") -> 0 | AU27: D&A | AV27: =GETPIVOTDATA("ago-27 ",TABLA!$B$3,"Nivel 4","8.- Amortización del inmovilizado")/1000 -> -19.22535 | AW27: -19.06025 | AX27: =AV27-AW27 -> -0.1651 | AY27: =+IF(IFERROR(AV27/AW27-1,"-")<300%,IFERROR(AV27/AW27-1,"-"),"n.a.") -> 0.008662006 | AZ27: =AV27 -> -19.22535 | BA27: =AV27-AZ27 -> 0 | BB27: =+IF(IFERROR(AV27/AZ27-1,"-")<300%,IFERROR(AV27/AZ27-1,"-"),"n.a.") -> 0 | BD27: D&A | BE27: =GETPIVOTDATA("jul-27 ",TABLA!$B$3,"Nivel 4","8.- Amortización del inmovilizado")/1000 -> -19.22535 | BF27: -19.22529 | BG27: =BE27-BF27 -> -6e-05 | BH27: =+IF(IFERROR(BE27/BF27-1,"-")<300%,IFERROR(BE27/BF27-1,"-"),"n.a.") -> 3.1208892e-06 | BI27: =BE27 -> -19.22535 | BJ27: =BE27-BI27 -> 0 | BK27: =+IF(IFERROR(BE27/BI27-1,"-")<300%,IFERROR(BE27/BI27-1,"-"),"n.a.") -> 0 | BM27: D&A | BN27: =GETPIVOTDATA("ago-27 ",TABLA!$B$3,"Nivel 4","8.- Amortización del inmovilizado")/1000 -> -19.22535 | BO27: -19.22529 | BP27: =BN27-BO27 -> -6e-05 | BQ27: =+IF(IFERROR(BN27/BO27-1,"-")<300%,IFERROR(BN27/BO27-1,"-"),"n.a.") -> 3.1208892e-06 | BR27: =BN27 -> -19.22535 | BS27: =BN27-BR27 -> 0 | BT27: =+IF(IFERROR(BN27/BR27-1,"-")<300%,IFERROR(BN27/BR27-1,"-"),"n.a.") -> 0 | BV27: D&A | BW27: =GETPIVOTDATA("sep-27 ",TABLA!$B$3,"Nivel 4","8.- Amortización del inmovilizado")/1000 -> -19.22535 | BX27: -19.22535 | BY27: =BW27-BX27 -> 0 | BZ27: =+IF(IFERROR(BW27/BX27-1,"-")<300%,IFERROR(BW27/BX27-1,"-"),"n.a.") -> 0 | CA27: =BW27 -> -19.22535 | CB27: =BW27-CA27 -> 0 | CC27: =+IF(IFERROR(BW27/CA27-1,"-")<300%,IFERROR(BW27/CA27-1,"-"),"n.a.") -> 0 | CE27: D&A | CF27: =GETPIVOTDATA("oct-27 ",TABLA!$B$3,"Nivel 4","8.- Amortización del inmovilizado")/1000 -> -19.22535 | CG27: -19.22535 | CH27: =CF27-CG27 -> 0 | CI27: =+IF(IFERROR(CF27/CG27-1,"-")<300%,IFERROR(CF27/CG27-1,"-"),"n.a.") -> 0 | CJ27: =CF27 -> -19.22535 | CK27: =CF27-CJ27 -> 0 | CL27: =+IF(IFERROR(CF27/CJ27-1,"-")<300%,IFERROR(CF27/CJ27-1,"-"),"n.a.") -> 0 | CN27: D&A | CO27: =GETPIVOTDATA("nov-27 ",TABLA!$B$3,"Nivel 4","8.- Amortización del inmovilizado")/1000 -> -19.22535 | CP27: -19.22535 | CQ27: =CO27-CP27 -> 0 | CR27: =+IF(IFERROR(CO27/CP27-1,"-")<300%,IFERROR(CO27/CP27-1,"-"),"n.a.") -> 0 | CS27: =CO27 -> -19.22535 | CT27: =CO27-CS27 -> 0 | CU27: =+IF(IFERROR(CO27/CS27-1,"-")<300%,IFERROR(CO27/CS27-1,"-"),"n.a.") -> 0 | CW27: D&A | CX27: =GETPIVOTDATA("dic-27 ",TABLA!$B$3,"Nivel 4","8.- Amortización del inmovilizado")/1000 -> -19.22535 | CY27: -19.22535 | CZ27: =CX27-CY27 -> 0 | DA27: =+IF(IFERROR(CX27/CY27-1,"-")<300%,IFERROR(CX27/CY27-1,"-"),"n.a.") -> 0 | DB27: =CX27 -> -19.22535 | DC27: =CX27-DB27 -> 0 | DD27: =+IF(IFERROR(CX27/DB27-1,"-")<300%,IFERROR(CX27/DB27-1,"-"),"n.a.") -> 0 | DF27: D&A | DG27: =GETPIVOTDATA("Total 2027 ",TABLA!$B$3,"Nivel 4","8.- Amortización del inmovilizado")/1000 -> -230.7042 | DH27: =CY27+CP27+CG27+BX27+BO27+BF27+AW27+AN27+AE27+V27+M27+D27 -> -229.67475 | DI27: =DG27-DH27 -> -1.02945 | DJ27: =+IF(IFERROR(DG27/DH27-1,"-")<300%,IFERROR(DG27/DH27-1,"-"),"n.a.") -> 0.004482208 | DK27: =DG27 -> -230.7042 | DL27: =DG27-DK27 -> 0 | DM27: =+IF(IFERROR(DG27/DK27-1,"-")<300%,IFERROR(DG27/DK27-1,"-"),"n.a.") -> 0
B28: Other Gains/Losses | C28: =GETPIVOTDATA("ene-27 ",TABLA!$B$3,"Nivel 4","13.- Otros resultados")/1000+GETPIVOTDATA("ago-27 ",TABLA!$B$3,"Nivel 4","11.- Deterioro y resultado por enajenaciones del inmovilizado")/1000 -> 0 | D28: 3.06527 | E28: =C28-D28 -> -3.06527 | F28: n.a. | G28: =C28 -> 0 | H28: =C28-G28 -> 0 | I28: =+IF(IFERROR(C28/G28-1,"-")<300%,IFERROR(C28/G28-1,"-"),"n.a.") -> n.a. | K28: Other Gains/Losses | L28: =GETPIVOTDATA("feb-27 ",TABLA!$B$3,"Nivel 4","13.- Otros resultados")+GETPIVOTDATA("ago-27 ",TABLA!$B$3,"Nivel 4","11.- Deterioro y resultado por enajenaciones del inmovilizado")/1000 -> 0 | M28: 2e-05 | N28: =L28-M28 -> -2e-05 | O28: n.a. | P28: =L28 -> 0 | Q28: =L28-P28 -> 0 | R28: =+IF(IFERROR(L28/P28-1,"-")<300%,IFERROR(L28/P28-1,"-"),"n.a.") -> n.a. | T28: Other Gains/Losses | U28: =(GETPIVOTDATA("mar-27 ",TABLA!$B$3,"Nivel 4","11.- Deterioro y resultado por enajenaciones del inmovilizado")+GETPIVOTDATA("mar-27 ",TABLA!$B$3,"Nivel 4","13.- Otros resultados"))/1000 -> 0 | V28: 1.99986 | W28: =U28-V28 -> -1.99986 | X28: n.a. | Y28: =U28 -> 0 | Z28: =U28-Y28 -> 0 | AA28: =+IF(IFERROR(U28/Y28-1,"-")<300%,IFERROR(U28/Y28-1,"-"),"n.a.") -> n.a. | AC28: Other Gains/Losses | AD28: =GETPIVOTDATA("abr-27 ",TABLA!$B$3,"Nivel 4","13.- Otros resultados")/1000+GETPIVOTDATA("ago-27 ",TABLA!$B$3,"Nivel 4","11.- Deterioro y resultado por enajenaciones del inmovilizado")/1000 -> 0 | AE28: 1.02426 | AF28: =AD28-AE28 -> -1.02426 | AG28: n.a. | AH28: =AD28 -> 0 | AI28: =AD28-AH28 -> 0 | AJ28: =+IF(IFERROR(AD28/AH28-1,"-")<300%,IFERROR(AD28/AH28-1,"-"),"n.a.") -> n.a. | AL28: Other Gains/Losses | AM28: =GETPIVOTDATA("may-27 ",TABLA!$B$3,"Nivel 4","13.- Otros resultados")+GETPIVOTDATA("ago-27 ",TABLA!$B$3,"Nivel 4","11.- Deterioro y resultado por enajenaciones del inmovilizado")/1000 -> 0 | AN28: 0 | AO28: =AM28-AN28 -> 0 | AP28: n.a. | AQ28: =AM28 -> 0 | AR28: =AM28-AQ28 -> 0 | AS28: =+IF(IFERROR(AM28/AQ28-1,"-")<300%,IFERROR(AM28/AQ28-1,"-"),"n.a.") -> n.a. | AU28: Other Gains/Losses | AV28: =(GETPIVOTDATA("jun-27 ",TABLA!$B$3,"Nivel 4","11.- Deterioro y resultado por enajenaciones del inmovilizado")+GETPIVOTDATA("jun-27 ",TABLA!$B$3,"Nivel 4","13.- Otros resultados"))/1000 -> 0 | AW28: 0 | AX28: =AV28-AW28 -> 0 | AY28: n.a. | AZ28: =AV28 -> 0 | BA28: =AV28-AZ28 -> 0 | BB28: =+IF(IFERROR(AV28/AZ28-1,"-")<300%,IFERROR(AV28/AZ28-1,"-"),"n.a.") -> n.a. | BD28: Other Gains/Losses | BE28: =GETPIVOTDATA("jul-27 ",TABLA!$B$3,"Nivel 4","13.- Otros resultados")+GETPIVOTDATA("ago-27 ",TABLA!$B$3,"Nivel 4","11.- Deterioro y resultado por enajenaciones del inmovilizado")/1000 -> 0 | BF28: -0.08803 | BG28: =BE28-BF28 -> 0.08803 | BH28: n.a. | BI28: =BE28 -> 0 | BJ28: =BE28-BI28 -> 0 | BK28: =+IF(IFERROR(BE28/BI28-1,"-")<300%,IFERROR(BE28/BI28-1,"-"),"n.a.") -> n.a. | BM28: Other Gains/Losses | BN28: =GETPIVOTDATA("ago-27 ",TABLA!$B$3,"Nivel 4","13.- Otros resultados")+GETPIVOTDATA("ago-27 ",TABLA!$B$3,"Nivel 4","11.- Deterioro y resultado por enajenaciones del inmovilizado")/1000 -> 0 | BO28: -0.01 | BP28: =BN28-BO28 -> 0.01 | BQ28: n.a. | BR28: =BN28 -> 0 | BS28: =BN28-BR28 -> 0 | BT28: =+IF(IFERROR(BN28/BR28-1,"-")<300%,IFERROR(BN28/BR28-1,"-"),"n.a.") -> n.a. | BV28: Other Gains/Losses | BW28: =GETPIVOTDATA("sep-27 ",TABLA!$B$3,"Nivel 4","13.- Otros resultados")+GETPIVOTDATA("ago-27 ",TABLA!$B$3,"Nivel 4","11.- Deterioro y resultado por enajenaciones del inmovilizado")/1000 -> 0 | BX28: 0 | BY28: =BW28-BX28 -> 0 | BZ28: n.a. | CA28: =BW28 -> 0 | CB28: =BW28-CA28 -> 0 | CC28: =+IF(IFERROR(BW28/CA28-1,"-")<300%,IFERROR(BW28/CA28-1,"-"),"n.a.") -> n.a. | CE28: Other Gains/Losses | CF28: =GETPIVOTDATA("oct-27 ",TABLA!$B$3,"Nivel 4","13.- Otros resultados")+GETPIVOTDATA("ago-27 ",TABLA!$B$3,"Nivel 4","11.- Deterioro y resultado por enajenaciones del inmovilizado")/1000 -> 0 | CG28: 0 | CH28: =CF28-CG28 -> 0 | CI28: n.a. | CJ28: =CF28 -> 0 | CK28: =CF28-CJ28 -> 0 | CL28: =+IF(IFERROR(CF28/CJ28-1,"-")<300%,IFERROR(CF28/CJ28-1,"-"),"n.a.") -> n.a. | CN28: Other Gains/Losses | CO28: =GETPIVOTDATA("nov-27 ",TABLA!$B$3,"Nivel 4","13.- Otros resultados")+GETPIVOTDATA("ago-27 ",TABLA!$B$3,"Nivel 4","11.- Deterioro y resultado por enajenaciones del inmovilizado")/1000 -> 0 | CP28: 0 | CQ28: =CO28-CP28 -> 0 | CR28: n.a. | CS28: =CO28 -> 0 | CT28: =CO28-CS28 -> 0 | CU28: =+IF(IFERROR(CO28/CS28-1,"-")<300%,IFERROR(CO28/CS28-1,"-"),"n.a.") -> n.a. | CW28: Other Gains/Losses | CX28: =GETPIVOTDATA("dic-27 ",TABLA!$B$3,"Nivel 4","13.- Otros resultados")+GETPIVOTDATA("ago-27 ",TABLA!$B$3,"Nivel 4","11.- Deterioro y resultado por enajenaciones del inmovilizado")/1000 -> 0 | CY28: 0 | CZ28: =CX28-CY28 -> 0 | DA28: n.a. | DB28: =CX28 -> 0 | DC28: =CX28-DB28 -> 0 | DD28: =+IF(IFERROR(CX28/DB28-1,"-")<300%,IFERROR(CX28/DB28-1,"-"),"n.a.") -> n.a. | DF28: Other Gains/Losses | DG28: =GETPIVOTDATA("Total 2027 ",TABLA!$B$3,"Nivel 4","13.- Otros resultados")/1000+GETPIVOTDATA("ago-27 ",TABLA!$B$3,"Nivel 4","11.- Deterioro y resultado por enajenaciones del inmovilizado")/1000 -> 0 | DH28: =CY28+CP28+CG28+BX28+BO28+BF28+AW28+AN28+AE28+V28+M28+D28 -> 5.99138 | DI28: =DG28-DH28 -> -5.99138 | DJ28: n.a. | DK28: =DG28 -> 0 | DL28: =DG28-DK28 -> 0 | DM28: =+IF(IFERROR(DG28/DK28-1,"-")<300%,IFERROR(DG28/DK28-1,"-"),"n.a.") -> n.a.
B29: Adjusted EBIT | C29: =C24+C27+C28 -> 499.09428 | D29: 250.10021 | E29: =C29-D29 -> 248.99407 | F29: =+IF(IFERROR(C29/D29-1,"-")<300%,IFERROR(C29/D29-1,"-"),"n.a.") -> 0.99557721 | G29: =G24+G27+G28 -> 499.09428 | H29: =C29-G29 -> 0 | I29: =+IF(IFERROR(C29/G29-1,"-")<300%,IFERROR(C29/G29-1,"-"),"n.a.") -> 0 | K29: Adjusted EBIT | L29: =L24+L27+L28 -> 903.46548 | M29: 889.63206 | N29: =L29-M29 -> 13.83342 | O29: =+IF(IFERROR(L29/M29-1,"-")<300%,IFERROR(L29/M29-1,"-"),"n.a.") -> 0.015549597 | P29: =P24+P27+P28 -> 903.46548 | Q29: =L29-P29 -> 0 | R29: =+IF(IFERROR(L29/P29-1,"-")<300%,IFERROR(L29/P29-1,"-"),"n.a.") -> 0 | T29: Adjusted EBIT | U29: =U24+U27+U28 -> 788.64272 | V29: 874.34621 | W29: =U29-V29 -> -85.70349 | X29: =+IF(IFERROR(U29/V29-1,"-")<300%,IFERROR(U29/V29-1,"-"),"n.a.") -> -0.098020085 | Y29: =Y24+Y27+Y28 -> 788.64272 | Z29: =U29-Y29 -> 0 | AA29: =+IF(IFERROR(U29/Y29-1,"-")<300%,IFERROR(U29/Y29-1,"-"),"n.a.") -> 0 | AC29: Adjusted EBIT | AD29: =AD24+AD27+AD28 -> 587.49312 | AE29: 701.06033 | AF29: =AD29-AE29 -> -113.56721 | AG29: =+IF(IFERROR(AD29/AE29-1,"-")<300%,IFERROR(AD29/AE29-1,"-"),"n.a.") -> -0.16199349 | AH29: =AH24+AH27+AH28 -> 587.49312 | AI29: =AD29-AH29 -> 0 | AJ29: =+IF(IFERROR(AD29/AH29-1,"-")<300%,IFERROR(AD29/AH29-1,"-"),"n.a.") -> 0 | AL29: Adjusted EBIT | AM29: =AM24+AM27+AM28 -> 1183.3072 | AN29: 1049.224 | AO29: =AM29-AN29 -> 134.08318 | AP29: =+IF(IFERROR(AM29/AN29-1,"-")<300%,IFERROR(AM29/AN29-1,"-"),"n.a.") -> 0.12779271 | AQ29: =AQ24+AQ27+AQ28 -> 1183.3072 | AR29: =AM29-AQ29 -> 0 | AS29: =+IF(IFERROR(AM29/AQ29-1,"-")<300%,IFERROR(AM29/AQ29-1,"-"),"n.a.") -> 0 | AU29: Adjusted EBIT | AV29: =AV24+AV27+AV28 -> 1155.284 | AW29: 902.53455 | AX29: =AV29-AW29 -> 252.74946 | AY29: =+IF(IFERROR(AV29/AW29-1,"-")<300%,IFERROR(AV29/AW29-1,"-"),"n.a.") -> 0.28004408 | AZ29: =AZ24+AZ27+AZ28 -> 1155.284 | BA29: =AV29-AZ29 -> 0 | BB29: =+IF(IFERROR(AV29/AZ29-1,"-")<300%,IFERROR(AV29/AZ29-1,"-"),"n.a.") -> 0 | BD29: Adjusted EBIT | BE29: =BE24+BE27+BE28 -> 614.87928 | BF29: 442.46773 | BG29: =BE29-BF29 -> 172.41155 | BH29: =+IF(IFERROR(BE29/BF29-1,"-")<300%,IFERROR(BE29/BF29-1,"-"),"n.a.") -> 0.38965905 | BI29: =BI24+BI27+BI28 -> 614.87928 | BJ29: =BE29-BI29 -> 0 | BK29: =+IF(IFERROR(BE29/BI29-1,"-")<300%,IFERROR(BE29/BI29-1,"-"),"n.a.") -> 0 | BM29: Adjusted EBIT | BN29: =BN24+BN27+BN28 -> 308.40001 | BO29: 225.48518 | BP29: =BN29-BO29 -> 82.914831 | BQ29: =+IF(IFERROR(BN29/BO29-1,"-")<300%,IFERROR(BN29/BO29-1,"-"),"n.a.") -> 0.36771743 | BR29: =BR24+BR27+BR28 -> 308.40001 | BS29: =BN29-BR29 -> 0 | BT29: =+IF(IFERROR(BN29/BR29-1,"-")<300%,IFERROR(BN29/BR29-1,"-"),"n.a.") -> 0 | BV29: Adjusted EBIT | BW29: =BW24+BW27+BW28 -> 30.2014 | BX29: 44.87932 | BY29: =BW29-BX29 -> -14.67792 | BZ29: =+IF(IFERROR(BW29/BX29-1,"-")<300%,IFERROR(BW29/BX29-1,"-"),"n.a.") -> -0.32705308 | CA29: =CA24+CA27+CA28 -> 30.2014 | CB29: =BW29-CA29 -> 0 | CC29: =+IF(IFERROR(BW29/CA29-1,"-")<300%,IFERROR(BW29/CA29-1,"-"),"n.a.") -> 0 | CE29: Adjusted EBIT | CF29: =CF24+CF27+CF28 -> 269.16651 | CG29: 310.00432 | CH29: =CF29-CG29 -> -40.83781 | CI29: =+IF(IFERROR(CF29/CG29-1,"-")<300%,IFERROR(CF29/CG29-1,"-"),"n.a.") -> -0.13173304 | CJ29: =CJ24+CJ27+CJ28 -> 269.16651 | CK29: =CF29-CJ29 -> 0 | CL29: =+IF(IFERROR(CF29/CJ29-1,"-")<300%,IFERROR(CF29/CJ29-1,"-"),"n.a.") -> 0 | CN29: Adjusted EBIT | CO29: =CO24+CO27+CO28 -> 548.23252 | CP29: 519.12494 | CQ29: =CO29-CP29 -> 29.10758 | CR29: =+IF(IFERROR(CO29/CP29-1,"-")<300%,IFERROR(CO29/CP29-1,"-"),"n.a.") -> 0.056070471 | CS29: =CS24+CS27+CS28 -> 548.23252 | CT29: =CO29-CS29 -> 0 | CU29: =+IF(IFERROR(CO29/CS29-1,"-")<300%,IFERROR(CO29/CS29-1,"-"),"n.a.") -> 0 | CW29: Adjusted EBIT | CX29: =CX24+CX27+CX28 -> 278.14901 | CY29: -8.04238 | CZ29: =CX29-CY29 -> 286.19139 | DA29: =+IF(IFERROR(CX29/CY29-1,"-")<300%,IFERROR(CX29/CY29-1,"-"),"n.a.") -> -35.58541 | DB29: =DB24+DB27+DB28 -> 278.14901 | DC29: =CX29-DB29 -> 0 | DD29: =+IF(IFERROR(CX29/DB29-1,"-")<300%,IFERROR(CX29/DB29-1,"-"),"n.a.") -> 0 | DF29: Adjusted EBIT | DG29: =DG24+DG27+DG28 -> 7166.3156 | DH29: =DH24+DH27+DH28 -> 6200.8165 | DI29: =DG29-DH29 -> 965.49906 | DJ29: =+IF(IFERROR(DG29/DH29-1,"-")<300%,IFERROR(DG29/DH29-1,"-"),"n.a.") -> 0.15570515 | DK29: =DK24+DK27+DK28 -> 7166.3156 | DL29: =DG29-DK29 -> 0 | DM29: =+IF(IFERROR(DG29/DK29-1,"-")<300%,IFERROR(DG29/DK29-1,"-"),"n.a.") -> 0
B30: % EBIT Margin | C30: =C29/C10 -> 0.43637326 | D30: 0.25421412 | G30: =G29/G10 -> 0.43637326 | K30: % EBIT Margin | L30: =L29/L10 -> 0.48766348 | M30: 0.60501566 | P30: =P29/P10 -> 0.48766348 | T30: % EBIT Margin | U30: =U29/U10 -> 0.44377221 | V30: 0.57005623 | Y30: =Y29/Y10 -> 0.44377221 | AC30: % EBIT Margin | AD30: =AD29/AD10 -> 0.41061846 | AE30: 0.47947346 | AH30: =AH29/AH10 -> 0.41061846 | AL30: % EBIT Margin | AM30: =AM29/AM10 -> 0.50374261 | AN30: 0.54478828 | AQ30: =AQ29/AQ10 -> 0.50374261 | AU30: % EBIT Margin | AV30: =AV29/AV10 -> 0.49593993 | AW30: 0.45994604 | AZ30: =AZ29/AZ10 -> 0.49593993 | BD30: % EBIT Margin | BE30: =BE29/BE10 -> 0.41602614 | BF30: 0.34282437 | BI30: =BI29/BI10 -> 0.41602614 | BM30: % EBIT Margin | BN30: =BN29/BN10 -> 0.32696465 | BO30: 0.28611053 | BR30: =BR29/BR10 -> 0.32696465 | BV30: % EBIT Margin | BW30: =BW29/BW10 -> 0.055122487 | BX30: 0.09290174 | CA30: =CA29/CA10 -> 0.055122487 | CE30: % EBIT Margin | CF30: =CF29/CF10 -> 0.29375468 | CG30: 0.33989652 | CJ30: =CJ29/CJ10 -> 0.29375468 | CN30: % EBIT Margin | CO30: =CO29/CO10 -> 0.38706959 | CP30: 0.42366417 | CS30: =CS29/CS10 -> 0.38706959 | CW30: % EBIT Margin | CX30: =CX29/CX10 -> 0.17903262 | CY30: -0.007039853 | DB30: =DB29/DB10 -> 0.17903262 | DF30: % EBIT Margin | DG30: =DG29/DG10 -> 0.40400557 | DH30: =DH29/DH10 -> 0.40848594 | DK30: =DK29/DK10 -> 0.40400557

Sheet TABLA
B1: Periodo | C1: 2027
B3: Detalle sin Ajustar | C3: ene-27 | D3: feb-27 | E3: mar-27 | F3: abr-27 | G3: may-27 | H3: jun-27 | I3: jul-27 | J3: ago-27 | K3: sep-27 | L3: oct-27 | M3: nov-27 | N3: dic-27 | O3: Total 2027
B4: 1.- Importe neto de la cifra de negocios | C4: 1143732.5 | D4: 1852641.3 | E4: 1777134.1 | F4: 1430751.8 | G4: 2349031.4 | H4: 2329483.8 | I4: 1477982.3 | J4: 943221.27 | K4: 547896.18 | L4: 916296.91 | M4: 1416366.8 | N4: 1553621.9 | O4: 17738160
B5: 2.- Variación de existencias | C5: 0 | D5: 0 | E5: 0 | F5: 0 | G5: 0 | H5: 0 | I5: 0 | J5: 0 | K5: 0 | L5: 0 | M5: 0 | N5: 0 | O5: 0
B6: 4.- Aprovisionamientos | C6: -329984.43 | D6: -632159.77 | E6: -664980.37 | F6: -517768.13 | G6: -838058.2 | H6: -864738.97 | I6: -562011.2 | J6: -339958.13 | K6: -210012.74 | L6: -342591.67 | M6: -542669.87 | N6: -562313.02 | O6: -6407246.5
B7: 6.- Gastos de personal | C7: -162382.74 | D7: -162382.74 | E7: -162382.74 | F7: -162382.74 | G7: -162382.74 | H7: -162382.74 | I7: -162382.74 | J7: -162382.74 | K7: -162382.74 | L7: -162382.74 | M7: -163382.74 | N7: -441399.46 | O7: -2228609.6
B8: 5.- Otros ingresos de explotación | C8: 29809.2 | D8: 21246.7 | E8: 19638.3 | F8: 8004.2 | G8: 38718.8 | H8: 33492 | I8: 13212.8 | J8: 18509.6 | K8: 24148.9 | L8: 23411.3 | M8: 40650.7 | N8: 34380.8 | O8: 305223.3
B9: 7.- Otros gastos de explotación | C9: -162854.9 | D9: -156654.63 | E9: -161541.22 | F9: -151886.7 | G9: -184776.71 | H9: -161344.68 | I9: -132696.54 | J9: -131764.64 | K9: -150222.85 | L9: -146341.94 | M9: -183507.03 | N9: -286915.89 | O9: -2010507.7
B10: 11.- Deterioro y resultado por enajenaciones del inmovilizado | C10: 0 | D10: 0 | E10: 0 | F10: 0 | G10: 0 | H10: 0 | I10: 0 | J10: 0 | K10: 0 | L10: 0 | M10: 0 | N10: 0 | O10: 0
B11: 8.- Amortización del inmovilizado | C11: -19225.35 | D11: -19225.35 | E11: -19225.35 | F11: -19225.35 | G11: -19225.35 | H11: -19225.35 | I11: -19225.35 | J11: -19225.35 | K11: -19225.35 | L11: -19225.35 | M11: -19225.35 | N11: -19225.35 | O11: -230704.2
B12: 13.- Otros resultados | C12: 0 | D12: 0 | E12: 0 | F12: 0 | G12: 0 | H12: 0 | I12: 0 | J12: 0 | K12: 0 | L12: 0 | M12: 0 | N12: 0 | O12: 0
B13: 15.- Gastos financieros | C13: -30880.78 | D13: -50021.31 | E13: -47982.62 | F13: -38630.3 | G13: -63423.85 | H13: -62896.06 | I13: -39905.52 | J13: -25466.97 | K13: -14793.2 | L13: -24740.02 | M13: -38241.9 | N13: -41947.79 | O13: -478930.32
B14: 17.- Diferencias de cambio | C14: 0 | D14: 0 | E14: 0 | F14: 0 | G14: 0 | H14: 0 | I14: 0 | J14: 0 | K14: 0 | L14: 0 | M14: 0 | N14: 0 | O14: 0
B15: 14.- Ingresos financieros | C15: 0 | D15: 0 | E15: 0 | F15: 0 | G15: 0 | H15: 0 | I15: 0 | J15: 0 | K15: 0 | L15: 0 | M15: 0 | N15: 0 | O15: 0
B16: Total general | C16: 468213.5 | D16: 853444.17 | E16: 740660.1 | F16: 548862.82 | G16: 1119883.4 | H16: 1092387.9 | I16: 574973.76 | J16: 282933.04 | K16: 15408.2 | L16: 244426.49 | M16: 509990.62 | N16: 236201.22 | O16: 6687385.2
B17: EBITDA | C17: =+SUM(C4:C9) -> 518319.63 | D17: =+SUM(D4:D9) -> 922690.83 | E17: =+SUM(E4:E9) -> 807868.07 | F17: =+SUM(F4:F9) -> 606718.47 | G17: =+SUM(G4:G9) -> 1202532.6 | H17: =+SUM(H4:H9) -> 1174509.4 | I17: =+SUM(I4:I9) -> 634104.63 | J17: =+SUM(J4:J9) -> 327625.36 | ... O17: =+SUM(O4:O9) -> 7397019.8
B18: EBITDA % | C18: =C17/C4 -> 0.45318257 | D18: =D17/D4 -> 0.49804074 | E18: =E17/E4 -> 0.45459038 | F18: =F17/F4 -> 0.4240557 | G18: =G17/G4 -> 0.51192698 | H18: =H17/H4 -> 0.50419298 | I18: =I17/I4 -> 0.42903398 | J18: =J17/J4 -> 0.3473473 | ... O18: =O17/O4 -> 0.41701167
N19: Check | O19: =SUM(C16:N16)-O16 -> 0

Sheet PL Mensual 2027
K2: =SUBTOTAL(9,K4:K215) -> 483243.78 | L2: =SUBTOTAL(9,L4:L215) -> 881363.22 | M2: =SUBTOTAL(9,M4:M215) -> 770220.19 | N2: =SUBTOTAL(9,N4:N215) -> 571062.28 | O2: =SUBTOTAL(9,O4:O2027) -> 1158097.3 | P2: =SUBTOTAL(9,P4:P2027) -> 1131936 | Q2: =SUBTOTAL(9,Q4:Q2096) -> 599385.39 | R2: =SUBTOTAL(9,R4:R2015) -> 300562.01 | S2: =SUBTOTAL(9,S4:S215) -> 22339.9 | T2: =SUBTOTAL(9,T4:T215) -> 257987.14 | U2: =SUBTOTAL(9,U4:U215) -> 533435.17 | V2: =SUBTOTAL(9,V4:V215) -> 262477.89 | W2: =SUBTOTAL(9,W4:W2036) -> 6972110.3
B3: Periodo | C3: Empresa | D3: Nivel 1 | E3: Nivel 2 | F3: Nivel 3 | G3: Nivel 4 | H3: Nivel 5 | I3: Cuenta | J3: Grupo Ext Item | K3: 46388 | L3: 46419 | M3: 46447 | N3: 46478 | O3: 46508 | P3: 46539 | Q3: 46569 | R3: 46600 | S3: 46631 | T3: 46661 | U3: 46692 | V3: 46722 | W3: Total 2027
B4: 2027 | C4: Codiagro | D4: RESULTADO DEL EJERCICIO | E4: RESULTADO ANTES DE IMPUESTOS | F4: RESULTADO DE LA EXPLOTACION | G4: 1.- Importe neto de la cifra de negocios | H4: (700) Ventas | I4: 700000000 - Ventas de mercaderías | J4: - | K4: 1167113.2 | L4: 1890513.7 | M4: 1813463 | N4: 1459999.9 | O4: 2397051.3 | P4: 2377104 | Q4: 1508195.8 | R4: 962502.99 | S4: 559096.5 | T4: 935028.24 | U4: 1445320.8 | V4: 1585381.7 | W4: 18100771 | X4: Presupuesto de Ventas Brutas 2027 ajustado (18.100.771,19 €) para obtener exactamente 17.738.160,29 € de Cifra Neta tras rappels (397k €) y envases (34k €).
B5: 2027 | C5: Codiagro | D5: RESULTADO DEL EJERCICIO | E5: RESULTADO ANTES DE IMPUESTOS | F5: RESULTADO DE LA EXPLOTACION | G5: 1.- Importe neto de la cifra de negocios | H5: (700) Ventas | I5: 700000001 - VENTA MERCADERIAS POR ANTICIPO | J5: - | K5: 0 | L5: 0 | M5: 0 | N5: 0 | O5: 0 | P5: 0 | Q5: 0 | R5: 0 | S5: 0 | T5: 0 | U5: 0 | V5: 0 | W5: 0 | X5: Sin dotación presupuestada en 2027 por corresponder a partidas singulares/no recurrentes.
B6: 2027 | C6: Codiagro | D6: RESULTADO DEL EJERCICIO | E6: RESULTADO ANTES DE IMPUESTOS | F6: RESULTADO DE LA EXPLOTACION | G6: 1.- Importe neto de la cifra de negocios | H6: (700) Ventas | I6: 700000624 - VENTA POR TRANSP. REP. AL CLIENTE | J6: - | K6: 0 | L6: 0 | M6: 0 | N6: 0 | O6: 0 | P6: 0 | Q6: 0 | R6: 0 | S6: 0 | T6: 0 | U6: 0 | V6: 0 | W6: 0 | X6: Sin dotación presupuestada en 2027 por corresponder a partidas singulares/no recurrentes.
B7: 2027 | C7: Codiagro | D7: RESULTADO DEL EJERCICIO | E7: RESULTADO ANTES DE IMPUESTOS | F7: RESULTADO DE LA EXPLOTACION | G7: 5.- Otros ingresos de explotación | H7: (700) Ventas | I7: 700001624 - VENTA POR TRANSPORTE REP. AL CLIENTE DEFINITIVO | J7: - | K7: 29809.2 | L7: 21246.7 | M7: 19638.3 | N7: 8004.2 | O7: 38718.8 | P7: 33492 | Q7: 13212.8 | R7: 18509.6 | S7: 24148.9 | T7: 23411.3 | U7: 40650.7 | V7: 34380.8 | W7: 305223.3 | X7: Según presupuesto de transporte 2027: facturación y repercusión íntegra del transporte de exportación al cliente (+305.223,30 €). Efecto compensado al 100% con el gasto 624000002 (impacto 0 en EBITDA).
B8: 2027 | C8: Codiagro | D8: RESULTADO DEL EJERCICIO | E8: RESULTADO ANTES DE IMPUESTOS | F8: RESULTADO DE LA EXPLOTACION | G8: 1.- Importe neto de la cifra de negocios | H8: (700) Ventas | I8: 700000769 - INGRESOS POR RETRASOS DE COBRO Y ACTUALIZACION | J8: - | K8: 0 | L8: 0 | M8: 0 | N8: 0 | O8: 0 | P8: 0 | Q8: 0 | R8: 0 | S8: 0 | T8: 0 | U8: 0 | V8: 0 | W8: 0 | X8: Sin dotación presupuestada en 2027 por corresponder a partidas singulares/no recurrentes.
B9: 2027 | C9: Codiagro | D9: RESULTADO DEL EJERCICIO | E9: RESULTADO ANTES DE IMPUESTOS | F9: RESULTADO FINANCIERO | G9: 14.- Ingresos financieros | H9: (700) Ventas | I9: 700000769 - INGRESOS POR RETRASOS DE COBRO Y ACTUALIZACION | J9: - | K9: 0 | L9: 0 | M9: 0 | N9: 0 | O9: 0 | P9: 0 | Q9: 0 | R9: 0 | S9: 0 | T9: 0 | U9: 0 | V9: 0 | W9: 0 | X9: Sin dotación presupuestada en 2027 por corresponder a partidas singulares/no recurrentes.
B10: 2027 | C10: Codiagro | D10: RESULTADO DEL EJERCICIO | E10: RESULTADO ANTES DE IMPUESTOS | F10: RESULTADO DE LA EXPLOTACION | G10: 1.- Importe neto de la cifra de negocios | H10: (702) Ventas de productos semiterminados | I10: 702000000 - Ventas de productos semiterminados | J10: - | K10: 0 | L10: 0 | M10: 0 | N10: 0 | O10: 0 | P10: 0 | Q10: 0 | R10: 0 | S10: 0 | T10: 0 | U10: 0 | V10: 0 | W10: 0 | X10: Sin dotación presupuestada en 2027 por corresponder a partidas singulares/no recurrentes.
B11: 2027 | C11: Codiagro | D11: RESULTADO DEL EJERCICIO | E11: RESULTADO ANTES DE IMPUESTOS | F11: RESULTADO DE LA EXPLOTACION | G11: 1.- Importe neto de la cifra de negocios | H11: (703) Ventas por subproductos y residuos | I11: 703000000 - Ventas de subproductos y residuos | J11: - | K11: 0 | L11: 0 | M11: 0 | N11: 0 | O11: 0 | P11: 0 | Q11: 0 | R11: 0 | S11: 0 | T11: 0 | U11: 0 | V11: 0 | W11: 0 | X11: Sin dotación presupuestada en 2027 por corresponder a partidas singulares/no recurrentes.
B12: 2027 | C12: Codiagro | D12: RESULTADO DEL EJERCICIO | E12: RESULTADO ANTES DE IMPUESTOS | F12: RESULTADO DE LA EXPLOTACION | G12: 1.- Importe neto de la cifra de negocios | H12: (704) Venta de envases y embalajes | I12: 704000000 - Ventas de envases y embalajes | J12: - | K12: 0 | L12: 0 | M12: 0 | N12: 0 | O12: 0 | P12: 0 | Q12: 0 | R12: 0 | S12: 0 | T12: 0 | U12: 0 | V12: 0 | W12: 0 | X12: Sin dotación presupuestada en 2027 por corresponder a partidas singulares/no recurrentes.
B13: 2027 | C13: Codiagro | D13: RESULTADO DEL EJERCICIO | E13: RESULTADO ANTES DE IMPUESTOS | F13: RESULTADO DE LA EXPLOTACION | G13: 1.- Importe neto de la cifra de negocios | H13: (705) Prestación de servicios | I13: 705000000 - Prestaciones de servicios | J13: - | K13: 0 | L13: 0 | M13: 0 | N13: 0 | O13: 0 | P13: 0 | Q13: 0 | R13: 0 | S13: 0 | T13: 0 | U13: 0 | V13: 0 | W13: 0 | X13: Sin dotación presupuestada en 2027 por corresponder a partidas singulares/no recurrentes.
B14: 2027 | C14: Codiagro | D14: RESULTADO DEL EJERCICIO | E14: RESULTADO ANTES DE IMPUESTOS | F14: RESULTADO DE LA EXPLOTACION | G14: 1.- Importe neto de la cifra de negocios | H14: (705) Prestación de servicios | I14: 705000001 - INGRESO POR GESTIÓN DE ENVASES | J14: - | K14: 2221.91 | L14: 3599.09 | M14: 3452.4 | N14: 2779.49 | O14: 4563.41 | P14: 4525.44 | Q14: 2871.25 | R14: 1832.38 | S14: 1064.39 | T14: 1780.07 | U14: 2751.55 | V14: 3018.19 | W14: 34459.57 | X14: Ingreso por gestión de envases 2027 (+34.459,57 €), facturación recurrente complementaria.
B15: 2027 | C15: Codiagro | D15: RESULTADO DEL EJERCICIO | E15: RESULTADO ANTES DE IMPUESTOS | F15: RESULTADO DE LA EXPLOTACION | G15: 1.- Importe neto de la cifra de negocios | H15: (706) Dto. s/vtas p.p. | I15: 706000000 - Dtos. ventas por pronto pago mercaderías | J15: - | K15: 0 | L15: 0 | M15: 0 | N15: 0 | O15: 0 | P15: 0 | Q15: 0 | R15: 0 | S15: 0 | T15: 0 | U15: 0 | V15: 0 | W15: 0 | X15: Sin dotación presupuestada en 2027 por corresponder a partidas singulares/no recurrentes.
... B205: 2027 | C205: Codiagro | D205: RESULTADO DEL EJERCICIO | E205: RESULTADO ANTES DE IMPUESTOS | F205: RESULTADO FINANCIERO | G205: 14.- Ingresos financieros | H205: (769) Otros ingresos financieros | I205: 769000000 - Otros ingresos financieros | J205: - | K205: 0 | L205: 0 | M205: 0 | N205: 0 | O205: 0 | P205: 0 | Q205: 0 | R205: 0 | S205: 0 | T205: 0 | U205: 0 | V205: 0 | W205: 0 | X205: Otros ingresos financieros: sin estimación en 2027.

Sheet Ginger
A1: Cuenta | B1: Grupo Ext Item | C1: 46023 | D1: 46054 | E1: 46082 | F1: 46113 | G1: 46143 | H1: Comprobación | I1: Dif
A2: 700000000 - Ventas de mercaderías | B2: - | G2: 2029267 | H2: =VLOOKUP(A2,'PL Mensual 2027'!I:O,7,0) -> 2397051.3 | I2: =G2-H2 -> -367784.32
A3: 700000001 - VENTA MERCADERIAS POR ANTICIPO | B3: - | G3: -106250.17 | H3: =VLOOKUP(A3,'PL Mensual 2027'!I:O,7,0) -> 0 | I3: =G3-H3 -> -106250.17
A4: 700000624 - VENTA POR TRANSP. REP. AL CLIENTE | B4: - | G4: - | H4: =VLOOKUP(A4,'PL Mensual 2027'!I:O,7,0) -> 0
A5: 700000769 - INGRESOS POR RETRASOS DE COBRO Y ACTUALIZACION | B5: - | G5: - | H5: =VLOOKUP(A5,'PL Mensual 2027'!I:O,7,0) -> 0
A6: 700001624 - VENTA POR TRANSPORTE REP. AL CLIENTE DEFINITIVO | B6: - | G6: 25140.75 | H6: =VLOOKUP(A6,'PL Mensual 2027'!I:O,7,0) -> 38718.8 | I6: =G6-H6 -> -13578.05
A7: 702000000 - Ventas de productos semiterminados | B7: - | G7: 101865.8 | H7: =VLOOKUP(A7,'PL Mensual 2027'!I:O,7,0) -> 0 | I7: =G7-H7 -> 101865.8
A8: 703000000 - Ventas de subproductos y residuos | B8: - | G8: - | H8: =VLOOKUP(A8,'PL Mensual 2027'!I:O,7,0) -> 0
A9: 704000000 - Ventas de envases y embalajes | B9: - | G9: 80917.99 | H9: =VLOOKUP(A9,'PL Mensual 2027'!I:O,7,0) -> 0 | I9: =G9-H9 -> 80917.99
A10: 705000000 - Prestaciones de servicios | B10: - | G10: 111557.6 | H10: =VLOOKUP(A10,'PL Mensual 2027'!I:O,7,0) -> 0 | I10: =G10-H10 -> 111557.6
A11: - - | B11: Maquila | G11: -111557.6 | H11: =VLOOKUP(A11,'PL Mensual 2027'!I:O,7,0) -> #N/A | I11: =G11-H11 -> #N/A
A12: 705000001 - INGRESO POR GESTIÓN DE ENVASES | B12: - | G12: 2913.09 | H12: =VLOOKUP(A12,'PL Mensual 2027'!I:O,7,0) -> 4563.41 | I12: =G12-H12 -> -1650.32
A13: 706000000 - Dtos. ventas por pronto pago mercaderías | B13: - | G13: - | H13: =VLOOKUP(A13,'PL Mensual 2027'!I:O,7,0) -> 0
A14: 706000001 - DESCUENTO POR PRONTO PAGO DEFINITIVO | B14: - | G14: -38633.95 | H14: =VLOOKUP(A14,'PL Mensual 2027'!I:O,7,0) -> -63423.85 | I14: =G14-H14 -> 24789.9
A15: 709000000 - «Rappels» ventas de mercaderías | B15: - | G15: - | H15: =VLOOKUP(A15,'PL Mensual 2027'!I:O,7,0) -> 0
A16: 709000001 - PROVISION RAPPELS | B16: - | G16: - | H16: =VLOOKUP(A16,'PL Mensual 2027'!I:O,7,0) -> -52583.3
A17: 709001500 - RAPPEL BONIFICACIONES POR PMK DEFINITIVO | B17: - | G17: -1350 | H17: =VLOOKUP(A17,'PL Mensual 2027'!I:O,7,0) -> 0 | I17: =G17-H17 -> -1350
A18: 711000000 - Variación existencias de prod. semiterminados | B18: - | G18: 4436.02 | H18: =VLOOKUP(A18,'PL Mensual 2027'!I:O,7,0) -> 0 | I18: =G18-H18 -> 4436.02
A19: 712000000 - Variación existencias de prod. terminados | B19: - | G19: -34727.12 | H19: =VLOOKUP(A19,'PL Mensual 2027'!I:O,7,0) -> 0 | I19: =G19-H19 -> -34727.12
A20: 601000000 - Compras de materias primas | B20: - | G20: -417425.43 | H20: =VLOOKUP(A20,'PL Mensual 2027'!I:O,7,0) -> -607735.53 | I20: =G20-H20 -> 190310.1
A21: 601000001 - COMPRAS MAT. PRIMAS INTRACOMUNITARIAS | B21: - | G21: -108150 | H21: =VLOOKUP(A21,'PL Mensual 2027'!I:O,7,0) -> #N/A | I21: =G21-H21 -> #N/A
A22: 602000001 - COMPRA DE ENVASES Y EMBALAJES | B22: - | G22: -111111.14 | H22: =VLOOKUP(A22,'PL Mensual 2027'!I:O,7,0) -> -125465.45 | I22: =G22-H22 -> 14354.31
A23: 602000002 - COMPRA DE ETIQUETAS | B23: - | G23: -2784.91 | H23: =VLOOKUP(A23,'PL Mensual 2027'!I:O,7,0) -> -19591.74 | I23: =G23-H23 -> 16806.83
A24: 602000003 - COMPRA DE PALETS | B24: - | G24: -17326.4 | H24: =VLOOKUP(A24,'PL Mensual 2027'!I:O,7,0) -> -20375.4 | I24: =G24-H24 -> 3049
A25: 602000004 - COMPRA MATERIAL DE LIMPIEZA | B25: - | G25: - | H25: =VLOOKUP(A25,'PL Mensual 2027'!I:O,7,0) -> -131.92
A26: 602000005 - COMPRA MATERIAL DE OFICINA | B26: - | G26: - | H26: =VLOOKUP(A26,'PL Mensual 2027'!I:O,7,0) -> -204.02
A27: 602000006 - COMPRA TAPONES DE ENVASES | B27: - | G27: - | H27: =VLOOKUP(A27,'PL Mensual 2027'!I:O,7,0) -> -10501.17
A28: 602000011 - COMPRAS VARIAS PLANTA | B28: - | G28: - | H28: =VLOOKUP(A28,'PL Mensual 2027'!I:O,7,0) -> -964.39
A29: 602000012 - REPUESTOS INFORMATICOS | B29: - | G29: - | H29: =VLOOKUP(A29,'PL Mensual 2027'!I:O,7,0) -> -1559.63
A30: 602000013 - COMPRA TINTA INPRESORA ETIQUETAS | B30: - | G30: -480.84 | H30: =VLOOKUP(A30,'PL Mensual 2027'!I:O,7,0) -> -2600 | I30: =G30-H30 -> 2119.16
A31: 602000100 - ENVASES Y EMBALAJES A DEVOLVER | B31: - | G31: 1124 | H31: =VLOOKUP(A31,'PL Mensual 2027'!I:O,7,0) -> -183.2 | I31: =G31-H31 -> 1307.2
A32: 607000000 - Trabajos realizados por otras empresas | B32: - | G32: -32102.71 | H32: =VLOOKUP(A32,'PL Mensual 2027'!I:O,7,0) -> -7500 | I32: =G32-H32 -> -24602.71
A33: - - | B33: Maquila | G33: 28562.71 | H33: =VLOOKUP(A33,'PL Mensual 2027'!I:O,7,0) -> #N/A | I33: =G33-H33 -> #N/A
A34: 611000000 - Variación de existencias de materias primas | B34: - | G34: -43504.89 | H34: =VLOOKUP(A34,'PL Mensual 2027'!I:O,7,0) -> 0 | I34: =G34-H34 -> -43504.89
A35: 612000000 - Variación de existencias otros aprovisionamientos | B35: - | G35: -73565.42 | H35: =VLOOKUP(A35,'PL Mensual 2027'!I:O,7,0) -> 0 | I35: =G35-H35 -> -73565.42
A36: 640000000 - Sueldos y salarios | B36: - | G36: -104048.18 | H36: =VLOOKUP(A36,'PL Mensual 2027'!I:O,7,0) -> -127379.94 | I36: =G36-H36 -> 23331.76
A37: 641000000 - Indemnizaciones | B37: - | G37: - | H37: =VLOOKUP(A37,'PL Mensual 2027'!I:O,7,0) -> #N/A
A38: 642000000 - Seguridad Social a cargo empresa | B38: - | G38: -30856.34 | H38: =VLOOKUP(A38,'PL Mensual 2027'!I:O,7,0) -> -35002.8 | I38: =G38-H38 -> 4146.46
A39: 649000100 - GTOS. CURSOS PERSONAL | B39: - | G39: -88 | H39: =VLOOKUP(A39,'PL Mensual 2027'!I:O,7,0) -> 0 | I39: =G39-H39 -> -88
A40: 620000002 - COMPRAS LABORATORIO | B40: - | G40: -487.47 | H40: =VLOOKUP(A40,'PL Mensual 2027'!I:O,7,0) -> -322.5 | I40: =G40-H40 -> -164.97
A41: 620000003 - SUMINISTROS LABORATORIO | B41: - | G41: -1464.58 | H41: =VLOOKUP(A41,'PL Mensual 2027'!I:O,7,0) -> -812.59 | I41: =G41-H41 -> -651.99
A42: 620000004 - GTOS. ANALISIS LABORATORIOS | B42: - | G42: -1476.12 | H42: =VLOOKUP(A42,'PL Mensual 2027'!I:O,7,0) -> -1229.19 | I42: =G42-H42 -> -246.93
A43: 621000001 - ALQUILER OFICINA CARTAGENA | B43: - | G43: -192 | H43: =VLOOKUP(A43,'PL Mensual 2027'!I:O,7,0) -> -192 | I43: =G43-H43 -> 0
A44: 621000014 - ALQUILER MURANO | B44: - | G44: -15421.92 | H44: =VLOOKUP(A44,'PL Mensual 2027'!I:O,7,0) -> -1877.6 | I44: =G44-H44 -> -13544.32
A45: 621000024 - ALQUILER RENTING 2255KXN ANTONIO | B45: - | G45: - | H45: =VLOOKUP(A45,'PL Mensual 2027'!I:O,7,0) -> -361.46
A46: 621000026 - ALQUILER RENTING 9319LCL CURRO | B46: - | G46: - | H46: =VLOOKUP(A46,'PL Mensual 2027'!I:O,7,0) -> -369.97
A47: 621000031 - ALQUILER RENTING KONICA-MINOLTA Y KYOCERA | B47: - | G47: -338 | H47: =VLOOKUP(A47,'PL Mensual 2027'!I:O,7,0) -> -338 | I47: =G47-H47 -> 0
A48: 621000032 - ALQUILER RENTING 6665-LVK JOSE JUAN | B48: - | G48: -443.49 | H48: =VLOOKUP(A48,'PL Mensual 2027'!I:O,7,0) -> -470.16 | I48: =G48-H48 -> 26.67
A49: 621000033 - ALQUILER RENTING 2612-MBY ANTONIO | B49: - | G49: -399.42 | H49: =VLOOKUP(A49,'PL Mensual 2027'!I:O,7,0) -> -345.06 | I49: =G49-H49 -> -54.36
A50: 621000034 - ALQUILER RENTING 3108-LZM NIEVES | B50: - | G50: - | H50: =VLOOKUP(A50,'PL Mensual 2027'!I:O,7,0) -> -813.69
A51: 621000037 - CARRETILLA STILL ELEKTROSTAPLER 516213H00521 | B51: - | G51: -200 | H51: =VLOOKUP(A51,'PL Mensual 2027'!I:O,7,0) -> -228.57 | I51: =G51-H51 -> 28.57
A52: 621000038 - CARRETILLA STILL ELEKTROSTAPLER 516223J00123 | B52: - | G52: -200.22 | H52: =VLOOKUP(A52,'PL Mensual 2027'!I:O,7,0) -> -228.82 | I52: =G52-H52 -> 28.6
A53: 621000039 - ALQUILER RENTING 5043-MWW CURRO | B53: - | G53: - | H53: =VLOOKUP(A53,'PL Mensual 2027'!I:O,7,0) -> -482.36
A54: 621000040 - ALQUILER RENTING 8917-MZT JAVIER | B54: - | G54: -1172.14 | H54: =VLOOKUP(A54,'PL Mensual 2027'!I:O,7,0) -> -1557.86 | I54: =G54-H54 -> 385.72
A55: 621000041 - ALQUILER RENTING 8929-MZT RICARDO | B55: - | G55: -1015.21 | H55: =VLOOKUP(A55,'PL Mensual 2027'!I:O,7,0) -> -1338.15 | I55: =G55-H55 -> 322.94
A56: 621000042 - ALQUILER RENTING 4946-NFH GARCIA | B56: - | G56: -677.53 | H56: =VLOOKUP(A56,'PL Mensual 2027'!I:O,7,0) -> -645.34 | I56: =G56-H56 -> -32.19
A57: 621000044 - ALQUILER COMPRESOR DE TORNILLO 37KW KAESER BSD 75C | B57: - | G57: -1600 | H57: =VLOOKUP(A57,'PL Mensual 2027'!I:O,7,0) -> -1600 | I57: =G57-H57 -> 0
A58: 621000045 - ALQUILER RENTING 3421-NJT PERE | B58: - | G58: -1208.01 | H58: =VLOOKUP(A58,'PL Mensual 2027'!I:O,7,0) -> -1093.31 | I58: =G58-H58 -> -114.7
A59: 621000046 - ALQUILER CARRETILLAS | B59: - | G59: -665 | H59: =VLOOKUP(A59,'PL Mensual 2027'!I:O,7,0) -> -677.75 | I59: =G59-H59 -> 12.75
A60: - - | B60: Maquila | G60: 665 | H60: =VLOOKUP(A60,'PL Mensual 2027'!I:O,7,0) -> #N/A | I60: =G60-H60 -> #N/A
A61: 622000001 - REPAR. EQUIPOS INFORM. Y FOTOCOPIADORAS | B61: - | G61: - | H61: =VLOOKUP(A61,'PL Mensual 2027'!I:O,7,0) -> -748.65
A62: 622000004 - REP. Y CONSERV. CARRETILLA ELECTRICA | B62: - | G62: - | H62: =VLOOKUP(A62,'PL Mensual 2027'!I:O,7,0) -> -731.87
A63: 622000005 - REP. Y MANT. EQUIPOS SEGURIDAD | B63: - | G63: -183.66 | H63: =VLOOKUP(A63,'PL Mensual 2027'!I:O,7,0) -> -122.19 | I63: =G63-H63 -> -61.47
A64: 622000006 - REP. Y MANT. INSTALACIONES VARIAS | B64: - | G64: - | H64: =VLOOKUP(A64,'PL Mensual 2027'!I:O,7,0) -> -800
A65: 622000007 - REP. Y MANT. HYUNDAI 0377CJG | B65: - | G65: - | H65: =VLOOKUP(A65,'PL Mensual 2027'!I:O,7,0) -> -249.63
A66: 622000008 - REP. Y MANT. MAQUINA BARREDORA | B66: - | G66: - | H66: =VLOOKUP(A66,'PL Mensual 2027'!I:O,7,0) -> -515.01
A67: 622000012 - LIMPIEZA OFICINAS, LABORATORIO Y VESTUARIOS | B67: - | G67: - | H67: =VLOOKUP(A67,'PL Mensual 2027'!I:O,7,0) -> -935.11
A68: 622010200 - ALCAPLANT | B68: - | G68: -942.88 | H68: =VLOOKUP(A68,'PL Mensual 2027'!I:O,7,0) -> 0 | I68: =G68-H68 -> -942.88
A69: 622010201 - REPARACIONES ALCAPLANT | B69: - | G69: - | H69: =VLOOKUP(A69,'PL Mensual 2027'!I:O,7,0) -> 0
A70: 622010300 - SOLIDOS | B70: - | G70: - | H70: =VLOOKUP(A70,'PL Mensual 2027'!I:O,7,0) -> -367.5
A71: 622010400 - LIQUIDOS | B71: - | G71: -1092.45 | H71: =VLOOKUP(A71,'PL Mensual 2027'!I:O,7,0) -> 0 | I71: =G71-H71 -> -1092.45
A72: 622010500 - REPUESTOS MANT. VARIOS | B72: - | G72: -799.04 | H72: =VLOOKUP(A72,'PL Mensual 2027'!I:O,7,0) -> -262.5 | I72: =G72-H72 -> -536.54
A73: 622010501 - REP. MANT. FONTANERIA | B73: - | G73: - | H73: =VLOOKUP(A73,'PL Mensual 2027'!I:O,7,0) -> 0
A74: 623000001 - SERV. PROF. INDEPENDIENTES | B74: - | G74: -21698 | H74: =VLOOKUP(A74,'PL Mensual 2027'!I:O,7,0) -> -6000 | I74: =G74-H74 -> -15698
A75: 623000002 - SERVICIOS CONTABLES Y FINANCIEROS | B75: - | G75: -2891.19 | H75: =VLOOKUP(A75,'PL Mensual 2027'!I:O,7,0) -> -1400 | I75: =G75-H75 -> -1491.19
A76: 623000003 - SERV. NOTARIOS, REGISTROS, LEGAL | B76: - | G76: -2271.24 | H76: =VLOOKUP(A76,'PL Mensual 2027'!I:O,7,0) -> 0 | I76: =G76-H76 -> -2271.24
A77: 623000004 - GTOS. BCS. OKO | B77: - | G77: -1574.71 | H77: =VLOOKUP(A77,'PL Mensual 2027'!I:O,7,0) -> -1610 | I77: =G77-H77 -> 35.29
A78: 623000005 - SERVICIOS PREST. CAMARA COMERCIO | B78: - | G78: -429 | H78: =VLOOKUP(A78,'PL Mensual 2027'!I:O,7,0) -> -610.56 | I78: =G78-H78 -> 181.56
A79: 623100002 - GASTOS MAURICIO ALISTE | B79: - | G79: -4225.22 | H79: =VLOOKUP(A79,'PL Mensual 2027'!I:O,7,0) -> -4000 | I79: =G79-H79 -> -225.22
A80: 623100006 - GASTOS Y SERVICIOS AGRICOLA DEL JUCAR | B80: - | G80: -141.55 | H80: =VLOOKUP(A80,'PL Mensual 2027'!I:O,7,0) -> -500 | I80: =G80-H80 -> 358.45
A81: 623100007 - GASTOS Y SUELDO MEHMET CILOGLU | B81: - | G81: - | H81: =VLOOKUP(A81,'PL Mensual 2027'!I:O,7,0) -> -6000
A82: 623100008 - COMISIONES KAMAL KEHAL | B82: - | G82: -3398.55 | H82: =VLOOKUP(A82,'PL Mensual 2027'!I:O,7,0) -> -283.21 | I82: =G82-H82 -> -3115.34
A83: 623200001 - GASTOS MARCAS EN ESPAÑA | B83: - | G83: -377.56 | H83: =VLOOKUP(A83,'PL Mensual 2027'!I:O,7,0) -> 0 | I83: =G83-H83 -> -377.56
A84: 623200006 - MARCAS UNION EUROPEA | B84: - | G84: - | H84: =VLOOKUP(A84,'PL Mensual 2027'!I:O,7,0) -> 0
A85: 623200008 - GASTOS MARCAS EGIPTO | B85: - | G85: -53.14 | H85: =VLOOKUP(A85,'PL Mensual 2027'!I:O,7,0) -> 0 | I85: =G85-H85 -> -53.14
A86: 623200009 - GASTOS MARCAS MARRUECOS | B86: - | G86: - | H86: =VLOOKUP(A86,'PL Mensual 2027'!I:O,7,0) -> 0
A87: 623200010 - GASTOS MARCAS TURQUIA | B87: - | G87: - | H87: =VLOOKUP(A87,'PL Mensual 2027'!I:O,7,0) -> 0
A88: 623200011 - GASTOS MARCAS COLOMBIA | B88: - | G88: -53.12 | H88: =VLOOKUP(A88,'PL Mensual 2027'!I:O,7,0) -> 0 | I88: =G88-H88 -> -53.12
A89: 623200016 - GASTOS MARCAS ECUADOR | B89: - | G89: - | H89: =VLOOKUP(A89,'PL Mensual 2027'!I:O,7,0) -> 0
A90: 623200020 - GASTOS MARCAS TUNEZ | B90: - | G90: - | H90: =VLOOKUP(A90,'PL Mensual 2027'!I:O,7,0) -> 0
A91: 623200022 - GASTOS MARCAS BOLIVIA | B91: - | G91: - | H91: =VLOOKUP(A91,'PL Mensual 2027'!I:O,7,0) -> 0
A92: 623200023 - GASTOS MARCAS ARGELIA | B92: - | G92: -53.12 | H92: =VLOOKUP(A92,'PL Mensual 2027'!I:O,7,0) -> 0 | I92: =G92-H92 -> -53.12
A93: 623200024 - GASTOS MARCAS INTERNACIONALES | B93: - | G93: - | H93: =VLOOKUP(A93,'PL Mensual 2027'!I:O,7,0) -> 0
A94: 623200029 - GASTOS MARCAS GEORGIA | B94: - | G94: - | H94: =VLOOKUP(A94,'PL Mensual 2027'!I:O,7,0) -> 0
A95: 623200030 - GASTOS MARCAS AZERBAIYAN | B95: - | G95: -53.12 | H95: =VLOOKUP(A95,'PL Mensual 2027'!I:O,7,0) -> 0 | I95: =G95-H95 -> -53.12
A96: 624000001 - TRANSPORTES NACIONAL | B96: - | G96: -17966.84 | H96: =VLOOKUP(A96,'PL Mensual 2027'!I:O,7,0) -> -18645.63 | I96: =G96-H96 -> 678.79
A97: 624000002 - TRANSPORTE INTERNACIONAL | B97: - | G97: -951.38 | H97: =VLOOKUP(A97,'PL Mensual 2027'!I:O,7,0) -> -38718.8 | I97: =G97-H97 -> 37767.42
A98: 624000003 - TRANSPORTES CANARIAS | B98: - | G98: -6790.44 | H98: =VLOOKUP(A98,'PL Mensual 2027'!I:O,7,0) -> -14028.95 | I98: =G98-H98 -> 7238.51
A99: 624000004 - GTOS. FLETE REP. AL CLIENTE | B99: - | G99: - | H99: =VLOOKUP(A99,'PL Mensual 2027'!I:O,7,0) -> 0
A100: 624000005 - TTE. PAQUETERIA | B100: - | G100: - | H100: =VLOOKUP(A100,'PL Mensual 2027'!I:O,7,0) -> #N/A
...

Sheet Extraitems 2026
B1: EXTRAITEMS
B2: 2026
B4: 1 | C4: 2 | D4: 3 | E4: 4 | F4: 5 | G4: 6 | H4: 7 | I4: 8 | J4: 9 | K4: 10 | L4: 11 | M4: 12
B5: ENERO | C5: FEBRERO | D5: MARZO | E5: ABRIL | F5: MAYO | G5: JUNIO | H5: JULIO | I5: AGOSTO | J5: SEPTIEMBRE | K5: OCTUBRE | L5: NOVIEMBRE | M5: DICIEMBRE
B6: 26.2017 | C6: 40.07489 | D6: 29.27336 | E6: 0

Sheet Ext Items 2026
N1: =SUM(N3:N2300) -> -100248.99
A2: Fecha de contabilización | B2: Mes report | C2: Empresa | D2: Grupo EI | E2: Factura | F2: Nivel 1 | G2: Nivel 2 | H2: Nivel 3 | I2: Nivel 4 | J2: Nivel 5 | K2: Cuenta contable | L2: Acreedor/Proveedor | M2: Detalle | N2: Importe € | O2: Comentarios
A3: 46053 | B3: 1 | C3: Codiagro | D3: Personal | F3: RESULTADO DEL EJERCICIO | G3: RESULTADO ANTES DE IMPUESTOS | H3: RESULTADO DE LA EXPLOTACION | I3: 6.- Gastos de personal | J3: (640) Sueldos y salarios | K3: - | N3: 7934.82 | O3: NIEVES RUIZ CESPEDES
A4: 46053 | B4: 1 | C4: Codiagro | D4: Personal | F4: RESULTADO DEL EJERCICIO | G4: RESULTADO ANTES DE IMPUESTOS | H4: RESULTADO DE LA EXPLOTACION | I4: 6.- Gastos de personal | J4: (642) Seguridad social a cargo empresa | K4: - | N4: 1693.8 | O4: NIEVES RUIZ CESPEDES
A5: 46053 | B5: 1 | C5: Codiagro | D5: Personal | F5: RESULTADO DEL EJERCICIO | G5: RESULTADO ANTES DE IMPUESTOS | H5: RESULTADO DE LA EXPLOTACION | I5: 6.- Gastos de personal | J5: (640) Sueldos y salarios | K5: - | N5: 2166.76 | O5: FRANCISCO LAGOSTENA DE GUZMAN
A6: 46053 | B6: 1 | C6: Codiagro | D6: Personal | F6: RESULTADO DEL EJERCICIO | G6: RESULTADO ANTES DE IMPUESTOS | H6: RESULTADO DE LA EXPLOTACION | I6: 6.- Gastos de personal | J6: (642) Seguridad social a cargo empresa | K6: - | N6: 911.41 | O6: FRANCISCO LAGOSTENA DE GUZMAN
A7: 46053 | B7: 1 | C7: Codiagro | D7: Personal | F7: RESULTADO DEL EJERCICIO | G7: RESULTADO ANTES DE IMPUESTOS | H7: RESULTADO DE LA EXPLOTACION | I7: 6.- Gastos de personal | J7: (640) Sueldos y salarios | K7: - | N7: 4444.21 | O7: RAUL AMELA MELIA
A8: 46053 | B8: 1 | C8: Codiagro | D8: Personal | F8: RESULTADO DEL EJERCICIO | G8: RESULTADO ANTES DE IMPUESTOS | H8: RESULTADO DE LA EXPLOTACION | I8: 6.- Gastos de personal | J8: (642) Seguridad social a cargo empresa | K8: - | N8: 1720.91 | O8: RAUL AMELA MELIA
A9: 46053 | B9: 1 | C9: Codiagro | D9: Personal | F9: RESULTADO DEL EJERCICIO | G9: RESULTADO ANTES DE IMPUESTOS | H9: RESULTADO DE LA EXPLOTACION | I9: 6.- Gastos de personal | J9: (640) Sueldos y salarios | K9: - | N9: 5593.98 | O9: CARLOS BARREDA MAS
A10: 46053 | B10: 1 | C10: Codiagro | D10: Personal | F10: RESULTADO DEL EJERCICIO | G10: RESULTADO ANTES DE IMPUESTOS | H10: RESULTADO DE LA EXPLOTACION | I10: 6.- Gastos de personal | J10: (642) Seguridad social a cargo empresa | K10: - | N10: 1735.81 | O10: CARLOS BARREDA MAS
A11: 46081 | B11: 2 | C11: Codiagro | D11: Personal | F11: RESULTADO DEL EJERCICIO | G11: RESULTADO ANTES DE IMPUESTOS | H11: RESULTADO DE LA EXPLOTACION | I11: 6.- Gastos de personal | J11: (640) Sueldos y salarios | K11: - | N11: 9273.34 | O11: NIEVES RUIZ CESPEDES
A12: 46081 | B12: 2 | C12: Codiagro | D12: Personal | F12: RESULTADO DEL EJERCICIO | G12: RESULTADO ANTES DE IMPUESTOS | H12: RESULTADO DE LA EXPLOTACION | I12: 6.- Gastos de personal | J12: (642) Seguridad social a cargo empresa | K12: - | N12: 1774.57 | O12: NIEVES RUIZ CESPEDES
A13: 46081 | B13: 2 | C13: Codiagro | D13: Personal | F13: RESULTADO DEL EJERCICIO | G13: RESULTADO ANTES DE IMPUESTOS | H13: RESULTADO DE LA EXPLOTACION | I13: 6.- Gastos de personal | J13: (640) Sueldos y salarios | K13: - | N13: 3414.13 | O13: FRANCISCO LAGOSTENA DE GUZMAN
A14: 46081 | B14: 2 | C14: Codiagro | D14: Personal | F14: RESULTADO DEL EJERCICIO | G14: RESULTADO ANTES DE IMPUESTOS | H14: RESULTADO DE LA EXPLOTACION | I14: 6.- Gastos de personal | J14: (642) Seguridad social a cargo empresa | K14: - | N14: 838.96 | O14: FRANCISCO LAGOSTENA DE GUZMAN
... A59: 46265 | B59: 8 | C59: Codiagro | D59: INDIVIDUAL-Ext Item Codiagro-SAS | F59: RESULTADO DEL EJERCICIO | G59: RESULTADO ANTES DE IMPUESTOS | H59: RESULTADO DE LA EXPLOTACION | I59: 4.- Aprovisionamientos | J59: (602) Compras de otros aprovisionamientos | K59: 602000001 - COMPRA DE ENVASES Y EMBALAJES | N59: 59572.72 | O59: Packing repercutido

Sheet Ext Items Budget
L1: =SUBTOTAL(9,L3:L52) -> 174.42694
A2: Ext Item/Cap | B2: Empresa | C2: Normalización | D2: Nivel 1 | E2: Nivel 2 | F2: Nivel 3 | G2: Nivel 4 | H2: Nivel 5 | I2: Cuenta | J2: Mes | K2: Importe EUR | L2: Importe EUR ('000) | M2: Comentarios | N2: Grupo EI
B3: Codiagro | C3: Gastos de personal | D3: RESULTADO DEL EJERCICIO | E3: RESULTADO ANTES DE IMPUESTOS | F3: RESULTADO DE LA EXPLOTACION | G3: 6.- Gastos de personal | H3: (640) Sueldos y salarios | J3: 1 | K3: 9918.52 | L3: =+K3/1000 -> 9.91852 | M3: NIEVES RUIZ CESPEDES | N3: Personal
B4: Codiagro | C4: Gastos de personal | D4: RESULTADO DEL EJERCICIO | E4: RESULTADO ANTES DE IMPUESTOS | F4: RESULTADO DE LA EXPLOTACION | G4: 6.- Gastos de personal | H4: (642) Seguridad social a cargo empresa | J4: 1 | K4: 6612.34 | L4: =+K4/1000 -> 6.61234 | M4: NIEVES RUIZ CESPEDES | N4: Personal
B5: Codiagro | C5: Gastos de personal | D5: RESULTADO DEL EJERCICIO | E5: RESULTADO ANTES DE IMPUESTOS | F5: RESULTADO DE LA EXPLOTACION | G5: 6.- Gastos de personal | H5: (640) Sueldos y salarios | J5: 2 | K5: 1295.91 | L5: =+K5/1000 -> 1.29591 | M5: NIEVES RUIZ CESPEDES | N5: Personal
B6: Codiagro | C6: Gastos de personal | D6: RESULTADO DEL EJERCICIO | E6: RESULTADO ANTES DE IMPUESTOS | F6: RESULTADO DE LA EXPLOTACION | G6: 6.- Gastos de personal | H6: (642) Seguridad social a cargo empresa | J6: 2 | K6: 863.94 | L6: =+K6/1000 -> 0.86394 | M6: NIEVES RUIZ CESPEDES | N6: Personal
B7: Codiagro | C7: Gastos de personal | D7: RESULTADO DEL EJERCICIO | E7: RESULTADO ANTES DE IMPUESTOS | F7: RESULTADO DE LA EXPLOTACION | G7: 6.- Gastos de personal | H7: (640) Sueldos y salarios | J7: 1 | K7: 1708.45 | L7: =+K7/1000 -> 1.70845 | M7: FRANCISCO LAGOSTENA DE GUZMAN | N7: Personal
B8: Codiagro | C8: Gastos de personal | D8: RESULTADO DEL EJERCICIO | E8: RESULTADO ANTES DE IMPUESTOS | F8: RESULTADO DE LA EXPLOTACION | G8: 6.- Gastos de personal | H8: (642) Seguridad social a cargo empresa | J8: 1 | K8: 659.51 | L8: =+K8/1000 -> 0.65951 | M8: FRANCISCO LAGOSTENA DE GUZMAN | N8: Personal
B9: Codiagro | C9: Gastos de personal | D9: RESULTADO DEL EJERCICIO | E9: RESULTADO ANTES DE IMPUESTOS | F9: RESULTADO DE LA EXPLOTACION | G9: 6.- Gastos de personal | H9: (640) Sueldos y salarios | J9: 2 | K9: 1708.45 | L9: =+K9/1000 -> 1.70845 | M9: FRANCISCO LAGOSTENA DE GUZMAN | N9: Personal
B10: Codiagro | C10: Gastos de personal | D10: RESULTADO DEL EJERCICIO | E10: RESULTADO ANTES DE IMPUESTOS | F10: RESULTADO DE LA EXPLOTACION | G10: 6.- Gastos de personal | H10: (642) Seguridad social a cargo empresa | J10: 2 | K10: 659.51 | L10: =+K10/1000 -> 0.65951 | M10: FRANCISCO LAGOSTENA DE GUZMAN | N10: Personal
B11: Codiagro | C11: Gastos de personal | D11: RESULTADO DEL EJERCICIO | E11: RESULTADO ANTES DE IMPUESTOS | F11: RESULTADO DE LA EXPLOTACION | G11: 6.- Gastos de personal | H11: (640) Sueldos y salarios | J11: 3 | K11: 1708.45 | L11: =+K11/1000 -> 1.70845 | M11: FRANCISCO LAGOSTENA DE GUZMAN | N11: Personal
B12: Codiagro | C12: Gastos de personal | D12: RESULTADO DEL EJERCICIO | E12: RESULTADO ANTES DE IMPUESTOS | F12: RESULTADO DE LA EXPLOTACION | G12: 6.- Gastos de personal | H12: (642) Seguridad social a cargo empresa | J12: 3 | K12: 659.51 | L12: =+K12/1000 -> 0.65951 | M12: FRANCISCO LAGOSTENA DE GUZMAN | N12: Personal
B13: Codiagro | C13: Gastos de personal | D13: RESULTADO DEL EJERCICIO | E13: RESULTADO ANTES DE IMPUESTOS | F13: RESULTADO DE LA EXPLOTACION | G13: 6.- Gastos de personal | H13: (641) Indemnizaciones | J13: 3 | K13: 19064.32 | L13: =+K13/1000 -> 19.06432 | M13: FRANCISCO LAGOSTENA DE GUZMAN | N13: Indemnizaciones
B14: Codiagro | C14: Gastos de personal | D14: RESULTADO DEL EJERCICIO | E14: RESULTADO ANTES DE IMPUESTOS | F14: RESULTADO DE LA EXPLOTACION | G14: 6.- Gastos de personal | H14: (640) Sueldos y salarios | J14: 1 | K14: 5700.18 | L14: =+K14/1000 -> 5.70018 | M14: RAUL AMELA MELIA | N14: Personal
... B45: Codiagro | C45: Gastos de personal | D45: RESULTADO DEL EJERCICIO | E45: RESULTADO ANTES DE IMPUESTOS | F45: RESULTADO DE LA EXPLOTACION | G45: 6.- Gastos de personal | H45: (642) Seguridad social a cargo empresa | J45: 8 | K45: 950.61913 | L45: =+K45/1000 -> 0.95061913 | M45: CARLOS BARREDA MAS | N45: Personal

Sheet Ext Items 2025
P1: Mes report | Q1: (Todas)
B2: Fecha de contabilización | C2: Mes report | D2: Empresa | E2: Concepto | F2: Factura | G2: Cuenta contable | H2: Normalización | I2: Nivel 4 | J2: Acreedor/Proveedor | K2: Detalle | L2: Importe | M2: Importe ('000)
B3: 45667 | C3: =MONTH(B3) -> 1 | D3: CODIAGRO | E3: Indemnizaciones | G3: 641000007 | H3: Gastos de personal | K3: INDEMNIZACION MIGUEL BELLES | L3: 112732.33 | M3: 112.73233 | P3: Etiquetas de fila | Q3: Suma de Importe ('000)
B4: 45734 | C4: =MONTH(B4) -> 3 | D4: CODIAGRO | E4: Costes Transacción | F4: 440FVN25000044 | G4: 623000001 | H4: Otros Gastos Operativos | J4: AUREN CORPORATE | K4: Asesoramiento | L4: 14111.19 | M4: 14.11119 | P4: Costes Transacción | Q4: 161.05205
B5: 45744 | C5: =MONTH(B5) -> 3 | D5: CODIAGRO | E5: Costes Transacción | F5: 440FVN25000048 | G5: 623000001 | H5: Otros Gastos Operativos | J5: AUREN CORPORATE | K5: Asesoramiento | L5: 4000 | M5: 4 | P5: Gastos periodos anteriores | Q5: 134.19399
B6: 45776 | C6: =MONTH(B6) -> 4 | D6: CODIAGRO | E6: Costes Transacción | F6: 440FVN25000070 | G6: 623000001 | H6: Otros Gastos Operativos | J6: AUREN CORPORATE | K6: Asesoramiento | L6: 4297.23 | M6: 4.29723 | P6: Gastos Representación | Q6: 48.99744
B7: 45805 | C7: =MONTH(B7) -> 5 | D7: CODIAGRO | E7: Costes Transacción | F7: 440FVN25000094 | G7: 623000001 | H7: Otros Gastos Operativos | J7: AUREN CORPORATE | K7: Asesoramiento | L7: 4000 | M7: 4 | P7: Indemnizaciones | Q7: 112.73233
B8: 45838 | C8: =MONTH(B8) -> 6 | D8: CODIAGRO | E8: Costes Transacción | F8: 440FVN25000118 | G8: 623000001 | H8: Otros Gastos Operativos | J8: AUREN CORPORATE | K8: Asesoramiento | L8: 4000 | M8: 4 | P8: TICS | Q8: 1.8
B9: 45866 | C9: =MONTH(B9) -> 7 | D9: CODIAGRO | E9: Costes Transacción | F9: 440FVN25000150 | G9: 623000001 | H9: Otros Gastos Operativos | J9: AUREN CORPORATE | K9: Asesoramiento | L9: 4589.25 | M9: 4.58925 | P9: Gastos de personal | Q9: 310.01329
B10: 45901 | C10: =MONTH(B10) -> 9 | D10: CODIAGRO | E10: Costes Transacción | F10: 440FVN25000171 | G10: 623000001 | H10: Otros Gastos Operativos | J10: AUREN CORPORATE | K10: Asesoramiento | L10: 4000 | M10: 4 | P10: Rappel Dotra (cliente Egipto) 2024 | Q10: 139.50071
B11: 45929 | C11: =MONTH(B11) -> 9 | D11: CODIAGRO | E11: Costes Transacción | F11: 440FVN25000191 | G11: 623000001 | H11: Otros Gastos Operativos | J11: AUREN CORPORATE | K11: Asesoramiento | L11: 4054.38 | M11: 4.05438 | P11: Reparaciones extraordinarias | Q11: 50.39565
B12: 45875 | C12: =MONTH(B12) -> 8 | D12: CODIAGRO | E12: Gastos Representación | F12: 52/000095 | G12: 627000005 | H12: Otros Gastos Operativos | J12: VILLARREAL CLUB DE FUTBOL | K12: PALCO TEMPORADA | L12: 40493.75 | M12: 40.49375 | P12: Total general | Q12: 958.68546
B13: 45875 | C13: =MONTH(B13) -> 8 | D13: CODIAGRO | E13: Gastos Representación | F13: 52/000095 | G13: 634100000 | H13: Otros Gastos Operativos | J13: VILLARREAL CLUB DE FUTBOL | K13: IVA NO DEDUCIBLE del Palco | L13: 8503.69 | M13: 8.50369
B14: 45962 | C14: =MONTH(B14) -> 11 | D14: CODIAGRO | E14: Costes Transacción | F14: 3522900376 | G14: 623000001 | H14: Otros Gastos Operativos | J14: KPMG | K14: VENDOR DIU DILIGENCE | L14: 118000 | M14: 118
B15: 45993 | C15: =MONTH(B15) -> 12 | D15: CODIAGRO | E15: TICS | G15: 623000001 | H15: Otros Gastos Operativos | J15: INTRALINKS | K15: NUBE PARA LA DOCUMENTACION | L15: 1800 | M15: 1.8
B16: 45748 | C16: =MONTH(B16) -> 4 | D16: CODIAGRO | E16: Reparaciones extraordinarias | F16: 153/25 | G16: 622010201 | H16: Otros Gastos Operativos | J16: MAQUISEL SERVICIOS QUIMICOS, S.L.L. | K16: REPARACION ALCAPLANT CADA 6/7 AÑOS | L16: 11502.5 | M16: 11.5025
B17: 45748 | C17: =MONTH(B17) -> 4 | D17: CODIAGRO | E17: Reparaciones extraordinarias | F17: 154/25 | G17: 622010201 | H17: Otros Gastos Operativos | J17: MAQUISEL SERVICIOS QUIMICOS, S.L.L. | K17: REPARACION ALCAPLANT CADA 6/7 AÑOS | L17: 11049.5 | M17: 11.0495
B18: 45992 | C18: =MONTH(B18) -> 12 | D18: CODIAGRO | E18: Reparaciones extraordinarias | F18: 278/25 | G18: 622010201 | H18: Otros Gastos Operativos | J18: MAQUISEL SERVICIOS QUIMICOS, S.L.L. | K18: REPARACION ALCAPLANT CADA 6/7 AÑOS | L18: 12968 | M18: 12.968
B19: 45992 | C19: =MONTH(B19) -> 12 | D19: CODIAGRO | E19: Reparaciones extraordinarias | F19: 560/25 | G19: 622000006 | H19: Otros Gastos Operativos | J19: MAQUISEL SERVICIOS QUIMICOS, S.L.L. | L19: 4897 | M19: 4.897
B20: 45713 | C20: =MONTH(B20) -> 2 | D20: CODIAGRO | E20: Reparaciones extraordinarias | F20: 25000332 | G20: 622010200 | H20: Otros Gastos Operativos | J20: OLIVER & BATLLE, S.A. | K20: REPARACION ALCAPLANT CADA 6/7 AÑOS | L20: 9978.65 | M20: 9.97865
B21: 45721 | C21: =MONTH(B21) -> 3 | D21: CODIAGRO | E21: Gastos periodos anteriores | G21: 627000008 | H21: Otros Gastos Operativos | K21: Marketing 2024 Marcoser | L21: 8479.84 | M21: 8.47984
B22: 45677 | C22: =MONTH(B22) -> 1 | D22: CODIAGRO | E22: Gastos periodos anteriores | G22: 623100006 | H22: Otros Gastos Operativos | K22: Comisiones 2024 Alfonso (agricola Juncar) | L22: 21135 | M22: 21.135
B23: 45660 | C23: =MONTH(B23) -> 1 | D23: CODIAGRO | E23: Gastos periodos anteriores | G23: 623100007 | H23: Otros Gastos Operativos | K23: Comisiones 2024 Mehmet | L23: 18863.51 | M23: 18.86351
B24: 45692 | C24: =MONTH(B24) -> 2 | D24: CODIAGRO | E24: Gastos periodos anteriores | G24: 623100007 | H24: Otros Gastos Operativos | K24: Comisiones 2024 Mehmet | L24: 3423.3 | M24: 3.4233
B25: 45838 | C25: =MONTH(B25) -> 6 | D25: CODIAGRO | E25: Gastos de personal | G25: 640000000 | H25: Gastos de personal | K25: Importe Producción-Planta 2024 | L25: 26136.49 | M25: 26.13649
B26: 45930 | C26: =MONTH(B26) -> 9 | D26: CODIAGRO | E26: Gastos de personal | G26: 647000000 | H26: Gastos de personal | K26: Retribución consejo 2024 | L26: 65849.57 | M26: 65.84957
B27: 45827 | C27: =MONTH(B27) -> 6 | D27: CODIAGRO | E27: Gastos periodos anteriores | G27: 623000001 | H27: Otros Gastos Operativos | K27: Comisiones Eurofertil 2024 | L27: 10969.96 | M27: 10.96996
B28: 45740 | C28: =MONTH(B28) -> 3 | D28: CODIAGRO | E28: Gastos periodos anteriores | G28: 623000001 | H28: Otros Gastos Operativos | K28: Comisiones Eurofertil 2024,2023,2022 | L28: 50283.36 | M28: 50.28336
B29: 45775 | C29: =MONTH(B29) -> 4 | D29: CODIAGRO | E29: Rappel Dotra (cliente Egipto) 2024 | G29: 709000000 | H29: Ventas | K29: Rappel Dotra (cliente Egipto) 2024 | L29: 102533.02 | M29: 102.53302
B30: 45775 | C30: =MONTH(B30) -> 4 | D30: CODIAGRO | E30: Rappel Dotra (cliente Egipto) 2024 | G30: 709000000 | H30: Ventas | K30: Rappel Dotra (cliente Egipto) 2024 | L30: 36967.69 | M30: 36.96769
B31: 45716 | C31: =MONTH(B31) -> 2 | D31: CODIAGRO | E31: Gastos de personal | G31: 640000000 | H31: Gastos de personal | K31: Bonus 2024 | L31: 135000 | M31: 135
B32: 45665 | C32: =MONTH(B32) -> 1 | D32: CODIAGRO | E32: Gastos periodos anteriores | G32: 627000010 | H32: Otros Gastos Operativos | K32: Promoción 2023 Tecnicos Campo Egido | L32: 9175.46 | M32: 9.17546
... B35: 45838 | C35: =MONTH(B35) -> 6 | D35: CODIAGRO | E35: Gastos de personal | G35: 640000000 | H35: Gastos de personal | K35: Comisiones Comercial en nomina de periodo de junio a diciembre 2024 - Pendiente el asiento | L35: 41513.615 | M35: 41.513615

Sheet Cuenta Ok
A1: AGOSTO
A2: Cuenta | B2: SALDO
A3: 700000000 - Ventas de mercaderías | B3: 802410.56
A4: 700000001 - VENTA MERCADERIAS POR ANTICIPO | B4: 0
A5: 700000624 - VENTA POR TRANSP. REP. AL CLIENTE | B5: -
A6: 700001624 - VENTA POR TRANSPORTE REP. AL CLIENTE DEFINITIVO | B6: 11429
A7: 700000769 - INGRESOS POR RETRASOS DE COBRO Y ACTUALIZACION | B7: -
A8: 700000769 - INGRESOS POR RETRASOS DE COBRO Y ACTUALIZACION | B8: -
A9: 702000000 - Ventas de productos semiterminados | B9: 141074.4
A10: 703000000 - Ventas de subproductos y residuos | B10: -
A11: 704000000 - Ventas de envases y embalajes | B11: 59572.72
A12: 705000000 - Prestaciones de servicios | B12: 101520
A13: 705000001 - INGRESO POR GESTIÓN DE ENVASES | B13: 1694.59
A14: 706000000 - Dtos. ventas por pronto pago mercaderías | B14: -
A15: 709000000 - «Rappels» ventas de mercaderías | B15: -
A16: 709000001 - PROVISION RAPPELS | B16: -16000
A17: 771000000 - Beneficios del inmovilizado material | B17: -
A18: 678000000 - Gastos excepcionales | B18: -0.02
A19: 778000000 - Ingresos excepcionales | B19: 0.01
A20: 711000000 - Variación existencias de prod. semiterminados | B20: 27557.62
A21: 712000000 - Variación existencias de prod. terminados | B21: -20822.98
A22: 601000000 - Compras de materias primas | B22: -265516.84
A23: 601000001 - COMPRAS MAT. PRIMAS INTRACOMUNITARIAS | B23: -64800
A24: 602000001 - COMPRA DE ENVASES Y EMBALAJES | B24: -68178.76
A25: 602000000 - Compras de otros aprovisionamientos | B25: -
A26: 602000002 - COMPRA DE ETIQUETAS | B26: -2886.68
A27: 602000003 - COMPRA DE PALETS | B27: -4331.6
A28: 602000004 - COMPRA MATERIAL DE LIMPIEZA | B28: -
A29: 602000005 - COMPRA MATERIAL DE OFICINA | B29: -
A30: 602000006 - COMPRA TAPONES DE ENVASES | B30: -1108.8
A31: 602000007 - COMPRAS LABORATORIO | B31: 0
A32: 602000008 - RESPUESTOS PLANTA | B32: 0
A33: 602000010 - COMPRA RIBBON | B33: 0
A34: 602000011 - COMPRAS VARIAS PLANTA | B34: -371.23
A35: 602000012 - REPUESTOS INFORMATICOS | B35: -
A36: 602000013 - COMPRA TINTA INPRESORA ETIQUETAS | B36: -2557.66
A37: 602000100 - ENVASES Y EMBALAJES A DEVOLVER | B37: -
A38: 607000000 - Trabajos realizados por otras empresas | B38: -25856.5
A39: 611000000 - Variación de existencias de materias primas | B39: -59037.03
A40: 612000000 - Variación de existencias otros aprovisionamientos | B40: -4582.08
A41: 759000000 - Ingresos por servicios diversos | B41: 0
A42: 640000000 - Sueldos y salarios | B42: -128060.74
A43: 640000200 - GASTO POR E. TRAB. TEMPORAL | B43: 0
A44: 640000300 - PROVISION PAGAS EXTRAS | B44: 0
A45: 641000000 - Indemnizaciones | B45: -
A46: 641000007 - INDEMNIZACION MIGUEL BELLES | B46: 0
A47: 642000000 - Seguridad Social a cargo empresa | B47: -24572.05
A48: 649000000 - Otros gastos sociales | B48: 0
A49: 649000001 - GASTOS COMERCIALES NIEVES RUIZ | B49: 0
A50: 649000002 - GASTOS EMPR. ANTONIO ANDREU | B50: 0
A51: 649000004 - GASTOS COMERCIALES RICARDO PEREZ | B51: 0
A52: 649000007 - GASTOS COMERCIALES J.PAREDES | B52: 0
A53: 649000009 - GASTOS COMERCIALES J.A. GARCIA | B53: 0
A54: 649000010 - GASTOS EMP. CURRO | B54: 0
A55: 649000012 - GASTOS COMERCIALES IRENE GARCIA | B55: 0
A56: 649000100 - GTOS. CURSOS PERSONAL | B56: -
A57: 649000101 - GTOS. SEG. Y RIESGOS PERSONAL | B57: 0
A58: 649000102 - GASTOS ROPA UNIFORMES TRABAJADORES | B58: 0
A59: 649000103 - GASTOS COMBUSTIBLE TRAB. | B59: 0
A60: 649100001 - GTOS. COMIDAS TRAB. | B60: 0
A61: 649100002 - GASTOS TRAB. EMPRESA VARIOS | B61: 0
A62: 620000002 - COMPRAS LABORATORIO | B62: -
A63: 620000003 - SUMINISTROS LABORATORIO | B63: -399.98
A64: 620000004 - GTOS. ANALISIS LABORATORIOS | B64: -911.52
A65: 621000001 - ALQUILER OFICINA CARTAGENA | B65: -192
A66: 621000014 - ALQUILER MURANO | B66: -
A67: 621000023 - RENTING TRANSPALETA ELECTRICA DE PIE | B67: 0
A68: 621000024 - ALQUILER RENTING 2255KXN ANTONIO | B68: -
A69: 621000025 - ALQUILER RENTING 9128 LBT NIEVES | B69: 0
A70: 621000026 - ALQUILER RENTING 9319LCL CURRO | B70: -
A71: 621000030 - ALQUILER RENTING 1075-LSC GARCIA | B71: 0
A72: 621000031 - ALQUILER RENTING KONICA-MINOLTA Y KYOCERA | B72: -338
A73: 621000032 - ALQUILER RENTING 6665-LVK JOSE JUAN | B73: -
A74: 621000033 - ALQUILER RENTING 2612-MBY ANTONIO | B74: -399.42
A75: 621000034 - ALQUILER RENTING 3108-LZM NIEVES | B75: -1139.16
A76: 621000035 - ALQUILER RENTING 2142-MCS RICARDO | B76: 0
A77: 621000036 - ALQUILER RENTING 3277-MDX JAVIER | B77: 0
A78: 621000037 - CARRETILLA STILL ELEKTROSTAPLER 516213H00521 | B78: -400
A79: 621000038 - CARRETILLA STILL ELEKTROSTAPLER 516223J00123 | B79: -400.44
A80: 621000039 - ALQUILER RENTING 5043-MWW CURRO | B80: -
A81: 621000040 - ALQUILER RENTING 8917-MZT JAVIER | B81: -
A82: 621000041 - ALQUILER RENTING 8929-MZT RICARDO | B82: -
A83: 621000042 - ALQUILER RENTING 4946-NFH GARCIA | B83: -677.53
A84: 621000044 - ALQUILER COMPRESOR DE TORNILLO 37KW KAESER BSD 75C | B84: -1600
A85: 621000045 - ALQUILER RENTING 3421-NJT PERE | B85: -1208.01
A86: 621000046 - ALQUILER CARRETILLAS | B86: -1407
A87: 622000001 - REPAR. EQUIPOS INFORM. Y FOTOCOPIADORAS | B87: -
A88: 622000004 - REP. Y CONSERV. CARRETILLA ELECTRICA | B88: -115.48
A89: 622000005 - REP. Y MANT. EQUIPOS SEGURIDAD | B89: -
A90: 622000006 - REP. Y MANT. INSTALACIONES VARIAS | B90: -
A91: 622000007 - REP. Y MANT. HYUNDAI 0377CJG | B91: -
A92: 622000008 - REP. Y MANT. MAQUINA BARREDORA | B92: -
A93: 622000009 - REP. Y MANT. FURGONETA 2589CRJ | B93: 0
A94: 622000012 - LIMPIEZA OFICINAS, LABORATORIO Y VESTUARIOS | B94: -977.98
A95: 622010000 MANTENIMIENTO | B95: -
A96: 622010001 - MANTENIMIENTO REPUESTO COMPRA AMAZON | B96: 0
A97: 622010200 - ALCAPLANT | B97: -1983.69
A98: 622010201 - REPARACIONES ALCAPLANT | B98: -5848.16
A99: 622010300 - SOLIDOS | B99: -11965.55
A100: 622010400 - LIQUIDOS | B100: -288.39
...
