Workbook

Sheet Resumen general
A2: Presupuesto de transporte · Codiagro
A3: Cuatrimestre septiembre–diciembre 2026 y ejercicio completo 2027 · nacional, Canarias y exportación.
A5: Período | B5: Resto nacional (€) | C5: Canarias (€) | D5: Exportación (€) | E5: Total (€)
A6: 2026 · sep-dic | B6: ='Nacional 2026'!D11 -> 31199.837 | C6: ='Nacional 2026'!G11 -> 22275.215 | D6: ='Export · costes'!C11 -> 97236 | E6: =SUM(B6:D6) -> 150711.05
A7: 2027 · ene-dic | B7: ='Nacional 2027'!D19 -> 166472.15 | C7: ='Nacional 2027'!G19 -> 79198.291 | D7: ='Export · costes'!C27 -> 305223.3 | E7: =SUM(B7:D7) -> 550893.74
A10: 2026 · septiembre a diciembre
A11: Mes | B11: Resto nacional (€) | C11: Canarias (€) | D11: Exportación (€) | E11: Total (€)
A12: Sep | B12: ='Nacional 2026'!D7 -> 6434.5324 | C12: ='Nacional 2026'!G7 -> 2450.109 | D12: ='Export · costes'!C7 -> 16253 | E12: =SUM(B12:D12) -> 25137.641
A13: Oct | B13: ='Nacional 2026'!D8 -> 10499.025 | C13: ='Nacional 2026'!G8 -> 7990.591 | D13: ='Export · costes'!C8 -> 21379 | E13: =SUM(B13:D13) -> 39868.616
A14: Nov | B14: ='Nacional 2026'!D9 -> 10212.345 | C14: ='Nacional 2026'!G9 -> 11300.379 | D14: ='Export · costes'!C9 -> 32454 | E14: =SUM(B14:D14) -> 53966.724
A15: Dic | B15: ='Nacional 2026'!D10 -> 4053.9348 | C15: ='Nacional 2026'!G10 -> 534.13573 | D15: ='Export · costes'!C10 -> 27150 | E15: =SUM(B15:D15) -> 31738.071
A16: TOTAL 2026 | B16: =SUM(B12:B15) -> 31199.837 | C16: =SUM(C12:C15) -> 22275.215 | D16: =SUM(D12:D15) -> 97236 | E16: =SUM(E12:E15) -> 150711.05
A19: 2027 · enero a diciembre
A20: Mes | B20: Resto nacional (€) | C20: Canarias (€) | D20: Exportación (€) | E20: Total (€)
A21: Ene | B21: ='Nacional 2027'!D7 -> 7016.8542 | C21: ='Nacional 2027'!G7 -> 6088.1813 | D21: ='Export · costes'!C15 -> 29809.2 | E21: =SUM(B21:D21) -> 42914.235
A22: Feb | B22: ='Nacional 2027'!D8 -> 13619.902 | C22: ='Nacional 2027'!G8 -> 5367.2581 | D22: ='Export · costes'!C16 -> 21246.7 | E22: =SUM(B22:D22) -> 40233.86
A23: Mar | B23: ='Nacional 2027'!D9 -> 18607.541 | C23: ='Nacional 2027'!G9 -> 7224.7247 | D23: ='Export · costes'!C17 -> 19638.3 | E23: =SUM(B23:D23) -> 45470.566
A24: Abr | B24: ='Nacional 2027'!D10 -> 22055.439 | C24: ='Nacional 2027'!G10 -> 3712.0421 | D24: ='Export · costes'!C18 -> 8004.2 | E24: =SUM(B24:D24) -> 33771.681
A25: May | B25: ='Nacional 2027'!D11 -> 18645.631 | C25: ='Nacional 2027'!G11 -> 14028.954 | D25: ='Export · costes'!C19 -> 38718.8 | E25: =SUM(B25:D25) -> 71393.385
A26: Jun | B26: ='Nacional 2027'!D12 -> 20396.407 | C26: ='Nacional 2027'!G12 -> 2584.44 | D26: ='Export · costes'!C20 -> 33492 | E26: =SUM(B26:D26) -> 56472.847
A27: Jul | B27: ='Nacional 2027'!D13 -> 14747.912 | C27: ='Nacional 2027'!G13 -> 4588.2983 | D27: ='Export · costes'!C21 -> 13212.8 | E27: =SUM(B27:D27) -> 32549.01
A28: Ago | B28: ='Nacional 2027'!D14 -> 13338.449 | C28: ='Nacional 2027'!G14 -> 8667.6855 | D28: ='Export · costes'!C22 -> 18509.6 | E28: =SUM(B28:D28) -> 40515.734
A29: Sep | B29: ='Nacional 2027'!D15 -> 7825.8588 | C29: ='Nacional 2027'!G15 -> 2950.8535 | D29: ='Export · costes'!C23 -> 24148.9 | E29: =SUM(B29:D29) -> 34925.612
A30: Oct | B30: ='Nacional 2027'!D16 -> 12700.116 | C30: ='Nacional 2027'!G16 -> 9635.0411 | D30: ='Export · costes'!C24 -> 23411.3 | E30: =SUM(B30:D30) -> 45746.457
A31: Nov | B31: ='Nacional 2027'!D17 -> 12528.192 | C31: ='Nacional 2027'!G17 -> 13725.162 | D31: ='Export · costes'!C25 -> 40650.7 | E31: =SUM(B31:D31) -> 66904.053
A32: Dic | B32: ='Nacional 2027'!D18 -> 4989.8491 | C32: ='Nacional 2027'!G18 -> 625.65144 | D32: ='Export · costes'!C26 -> 34380.8 | E32: =SUM(B32:D32) -> 39996.301
A33: TOTAL 2027 | B33: =SUM(B21:B32) -> 166472.15 | C33: =SUM(C21:C32) -> 79198.291 | D33: =SUM(D21:D32) -> 305223.3 | E33: =SUM(E21:E32) -> 550893.74
A36: Base del resumen: 2026 incluye septiembre estimado en exportación; 2027 nacional/Canarias aplica +10 % y exportación usa el importe del archivo adjunto.
A37: La oferta de Canarias no fija T-3 embarque ni gastos de destino; los importes mostrados no los incluyen.

Sheet Nacional 2026
A2: Presupuesto transporte nacional 2026
A3: Septiembre a diciembre · Campillo y Canarias separados · importe sin T-3 ni gastos de destino
A6: Mes | B6: Resto kg | C6: Resto palets | D6: Campillo (€) | E6: Canarias kg | F6: Canarias palets | G6: Sealine (€) | H6: Total kg | I6: Total (€)
A7: Sep | B7: =SUMIFS('Nacional · base'!$E$1074:$E$1473,'Nacional · base'!$A$1074:$A$1473,2026,'Nacional · base'!$B$1074:$B$1473,9,'Nacional · base'!$D$1074:$D$1473,"Resto nacional") -> 72566.526 | C7: =SUMIFS('Nacional · base'!$G$1074:$G$1473,'Nacional · base'!$A$1074:$A$1473,2026,'Nacional · base'!$B$1074:$B$1473,9,'Nacional · base'!$D$1074:$D$1473,"Resto nacional") -> 97 | D7: =SUMIFS('Nacional · base'!$Q$1074:$Q$1473,'Nacional · base'!$A$1074:$A$1473,2026,'Nacional · base'!$B$1074:$B$1473,9,'Nacional · base'!$D$1074:$D$1473,"Resto nacional") -> 6434.5324 | E7: =SUMIFS('Nacional · base'!$E$1074:$E$1473,'Nacional · base'!$A$1074:$A$1473,2026,'Nacional · base'!$B$1074:$B$1473,9,'Nacional · base'!$D$1074:$D$1473,"Canarias") -> 9089.387 | F7: =SUMIFS('Nacional · base'!$G$1074:$G$1473,'Nacional · base'!$A$1074:$A$1473,2026,'Nacional · base'!$B$1074:$B$1473,9,'Nacional · base'!$D$1074:$D$1473,"Canarias") -> 13 | G7: =SUMIFS('Nacional · base'!$R$1074:$R$1473,'Nacional · base'!$A$1074:$A$1473,2026,'Nacional · base'!$B$1074:$B$1473,9,'Nacional · base'!$D$1074:$D$1473,"Canarias") -> 2450.109 | H7: =B7+E7 -> 81655.913 | I7: =D7+G7 -> 8884.6414
A8: Oct | B8: =SUMIFS('Nacional · base'!$E$1074:$E$1473,'Nacional · base'!$A$1074:$A$1473,2026,'Nacional · base'!$B$1074:$B$1473,10,'Nacional · base'!$D$1074:$D$1473,"Resto nacional") -> 118404.53 | C8: =SUMIFS('Nacional · base'!$G$1074:$G$1473,'Nacional · base'!$A$1074:$A$1473,2026,'Nacional · base'!$B$1074:$B$1473,10,'Nacional · base'!$D$1074:$D$1473,"Resto nacional") -> 151 | D8: =SUMIFS('Nacional · base'!$Q$1074:$Q$1473,'Nacional · base'!$A$1074:$A$1473,2026,'Nacional · base'!$B$1074:$B$1473,10,'Nacional · base'!$D$1074:$D$1473,"Resto nacional") -> 10499.025 | E8: =SUMIFS('Nacional · base'!$E$1074:$E$1473,'Nacional · base'!$A$1074:$A$1473,2026,'Nacional · base'!$B$1074:$B$1473,10,'Nacional · base'!$D$1074:$D$1473,"Canarias") -> 35824.774 | F8: =SUMIFS('Nacional · base'!$G$1074:$G$1473,'Nacional · base'!$A$1074:$A$1473,2026,'Nacional · base'!$B$1074:$B$1473,10,'Nacional · base'!$D$1074:$D$1473,"Canarias") -> 41 | G8: =SUMIFS('Nacional · base'!$R$1074:$R$1473,'Nacional · base'!$A$1074:$A$1473,2026,'Nacional · base'!$B$1074:$B$1473,10,'Nacional · base'!$D$1074:$D$1473,"Canarias") -> 7990.591 | H8: =B8+E8 -> 154229.3 | I8: =D8+G8 -> 18489.616
A9: Nov | B9: =SUMIFS('Nacional · base'!$E$1074:$E$1473,'Nacional · base'!$A$1074:$A$1473,2026,'Nacional · base'!$B$1074:$B$1473,11,'Nacional · base'!$D$1074:$D$1473,"Resto nacional") -> 115171.44 | C9: =SUMIFS('Nacional · base'!$G$1074:$G$1473,'Nacional · base'!$A$1074:$A$1473,2026,'Nacional · base'!$B$1074:$B$1473,11,'Nacional · base'!$D$1074:$D$1473,"Resto nacional") -> 139 | D9: =SUMIFS('Nacional · base'!$Q$1074:$Q$1473,'Nacional · base'!$A$1074:$A$1473,2026,'Nacional · base'!$B$1074:$B$1473,11,'Nacional · base'!$D$1074:$D$1473,"Resto nacional") -> 10212.345 | E9: =SUMIFS('Nacional · base'!$E$1074:$E$1473,'Nacional · base'!$A$1074:$A$1473,2026,'Nacional · base'!$B$1074:$B$1473,11,'Nacional · base'!$D$1074:$D$1473,"Canarias") -> 47468.442 | F9: =SUMIFS('Nacional · base'!$G$1074:$G$1473,'Nacional · base'!$A$1074:$A$1473,2026,'Nacional · base'!$B$1074:$B$1473,11,'Nacional · base'!$D$1074:$D$1473,"Canarias") -> 57 | G9: =SUMIFS('Nacional · base'!$R$1074:$R$1473,'Nacional · base'!$A$1074:$A$1473,2026,'Nacional · base'!$B$1074:$B$1473,11,'Nacional · base'!$D$1074:$D$1473,"Canarias") -> 11300.379 | H9: =B9+E9 -> 162639.89 | I9: =D9+G9 -> 21512.724
A10: Dic | B10: =SUMIFS('Nacional · base'!$E$1074:$E$1473,'Nacional · base'!$A$1074:$A$1473,2026,'Nacional · base'!$B$1074:$B$1473,12,'Nacional · base'!$D$1074:$D$1473,"Resto nacional") -> 45718.934 | C10: =SUMIFS('Nacional · base'!$G$1074:$G$1473,'Nacional · base'!$A$1074:$A$1473,2026,'Nacional · base'!$B$1074:$B$1473,12,'Nacional · base'!$D$1074:$D$1473,"Resto nacional") -> 66 | D10: =SUMIFS('Nacional · base'!$Q$1074:$Q$1473,'Nacional · base'!$A$1074:$A$1473,2026,'Nacional · base'!$B$1074:$B$1473,12,'Nacional · base'!$D$1074:$D$1473,"Resto nacional") -> 4053.9348 | E10: =SUMIFS('Nacional · base'!$E$1074:$E$1473,'Nacional · base'!$A$1074:$A$1473,2026,'Nacional · base'!$B$1074:$B$1473,12,'Nacional · base'!$D$1074:$D$1473,"Canarias") -> 2505.7434 | F10: =SUMIFS('Nacional · base'!$G$1074:$G$1473,'Nacional · base'!$A$1074:$A$1473,2026,'Nacional · base'!$B$1074:$B$1473,12,'Nacional · base'!$D$1074:$D$1473,"Canarias") -> 3 | G10: =SUMIFS('Nacional · base'!$R$1074:$R$1473,'Nacional · base'!$A$1074:$A$1473,2026,'Nacional · base'!$B$1074:$B$1473,12,'Nacional · base'!$D$1074:$D$1473,"Canarias") -> 534.13573 | H10: =B10+E10 -> 48224.677 | I10: =D10+G10 -> 4588.0705
A11: TOTAL | B11: =SUM(B7:B10) -> 351861.43 | C11: =SUM(C7:C10) -> 453 | D11: =SUM(D7:D10) -> 31199.837 | E11: =SUM(E7:E10) -> 94888.346 | F11: =SUM(F7:F10) -> 114 | G11: =SUM(G7:G10) -> 22275.215 | H11: =SUM(H7:H10) -> 446749.78 | I11: =SUM(I7:I10) -> 53475.052
A15: Canarias · coste por cliente y mes
A16: Mes | B16: Cliente / destino | C16: Kilos | D16: Palets | E16: Sealine (€)
A17: Sep | B17: AGROQUIMICAS DRAGO S.L. · La Montañeta, El Calero | C17: =SUMIFS('Nacional · base'!$E$1074:$E$1473,'Nacional · base'!$A$1074:$A$1473,2026,'Nacional · base'!$B$1074:$B$1473,9,'Nacional · base'!$C$1074:$C$1473,"AGROQUIMICAS DRAGO S.L.") -> 2832.6125 | D17: =SUMIFS('Nacional · base'!$G$1074:$G$1473,'Nacional · base'!$A$1074:$A$1473,2026,'Nacional · base'!$B$1074:$B$1473,9,'Nacional · base'!$C$1074:$C$1473,"AGROQUIMICAS DRAGO S.L.") -> 4 | E17: =SUMIFS('Nacional · base'!$R$1074:$R$1473,'Nacional · base'!$A$1074:$A$1473,2026,'Nacional · base'!$B$1074:$B$1473,9,'Nacional · base'!$C$1074:$C$1473,"AGROQUIMICAS DRAGO S.L.") -> 597.13574
A18: Sep | B18: FITOSANITARIOS DRAGO S.L.U · Santa Cruz de Tenerife | C18: =SUMIFS('Nacional · base'!$E$1074:$E$1473,'Nacional · base'!$A$1074:$A$1473,2026,'Nacional · base'!$B$1074:$B$1473,9,'Nacional · base'!$C$1074:$C$1473,"FITOSANITARIOS DRAGO S.L.U") -> 0 | D18: =SUMIFS('Nacional · base'!$G$1074:$G$1473,'Nacional · base'!$A$1074:$A$1473,2026,'Nacional · base'!$B$1074:$B$1473,9,'Nacional · base'!$C$1074:$C$1473,"FITOSANITARIOS DRAGO S.L.U") -> 0 | E18: =SUMIFS('Nacional · base'!$R$1074:$R$1473,'Nacional · base'!$A$1074:$A$1473,2026,'Nacional · base'!$B$1074:$B$1473,9,'Nacional · base'!$C$1074:$C$1473,"FITOSANITARIOS DRAGO S.L.U") -> 0
A19: Sep | B19: CABRERA MORALES FRANCISCO · Santa Cruz de La Palma | C19: =SUMIFS('Nacional · base'!$E$1074:$E$1473,'Nacional · base'!$A$1074:$A$1473,2026,'Nacional · base'!$B$1074:$B$1473,9,'Nacional · base'!$C$1074:$C$1473,"CABRERA MORALES FRANCISCO") -> 6256.7745 | D19: =SUMIFS('Nacional · base'!$G$1074:$G$1473,'Nacional · base'!$A$1074:$A$1473,2026,'Nacional · base'!$B$1074:$B$1473,9,'Nacional · base'!$C$1074:$C$1473,"CABRERA MORALES FRANCISCO") -> 9 | E19: =SUMIFS('Nacional · base'!$R$1074:$R$1473,'Nacional · base'!$A$1074:$A$1473,2026,'Nacional · base'!$B$1074:$B$1473,9,'Nacional · base'!$C$1074:$C$1473,"CABRERA MORALES FRANCISCO") -> 1852.9732
A20: Oct | B20: AGROQUIMICAS DRAGO S.L. · La Montañeta, El Calero | C20: =SUMIFS('Nacional · base'!$E$1074:$E$1473,'Nacional · base'!$A$1074:$A$1473,2026,'Nacional · base'!$B$1074:$B$1473,10,'Nacional · base'!$C$1074:$C$1473,"AGROQUIMICAS DRAGO S.L.") -> 12645.51 | D20: =SUMIFS('Nacional · base'!$G$1074:$G$1473,'Nacional · base'!$A$1074:$A$1473,2026,'Nacional · base'!$B$1074:$B$1473,10,'Nacional · base'!$C$1074:$C$1473,"AGROQUIMICAS DRAGO S.L.") -> 15 | E20: =SUMIFS('Nacional · base'!$R$1074:$R$1473,'Nacional · base'!$A$1074:$A$1473,2026,'Nacional · base'!$B$1074:$B$1473,10,'Nacional · base'!$C$1074:$C$1473,"AGROQUIMICAS DRAGO S.L.") -> 2553.3303
A21: Oct | B21: FITOSANITARIOS DRAGO S.L.U · Santa Cruz de Tenerife | C21: =SUMIFS('Nacional · base'!$E$1074:$E$1473,'Nacional · base'!$A$1074:$A$1473,2026,'Nacional · base'!$B$1074:$B$1473,10,'Nacional · base'!$C$1074:$C$1473,"FITOSANITARIOS DRAGO S.L.U") -> 15191.069 | D21: =SUMIFS('Nacional · base'!$G$1074:$G$1473,'Nacional · base'!$A$1074:$A$1473,2026,'Nacional · base'!$B$1074:$B$1473,10,'Nacional · base'!$C$1074:$C$1473,"FITOSANITARIOS DRAGO S.L.U") -> 15 | E21: =SUMIFS('Nacional · base'!$R$1074:$R$1473,'Nacional · base'!$A$1074:$A$1473,2026,'Nacional · base'!$B$1074:$B$1473,10,'Nacional · base'!$C$1074:$C$1473,"FITOSANITARIOS DRAGO S.L.U") -> 3076.529
A22: Oct | B22: CABRERA MORALES FRANCISCO · Santa Cruz de La Palma | C22: =SUMIFS('Nacional · base'!$E$1074:$E$1473,'Nacional · base'!$A$1074:$A$1473,2026,'Nacional · base'!$B$1074:$B$1473,10,'Nacional · base'!$C$1074:$C$1473,"CABRERA MORALES FRANCISCO") -> 7988.1947 | D22: =SUMIFS('Nacional · base'!$G$1074:$G$1473,'Nacional · base'!$A$1074:$A$1473,2026,'Nacional · base'!$B$1074:$B$1473,10,'Nacional · base'!$C$1074:$C$1473,"CABRERA MORALES FRANCISCO") -> 11 | E22: =SUMIFS('Nacional · base'!$R$1074:$R$1473,'Nacional · base'!$A$1074:$A$1473,2026,'Nacional · base'!$B$1074:$B$1473,10,'Nacional · base'!$C$1074:$C$1473,"CABRERA MORALES FRANCISCO") -> 2360.7317
A23: Nov | B23: AGROQUIMICAS DRAGO S.L. · La Montañeta, El Calero | C23: =SUMIFS('Nacional · base'!$E$1074:$E$1473,'Nacional · base'!$A$1074:$A$1473,2026,'Nacional · base'!$B$1074:$B$1473,11,'Nacional · base'!$C$1074:$C$1473,"AGROQUIMICAS DRAGO S.L.") -> 14119.075 | D23: =SUMIFS('Nacional · base'!$G$1074:$G$1473,'Nacional · base'!$A$1074:$A$1473,2026,'Nacional · base'!$B$1074:$B$1473,11,'Nacional · base'!$C$1074:$C$1473,"AGROQUIMICAS DRAGO S.L.") -> 17 | E23: =SUMIFS('Nacional · base'!$R$1074:$R$1473,'Nacional · base'!$A$1074:$A$1473,2026,'Nacional · base'!$B$1074:$B$1473,11,'Nacional · base'!$C$1074:$C$1473,"AGROQUIMICAS DRAGO S.L.") -> 2855.2046
A24: Nov | B24: FITOSANITARIOS DRAGO S.L.U · Santa Cruz de Tenerife | C24: =SUMIFS('Nacional · base'!$E$1074:$E$1473,'Nacional · base'!$A$1074:$A$1473,2026,'Nacional · base'!$B$1074:$B$1473,11,'Nacional · base'!$C$1074:$C$1473,"FITOSANITARIOS DRAGO S.L.U") -> 15459.542 | D24: =SUMIFS('Nacional · base'!$G$1074:$G$1473,'Nacional · base'!$A$1074:$A$1473,2026,'Nacional · base'!$B$1074:$B$1473,11,'Nacional · base'!$C$1074:$C$1473,"FITOSANITARIOS DRAGO S.L.U") -> 16 | E24: =SUMIFS('Nacional · base'!$R$1074:$R$1473,'Nacional · base'!$A$1074:$A$1473,2026,'Nacional · base'!$B$1074:$B$1473,11,'Nacional · base'!$C$1074:$C$1473,"FITOSANITARIOS DRAGO S.L.U") -> 3130.9249
A25: Nov | B25: CABRERA MORALES FRANCISCO · Santa Cruz de La Palma | C25: =SUMIFS('Nacional · base'!$E$1074:$E$1473,'Nacional · base'!$A$1074:$A$1473,2026,'Nacional · base'!$B$1074:$B$1473,11,'Nacional · base'!$C$1074:$C$1473,"CABRERA MORALES FRANCISCO") -> 17889.825 | D25: =SUMIFS('Nacional · base'!$G$1074:$G$1473,'Nacional · base'!$A$1074:$A$1473,2026,'Nacional · base'!$B$1074:$B$1473,11,'Nacional · base'!$C$1074:$C$1473,"CABRERA MORALES FRANCISCO") -> 24 | E25: =SUMIFS('Nacional · base'!$R$1074:$R$1473,'Nacional · base'!$A$1074:$A$1473,2026,'Nacional · base'!$B$1074:$B$1473,11,'Nacional · base'!$C$1074:$C$1473,"CABRERA MORALES FRANCISCO") -> 5314.2496
A26: Dic | B26: AGROQUIMICAS DRAGO S.L. · La Montañeta, El Calero | C26: =SUMIFS('Nacional · base'!$E$1074:$E$1473,'Nacional · base'!$A$1074:$A$1473,2026,'Nacional · base'!$B$1074:$B$1473,12,'Nacional · base'!$C$1074:$C$1473,"AGROQUIMICAS DRAGO S.L.") -> 2505.7434 | D26: =SUMIFS('Nacional · base'!$G$1074:$G$1473,'Nacional · base'!$A$1074:$A$1473,2026,'Nacional · base'!$B$1074:$B$1473,12,'Nacional · base'!$C$1074:$C$1473,"AGROQUIMICAS DRAGO S.L.") -> 3 | E26: =SUMIFS('Nacional · base'!$R$1074:$R$1473,'Nacional · base'!$A$1074:$A$1473,2026,'Nacional · base'!$B$1074:$B$1473,12,'Nacional · base'!$C$1074:$C$1473,"AGROQUIMICAS DRAGO S.L.") -> 534.13573
A27: Dic | B27: FITOSANITARIOS DRAGO S.L.U · Santa Cruz de Tenerife | C27: =SUMIFS('Nacional · base'!$E$1074:$E$1473,'Nacional · base'!$A$1074:$A$1473,2026,'Nacional · base'!$B$1074:$B$1473,12,'Nacional · base'!$C$1074:$C$1473,"FITOSANITARIOS DRAGO S.L.U") -> 0 | D27: =SUMIFS('Nacional · base'!$G$1074:$G$1473,'Nacional · base'!$A$1074:$A$1473,2026,'Nacional · base'!$B$1074:$B$1473,12,'Nacional · base'!$C$1074:$C$1473,"FITOSANITARIOS DRAGO S.L.U") -> 0 | E27: =SUMIFS('Nacional · base'!$R$1074:$R$1473,'Nacional · base'!$A$1074:$A$1473,2026,'Nacional · base'!$B$1074:$B$1473,12,'Nacional · base'!$C$1074:$C$1473,"FITOSANITARIOS DRAGO S.L.U") -> 0
A28: Dic | B28: CABRERA MORALES FRANCISCO · Santa Cruz de La Palma | C28: =SUMIFS('Nacional · base'!$E$1074:$E$1473,'Nacional · base'!$A$1074:$A$1473,2026,'Nacional · base'!$B$1074:$B$1473,12,'Nacional · base'!$C$1074:$C$1473,"CABRERA MORALES FRANCISCO") -> 0 | D28: =SUMIFS('Nacional · base'!$G$1074:$G$1473,'Nacional · base'!$A$1074:$A$1473,2026,'Nacional · base'!$B$1074:$B$1473,12,'Nacional · base'!$C$1074:$C$1473,"CABRERA MORALES FRANCISCO") -> 0 | E28: =SUMIFS('Nacional · base'!$R$1074:$R$1473,'Nacional · base'!$A$1074:$A$1473,2026,'Nacional · base'!$B$1074:$B$1473,12,'Nacional · base'!$C$1074:$C$1473,"CABRERA MORALES FRANCISCO") -> 0

Sheet Nacional 2027
A2: Presupuesto transporte nacional 2027
A3: Enero a diciembre · tarifas 2026 + 10 % (4,5 % IPC y 5,5 % combustible) · sin T-3 ni destino
A6: Mes | B6: Resto kg | C6: Resto palets | D6: Campillo (€) | E6: Canarias kg | F6: Canarias palets | G6: Sealine (€) | H6: Total kg | I6: Total (€)
A7: Ene | B7: =SUMIFS('Nacional · base'!$E$1074:$E$1473,'Nacional · base'!$A$1074:$A$1473,2027,'Nacional · base'!$B$1074:$B$1473,1,'Nacional · base'!$D$1074:$D$1473,"Resto nacional") -> 71939.78 | C7: =SUMIFS('Nacional · base'!$G$1074:$G$1473,'Nacional · base'!$A$1074:$A$1473,2027,'Nacional · base'!$B$1074:$B$1473,1,'Nacional · base'!$D$1074:$D$1473,"Resto nacional") -> 103 | D7: =SUMIFS('Nacional · base'!$Q$1074:$Q$1473,'Nacional · base'!$A$1074:$A$1473,2027,'Nacional · base'!$B$1074:$B$1473,1,'Nacional · base'!$D$1074:$D$1473,"Resto nacional") -> 7016.8542 | E7: =SUMIFS('Nacional · base'!$E$1074:$E$1473,'Nacional · base'!$A$1074:$A$1473,2027,'Nacional · base'!$B$1074:$B$1473,1,'Nacional · base'!$D$1074:$D$1473,"Canarias") -> 21809.84 | F7: =SUMIFS('Nacional · base'!$G$1074:$G$1473,'Nacional · base'!$A$1074:$A$1473,2027,'Nacional · base'!$B$1074:$B$1473,1,'Nacional · base'!$D$1074:$D$1473,"Canarias") -> 28 | G7: =SUMIFS('Nacional · base'!$R$1074:$R$1473,'Nacional · base'!$A$1074:$A$1473,2027,'Nacional · base'!$B$1074:$B$1473,1,'Nacional · base'!$D$1074:$D$1473,"Canarias") -> 6088.1813 | H7: =B7+E7 -> 93749.62 | I7: =D7+G7 -> 13105.035
A8: Feb | B8: =SUMIFS('Nacional · base'!$E$1074:$E$1473,'Nacional · base'!$A$1074:$A$1473,2027,'Nacional · base'!$B$1074:$B$1473,2,'Nacional · base'!$D$1074:$D$1473,"Resto nacional") -> 139637.04 | C8: =SUMIFS('Nacional · base'!$G$1074:$G$1473,'Nacional · base'!$A$1074:$A$1473,2027,'Nacional · base'!$B$1074:$B$1473,2,'Nacional · base'!$D$1074:$D$1473,"Resto nacional") -> 184 | D8: =SUMIFS('Nacional · base'!$Q$1074:$Q$1473,'Nacional · base'!$A$1074:$A$1473,2027,'Nacional · base'!$B$1074:$B$1473,2,'Nacional · base'!$D$1074:$D$1473,"Resto nacional") -> 13619.902 | E8: =SUMIFS('Nacional · base'!$E$1074:$E$1473,'Nacional · base'!$A$1074:$A$1473,2027,'Nacional · base'!$B$1074:$B$1473,2,'Nacional · base'!$D$1074:$D$1473,"Canarias") -> 19473.88 | F8: =SUMIFS('Nacional · base'!$G$1074:$G$1473,'Nacional · base'!$A$1074:$A$1473,2027,'Nacional · base'!$B$1074:$B$1473,2,'Nacional · base'!$D$1074:$D$1473,"Canarias") -> 25 | G8: =SUMIFS('Nacional · base'!$R$1074:$R$1473,'Nacional · base'!$A$1074:$A$1473,2027,'Nacional · base'!$B$1074:$B$1473,2,'Nacional · base'!$D$1074:$D$1473,"Canarias") -> 5367.2581 | H8: =B8+E8 -> 159110.92 | I8: =D8+G8 -> 18987.16
A9: Mar | B9: =SUMIFS('Nacional · base'!$E$1074:$E$1473,'Nacional · base'!$A$1074:$A$1473,2027,'Nacional · base'!$B$1074:$B$1473,3,'Nacional · base'!$D$1074:$D$1473,"Resto nacional") -> 190772.44 | C9: =SUMIFS('Nacional · base'!$G$1074:$G$1473,'Nacional · base'!$A$1074:$A$1473,2027,'Nacional · base'!$B$1074:$B$1473,3,'Nacional · base'!$D$1074:$D$1473,"Resto nacional") -> 246 | D9: =SUMIFS('Nacional · base'!$Q$1074:$Q$1473,'Nacional · base'!$A$1074:$A$1473,2027,'Nacional · base'!$B$1074:$B$1473,3,'Nacional · base'!$D$1074:$D$1473,"Resto nacional") -> 18607.541 | E9: =SUMIFS('Nacional · base'!$E$1074:$E$1473,'Nacional · base'!$A$1074:$A$1473,2027,'Nacional · base'!$B$1074:$B$1473,3,'Nacional · base'!$D$1074:$D$1473,"Canarias") -> 27761.06 | F9: =SUMIFS('Nacional · base'!$G$1074:$G$1473,'Nacional · base'!$A$1074:$A$1473,2027,'Nacional · base'!$B$1074:$B$1473,3,'Nacional · base'!$D$1074:$D$1473,"Canarias") -> 34 | G9: =SUMIFS('Nacional · base'!$R$1074:$R$1473,'Nacional · base'!$A$1074:$A$1473,2027,'Nacional · base'!$B$1074:$B$1473,3,'Nacional · base'!$D$1074:$D$1473,"Canarias") -> 7224.7247 | H9: =B9+E9 -> 218533.5 | I9: =D9+G9 -> 25832.266
A10: Abr | B10: =SUMIFS('Nacional · base'!$E$1074:$E$1473,'Nacional · base'!$A$1074:$A$1473,2027,'Nacional · base'!$B$1074:$B$1473,4,'Nacional · base'!$D$1074:$D$1473,"Resto nacional") -> 226121.76 | C10: =SUMIFS('Nacional · base'!$G$1074:$G$1473,'Nacional · base'!$A$1074:$A$1473,2027,'Nacional · base'!$B$1074:$B$1473,4,'Nacional · base'!$D$1074:$D$1473,"Resto nacional") -> 296 | D10: =SUMIFS('Nacional · base'!$Q$1074:$Q$1473,'Nacional · base'!$A$1074:$A$1473,2027,'Nacional · base'!$B$1074:$B$1473,4,'Nacional · base'!$D$1074:$D$1473,"Resto nacional") -> 22055.439 | E10: =SUMIFS('Nacional · base'!$E$1074:$E$1473,'Nacional · base'!$A$1074:$A$1473,2027,'Nacional · base'!$B$1074:$B$1473,4,'Nacional · base'!$D$1074:$D$1473,"Canarias") -> 13650.64 | F10: =SUMIFS('Nacional · base'!$G$1074:$G$1473,'Nacional · base'!$A$1074:$A$1473,2027,'Nacional · base'!$B$1074:$B$1473,4,'Nacional · base'!$D$1074:$D$1473,"Canarias") -> 18 | G10: =SUMIFS('Nacional · base'!$R$1074:$R$1473,'Nacional · base'!$A$1074:$A$1473,2027,'Nacional · base'!$B$1074:$B$1473,4,'Nacional · base'!$D$1074:$D$1473,"Canarias") -> 3712.0421 | H10: =B10+E10 -> 239772.4 | I10: =D10+G10 -> 25767.481
A11: May | B11: =SUMIFS('Nacional · base'!$E$1074:$E$1473,'Nacional · base'!$A$1074:$A$1473,2027,'Nacional · base'!$B$1074:$B$1473,5,'Nacional · base'!$D$1074:$D$1473,"Resto nacional") -> 191162.96 | C11: =SUMIFS('Nacional · base'!$G$1074:$G$1473,'Nacional · base'!$A$1074:$A$1473,2027,'Nacional · base'!$B$1074:$B$1473,5,'Nacional · base'!$D$1074:$D$1473,"Resto nacional") -> 250 | D11: =SUMIFS('Nacional · base'!$Q$1074:$Q$1473,'Nacional · base'!$A$1074:$A$1473,2027,'Nacional · base'!$B$1074:$B$1473,5,'Nacional · base'!$D$1074:$D$1473,"Resto nacional") -> 18645.631 | E11: =SUMIFS('Nacional · base'!$E$1074:$E$1473,'Nacional · base'!$A$1074:$A$1473,2027,'Nacional · base'!$B$1074:$B$1473,5,'Nacional · base'!$D$1074:$D$1473,"Canarias") -> 50703.5 | F11: =SUMIFS('Nacional · base'!$G$1074:$G$1473,'Nacional · base'!$A$1074:$A$1473,2027,'Nacional · base'!$B$1074:$B$1473,5,'Nacional · base'!$D$1074:$D$1473,"Canarias") -> 63 | G11: =SUMIFS('Nacional · base'!$R$1074:$R$1473,'Nacional · base'!$A$1074:$A$1473,2027,'Nacional · base'!$B$1074:$B$1473,5,'Nacional · base'!$D$1074:$D$1473,"Canarias") -> 14028.954 | H11: =B11+E11 -> 241866.46 | I11: =D11+G11 -> 32674.585
A12: Jun | B12: =SUMIFS('Nacional · base'!$E$1074:$E$1473,'Nacional · base'!$A$1074:$A$1473,2027,'Nacional · base'!$B$1074:$B$1473,6,'Nacional · base'!$D$1074:$D$1473,"Resto nacional") -> 209112.66 | C12: =SUMIFS('Nacional · base'!$G$1074:$G$1473,'Nacional · base'!$A$1074:$A$1473,2027,'Nacional · base'!$B$1074:$B$1473,6,'Nacional · base'!$D$1074:$D$1473,"Resto nacional") -> 270 | D12: =SUMIFS('Nacional · base'!$Q$1074:$Q$1473,'Nacional · base'!$A$1074:$A$1473,2027,'Nacional · base'!$B$1074:$B$1473,6,'Nacional · base'!$D$1074:$D$1473,"Resto nacional") -> 20396.407 | E12: =SUMIFS('Nacional · base'!$E$1074:$E$1473,'Nacional · base'!$A$1074:$A$1473,2027,'Nacional · base'!$B$1074:$B$1473,6,'Nacional · base'!$D$1074:$D$1473,"Canarias") -> 8591.18 | F12: =SUMIFS('Nacional · base'!$G$1074:$G$1473,'Nacional · base'!$A$1074:$A$1473,2027,'Nacional · base'!$B$1074:$B$1473,6,'Nacional · base'!$D$1074:$D$1473,"Canarias") -> 13 | G12: =SUMIFS('Nacional · base'!$R$1074:$R$1473,'Nacional · base'!$A$1074:$A$1473,2027,'Nacional · base'!$B$1074:$B$1473,6,'Nacional · base'!$D$1074:$D$1473,"Canarias") -> 2584.44 | H12: =B12+E12 -> 217703.84 | I12: =D12+G12 -> 22980.847
A13: Jul | B13: =SUMIFS('Nacional · base'!$E$1074:$E$1473,'Nacional · base'!$A$1074:$A$1473,2027,'Nacional · base'!$B$1074:$B$1473,7,'Nacional · base'!$D$1074:$D$1473,"Resto nacional") -> 151201.88 | C13: =SUMIFS('Nacional · base'!$G$1074:$G$1473,'Nacional · base'!$A$1074:$A$1473,2027,'Nacional · base'!$B$1074:$B$1473,7,'Nacional · base'!$D$1074:$D$1473,"Resto nacional") -> 199 | D13: =SUMIFS('Nacional · base'!$Q$1074:$Q$1473,'Nacional · base'!$A$1074:$A$1473,2027,'Nacional · base'!$B$1074:$B$1473,7,'Nacional · base'!$D$1074:$D$1473,"Resto nacional") -> 14747.912 | E13: =SUMIFS('Nacional · base'!$E$1074:$E$1473,'Nacional · base'!$A$1074:$A$1473,2027,'Nacional · base'!$B$1074:$B$1473,7,'Nacional · base'!$D$1074:$D$1473,"Canarias") -> 16143.1 | F13: =SUMIFS('Nacional · base'!$G$1074:$G$1473,'Nacional · base'!$A$1074:$A$1473,2027,'Nacional · base'!$B$1074:$B$1473,7,'Nacional · base'!$D$1074:$D$1473,"Canarias") -> 23 | G13: =SUMIFS('Nacional · base'!$R$1074:$R$1473,'Nacional · base'!$A$1074:$A$1473,2027,'Nacional · base'!$B$1074:$B$1473,7,'Nacional · base'!$D$1074:$D$1473,"Canarias") -> 4588.2983 | H13: =B13+E13 -> 167344.98 | I13: =D13+G13 -> 19336.21
A14: Ago | B14: =SUMIFS('Nacional · base'!$E$1074:$E$1473,'Nacional · base'!$A$1074:$A$1473,2027,'Nacional · base'!$B$1074:$B$1473,8,'Nacional · base'!$D$1074:$D$1473,"Resto nacional") -> 136751.46 | C14: =SUMIFS('Nacional · base'!$G$1074:$G$1473,'Nacional · base'!$A$1074:$A$1473,2027,'Nacional · base'!$B$1074:$B$1473,8,'Nacional · base'!$D$1074:$D$1473,"Resto nacional") -> 167 | D14: =SUMIFS('Nacional · base'!$Q$1074:$Q$1473,'Nacional · base'!$A$1074:$A$1473,2027,'Nacional · base'!$B$1074:$B$1473,8,'Nacional · base'!$D$1074:$D$1473,"Resto nacional") -> 13338.449 | E14: =SUMIFS('Nacional · base'!$E$1074:$E$1473,'Nacional · base'!$A$1074:$A$1473,2027,'Nacional · base'!$B$1074:$B$1473,8,'Nacional · base'!$D$1074:$D$1473,"Canarias") -> 27209.98 | F14: =SUMIFS('Nacional · base'!$G$1074:$G$1473,'Nacional · base'!$A$1074:$A$1473,2027,'Nacional · base'!$B$1074:$B$1473,8,'Nacional · base'!$D$1074:$D$1473,"Canarias") -> 37 | G14: =SUMIFS('Nacional · base'!$R$1074:$R$1473,'Nacional · base'!$A$1074:$A$1473,2027,'Nacional · base'!$B$1074:$B$1473,8,'Nacional · base'!$D$1074:$D$1473,"Canarias") -> 8667.6855 | H14: =B14+E14 -> 163961.44 | I14: =D14+G14 -> 22006.134
A15: Sep | B15: =SUMIFS('Nacional · base'!$E$1074:$E$1473,'Nacional · base'!$A$1074:$A$1473,2027,'Nacional · base'!$B$1074:$B$1473,9,'Nacional · base'!$D$1074:$D$1473,"Resto nacional") -> 80234.04 | C15: =SUMIFS('Nacional · base'!$G$1074:$G$1473,'Nacional · base'!$A$1074:$A$1473,2027,'Nacional · base'!$B$1074:$B$1473,9,'Nacional · base'!$D$1074:$D$1473,"Resto nacional") -> 102 | D15: =SUMIFS('Nacional · base'!$Q$1074:$Q$1473,'Nacional · base'!$A$1074:$A$1473,2027,'Nacional · base'!$B$1074:$B$1473,9,'Nacional · base'!$D$1074:$D$1473,"Resto nacional") -> 7825.8588 | E15: =SUMIFS('Nacional · base'!$E$1074:$E$1473,'Nacional · base'!$A$1074:$A$1473,2027,'Nacional · base'!$B$1074:$B$1473,9,'Nacional · base'!$D$1074:$D$1473,"Canarias") -> 9928 | F15: =SUMIFS('Nacional · base'!$G$1074:$G$1473,'Nacional · base'!$A$1074:$A$1473,2027,'Nacional · base'!$B$1074:$B$1473,9,'Nacional · base'!$D$1074:$D$1473,"Canarias") -> 14 | G15: =SUMIFS('Nacional · base'!$R$1074:$R$1473,'Nacional · base'!$A$1074:$A$1473,2027,'Nacional · base'!$B$1074:$B$1473,9,'Nacional · base'!$D$1074:$D$1473,"Canarias") -> 2950.8535 | H15: =B15+E15 -> 90162.04 | I15: =D15+G15 -> 10776.712
A16: Oct | B16: =SUMIFS('Nacional · base'!$E$1074:$E$1473,'Nacional · base'!$A$1074:$A$1473,2027,'Nacional · base'!$B$1074:$B$1473,10,'Nacional · base'!$D$1074:$D$1473,"Resto nacional") -> 130207 | C16: =SUMIFS('Nacional · base'!$G$1074:$G$1473,'Nacional · base'!$A$1074:$A$1473,2027,'Nacional · base'!$B$1074:$B$1473,10,'Nacional · base'!$D$1074:$D$1473,"Resto nacional") -> 165 | D16: =SUMIFS('Nacional · base'!$Q$1074:$Q$1473,'Nacional · base'!$A$1074:$A$1473,2027,'Nacional · base'!$B$1074:$B$1473,10,'Nacional · base'!$D$1074:$D$1473,"Resto nacional") -> 12700.116 | E16: =SUMIFS('Nacional · base'!$E$1074:$E$1473,'Nacional · base'!$A$1074:$A$1473,2027,'Nacional · base'!$B$1074:$B$1473,10,'Nacional · base'!$D$1074:$D$1473,"Canarias") -> 39003.2 | F16: =SUMIFS('Nacional · base'!$G$1074:$G$1473,'Nacional · base'!$A$1074:$A$1473,2027,'Nacional · base'!$B$1074:$B$1473,10,'Nacional · base'!$D$1074:$D$1473,"Canarias") -> 45 | G16: =SUMIFS('Nacional · base'!$R$1074:$R$1473,'Nacional · base'!$A$1074:$A$1473,2027,'Nacional · base'!$B$1074:$B$1473,10,'Nacional · base'!$D$1074:$D$1473,"Canarias") -> 9635.0411 | H16: =B16+E16 -> 169210.2 | I16: =D16+G16 -> 22335.157
A17: Nov | B17: =SUMIFS('Nacional · base'!$E$1074:$E$1473,'Nacional · base'!$A$1074:$A$1473,2027,'Nacional · base'!$B$1074:$B$1473,11,'Nacional · base'!$D$1074:$D$1473,"Resto nacional") -> 128444.36 | C17: =SUMIFS('Nacional · base'!$G$1074:$G$1473,'Nacional · base'!$A$1074:$A$1473,2027,'Nacional · base'!$B$1074:$B$1473,11,'Nacional · base'!$D$1074:$D$1473,"Resto nacional") -> 155 | D17: =SUMIFS('Nacional · base'!$Q$1074:$Q$1473,'Nacional · base'!$A$1074:$A$1473,2027,'Nacional · base'!$B$1074:$B$1473,11,'Nacional · base'!$D$1074:$D$1473,"Resto nacional") -> 12528.192 | E17: =SUMIFS('Nacional · base'!$E$1074:$E$1473,'Nacional · base'!$A$1074:$A$1473,2027,'Nacional · base'!$B$1074:$B$1473,11,'Nacional · base'!$D$1074:$D$1473,"Canarias") -> 52107.9 | F17: =SUMIFS('Nacional · base'!$G$1074:$G$1473,'Nacional · base'!$A$1074:$A$1473,2027,'Nacional · base'!$B$1074:$B$1473,11,'Nacional · base'!$D$1074:$D$1473,"Canarias") -> 62 | G17: =SUMIFS('Nacional · base'!$R$1074:$R$1473,'Nacional · base'!$A$1074:$A$1473,2027,'Nacional · base'!$B$1074:$B$1473,11,'Nacional · base'!$D$1074:$D$1473,"Canarias") -> 13725.162 | H17: =B17+E17 -> 180552.26 | I17: =D17+G17 -> 26253.353
A18: Dic | B18: =SUMIFS('Nacional · base'!$E$1074:$E$1473,'Nacional · base'!$A$1074:$A$1473,2027,'Nacional · base'!$B$1074:$B$1473,12,'Nacional · base'!$D$1074:$D$1473,"Resto nacional") -> 51158.06 | C18: =SUMIFS('Nacional · base'!$G$1074:$G$1473,'Nacional · base'!$A$1074:$A$1473,2027,'Nacional · base'!$B$1074:$B$1473,12,'Nacional · base'!$D$1074:$D$1473,"Resto nacional") -> 74 | D18: =SUMIFS('Nacional · base'!$Q$1074:$Q$1473,'Nacional · base'!$A$1074:$A$1473,2027,'Nacional · base'!$B$1074:$B$1473,12,'Nacional · base'!$D$1074:$D$1473,"Resto nacional") -> 4989.8491 | E18: =SUMIFS('Nacional · base'!$E$1074:$E$1473,'Nacional · base'!$A$1074:$A$1473,2027,'Nacional · base'!$B$1074:$B$1473,12,'Nacional · base'!$D$1074:$D$1473,"Canarias") -> 2666.8 | F18: =SUMIFS('Nacional · base'!$G$1074:$G$1473,'Nacional · base'!$A$1074:$A$1473,2027,'Nacional · base'!$B$1074:$B$1473,12,'Nacional · base'!$D$1074:$D$1473,"Canarias") -> 4 | G18: =SUMIFS('Nacional · base'!$R$1074:$R$1473,'Nacional · base'!$A$1074:$A$1473,2027,'Nacional · base'!$B$1074:$B$1473,12,'Nacional · base'!$D$1074:$D$1473,"Canarias") -> 625.65144 | H18: =B18+E18 -> 53824.86 | I18: =D18+G18 -> 5615.5006
A19: TOTAL | B19: =SUM(B7:B18) -> 1706743.4 | C19: =SUM(C7:C18) -> 2211 | D19: =SUM(D7:D18) -> 166472.15 | E19: =SUM(E7:E18) -> 289049.08 | F19: =SUM(F7:F18) -> 366 | G19: =SUM(G7:G18) -> 79198.291 | H19: =SUM(H7:H18) -> 1995792.5 | I19: =SUM(I7:I18) -> 245670.44
A23: Canarias · coste por cliente y mes
A24: Mes | B24: Cliente / destino | C24: Kilos | D24: Palets | E24: Sealine (€)
A25: Ene | B25: AGROQUIMICAS DRAGO S.L. · La Montañeta, El Calero | C25: =SUMIFS('Nacional · base'!$E$1074:$E$1473,'Nacional · base'!$A$1074:$A$1473,2027,'Nacional · base'!$B$1074:$B$1473,1,'Nacional · base'!$C$1074:$C$1473,"AGROQUIMICAS DRAGO S.L.") -> 8598.06 | D25: =SUMIFS('Nacional · base'!$G$1074:$G$1473,'Nacional · base'!$A$1074:$A$1473,2027,'Nacional · base'!$B$1074:$B$1473,1,'Nacional · base'!$C$1074:$C$1473,"AGROQUIMICAS DRAGO S.L.") -> 10 | E25: =SUMIFS('Nacional · base'!$R$1074:$R$1473,'Nacional · base'!$A$1074:$A$1473,2027,'Nacional · base'!$B$1074:$B$1473,1,'Nacional · base'!$C$1074:$C$1473,"AGROQUIMICAS DRAGO S.L.") -> 1934.4507
A26: Ene | B26: FITOSANITARIOS DRAGO S.L.U · Santa Cruz de Tenerife | C26: =SUMIFS('Nacional · base'!$E$1074:$E$1473,'Nacional · base'!$A$1074:$A$1473,2027,'Nacional · base'!$B$1074:$B$1473,1,'Nacional · base'!$C$1074:$C$1473,"FITOSANITARIOS DRAGO S.L.U") -> 1959.74 | D26: =SUMIFS('Nacional · base'!$G$1074:$G$1473,'Nacional · base'!$A$1074:$A$1473,2027,'Nacional · base'!$B$1074:$B$1473,1,'Nacional · base'!$C$1074:$C$1473,"FITOSANITARIOS DRAGO S.L.U") -> 3 | E26: =SUMIFS('Nacional · base'!$R$1074:$R$1473,'Nacional · base'!$A$1074:$A$1473,2027,'Nacional · base'!$B$1074:$B$1473,1,'Nacional · base'!$C$1074:$C$1473,"FITOSANITARIOS DRAGO S.L.U") -> 479.17655
A27: Ene | B27: CABRERA MORALES FRANCISCO · Santa Cruz de La Palma | C27: =SUMIFS('Nacional · base'!$E$1074:$E$1473,'Nacional · base'!$A$1074:$A$1473,2027,'Nacional · base'!$B$1074:$B$1473,1,'Nacional · base'!$C$1074:$C$1473,"CABRERA MORALES FRANCISCO") -> 11252.04 | D27: =SUMIFS('Nacional · base'!$G$1074:$G$1473,'Nacional · base'!$A$1074:$A$1473,2027,'Nacional · base'!$B$1074:$B$1473,1,'Nacional · base'!$C$1074:$C$1473,"CABRERA MORALES FRANCISCO") -> 15 | E27: =SUMIFS('Nacional · base'!$R$1074:$R$1473,'Nacional · base'!$A$1074:$A$1473,2027,'Nacional · base'!$B$1074:$B$1473,1,'Nacional · base'!$C$1074:$C$1473,"CABRERA MORALES FRANCISCO") -> 3674.554
A28: Feb | B28: AGROQUIMICAS DRAGO S.L. · La Montañeta, El Calero | C28: =SUMIFS('Nacional · base'!$E$1074:$E$1473,'Nacional · base'!$A$1074:$A$1473,2027,'Nacional · base'!$B$1074:$B$1473,2,'Nacional · base'!$C$1074:$C$1473,"AGROQUIMICAS DRAGO S.L.") -> 4192.54 | D28: =SUMIFS('Nacional · base'!$G$1074:$G$1473,'Nacional · base'!$A$1074:$A$1473,2027,'Nacional · base'!$B$1074:$B$1473,2,'Nacional · base'!$C$1074:$C$1473,"AGROQUIMICAS DRAGO S.L.") -> 6 | E28: =SUMIFS('Nacional · base'!$R$1074:$R$1473,'Nacional · base'!$A$1074:$A$1473,2027,'Nacional · base'!$B$1074:$B$1473,2,'Nacional · base'!$C$1074:$C$1473,"AGROQUIMICAS DRAGO S.L.") -> 970.08255
A29: Feb | B29: FITOSANITARIOS DRAGO S.L.U · Santa Cruz de Tenerife | C29: =SUMIFS('Nacional · base'!$E$1074:$E$1473,'Nacional · base'!$A$1074:$A$1473,2027,'Nacional · base'!$B$1074:$B$1473,2,'Nacional · base'!$C$1074:$C$1473,"FITOSANITARIOS DRAGO S.L.U") -> 5785.54 | D29: =SUMIFS('Nacional · base'!$G$1074:$G$1473,'Nacional · base'!$A$1074:$A$1473,2027,'Nacional · base'!$B$1074:$B$1473,2,'Nacional · base'!$C$1074:$C$1473,"FITOSANITARIOS DRAGO S.L.U") -> 6 | E29: =SUMIFS('Nacional · base'!$R$1074:$R$1473,'Nacional · base'!$A$1074:$A$1473,2027,'Nacional · base'!$B$1074:$B$1473,2,'Nacional · base'!$C$1074:$C$1473,"FITOSANITARIOS DRAGO S.L.U") -> 1278.6532
A30: Feb | B30: CABRERA MORALES FRANCISCO · Santa Cruz de La Palma | C30: =SUMIFS('Nacional · base'!$E$1074:$E$1473,'Nacional · base'!$A$1074:$A$1473,2027,'Nacional · base'!$B$1074:$B$1473,2,'Nacional · base'!$C$1074:$C$1473,"CABRERA MORALES FRANCISCO") -> 9495.8 | D30: =SUMIFS('Nacional · base'!$G$1074:$G$1473,'Nacional · base'!$A$1074:$A$1473,2027,'Nacional · base'!$B$1074:$B$1473,2,'Nacional · base'!$C$1074:$C$1473,"CABRERA MORALES FRANCISCO") -> 13 | E30: =SUMIFS('Nacional · base'!$R$1074:$R$1473,'Nacional · base'!$A$1074:$A$1473,2027,'Nacional · base'!$B$1074:$B$1473,2,'Nacional · base'!$C$1074:$C$1473,"CABRERA MORALES FRANCISCO") -> 3118.5224
A31: Mar | B31: AGROQUIMICAS DRAGO S.L. · La Montañeta, El Calero | C31: =SUMIFS('Nacional · base'!$E$1074:$E$1473,'Nacional · base'!$A$1074:$A$1473,2027,'Nacional · base'!$B$1074:$B$1473,3,'Nacional · base'!$C$1074:$C$1473,"AGROQUIMICAS DRAGO S.L.") -> 11280.2 | D31: =SUMIFS('Nacional · base'!$G$1074:$G$1473,'Nacional · base'!$A$1074:$A$1473,2027,'Nacional · base'!$B$1074:$B$1473,3,'Nacional · base'!$C$1074:$C$1473,"AGROQUIMICAS DRAGO S.L.") -> 14 | E31: =SUMIFS('Nacional · base'!$R$1074:$R$1473,'Nacional · base'!$A$1074:$A$1473,2027,'Nacional · base'!$B$1074:$B$1473,3,'Nacional · base'!$C$1074:$C$1473,"AGROQUIMICAS DRAGO S.L.") -> 2537.6171
A32: Mar | B32: FITOSANITARIOS DRAGO S.L.U · Santa Cruz de Tenerife | C32: =SUMIFS('Nacional · base'!$E$1074:$E$1473,'Nacional · base'!$A$1074:$A$1473,2027,'Nacional · base'!$B$1074:$B$1473,3,'Nacional · base'!$C$1074:$C$1473,"FITOSANITARIOS DRAGO S.L.U") -> 6819.44 | D32: =SUMIFS('Nacional · base'!$G$1074:$G$1473,'Nacional · base'!$A$1074:$A$1473,2027,'Nacional · base'!$B$1074:$B$1473,3,'Nacional · base'!$C$1074:$C$1473,"FITOSANITARIOS DRAGO S.L.U") -> 7 | E32: =SUMIFS('Nacional · base'!$R$1074:$R$1473,'Nacional · base'!$A$1074:$A$1473,2027,'Nacional · base'!$B$1074:$B$1473,3,'Nacional · base'!$C$1074:$C$1473,"FITOSANITARIOS DRAGO S.L.U") -> 1541.2203
A33: Mar | B33: CABRERA MORALES FRANCISCO · Santa Cruz de La Palma | C33: =SUMIFS('Nacional · base'!$E$1074:$E$1473,'Nacional · base'!$A$1074:$A$1473,2027,'Nacional · base'!$B$1074:$B$1473,3,'Nacional · base'!$C$1074:$C$1473,"CABRERA MORALES FRANCISCO") -> 9661.42 | D33: =SUMIFS('Nacional · base'!$G$1074:$G$1473,'Nacional · base'!$A$1074:$A$1473,2027,'Nacional · base'!$B$1074:$B$1473,3,'Nacional · base'!$C$1074:$C$1473,"CABRERA MORALES FRANCISCO") -> 13 | E33: =SUMIFS('Nacional · base'!$R$1074:$R$1473,'Nacional · base'!$A$1074:$A$1473,2027,'Nacional · base'!$B$1074:$B$1473,3,'Nacional · base'!$C$1074:$C$1473,"CABRERA MORALES FRANCISCO") -> 3145.8873
A34: Abr | B34: AGROQUIMICAS DRAGO S.L. · La Montañeta, El Calero | C34: =SUMIFS('Nacional · base'!$E$1074:$E$1473,'Nacional · base'!$A$1074:$A$1473,2027,'Nacional · base'!$B$1074:$B$1473,4,'Nacional · base'!$C$1074:$C$1473,"AGROQUIMICAS DRAGO S.L.") -> 4948.84 | D34: =SUMIFS('Nacional · base'!$G$1074:$G$1473,'Nacional · base'!$A$1074:$A$1473,2027,'Nacional · base'!$B$1074:$B$1473,4,'Nacional · base'!$C$1074:$C$1473,"AGROQUIMICAS DRAGO S.L.") -> 7 | E34: =SUMIFS('Nacional · base'!$R$1074:$R$1473,'Nacional · base'!$A$1074:$A$1473,2027,'Nacional · base'!$B$1074:$B$1473,4,'Nacional · base'!$C$1074:$C$1473,"AGROQUIMICAS DRAGO S.L.") -> 1142.1143
A35: Abr | B35: FITOSANITARIOS DRAGO S.L.U · Santa Cruz de Tenerife | C35: =SUMIFS('Nacional · base'!$E$1074:$E$1473,'Nacional · base'!$A$1074:$A$1473,2027,'Nacional · base'!$B$1074:$B$1473,4,'Nacional · base'!$C$1074:$C$1473,"FITOSANITARIOS DRAGO S.L.U") -> 3009 | D35: =SUMIFS('Nacional · base'!$G$1074:$G$1473,'Nacional · base'!$A$1074:$A$1473,2027,'Nacional · base'!$B$1074:$B$1473,4,'Nacional · base'!$C$1074:$C$1473,"FITOSANITARIOS DRAGO S.L.U") -> 3 | E35: =SUMIFS('Nacional · base'!$R$1074:$R$1473,'Nacional · base'!$A$1074:$A$1473,2027,'Nacional · base'!$B$1074:$B$1473,4,'Nacional · base'!$C$1074:$C$1473,"FITOSANITARIOS DRAGO S.L.U") -> 702.69258
A36: Abr | B36: CABRERA MORALES FRANCISCO · Santa Cruz de La Palma | C36: =SUMIFS('Nacional · base'!$E$1074:$E$1473,'Nacional · base'!$A$1074:$A$1473,2027,'Nacional · base'!$B$1074:$B$1473,4,'Nacional · base'!$C$1074:$C$1473,"CABRERA MORALES FRANCISCO") -> 5692.8 | D36: =SUMIFS('Nacional · base'!$G$1074:$G$1473,'Nacional · base'!$A$1074:$A$1473,2027,'Nacional · base'!$B$1074:$B$1473,4,'Nacional · base'!$C$1074:$C$1473,"CABRERA MORALES FRANCISCO") -> 8 | E36: =SUMIFS('Nacional · base'!$R$1074:$R$1473,'Nacional · base'!$A$1074:$A$1473,2027,'Nacional · base'!$B$1074:$B$1473,4,'Nacional · base'!$C$1074:$C$1473,"CABRERA MORALES FRANCISCO") -> 1867.2352
A37: May | B37: AGROQUIMICAS DRAGO S.L. · La Montañeta, El Calero | C37: =SUMIFS('Nacional · base'!$E$1074:$E$1473,'Nacional · base'!$A$1074:$A$1473,2027,'Nacional · base'!$B$1074:$B$1473,5,'Nacional · base'!$C$1074:$C$1473,"AGROQUIMICAS DRAGO S.L.") -> 4124.1 | D37: =SUMIFS('Nacional · base'!$G$1074:$G$1473,'Nacional · base'!$A$1074:$A$1473,2027,'Nacional · base'!$B$1074:$B$1473,5,'Nacional · base'!$C$1074:$C$1473,"AGROQUIMICAS DRAGO S.L.") -> 6 | E37: =SUMIFS('Nacional · base'!$R$1074:$R$1473,'Nacional · base'!$A$1074:$A$1473,2027,'Nacional · base'!$B$1074:$B$1473,5,'Nacional · base'!$C$1074:$C$1473,"AGROQUIMICAS DRAGO S.L.") -> 956.64325
A38: May | B38: FITOSANITARIOS DRAGO S.L.U · Santa Cruz de Tenerife | C38: =SUMIFS('Nacional · base'!$E$1074:$E$1473,'Nacional · base'!$A$1074:$A$1473,2027,'Nacional · base'!$B$1074:$B$1473,5,'Nacional · base'!$C$1074:$C$1473,"FITOSANITARIOS DRAGO S.L.U") -> 20681.5 | D38: =SUMIFS('Nacional · base'!$G$1074:$G$1473,'Nacional · base'!$A$1074:$A$1473,2027,'Nacional · base'!$B$1074:$B$1473,5,'Nacional · base'!$C$1074:$C$1473,"FITOSANITARIOS DRAGO S.L.U") -> 22 | E38: =SUMIFS('Nacional · base'!$R$1074:$R$1473,'Nacional · base'!$A$1074:$A$1473,2027,'Nacional · base'!$B$1074:$B$1473,5,'Nacional · base'!$C$1074:$C$1473,"FITOSANITARIOS DRAGO S.L.U") -> 4621.9335
A39: May | B39: CABRERA MORALES FRANCISCO · Santa Cruz de La Palma | C39: =SUMIFS('Nacional · base'!$E$1074:$E$1473,'Nacional · base'!$A$1074:$A$1473,2027,'Nacional · base'!$B$1074:$B$1473,5,'Nacional · base'!$C$1074:$C$1473,"CABRERA MORALES FRANCISCO") -> 25897.9 | D39: =SUMIFS('Nacional · base'!$G$1074:$G$1473,'Nacional · base'!$A$1074:$A$1473,2027,'Nacional · base'!$B$1074:$B$1473,5,'Nacional · base'!$C$1074:$C$1473,"CABRERA MORALES FRANCISCO") -> 35 | E39: =SUMIFS('Nacional · base'!$R$1074:$R$1473,'Nacional · base'!$A$1074:$A$1473,2027,'Nacional · base'!$B$1074:$B$1473,5,'Nacional · base'!$C$1074:$C$1473,"CABRERA MORALES FRANCISCO") -> 8450.3769
A40: Jun | B40: AGROQUIMICAS DRAGO S.L. · La Montañeta, El Calero | C40: =SUMIFS('Nacional · base'!$E$1074:$E$1473,'Nacional · base'!$A$1074:$A$1473,2027,'Nacional · base'!$B$1074:$B$1473,6,'Nacional · base'!$C$1074:$C$1473,"AGROQUIMICAS DRAGO S.L.") -> 2573.28 | D40: =SUMIFS('Nacional · base'!$G$1074:$G$1473,'Nacional · base'!$A$1074:$A$1473,2027,'Nacional · base'!$B$1074:$B$1473,6,'Nacional · base'!$C$1074:$C$1473,"AGROQUIMICAS DRAGO S.L.") -> 4 | E40: =SUMIFS('Nacional · base'!$R$1074:$R$1473,'Nacional · base'!$A$1074:$A$1473,2027,'Nacional · base'!$B$1074:$B$1473,6,'Nacional · base'!$C$1074:$C$1473,"AGROQUIMICAS DRAGO S.L.") -> 602.49977
A41: Jun | B41: FITOSANITARIOS DRAGO S.L.U · Santa Cruz de Tenerife | C41: =SUMIFS('Nacional · base'!$E$1074:$E$1473,'Nacional · base'!$A$1074:$A$1473,2027,'Nacional · base'!$B$1074:$B$1473,6,'Nacional · base'!$C$1074:$C$1473,"FITOSANITARIOS DRAGO S.L.U") -> 0 | D41: =SUMIFS('Nacional · base'!$G$1074:$G$1473,'Nacional · base'!$A$1074:$A$1473,2027,'Nacional · base'!$B$1074:$B$1473,6,'Nacional · base'!$C$1074:$C$1473,"FITOSANITARIOS DRAGO S.L.U") -> 0 | E41: =SUMIFS('Nacional · base'!$R$1074:$R$1473,'Nacional · base'!$A$1074:$A$1473,2027,'Nacional · base'!$B$1074:$B$1473,6,'Nacional · base'!$C$1074:$C$1473,"FITOSANITARIOS DRAGO S.L.U") -> 0
A42: Jun | B42: CABRERA MORALES FRANCISCO · Santa Cruz de La Palma | C42: =SUMIFS('Nacional · base'!$E$1074:$E$1473,'Nacional · base'!$A$1074:$A$1473,2027,'Nacional · base'!$B$1074:$B$1473,6,'Nacional · base'!$C$1074:$C$1473,"CABRERA MORALES FRANCISCO") -> 6017.9 | D42: =SUMIFS('Nacional · base'!$G$1074:$G$1473,'Nacional · base'!$A$1074:$A$1473,2027,'Nacional · base'!$B$1074:$B$1473,6,'Nacional · base'!$C$1074:$C$1473,"CABRERA MORALES FRANCISCO") -> 9 | E42: =SUMIFS('Nacional · base'!$R$1074:$R$1473,'Nacional · base'!$A$1074:$A$1473,2027,'Nacional · base'!$B$1074:$B$1473,6,'Nacional · base'!$C$1074:$C$1473,"CABRERA MORALES FRANCISCO") -> 1981.9402
A43: Jul | B43: AGROQUIMICAS DRAGO S.L. · La Montañeta, El Calero | C43: =SUMIFS('Nacional · base'!$E$1074:$E$1473,'Nacional · base'!$A$1074:$A$1473,2027,'Nacional · base'!$B$1074:$B$1473,7,'Nacional · base'!$C$1074:$C$1473,"AGROQUIMICAS DRAGO S.L.") -> 4913.1 | D43: =SUMIFS('Nacional · base'!$G$1074:$G$1473,'Nacional · base'!$A$1074:$A$1473,2027,'Nacional · base'!$B$1074:$B$1473,7,'Nacional · base'!$C$1074:$C$1473,"AGROQUIMICAS DRAGO S.L.") -> 7 | E43: =SUMIFS('Nacional · base'!$R$1074:$R$1473,'Nacional · base'!$A$1074:$A$1473,2027,'Nacional · base'!$B$1074:$B$1473,7,'Nacional · base'!$C$1074:$C$1473,"AGROQUIMICAS DRAGO S.L.") -> 1139.6776
A44: Jul | B44: FITOSANITARIOS DRAGO S.L.U · Santa Cruz de Tenerife | C44: =SUMIFS('Nacional · base'!$E$1074:$E$1473,'Nacional · base'!$A$1074:$A$1473,2027,'Nacional · base'!$B$1074:$B$1473,7,'Nacional · base'!$C$1074:$C$1473,"FITOSANITARIOS DRAGO S.L.U") -> 2407.2 | D44: =SUMIFS('Nacional · base'!$G$1074:$G$1473,'Nacional · base'!$A$1074:$A$1473,2027,'Nacional · base'!$B$1074:$B$1473,7,'Nacional · base'!$C$1074:$C$1473,"FITOSANITARIOS DRAGO S.L.U") -> 4 | E44: =SUMIFS('Nacional · base'!$R$1074:$R$1473,'Nacional · base'!$A$1074:$A$1473,2027,'Nacional · base'!$B$1074:$B$1473,7,'Nacional · base'!$C$1074:$C$1473,"FITOSANITARIOS DRAGO S.L.U") -> 563.70181
A45: Jul | B45: CABRERA MORALES FRANCISCO · Santa Cruz de La Palma | C45: =SUMIFS('Nacional · base'!$E$1074:$E$1473,'Nacional · base'!$A$1074:$A$1473,2027,'Nacional · base'!$B$1074:$B$1473,7,'Nacional · base'!$C$1074:$C$1473,"CABRERA MORALES FRANCISCO") -> 8822.8 | D45: =SUMIFS('Nacional · base'!$G$1074:$G$1473,'Nacional · base'!$A$1074:$A$1473,2027,'Nacional · base'!$B$1074:$B$1473,7,'Nacional · base'!$C$1074:$C$1473,"CABRERA MORALES FRANCISCO") -> 12 | E45: =SUMIFS('Nacional · base'!$R$1074:$R$1473,'Nacional · base'!$A$1074:$A$1473,2027,'Nacional · base'!$B$1074:$B$1473,7,'Nacional · base'!$C$1074:$C$1473,"CABRERA MORALES FRANCISCO") -> 2884.9188
A46: Ago | B46: AGROQUIMICAS DRAGO S.L. · La Montañeta, El Calero | C46: =SUMIFS('Nacional · base'!$E$1074:$E$1473,'Nacional · base'!$A$1074:$A$1473,2027,'Nacional · base'!$B$1074:$B$1473,8,'Nacional · base'!$C$1074:$C$1473,"AGROQUIMICAS DRAGO S.L.") -> 3001.96 | D46: =SUMIFS('Nacional · base'!$G$1074:$G$1473,'Nacional · base'!$A$1074:$A$1473,2027,'Nacional · base'!$B$1074:$B$1473,8,'Nacional · base'!$C$1074:$C$1473,"AGROQUIMICAS DRAGO S.L.") -> 4 | E46: =SUMIFS('Nacional · base'!$R$1074:$R$1473,'Nacional · base'!$A$1074:$A$1473,2027,'Nacional · base'!$B$1074:$B$1473,8,'Nacional · base'!$C$1074:$C$1473,"AGROQUIMICAS DRAGO S.L.") -> 697.07145
A47: Ago | B47: FITOSANITARIOS DRAGO S.L.U · Santa Cruz de Tenerife | C47: =SUMIFS('Nacional · base'!$E$1074:$E$1473,'Nacional · base'!$A$1074:$A$1473,2027,'Nacional · base'!$B$1074:$B$1473,8,'Nacional · base'!$C$1074:$C$1473,"FITOSANITARIOS DRAGO S.L.U") -> 0 | D47: =SUMIFS('Nacional · base'!$G$1074:$G$1473,'Nacional · base'!$A$1074:$A$1473,2027,'Nacional · base'!$B$1074:$B$1473,8,'Nacional · base'!$C$1074:$C$1473,"FITOSANITARIOS DRAGO S.L.U") -> 0 | E47: =SUMIFS('Nacional · base'!$R$1074:$R$1473,'Nacional · base'!$A$1074:$A$1473,2027,'Nacional · base'!$B$1074:$B$1473,8,'Nacional · base'!$C$1074:$C$1473,"FITOSANITARIOS DRAGO S.L.U") -> 0
A48: Ago | B48: CABRERA MORALES FRANCISCO · Santa Cruz de La Palma | C48: =SUMIFS('Nacional · base'!$E$1074:$E$1473,'Nacional · base'!$A$1074:$A$1473,2027,'Nacional · base'!$B$1074:$B$1473,8,'Nacional · base'!$C$1074:$C$1473,"CABRERA MORALES FRANCISCO") -> 24208.02 | D48: =SUMIFS('Nacional · base'!$G$1074:$G$1473,'Nacional · base'!$A$1074:$A$1473,2027,'Nacional · base'!$B$1074:$B$1473,8,'Nacional · base'!$C$1074:$C$1473,"CABRERA MORALES FRANCISCO") -> 33 | E48: =SUMIFS('Nacional · base'!$R$1074:$R$1473,'Nacional · base'!$A$1074:$A$1473,2027,'Nacional · base'!$B$1074:$B$1473,8,'Nacional · base'!$C$1074:$C$1473,"CABRERA MORALES FRANCISCO") -> 7970.6141
A49: Sep | B49: AGROQUIMICAS DRAGO S.L. · La Montañeta, El Calero | C49: =SUMIFS('Nacional · base'!$E$1074:$E$1473,'Nacional · base'!$A$1074:$A$1473,2027,'Nacional · base'!$B$1074:$B$1473,9,'Nacional · base'!$C$1074:$C$1473,"AGROQUIMICAS DRAGO S.L.") -> 3028 | D49: =SUMIFS('Nacional · base'!$G$1074:$G$1473,'Nacional · base'!$A$1074:$A$1473,2027,'Nacional · base'!$B$1074:$B$1473,9,'Nacional · base'!$C$1074:$C$1473,"AGROQUIMICAS DRAGO S.L.") -> 4 | E49: =SUMIFS('Nacional · base'!$R$1074:$R$1473,'Nacional · base'!$A$1074:$A$1473,2027,'Nacional · base'!$B$1074:$B$1473,9,'Nacional · base'!$C$1074:$C$1473,"AGROQUIMICAS DRAGO S.L.") -> 702.24039
A50: Sep | B50: FITOSANITARIOS DRAGO S.L.U · Santa Cruz de Tenerife | C50: =SUMIFS('Nacional · base'!$E$1074:$E$1473,'Nacional · base'!$A$1074:$A$1473,2027,'Nacional · base'!$B$1074:$B$1473,9,'Nacional · base'!$C$1074:$C$1473,"FITOSANITARIOS DRAGO S.L.U") -> 0 | D50: =SUMIFS('Nacional · base'!$G$1074:$G$1473,'Nacional · base'!$A$1074:$A$1473,2027,'Nacional · base'!$B$1074:$B$1473,9,'Nacional · base'!$C$1074:$C$1473,"FITOSANITARIOS DRAGO S.L.U") -> 0 | E50: =SUMIFS('Nacional · base'!$R$1074:$R$1473,'Nacional · base'!$A$1074:$A$1473,2027,'Nacional · base'!$B$1074:$B$1473,9,'Nacional · base'!$C$1074:$C$1473,"FITOSANITARIOS DRAGO S.L.U") -> 0
A51: Sep | B51: CABRERA MORALES FRANCISCO · Santa Cruz de La Palma | C51: =SUMIFS('Nacional · base'!$E$1074:$E$1473,'Nacional · base'!$A$1074:$A$1473,2027,'Nacional · base'!$B$1074:$B$1473,9,'Nacional · base'!$C$1074:$C$1473,"CABRERA MORALES FRANCISCO") -> 6900 | D51: =SUMIFS('Nacional · base'!$G$1074:$G$1473,'Nacional · base'!$A$1074:$A$1473,2027,'Nacional · base'!$B$1074:$B$1473,9,'Nacional · base'!$C$1074:$C$1473,"CABRERA MORALES FRANCISCO") -> 10 | E51: =SUMIFS('Nacional · base'!$R$1074:$R$1473,'Nacional · base'!$A$1074:$A$1473,2027,'Nacional · base'!$B$1074:$B$1473,9,'Nacional · base'!$C$1074:$C$1473,"CABRERA MORALES FRANCISCO") -> 2248.6131
A52: Oct | B52: AGROQUIMICAS DRAGO S.L. · La Montañeta, El Calero | C52: =SUMIFS('Nacional · base'!$E$1074:$E$1473,'Nacional · base'!$A$1074:$A$1473,2027,'Nacional · base'!$B$1074:$B$1473,10,'Nacional · base'!$C$1074:$C$1473,"AGROQUIMICAS DRAGO S.L.") -> 13704.7 | D52: =SUMIFS('Nacional · base'!$G$1074:$G$1473,'Nacional · base'!$A$1074:$A$1473,2027,'Nacional · base'!$B$1074:$B$1473,10,'Nacional · base'!$C$1074:$C$1473,"AGROQUIMICAS DRAGO S.L.") -> 16 | E52: =SUMIFS('Nacional · base'!$R$1074:$R$1473,'Nacional · base'!$A$1074:$A$1473,2027,'Nacional · base'!$B$1074:$B$1473,10,'Nacional · base'!$C$1074:$C$1473,"AGROQUIMICAS DRAGO S.L.") -> 3048.1999
A53: Oct | B53: FITOSANITARIOS DRAGO S.L.U · Santa Cruz de Tenerife | C53: =SUMIFS('Nacional · base'!$E$1074:$E$1473,'Nacional · base'!$A$1074:$A$1473,2027,'Nacional · base'!$B$1074:$B$1473,10,'Nacional · base'!$C$1074:$C$1473,"FITOSANITARIOS DRAGO S.L.U") -> 16071.6 | D53: =SUMIFS('Nacional · base'!$G$1074:$G$1473,'Nacional · base'!$A$1074:$A$1473,2027,'Nacional · base'!$B$1074:$B$1473,10,'Nacional · base'!$C$1074:$C$1473,"FITOSANITARIOS DRAGO S.L.U") -> 16 | E53: =SUMIFS('Nacional · base'!$R$1074:$R$1473,'Nacional · base'!$A$1074:$A$1473,2027,'Nacional · base'!$B$1074:$B$1473,10,'Nacional · base'!$C$1074:$C$1473,"FITOSANITARIOS DRAGO S.L.U") -> 3586.5743
A54: Oct | B54: CABRERA MORALES FRANCISCO · Santa Cruz de La Palma | C54: =SUMIFS('Nacional · base'!$E$1074:$E$1473,'Nacional · base'!$A$1074:$A$1473,2027,'Nacional · base'!$B$1074:$B$1473,10,'Nacional · base'!$C$1074:$C$1473,"CABRERA MORALES FRANCISCO") -> 9226.9 | D54: =SUMIFS('Nacional · base'!$G$1074:$G$1473,'Nacional · base'!$A$1074:$A$1473,2027,'Nacional · base'!$B$1074:$B$1473,10,'Nacional · base'!$C$1074:$C$1473,"CABRERA MORALES FRANCISCO") -> 13 | E54: =SUMIFS('Nacional · base'!$R$1074:$R$1473,'Nacional · base'!$A$1074:$A$1473,2027,'Nacional · base'!$B$1074:$B$1473,10,'Nacional · base'!$C$1074:$C$1473,"CABRERA MORALES FRANCISCO") -> 3000.2669
A55: Nov | B55: AGROQUIMICAS DRAGO S.L. · La Montañeta, El Calero | C55: =SUMIFS('Nacional · base'!$E$1074:$E$1473,'Nacional · base'!$A$1074:$A$1473,2027,'Nacional · base'!$B$1074:$B$1473,11,'Nacional · base'!$C$1074:$C$1473,"AGROQUIMICAS DRAGO S.L.") -> 15252.2 | D55: =SUMIFS('Nacional · base'!$G$1074:$G$1473,'Nacional · base'!$A$1074:$A$1473,2027,'Nacional · base'!$B$1074:$B$1473,11,'Nacional · base'!$C$1074:$C$1473,"AGROQUIMICAS DRAGO S.L.") -> 18 | E55: =SUMIFS('Nacional · base'!$R$1074:$R$1473,'Nacional · base'!$A$1074:$A$1473,2027,'Nacional · base'!$B$1074:$B$1473,11,'Nacional · base'!$C$1074:$C$1473,"AGROQUIMICAS DRAGO S.L.") -> 3398.1948
A56: Nov | B56: FITOSANITARIOS DRAGO S.L.U · Santa Cruz de Tenerife | C56: =SUMIFS('Nacional · base'!$E$1074:$E$1473,'Nacional · base'!$A$1074:$A$1473,2027,'Nacional · base'!$B$1074:$B$1473,11,'Nacional · base'!$C$1074:$C$1473,"FITOSANITARIOS DRAGO S.L.U") -> 16638 | D56: =SUMIFS('Nacional · base'!$G$1074:$G$1473,'Nacional · base'!$A$1074:$A$1473,2027,'Nacional · base'!$B$1074:$B$1473,11,'Nacional · base'!$C$1074:$C$1473,"FITOSANITARIOS DRAGO S.L.U") -> 17 | E56: =SUMIFS('Nacional · base'!$R$1074:$R$1473,'Nacional · base'!$A$1074:$A$1473,2027,'Nacional · base'!$B$1074:$B$1473,11,'Nacional · base'!$C$1074:$C$1473,"FITOSANITARIOS DRAGO S.L.U") -> 3713.1434
A57: Nov | B57: CABRERA MORALES FRANCISCO · Santa Cruz de La Palma | C57: =SUMIFS('Nacional · base'!$E$1074:$E$1473,'Nacional · base'!$A$1074:$A$1473,2027,'Nacional · base'!$B$1074:$B$1473,11,'Nacional · base'!$C$1074:$C$1473,"CABRERA MORALES FRANCISCO") -> 20217.7 | D57: =SUMIFS('Nacional · base'!$G$1074:$G$1473,'Nacional · base'!$A$1074:$A$1473,2027,'Nacional · base'!$B$1074:$B$1473,11,'Nacional · base'!$C$1074:$C$1473,"CABRERA MORALES FRANCISCO") -> 27 | E57: =SUMIFS('Nacional · base'!$R$1074:$R$1473,'Nacional · base'!$A$1074:$A$1473,2027,'Nacional · base'!$B$1074:$B$1473,11,'Nacional · base'!$C$1074:$C$1473,"CABRERA MORALES FRANCISCO") -> 6613.8235
A58: Dic | B58: AGROQUIMICAS DRAGO S.L. · La Montañeta, El Calero | C58: =SUMIFS('Nacional · base'!$E$1074:$E$1473,'Nacional · base'!$A$1074:$A$1473,2027,'Nacional · base'!$B$1074:$B$1473,12,'Nacional · base'!$C$1074:$C$1473,"AGROQUIMICAS DRAGO S.L.") -> 2666.8 | D58: =SUMIFS('Nacional · base'!$G$1074:$G$1473,'Nacional · base'!$A$1074:$A$1473,2027,'Nacional · base'!$B$1074:$B$1473,12,'Nacional · base'!$C$1074:$C$1473,"AGROQUIMICAS DRAGO S.L.") -> 4 | E58: =SUMIFS('Nacional · base'!$R$1074:$R$1473,'Nacional · base'!$A$1074:$A$1473,2027,'Nacional · base'!$B$1074:$B$1473,12,'Nacional · base'!$C$1074:$C$1473,"AGROQUIMICAS DRAGO S.L.") -> 625.65144
A59: Dic | B59: FITOSANITARIOS DRAGO S.L.U · Santa Cruz de Tenerife | C59: =SUMIFS('Nacional · base'!$E$1074:$E$1473,'Nacional · base'!$A$1074:$A$1473,2027,'Nacional · base'!$B$1074:$B$1473,12,'Nacional · base'!$C$1074:$C$1473,"FITOSANITARIOS DRAGO S.L.U") -> 0 | D59: =SUMIFS('Nacional · base'!$G$1074:$G$1473,'Nacional · base'!$A$1074:$A$1473,2027,'Nacional · base'!$B$1074:$B$1473,12,'Nacional · base'!$C$1074:$C$1473,"FITOSANITARIOS DRAGO S.L.U") -> 0 | E59: =SUMIFS('Nacional · base'!$R$1074:$R$1473,'Nacional · base'!$A$1074:$A$1473,2027,'Nacional · base'!$B$1074:$B$1473,12,'Nacional · base'!$C$1074:$C$1473,"FITOSANITARIOS DRAGO S.L.U") -> 0
A60: Dic | B60: CABRERA MORALES FRANCISCO · Santa Cruz de La Palma | C60: =SUMIFS('Nacional · base'!$E$1074:$E$1473,'Nacional · base'!$A$1074:$A$1473,2027,'Nacional · base'!$B$1074:$B$1473,12,'Nacional · base'!$C$1074:$C$1473,"CABRERA MORALES FRANCISCO") -> 0 | D60: =SUMIFS('Nacional · base'!$G$1074:$G$1473,'Nacional · base'!$A$1074:$A$1473,2027,'Nacional · base'!$B$1074:$B$1473,12,'Nacional · base'!$C$1074:$C$1473,"CABRERA MORALES FRANCISCO") -> 0 | E60: =SUMIFS('Nacional · base'!$R$1074:$R$1473,'Nacional · base'!$A$1074:$A$1473,2027,'Nacional · base'!$B$1074:$B$1473,12,'Nacional · base'!$C$1074:$C$1473,"CABRERA MORALES FRANCISCO") -> 0

Sheet Export · costes
A2: Costes mensuales de exportación
A3: Septiembre de 2026 añadido desde previsión de ventas; el resto se distribuye según coste anual por país del archivo adjunto.
A4: La documentación fija de 54 € de Arabia Saudí se asigna a octubre para reconciliar el total 2026 del origen.
A6: Año | B6: Mes | C6: Coste (€)
A7: 2026 | B7: Sep | C7: =SUMIFS($F$32:$F$207,$A$32:$A$207,2026,$B$32:$B$207,"Sep") -> 16253
A8: 2026 | B8: Oct | C8: =SUMIFS($F$32:$F$207,$A$32:$A$207,2026,$B$32:$B$207,"Oct")+'Export · países'!F7 -> 21379
A9: 2026 | B9: Nov | C9: =SUMIFS($F$32:$F$207,$A$32:$A$207,2026,$B$32:$B$207,"Nov") -> 32454
A10: 2026 | B10: Dic | C10: =SUMIFS($F$32:$F$207,$A$32:$A$207,2026,$B$32:$B$207,"Dic") -> 27150
A11: TOTAL 2026 | C11: =SUM(C7:C10) -> 97236
A14: Año | B14: Mes | C14: Coste (€)
A15: 2027 | B15: Ene | C15: =SUMIFS($F$32:$F$207,$A$32:$A$207,2027,$B$32:$B$207,"Ene") -> 29809.2
A16: 2027 | B16: Feb | C16: =SUMIFS($F$32:$F$207,$A$32:$A$207,2027,$B$32:$B$207,"Feb") -> 21246.7
A17: 2027 | B17: Mar | C17: =SUMIFS($F$32:$F$207,$A$32:$A$207,2027,$B$32:$B$207,"Mar") -> 19638.3
A18: 2027 | B18: Abr | C18: =SUMIFS($F$32:$F$207,$A$32:$A$207,2027,$B$32:$B$207,"Abr") -> 8004.2
A19: 2027 | B19: May | C19: =SUMIFS($F$32:$F$207,$A$32:$A$207,2027,$B$32:$B$207,"May") -> 38718.8
A20: 2027 | B20: Jun | C20: =SUMIFS($F$32:$F$207,$A$32:$A$207,2027,$B$32:$B$207,"Jun") -> 33492
A21: 2027 | B21: Jul | C21: =SUMIFS($F$32:$F$207,$A$32:$A$207,2027,$B$32:$B$207,"Jul") -> 13212.8
A22: 2027 | B22: Ago | C22: =SUMIFS($F$32:$F$207,$A$32:$A$207,2027,$B$32:$B$207,"Ago") -> 18509.6
A23: 2027 | B23: Sep | C23: =SUMIFS($F$32:$F$207,$A$32:$A$207,2027,$B$32:$B$207,"Sep") -> 24148.9
A24: 2027 | B24: Oct | C24: =SUMIFS($F$32:$F$207,$A$32:$A$207,2027,$B$32:$B$207,"Oct") -> 23411.3
A25: 2027 | B25: Nov | C25: =SUMIFS($F$32:$F$207,$A$32:$A$207,2027,$B$32:$B$207,"Nov") -> 40650.7
A26: 2027 | B26: Dic | C26: =SUMIFS($F$32:$F$207,$A$32:$A$207,2027,$B$32:$B$207,"Dic") -> 34380.8
A27: TOTAL 2027 | C27: =SUM(C15:C26) -> 305223.3
A31: Año | B31: Mes | C31: País | D31: Envíos | E31: Coste/envío (€) | F31: Coste (€)
A32: 2026 | B32: Sep | C32: ARABIA SAUDÍ | D32: =0 -> 0 | E32: =IFERROR('Export · países'!F7/'Export · países'!C7,0) -> 0 | F32: =D32*E32 -> 0
A33: 2026 | B33: Sep | C33: AZERBAIYÁN | D33: =0 -> 0 | E33: =IFERROR('Export · países'!F8/'Export · países'!C8,0) -> 1701 | F33: =D33*E33 -> 0
A34: 2026 | B34: Sep | C34: COSTA RICA | D34: =1 -> 1 | E34: =IFERROR('Export · países'!F11/'Export · países'!C11,0) -> 3850 | F34: =D34*E34 -> 3850
A35: 2026 | B35: Sep | C35: DOMINICANA, REPÚBLICA | D35: =0 -> 0 | E35: =IFERROR('Export · países'!F12/'Export · países'!C12,0) -> 3675 | F35: =D35*E35 -> 0
A36: 2026 | B36: Sep | C36: ECUADOR (incluidas las Islas Galápagos) | D36: =0 -> 0 | E36: =IFERROR('Export · países'!F13/'Export · países'!C13,0) -> 104 | F36: =D36*E36 -> 0
A37: 2026 | B37: Sep | C37: EGIPTO | D37: =1 -> 1 | E37: =IFERROR('Export · países'!F14/'Export · países'!C14,0) -> 179 | F37: =D37*E37 -> 179
A38: 2026 | B38: Sep | C38: ITALIA | D38: =0 -> 0 | E38: =IFERROR('Export · países'!F17/'Export · países'!C17,0) -> 487 | F38: =D38*E38 -> 0
A39: 2026 | B39: Sep | C39: LÍBANO | D39: =0 -> 0 | E39: =IFERROR('Export · países'!F18/'Export · países'!C18,0) -> 1579 | F39: =D39*E39 -> 0
A40: 2026 | B40: Sep | C40: NETHERLANS | D40: =2 -> 2 | E40: =IFERROR('Export · países'!F20/'Export · países'!C20,0) -> 4413 | F40: =D40*E40 -> 8826
A41: 2026 | B41: Sep | C41: PANAMÁ | D41: =0 -> 0 | E41: =IFERROR('Export · países'!F21/'Export · países'!C21,0) -> 3449 | F41: =D41*E41 -> 0
A42: 2026 | B42: Sep | C42: TURQUÍA | D42: =2 -> 2 | E42: =IFERROR('Export · países'!F25/'Export · países'!C25,0) -> 1699 | F42: =D42*E42 -> 3398
A43: 2026 | B43: Oct | C43: ARABIA SAUDÍ | D43: ='Export · detalle'!B7 -> 0 | E43: =IFERROR('Export · países'!F7/'Export · países'!C7,0) -> 0 | F43: =D43*E43 -> 0
A44: 2026 | B44: Oct | C44: AZERBAIYÁN | D44: ='Export · detalle'!B8 -> 0 | E44: =IFERROR('Export · países'!F8/'Export · países'!C8,0) -> 1701 | F44: =D44*E44 -> 0
A45: 2026 | B45: Oct | C45: COSTA RICA | D45: ='Export · detalle'!B11 -> 3 | E45: =IFERROR('Export · países'!F11/'Export · países'!C11,0) -> 3850 | F45: =D45*E45 -> 11550
A46: 2026 | B46: Oct | C46: DOMINICANA, REPÚBLICA | D46: ='Export · detalle'!B12 -> 0 | E46: =IFERROR('Export · países'!F12/'Export · países'!C12,0) -> 3675 | F46: =D46*E46 -> 0
A47: 2026 | B47: Oct | C47: ECUADOR (incluidas las Islas Galápagos) | D47: ='Export · detalle'!B13 -> 1 | E47: =IFERROR('Export · países'!F13/'Export · países'!C13,0) -> 104 | F47: =D47*E47 -> 104
A48: 2026 | B48: Oct | C48: EGIPTO | D48: ='Export · detalle'!B14 -> 2 | E48: =IFERROR('Export · países'!F14/'Export · países'!C14,0) -> 179 | F48: =D48*E48 -> 358
A49: 2026 | B49: Oct | C49: ITALIA | D49: ='Export · detalle'!B17 -> 1 | E49: =IFERROR('Export · países'!F17/'Export · países'!C17,0) -> 487 | F49: =D49*E49 -> 487
A50: 2026 | B50: Oct | C50: LÍBANO | D50: ='Export · detalle'!B18 -> 0 | E50: =IFERROR('Export · países'!F18/'Export · países'!C18,0) -> 1579 | F50: =D50*E50 -> 0
A51: 2026 | B51: Oct | C51: NETHERLANS | D51: ='Export · detalle'!B20 -> 2 | E51: =IFERROR('Export · países'!F20/'Export · países'!C20,0) -> 4413 | F51: =D51*E51 -> 8826
A52: 2026 | B52: Oct | C52: PANAMÁ | D52: ='Export · detalle'!B21 -> 0 | E52: =IFERROR('Export · países'!F21/'Export · países'!C21,0) -> 3449 | F52: =D52*E52 -> 0
A53: 2026 | B53: Oct | C53: TURQUÍA | D53: ='Export · detalle'!B25 -> 0 | E53: =IFERROR('Export · países'!F25/'Export · países'!C25,0) -> 1699 | F53: =D53*E53 -> 0
A54: 2026 | B54: Nov | C54: ARABIA SAUDÍ | D54: ='Export · detalle'!C7 -> 0 | E54: =IFERROR('Export · países'!F7/'Export · países'!C7,0) -> 0 | F54: =D54*E54 -> 0
A55: 2026 | B55: Nov | C55: AZERBAIYÁN | D55: ='Export · detalle'!C8 -> 0 | E55: =IFERROR('Export · países'!F8/'Export · países'!C8,0) -> 1701 | F55: =D55*E55 -> 0
A56: 2026 | B56: Nov | C56: COSTA RICA | D56: ='Export · detalle'!C11 -> 2 | E56: =IFERROR('Export · países'!F11/'Export · países'!C11,0) -> 3850 | F56: =D56*E56 -> 7700
A57: 2026 | B57: Nov | C57: DOMINICANA, REPÚBLICA | D57: ='Export · detalle'!C12 -> 2 | E57: =IFERROR('Export · países'!F12/'Export · países'!C12,0) -> 3675 | F57: =D57*E57 -> 7350
A58: 2026 | B58: Nov | C58: ECUADOR (incluidas las Islas Galápagos) | D58: ='Export · detalle'!C13 -> 0 | E58: =IFERROR('Export · países'!F13/'Export · países'!C13,0) -> 104 | F58: =D58*E58 -> 0
A59: 2026 | B59: Nov | C59: EGIPTO | D59: ='Export · detalle'!C14 -> 4 | E59: =IFERROR('Export · países'!F14/'Export · países'!C14,0) -> 179 | F59: =D59*E59 -> 716
A60: 2026 | B60: Nov | C60: ITALIA | D60: ='Export · detalle'!C17 -> 0 | E60: =IFERROR('Export · países'!F17/'Export · países'!C17,0) -> 487 | F60: =D60*E60 -> 0
A61: 2026 | B61: Nov | C61: LÍBANO | D61: ='Export · detalle'!C18 -> 0 | E61: =IFERROR('Export · países'!F18/'Export · países'!C18,0) -> 1579 | F61: =D61*E61 -> 0
A62: 2026 | B62: Nov | C62: NETHERLANS | D62: ='Export · detalle'!C20 -> 3 | E62: =IFERROR('Export · países'!F20/'Export · países'!C20,0) -> 4413 | F62: =D62*E62 -> 13239
A63: 2026 | B63: Nov | C63: PANAMÁ | D63: ='Export · detalle'!C21 -> 1 | E63: =IFERROR('Export · países'!F21/'Export · países'!C21,0) -> 3449 | F63: =D63*E63 -> 3449
A64: 2026 | B64: Nov | C64: TURQUÍA | D64: ='Export · detalle'!C25 -> 0 | E64: =IFERROR('Export · países'!F25/'Export · países'!C25,0) -> 1699 | F64: =D64*E64 -> 0
A65: 2026 | B65: Dic | C65: ARABIA SAUDÍ | D65: ='Export · detalle'!D7 -> 0 | E65: =IFERROR('Export · países'!F7/'Export · países'!C7,0) -> 0 | F65: =D65*E65 -> 0
A66: 2026 | B66: Dic | C66: AZERBAIYÁN | D66: ='Export · detalle'!D8 -> 2 | E66: =IFERROR('Export · países'!F8/'Export · países'!C8,0) -> 1701 | F66: =D66*E66 -> 3402
A67: 2026 | B67: Dic | C67: COSTA RICA | D67: ='Export · detalle'!D11 -> 2 | E67: =IFERROR('Export · países'!F11/'Export · países'!C11,0) -> 3850 | F67: =D67*E67 -> 7700
A68: 2026 | B68: Dic | C68: DOMINICANA, REPÚBLICA | D68: ='Export · detalle'!D12 -> 0 | E68: =IFERROR('Export · países'!F12/'Export · países'!C12,0) -> 3675 | F68: =D68*E68 -> 0
A69: 2026 | B69: Dic | C69: ECUADOR (incluidas las Islas Galápagos) | D69: ='Export · detalle'!D13 -> 0 | E69: =IFERROR('Export · países'!F13/'Export · países'!C13,0) -> 104 | F69: =D69*E69 -> 0
A70: 2026 | B70: Dic | C70: EGIPTO | D70: ='Export · detalle'!D14 -> 1 | E70: =IFERROR('Export · países'!F14/'Export · países'!C14,0) -> 179 | F70: =D70*E70 -> 179
A71: 2026 | B71: Dic | C71: ITALIA | D71: ='Export · detalle'!D17 -> 1 | E71: =IFERROR('Export · países'!F17/'Export · países'!C17,0) -> 487 | F71: =D71*E71 -> 487
A72: 2026 | B72: Dic | C72: LÍBANO | D72: ='Export · detalle'!D18 -> 2 | E72: =IFERROR('Export · países'!F18/'Export · países'!C18,0) -> 1579 | F72: =D72*E72 -> 3158
A73: 2026 | B73: Dic | C73: NETHERLANS | D73: ='Export · detalle'!D20 -> 2 | E73: =IFERROR('Export · países'!F20/'Export · países'!C20,0) -> 4413 | F73: =D73*E73 -> 8826
A74: 2026 | B74: Dic | C74: PANAMÁ | D74: ='Export · detalle'!D21 -> 0 | E74: =IFERROR('Export · países'!F21/'Export · países'!C21,0) -> 3449 | F74: =D74*E74 -> 0
A75: 2026 | B75: Dic | C75: TURQUÍA | D75: ='Export · detalle'!D25 -> 2 | E75: =IFERROR('Export · países'!F25/'Export · países'!C25,0) -> 1699 | F75: =D75*E75 -> 3398
A76: 2027 | B76: Ene | C76: ARABIA SAUDÍ | D76: ='Export · detalle'!B31 -> 0 | E76: =IFERROR('Export · países'!K7/'Export · países'!H7,0) -> 54 | F76: =D76*E76 -> 0
A77: 2027 | B77: Ene | C77: AZERBAIYÁN | D77: ='Export · detalle'!B32 -> 3 | E77: =IFERROR('Export · países'!K8/'Export · países'!H8,0) -> 1866.1 | F77: =D77*E77 -> 5598.3
A78: 2027 | B78: Ene | C78: COSTA RICA | D78: ='Export · detalle'!B35 -> 2 | E78: =IFERROR('Export · países'!K11/'Export · países'!H11,0) -> 4235 | F78: =D78*E78 -> 8470
A79: 2027 | B79: Ene | C79: DOMINICANA, REPÚBLICA | D79: ='Export · detalle'!B36 -> 0 | E79: =IFERROR('Export · países'!K12/'Export · países'!H12,0) -> 4042.5 | F79: =D79*E79 -> 0
A80: 2027 | B80: Ene | C80: ECUADOR (incluidas las Islas Galápagos) | D80: ='Export · detalle'!B37 -> 1 | E80: =IFERROR('Export · países'!K13/'Export · países'!H13,0) -> 104 | F80: =D80*E80 -> 104
A81: 2027 | B81: Ene | C81: EGIPTO | D81: ='Export · detalle'!B38 -> 6 | E81: =IFERROR('Export · países'!K14/'Export · países'!H14,0) -> 179 | F81: =D81*E81 -> 1074
A82: 2027 | B82: Ene | C82: ITALIA | D82: ='Export · detalle'!B41 -> 0 | E82: =IFERROR('Export · países'!K17/'Export · países'!H17,0) -> 535.7 | F82: =D82*E82 -> 0
A83: 2027 | B83: Ene | C83: LÍBANO | D83: ='Export · detalle'!B42 -> 0 | E83: =IFERROR('Export · países'!K18/'Export · países'!H18,0) -> 1726.5 | F83: =D83*E83 -> 0
A84: 2027 | B84: Ene | C84: NETHERLANS | D84: ='Export · detalle'!B44 -> 3 | E84: =IFERROR('Export · países'!K20/'Export · países'!H20,0) -> 4854.3 | F84: =D84*E84 -> 14562.9
A85: 2027 | B85: Ene | C85: PANAMÁ | D85: ='Export · detalle'!B45 -> 0 | E85: =IFERROR('Export · países'!K21/'Export · países'!H21,0) -> 3783.5 | F85: =D85*E85 -> 0
A86: 2027 | B86: Ene | C86: TURQUÍA | D86: ='Export · detalle'!B49 -> 0 | E86: =IFERROR('Export · países'!K25/'Export · países'!H25,0) -> 1724 | F86: =D86*E86 -> 0
A87: 2027 | B87: Feb | C87: ARABIA SAUDÍ | D87: ='Export · detalle'!C31 -> 0 | E87: =IFERROR('Export · países'!K7/'Export · países'!H7,0) -> 54 | F87: =D87*E87 -> 0
A88: 2027 | B88: Feb | C88: AZERBAIYÁN | D88: ='Export · detalle'!C32 -> 0 | E88: =IFERROR('Export · países'!K8/'Export · países'!H8,0) -> 1866.1 | F88: =D88*E88 -> 0
A89: 2027 | B89: Feb | C89: COSTA RICA | D89: ='Export · detalle'!C35 -> 0 | E89: =IFERROR('Export · países'!K11/'Export · países'!H11,0) -> 4235 | F89: =D89*E89 -> 0
A90: 2027 | B90: Feb | C90: DOMINICANA, REPÚBLICA | D90: ='Export · detalle'!C36 -> 2 | E90: =IFERROR('Export · países'!K12/'Export · países'!H12,0) -> 4042.5 | F90: =D90*E90 -> 8085
A91: 2027 | B91: Feb | C91: ECUADOR (incluidas las Islas Galápagos) | D91: ='Export · detalle'!C37 -> 0 | E91: =IFERROR('Export · países'!K13/'Export · países'!H13,0) -> 104 | F91: =D91*E91 -> 0
A92: 2027 | B92: Feb | C92: EGIPTO | D92: ='Export · detalle'!C38 -> 9 | E92: =IFERROR('Export · países'!K14/'Export · países'!H14,0) -> 179 | F92: =D92*E92 -> 1611
A93: 2027 | B93: Feb | C93: ITALIA | D93: ='Export · detalle'!C41 -> 1 | E93: =IFERROR('Export · países'!K17/'Export · países'!H17,0) -> 535.7 | F93: =D93*E93 -> 535.7
A94: 2027 | B94: Feb | C94: LÍBANO | D94: ='Export · detalle'!C42 -> 0 | E94: =IFERROR('Export · países'!K18/'Export · países'!H18,0) -> 1726.5 | F94: =D94*E94 -> 0
A95: 2027 | B95: Feb | C95: NETHERLANS | D95: ='Export · detalle'!C44 -> 0 | E95: =IFERROR('Export · países'!K20/'Export · países'!H20,0) -> 4854.3 | F95: =D95*E95 -> 0
A96: 2027 | B96: Feb | C96: PANAMÁ | D96: ='Export · detalle'!C45 -> 2 | E96: =IFERROR('Export · países'!K21/'Export · países'!H21,0) -> 3783.5 | F96: =D96*E96 -> 7567
A97: 2027 | B97: Feb | C97: TURQUÍA | D97: ='Export · detalle'!C49 -> 2 | E97: =IFERROR('Export · países'!K25/'Export · países'!H25,0) -> 1724 | F97: =D97*E97 -> 3448
A98: 2027 | B98: Mar | C98: ARABIA SAUDÍ | D98: ='Export · detalle'!D31 -> 0 | E98: =IFERROR('Export · países'!K7/'Export · países'!H7,0) -> 54 | F98: =D98*E98 -> 0
A99: 2027 | B99: Mar | C99: AZERBAIYÁN | D99: ='Export · detalle'!D32 -> 0 | E99: =IFERROR('Export · países'!K8/'Export · países'!H8,0) -> 1866.1 | F99: =D99*E99 -> 0
A100: 2027 | B100: Mar | C100: COSTA RICA | D100: ='Export · detalle'!D35 -> 2 | E100: =IFERROR('Export · países'!K11/'Export · países'!H11,0) -> 4235 | F100: =D100*E100 -> 8470
A101: 2027 | B101: Mar | C101: DOMINICANA, REPÚBLICA | D101: ='Export · detalle'!D36 -> 0 | E101: =IFERROR('Export · países'!K12/'Export · países'!H12,0) -> 4042.5 | F101: =D101*E101 -> 0
A102: 2027 | B102: Mar | C102: ECUADOR (incluidas las Islas Galápagos) | D102: ='Export · detalle'!D37 -> 2 | E102: =IFERROR('Export · países'!K13/'Export · países'!H13,0) -> 104 | F102: =D102*E102 -> 208
A103: 2027 | B103: Mar | C103: EGIPTO | D103: ='Export · detalle'!D38 -> 4 | E103: =IFERROR('Export · países'!K14/'Export · países'!H14,0) -> 179 | F103: =D103*E103 -> 716
A104: 2027 | B104: Mar | C104: ITALIA | D104: ='Export · detalle'!D41 -> 1 | E104: =IFERROR('Export · países'!K17/'Export · países'!H17,0) -> 535.7 | F104: =D104*E104 -> 535.7
A105: 2027 | B105: Mar | C105: LÍBANO | D105: ='Export · detalle'!D42 -> 0 | E105: =IFERROR('Export · países'!K18/'Export · países'!H18,0) -> 1726.5 | F105: =D105*E105 -> 0
A106: 2027 | B106: Mar | C106: NETHERLANS | D106: ='Export · detalle'!D44 -> 2 | E106: =IFERROR('Export · países'!K20/'Export · países'!H20,0) -> 4854.3 | F106: =D106*E106 -> 9708.6
A107: 2027 | B107: Mar | C107: PANAMÁ | D107: ='Export · detalle'!D45 -> 0 | E107: =IFERROR('Export · países'!K21/'Export · países'!H21,0) -> 3783.5 | F107: =D107*E107 -> 0
...

Sheet Export · detalle
A2: Envíos previstos de exportación
A3: Por país y mes · máximo 21 palets por envío · España excluida
A5: 2026 · octubre a diciembre
A6: País | B6: Oct | C6: Nov | D6: Dic | E6: Total 2026
A7: ARABIA SAUDÍ | B7: =ROUNDUP(SUMIFS('Export · base'!$H$7:$H$408,'Export · base'!$A$7:$A$408,2026,'Export · base'!$B$7:$B$408,10,'Export · base'!$C$7:$C$408,$A7)/'Export · supuestos'!$B$5,0) -> 0 | C7: =ROUNDUP(SUMIFS('Export · base'!$H$7:$H$408,'Export · base'!$A$7:$A$408,2026,'Export · base'!$B$7:$B$408,11,'Export · base'!$C$7:$C$408,$A7)/'Export · supuestos'!$B$5,0) -> 0 | D7: =ROUNDUP(SUMIFS('Export · base'!$H$7:$H$408,'Export · base'!$A$7:$A$408,2026,'Export · base'!$B$7:$B$408,12,'Export · base'!$C$7:$C$408,$A7)/'Export · supuestos'!$B$5,0) -> 0 | E7: =SUM(B7:D7) -> 0
A8: AZERBAIYÁN | B8: =ROUNDUP(SUMIFS('Export · base'!$H$7:$H$408,'Export · base'!$A$7:$A$408,2026,'Export · base'!$B$7:$B$408,10,'Export · base'!$C$7:$C$408,$A8)/'Export · supuestos'!$B$5,0) -> 0 | C8: =ROUNDUP(SUMIFS('Export · base'!$H$7:$H$408,'Export · base'!$A$7:$A$408,2026,'Export · base'!$B$7:$B$408,11,'Export · base'!$C$7:$C$408,$A8)/'Export · supuestos'!$B$5,0) -> 0 | D8: =ROUNDUP(SUMIFS('Export · base'!$H$7:$H$408,'Export · base'!$A$7:$A$408,2026,'Export · base'!$B$7:$B$408,12,'Export · base'!$C$7:$C$408,$A8)/'Export · supuestos'!$B$5,0) -> 2 | E8: =SUM(B8:D8) -> 2
A9: CHILE | B9: =ROUNDUP(SUMIFS('Export · base'!$H$7:$H$408,'Export · base'!$A$7:$A$408,2026,'Export · base'!$B$7:$B$408,10,'Export · base'!$C$7:$C$408,$A9)/'Export · supuestos'!$B$5,0) -> 0 | C9: =ROUNDUP(SUMIFS('Export · base'!$H$7:$H$408,'Export · base'!$A$7:$A$408,2026,'Export · base'!$B$7:$B$408,11,'Export · base'!$C$7:$C$408,$A9)/'Export · supuestos'!$B$5,0) -> 0 | D9: =ROUNDUP(SUMIFS('Export · base'!$H$7:$H$408,'Export · base'!$A$7:$A$408,2026,'Export · base'!$B$7:$B$408,12,'Export · base'!$C$7:$C$408,$A9)/'Export · supuestos'!$B$5,0) -> 10 | E9: =SUM(B9:D9) -> 10
A10: COLOMBIA | B10: =ROUNDUP(SUMIFS('Export · base'!$H$7:$H$408,'Export · base'!$A$7:$A$408,2026,'Export · base'!$B$7:$B$408,10,'Export · base'!$C$7:$C$408,$A10)/'Export · supuestos'!$B$5,0) -> 0 | C10: =ROUNDUP(SUMIFS('Export · base'!$H$7:$H$408,'Export · base'!$A$7:$A$408,2026,'Export · base'!$B$7:$B$408,11,'Export · base'!$C$7:$C$408,$A10)/'Export · supuestos'!$B$5,0) -> 2 | D10: =ROUNDUP(SUMIFS('Export · base'!$H$7:$H$408,'Export · base'!$A$7:$A$408,2026,'Export · base'!$B$7:$B$408,12,'Export · base'!$C$7:$C$408,$A10)/'Export · supuestos'!$B$5,0) -> 0 | E10: =SUM(B10:D10) -> 2
A11: COSTA RICA | B11: =ROUNDUP(SUMIFS('Export · base'!$H$7:$H$408,'Export · base'!$A$7:$A$408,2026,'Export · base'!$B$7:$B$408,10,'Export · base'!$C$7:$C$408,$A11)/'Export · supuestos'!$B$5,0) -> 3 | C11: =ROUNDUP(SUMIFS('Export · base'!$H$7:$H$408,'Export · base'!$A$7:$A$408,2026,'Export · base'!$B$7:$B$408,11,'Export · base'!$C$7:$C$408,$A11)/'Export · supuestos'!$B$5,0) -> 2 | D11: =ROUNDUP(SUMIFS('Export · base'!$H$7:$H$408,'Export · base'!$A$7:$A$408,2026,'Export · base'!$B$7:$B$408,12,'Export · base'!$C$7:$C$408,$A11)/'Export · supuestos'!$B$5,0) -> 2 | E11: =SUM(B11:D11) -> 7
A12: DOMINICANA, REPÚBLICA | B12: =ROUNDUP(SUMIFS('Export · base'!$H$7:$H$408,'Export · base'!$A$7:$A$408,2026,'Export · base'!$B$7:$B$408,10,'Export · base'!$C$7:$C$408,$A12)/'Export · supuestos'!$B$5,0) -> 0 | C12: =ROUNDUP(SUMIFS('Export · base'!$H$7:$H$408,'Export · base'!$A$7:$A$408,2026,'Export · base'!$B$7:$B$408,11,'Export · base'!$C$7:$C$408,$A12)/'Export · supuestos'!$B$5,0) -> 2 | D12: =ROUNDUP(SUMIFS('Export · base'!$H$7:$H$408,'Export · base'!$A$7:$A$408,2026,'Export · base'!$B$7:$B$408,12,'Export · base'!$C$7:$C$408,$A12)/'Export · supuestos'!$B$5,0) -> 0 | E12: =SUM(B12:D12) -> 2
A13: ECUADOR (incluidas las Islas Galápagos) | B13: =ROUNDUP(SUMIFS('Export · base'!$H$7:$H$408,'Export · base'!$A$7:$A$408,2026,'Export · base'!$B$7:$B$408,10,'Export · base'!$C$7:$C$408,$A13)/'Export · supuestos'!$B$5,0) -> 1 | C13: =ROUNDUP(SUMIFS('Export · base'!$H$7:$H$408,'Export · base'!$A$7:$A$408,2026,'Export · base'!$B$7:$B$408,11,'Export · base'!$C$7:$C$408,$A13)/'Export · supuestos'!$B$5,0) -> 0 | D13: =ROUNDUP(SUMIFS('Export · base'!$H$7:$H$408,'Export · base'!$A$7:$A$408,2026,'Export · base'!$B$7:$B$408,12,'Export · base'!$C$7:$C$408,$A13)/'Export · supuestos'!$B$5,0) -> 0 | E13: =SUM(B13:D13) -> 1
A14: EGIPTO | B14: =ROUNDUP(SUMIFS('Export · base'!$H$7:$H$408,'Export · base'!$A$7:$A$408,2026,'Export · base'!$B$7:$B$408,10,'Export · base'!$C$7:$C$408,$A14)/'Export · supuestos'!$B$5,0) -> 2 | C14: =ROUNDUP(SUMIFS('Export · base'!$H$7:$H$408,'Export · base'!$A$7:$A$408,2026,'Export · base'!$B$7:$B$408,11,'Export · base'!$C$7:$C$408,$A14)/'Export · supuestos'!$B$5,0) -> 4 | D14: =ROUNDUP(SUMIFS('Export · base'!$H$7:$H$408,'Export · base'!$A$7:$A$408,2026,'Export · base'!$B$7:$B$408,12,'Export · base'!$C$7:$C$408,$A14)/'Export · supuestos'!$B$5,0) -> 1 | E14: =SUM(B14:D14) -> 7
A15: GEORGIA | B15: =ROUNDUP(SUMIFS('Export · base'!$H$7:$H$408,'Export · base'!$A$7:$A$408,2026,'Export · base'!$B$7:$B$408,10,'Export · base'!$C$7:$C$408,$A15)/'Export · supuestos'!$B$5,0) -> 0 | C15: =ROUNDUP(SUMIFS('Export · base'!$H$7:$H$408,'Export · base'!$A$7:$A$408,2026,'Export · base'!$B$7:$B$408,11,'Export · base'!$C$7:$C$408,$A15)/'Export · supuestos'!$B$5,0) -> 0 | D15: =ROUNDUP(SUMIFS('Export · base'!$H$7:$H$408,'Export · base'!$A$7:$A$408,2026,'Export · base'!$B$7:$B$408,12,'Export · base'!$C$7:$C$408,$A15)/'Export · supuestos'!$B$5,0) -> 3 | E15: =SUM(B15:D15) -> 3
A16: GRECIA | B16: =ROUNDUP(SUMIFS('Export · base'!$H$7:$H$408,'Export · base'!$A$7:$A$408,2026,'Export · base'!$B$7:$B$408,10,'Export · base'!$C$7:$C$408,$A16)/'Export · supuestos'!$B$5,0) -> 0 | C16: =ROUNDUP(SUMIFS('Export · base'!$H$7:$H$408,'Export · base'!$A$7:$A$408,2026,'Export · base'!$B$7:$B$408,11,'Export · base'!$C$7:$C$408,$A16)/'Export · supuestos'!$B$5,0) -> 0 | D16: =ROUNDUP(SUMIFS('Export · base'!$H$7:$H$408,'Export · base'!$A$7:$A$408,2026,'Export · base'!$B$7:$B$408,12,'Export · base'!$C$7:$C$408,$A16)/'Export · supuestos'!$B$5,0) -> 2 | E16: =SUM(B16:D16) -> 2
A17: ITALIA | B17: =ROUNDUP(SUMIFS('Export · base'!$H$7:$H$408,'Export · base'!$A$7:$A$408,2026,'Export · base'!$B$7:$B$408,10,'Export · base'!$C$7:$C$408,$A17)/'Export · supuestos'!$B$5,0) -> 1 | C17: =ROUNDUP(SUMIFS('Export · base'!$H$7:$H$408,'Export · base'!$A$7:$A$408,2026,'Export · base'!$B$7:$B$408,11,'Export · base'!$C$7:$C$408,$A17)/'Export · supuestos'!$B$5,0) -> 0 | D17: =ROUNDUP(SUMIFS('Export · base'!$H$7:$H$408,'Export · base'!$A$7:$A$408,2026,'Export · base'!$B$7:$B$408,12,'Export · base'!$C$7:$C$408,$A17)/'Export · supuestos'!$B$5,0) -> 1 | E17: =SUM(B17:D17) -> 2
A18: LÍBANO | B18: =ROUNDUP(SUMIFS('Export · base'!$H$7:$H$408,'Export · base'!$A$7:$A$408,2026,'Export · base'!$B$7:$B$408,10,'Export · base'!$C$7:$C$408,$A18)/'Export · supuestos'!$B$5,0) -> 0 | C18: =ROUNDUP(SUMIFS('Export · base'!$H$7:$H$408,'Export · base'!$A$7:$A$408,2026,'Export · base'!$B$7:$B$408,11,'Export · base'!$C$7:$C$408,$A18)/'Export · supuestos'!$B$5,0) -> 0 | D18: =ROUNDUP(SUMIFS('Export · base'!$H$7:$H$408,'Export · base'!$A$7:$A$408,2026,'Export · base'!$B$7:$B$408,12,'Export · base'!$C$7:$C$408,$A18)/'Export · supuestos'!$B$5,0) -> 2 | E18: =SUM(B18:D18) -> 2
... A25: TURQUÍA | B25: =ROUNDUP(SUMIFS('Export · base'!$H$7:$H$408,'Export · base'!$A$7:$A$408,2026,'Export · base'!$B$7:$B$408,10,'Export · base'!$C$7:$C$408,$A25)/'Export · supuestos'!$B$5,0) -> 0 | C25: =ROUNDUP(SUMIFS('Export · base'!$H$7:$H$408,'Export · base'!$A$7:$A$408,2026,'Export · base'!$B$7:$B$408,11,'Export · base'!$C$7:$C$408,$A25)/'Export · supuestos'!$B$5,0) -> 0 | D25: =ROUNDUP(SUMIFS('Export · base'!$H$7:$H$408,'Export · base'!$A$7:$A$408,2026,'Export · base'!$B$7:$B$408,12,'Export · base'!$C$7:$C$408,$A25)/'Export · supuestos'!$B$5,0) -> 2 | E25: =SUM(B25:D25) -> 2
A26: TOTAL | B26: =SUM(B7:B25) -> 10 | C26: =SUM(C7:C25) -> 16 | D26: =SUM(D7:D25) -> 30 | E26: =SUM(E7:E25) -> 56
A29: 2027 · enero a diciembre
A30: País | B30: Ene | C30: Feb | D30: Mar | E30: Abr | F30: May | G30: Jun | H30: Jul | I30: Ago | J30: Sep | K30: Oct | L30: Nov | M30: Dic | N30: Total 2027
A31: ARABIA SAUDÍ | B31: =ROUNDUP(SUMIFS('Export · base'!$H$7:$H$408,'Export · base'!$A$7:$A$408,2027,'Export · base'!$B$7:$B$408,1,'Export · base'!$C$7:$C$408,$A31)/'Export · supuestos'!$B$5,0) -> 0 | C31: =ROUNDUP(SUMIFS('Export · base'!$H$7:$H$408,'Export · base'!$A$7:$A$408,2027,'Export · base'!$B$7:$B$408,2,'Export · base'!$C$7:$C$408,$A31)/'Export · supuestos'!$B$5,0) -> 0 | D31: =ROUNDUP(SUMIFS('Export · base'!$H$7:$H$408,'Export · base'!$A$7:$A$408,2027,'Export · base'!$B$7:$B$408,3,'Export · base'!$C$7:$C$408,$A31)/'Export · supuestos'!$B$5,0) -> 0 | E31: =ROUNDUP(SUMIFS('Export · base'!$H$7:$H$408,'Export · base'!$A$7:$A$408,2027,'Export · base'!$B$7:$B$408,4,'Export · base'!$C$7:$C$408,$A31)/'Export · supuestos'!$B$5,0) -> 2 | F31: =ROUNDUP(SUMIFS('Export · base'!$H$7:$H$408,'Export · base'!$A$7:$A$408,2027,'Export · base'!$B$7:$B$408,5,'Export · base'!$C$7:$C$408,$A31)/'Export · supuestos'!$B$5,0) -> 0 | G31: =ROUNDUP(SUMIFS('Export · base'!$H$7:$H$408,'Export · base'!$A$7:$A$408,2027,'Export · base'!$B$7:$B$408,6,'Export · base'!$C$7:$C$408,$A31)/'Export · supuestos'!$B$5,0) -> 0 | H31: =ROUNDUP(SUMIFS('Export · base'!$H$7:$H$408,'Export · base'!$A$7:$A$408,2027,'Export · base'!$B$7:$B$408,7,'Export · base'!$C$7:$C$408,$A31)/'Export · supuestos'!$B$5,0) -> 0 | I31: =ROUNDUP(SUMIFS('Export · base'!$H$7:$H$408,'Export · base'!$A$7:$A$408,2027,'Export · base'!$B$7:$B$408,8,'Export · base'!$C$7:$C$408,$A31)/'Export · supuestos'!$B$5,0) -> 0 | J31: =ROUNDUP(SUMIFS('Export · base'!$H$7:$H$408,'Export · base'!$A$7:$A$408,2027,'Export · base'!$B$7:$B$408,9,'Export · base'!$C$7:$C$408,$A31)/'Export · supuestos'!$B$5,0) -> 0 | K31: =ROUNDUP(SUMIFS('Export · base'!$H$7:$H$408,'Export · base'!$A$7:$A$408,2027,'Export · base'!$B$7:$B$408,10,'Export · base'!$C$7:$C$408,$A31)/'Export · supuestos'!$B$5,0) -> 0 | L31: =ROUNDUP(SUMIFS('Export · base'!$H$7:$H$408,'Export · base'!$A$7:$A$408,2027,'Export · base'!$B$7:$B$408,11,'Export · base'!$C$7:$C$408,$A31)/'Export · supuestos'!$B$5,0) -> 0 | M31: =ROUNDUP(SUMIFS('Export · base'!$H$7:$H$408,'Export · base'!$A$7:$A$408,2027,'Export · base'!$B$7:$B$408,12,'Export · base'!$C$7:$C$408,$A31)/'Export · supuestos'!$B$5,0) -> 0 | N31: =SUM(B31:M31) -> 2
A32: AZERBAIYÁN | B32: =ROUNDUP(SUMIFS('Export · base'!$H$7:$H$408,'Export · base'!$A$7:$A$408,2027,'Export · base'!$B$7:$B$408,1,'Export · base'!$C$7:$C$408,$A32)/'Export · supuestos'!$B$5,0) -> 3 | C32: =ROUNDUP(SUMIFS('Export · base'!$H$7:$H$408,'Export · base'!$A$7:$A$408,2027,'Export · base'!$B$7:$B$408,2,'Export · base'!$C$7:$C$408,$A32)/'Export · supuestos'!$B$5,0) -> 0 | D32: =ROUNDUP(SUMIFS('Export · base'!$H$7:$H$408,'Export · base'!$A$7:$A$408,2027,'Export · base'!$B$7:$B$408,3,'Export · base'!$C$7:$C$408,$A32)/'Export · supuestos'!$B$5,0) -> 0 | E32: =ROUNDUP(SUMIFS('Export · base'!$H$7:$H$408,'Export · base'!$A$7:$A$408,2027,'Export · base'!$B$7:$B$408,4,'Export · base'!$C$7:$C$408,$A32)/'Export · supuestos'!$B$5,0) -> 2 | F32: =ROUNDUP(SUMIFS('Export · base'!$H$7:$H$408,'Export · base'!$A$7:$A$408,2027,'Export · base'!$B$7:$B$408,5,'Export · base'!$C$7:$C$408,$A32)/'Export · supuestos'!$B$5,0) -> 2 | G32: =ROUNDUP(SUMIFS('Export · base'!$H$7:$H$408,'Export · base'!$A$7:$A$408,2027,'Export · base'!$B$7:$B$408,6,'Export · base'!$C$7:$C$408,$A32)/'Export · supuestos'!$B$5,0) -> 7 | H32: =ROUNDUP(SUMIFS('Export · base'!$H$7:$H$408,'Export · base'!$A$7:$A$408,2027,'Export · base'!$B$7:$B$408,7,'Export · base'!$C$7:$C$408,$A32)/'Export · supuestos'!$B$5,0) -> 3 | I32: =ROUNDUP(SUMIFS('Export · base'!$H$7:$H$408,'Export · base'!$A$7:$A$408,2027,'Export · base'!$B$7:$B$408,8,'Export · base'!$C$7:$C$408,$A32)/'Export · supuestos'!$B$5,0) -> 0 | J32: =ROUNDUP(SUMIFS('Export · base'!$H$7:$H$408,'Export · base'!$A$7:$A$408,2027,'Export · base'!$B$7:$B$408,9,'Export · base'!$C$7:$C$408,$A32)/'Export · supuestos'!$B$5,0) -> 0 | K32: =ROUNDUP(SUMIFS('Export · base'!$H$7:$H$408,'Export · base'!$A$7:$A$408,2027,'Export · base'!$B$7:$B$408,10,'Export · base'!$C$7:$C$408,$A32)/'Export · supuestos'!$B$5,0) -> 0 | L32: =ROUNDUP(SUMIFS('Export · base'!$H$7:$H$408,'Export · base'!$A$7:$A$408,2027,'Export · base'!$B$7:$B$408,11,'Export · base'!$C$7:$C$408,$A32)/'Export · supuestos'!$B$5,0) -> 0 | M32: =ROUNDUP(SUMIFS('Export · base'!$H$7:$H$408,'Export · base'!$A$7:$A$408,2027,'Export · base'!$B$7:$B$408,12,'Export · base'!$C$7:$C$408,$A32)/'Export · supuestos'!$B$5,0) -> 2 | N32: =SUM(B32:M32) -> 19
A33: CHILE | B33: =ROUNDUP(SUMIFS('Export · base'!$H$7:$H$408,'Export · base'!$A$7:$A$408,2027,'Export · base'!$B$7:$B$408,1,'Export · base'!$C$7:$C$408,$A33)/'Export · supuestos'!$B$5,0) -> 0 | C33: =ROUNDUP(SUMIFS('Export · base'!$H$7:$H$408,'Export · base'!$A$7:$A$408,2027,'Export · base'!$B$7:$B$408,2,'Export · base'!$C$7:$C$408,$A33)/'Export · supuestos'!$B$5,0) -> 0 | D33: =ROUNDUP(SUMIFS('Export · base'!$H$7:$H$408,'Export · base'!$A$7:$A$408,2027,'Export · base'!$B$7:$B$408,3,'Export · base'!$C$7:$C$408,$A33)/'Export · supuestos'!$B$5,0) -> 21 | E33: =ROUNDUP(SUMIFS('Export · base'!$H$7:$H$408,'Export · base'!$A$7:$A$408,2027,'Export · base'!$B$7:$B$408,4,'Export · base'!$C$7:$C$408,$A33)/'Export · supuestos'!$B$5,0) -> 10 | F33: =ROUNDUP(SUMIFS('Export · base'!$H$7:$H$408,'Export · base'!$A$7:$A$408,2027,'Export · base'!$B$7:$B$408,5,'Export · base'!$C$7:$C$408,$A33)/'Export · supuestos'!$B$5,0) -> 16 | G33: =ROUNDUP(SUMIFS('Export · base'!$H$7:$H$408,'Export · base'!$A$7:$A$408,2027,'Export · base'!$B$7:$B$408,6,'Export · base'!$C$7:$C$408,$A33)/'Export · supuestos'!$B$5,0) -> 14 | H33: =ROUNDUP(SUMIFS('Export · base'!$H$7:$H$408,'Export · base'!$A$7:$A$408,2027,'Export · base'!$B$7:$B$408,7,'Export · base'!$C$7:$C$408,$A33)/'Export · supuestos'!$B$5,0) -> 10 | I33: =ROUNDUP(SUMIFS('Export · base'!$H$7:$H$408,'Export · base'!$A$7:$A$408,2027,'Export · base'!$B$7:$B$408,8,'Export · base'!$C$7:$C$408,$A33)/'Export · supuestos'!$B$5,0) -> 0 | J33: =ROUNDUP(SUMIFS('Export · base'!$H$7:$H$408,'Export · base'!$A$7:$A$408,2027,'Export · base'!$B$7:$B$408,9,'Export · base'!$C$7:$C$408,$A33)/'Export · supuestos'!$B$5,0) -> 0 | K33: =ROUNDUP(SUMIFS('Export · base'!$H$7:$H$408,'Export · base'!$A$7:$A$408,2027,'Export · base'!$B$7:$B$408,10,'Export · base'!$C$7:$C$408,$A33)/'Export · supuestos'!$B$5,0) -> 0 | L33: =ROUNDUP(SUMIFS('Export · base'!$H$7:$H$408,'Export · base'!$A$7:$A$408,2027,'Export · base'!$B$7:$B$408,11,'Export · base'!$C$7:$C$408,$A33)/'Export · supuestos'!$B$5,0) -> 0 | M33: =ROUNDUP(SUMIFS('Export · base'!$H$7:$H$408,'Export · base'!$A$7:$A$408,2027,'Export · base'!$B$7:$B$408,12,'Export · base'!$C$7:$C$408,$A33)/'Export · supuestos'!$B$5,0) -> 12 | N33: =SUM(B33:M33) -> 83
A34: COLOMBIA | B34: =ROUNDUP(SUMIFS('Export · base'!$H$7:$H$408,'Export · base'!$A$7:$A$408,2027,'Export · base'!$B$7:$B$408,1,'Export · base'!$C$7:$C$408,$A34)/'Export · supuestos'!$B$5,0) -> 0 | C34: =ROUNDUP(SUMIFS('Export · base'!$H$7:$H$408,'Export · base'!$A$7:$A$408,2027,'Export · base'!$B$7:$B$408,2,'Export · base'!$C$7:$C$408,$A34)/'Export · supuestos'!$B$5,0) -> 0 | D34: =ROUNDUP(SUMIFS('Export · base'!$H$7:$H$408,'Export · base'!$A$7:$A$408,2027,'Export · base'!$B$7:$B$408,3,'Export · base'!$C$7:$C$408,$A34)/'Export · supuestos'!$B$5,0) -> 0 | E34: =ROUNDUP(SUMIFS('Export · base'!$H$7:$H$408,'Export · base'!$A$7:$A$408,2027,'Export · base'!$B$7:$B$408,4,'Export · base'!$C$7:$C$408,$A34)/'Export · supuestos'!$B$5,0) -> 0 | F34: =ROUNDUP(SUMIFS('Export · base'!$H$7:$H$408,'Export · base'!$A$7:$A$408,2027,'Export · base'!$B$7:$B$408,5,'Export · base'!$C$7:$C$408,$A34)/'Export · supuestos'!$B$5,0) -> 2 | G34: =ROUNDUP(SUMIFS('Export · base'!$H$7:$H$408,'Export · base'!$A$7:$A$408,2027,'Export · base'!$B$7:$B$408,6,'Export · base'!$C$7:$C$408,$A34)/'Export · supuestos'!$B$5,0) -> 0 | H34: =ROUNDUP(SUMIFS('Export · base'!$H$7:$H$408,'Export · base'!$A$7:$A$408,2027,'Export · base'!$B$7:$B$408,7,'Export · base'!$C$7:$C$408,$A34)/'Export · supuestos'!$B$5,0) -> 0 | I34: =ROUNDUP(SUMIFS('Export · base'!$H$7:$H$408,'Export · base'!$A$7:$A$408,2027,'Export · base'!$B$7:$B$408,8,'Export · base'!$C$7:$C$408,$A34)/'Export · supuestos'!$B$5,0) -> 2 | J34: =ROUNDUP(SUMIFS('Export · base'!$H$7:$H$408,'Export · base'!$A$7:$A$408,2027,'Export · base'!$B$7:$B$408,9,'Export · base'!$C$7:$C$408,$A34)/'Export · supuestos'!$B$5,0) -> 0 | K34: =ROUNDUP(SUMIFS('Export · base'!$H$7:$H$408,'Export · base'!$A$7:$A$408,2027,'Export · base'!$B$7:$B$408,10,'Export · base'!$C$7:$C$408,$A34)/'Export · supuestos'!$B$5,0) -> 0 | L34: =ROUNDUP(SUMIFS('Export · base'!$H$7:$H$408,'Export · base'!$A$7:$A$408,2027,'Export · base'!$B$7:$B$408,11,'Export · base'!$C$7:$C$408,$A34)/'Export · supuestos'!$B$5,0) -> 2 | M34: =ROUNDUP(SUMIFS('Export · base'!$H$7:$H$408,'Export · base'!$A$7:$A$408,2027,'Export · base'!$B$7:$B$408,12,'Export · base'!$C$7:$C$408,$A34)/'Export · supuestos'!$B$5,0) -> 0 | N34: =SUM(B34:M34) -> 6
A35: COSTA RICA | B35: =ROUNDUP(SUMIFS('Export · base'!$H$7:$H$408,'Export · base'!$A$7:$A$408,2027,'Export · base'!$B$7:$B$408,1,'Export · base'!$C$7:$C$408,$A35)/'Export · supuestos'!$B$5,0) -> 2 | C35: =ROUNDUP(SUMIFS('Export · base'!$H$7:$H$408,'Export · base'!$A$7:$A$408,2027,'Export · base'!$B$7:$B$408,2,'Export · base'!$C$7:$C$408,$A35)/'Export · supuestos'!$B$5,0) -> 0 | D35: =ROUNDUP(SUMIFS('Export · base'!$H$7:$H$408,'Export · base'!$A$7:$A$408,2027,'Export · base'!$B$7:$B$408,3,'Export · base'!$C$7:$C$408,$A35)/'Export · supuestos'!$B$5,0) -> 2 | E35: =ROUNDUP(SUMIFS('Export · base'!$H$7:$H$408,'Export · base'!$A$7:$A$408,2027,'Export · base'!$B$7:$B$408,4,'Export · base'!$C$7:$C$408,$A35)/'Export · supuestos'!$B$5,0) -> 0 | F35: =ROUNDUP(SUMIFS('Export · base'!$H$7:$H$408,'Export · base'!$A$7:$A$408,2027,'Export · base'!$B$7:$B$408,5,'Export · base'!$C$7:$C$408,$A35)/'Export · supuestos'!$B$5,0) -> 2 | G35: =ROUNDUP(SUMIFS('Export · base'!$H$7:$H$408,'Export · base'!$A$7:$A$408,2027,'Export · base'!$B$7:$B$408,6,'Export · base'!$C$7:$C$408,$A35)/'Export · supuestos'!$B$5,0) -> 2 | H35: =ROUNDUP(SUMIFS('Export · base'!$H$7:$H$408,'Export · base'!$A$7:$A$408,2027,'Export · base'!$B$7:$B$408,7,'Export · base'!$C$7:$C$408,$A35)/'Export · supuestos'!$B$5,0) -> 0 | I35: =ROUNDUP(SUMIFS('Export · base'!$H$7:$H$408,'Export · base'!$A$7:$A$408,2027,'Export · base'!$B$7:$B$408,8,'Export · base'!$C$7:$C$408,$A35)/'Export · supuestos'!$B$5,0) -> 0 | J35: =ROUNDUP(SUMIFS('Export · base'!$H$7:$H$408,'Export · base'!$A$7:$A$408,2027,'Export · base'!$B$7:$B$408,9,'Export · base'!$C$7:$C$408,$A35)/'Export · supuestos'!$B$5,0) -> 1 | K35: =ROUNDUP(SUMIFS('Export · base'!$H$7:$H$408,'Export · base'!$A$7:$A$408,2027,'Export · base'!$B$7:$B$408,10,'Export · base'!$C$7:$C$408,$A35)/'Export · supuestos'!$B$5,0) -> 3 | L35: =ROUNDUP(SUMIFS('Export · base'!$H$7:$H$408,'Export · base'!$A$7:$A$408,2027,'Export · base'!$B$7:$B$408,11,'Export · base'!$C$7:$C$408,$A35)/'Export · supuestos'!$B$5,0) -> 2 | M35: =ROUNDUP(SUMIFS('Export · base'!$H$7:$H$408,'Export · base'!$A$7:$A$408,2027,'Export · base'!$B$7:$B$408,12,'Export · base'!$C$7:$C$408,$A35)/'Export · supuestos'!$B$5,0) -> 2 | N35: =SUM(B35:M35) -> 16
A36: DOMINICANA, REPÚBLICA | B36: =ROUNDUP(SUMIFS('Export · base'!$H$7:$H$408,'Export · base'!$A$7:$A$408,2027,'Export · base'!$B$7:$B$408,1,'Export · base'!$C$7:$C$408,$A36)/'Export · supuestos'!$B$5,0) -> 0 | C36: =ROUNDUP(SUMIFS('Export · base'!$H$7:$H$408,'Export · base'!$A$7:$A$408,2027,'Export · base'!$B$7:$B$408,2,'Export · base'!$C$7:$C$408,$A36)/'Export · supuestos'!$B$5,0) -> 2 | D36: =ROUNDUP(SUMIFS('Export · base'!$H$7:$H$408,'Export · base'!$A$7:$A$408,2027,'Export · base'!$B$7:$B$408,3,'Export · base'!$C$7:$C$408,$A36)/'Export · supuestos'!$B$5,0) -> 0 | E36: =ROUNDUP(SUMIFS('Export · base'!$H$7:$H$408,'Export · base'!$A$7:$A$408,2027,'Export · base'!$B$7:$B$408,4,'Export · base'!$C$7:$C$408,$A36)/'Export · supuestos'!$B$5,0) -> 0 | F36: =ROUNDUP(SUMIFS('Export · base'!$H$7:$H$408,'Export · base'!$A$7:$A$408,2027,'Export · base'!$B$7:$B$408,5,'Export · base'!$C$7:$C$408,$A36)/'Export · supuestos'!$B$5,0) -> 0 | G36: =ROUNDUP(SUMIFS('Export · base'!$H$7:$H$408,'Export · base'!$A$7:$A$408,2027,'Export · base'!$B$7:$B$408,6,'Export · base'!$C$7:$C$408,$A36)/'Export · supuestos'!$B$5,0) -> 0 | H36: =ROUNDUP(SUMIFS('Export · base'!$H$7:$H$408,'Export · base'!$A$7:$A$408,2027,'Export · base'!$B$7:$B$408,7,'Export · base'!$C$7:$C$408,$A36)/'Export · supuestos'!$B$5,0) -> 0 | I36: =ROUNDUP(SUMIFS('Export · base'!$H$7:$H$408,'Export · base'!$A$7:$A$408,2027,'Export · base'!$B$7:$B$408,8,'Export · base'!$C$7:$C$408,$A36)/'Export · supuestos'!$B$5,0) -> 2 | J36: =ROUNDUP(SUMIFS('Export · base'!$H$7:$H$408,'Export · base'!$A$7:$A$408,2027,'Export · base'!$B$7:$B$408,9,'Export · base'!$C$7:$C$408,$A36)/'Export · supuestos'!$B$5,0) -> 0 | K36: =ROUNDUP(SUMIFS('Export · base'!$H$7:$H$408,'Export · base'!$A$7:$A$408,2027,'Export · base'!$B$7:$B$408,10,'Export · base'!$C$7:$C$408,$A36)/'Export · supuestos'!$B$5,0) -> 0 | L36: =ROUNDUP(SUMIFS('Export · base'!$H$7:$H$408,'Export · base'!$A$7:$A$408,2027,'Export · base'!$B$7:$B$408,11,'Export · base'!$C$7:$C$408,$A36)/'Export · supuestos'!$B$5,0) -> 2 | M36: =ROUNDUP(SUMIFS('Export · base'!$H$7:$H$408,'Export · base'!$A$7:$A$408,2027,'Export · base'!$B$7:$B$408,12,'Export · base'!$C$7:$C$408,$A36)/'Export · supuestos'!$B$5,0) -> 0 | N36: =SUM(B36:M36) -> 6
A37: ECUADOR (incluidas las Islas Galápagos) | B37: =ROUNDUP(SUMIFS('Export · base'!$H$7:$H$408,'Export · base'!$A$7:$A$408,2027,'Export · base'!$B$7:$B$408,1,'Export · base'!$C$7:$C$408,$A37)/'Export · supuestos'!$B$5,0) -> 1 | C37: =ROUNDUP(SUMIFS('Export · base'!$H$7:$H$408,'Export · base'!$A$7:$A$408,2027,'Export · base'!$B$7:$B$408,2,'Export · base'!$C$7:$C$408,$A37)/'Export · supuestos'!$B$5,0) -> 0 | D37: =ROUNDUP(SUMIFS('Export · base'!$H$7:$H$408,'Export · base'!$A$7:$A$408,2027,'Export · base'!$B$7:$B$408,3,'Export · base'!$C$7:$C$408,$A37)/'Export · supuestos'!$B$5,0) -> 2 | E37: =ROUNDUP(SUMIFS('Export · base'!$H$7:$H$408,'Export · base'!$A$7:$A$408,2027,'Export · base'!$B$7:$B$408,4,'Export · base'!$C$7:$C$408,$A37)/'Export · supuestos'!$B$5,0) -> 0 | F37: =ROUNDUP(SUMIFS('Export · base'!$H$7:$H$408,'Export · base'!$A$7:$A$408,2027,'Export · base'!$B$7:$B$408,5,'Export · base'!$C$7:$C$408,$A37)/'Export · supuestos'!$B$5,0) -> 0 | G37: =ROUNDUP(SUMIFS('Export · base'!$H$7:$H$408,'Export · base'!$A$7:$A$408,2027,'Export · base'!$B$7:$B$408,6,'Export · base'!$C$7:$C$408,$A37)/'Export · supuestos'!$B$5,0) -> 1 | H37: =ROUNDUP(SUMIFS('Export · base'!$H$7:$H$408,'Export · base'!$A$7:$A$408,2027,'Export · base'!$B$7:$B$408,7,'Export · base'!$C$7:$C$408,$A37)/'Export · supuestos'!$B$5,0) -> 0 | I37: =ROUNDUP(SUMIFS('Export · base'!$H$7:$H$408,'Export · base'!$A$7:$A$408,2027,'Export · base'!$B$7:$B$408,8,'Export · base'!$C$7:$C$408,$A37)/'Export · supuestos'!$B$5,0) -> 0 | J37: =ROUNDUP(SUMIFS('Export · base'!$H$7:$H$408,'Export · base'!$A$7:$A$408,2027,'Export · base'!$B$7:$B$408,9,'Export · base'!$C$7:$C$408,$A37)/'Export · supuestos'!$B$5,0) -> 0 | K37: =ROUNDUP(SUMIFS('Export · base'!$H$7:$H$408,'Export · base'!$A$7:$A$408,2027,'Export · base'!$B$7:$B$408,10,'Export · base'!$C$7:$C$408,$A37)/'Export · supuestos'!$B$5,0) -> 1 | L37: =ROUNDUP(SUMIFS('Export · base'!$H$7:$H$408,'Export · base'!$A$7:$A$408,2027,'Export · base'!$B$7:$B$408,11,'Export · base'!$C$7:$C$408,$A37)/'Export · supuestos'!$B$5,0) -> 0 | M37: =ROUNDUP(SUMIFS('Export · base'!$H$7:$H$408,'Export · base'!$A$7:$A$408,2027,'Export · base'!$B$7:$B$408,12,'Export · base'!$C$7:$C$408,$A37)/'Export · supuestos'!$B$5,0) -> 0 | N37: =SUM(B37:M37) -> 5
A38: EGIPTO | B38: =ROUNDUP(SUMIFS('Export · base'!$H$7:$H$408,'Export · base'!$A$7:$A$408,2027,'Export · base'!$B$7:$B$408,1,'Export · base'!$C$7:$C$408,$A38)/'Export · supuestos'!$B$5,0) -> 6 | C38: =ROUNDUP(SUMIFS('Export · base'!$H$7:$H$408,'Export · base'!$A$7:$A$408,2027,'Export · base'!$B$7:$B$408,2,'Export · base'!$C$7:$C$408,$A38)/'Export · supuestos'!$B$5,0) -> 9 | D38: =ROUNDUP(SUMIFS('Export · base'!$H$7:$H$408,'Export · base'!$A$7:$A$408,2027,'Export · base'!$B$7:$B$408,3,'Export · base'!$C$7:$C$408,$A38)/'Export · supuestos'!$B$5,0) -> 4 | E38: =ROUNDUP(SUMIFS('Export · base'!$H$7:$H$408,'Export · base'!$A$7:$A$408,2027,'Export · base'!$B$7:$B$408,4,'Export · base'!$C$7:$C$408,$A38)/'Export · supuestos'!$B$5,0) -> 4 | F38: =ROUNDUP(SUMIFS('Export · base'!$H$7:$H$408,'Export · base'!$A$7:$A$408,2027,'Export · base'!$B$7:$B$408,5,'Export · base'!$C$7:$C$408,$A38)/'Export · supuestos'!$B$5,0) -> 6 | G38: =ROUNDUP(SUMIFS('Export · base'!$H$7:$H$408,'Export · base'!$A$7:$A$408,2027,'Export · base'!$B$7:$B$408,6,'Export · base'!$C$7:$C$408,$A38)/'Export · supuestos'!$B$5,0) -> 9 | H38: =ROUNDUP(SUMIFS('Export · base'!$H$7:$H$408,'Export · base'!$A$7:$A$408,2027,'Export · base'!$B$7:$B$408,7,'Export · base'!$C$7:$C$408,$A38)/'Export · supuestos'!$B$5,0) -> 4 | I38: =ROUNDUP(SUMIFS('Export · base'!$H$7:$H$408,'Export · base'!$A$7:$A$408,2027,'Export · base'!$B$7:$B$408,8,'Export · base'!$C$7:$C$408,$A38)/'Export · supuestos'!$B$5,0) -> 4 | J38: =ROUNDUP(SUMIFS('Export · base'!$H$7:$H$408,'Export · base'!$A$7:$A$408,2027,'Export · base'!$B$7:$B$408,9,'Export · base'!$C$7:$C$408,$A38)/'Export · supuestos'!$B$5,0) -> 1 | K38: =ROUNDUP(SUMIFS('Export · base'!$H$7:$H$408,'Export · base'!$A$7:$A$408,2027,'Export · base'!$B$7:$B$408,10,'Export · base'!$C$7:$C$408,$A38)/'Export · supuestos'!$B$5,0) -> 2 | L38: =ROUNDUP(SUMIFS('Export · base'!$H$7:$H$408,'Export · base'!$A$7:$A$408,2027,'Export · base'!$B$7:$B$408,11,'Export · base'!$C$7:$C$408,$A38)/'Export · supuestos'!$B$5,0) -> 5 | M38: =ROUNDUP(SUMIFS('Export · base'!$H$7:$H$408,'Export · base'!$A$7:$A$408,2027,'Export · base'!$B$7:$B$408,12,'Export · base'!$C$7:$C$408,$A38)/'Export · supuestos'!$B$5,0) -> 1 | N38: =SUM(B38:M38) -> 55
A39: GEORGIA | B39: =ROUNDUP(SUMIFS('Export · base'!$H$7:$H$408,'Export · base'!$A$7:$A$408,2027,'Export · base'!$B$7:$B$408,1,'Export · base'!$C$7:$C$408,$A39)/'Export · supuestos'!$B$5,0) -> 0 | C39: =ROUNDUP(SUMIFS('Export · base'!$H$7:$H$408,'Export · base'!$A$7:$A$408,2027,'Export · base'!$B$7:$B$408,2,'Export · base'!$C$7:$C$408,$A39)/'Export · supuestos'!$B$5,0) -> 3 | D39: =ROUNDUP(SUMIFS('Export · base'!$H$7:$H$408,'Export · base'!$A$7:$A$408,2027,'Export · base'!$B$7:$B$408,3,'Export · base'!$C$7:$C$408,$A39)/'Export · supuestos'!$B$5,0) -> 0 | E39: =ROUNDUP(SUMIFS('Export · base'!$H$7:$H$408,'Export · base'!$A$7:$A$408,2027,'Export · base'!$B$7:$B$408,4,'Export · base'!$C$7:$C$408,$A39)/'Export · supuestos'!$B$5,0) -> 0 | F39: =ROUNDUP(SUMIFS('Export · base'!$H$7:$H$408,'Export · base'!$A$7:$A$408,2027,'Export · base'!$B$7:$B$408,5,'Export · base'!$C$7:$C$408,$A39)/'Export · supuestos'!$B$5,0) -> 0 | G39: =ROUNDUP(SUMIFS('Export · base'!$H$7:$H$408,'Export · base'!$A$7:$A$408,2027,'Export · base'!$B$7:$B$408,6,'Export · base'!$C$7:$C$408,$A39)/'Export · supuestos'!$B$5,0) -> 0 | H39: =ROUNDUP(SUMIFS('Export · base'!$H$7:$H$408,'Export · base'!$A$7:$A$408,2027,'Export · base'!$B$7:$B$408,7,'Export · base'!$C$7:$C$408,$A39)/'Export · supuestos'!$B$5,0) -> 0 | I39: =ROUNDUP(SUMIFS('Export · base'!$H$7:$H$408,'Export · base'!$A$7:$A$408,2027,'Export · base'!$B$7:$B$408,8,'Export · base'!$C$7:$C$408,$A39)/'Export · supuestos'!$B$5,0) -> 0 | J39: =ROUNDUP(SUMIFS('Export · base'!$H$7:$H$408,'Export · base'!$A$7:$A$408,2027,'Export · base'!$B$7:$B$408,9,'Export · base'!$C$7:$C$408,$A39)/'Export · supuestos'!$B$5,0) -> 0 | K39: =ROUNDUP(SUMIFS('Export · base'!$H$7:$H$408,'Export · base'!$A$7:$A$408,2027,'Export · base'!$B$7:$B$408,10,'Export · base'!$C$7:$C$408,$A39)/'Export · supuestos'!$B$5,0) -> 0 | L39: =ROUNDUP(SUMIFS('Export · base'!$H$7:$H$408,'Export · base'!$A$7:$A$408,2027,'Export · base'!$B$7:$B$408,11,'Export · base'!$C$7:$C$408,$A39)/'Export · supuestos'!$B$5,0) -> 0 | M39: =ROUNDUP(SUMIFS('Export · base'!$H$7:$H$408,'Export · base'!$A$7:$A$408,2027,'Export · base'!$B$7:$B$408,12,'Export · base'!$C$7:$C$408,$A39)/'Export · supuestos'!$B$5,0) -> 3 | N39: =SUM(B39:M39) -> 6
A40: GRECIA | B40: =ROUNDUP(SUMIFS('Export · base'!$H$7:$H$408,'Export · base'!$A$7:$A$408,2027,'Export · base'!$B$7:$B$408,1,'Export · base'!$C$7:$C$408,$A40)/'Export · supuestos'!$B$5,0) -> 0 | C40: =ROUNDUP(SUMIFS('Export · base'!$H$7:$H$408,'Export · base'!$A$7:$A$408,2027,'Export · base'!$B$7:$B$408,2,'Export · base'!$C$7:$C$408,$A40)/'Export · supuestos'!$B$5,0) -> 2 | D40: =ROUNDUP(SUMIFS('Export · base'!$H$7:$H$408,'Export · base'!$A$7:$A$408,2027,'Export · base'!$B$7:$B$408,3,'Export · base'!$C$7:$C$408,$A40)/'Export · supuestos'!$B$5,0) -> 0 | E40: =ROUNDUP(SUMIFS('Export · base'!$H$7:$H$408,'Export · base'!$A$7:$A$408,2027,'Export · base'!$B$7:$B$408,4,'Export · base'!$C$7:$C$408,$A40)/'Export · supuestos'!$B$5,0) -> 0 | F40: =ROUNDUP(SUMIFS('Export · base'!$H$7:$H$408,'Export · base'!$A$7:$A$408,2027,'Export · base'!$B$7:$B$408,5,'Export · base'!$C$7:$C$408,$A40)/'Export · supuestos'!$B$5,0) -> 1 | G40: =ROUNDUP(SUMIFS('Export · base'!$H$7:$H$408,'Export · base'!$A$7:$A$408,2027,'Export · base'!$B$7:$B$408,6,'Export · base'!$C$7:$C$408,$A40)/'Export · supuestos'!$B$5,0) -> 0 | H40: =ROUNDUP(SUMIFS('Export · base'!$H$7:$H$408,'Export · base'!$A$7:$A$408,2027,'Export · base'!$B$7:$B$408,7,'Export · base'!$C$7:$C$408,$A40)/'Export · supuestos'!$B$5,0) -> 0 | I40: =ROUNDUP(SUMIFS('Export · base'!$H$7:$H$408,'Export · base'!$A$7:$A$408,2027,'Export · base'!$B$7:$B$408,8,'Export · base'!$C$7:$C$408,$A40)/'Export · supuestos'!$B$5,0) -> 0 | J40: =ROUNDUP(SUMIFS('Export · base'!$H$7:$H$408,'Export · base'!$A$7:$A$408,2027,'Export · base'!$B$7:$B$408,9,'Export · base'!$C$7:$C$408,$A40)/'Export · supuestos'!$B$5,0) -> 0 | K40: =ROUNDUP(SUMIFS('Export · base'!$H$7:$H$408,'Export · base'!$A$7:$A$408,2027,'Export · base'!$B$7:$B$408,10,'Export · base'!$C$7:$C$408,$A40)/'Export · supuestos'!$B$5,0) -> 0 | L40: =ROUNDUP(SUMIFS('Export · base'!$H$7:$H$408,'Export · base'!$A$7:$A$408,2027,'Export · base'!$B$7:$B$408,11,'Export · base'!$C$7:$C$408,$A40)/'Export · supuestos'!$B$5,0) -> 0 | M40: =ROUNDUP(SUMIFS('Export · base'!$H$7:$H$408,'Export · base'!$A$7:$A$408,2027,'Export · base'!$B$7:$B$408,12,'Export · base'!$C$7:$C$408,$A40)/'Export · supuestos'!$B$5,0) -> 3 | N40: =SUM(B40:M40) -> 6
A41: ITALIA | B41: =ROUNDUP(SUMIFS('Export · base'!$H$7:$H$408,'Export · base'!$A$7:$A$408,2027,'Export · base'!$B$7:$B$408,1,'Export · base'!$C$7:$C$408,$A41)/'Export · supuestos'!$B$5,0) -> 0 | C41: =ROUNDUP(SUMIFS('Export · base'!$H$7:$H$408,'Export · base'!$A$7:$A$408,2027,'Export · base'!$B$7:$B$408,2,'Export · base'!$C$7:$C$408,$A41)/'Export · supuestos'!$B$5,0) -> 1 | D41: =ROUNDUP(SUMIFS('Export · base'!$H$7:$H$408,'Export · base'!$A$7:$A$408,2027,'Export · base'!$B$7:$B$408,3,'Export · base'!$C$7:$C$408,$A41)/'Export · supuestos'!$B$5,0) -> 1 | E41: =ROUNDUP(SUMIFS('Export · base'!$H$7:$H$408,'Export · base'!$A$7:$A$408,2027,'Export · base'!$B$7:$B$408,4,'Export · base'!$C$7:$C$408,$A41)/'Export · supuestos'!$B$5,0) -> 0 | F41: =ROUNDUP(SUMIFS('Export · base'!$H$7:$H$408,'Export · base'!$A$7:$A$408,2027,'Export · base'!$B$7:$B$408,5,'Export · base'!$C$7:$C$408,$A41)/'Export · supuestos'!$B$5,0) -> 1 | G41: =ROUNDUP(SUMIFS('Export · base'!$H$7:$H$408,'Export · base'!$A$7:$A$408,2027,'Export · base'!$B$7:$B$408,6,'Export · base'!$C$7:$C$408,$A41)/'Export · supuestos'!$B$5,0) -> 1 | H41: =ROUNDUP(SUMIFS('Export · base'!$H$7:$H$408,'Export · base'!$A$7:$A$408,2027,'Export · base'!$B$7:$B$408,7,'Export · base'!$C$7:$C$408,$A41)/'Export · supuestos'!$B$5,0) -> 0 | I41: =ROUNDUP(SUMIFS('Export · base'!$H$7:$H$408,'Export · base'!$A$7:$A$408,2027,'Export · base'!$B$7:$B$408,8,'Export · base'!$C$7:$C$408,$A41)/'Export · supuestos'!$B$5,0) -> 0 | J41: =ROUNDUP(SUMIFS('Export · base'!$H$7:$H$408,'Export · base'!$A$7:$A$408,2027,'Export · base'!$B$7:$B$408,9,'Export · base'!$C$7:$C$408,$A41)/'Export · supuestos'!$B$5,0) -> 0 | K41: =ROUNDUP(SUMIFS('Export · base'!$H$7:$H$408,'Export · base'!$A$7:$A$408,2027,'Export · base'!$B$7:$B$408,10,'Export · base'!$C$7:$C$408,$A41)/'Export · supuestos'!$B$5,0) -> 1 | L41: =ROUNDUP(SUMIFS('Export · base'!$H$7:$H$408,'Export · base'!$A$7:$A$408,2027,'Export · base'!$B$7:$B$408,11,'Export · base'!$C$7:$C$408,$A41)/'Export · supuestos'!$B$5,0) -> 0 | M41: =ROUNDUP(SUMIFS('Export · base'!$H$7:$H$408,'Export · base'!$A$7:$A$408,2027,'Export · base'!$B$7:$B$408,12,'Export · base'!$C$7:$C$408,$A41)/'Export · supuestos'!$B$5,0) -> 1 | N41: =SUM(B41:M41) -> 6
A42: LÍBANO | B42: =ROUNDUP(SUMIFS('Export · base'!$H$7:$H$408,'Export · base'!$A$7:$A$408,2027,'Export · base'!$B$7:$B$408,1,'Export · base'!$C$7:$C$408,$A42)/'Export · supuestos'!$B$5,0) -> 0 | C42: =ROUNDUP(SUMIFS('Export · base'!$H$7:$H$408,'Export · base'!$A$7:$A$408,2027,'Export · base'!$B$7:$B$408,2,'Export · base'!$C$7:$C$408,$A42)/'Export · supuestos'!$B$5,0) -> 0 | D42: =ROUNDUP(SUMIFS('Export · base'!$H$7:$H$408,'Export · base'!$A$7:$A$408,2027,'Export · base'!$B$7:$B$408,3,'Export · base'!$C$7:$C$408,$A42)/'Export · supuestos'!$B$5,0) -> 0 | E42: =ROUNDUP(SUMIFS('Export · base'!$H$7:$H$408,'Export · base'!$A$7:$A$408,2027,'Export · base'!$B$7:$B$408,4,'Export · base'!$C$7:$C$408,$A42)/'Export · supuestos'!$B$5,0) -> 0 | F42: =ROUNDUP(SUMIFS('Export · base'!$H$7:$H$408,'Export · base'!$A$7:$A$408,2027,'Export · base'!$B$7:$B$408,5,'Export · base'!$C$7:$C$408,$A42)/'Export · supuestos'!$B$5,0) -> 0 | G42: =ROUNDUP(SUMIFS('Export · base'!$H$7:$H$408,'Export · base'!$A$7:$A$408,2027,'Export · base'!$B$7:$B$408,6,'Export · base'!$C$7:$C$408,$A42)/'Export · supuestos'!$B$5,0) -> 0 | H42: =ROUNDUP(SUMIFS('Export · base'!$H$7:$H$408,'Export · base'!$A$7:$A$408,2027,'Export · base'!$B$7:$B$408,7,'Export · base'!$C$7:$C$408,$A42)/'Export · supuestos'!$B$5,0) -> 1 | I42: =ROUNDUP(SUMIFS('Export · base'!$H$7:$H$408,'Export · base'!$A$7:$A$408,2027,'Export · base'!$B$7:$B$408,8,'Export · base'!$C$7:$C$408,$A42)/'Export · supuestos'!$B$5,0) -> 0 | J42: =ROUNDUP(SUMIFS('Export · base'!$H$7:$H$408,'Export · base'!$A$7:$A$408,2027,'Export · base'!$B$7:$B$408,9,'Export · base'!$C$7:$C$408,$A42)/'Export · supuestos'!$B$5,0) -> 0 | K42: =ROUNDUP(SUMIFS('Export · base'!$H$7:$H$408,'Export · base'!$A$7:$A$408,2027,'Export · base'!$B$7:$B$408,10,'Export · base'!$C$7:$C$408,$A42)/'Export · supuestos'!$B$5,0) -> 0 | L42: =ROUNDUP(SUMIFS('Export · base'!$H$7:$H$408,'Export · base'!$A$7:$A$408,2027,'Export · base'!$B$7:$B$408,11,'Export · base'!$C$7:$C$408,$A42)/'Export · supuestos'!$B$5,0) -> 0 | M42: =ROUNDUP(SUMIFS('Export · base'!$H$7:$H$408,'Export · base'!$A$7:$A$408,2027,'Export · base'!$B$7:$B$408,12,'Export · base'!$C$7:$C$408,$A42)/'Export · supuestos'!$B$5,0) -> 2 | N42: =SUM(B42:M42) -> 3
... A49: TURQUÍA | B49: =ROUNDUP(SUMIFS('Export · base'!$H$7:$H$408,'Export · base'!$A$7:$A$408,2027,'Export · base'!$B$7:$B$408,1,'Export · base'!$C$7:$C$408,$A49)/'Export · supuestos'!$B$5,0) -> 0 | C49: =ROUNDUP(SUMIFS('Export · base'!$H$7:$H$408,'Export · base'!$A$7:$A$408,2027,'Export · base'!$B$7:$B$408,2,'Export · base'!$C$7:$C$408,$A49)/'Export · supuestos'!$B$5,0) -> 2 | D49: =ROUNDUP(SUMIFS('Export · base'!$H$7:$H$408,'Export · base'!$A$7:$A$408,2027,'Export · base'!$B$7:$B$408,3,'Export · base'!$C$7:$C$408,$A49)/'Export · supuestos'!$B$5,0) -> 0 | E49: =ROUNDUP(SUMIFS('Export · base'!$H$7:$H$408,'Export · base'!$A$7:$A$408,2027,'Export · base'!$B$7:$B$408,4,'Export · base'!$C$7:$C$408,$A49)/'Export · supuestos'!$B$5,0) -> 2 | F49: =ROUNDUP(SUMIFS('Export · base'!$H$7:$H$408,'Export · base'!$A$7:$A$408,2027,'Export · base'!$B$7:$B$408,5,'Export · base'!$C$7:$C$408,$A49)/'Export · supuestos'!$B$5,0) -> 6 | G49: =ROUNDUP(SUMIFS('Export · base'!$H$7:$H$408,'Export · base'!$A$7:$A$408,2027,'Export · base'!$B$7:$B$408,6,'Export · base'!$C$7:$C$408,$A49)/'Export · supuestos'!$B$5,0) -> 0 | H49: =ROUNDUP(SUMIFS('Export · base'!$H$7:$H$408,'Export · base'!$A$7:$A$408,2027,'Export · base'!$B$7:$B$408,7,'Export · base'!$C$7:$C$408,$A49)/'Export · supuestos'!$B$5,0) -> 3 | I49: =ROUNDUP(SUMIFS('Export · base'!$H$7:$H$408,'Export · base'!$A$7:$A$408,2027,'Export · base'!$B$7:$B$408,8,'Export · base'!$C$7:$C$408,$A49)/'Export · supuestos'!$B$5,0) -> 0 | J49: =ROUNDUP(SUMIFS('Export · base'!$H$7:$H$408,'Export · base'!$A$7:$A$408,2027,'Export · base'!$B$7:$B$408,9,'Export · base'!$C$7:$C$408,$A49)/'Export · supuestos'!$B$5,0) -> 3 | K49: =ROUNDUP(SUMIFS('Export · base'!$H$7:$H$408,'Export · base'!$A$7:$A$408,2027,'Export · base'!$B$7:$B$408,10,'Export · base'!$C$7:$C$408,$A49)/'Export · supuestos'!$B$5,0) -> 0 | L49: =ROUNDUP(SUMIFS('Export · base'!$H$7:$H$408,'Export · base'!$A$7:$A$408,2027,'Export · base'!$B$7:$B$408,11,'Export · base'!$C$7:$C$408,$A49)/'Export · supuestos'!$B$5,0) -> 0 | M49: =ROUNDUP(SUMIFS('Export · base'!$H$7:$H$408,'Export · base'!$A$7:$A$408,2027,'Export · base'!$B$7:$B$408,12,'Export · base'!$C$7:$C$408,$A49)/'Export · supuestos'!$B$5,0) -> 2 | N49: =SUM(B49:M49) -> 18
A50: TOTAL | B50: =SUM(B31:B49) -> 19 | C50: =SUM(C31:C49) -> 26 | D50: =SUM(D31:D49) -> 36 | E50: =SUM(E31:E49) -> 21 | F50: =SUM(F31:F49) -> 44 | G50: =SUM(G31:G49) -> 41 | H50: =SUM(H31:H49) -> 25 | I50: =SUM(I31:I49) -> 12 | ... N50: =SUM(N31:N49) -> 296

Sheet Export · países
A2: Resumen de envíos por país
A3: 2026: solo octubre–diciembre · 2027: año completo · palets equivalentes antes de redondear
A6: País | B6: Palets 2026 | C6: Envíos 2026 | D6: Coste Transporte | E6: Documentacion | F6: Total coste 2026 | G6: Palets 2027 | H6: Envíos 2027 | I6: Coste Transporte | J6: Documentacion | K6: Total coste
A7: ARABIA SAUDÍ | B7: =SUMIFS('Export · base'!$H$7:$H$408,'Export · base'!$A$7:$A$408,2026,'Export · base'!$C$7:$C$408,$A7) -> 0 | C7: ='Export · detalle'!E7 -> 0 | D7: EXW | E7: 54 | F7: =C7+E7 -> 54 | G7: =SUMIFS('Export · base'!$H$7:$H$408,'Export · base'!$A$7:$A$408,2027,'Export · base'!$C$7:$C$408,$A7) -> 26.371831 | H7: ='Export · detalle'!N31 -> 2 | I7: =D7 -> EXW | J7: 54 | K7: =J7*H7 -> 108
A8: AZERBAIYÁN | B8: =SUMIFS('Export · base'!$H$7:$H$408,'Export · base'!$A$7:$A$408,2026,'Export · base'!$C$7:$C$408,$A8) -> 22.140258 | C8: ='Export · detalle'!E8 -> 2 | D8: =(1595*0.8)+(1875*0.2) -> 1651 | E8: =2*50 -> 100 | F8: =C8*D8+E8 -> 3402 | G8: =SUMIFS('Export · base'!$H$7:$H$408,'Export · base'!$A$7:$A$408,2027,'Export · base'!$C$7:$C$408,$A8) -> 332.06799 | H8: ='Export · detalle'!N32 -> 19 | I8: =D8*1.1 -> 1816.1 | J8: 50 | K8: =+(H8*I8)+J8*H8 -> 35455.9
A9: CHILE | B9: =SUMIFS('Export · base'!$H$7:$H$408,'Export · base'!$A$7:$A$408,2026,'Export · base'!$C$7:$C$408,$A9) -> 208.55915 | C9: ='Export · detalle'!E9 -> 10 | D9: EXW | E9: 0 | F9: 0 | G9: =SUMIFS('Export · base'!$H$7:$H$408,'Export · base'!$A$7:$A$408,2027,'Export · base'!$C$7:$C$408,$A9) -> 1664.2467 | H9: ='Export · detalle'!N33 -> 83 | I9: =D9 -> EXW | J9: 0 | K9: =J9*H9 -> 0
A10: COLOMBIA | B10: =SUMIFS('Export · base'!$H$7:$H$408,'Export · base'!$A$7:$A$408,2026,'Export · base'!$C$7:$C$408,$A10) -> 26.382541 | C10: ='Export · detalle'!E10 -> 2 | D10: EXW | E10: =+C10*50 -> 100 | F10: 0 | G10: =SUMIFS('Export · base'!$H$7:$H$408,'Export · base'!$A$7:$A$408,2027,'Export · base'!$C$7:$C$408,$A10) -> 89.234381 | H10: ='Export · detalle'!N34 -> 6 | I10: =D10 -> EXW | J10: 0 | K10: =J10*H10 -> 0
A11: COSTA RICA | B11: =SUMIFS('Export · base'!$H$7:$H$408,'Export · base'!$A$7:$A$408,2026,'Export · base'!$C$7:$C$408,$A11) -> 96.193264 | C11: ='Export · detalle'!E11 -> 7 | D11: 3850 | E11: 0 | F11: =C11*D11 -> 26950 | G11: =SUMIFS('Export · base'!$H$7:$H$408,'Export · base'!$A$7:$A$408,2027,'Export · base'!$C$7:$C$408,$A11) -> 196.47896 | H11: ='Export · detalle'!N35 -> 16 | I11: =D11*1.1 -> 4235 | J11: 0 | K11: =H11*I11 -> 67760
A12: DOMINICANA, REPÚBLICA | B12: =SUMIFS('Export · base'!$H$7:$H$408,'Export · base'!$A$7:$A$408,2026,'Export · base'!$C$7:$C$408,$A12) -> 30.272318 | C12: ='Export · detalle'!E12 -> 2 | D12: 3675 | E12: 0 | F12: =C12*D12 -> 7350 | G12: =SUMIFS('Export · base'!$H$7:$H$408,'Export · base'!$A$7:$A$408,2027,'Export · base'!$C$7:$C$408,$A12) -> 101.41168 | H12: ='Export · detalle'!N36 -> 6 | I12: =D12*1.1 -> 4042.5 | J12: 0 | K12: =H12*I12 -> 24255
A13: ECUADOR (incluidas las Islas Galápagos) | B13: =SUMIFS('Export · base'!$H$7:$H$408,'Export · base'!$A$7:$A$408,2026,'Export · base'!$C$7:$C$408,$A13) -> 16.495133 | C13: ='Export · detalle'!E13 -> 1 | D13: EXW | E13: =50+54 -> 104 | F13: 104 | G13: =SUMIFS('Export · base'!$H$7:$H$408,'Export · base'!$A$7:$A$408,2027,'Export · base'!$C$7:$C$408,$A13) -> 68.390833 | H13: ='Export · detalle'!N37 -> 5 | I13: =D13 -> EXW | J13: 104 | K13: =J13*H13 -> 520
A14: EGIPTO | B14: =SUMIFS('Export · base'!$H$7:$H$408,'Export · base'!$A$7:$A$408,2026,'Export · base'!$C$7:$C$408,$A14) -> 116.73998 | C14: ='Export · detalle'!E14 -> 7 | D14: EXW | E14: =(54+50+75)*C14 -> 1253 | F14: 1253 | G14: =SUMIFS('Export · base'!$H$7:$H$408,'Export · base'!$A$7:$A$408,2027,'Export · base'!$C$7:$C$408,$A14) -> 1028.3723 | H14: ='Export · detalle'!N38 -> 55 | I14: =D14 -> EXW | J14: =50+54+75 -> 179 | K14: =J14*H14 -> 9845
A15: GEORGIA | B15: =SUMIFS('Export · base'!$H$7:$H$408,'Export · base'!$A$7:$A$408,2026,'Export · base'!$C$7:$C$408,$A15) -> 46.868355 | C15: ='Export · detalle'!E15 -> 3 | D15: EXW | E15: 0 | F15: 0 | G15: =SUMIFS('Export · base'!$H$7:$H$408,'Export · base'!$A$7:$A$408,2027,'Export · base'!$C$7:$C$408,$A15) -> 110.48561 | H15: ='Export · detalle'!N39 -> 6 | I15: =D15 -> EXW | J15: 0 | K15: =J15*H15 -> 0
A16: GRECIA | B16: =SUMIFS('Export · base'!$H$7:$H$408,'Export · base'!$A$7:$A$408,2026,'Export · base'!$C$7:$C$408,$A16) -> 40.50529 | C16: ='Export · detalle'!E16 -> 2 | D16: EXW | E16: 0 | F16: 0 | G16: =SUMIFS('Export · base'!$H$7:$H$408,'Export · base'!$A$7:$A$408,2027,'Export · base'!$C$7:$C$408,$A16) -> 84.099874 | H16: ='Export · detalle'!N40 -> 6 | I16: =D16 -> EXW | J16: 0 | K16: =J16*H16 -> 0
A17: ITALIA | B17: =SUMIFS('Export · base'!$H$7:$H$408,'Export · base'!$A$7:$A$408,2026,'Export · base'!$C$7:$C$408,$A17) -> 5.8775761 | C17: ='Export · detalle'!E17 -> 2 | D17: 487 | E17: 0 | F17: =C17*D17 -> 974 | G17: =SUMIFS('Export · base'!$H$7:$H$408,'Export · base'!$A$7:$A$408,2027,'Export · base'!$C$7:$C$408,$A17) -> 18.205 | H17: ='Export · detalle'!N41 -> 6 | I17: =D17*1.1 -> 535.7 | J17: 0 | K17: =H17*I17 -> 3214.2
A18: LÍBANO | B18: =SUMIFS('Export · base'!$H$7:$H$408,'Export · base'!$A$7:$A$408,2026,'Export · base'!$C$7:$C$408,$A18) -> 27.404988 | C18: ='Export · detalle'!E18 -> 2 | D18: 1475 | E18: =+C18*(50+54) -> 208 | F18: =(C18*D18)+E18 -> 3158 | G18: =SUMIFS('Export · base'!$H$7:$H$408,'Export · base'!$A$7:$A$408,2027,'Export · base'!$C$7:$C$408,$A18) -> 41.020833 | H18: ='Export · detalle'!N42 -> 3 | I18: =D18*1.1 -> 1622.5 | J18: 104 | K18: =(H18*I18)+J18*H18 -> 5179.5
A19: MARRUECOS | B19: =SUMIFS('Export · base'!$H$7:$H$408,'Export · base'!$A$7:$A$408,2026,'Export · base'!$C$7:$C$408,$A19) -> 54.292529 | C19: ='Export · detalle'!E19 -> 4 | D19: EXW | E19: 0 | F19: 0 | G19: =SUMIFS('Export · base'!$H$7:$H$408,'Export · base'!$A$7:$A$408,2027,'Export · base'!$C$7:$C$408,$A19) -> 227.3508 | H19: ='Export · detalle'!N43 -> 19 | I19: =D19 -> EXW | J19: 0 | K19: =J19*H19 -> 0
A20: NETHERLANS | B20: =SUMIFS('Export · base'!$H$7:$H$408,'Export · base'!$A$7:$A$408,2026,'Export · base'!$C$7:$C$408,$A20) -> 134.14145 | C20: ='Export · detalle'!E20 -> 7 | D20: =(3600+5226)/2 -> 4413 | E20: 0 | F20: =D20*C20 -> 30891 | G20: =SUMIFS('Export · base'!$H$7:$H$408,'Export · base'!$A$7:$A$408,2027,'Export · base'!$C$7:$C$408,$A20) -> 378.81792 | H20: ='Export · detalle'!N44 -> 24 | I20: =D20*1.1 -> 4854.3 | J20: 0 | K20: =H20*I20 -> 116503.2
A21: PANAMÁ | B21: =SUMIFS('Export · base'!$H$7:$H$408,'Export · base'!$A$7:$A$408,2026,'Export · base'!$C$7:$C$408,$A21) -> 16.273934 | C21: ='Export · detalle'!E21 -> 1 | D21: 3345 | E21: =54+50 -> 104 | F21: =3345+E21 -> 3449 | G21: =SUMIFS('Export · base'!$H$7:$H$408,'Export · base'!$A$7:$A$408,2027,'Export · base'!$C$7:$C$408,$A21) -> 43.014545 | H21: ='Export · detalle'!N45 -> 3 | I21: =D21*1.1 -> 3679.5 | J21: 104 | K21: =(H21*I21)+J21*H21 -> 11350.5
A22: PERÚ | B22: =SUMIFS('Export · base'!$H$7:$H$408,'Export · base'!$A$7:$A$408,2026,'Export · base'!$C$7:$C$408,$A22) -> 0 | C22: ='Export · detalle'!E22 -> 0 | D22: EXW | E22: 0 | F22: 0 | G22: =SUMIFS('Export · base'!$H$7:$H$408,'Export · base'!$A$7:$A$408,2027,'Export · base'!$C$7:$C$408,$A22) -> 72.9 | H22: ='Export · detalle'!N46 -> 5 | I22: =D22 -> EXW | J22: 0 | K22: =J22*H22 -> 0
A23: RUMANÍA | B23: =SUMIFS('Export · base'!$H$7:$H$408,'Export · base'!$A$7:$A$408,2026,'Export · base'!$C$7:$C$408,$A23) -> 19.350253 | C23: ='Export · detalle'!E23 -> 1 | D23: EXW | E23: 0 | F23: 0 | G23: =SUMIFS('Export · base'!$H$7:$H$408,'Export · base'!$A$7:$A$408,2027,'Export · base'!$C$7:$C$408,$A23) -> 180.52857 | H23: ='Export · detalle'!N47 -> 12 | I23: =D23 -> EXW | J23: 0 | K23: =J23*H23 -> 0
A24: SERBIA | B24: =SUMIFS('Export · base'!$H$7:$H$408,'Export · base'!$A$7:$A$408,2026,'Export · base'!$C$7:$C$408,$A24) -> 6.6714031 | C24: ='Export · detalle'!E24 -> 1 | D24: EXW | E24: 0 | F24: 0 | G24: =SUMIFS('Export · base'!$H$7:$H$408,'Export · base'!$A$7:$A$408,2027,'Export · base'!$C$7:$C$408,$A24) -> 19.047197 | H24: ='Export · detalle'!N48 -> 2 | I24: =D24 -> EXW | J24: 0 | K24: =J24*H24 -> 0
A25: TURQUÍA | B25: =SUMIFS('Export · base'!$H$7:$H$408,'Export · base'!$A$7:$A$408,2026,'Export · base'!$C$7:$C$408,$A25) -> 28.439884 | C25: ='Export · detalle'!E25 -> 2 | D25: 1620 | E25: =108+50 -> 158 | F25: =(C25*D25)+E25 -> 3398 | G25: =SUMIFS('Export · base'!$H$7:$H$408,'Export · base'!$A$7:$A$408,2027,'Export · base'!$C$7:$C$408,$A25) -> 297.41372 | H25: ='Export · detalle'!N49 -> 18 | I25: =D25 -> 1620 | J25: 104 | K25: =(H25*I25)+J25*H25 -> 31032
A26: TOTAL | B26: =SUM(B7:B25) -> 896.60831 | C26: =SUM(C7:C25) -> 56 | E26: =SUM(E7:E25) -> 2081 | F26: =SUM(F7:F25) -> 80983 | G26: =SUM(G7:G25) -> 4979.4587 | H26: =SUM(H7:H25) -> 296 | K26: =SUM(K7:K25) -> 305223.3

Sheet Export · base
A2: Base de unidades y cálculo de palets
A4: Agregado por año, mes, país y formato; unidades tomadas del archivo de previsión.
A6: Año | B6: Mes n.º | C6: País | D6: Formato | E6: Unidades | F6: Líneas origen | G6: Capacidad/palet | H6: Palets equiv.
A7: 2026 | B7: 10 | C7: COSTA RICA | D7: L1000 | E7: 15167.938 | F7: 6 | G7: ='Export · supuestos'!$B$14 -> 1000 | H7: =E7/G7 -> 15.167938
A8: 2026 | B8: 10 | C8: COSTA RICA | D8: L5 | E8: 379.19846 | F8: 1 | G8: ='Export · supuestos'!$B$11 -> 800 | H8: =E8/G8 -> 0.47399807
A9: 2026 | B9: 10 | C9: COSTA RICA | D9: kg1 | E9: 1001.0839 | F9: 1 | G9: ='Export · supuestos'!$B$15 -> 1056 | H9: =E9/G9 -> 0.94799614
A10: 2026 | B10: 10 | C10: COSTA RICA | D10: kg20 | E10: 13044.427 | F10: 2 | G10: ='Export · supuestos'!$B$17 -> 1000 | H10: =E10/G10 -> 13.044427
A11: 2026 | B11: 10 | C11: COSTA RICA | D11: kg5 | E11: 14788.74 | F11: 6 | G11: ='Export · supuestos'!$B$16 -> 1000 | H11: =E11/G11 -> 14.78874
A12: 2026 | B12: 10 | C12: ECUADOR (incluidas las Islas Galápagos) | D12: L1 | E12: 2252.4388 | F12: 1 | G12: ='Export · supuestos'!$B$10 -> 792 | H12: =E12/G12 -> 2.8439884
A13: 2026 | B13: 10 | C13: ECUADOR (incluidas las Islas Galápagos) | D13: kg20 | E13: 9479.9614 | F13: 1 | G13: ='Export · supuestos'!$B$17 -> 1000 | H13: =E13/G13 -> 9.4799614
A14: 2026 | B14: 10 | C14: ECUADOR (incluidas las Islas Galápagos) | D14: kg5 | E14: 4171.183 | F14: 1 | G14: ='Export · supuestos'!$B$16 -> 1000 | H14: =E14/G14 -> 4.171183
A15: 2026 | B15: 10 | C15: EGIPTO | D15: L1 | E15: 7583.9691 | F15: 2 | G15: ='Export · supuestos'!$B$10 -> 792 | H15: =E15/G15 -> 9.5757186
A16: 2026 | B16: 10 | C16: EGIPTO | D16: kg1 | E16: 1895.9923 | F16: 1 | G16: ='Export · supuestos'!$B$15 -> 1056 | H16: =E16/G16 -> 1.7954472
A17: 2026 | B17: 10 | C17: EGIPTO | D17: kg5 | E17: 18959.923 | F17: 1 | G17: ='Export · supuestos'!$B$16 -> 1000 | H17: =E17/G17 -> 18.959923
A18: 2026 | B18: 10 | C18: ITALIA | D18: L1000 | E18: 2843.9884 | F18: 1 | G18: ='Export · supuestos'!$B$14 -> 1000 | H18: =E18/G18 -> 2.8439884
A19: 2026 | B19: 10 | C19: ITALIA | D19: kg5 | E19: 189.59923 | F19: 1 | G19: ='Export · supuestos'!$B$16 -> 1000 | H19: =E19/G19 -> 0.18959923
A20: 2026 | B20: 10 | C20: MARRUECOS | D20: L20 | E20: 7583.9691 | F20: 2 | G20: ='Export · supuestos'!$B$12 -> 960 | H20: =E20/G20 -> 7.8999678
A21: 2026 | B21: 10 | C21: MARRUECOS | D21: L200 | E21: 5687.9768 | F21: 2 | G21: ='Export · supuestos'!$B$13 -> 800 | H21: =E21/G21 -> 7.109971
A22: 2026 | B22: 10 | C22: MARRUECOS | D22: kg20 | E22: 947.99614 | F22: 1 | G22: ='Export · supuestos'!$B$17 -> 1000 | H22: =E22/G22 -> 0.94799614
A23: 2026 | B23: 10 | C23: MARRUECOS | D23: kg5 | E23: 2843.9884 | F23: 1 | G23: ='Export · supuestos'!$B$16 -> 1000 | H23: =E23/G23 -> 2.8439884
A24: 2026 | B24: 10 | C24: NETHERLANS | D24: L20 | E24: 9100.7629 | F24: 1 | G24: ='Export · supuestos'!$B$12 -> 960 | H24: =E24/G24 -> 9.4799614
A25: 2026 | B25: 10 | C25: NETHERLANS | D25: kg20 | E25: 20855.915 | F25: 1 | G25: ='Export · supuestos'!$B$17 -> 1000 | H25: =E25/G25 -> 20.855915
A26: 2026 | B26: 11 | C26: COLOMBIA | D26: L1 | E26: 1213.4351 | F26: 4 | G26: ='Export · supuestos'!$B$10 -> 792 | H26: =E26/G26 -> 1.532115
A27: 2026 | B27: 11 | C27: COLOMBIA | D27: L20 | E27: 758.39691 | F27: 1 | G27: ='Export · supuestos'!$B$12 -> 960 | H27: =E27/G27 -> 0.78999678
A28: 2026 | B28: 11 | C28: COLOMBIA | D28: L5 | E28: 1554.7137 | F28: 4 | G28: ='Export · supuestos'!$B$11 -> 800 | H28: =E28/G28 -> 1.9433921
A29: 2026 | B29: 11 | C29: COLOMBIA | D29: kg1 | E29: 530.87784 | F29: 2 | G29: ='Export · supuestos'!$B$15 -> 1056 | H29: =E29/G29 -> 0.50272523
A30: 2026 | B30: 11 | C30: COLOMBIA | D30: kg20 | E30: 6635.973 | F30: 1 | G30: ='Export · supuestos'!$B$17 -> 1000 | H30: =E30/G30 -> 6.635973
A31: 2026 | B31: 11 | C31: COLOMBIA | D31: kg5 | E31: 14978.339 | F31: 3 | G31: ='Export · supuestos'!$B$16 -> 1000 | H31: =E31/G31 -> 14.978339
A32: 2026 | B32: 11 | C32: COSTA RICA | D32: L1 | E32: 473.99807 | F32: 1 | G32: ='Export · supuestos'!$B$10 -> 792 | H32: =E32/G32 -> 0.59848241
A33: 2026 | B33: 11 | C33: COSTA RICA | D33: L1000 | E33: 10427.958 | F33: 5 | G33: ='Export · supuestos'!$B$14 -> 1000 | H33: =E33/G33 -> 10.427958
A34: 2026 | B34: 11 | C34: COSTA RICA | D34: L5 | E34: 379.19846 | F34: 1 | G34: ='Export · supuestos'!$B$11 -> 800 | H34: =E34/G34 -> 0.47399807
A35: 2026 | B35: 11 | C35: COSTA RICA | D35: kg1 | E35: 1001.0839 | F35: 1 | G35: ='Export · supuestos'!$B$15 -> 1056 | H35: =E35/G35 -> 0.94799614
A36: 2026 | B36: 11 | C36: COSTA RICA | D36: kg20 | E36: 16305.534 | F36: 3 | G36: ='Export · supuestos'!$B$17 -> 1000 | H36: =E36/G36 -> 16.305534
A37: 2026 | B37: 11 | C37: COSTA RICA | D37: kg5 | E37: 1990.7919 | F37: 2 | G37: ='Export · supuestos'!$B$16 -> 1000 | H37: =E37/G37 -> 1.9907919
A38: 2026 | B38: 11 | C38: DOMINICANA, REPÚBLICA | D38: L1 | E38: 12024.383 | F38: 12 | G38: ='Export · supuestos'!$B$10 -> 792 | H38: =E38/G38 -> 15.182302
A39: 2026 | B39: 11 | C39: DOMINICANA, REPÚBLICA | D39: L20 | E39: 2369.9903 | F39: 1 | G39: ='Export · supuestos'!$B$12 -> 960 | H39: =E39/G39 -> 2.4687399
A40: 2026 | B40: 11 | C40: DOMINICANA, REPÚBLICA | D40: L5 | E40: 6560.1333 | F40: 5 | G40: ='Export · supuestos'!$B$11 -> 800 | H40: =E40/G40 -> 8.2001666
A41: 2026 | B41: 11 | C41: DOMINICANA, REPÚBLICA | D41: kg1 | E41: 1365.1144 | F41: 2 | G41: ='Export · supuestos'!$B$15 -> 1056 | H41: =E41/G41 -> 1.292722
A42: 2026 | B42: 11 | C42: DOMINICANA, REPÚBLICA | D42: kg5 | E42: 3128.3873 | F42: 1 | G42: ='Export · supuestos'!$B$16 -> 1000 | H42: =E42/G42 -> 3.1283873
A43: 2026 | B43: 11 | C43: EGIPTO | D43: L1 | E43: 16988.091 | F43: 2 | G43: ='Export · supuestos'!$B$10 -> 792 | H43: =E43/G43 -> 21.44961
A44: 2026 | B44: 11 | C44: EGIPTO | D44: kg1000 | E44: 18959.923 | F44: 1 | G44: ='Export · supuestos'!$B$18 -> 1000 | H44: =E44/G44 -> 18.959923
A45: 2026 | B45: 11 | C45: EGIPTO | D45: kg20 | E45: 9479.9614 | F45: 1 | G45: ='Export · supuestos'!$B$17 -> 1000 | H45: =E45/G45 -> 9.4799614
A46: 2026 | B46: 11 | C46: EGIPTO | D46: kg5 | E46: 28439.884 | F46: 1 | G46: ='Export · supuestos'!$B$16 -> 1000 | H46: =E46/G46 -> 28.439884
A47: 2026 | B47: 11 | C47: MARRUECOS | D47: L20 | E47: 947.99614 | F47: 1 | G47: ='Export · supuestos'!$B$12 -> 960 | H47: =E47/G47 -> 0.98749598
A48: 2026 | B48: 11 | C48: NETHERLANS | D48: L20 | E48: 15926.335 | F48: 1 | G48: ='Export · supuestos'!$B$12 -> 960 | H48: =E48/G48 -> 16.589932
A49: 2026 | B49: 11 | C49: NETHERLANS | D49: kg20 | E49: 41711.83 | F49: 2 | G49: ='Export · supuestos'!$B$17 -> 1000 | H49: =E49/G49 -> 41.71183
A50: 2026 | B50: 11 | C50: NETHERLANS | D50: kg5 | E50: 3791.9846 | F50: 2 | G50: ='Export · supuestos'!$B$16 -> 1000 | H50: =E50/G50 -> 3.7919846
A51: 2026 | B51: 11 | C51: PANAMÁ | D51: L1 | E51: 5756.2326 | F51: 5 | G51: ='Export · supuestos'!$B$10 -> 792 | H51: =E51/G51 -> 7.2679704
A52: 2026 | B52: 11 | C52: PANAMÁ | D52: L5 | E52: 2275.1907 | F52: 4 | G52: ='Export · supuestos'!$B$11 -> 800 | H52: =E52/G52 -> 2.8439884
A53: 2026 | B53: 11 | C53: PANAMÁ | D53: kg1 | E53: 500.54196 | F53: 1 | G53: ='Export · supuestos'!$B$15 -> 1056 | H53: =E53/G53 -> 0.47399807
A54: 2026 | B54: 11 | C54: PANAMÁ | D54: kg5 | E54: 5687.9768 | F54: 1 | G54: ='Export · supuestos'!$B$16 -> 1000 | H54: =E54/G54 -> 5.6879768
A55: 2026 | B55: 11 | C55: RUMANÍA | D55: L1 | E55: 5176.0589 | F55: 9 | G55: ='Export · supuestos'!$B$10 -> 792 | H55: =E55/G55 -> 6.5354279
A56: 2026 | B56: 11 | C56: RUMANÍA | D56: L1000 | E56: 2843.9884 | F56: 2 | G56: ='Export · supuestos'!$B$14 -> 1000 | H56: =E56/G56 -> 2.8439884
A57: 2026 | B57: 11 | C57: RUMANÍA | D57: L20 | E57: 3317.9865 | F57: 6 | G57: ='Export · supuestos'!$B$12 -> 960 | H57: =E57/G57 -> 3.4562359
A58: 2026 | B58: 11 | C58: RUMANÍA | D58: L200 | E58: 1137.5954 | F58: 3 | G58: ='Export · supuestos'!$B$13 -> 800 | H58: =E58/G58 -> 1.4219942
A59: 2026 | B59: 11 | C59: RUMANÍA | D59: L5 | E59: 284.39884 | F59: 1 | G59: ='Export · supuestos'!$B$11 -> 800 | H59: =E59/G59 -> 0.35549855
A60: 2026 | B60: 11 | C60: RUMANÍA | D60: kg1 | E60: 2699.893 | F60: 4 | G60: ='Export · supuestos'!$B$15 -> 1056 | H60: =E60/G60 -> 2.5567169
A61: 2026 | B61: 11 | C61: RUMANÍA | D61: kg20 | E61: 1611.5934 | F61: 2 | G61: ='Export · supuestos'!$B$17 -> 1000 | H61: =E61/G61 -> 1.6115934
A62: 2026 | B62: 11 | C62: RUMANÍA | D62: kg5 | E62: 568.79768 | F62: 1 | G62: ='Export · supuestos'!$B$16 -> 1000 | H62: =E62/G62 -> 0.56879768
A63: 2026 | B63: 12 | C63: AZERBAIYÁN | D63: L1 | E63: 3716.1449 | F63: 2 | G63: ='Export · supuestos'!$B$10 -> 792 | H63: =E63/G63 -> 4.6921021
A64: 2026 | B64: 12 | C64: AZERBAIYÁN | D64: L20 | E64: 4739.9807 | F64: 2 | G64: ='Export · supuestos'!$B$12 -> 960 | H64: =E64/G64 -> 4.9374799
A65: 2026 | B65: 12 | C65: AZERBAIYÁN | D65: L5 | E65: 8531.9653 | F65: 3 | G65: ='Export · supuestos'!$B$11 -> 800 | H65: =E65/G65 -> 10.664957
A66: 2026 | B66: 12 | C66: AZERBAIYÁN | D66: kg1 | E66: 947.99614 | F66: 1 | G66: ='Export · supuestos'!$B$15 -> 1056 | H66: =E66/G66 -> 0.89772362
A67: 2026 | B67: 12 | C67: AZERBAIYÁN | D67: kg5 | E67: 947.99614 | F67: 1 | G67: ='Export · supuestos'!$B$16 -> 1000 | H67: =E67/G67 -> 0.94799614
A68: 2026 | B68: 12 | C68: CHILE | D68: kg20 | E68: 208559.15 | F68: 1 | G68: ='Export · supuestos'!$B$17 -> 1000 | H68: =E68/G68 -> 208.55915
A69: 2026 | B69: 12 | C69: COSTA RICA | D69: L1000 | E69: 10901.956 | F69: 6 | G69: ='Export · supuestos'!$B$14 -> 1000 | H69: =E69/G69 -> 10.901956
A70: 2026 | B70: 12 | C70: COSTA RICA | D70: kg1 | E70: 379.19846 | F70: 1 | G70: ='Export · supuestos'!$B$15 -> 1056 | H70: =E70/G70 -> 0.35908945
A71: 2026 | B71: 12 | C71: COSTA RICA | D71: kg20 | E71: 758.39691 | F71: 1 | G71: ='Export · supuestos'!$B$17 -> 1000 | H71: =E71/G71 -> 0.75839691
A72: 2026 | B72: 12 | C72: COSTA RICA | D72: kg5 | E72: 9005.9633 | F72: 5 | G72: ='Export · supuestos'!$B$16 -> 1000 | H72: =E72/G72 -> 9.0059633
A73: 2026 | B73: 12 | C73: EGIPTO | D73: L1 | E73: 2843.9884 | F73: 1 | G73: ='Export · supuestos'!$B$10 -> 792 | H73: =E73/G73 -> 3.5908945
A74: 2026 | B74: 12 | C74: EGIPTO | D74: kg1 | E74: 4739.9807 | F74: 1 | G74: ='Export · supuestos'!$B$15 -> 1056 | H74: =E74/G74 -> 4.4886181
A75: 2026 | B75: 12 | C75: GEORGIA | D75: L1 | E75: 1820.1526 | F75: 2 | G75: ='Export · supuestos'!$B$10 -> 792 | H75: =E75/G75 -> 2.2981725
A76: 2026 | B76: 12 | C76: GEORGIA | D76: L20 | E76: 28439.884 | F76: 1 | G76: ='Export · supuestos'!$B$12 -> 960 | H76: =E76/G76 -> 29.624879
A77: 2026 | B77: 12 | C77: GEORGIA | D77: L5 | E77: 3791.9846 | F77: 4 | G77: ='Export · supuestos'!$B$11 -> 800 | H77: =E77/G77 -> 4.7399807
A78: 2026 | B78: 12 | C78: GEORGIA | D78: kg1 | E78: 2768.1487 | F78: 2 | G78: ='Export · supuestos'!$B$15 -> 1056 | H78: =E78/G78 -> 2.621353
A79: 2026 | B79: 12 | C79: GEORGIA | D79: kg20 | E79: 5687.9768 | F79: 1 | G79: ='Export · supuestos'!$B$17 -> 1000 | H79: =E79/G79 -> 5.6879768
A80: 2026 | B80: 12 | C80: GEORGIA | D80: kg5 | E80: 1895.9923 | F80: 2 | G80: ='Export · supuestos'!$B$16 -> 1000 | H80: =E80/G80 -> 1.8959923
A81: 2026 | B81: 12 | C81: GRECIA | D81: L1 | E81: 17063.931 | F81: 3 | G81: ='Export · supuestos'!$B$10 -> 792 | H81: =E81/G81 -> 21.545367
A82: 2026 | B82: 12 | C82: GRECIA | D82: L5 | E82: 15167.938 | F82: 3 | G82: ='Export · supuestos'!$B$11 -> 800 | H82: =E82/G82 -> 18.959923
A83: 2026 | B83: 12 | C83: ITALIA | D83: L1000 | E83: 2843.9884 | F83: 1 | G83: ='Export · supuestos'!$B$14 -> 1000 | H83: =E83/G83 -> 2.8439884
A84: 2026 | B84: 12 | C84: LÍBANO | D84: L20 | E84: 4739.9807 | F84: 1 | G84: ='Export · supuestos'!$B$12 -> 960 | H84: =E84/G84 -> 4.9374799
A85: 2026 | B85: 12 | C85: LÍBANO | D85: kg20 | E85: 7299.5703 | F85: 1 | G85: ='Export · supuestos'!$B$17 -> 1000 | H85: =E85/G85 -> 7.2995703
A86: 2026 | B86: 12 | C86: LÍBANO | D86: kg5 | E86: 15167.938 | F86: 3 | G86: ='Export · supuestos'!$B$16 -> 1000 | H86: =E86/G86 -> 15.167938
A87: 2026 | B87: 12 | C87: MARRUECOS | D87: L20 | E87: 18106.726 | F87: 6 | G87: ='Export · supuestos'!$B$12 -> 960 | H87: =E87/G87 -> 18.861173
A88: 2026 | B88: 12 | C88: MARRUECOS | D88: L200 | E88: 5687.9768 | F88: 2 | G88: ='Export · supuestos'!$B$13 -> 800 | H88: =E88/G88 -> 7.109971
A89: 2026 | B89: 12 | C89: MARRUECOS | D89: L5 | E89: 3791.9846 | F89: 2 | G89: ='Export · supuestos'!$B$11 -> 800 | H89: =E89/G89 -> 4.7399807
A90: 2026 | B90: 12 | C90: MARRUECOS | D90: kg5 | E90: 3791.9846 | F90: 3 | G90: ='Export · supuestos'!$B$16 -> 1000 | H90: =E90/G90 -> 3.7919846
A91: 2026 | B91: 12 | C91: NETHERLANS | D91: kg20 | E91: 41711.83 | F91: 2 | G91: ='Export · supuestos'!$B$17 -> 1000 | H91: =E91/G91 -> 41.71183
A92: 2026 | B92: 12 | C92: SERBIA | D92: L1 | E92: 1384.0744 | F92: 2 | G92: ='Export · supuestos'!$B$10 -> 792 | H92: =E92/G92 -> 1.7475686
A93: 2026 | B93: 12 | C93: SERBIA | D93: kg1 | E93: 1895.9923 | F93: 1 | G93: ='Export · supuestos'!$B$15 -> 1056 | H93: =E93/G93 -> 1.7954472
A94: 2026 | B94: 12 | C94: SERBIA | D94: kg20 | E94: 2085.5915 | F94: 1 | G94: ='Export · supuestos'!$B$17 -> 1000 | H94: =E94/G94 -> 2.0855915
A95: 2026 | B95: 12 | C95: SERBIA | D95: kg5 | E95: 1042.7958 | F95: 1 | G95: ='Export · supuestos'!$B$16 -> 1000 | H95: =E95/G95 -> 1.0427958
A96: 2026 | B96: 12 | C96: TURQUÍA | D96: L1000 | E96: 947.99614 | F96: 1 | G96: ='Export · supuestos'!$B$14 -> 1000 | H96: =E96/G96 -> 0.94799614
A97: 2026 | B97: 12 | C97: TURQUÍA | D97: kg1000 | E97: 3791.9846 | F97: 2 | G97: ='Export · supuestos'!$B$18 -> 1000 | H97: =E97/G97 -> 3.7919846
A98: 2026 | B98: 12 | C98: TURQUÍA | D98: kg5 | E98: 23699.903 | F98: 2 | G98: ='Export · supuestos'!$B$16 -> 1000 | H98: =E98/G98 -> 23.699903
A99: 2027 | B99: 1 | C99: AZERBAIYÁN | D99: L1 | E99: 2393 | F99: 1 | G99: ='Export · supuestos'!$B$10 -> 792 | H99: =E99/G99 -> 3.0214646
A100: 2027 | B100: 1 | C100: AZERBAIYÁN | D100: L20 | E100: 26580 | F100: 3 | G100: ='Export · supuestos'!$B$12 -> 960 | H100: =E100/G100 -> 27.6875
A101: 2027 | B101: 1 | C101: AZERBAIYÁN | D101: L5 | E101: 6855 | F101: 1 | G101: ='Export · supuestos'!$B$11 -> 800 | H101: =E101/G101 -> 8.56875
A102: 2027 | B102: 1 | C102: AZERBAIYÁN | D102: kg20 | E102: 7780 | F102: 1 | G102: ='Export · supuestos'!$B$17 -> 1000 | H102: =E102/G102 -> 7.78
A103: 2027 | B103: 1 | C103: AZERBAIYÁN | D103: kg5 | E103: 4365 | F103: 1 | G103: ='Export · supuestos'!$B$16 -> 1000 | H103: =E103/G103 -> 4.365
...

Sheet Export · supuestos
A2: Supuestos de paletización y envíos
A4: Ámbito | B4: Exportación (todos los países salvo España)
A5: Palets máximos por envío | B5: 21
A6: Período 2026 | B6: Octubre a diciembre
A7: Período 2027 | B7: Enero a diciembre
A9: Formato | B9: Capacidad | C9: Unidad | D9: Base del supuesto
A10: L1 | B10: 792 | C10: L/palet | D10: Exportación, envase de 1 L
A11: L5 | B11: 800 | C11: L/palet | D11: Exportación, envase de 5 L
A12: L20 | B12: 960 | C12: L/palet | D12: Exportación, envase de 20 L
A13: L200 | B13: 800 | C13: L/palet | D13: Capacidad de la tabla fotografiada
A14: L1000 | B14: 1000 | C14: L/palet | D14: Un contenedor de 1.000 L por palet
A15: kg1 | B15: 1056 | C15: kg/palet | D15: Nacional y exportación, envase sólido de 1 kg
A16: kg5 | B16: 1000 | C16: kg/palet | D16: Exportación, envase sólido de 5 kg
A17: kg20 | B17: 1000 | C17: kg/palet | D17: Exportación, envase sólido de 20 kg
A18: kg1000 | B18: 1000 | C18: kg/palet | D18: Un envase de 1.000 kg por palet
A21: Reglas de cálculo
A22: 1. Conversión | B22: Las unidades de cada formato se dividen por su capacidad de palet.
A23: 2. Consolidación | B23: Se suman palets equivalentes de productos distintos por país y mes.
A24: 3. Envíos | B24: Se redondea hacia arriba palets equivalentes / 21 en cada país y mes.
A25: 4. Resumen anual | B25: Suma de envíos mensuales. Nunca se redondea el agregado anual.
A26: 5. Clasificación | B26: Litros o kilos según descripción y código del artículo del Excel.
A27: 6. Formatos especiales | B27: Las nuevas capacidades de 5 y 20 kg se aplican también a FLOW y BR-59.
A28: 7. Coste | B28: Sin tarifa por país ni escala de precios: se calculan envíos, no euros.
B29: Coste transporte en 2026 el recibido o cargado este año
B30: Coste transporte en 2027 , es un 10% sobre el del 2026, por inflacion y incremento del combustible.
B31: Coste documentacion: 54 euros certificado de origen + 50 euros envio medio documentacion courier, por envio que lo soliciten
B32: Coste por envio de documentos por la aplicación XCARGO - 75€ (Solo egipto)
B33: Coste envio a LEKKERBIO es una media 50%/50% del coste del envio a MEXICO y LOS ANGELES.
A34: Fuente de unidades
A35: Copia de Presupuesto_Prevision_2026_2027_V6_DEFINITIVO (002).xlsx
A36: Hoja de origen: Detalle Líneas Clasificadas; solo unidades no nulas de exportación.

Sheet Nacional · base
A2: Bases del cálculo
A3: Arriba: unidades por cliente y formato; abajo: coste por cliente y mes. Valores originales de la previsión.
A6: Año | B6: Mes | C6: Cliente | D6: Ruta | E6: Formato | F6: Unidades | G6: Venta (€) | H6: Líneas | I6: Cap./palet | J6: Kilos | K6: Palets equiv.
A7: 2026 | B7: 9 | C7: ACTIV. PRODUC. Y COMERC. LA VEGUILLA, SL | D7: Resto nacional | E7: L20 | F7: 1820.1526 | G7: 4781.9524 | H7: 2 | I7: ='Nacional · supuestos'!$B$21 -> 640 | J7: =F7*'Nacional · supuestos'!$B$4 -> 2147.7801 | K7: =F7/I7 -> 2.8439884
A8: 2026 | B8: 9 | C8: AGROGIMEDEL, S.L.U. | D8: Resto nacional | E8: kg5 | F8: 663.5973 | G8: 4187.2989 | H8: 1 | I8: ='Nacional · supuestos'!$B$25 -> 750 | J8: =F8 -> 663.5973 | K8: =F8/I8 -> 0.8847964
A9: 2026 | B9: 9 | C9: AGRONEW FITO, S.L. | D9: Resto nacional | E9: L1000 | F9: 6635.973 | G9: 11809.622 | H9: 2 | I9: ='Nacional · supuestos'!$B$23 -> 1000 | J9: =F9*'Nacional · supuestos'!$B$4 -> 7830.4481 | K9: =F9/I9 -> 6.635973
A10: 2026 | B10: 9 | C10: AGRONEW FITO, S.L. | D10: Resto nacional | E10: L20 | F10: 1820.1526 | G10: 5387.6517 | H10: 1 | I10: ='Nacional · supuestos'!$B$21 -> 640 | J10: =F10*'Nacional · supuestos'!$B$4 -> 2147.7801 | K10: =F10/I10 -> 2.8439884
A11: 2026 | B11: 9 | C11: AGRONEW FITO, S.L. | D11: Resto nacional | E11: kg20 | F11: 2085.5915 | G11: 3469.9733 | H11: 1 | I11: ='Nacional · supuestos'!$B$26 -> 800 | J11: =F11 -> 2085.5915 | K11: =F11/I11 -> 2.6069894
A12: 2026 | B12: 9 | C12: AGRONEW FITO, S.L. | D12: Resto nacional | E12: kg5 | F12: 284.39884 | G12: 1404.9303 | H12: 1 | I12: ='Nacional · supuestos'!$B$25 -> 750 | J12: =F12 -> 284.39884 | K12: =F12/I12 -> 0.37919846
A13: 2026 | B13: 9 | C13: AGROQUIMICAS DRAGO S.L. | D13: Canarias | E13: L200 | F13: 1516.7938 | G13: 4397.0168 | H13: 1 | I13: ='Nacional · supuestos'!$B$22 -> 800 | J13: =F13*'Nacional · supuestos'!$B$4 -> 1789.8167 | K13: =F13/I13 -> 1.8959923
A14: 2026 | B14: 9 | C14: AGROQUIMICAS DRAGO S.L. | D14: Canarias | E14: kg20 | F14: 1042.7958 | G14: 1590.4721 | H14: 1 | I14: ='Nacional · supuestos'!$B$26 -> 800 | J14: =F14 -> 1042.7958 | K14: =F14/I14 -> 1.3034947
A15: 2026 | B15: 9 | C15: AGROREBOLLO, S.L. | D15: Resto nacional | E15: kg5 | F15: 473.99807 | G15: 3201.857 | H15: 1 | I15: ='Nacional · supuestos'!$B$25 -> 750 | J15: =F15 -> 473.99807 | K15: =F15/I15 -> 0.63199743
A16: 2026 | B16: 9 | C16: AGROSER BERNARDINO, S.L. | D16: Resto nacional | E16: kg20 | F16: 1042.7958 | G16: 1699.7571 | H16: 1 | I16: ='Nacional · supuestos'!$B$26 -> 800 | J16: =F16 -> 1042.7958 | K16: =F16/I16 -> 1.3034947
A17: 2026 | B17: 9 | C17: AGROTRAPICHE, S.L.U | D17: Resto nacional | E17: kg20 | F17: 189.59923 | G17: 904.38832 | H17: 1 | I17: ='Nacional · supuestos'!$B$26 -> 800 | J17: =F17 -> 189.59923 | K17: =F17/I17 -> 0.23699903
A18: 2026 | B18: 9 | C18: AGROTRAPICHE, S.L.U | D18: Resto nacional | E18: kg5 | F18: 284.39884 | G18: 1786.1457 | H18: 1 | I18: ='Nacional · supuestos'!$B$25 -> 750 | J18: =F18 -> 284.39884 | K18: =F18/I18 -> 0.37919846
A19: 2026 | B19: 9 | C19: AGROVEYCA,S.L | D19: Resto nacional | E19: L20 | F19: 379.19846 | G19: 897.35208 | H19: 1 | I19: ='Nacional · supuestos'!$B$21 -> 640 | J19: =F19*'Nacional · supuestos'!$B$4 -> 447.45418 | K19: =F19/I19 -> 0.59249759
A20: 2026 | B20: 9 | C20: AGRUPACION DE LABRADORES DEL POZUELO, SA | D20: Resto nacional | E20: L20 | F20: 284.39884 | G20: 1299.7027 | H20: 2 | I20: ='Nacional · supuestos'!$B$21 -> 640 | J20: =F20*'Nacional · supuestos'!$B$4 -> 335.59063 | K20: =F20/I20 -> 0.44437319
A21: 2026 | B21: 9 | C21: AGRUPACION DE LABRADORES DEL POZUELO, SA | D21: Resto nacional | E21: L5 | F21: 473.99807 | G21: 2373.1836 | H21: 2 | I21: ='Nacional · supuestos'!$B$20 -> 600 | J21: =F21*'Nacional · supuestos'!$B$4 -> 559.31772 | K21: =F21/I21 -> 0.78999678
A22: 2026 | B22: 9 | C22: ASESORAMIENTO TECNICO DE CULTIVOS, S.L. | D22: Resto nacional | E22: L20 | F22: 5460.4578 | G22: 17279.315 | H22: 4 | I22: ='Nacional · supuestos'!$B$21 -> 640 | J22: =F22*'Nacional · supuestos'!$B$4 -> 6443.3402 | K22: =F22/I22 -> 8.5319653
A23: 2026 | B23: 9 | C23: ASESORAMIENTO TECNICO DE CULTIVOS, S.L. | D23: Resto nacional | E23: L5 | F23: 284.39884 | G23: 907.23231 | H23: 1 | I23: ='Nacional · supuestos'!$B$20 -> 600 | J23: =F23*'Nacional · supuestos'!$B$4 -> 335.59063 | K23: =F23/I23 -> 0.47399807
A24: 2026 | B24: 9 | C24: CABRERA MORALES FRANCISCO | D24: Canarias | E24: kg5 | F24: 6256.7745 | G24: 10785.717 | H24: 1 | I24: ='Nacional · supuestos'!$B$25 -> 750 | J24: =F24 -> 6256.7745 | K24: =F24/I24 -> 8.342366
A25: 2026 | B25: 9 | C25: CAMPOEJIDO S.C.A. | D25: Resto nacional | E25: L1 | F25: 45.503815 | G25: 428.71094 | H25: 1 | I25: ='Nacional · supuestos'!$B$19 -> 528 | J25: =F25*'Nacional · supuestos'!$B$4 -> 53.694501 | K25: =F25/I25 -> 0.086181467
A26: 2026 | B26: 9 | C26: CAMPOEJIDO S.C.A. | D26: Resto nacional | E26: L20 | F26: 8190.6866 | G26: 26400.721 | H26: 6 | I26: ='Nacional · supuestos'!$B$21 -> 640 | J26: =F26*'Nacional · supuestos'!$B$4 -> 9665.0102 | K26: =F26/I26 -> 12.797948
A27: 2026 | B27: 9 | C27: CAMPOEJIDO S.C.A. | D27: Resto nacional | E27: L5 | F27: 1137.5954 | G27: 7367.5267 | H27: 5 | I27: ='Nacional · supuestos'!$B$20 -> 600 | J27: =F27*'Nacional · supuestos'!$B$4 -> 1342.3625 | K27: =F27/I27 -> 1.8959923
A28: 2026 | B28: 9 | C28: CAMPOEJIDO S.C.A. | D28: Resto nacional | E28: kg1 | F28: 56.879768 | G28: 535.90222 | H28: 1 | I28: ='Nacional · supuestos'!$B$24 -> 1056 | J28: =F28 -> 56.879768 | K28: =F28/I28 -> 0.053863417
A29: 2026 | B29: 9 | C29: CAMPOEJIDO S.C.A. | D29: Resto nacional | E29: kg5 | F29: 947.99614 | G29: 3950.6421 | H29: 2 | I29: ='Nacional · supuestos'!$B$25 -> 750 | J29: =F29 -> 947.99614 | K29: =F29/I29 -> 1.2639949
A30: 2026 | B30: 9 | C30: CODIMED EXPORT, S.L. | D30: Resto nacional | E30: L20 | F30: 606.71753 | G30: 2323.7281 | H30: 1 | I30: ='Nacional · supuestos'!$B$21 -> 640 | J30: =F30*'Nacional · supuestos'!$B$4 -> 715.92668 | K30: =F30/I30 -> 0.94799614
A31: 2026 | B31: 9 | C31: CODIMED EXPORT, S.L. | D31: Resto nacional | E31: L5 | F31: 189.59923 | G31: 773.56485 | H31: 1 | I31: ='Nacional · supuestos'!$B$20 -> 600 | J31: =F31*'Nacional · supuestos'!$B$4 -> 223.72709 | K31: =F31/I31 -> 0.31599871
A32: 2026 | B32: 9 | C32: COMERCIAL TÉCNICA FITOCARTHAGO, S.L. | D32: Resto nacional | E32: L1000 | F32: 6635.973 | G32: 12073.673 | H32: 2 | I32: ='Nacional · supuestos'!$B$23 -> 1000 | J32: =F32*'Nacional · supuestos'!$B$4 -> 7830.4481 | K32: =F32/I32 -> 6.635973
A33: 2026 | B33: 9 | C33: COMERCIAL TÉCNICA FITOCARTHAGO, S.L. | D33: Resto nacional | E33: L20 | F33: 1213.4351 | G33: 7334.8779 | H33: 2 | I33: ='Nacional · supuestos'!$B$21 -> 640 | J33: =F33*'Nacional · supuestos'!$B$4 -> 1431.8534 | K33: =F33/I33 -> 1.8959923
A34: 2026 | B34: 9 | C34: COMERCIAL TÉCNICA FITOCARTHAGO, S.L. | D34: Resto nacional | E34: L200 | F34: 758.39691 | G34: 1732.9369 | H34: 2 | I34: ='Nacional · supuestos'!$B$22 -> 800 | J34: =F34*'Nacional · supuestos'!$B$4 -> 894.90836 | K34: =F34/I34 -> 0.94799614
A35: 2026 | B35: 9 | C35: COMERCIAL TÉCNICA FITOCARTHAGO, S.L. | D35: Resto nacional | E35: kg20 | F35: 2085.5915 | G35: 3291.9415 | H35: 1 | I35: ='Nacional · supuestos'!$B$26 -> 800 | J35: =F35 -> 2085.5915 | K35: =F35/I35 -> 2.6069894
A36: 2026 | B36: 9 | C36: COOP.AGRIC. SAN ISIDRO S.C.A. | D36: Resto nacional | E36: L20 | F36: 4853.7402 | G36: 15755.241 | H36: 3 | I36: ='Nacional · supuestos'!$B$21 -> 640 | J36: =F36*'Nacional · supuestos'!$B$4 -> 5727.4135 | K36: =F36/I36 -> 7.5839691
A37: 2026 | B37: 9 | C37: COOP.AGRIC. SAN ISIDRO S.C.A. | D37: Resto nacional | E37: L200 | F37: 379.19846 | G37: 1221.019 | H37: 1 | I37: ='Nacional · supuestos'!$B$22 -> 800 | J37: =F37*'Nacional · supuestos'!$B$4 -> 447.45418 | K37: =F37/I37 -> 0.47399807
A38: 2026 | B38: 9 | C38: COOP.AGRIC. SAN ISIDRO S.C.A. | D38: Resto nacional | E38: L5 | F38: 1611.5934 | G38: 9949.4983 | H38: 3 | I38: ='Nacional · supuestos'!$B$20 -> 600 | J38: =F38*'Nacional · supuestos'!$B$4 -> 1901.6803 | K38: =F38/I38 -> 2.6859891
A39: 2026 | B39: 9 | C39: FITOXENT S.C.L.V. | D39: Resto nacional | E39: L20 | F39: 2426.8701 | G39: 7075.5822 | H39: 1 | I39: ='Nacional · supuestos'!$B$21 -> 640 | J39: =F39*'Nacional · supuestos'!$B$4 -> 2863.7067 | K39: =F39/I39 -> 3.7919846
A40: 2026 | B40: 9 | C40: FITOXENT S.C.L.V. | D40: Resto nacional | E40: kg5-FLOW | F40: 4171.183 | G40: 10203.756 | H40: 1 | I40: ='Nacional · supuestos'!$B$28 -> 1100 | J40: =F40 -> 4171.183 | K40: =F40/I40 -> 3.7919846
A41: 2026 | B41: 9 | C41: GUIVARTO AGRICOLA, S.L. | D41: Resto nacional | E41: L1 | F41: 34.127861 | G41: 554.57774 | H41: 1 | I41: ='Nacional · supuestos'!$B$19 -> 528 | J41: =F41*'Nacional · supuestos'!$B$4 -> 40.270876 | K41: =F41/I41 -> 0.0646361
A42: 2026 | B42: 9 | C42: GUIVARTO AGRICOLA, S.L. | D42: Resto nacional | E42: L20 | F42: 1858.0724 | G42: 7131.2459 | H42: 3 | I42: ='Nacional · supuestos'!$B$21 -> 640 | J42: =F42*'Nacional · supuestos'!$B$4 -> 2192.5255 | K42: =F42/I42 -> 2.9032382
A43: 2026 | B43: 9 | C43: GUIVARTO AGRICOLA, S.L. | D43: Resto nacional | E43: L5 | F43: 758.39691 | G43: 4338.8206 | H43: 2 | I43: ='Nacional · supuestos'!$B$20 -> 600 | J43: =F43*'Nacional · supuestos'!$B$4 -> 894.90836 | K43: =F43/I43 -> 1.2639949
A44: 2026 | B44: 9 | C44: GUIVARTO AGRICOLA, S.L. | D44: Resto nacional | E44: kg5 | F44: 142.19942 | G44: 796.94875 | H44: 2 | I44: ='Nacional · supuestos'!$B$25 -> 750 | J44: =F44 -> 142.19942 | K44: =F44/I44 -> 0.18959923
A45: 2026 | B45: 9 | C45: GUIVARTO AGRICOLA, S.L. | D45: Resto nacional | E45: kg5-FLOW | F45: 758.39691 | G45: 2129.1552 | H45: 1 | I45: ='Nacional · supuestos'!$B$28 -> 1100 | J45: =F45 -> 758.39691 | K45: =F45/I45 -> 0.68945174
A46: 2026 | B46: 9 | C46: INIESTA DEL PINO DISTRIBUCIONES S.L.U | D46: Resto nacional | E46: L20 | F46: 606.71753 | G46: 2093.1755 | H46: 1 | I46: ='Nacional · supuestos'!$B$21 -> 640 | J46: =F46*'Nacional · supuestos'!$B$4 -> 715.92668 | K46: =F46/I46 -> 0.94799614
A47: 2026 | B47: 9 | C47: INIESTA DEL PINO DISTRIBUCIONES S.L.U | D47: Resto nacional | E47: L5 | F47: 56.879768 | G47: 860.5909 | H47: 1 | I47: ='Nacional · supuestos'!$B$20 -> 600 | J47: =F47*'Nacional · supuestos'!$B$4 -> 67.118127 | K47: =F47/I47 -> 0.094799614
A48: 2026 | B48: 9 | C48: SERVIAGRI´ 97, S.L. | D48: Resto nacional | E48: L1 | F48: 11.375954 | G48: 56.026572 | H48: 1 | I48: ='Nacional · supuestos'!$B$19 -> 528 | J48: =F48*'Nacional · supuestos'!$B$4 -> 13.423625 | K48: =F48/I48 -> 0.021545367
A49: 2026 | B49: 9 | C49: SERVIAGRI´ 97, S.L. | D49: Resto nacional | E49: L5 | F49: 663.5973 | G49: 2129.2836 | H49: 4 | I49: ='Nacional · supuestos'!$B$20 -> 600 | J49: =F49*'Nacional · supuestos'!$B$4 -> 783.04481 | K49: =F49/I49 -> 1.1059955
A50: 2026 | B50: 9 | C50: SERVIAGRI´ 97, S.L. | D50: Resto nacional | E50: kg5-FLOW | F50: 284.39884 | G50: 790.58291 | H50: 1 | I50: ='Nacional · supuestos'!$B$28 -> 1100 | J50: =F50 -> 284.39884 | K50: =F50/I50 -> 0.2585444
A51: 2026 | B51: 9 | C51: TRATAMIENTOS AGRICOLAS BRENES, S.L. | D51: Resto nacional | E51: kg20 | F51: 1042.7958 | G51: 1929.1721 | H51: 1 | I51: ='Nacional · supuestos'!$B$26 -> 800 | J51: =F51 -> 1042.7958 | K51: =F51/I51 -> 1.3034947
A52: 2026 | B52: 10 | C52: ACTIV. PRODUC. Y COMERC. LA VEGUILLA, SL | D52: Resto nacional | E52: L20 | F52: 1782.2327 | G52: 4672.0883 | H52: 2 | I52: ='Nacional · supuestos'!$B$21 -> 640 | J52: =F52*'Nacional · supuestos'!$B$4 -> 2103.0346 | K52: =F52/I52 -> 2.7847387
A53: 2026 | B53: 10 | C53: AGRONEW FITO, S.L. | D53: Resto nacional | E53: L1000 | F53: 4739.9807 | G53: 7107.5609 | H53: 1 | I53: ='Nacional · supuestos'!$B$23 -> 1000 | J53: =F53*'Nacional · supuestos'!$B$4 -> 5593.1772 | K53: =F53/I53 -> 4.7399807
A54: 2026 | B54: 10 | C54: AGRONEW FITO, S.L. | D54: Resto nacional | E54: kg20 | F54: 1042.7958 | G54: 1734.9867 | H54: 1 | I54: ='Nacional · supuestos'!$B$26 -> 800 | J54: =F54 -> 1042.7958 | K54: =F54/I54 -> 1.3034947
A55: 2026 | B55: 10 | C55: AGROQUIMICAS DRAGO S.L. | D55: Canarias | E55: L1000 | F55: 1895.9923 | G55: 3659.2651 | H55: 1 | I55: ='Nacional · supuestos'!$B$23 -> 1000 | J55: =F55*'Nacional · supuestos'!$B$4 -> 2237.2709 | K55: =F55/I55 -> 1.8959923
A56: 2026 | B56: 10 | C56: AGROQUIMICAS DRAGO S.L. | D56: Canarias | E56: L20 | F56: 3924.704 | G56: 9883.0597 | H56: 6 | I56: ='Nacional · supuestos'!$B$21 -> 640 | J56: =F56*'Nacional · supuestos'!$B$4 -> 4631.1507 | K56: =F56/I56 -> 6.13235
A57: 2026 | B57: 10 | C57: AGROQUIMICAS DRAGO S.L. | D57: Canarias | E57: L200 | F57: 3033.5876 | G57: 7465.4907 | H57: 4 | I57: ='Nacional · supuestos'!$B$22 -> 800 | J57: =F57*'Nacional · supuestos'!$B$4 -> 3579.6334 | K57: =F57/I57 -> 3.7919846
A58: 2026 | B58: 10 | C58: AGROQUIMICAS DRAGO S.L. | D58: Canarias | E58: L5 | F58: 94.799614 | G58: 342.8744 | H58: 1 | I58: ='Nacional · supuestos'!$B$20 -> 600 | J58: =F58*'Nacional · supuestos'!$B$4 -> 111.86354 | K58: =F58/I58 -> 0.15799936
A59: 2026 | B59: 10 | C59: AGROQUIMICAS DRAGO S.L. | D59: Canarias | E59: kg20 | F59: 2085.5915 | G59: 3180.9442 | H59: 1 | I59: ='Nacional · supuestos'!$B$26 -> 800 | J59: =F59 -> 2085.5915 | K59: =F59/I59 -> 2.6069894
A60: 2026 | B60: 10 | C60: AGROSER BERNARDINO, S.L. | D60: Resto nacional | E60: L1000 | F60: 1895.9923 | G60: 3638.4092 | H60: 1 | I60: ='Nacional · supuestos'!$B$23 -> 1000 | J60: =F60*'Nacional · supuestos'!$B$4 -> 2237.2709 | K60: =F60/I60 -> 1.8959923
A61: 2026 | B61: 10 | C61: AGROSER BERNARDINO, S.L. | D61: Resto nacional | E61: L20 | F61: 1820.1526 | G61: 4811.27 | H61: 2 | I61: ='Nacional · supuestos'!$B$21 -> 640 | J61: =F61*'Nacional · supuestos'!$B$4 -> 2147.7801 | K61: =F61/I61 -> 2.8439884
A62: 2026 | B62: 10 | C62: AGROSER BERNARDINO, S.L. | D62: Resto nacional | E62: L5 | F62: 568.79768 | G62: 2235.3749 | H62: 1 | I62: ='Nacional · supuestos'!$B$20 -> 600 | J62: =F62*'Nacional · supuestos'!$B$4 -> 671.18127 | K62: =F62/I62 -> 0.94799614
A63: 2026 | B63: 10 | C63: AGROSER BERNARDINO, S.L. | D63: Resto nacional | E63: kg20 | F63: 2085.5915 | G63: 3399.5142 | H63: 1 | I63: ='Nacional · supuestos'!$B$26 -> 800 | J63: =F63 -> 2085.5915 | K63: =F63/I63 -> 2.6069894
A64: 2026 | B64: 10 | C64: AGROTRAPICHE, S.L.U | D64: Resto nacional | E64: L5 | F64: 94.799614 | G64: 492.01 | H64: 1 | I64: ='Nacional · supuestos'!$B$20 -> 600 | J64: =F64*'Nacional · supuestos'!$B$4 -> 111.86354 | K64: =F64/I64 -> 0.15799936
A65: 2026 | B65: 10 | C65: AGROVEYCA,S.L | D65: Resto nacional | E65: L20 | F65: 891.11637 | G65: 2432.4949 | H65: 2 | I65: ='Nacional · supuestos'!$B$21 -> 640 | J65: =F65*'Nacional · supuestos'!$B$4 -> 1051.5173 | K65: =F65/I65 -> 1.3923693
A66: 2026 | B66: 10 | C66: AGRUPACION DE LABRADORES DEL POZUELO, SA | D66: Resto nacional | E66: L20 | F66: 284.39884 | G66: 1299.7027 | H66: 2 | I66: ='Nacional · supuestos'!$B$21 -> 640 | J66: =F66*'Nacional · supuestos'!$B$4 -> 335.59063 | K66: =F66/I66 -> 0.44437319
A67: 2026 | B67: 10 | C67: AGRUPACION DE LABRADORES DEL POZUELO, SA | D67: Resto nacional | E67: L5 | F67: 284.39884 | G67: 1574.9708 | H67: 1 | I67: ='Nacional · supuestos'!$B$20 -> 600 | J67: =F67*'Nacional · supuestos'!$B$4 -> 335.59063 | K67: =F67/I67 -> 0.47399807
A68: 2026 | B68: 10 | C68: ASESORAMIENTO TECNICO DE CULTIVOS, S.L. | D68: Resto nacional | E68: L20 | F68: 3640.3052 | G68: 11465.445 | H68: 4 | I68: ='Nacional · supuestos'!$B$21 -> 640 | J68: =F68*'Nacional · supuestos'!$B$4 -> 4295.5601 | K68: =F68/I68 -> 5.6879768
A69: 2026 | B69: 10 | C69: ASESORAMIENTO TECNICO DE CULTIVOS, S.L. | D69: Resto nacional | E69: kg5 | F69: 473.99807 | G69: 1985.1039 | H69: 1 | I69: ='Nacional · supuestos'!$B$25 -> 750 | J69: =F69 -> 473.99807 | K69: =F69/I69 -> 0.63199743
A70: 2026 | B70: 10 | C70: CABRERA MORALES FRANCISCO | D70: Canarias | E70: L20 | F70: 1213.4351 | G70: 2341.9297 | H70: 1 | I70: ='Nacional · supuestos'!$B$21 -> 640 | J70: =F70*'Nacional · supuestos'!$B$4 -> 1431.8534 | K70: =F70/I70 -> 1.8959923
A71: 2026 | B71: 10 | C71: CABRERA MORALES FRANCISCO | D71: Canarias | E71: L5 | F71: 1137.5954 | G71: 2423.0781 | H71: 1 | I71: ='Nacional · supuestos'!$B$20 -> 600 | J71: =F71*'Nacional · supuestos'!$B$4 -> 1342.3625 | K71: =F71/I71 -> 1.8959923
A72: 2026 | B72: 10 | C72: CABRERA MORALES FRANCISCO | D72: Canarias | E72: kg20 | F72: 1042.7958 | G72: 1624.0691 | H72: 1 | I72: ='Nacional · supuestos'!$B$26 -> 800 | J72: =F72 -> 1042.7958 | K72: =F72/I72 -> 1.3034947
A73: 2026 | B73: 10 | C73: CABRERA MORALES FRANCISCO | D73: Canarias | E73: kg5 | F73: 4171.183 | G73: 7190.4778 | H73: 1 | I73: ='Nacional · supuestos'!$B$25 -> 750 | J73: =F73 -> 4171.183 | K73: =F73/I73 -> 5.5615774
A74: 2026 | B74: 10 | C74: CAMPOEJIDO S.C.A. | D74: Resto nacional | E74: L20 | F74: 11470.753 | G74: 32988.246 | H74: 5 | I74: ='Nacional · supuestos'!$B$21 -> 640 | J74: =F74*'Nacional · supuestos'!$B$4 -> 13535.489 | K74: =F74/I74 -> 17.923052
A75: 2026 | B75: 10 | C75: CAMPOEJIDO S.C.A. | D75: Resto nacional | E75: L5 | F75: 872.15645 | G75: 4704.2281 | H75: 6 | I75: ='Nacional · supuestos'!$B$20 -> 600 | J75: =F75*'Nacional · supuestos'!$B$4 -> 1029.1446 | K75: =F75/I75 -> 1.4535941
A76: 2026 | B76: 10 | C76: CAMPOEJIDO S.C.A. | D76: Resto nacional | E76: kg1 | F76: 113.75954 | G76: 1071.8044 | H76: 1 | I76: ='Nacional · supuestos'!$B$24 -> 1056 | J76: =F76 -> 113.75954 | K76: =F76/I76 -> 0.10772683
A77: 2026 | B77: 10 | C77: CAMPOEJIDO S.C.A. | D77: Resto nacional | E77: kg5 | F77: 805.79672 | G77: 3192.3258 | H77: 1 | I77: ='Nacional · supuestos'!$B$25 -> 750 | J77: =F77 -> 805.79672 | K77: =F77/I77 -> 1.0743956
A78: 2026 | B78: 10 | C78: CODIMED EXPORT, S.L. | D78: Resto nacional | E78: L1000 | F78: 2843.9884 | G78: 6550.6533 | H78: 2 | I78: ='Nacional · supuestos'!$B$23 -> 1000 | J78: =F78*'Nacional · supuestos'!$B$4 -> 3355.9063 | K78: =F78/I78 -> 2.8439884
A79: 2026 | B79: 10 | C79: CODIMED EXPORT, S.L. | D79: Resto nacional | E79: L20 | F79: 1213.4351 | G79: 3743.4472 | H79: 2 | I79: ='Nacional · supuestos'!$B$21 -> 640 | J79: =F79*'Nacional · supuestos'!$B$4 -> 1431.8534 | K79: =F79/I79 -> 1.8959923
A80: 2026 | B80: 10 | C80: CODIMED EXPORT, S.L. | D80: Resto nacional | E80: kg20 | F80: 1801.1927 | G80: 4201.7969 | H80: 2 | I80: ='Nacional · supuestos'!$B$26 -> 800 | J80: =F80 -> 1801.1927 | K80: =F80/I80 -> 2.2514908
A81: 2026 | B81: 10 | C81: COMERCIAL TÉCNICA FITOCARTHAGO, S.L. | D81: Resto nacional | E81: L1000 | F81: 7583.9691 | G81: 14377.303 | H81: 2 | I81: ='Nacional · supuestos'!$B$23 -> 1000 | J81: =F81*'Nacional · supuestos'!$B$4 -> 8949.0836 | K81: =F81/I81 -> 7.5839691
A82: 2026 | B82: 10 | C82: COMERCIAL TÉCNICA FITOCARTHAGO, S.L. | D82: Resto nacional | E82: L20 | F82: 3317.9865 | G82: 17961.198 | H82: 5 | I82: ='Nacional · supuestos'!$B$21 -> 640 | J82: =F82*'Nacional · supuestos'!$B$4 -> 3915.2241 | K82: =F82/I82 -> 5.1843539
A83: 2026 | B83: 10 | C83: COMERCIAL TÉCNICA FITOCARTHAGO, S.L. | D83: Resto nacional | E83: L200 | F83: 2275.1907 | G83: 4899.244 | H83: 2 | I83: ='Nacional · supuestos'!$B$22 -> 800 | J83: =F83*'Nacional · supuestos'!$B$4 -> 2684.7251 | K83: =F83/I83 -> 2.8439884
A84: 2026 | B84: 10 | C84: COMERCIAL TÉCNICA FITOCARTHAGO, S.L. | D84: Resto nacional | E84: kg20 | F84: 10901.956 | G84: 22850.249 | H84: 3 | I84: ='Nacional · supuestos'!$B$26 -> 800 | J84: =F84 -> 10901.956 | K84: =F84/I84 -> 13.627445
A85: 2026 | B85: 10 | C85: COOP.AGRIC. SAN ISIDRO S.C.A. | D85: Resto nacional | E85: L20 | F85: 7887.3279 | G85: 24481.861 | H85: 4 | I85: ='Nacional · supuestos'!$B$21 -> 640 | J85: =F85*'Nacional · supuestos'!$B$4 -> 9307.0469 | K85: =F85/I85 -> 12.32395
A86: 2026 | B86: 10 | C86: COOP.AGRIC. SAN ISIDRO S.C.A. | D86: Resto nacional | E86: L5 | F86: 1516.7938 | G86: 9240.3972 | H86: 3 | I86: ='Nacional · supuestos'!$B$20 -> 600 | J86: =F86*'Nacional · supuestos'!$B$4 -> 1789.8167 | K86: =F86/I86 -> 2.5279897
A87: 2026 | B87: 10 | C87: FITOMURCIA S.L. | D87: Resto nacional | E87: L1000 | F87: 8531.9653 | G87: 13076.626 | H87: 1 | I87: ='Nacional · supuestos'!$B$23 -> 1000 | J87: =F87*'Nacional · supuestos'!$B$4 -> 10067.719 | K87: =F87/I87 -> 8.5319653
A88: 2026 | B88: 10 | C88: FITOMURCIA S.L. | D88: Resto nacional | E88: L20 | F88: 4853.7402 | G88: 18117.852 | H88: 4 | I88: ='Nacional · supuestos'!$B$21 -> 640 | J88: =F88*'Nacional · supuestos'!$B$4 -> 5727.4135 | K88: =F88/I88 -> 7.5839691
A89: 2026 | B89: 10 | C89: FITOMURCIA S.L. | D89: Resto nacional | E89: kg20 | F89: 758.39691 | G89: 2513.7735 | H89: 1 | I89: ='Nacional · supuestos'!$B$26 -> 800 | J89: =F89 -> 758.39691 | K89: =F89/I89 -> 0.94799614
A90: 2026 | B90: 10 | C90: FITOSANITARIOS DRAGO S.L.U | D90: Canarias | E90: L1000 | F90: 9479.9614 | G90: 22508.54 | H90: 2 | I90: ='Nacional · supuestos'!$B$23 -> 1000 | J90: =F90*'Nacional · supuestos'!$B$4 -> 11186.354 | K90: =F90/I90 -> 9.4799614
A91: 2026 | B91: 10 | C91: FITOSANITARIOS DRAGO S.L.U | D91: Canarias | E91: L20 | F91: 2635.4293 | G91: 7535.9398 | H91: 3 | I91: ='Nacional · supuestos'!$B$21 -> 640 | J91: =F91*'Nacional · supuestos'!$B$4 -> 3109.8065 | K91: =F91/I91 -> 4.1178582
A92: 2026 | B92: 10 | C92: FITOSANITARIOS DRAGO S.L.U | D92: Canarias | E92: L200 | F92: 758.39691 | G92: 2143.013 | H92: 1 | I92: ='Nacional · supuestos'!$B$22 -> 800 | J92: =F92*'Nacional · supuestos'!$B$4 -> 894.90836 | K92: =F92/I92 -> 0.94799614
A93: 2026 | B93: 10 | C93: FITOXENT S.C.L.V. | D93: Resto nacional | E93: L20 | F93: 3033.5876 | G93: 8719.18 | H93: 2 | I93: ='Nacional · supuestos'!$B$21 -> 640 | J93: =F93*'Nacional · supuestos'!$B$4 -> 3579.6334 | K93: =F93/I93 -> 4.7399807
A94: 2026 | B94: 10 | C94: GUIVARTO AGRICOLA, S.L. | D94: Resto nacional | E94: L20 | F94: 3564.4655 | G94: 12020.898 | H94: 3 | I94: ='Nacional · supuestos'!$B$21 -> 640 | J94: =F94*'Nacional · supuestos'!$B$4 -> 4206.0693 | K94: =F94/I94 -> 5.5694773
A95: 2026 | B95: 10 | C95: GUIVARTO AGRICOLA, S.L. | D95: Resto nacional | E95: L5 | F95: 701.51714 | G95: 5529.8398 | H95: 4 | I95: ='Nacional · supuestos'!$B$20 -> 600 | J95: =F95*'Nacional · supuestos'!$B$4 -> 827.79023 | K95: =F95/I95 -> 1.1691952
A96: 2026 | B96: 10 | C96: GUIVARTO AGRICOLA, S.L. | D96: Resto nacional | E96: kg1 | F96: 102.38358 | G96: 997.2161 | H96: 1 | I96: ='Nacional · supuestos'!$B$24 -> 1056 | J96: =F96 -> 102.38358 | K96: =F96/I96 -> 0.096954151
A97: 2026 | B97: 10 | C97: INIESTA DEL PINO DISTRIBUCIONES S.L.U | D97: Resto nacional | E97: L20 | F97: 1820.1526 | G97: 6279.5264 | H97: 1 | I97: ='Nacional · supuestos'!$B$21 -> 640 | J97: =F97*'Nacional · supuestos'!$B$4 -> 2147.7801 | K97: =F97/I97 -> 2.8439884
A98: 2026 | B98: 10 | C98: INIESTA DEL PINO DISTRIBUCIONES S.L.U | D98: Resto nacional | E98: L5 | F98: 75.839691 | G98: 1147.4545 | H98: 1 | I98: ='Nacional · supuestos'!$B$20 -> 600 | J98: =F98*'Nacional · supuestos'!$B$4 -> 89.490836 | K98: =F98/I98 -> 0.12639949
A99: 2026 | B99: 10 | C99: INIESTA DEL PINO DISTRIBUCIONES S.L.U | D99: Resto nacional | E99: kg5 | F99: 71.09971 | G99: 308.66754 | H99: 1 | I99: ='Nacional · supuestos'!$B$25 -> 750 | J99: =F99 -> 71.09971 | K99: =F99/I99 -> 0.094799614
A100: 2026 | B100: 10 | C100: ROMAROC PONIENTE, S.L. | D100: Resto nacional | E100: L200 | F100: 758.39691 | G100: 2540.6297 | H100: 1 | I100: ='Nacional · supuestos'!$B$22 -> 800 | J100: =F100*'Nacional · supuestos'!$B$4 -> 894.90836 | K100: =F100/I100 -> 0.94799614
A101: 2026 | B101: 10 | C101: SERVIAGRI´ 97, S.L. | D101: Resto nacional | E101: L20 | F101: 1175.5152 | G101: 3302.3724 | H101: 2 | I101: ='Nacional · supuestos'!$B$21 -> 640 | J101: =F101*'Nacional · supuestos'!$B$4 -> 1387.108 | K101: =F101/I101 -> 1.8367425
A102: 2026 | B102: 10 | C102: SERVIAGRI´ 97, S.L. | D102: Resto nacional | E102: L5 | F102: 663.5973 | G102: 2129.2836 | H102: 4 | I102: ='Nacional · supuestos'!$B$20 -> 600 | J102: =F102*'Nacional · supuestos'!$B$4 -> 783.04481 | K102: =F102/I102 -> 1.1059955
A103: 2026 | B103: 10 | C103: SERVIAGRI´ 97, S.L. | D103: Resto nacional | E103: kg5 | F103: 189.59923 | G103: 875.19004 | H103: 1 | I103: ='Nacional · supuestos'!$B$25 -> 750 | J103: =F103 -> 189.59923 | K103: =F103/I103 -> 0.25279897
...

Sheet Nacional · supuestos
A2: Supuestos de transporte nacional y Canarias
A3: Entradas editables en amarillo · 2027 utiliza la previsión de volúmenes y un incremento de tarifa del 10 %.
A4: Densidad de líquidos (kg/L) | B4: 1.18
A5: Ámbito 2026 | B5: Septiembre a diciembre
A6: Incremento de costes 2027 | B6: =B7+B8 -> 0.1
A7: IPC presupuestado | B7: 0.045
A8: Incremento por combustible | B8: 0.055
A11: Coste base Campillo 2026 (€) | B11: 82638
A12: Kilos de referencia Campillo 2026 | B12: 931964
A13: Coste Campillo por kg (€) | B13: =B11/B12 -> 0.088670807
A14: Unidades de palet 2026 | B14: 1077
A15: Coste Campillo por palet (€) | B15: =B11/B14 -> 76.729805
A18: Formato | B18: Capacidad | C18: Unidad | D18: Criterio nacional
A19: L1 | B19: 528 | C19: L/palet | D19: Tabla nacional: envase 1 L
A20: L5 | B20: 600 | C20: L/palet | D20: Tabla nacional: envase 5 L
A21: L20 | B21: 640 | C21: L/palet | D21: Tabla nacional: envase 20 L
A22: L200 | B22: 800 | C22: L/palet | D22: Tabla nacional: bidón 200 L
A23: L1000 | B23: 1000 | C23: L/palet | D23: Un contenedor de 1.000 L por palet
A24: kg1 | B24: 1056 | C24: kg/palet | D24: Envase sólido de 1 kg, nacional y exportación
A25: kg5 | B25: 750 | C25: kg/palet | D25: Tabla nacional: envase 5 kg
A26: kg20 | B26: 800 | C26: kg/palet | D26: Tabla nacional: envase 20 kg
A27: kg1000 | B27: 1000 | C27: kg/palet | D27: Un envase de 1.000 kg por palet
A28: kg5-FLOW | B28: 1100 | C28: kg/palet | D28: FLOW / Fitokontrol, 5 kg
A29: kg20-FLOW | B29: 1100 | C29: kg/palet | D29: FLOW, 20 kg
A30: kg5-BR59 | B30: 1100 | C30: kg/palet | D30: BR-59, 5 kg
A31: kg20-BR59 | B31: 1100 | C31: kg/palet | D31: BR-59, 20 kg; capacidad especial aplicada
A33: Tramo de kg por expedición | B33: Drago €/kg | C33: Cabrera €/kg
A34: Hasta 2.000 | B34: 0.114 | C34: 0.207
A35: 2.000 a 5.000 | B35: 0.108 | C35: 0.202
A36: Más de 5.000 | B36: 0.104 | C36: 0.198
A38: Flete mínimo por expedición | B38: 24 | C38: 38
A41: Recogida €/kg | B41: 0.036
A42: Recogida mínima por expedición (€) | B42: 9
A43: Recargo IMO €/kg | B43: 0.012
A44: GRI €/kg | B44: 0.018
A45: Emergency Fuel €/kg | B45: 0.022
A46: DUA origen €/expedición (€) | B46: 15
A47: Seguro sobre valor de venta | B47: 0.0045
A48: Seguro mínimo por expedición (€) | B48: 2.5
A49: Relación de volumen (kg/m³) | B49: 333
A52: Criterios y alcance
A53: Rutas | B53: Resto nacional por Campillo; los tres clientes Drago/Cabrera por Sealine.
A54: Kilos | B54: Los sólidos conservan kg; líquidos × 1,18 kg/L.
A55: Palets | B55: Se suman formatos por cliente y mes; el total se redondea hacia arriba.
A56: Costes 2026 | B56: Campillo: coste medio base por kg. Sealine: una expedición por cliente y mes.
A57: Costes 2027 | B57: Tarifa base 2026 aplicada al volumen 2027, después × (1 + IPC + combustible).
A58: Seguro | B58: 0,45 % del valor previsto de venta como aproximación al valor asegurado.
A59: Conceptos excluidos | B59: T-3 embarque sin importe; gastos de destino, volumen facturable y otros extras no disponibles.
A60: Validez | B60: Tarifas de Campillo y Sealine aportadas válidas hasta 31/12/2026.
A61: Origen | B61: Previsión de ventas 2026–2027; tarifa Palletways 2026; oferta Sealine CANLCL00612.
