Workbook

Sheet Resumen mensual
A2: Presupuesto de compras · resumen mensual 2027
A4: Compras netas tras aplicar el stock; FILM incorpora las necesidades mensuales de FILMPR.
A6: Mes | B6: Formulados | C6: Envasados | D6: Compras calculadas | E6: Líneas sin precio | F6: Total sin reserva | G6: Reserva 3 % | H6: Presupuesto con reserva
A7: Ene | B7: =SUMIF(Importes!$C$8:$C$149,"Formulados",Importes!E8:E149) -> 265351.09 | C7: =SUMIF(Importes!$C$8:$C$149,"Envasados",Importes!E8:E149) -> 44591.897 | D7: =SUM(B7:C7) -> 309942.98 | E7: =COUNTIFS(Unidades!S8:S149,">0",Precios!$I$8:$I$149,"FALTA PRECIO") -> 0 | F7: =IF(E7=0,D7,"") -> 309942.98 | G7: =IF(E7=0,F7*Supuestos!$B$6,"") -> 9298.2895 | H7: =IF(E7=0,F7+G7,"") -> 319241.27
A8: Feb | B8: =SUMIF(Importes!$C$8:$C$149,"Formulados",Importes!F8:F149) -> 486359.41 | C8: =SUMIF(Importes!$C$8:$C$149,"Envasados",Importes!F8:F149) -> 114627.59 | D8: =SUM(B8:C8) -> 600987 | E8: =COUNTIFS(Unidades!T8:T149,">0",Precios!$I$8:$I$149,"FALTA PRECIO") -> 0 | F8: =IF(E8=0,D8,"") -> 600987 | G8: =IF(E8=0,F8*Supuestos!$B$6,"") -> 18029.61 | H8: =IF(E8=0,F8+G8,"") -> 619016.61
A9: Mar | B9: =SUMIF(Importes!$C$8:$C$149,"Formulados",Importes!G8:G149) -> 505792 | C9: =SUMIF(Importes!$C$8:$C$149,"Envasados",Importes!G8:G149) -> 127059.65 | D9: =SUM(B9:C9) -> 632851.65 | E9: =COUNTIFS(Unidades!U8:U149,">0",Precios!$I$8:$I$149,"FALTA PRECIO") -> 0 | F9: =IF(E9=0,D9,"") -> 632851.65 | G9: =IF(E9=0,F9*Supuestos!$B$6,"") -> 18985.549 | H9: =IF(E9=0,F9+G9,"") -> 651837.2
A10: Abr | B10: =SUMIF(Importes!$C$8:$C$149,"Formulados",Importes!H8:H149) -> 394529.55 | C10: =SUMIF(Importes!$C$8:$C$149,"Envasados",Importes!H8:H149) -> 95397.618 | D10: =SUM(B10:C10) -> 489927.17 | E10: =COUNTIFS(Unidades!V8:V149,">0",Precios!$I$8:$I$149,"FALTA PRECIO") -> 0 | F10: =IF(E10=0,D10,"") -> 489927.17 | G10: =IF(E10=0,F10*Supuestos!$B$6,"") -> 14697.815 | H10: =IF(E10=0,F10+G10,"") -> 504624.98
A11: May | B11: =SUMIF(Importes!$C$8:$C$149,"Formulados",Importes!I8:I149) -> 630729.55 | C11: =SUMIF(Importes!$C$8:$C$149,"Envasados",Importes!I8:I149) -> 170158.83 | D11: =SUM(B11:C11) -> 800888.39 | E11: =COUNTIFS(Unidades!W8:W149,">0",Precios!$I$8:$I$149,"FALTA PRECIO") -> 0 | F11: =IF(E11=0,D11,"") -> 800888.39 | G11: =IF(E11=0,F11*Supuestos!$B$6,"") -> 24026.652 | H11: =IF(E11=0,F11+G11,"") -> 824915.04
A12: Jun | B12: =SUMIF(Importes!$C$8:$C$149,"Formulados",Importes!J8:J149) -> 655001.92 | C12: =SUMIF(Importes!$C$8:$C$149,"Envasados",Importes!J8:J149) -> 171790.12 | D12: =SUM(B12:C12) -> 826792.04 | E12: =COUNTIFS(Unidades!X8:X149,">0",Precios!$I$8:$I$149,"FALTA PRECIO") -> 0 | F12: =IF(E12=0,D12,"") -> 826792.04 | G12: =IF(E12=0,F12*Supuestos!$B$6,"") -> 24803.761 | H12: =IF(E12=0,F12+G12,"") -> 851595.8
A13: Jul | B13: =SUMIF(Importes!$C$8:$C$149,"Formulados",Importes!K8:K149) -> 422019.33 | C13: =SUMIF(Importes!$C$8:$C$149,"Envasados",Importes!K8:K149) -> 110862.26 | D13: =SUM(B13:C13) -> 532881.59 | E13: =COUNTIFS(Unidades!Y8:Y149,">0",Precios!$I$8:$I$149,"FALTA PRECIO") -> 0 | F13: =IF(E13=0,D13,"") -> 532881.59 | G13: =IF(E13=0,F13*Supuestos!$B$6,"") -> 15986.448 | H13: =IF(E13=0,F13+G13,"") -> 548868.04
A14: Ago | B14: =SUMIF(Importes!$C$8:$C$149,"Formulados",Importes!L8:L149) -> 254773.2 | C14: =SUMIF(Importes!$C$8:$C$149,"Envasados",Importes!L8:L149) -> 64852.99 | D14: =SUM(B14:C14) -> 319626.19 | E14: =COUNTIFS(Unidades!Z8:Z149,">0",Precios!$I$8:$I$149,"FALTA PRECIO") -> 0 | F14: =IF(E14=0,D14,"") -> 319626.19 | G14: =IF(E14=0,F14*Supuestos!$B$6,"") -> 9588.7857 | H14: =IF(E14=0,F14+G14,"") -> 329214.98
A15: Sep | B15: =SUMIF(Importes!$C$8:$C$149,"Formulados",Importes!M8:M149) -> 157733.49 | C15: =SUMIF(Importes!$C$8:$C$149,"Envasados",Importes!M8:M149) -> 35732.125 | D15: =SUM(B15:C15) -> 193465.61 | E15: =COUNTIFS(Unidades!AA8:AA149,">0",Precios!$I$8:$I$149,"FALTA PRECIO") -> 0 | F15: =IF(E15=0,D15,"") -> 193465.61 | G15: =IF(E15=0,F15*Supuestos!$B$6,"") -> 5803.9684 | H15: =IF(E15=0,F15+G15,"") -> 199269.58
A16: Oct | B16: =SUMIF(Importes!$C$8:$C$149,"Formulados",Importes!N8:N149) -> 259565.29 | C16: =SUMIF(Importes!$C$8:$C$149,"Envasados",Importes!N8:N149) -> 62617.725 | D16: =SUM(B16:C16) -> 322183.02 | E16: =COUNTIFS(Unidades!AB8:AB149,">0",Precios!$I$8:$I$149,"FALTA PRECIO") -> 0 | F16: =IF(E16=0,D16,"") -> 322183.02 | G16: =IF(E16=0,F16*Supuestos!$B$6,"") -> 9665.4906 | H16: =IF(E16=0,F16+G16,"") -> 331848.51
A17: Nov | B17: =SUMIF(Importes!$C$8:$C$149,"Formulados",Importes!O8:O149) -> 406765.12 | C17: =SUMIF(Importes!$C$8:$C$149,"Envasados",Importes!O8:O149) -> 107338.49 | D17: =SUM(B17:C17) -> 514103.6 | E17: =COUNTIFS(Unidades!AC8:AC149,">0",Precios!$I$8:$I$149,"FALTA PRECIO") -> 0 | F17: =IF(E17=0,D17,"") -> 514103.6 | G17: =IF(E17=0,F17*Supuestos!$B$6,"") -> 15423.108 | H17: =IF(E17=0,F17+G17,"") -> 529526.71
A18: Dic | B18: =SUMIF(Importes!$C$8:$C$149,"Formulados",Importes!P8:P149) -> 411940.97 | C18: =SUMIF(Importes!$C$8:$C$149,"Envasados",Importes!P8:P149) -> 116379.27 | D18: =SUM(B18:C18) -> 528320.24 | E18: =COUNTIFS(Unidades!AD8:AD149,">0",Precios!$I$8:$I$149,"FALTA PRECIO") -> 0 | F18: =IF(E18=0,D18,"") -> 528320.24 | G18: =IF(E18=0,F18*Supuestos!$B$6,"") -> 15849.607 | H18: =IF(E18=0,F18+G18,"") -> 544169.85
A19: TOTAL 2027 | B19: =SUM(B7:B18) -> 4850560.9 | C19: =SUM(C7:C18) -> 1221408.6 | D19: =SUM(D7:D18) -> 6071969.5 | E19: =COUNTIF(Precios!I8:I149,"FALTA PRECIO") -> 0 | F19: =IF(E19=0,D19,"") -> 6071969.5 | G19: =SUM(G7:G18) -> 182159.08 | H19: =SUM(H7:H18) -> 6254128.6
A22: Stock al 31/12 del archivo aportado. LAM1 se toma exclusivamente de envasados.
A23: ROJ, VER, CONVER y JAU omitidos. FILMPR se suma a FILM, sin línea ni precio propios.
A24: La reserva es una previsión monetaria por pedidos mínimos desconocidos; no equivale a unidades compradas.

Sheet Resumen anual
A2: Presupuesto de compras · resumen anual 2027
A4: Resultado | B4: Importe / líneas
A5: Compras calculadas | B5: ='Resumen mensual'!D19 -> 6071969.5
A6: Líneas sin precio | B6: ='Resumen mensual'!E19 -> 0
A7: Total sin reserva | B7: =IF(B6=0,B5,"") -> 6071969.5
A8: Reserva pedidos mínimos | B8: ='Resumen mensual'!G19 -> 182159.08
A9: Presupuesto con reserva | B9: =IF(B6=0,B7+B8,"") -> 6254128.6
A12: Grupo | B12: Compras calculadas | C12: Líneas sin precio
A13: Formulados | B13: =SUMIF(Importes!$C$8:$C$149,A13,Importes!Q8:Q149) -> 4850560.9 | C13: =COUNTIFS(Unidades!$C$8:$C$149,A13,Precios!$I$8:$I$149,"FALTA PRECIO") -> 0
A14: Envasados | B14: =SUMIF(Importes!$C$8:$C$149,A14,Importes!Q8:Q149) -> 1221408.6 | C14: =COUNTIFS(Unidades!$C$8:$C$149,A14,Precios!$I$8:$I$149,"FALTA PRECIO") -> 0
A15: TOTAL | B15: =SUM(B13:B14) -> 6071969.5 | C15: =SUM(C13:C14) -> 0
A18: Las unidades de kg, g y ud no se suman entre artículos; consulta Unidades para cantidades por referencia.
A19: La reserva del 3 % es presupuestaria y no representa gasto consumido ni compra asignada a artículos.

Sheet Supuestos
A2: Supuestos del presupuesto de compras 2027
A4: Parámetro | B4: Valor
A5: Incremento precios 2027 | B5: 0.1
A6: Reserva por mínimos de pedido | B6: 0.03
A8: Fuente | B8: 3º MP PARA FORMULADOS y 4º MP PARA ENVASADOS del archivo NECESIDADES ENE_DIC_2027(3).xlsx.
A9: Stock inicial 2027 | B9: Se toma la columna STOCK AL 31/12 de cada hoja; el usuario indica que recoge la previsión y compras realizadas.
A10: Compras mensuales | B10: Necesidad acumulada menos stock al 31/12 y compras anteriores; se asignan al primer mes con déficit.
A11: LAM1 | B11: Solo se usa envasados: stock al 31/12 724,81 kg y sus necesidades mensuales. La fila de formulados queda excluida.
A12: FILMPR | B12: Las necesidades de FILMPR (kg) se suman mes a mes a FILM (kg), con precio de FILM. Ambos stocks al 31/12 son cero; FILMPR no se valora por separado.
A13: Lotes mínimos | B13: CMG 500 kg, HGA-FE 1.200 kg, HGA-MGL 1.250 kg, sólo cuando hay déficit.
A14: Exclusiones confirmadas | B14: ROJ, VER, CONVER y JAU omitidos por indicación del usuario.
A15: Exclusiones anteriores | B15: BAG, CMC500, CTRE0020 y LFIX excluidos según comentarios anteriores. LOT es actividad de loteado.
A16: Precios | B16: Precio neto del último mes disponible por código, más 4,5 % de inflación y 5,5 % de variación del combustible (10 % en conjunto). Se mantienen los precios manuales indicados.
A17: Códigos corregidos | B17: EPA220 usa KIA220; EPP220 usa KIA220P; KIA250 es correcto. Se respetan las equivalencias ya aplicadas.
A18: Reserva de compra | B18: 3 % provisional sobre las compras calculadas de cada mes y el total anual, por posibles formatos y pedidos mínimos desconocidos. No se imputa a unidades ni a artículos.
A19: Interpretación | B19: El presupuesto con reserva es una previsión de fondos para compras. Los materiales adquiridos y no consumidos quedarán en stock; la reserva no es gasto contable automático.
... A21: Alcance | B21: Totales mensuales y anuales ligados a las hojas Unidades, Precios e Importes; todos los artículos con compra deben tener precio.
A23: Las partidas anuales genéricas del presupuesto previo (FILM, CUP, CANT) no se duplican: aquí se valoran los códigos concretos de necesidades.

Sheet Importes
A2: Coste de compras netas por artículo · 2027
A4: Celdas vacías: compras sin precio confirmado. El subtotal valorado no incluye esas partidas.
A7: Artículo | B7: Descripción | C7: Grupo | D7: Precio 2027 | E7: Ene | F7: Feb | G7: Mar | H7: Abr | I7: May | J7: Jun | K7: Jul | L7: Ago | M7: Sep | N7: Oct | O7: Nov | P7: Dic | Q7: Total año
A8: ACE | B8: ACETAMIDA | C8: Formulados | D8: =IF(ISNUMBER(Precios!H8),Precios!H8,"") -> 40.92 | E8: =IF(Unidades!S8=0,0,IF(ISNUMBER($D8),Unidades!S8*$D8,"")) -> 0 | F8: =IF(Unidades!T8=0,0,IF(ISNUMBER($D8),Unidades!T8*$D8,"")) -> 0 | G8: =IF(Unidades!U8=0,0,IF(ISNUMBER($D8),Unidades!U8*$D8,"")) -> 0 | H8: =IF(Unidades!V8=0,0,IF(ISNUMBER($D8),Unidades!V8*$D8,"")) -> 0 | I8: =IF(Unidades!W8=0,0,IF(ISNUMBER($D8),Unidades!W8*$D8,"")) -> 0 | J8: =IF(Unidades!X8=0,0,IF(ISNUMBER($D8),Unidades!X8*$D8,"")) -> 0 | K8: =IF(Unidades!Y8=0,0,IF(ISNUMBER($D8),Unidades!Y8*$D8,"")) -> 1071.8314 | L8: =IF(Unidades!Z8=0,0,IF(ISNUMBER($D8),Unidades!Z8*$D8,"")) -> 573.87026 | ... P8: =IF(Unidades!AD8=0,0,IF(ISNUMBER($D8),Unidades!AD8*$D8,"")) -> 4244.4679 | Q8: =IF(AND(Unidades!AE8>0,NOT(ISNUMBER(D8))),"",SUM(E8:P8)) -> 8539.1298
A9: ACIT | B9: ACIDO CÍTRICO MONOHIDRATADO | C9: Formulados | D9: =IF(ISNUMBER(Precios!H9),Precios!H9,"") -> 1.43 | E9: =IF(Unidades!S9=0,0,IF(ISNUMBER($D9),Unidades!S9*$D9,"")) -> 1891.2465 | F9: =IF(Unidades!T9=0,0,IF(ISNUMBER($D9),Unidades!T9*$D9,"")) -> 4199.6061 | G9: =IF(Unidades!U9=0,0,IF(ISNUMBER($D9),Unidades!U9*$D9,"")) -> 1278.3664 | H9: =IF(Unidades!V9=0,0,IF(ISNUMBER($D9),Unidades!V9*$D9,"")) -> 2032.1194 | I9: =IF(Unidades!W9=0,0,IF(ISNUMBER($D9),Unidades!W9*$D9,"")) -> 1082.5457 | J9: =IF(Unidades!X9=0,0,IF(ISNUMBER($D9),Unidades!X9*$D9,"")) -> 4079.1429 | K9: =IF(Unidades!Y9=0,0,IF(ISNUMBER($D9),Unidades!Y9*$D9,"")) -> 703.274 | L9: =IF(Unidades!Z9=0,0,IF(ISNUMBER($D9),Unidades!Z9*$D9,"")) -> 2552.9969 | ... P9: =IF(Unidades!AD9=0,0,IF(ISNUMBER($D9),Unidades!AD9*$D9,"")) -> 5873.01 | Q9: =IF(AND(Unidades!AE9>0,NOT(ISNUMBER(D9))),"",SUM(E9:P9)) -> 32041.924
A10: ADI | B10: ACIDO ADIPICO | C10: Formulados | D10: =IF(ISNUMBER(Precios!H10),Precios!H10,"") -> 2.706 | E10: =IF(Unidades!S10=0,0,IF(ISNUMBER($D10),Unidades!S10*$D10,"")) -> 0 | F10: =IF(Unidades!T10=0,0,IF(ISNUMBER($D10),Unidades!T10*$D10,"")) -> 0 | G10: =IF(Unidades!U10=0,0,IF(ISNUMBER($D10),Unidades!U10*$D10,"")) -> 0 | H10: =IF(Unidades!V10=0,0,IF(ISNUMBER($D10),Unidades!V10*$D10,"")) -> 0 | I10: =IF(Unidades!W10=0,0,IF(ISNUMBER($D10),Unidades!W10*$D10,"")) -> 0 | J10: =IF(Unidades!X10=0,0,IF(ISNUMBER($D10),Unidades!X10*$D10,"")) -> 0 | K10: =IF(Unidades!Y10=0,0,IF(ISNUMBER($D10),Unidades!Y10*$D10,"")) -> 975.40063 | L10: =IF(Unidades!Z10=0,0,IF(ISNUMBER($D10),Unidades!Z10*$D10,"")) -> 1396.296 | ... P10: =IF(Unidades!AD10=0,0,IF(ISNUMBER($D10),Unidades!AD10*$D10,"")) -> 4188.888 | Q10: =IF(AND(Unidades!AE10>0,NOT(ISNUMBER(D10))),"",SUM(E10:P10)) -> 10480.469
A11: AMARILLO | B11: COLOR AMARILLO | C11: Formulados | D11: =IF(ISNUMBER(Precios!H11),Precios!H11,"") | E11: =IF(Unidades!S11=0,0,IF(ISNUMBER($D11),Unidades!S11*$D11,"")) -> 0 | F11: =IF(Unidades!T11=0,0,IF(ISNUMBER($D11),Unidades!T11*$D11,"")) -> 0 | G11: =IF(Unidades!U11=0,0,IF(ISNUMBER($D11),Unidades!U11*$D11,"")) -> 0 | H11: =IF(Unidades!V11=0,0,IF(ISNUMBER($D11),Unidades!V11*$D11,"")) -> 0 | I11: =IF(Unidades!W11=0,0,IF(ISNUMBER($D11),Unidades!W11*$D11,"")) -> 0 | J11: =IF(Unidades!X11=0,0,IF(ISNUMBER($D11),Unidades!X11*$D11,"")) -> 0 | K11: =IF(Unidades!Y11=0,0,IF(ISNUMBER($D11),Unidades!Y11*$D11,"")) -> 0 | L11: =IF(Unidades!Z11=0,0,IF(ISNUMBER($D11),Unidades!Z11*$D11,"")) -> 0 | ... P11: =IF(Unidades!AD11=0,0,IF(ISNUMBER($D11),Unidades!AD11*$D11,"")) -> 0 | Q11: =IF(AND(Unidades!AE11>0,NOT(ISNUMBER(D11))),"",SUM(E11:P11)) -> 0
A12: AMO | B12: AMONÍACO | C12: Formulados | D12: =IF(ISNUMBER(Precios!H12),Precios!H12,"") -> 0.418 | E12: =IF(Unidades!S12=0,0,IF(ISNUMBER($D12),Unidades!S12*$D12,"")) -> 91.834603 | F12: =IF(Unidades!T12=0,0,IF(ISNUMBER($D12),Unidades!T12*$D12,"")) -> 688.13607 | G12: =IF(Unidades!U12=0,0,IF(ISNUMBER($D12),Unidades!U12*$D12,"")) -> 1439.8257 | H12: =IF(Unidades!V12=0,0,IF(ISNUMBER($D12),Unidades!V12*$D12,"")) -> 723.77369 | I12: =IF(Unidades!W12=0,0,IF(ISNUMBER($D12),Unidades!W12*$D12,"")) -> 1342.6703 | J12: =IF(Unidades!X12=0,0,IF(ISNUMBER($D12),Unidades!X12*$D12,"")) -> 1020.2178 | K12: =IF(Unidades!Y12=0,0,IF(ISNUMBER($D12),Unidades!Y12*$D12,"")) -> 413.32613 | L12: =IF(Unidades!Z12=0,0,IF(ISNUMBER($D12),Unidades!Z12*$D12,"")) -> 550.21967 | ... P12: =IF(Unidades!AD12=0,0,IF(ISNUMBER($D12),Unidades!AD12*$D12,"")) -> 364.55159 | Q12: =IF(AND(Unidades!AE12>0,NOT(ISNUMBER(D12))),"",SUM(E12:P12)) -> 7967.7599
A13: ANTI | B13: ANTIESPUMANTE ANTISCHIUMA GEN | C13: Formulados | D13: =IF(ISNUMBER(Precios!H13),Precios!H13,"") -> 8.525 | E13: =IF(Unidades!S13=0,0,IF(ISNUMBER($D13),Unidades!S13*$D13,"")) -> 0 | F13: =IF(Unidades!T13=0,0,IF(ISNUMBER($D13),Unidades!T13*$D13,"")) -> 0 | G13: =IF(Unidades!U13=0,0,IF(ISNUMBER($D13),Unidades!U13*$D13,"")) -> 0 | H13: =IF(Unidades!V13=0,0,IF(ISNUMBER($D13),Unidades!V13*$D13,"")) -> 0 | I13: =IF(Unidades!W13=0,0,IF(ISNUMBER($D13),Unidades!W13*$D13,"")) -> 0 | J13: =IF(Unidades!X13=0,0,IF(ISNUMBER($D13),Unidades!X13*$D13,"")) -> 0 | K13: =IF(Unidades!Y13=0,0,IF(ISNUMBER($D13),Unidades!Y13*$D13,"")) -> 0 | L13: =IF(Unidades!Z13=0,0,IF(ISNUMBER($D13),Unidades!Z13*$D13,"")) -> 0 | ... P13: =IF(Unidades!AD13=0,0,IF(ISNUMBER($D13),Unidades!AD13*$D13,"")) -> 0 | Q13: =IF(AND(Unidades!AE13>0,NOT(ISNUMBER(D13))),"",SUM(E13:P13)) -> 0
A14: AR | B14: FINDET AR-52 | C14: Formulados | D14: =IF(ISNUMBER(Precios!H14),Precios!H14,"") -> 3.19 | E14: =IF(Unidades!S14=0,0,IF(ISNUMBER($D14),Unidades!S14*$D14,"")) -> 1518.8376 | F14: =IF(Unidades!T14=0,0,IF(ISNUMBER($D14),Unidades!T14*$D14,"")) -> 2072.3146 | G14: =IF(Unidades!U14=0,0,IF(ISNUMBER($D14),Unidades!U14*$D14,"")) -> 5943.0669 | H14: =IF(Unidades!V14=0,0,IF(ISNUMBER($D14),Unidades!V14*$D14,"")) -> 2962.3015 | I14: =IF(Unidades!W14=0,0,IF(ISNUMBER($D14),Unidades!W14*$D14,"")) -> 9088.3896 | J14: =IF(Unidades!X14=0,0,IF(ISNUMBER($D14),Unidades!X14*$D14,"")) -> 6570.4403 | K14: =IF(Unidades!Y14=0,0,IF(ISNUMBER($D14),Unidades!Y14*$D14,"")) -> 4652.5875 | L14: =IF(Unidades!Z14=0,0,IF(ISNUMBER($D14),Unidades!Z14*$D14,"")) -> 1649.338 | ... P14: =IF(Unidades!AD14=0,0,IF(ISNUMBER($D14),Unidades!AD14*$D14,"")) -> 5215.0595 | Q14: =IF(AND(Unidades!AE14>0,NOT(ISNUMBER(D14))),"",SUM(E14:P14)) -> 44664.776
A15: ATC | B15: AATC | C15: Formulados | D15: =IF(ISNUMBER(Precios!H15),Precios!H15,"") -> 35.09 | E15: =IF(Unidades!S15=0,0,IF(ISNUMBER($D15),Unidades!S15*$D15,"")) -> 275.24596 | F15: =IF(Unidades!T15=0,0,IF(ISNUMBER($D15),Unidades!T15*$D15,"")) -> 533.43818 | G15: =IF(Unidades!U15=0,0,IF(ISNUMBER($D15),Unidades!U15*$D15,"")) -> 89.30405 | H15: =IF(Unidades!V15=0,0,IF(ISNUMBER($D15),Unidades!V15*$D15,"")) -> 504.45384 | I15: =IF(Unidades!W15=0,0,IF(ISNUMBER($D15),Unidades!W15*$D15,"")) -> 153.86965 | J15: =IF(Unidades!X15=0,0,IF(ISNUMBER($D15),Unidades!X15*$D15,"")) -> 294.93145 | K15: =IF(Unidades!Y15=0,0,IF(ISNUMBER($D15),Unidades!Y15*$D15,"")) -> 111.69147 | L15: =IF(Unidades!Z15=0,0,IF(ISNUMBER($D15),Unidades!Z15*$D15,"")) -> 330.61798 | ... P15: =IF(Unidades!AD15=0,0,IF(ISNUMBER($D15),Unidades!AD15*$D15,"")) -> 397.42934 | Q15: =IF(AND(Unidades!AE15>0,NOT(ISNUMBER(D15))),"",SUM(E15:P15)) -> 3105.1492
A16: AV24 | B16: AV24 | C16: Formulados | D16: =IF(ISNUMBER(Precios!H16),Precios!H16,"") -> 1.705 | E16: =IF(Unidades!S16=0,0,IF(ISNUMBER($D16),Unidades!S16*$D16,"")) -> 0 | F16: =IF(Unidades!T16=0,0,IF(ISNUMBER($D16),Unidades!T16*$D16,"")) -> 8696.5452 | G16: =IF(Unidades!U16=0,0,IF(ISNUMBER($D16),Unidades!U16*$D16,"")) -> 0 | H16: =IF(Unidades!V16=0,0,IF(ISNUMBER($D16),Unidades!V16*$D16,"")) -> 19.69275 | I16: =IF(Unidades!W16=0,0,IF(ISNUMBER($D16),Unidades!W16*$D16,"")) -> 0 | J16: =IF(Unidades!X16=0,0,IF(ISNUMBER($D16),Unidades!X16*$D16,"")) -> 366.31925 | K16: =IF(Unidades!Y16=0,0,IF(ISNUMBER($D16),Unidades!Y16*$D16,"")) -> 0 | L16: =IF(Unidades!Z16=0,0,IF(ISNUMBER($D16),Unidades!Z16*$D16,"")) -> 262.27162 | ... P16: =IF(Unidades!AD16=0,0,IF(ISNUMBER($D16),Unidades!AD16*$D16,"")) -> 5263.9249 | Q16: =IF(AND(Unidades!AE16>0,NOT(ISNUMBER(D16))),"",SUM(E16:P16)) -> 14979.335
A17: BET | B17: BETAÍNA DE REMOLACHA | C17: Formulados | D17: =IF(ISNUMBER(Precios!H17),Precios!H17,"") -> 5.665 | E17: =IF(Unidades!S17=0,0,IF(ISNUMBER($D17),Unidades!S17*$D17,"")) -> 3376.2494 | F17: =IF(Unidades!T17=0,0,IF(ISNUMBER($D17),Unidades!T17*$D17,"")) -> 5225.9953 | G17: =IF(Unidades!U17=0,0,IF(ISNUMBER($D17),Unidades!U17*$D17,"")) -> 5762.0415 | H17: =IF(Unidades!V17=0,0,IF(ISNUMBER($D17),Unidades!V17*$D17,"")) -> 9392.5105 | I17: =IF(Unidades!W17=0,0,IF(ISNUMBER($D17),Unidades!W17*$D17,"")) -> 9817.1334 | J17: =IF(Unidades!X17=0,0,IF(ISNUMBER($D17),Unidades!X17*$D17,"")) -> 20005.429 | K17: =IF(Unidades!Y17=0,0,IF(ISNUMBER($D17),Unidades!Y17*$D17,"")) -> 7763.7239 | L17: =IF(Unidades!Z17=0,0,IF(ISNUMBER($D17),Unidades!Z17*$D17,"")) -> 2620.4364 | ... P17: =IF(Unidades!AD17=0,0,IF(ISNUMBER($D17),Unidades!AD17*$D17,"")) -> 2341.9082 | Q17: =IF(AND(Unidades!AE17>0,NOT(ISNUMBER(D17))),"",SUM(E17:P17)) -> 78471.65
A18: BICAR | B18: BICARBONATO SÓDICO ALIM. | C18: Formulados | D18: =IF(ISNUMBER(Precios!H18),Precios!H18,"") -> 0.517 | E18: =IF(Unidades!S18=0,0,IF(ISNUMBER($D18),Unidades!S18*$D18,"")) -> 0 | F18: =IF(Unidades!T18=0,0,IF(ISNUMBER($D18),Unidades!T18*$D18,"")) -> 0 | G18: =IF(Unidades!U18=0,0,IF(ISNUMBER($D18),Unidades!U18*$D18,"")) -> 0 | H18: =IF(Unidades!V18=0,0,IF(ISNUMBER($D18),Unidades!V18*$D18,"")) -> 0 | I18: =IF(Unidades!W18=0,0,IF(ISNUMBER($D18),Unidades!W18*$D18,"")) -> 0 | J18: =IF(Unidades!X18=0,0,IF(ISNUMBER($D18),Unidades!X18*$D18,"")) -> 0 | K18: =IF(Unidades!Y18=0,0,IF(ISNUMBER($D18),Unidades!Y18*$D18,"")) -> 0 | L18: =IF(Unidades!Z18=0,0,IF(ISNUMBER($D18),Unidades!Z18*$D18,"")) -> 0 | ... P18: =IF(Unidades!AD18=0,0,IF(ISNUMBER($D18),Unidades!AD18*$D18,"")) -> 0 | Q18: =IF(AND(Unidades!AE18>0,NOT(ISNUMBER(D18))),"",SUM(E18:P18)) -> 0
A19: BOCAL | B19: BRETAX-CL | C19: Formulados | D19: =IF(ISNUMBER(Precios!H19),Precios!H19,"") -> 0.44 | E19: =IF(Unidades!S19=0,0,IF(ISNUMBER($D19),Unidades!S19*$D19,"")) -> 0 | F19: =IF(Unidades!T19=0,0,IF(ISNUMBER($D19),Unidades!T19*$D19,"")) -> 0 | G19: =IF(Unidades!U19=0,0,IF(ISNUMBER($D19),Unidades!U19*$D19,"")) -> 0 | H19: =IF(Unidades!V19=0,0,IF(ISNUMBER($D19),Unidades!V19*$D19,"")) -> 0 | I19: =IF(Unidades!W19=0,0,IF(ISNUMBER($D19),Unidades!W19*$D19,"")) -> 0 | J19: =IF(Unidades!X19=0,0,IF(ISNUMBER($D19),Unidades!X19*$D19,"")) -> 0 | K19: =IF(Unidades!Y19=0,0,IF(ISNUMBER($D19),Unidades!Y19*$D19,"")) -> 0 | L19: =IF(Unidades!Z19=0,0,IF(ISNUMBER($D19),Unidades!Z19*$D19,"")) -> 0 | ... P19: =IF(Unidades!AD19=0,0,IF(ISNUMBER($D19),Unidades!AD19*$D19,"")) -> 0 | Q19: =IF(AND(Unidades!AE19>0,NOT(ISNUMBER(D19))),"",SUM(E19:P19)) -> 0
... A149: TPD63VS | B149: TAPÓN D63 VALVULA SETA, BLANCO | C149: Envasados | D149: =IF(ISNUMBER(Precios!H149),Precios!H149,"") -> 0.3179 | E149: =IF(Unidades!S149=0,0,IF(ISNUMBER($D149),Unidades!S149*$D149,"")) -> 609.47788 | F149: =IF(Unidades!T149=0,0,IF(ISNUMBER($D149),Unidades!T149*$D149,"")) -> 545.1985 | G149: =IF(Unidades!U149=0,0,IF(ISNUMBER($D149),Unidades!U149*$D149,"")) -> 126.19356 | H149: =IF(Unidades!V149=0,0,IF(ISNUMBER($D149),Unidades!V149*$D149,"")) -> 247.3262 | I149: =IF(Unidades!W149=0,0,IF(ISNUMBER($D149),Unidades!W149*$D149,"")) -> 342.3783 | J149: =IF(Unidades!X149=0,0,IF(ISNUMBER($D149),Unidades!X149*$D149,"")) -> 273.0761 | K149: =IF(Unidades!Y149=0,0,IF(ISNUMBER($D149),Unidades!Y149*$D149,"")) -> 258.4527 | L149: =IF(Unidades!Z149=0,0,IF(ISNUMBER($D149),Unidades!Z149*$D149,"")) -> 325.2117 | ... P149: =IF(Unidades!AD149=0,0,IF(ISNUMBER($D149),Unidades!AD149*$D149,"")) -> 498.7851 | Q149: =IF(AND(Unidades!AE149>0,NOT(ISNUMBER(D149))),"",SUM(E149:P149)) -> 3540.5031
A150: SUBTOTAL VALORADO | E150: =SUM(E8:E149) -> 309942.98 | F150: =SUM(F8:F149) -> 600987 | G150: =SUM(G8:G149) -> 632851.65 | H150: =SUM(H8:H149) -> 489927.17 | I150: =SUM(I8:I149) -> 800888.39 | J150: =SUM(J8:J149) -> 826792.04 | K150: =SUM(K8:K149) -> 532881.59 | L150: =SUM(L8:L149) -> 319626.19 | ... Q150: =SUM(Q8:Q149) -> 6071969.5

Sheet Unidades
A2: Compras netas después del stock · 2027
A4: El stock al 31/12 se consume cronológicamente. Las compras surgen cuando la necesidad acumulada lo supera.
A6: Para CMG y HGA se aplican los lotes mínimos confirmados cuando aparece la primera necesidad de compra.
A7: Artículo | B7: Descripción | C7: Grupo | D7: Unidad | E7: Stock 31/12 | F7: Nec. Ene | G7: Nec. Feb | H7: Nec. Mar | I7: Nec. Abr | J7: Nec. May | K7: Nec. Jun | L7: Nec. Jul | M7: Nec. Ago | N7: Nec. Sep | O7: Nec. Oct | P7: Nec. Nov | Q7: Nec. Dic | R7: Necesidad año | S7: Compra Ene | T7: Compra Feb | U7: Compra Mar | V7: Compra Abr | W7: Compra May | X7: Compra Jun | Y7: Compra Jul | Z7: Compra Ago | AA7: Compra Sep | AB7: Compra Oct | AC7: Compra Nov | AD7: Compra Dic | AE7: Compra año | AF7: Lote mín. | AG7: Criterio
A8: ACE | B8: ACETAMIDA | C8: Formulados | D8: kg | E8: 238.55654 | F8: 22.182981 | G8: 45.6496 | H8: 30.034 | I8: 19.638 | J8: 49.811 | K8: 63.861 | L8: 33.5733 | M8: 14.0242 | N8: 10.125 | O8: 33.7158 | P8: 20.8943 | Q8: 103.726 | R8: =SUM(F8:Q8) -> 447.23518 | S8: =IF(SUM($F8:F8)-$E8-0>0,MAX($AF8,SUM($F8:F8)-$E8-0),0) -> 0 | T8: =IF(SUM($F8:G8)-$E8-SUM($S8:S8)>0,MAX($AF8,SUM($F8:G8)-$E8-SUM($S8:S8)),0) -> 0 | U8: =IF(SUM($F8:H8)-$E8-SUM($S8:T8)>0,MAX($AF8,SUM($F8:H8)-$E8-SUM($S8:T8)),0) -> 0 | V8: =IF(SUM($F8:I8)-$E8-SUM($S8:U8)>0,MAX($AF8,SUM($F8:I8)-$E8-SUM($S8:U8)),0) -> 0 | W8: =IF(SUM($F8:J8)-$E8-SUM($S8:V8)>0,MAX($AF8,SUM($F8:J8)-$E8-SUM($S8:V8)),0) -> 0 | X8: =IF(SUM($F8:K8)-$E8-SUM($S8:W8)>0,MAX($AF8,SUM($F8:K8)-$E8-SUM($S8:W8)),0) -> 0 | Y8: =IF(SUM($F8:L8)-$E8-SUM($S8:X8)>0,MAX($AF8,SUM($F8:L8)-$E8-SUM($S8:X8)),0) -> 26.193338 | Z8: =IF(SUM($F8:M8)-$E8-SUM($S8:Y8)>0,MAX($AF8,SUM($F8:M8)-$E8-SUM($S8:Y8)),0) -> 14.0242 | AA8: =IF(SUM($F8:N8)-$E8-SUM($S8:Z8)>0,MAX($AF8,SUM($F8:N8)-$E8-SUM($S8:Z8)),0) -> 10.125 | ... AD8: =IF(SUM($F8:Q8)-$E8-SUM($S8:AC8)>0,MAX($AF8,SUM($F8:Q8)-$E8-SUM($S8:AC8)),0) -> 103.726 | AE8: =SUM(S8:AD8) -> 208.67864 | AF8: 0
A9: ACIT | B9: ACIDO CÍTRICO MONOHIDRATADO | C9: Formulados | D9: kg | E9: 0 | F9: 1322.55 | G9: 2936.7875 | H9: 893.9625 | I9: 1421.0625 | J9: 757.025 | K9: 2852.5475 | L9: 491.8 | M9: 1785.3125 | N9: 2331.45 | O9: 1477.9875 | P9: 2029.455 | Q9: 4107 | R9: =SUM(F9:Q9) -> 22406.94 | S9: =IF(SUM($F9:F9)-$E9-0>0,MAX($AF9,SUM($F9:F9)-$E9-0),0) -> 1322.55 | T9: =IF(SUM($F9:G9)-$E9-SUM($S9:S9)>0,MAX($AF9,SUM($F9:G9)-$E9-SUM($S9:S9)),0) -> 2936.7875 | U9: =IF(SUM($F9:H9)-$E9-SUM($S9:T9)>0,MAX($AF9,SUM($F9:H9)-$E9-SUM($S9:T9)),0) -> 893.9625 | V9: =IF(SUM($F9:I9)-$E9-SUM($S9:U9)>0,MAX($AF9,SUM($F9:I9)-$E9-SUM($S9:U9)),0) -> 1421.0625 | W9: =IF(SUM($F9:J9)-$E9-SUM($S9:V9)>0,MAX($AF9,SUM($F9:J9)-$E9-SUM($S9:V9)),0) -> 757.025 | X9: =IF(SUM($F9:K9)-$E9-SUM($S9:W9)>0,MAX($AF9,SUM($F9:K9)-$E9-SUM($S9:W9)),0) -> 2852.5475 | Y9: =IF(SUM($F9:L9)-$E9-SUM($S9:X9)>0,MAX($AF9,SUM($F9:L9)-$E9-SUM($S9:X9)),0) -> 491.8 | Z9: =IF(SUM($F9:M9)-$E9-SUM($S9:Y9)>0,MAX($AF9,SUM($F9:M9)-$E9-SUM($S9:Y9)),0) -> 1785.3125 | AA9: =IF(SUM($F9:N9)-$E9-SUM($S9:Z9)>0,MAX($AF9,SUM($F9:N9)-$E9-SUM($S9:Z9)),0) -> 2331.45 | ... AD9: =IF(SUM($F9:Q9)-$E9-SUM($S9:AC9)>0,MAX($AF9,SUM($F9:Q9)-$E9-SUM($S9:AC9)),0) -> 4107 | AE9: =SUM(S9:AD9) -> 22406.94 | AF9: 0
A10: ADI | B10: ACIDO ADIPICO | C10: Formulados | D10: kg | E10: 4952.0039 | F10: 0 | G10: 1700.8 | H10: 61.471543 | I10: 0 | J10: 1465.8308 | K10: 878.36 | L10: 1206 | M10: 516 | N10: 330 | O10: 462.59 | P10: 656 | Q10: 1548 | R10: =SUM(F10:Q10) -> 8825.0523 | S10: =IF(SUM($F10:F10)-$E10-0>0,MAX($AF10,SUM($F10:F10)-$E10-0),0) -> 0 | T10: =IF(SUM($F10:G10)-$E10-SUM($S10:S10)>0,MAX($AF10,SUM($F10:G10)-$E10-SUM($S10:S10)),0) -> 0 | U10: =IF(SUM($F10:H10)-$E10-SUM($S10:T10)>0,MAX($AF10,SUM($F10:H10)-$E10-SUM($S10:T10)),0) -> 0 | V10: =IF(SUM($F10:I10)-$E10-SUM($S10:U10)>0,MAX($AF10,SUM($F10:I10)-$E10-SUM($S10:U10)),0) -> 0 | W10: =IF(SUM($F10:J10)-$E10-SUM($S10:V10)>0,MAX($AF10,SUM($F10:J10)-$E10-SUM($S10:V10)),0) -> 0 | X10: =IF(SUM($F10:K10)-$E10-SUM($S10:W10)>0,MAX($AF10,SUM($F10:K10)-$E10-SUM($S10:W10)),0) -> 0 | Y10: =IF(SUM($F10:L10)-$E10-SUM($S10:X10)>0,MAX($AF10,SUM($F10:L10)-$E10-SUM($S10:X10)),0) -> 360.45847 | Z10: =IF(SUM($F10:M10)-$E10-SUM($S10:Y10)>0,MAX($AF10,SUM($F10:M10)-$E10-SUM($S10:Y10)),0) -> 516 | AA10: =IF(SUM($F10:N10)-$E10-SUM($S10:Z10)>0,MAX($AF10,SUM($F10:N10)-$E10-SUM($S10:Z10)),0) -> 330 | ... AD10: =IF(SUM($F10:Q10)-$E10-SUM($S10:AC10)>0,MAX($AF10,SUM($F10:Q10)-$E10-SUM($S10:AC10)),0) -> 1548 | AE10: =SUM(S10:AD10) -> 3873.0485 | AF10: 0
A11: AMARILLO | B11: COLOR AMARILLO | C11: Formulados | D11: kg | E11: 2.9307963 | F11: 0.06624 | G11: 0.04714 | H11: 0.0438 | I11: 0.0079 | J11: 0.0938 | K11: 0.18998 | L11: 0.01071 | M11: 0.01467 | N11: 0.0008 | O11: 0.032 | P11: 0.01133 | Q11: 0.03 | R11: =SUM(F11:Q11) -> 0.54837 | S11: =IF(SUM($F11:F11)-$E11-0>0,MAX($AF11,SUM($F11:F11)-$E11-0),0) -> 0 | T11: =IF(SUM($F11:G11)-$E11-SUM($S11:S11)>0,MAX($AF11,SUM($F11:G11)-$E11-SUM($S11:S11)),0) -> 0 | U11: =IF(SUM($F11:H11)-$E11-SUM($S11:T11)>0,MAX($AF11,SUM($F11:H11)-$E11-SUM($S11:T11)),0) -> 0 | V11: =IF(SUM($F11:I11)-$E11-SUM($S11:U11)>0,MAX($AF11,SUM($F11:I11)-$E11-SUM($S11:U11)),0) -> 0 | W11: =IF(SUM($F11:J11)-$E11-SUM($S11:V11)>0,MAX($AF11,SUM($F11:J11)-$E11-SUM($S11:V11)),0) -> 0 | X11: =IF(SUM($F11:K11)-$E11-SUM($S11:W11)>0,MAX($AF11,SUM($F11:K11)-$E11-SUM($S11:W11)),0) -> 0 | Y11: =IF(SUM($F11:L11)-$E11-SUM($S11:X11)>0,MAX($AF11,SUM($F11:L11)-$E11-SUM($S11:X11)),0) -> 0 | Z11: =IF(SUM($F11:M11)-$E11-SUM($S11:Y11)>0,MAX($AF11,SUM($F11:M11)-$E11-SUM($S11:Y11)),0) -> 0 | AA11: =IF(SUM($F11:N11)-$E11-SUM($S11:Z11)>0,MAX($AF11,SUM($F11:N11)-$E11-SUM($S11:Z11)),0) -> 0 | ... AD11: =IF(SUM($F11:Q11)-$E11-SUM($S11:AC11)>0,MAX($AF11,SUM($F11:Q11)-$E11-SUM($S11:AC11)),0) -> 0 | AE11: =SUM(S11:AD11) -> 0 | AF11: 0
A12: AMO | B12: AMONÍACO | C12: Formulados | D12: kg | E12: 1052.311 | F12: 1272.011 | G12: 1646.2585 | H12: 3444.559 | I12: 1731.516 | J12: 3212.13 | K12: 2440.7125 | L12: 988.8185 | M12: 1316.315 | N12: 753.876 | O12: 1089.428 | P12: 1346.18 | Q12: 872.133 | R12: =SUM(F12:Q12) -> 20113.937 | S12: =IF(SUM($F12:F12)-$E12-0>0,MAX($AF12,SUM($F12:F12)-$E12-0),0) -> 219.70001 | T12: =IF(SUM($F12:G12)-$E12-SUM($S12:S12)>0,MAX($AF12,SUM($F12:G12)-$E12-SUM($S12:S12)),0) -> 1646.2585 | U12: =IF(SUM($F12:H12)-$E12-SUM($S12:T12)>0,MAX($AF12,SUM($F12:H12)-$E12-SUM($S12:T12)),0) -> 3444.559 | V12: =IF(SUM($F12:I12)-$E12-SUM($S12:U12)>0,MAX($AF12,SUM($F12:I12)-$E12-SUM($S12:U12)),0) -> 1731.516 | W12: =IF(SUM($F12:J12)-$E12-SUM($S12:V12)>0,MAX($AF12,SUM($F12:J12)-$E12-SUM($S12:V12)),0) -> 3212.13 | X12: =IF(SUM($F12:K12)-$E12-SUM($S12:W12)>0,MAX($AF12,SUM($F12:K12)-$E12-SUM($S12:W12)),0) -> 2440.7125 | Y12: =IF(SUM($F12:L12)-$E12-SUM($S12:X12)>0,MAX($AF12,SUM($F12:L12)-$E12-SUM($S12:X12)),0) -> 988.8185 | Z12: =IF(SUM($F12:M12)-$E12-SUM($S12:Y12)>0,MAX($AF12,SUM($F12:M12)-$E12-SUM($S12:Y12)),0) -> 1316.315 | AA12: =IF(SUM($F12:N12)-$E12-SUM($S12:Z12)>0,MAX($AF12,SUM($F12:N12)-$E12-SUM($S12:Z12)),0) -> 753.876 | ... AD12: =IF(SUM($F12:Q12)-$E12-SUM($S12:AC12)>0,MAX($AF12,SUM($F12:Q12)-$E12-SUM($S12:AC12)),0) -> 872.133 | AE12: =SUM(S12:AD12) -> 19061.627 | AF12: 0
A13: ANTI | B13: ANTIESPUMANTE ANTISCHIUMA GEN | C13: Formulados | D13: kg | E13: 78.63163 | F13: 0.785 | G13: 1.0692588 | H13: 1.6735559 | I13: 1.8875 | J13: 0.7898 | K13: 1.0176 | L13: 1.8383 | M13: 2.8921 | N13: 0.3582 | O13: 1.2905 | P13: 6.3137 | Q13: 5.0494 | R13: =SUM(F13:Q13) -> 24.964915 | S13: =IF(SUM($F13:F13)-$E13-0>0,MAX($AF13,SUM($F13:F13)-$E13-0),0) -> 0 | T13: =IF(SUM($F13:G13)-$E13-SUM($S13:S13)>0,MAX($AF13,SUM($F13:G13)-$E13-SUM($S13:S13)),0) -> 0 | U13: =IF(SUM($F13:H13)-$E13-SUM($S13:T13)>0,MAX($AF13,SUM($F13:H13)-$E13-SUM($S13:T13)),0) -> 0 | V13: =IF(SUM($F13:I13)-$E13-SUM($S13:U13)>0,MAX($AF13,SUM($F13:I13)-$E13-SUM($S13:U13)),0) -> 0 | W13: =IF(SUM($F13:J13)-$E13-SUM($S13:V13)>0,MAX($AF13,SUM($F13:J13)-$E13-SUM($S13:V13)),0) -> 0 | X13: =IF(SUM($F13:K13)-$E13-SUM($S13:W13)>0,MAX($AF13,SUM($F13:K13)-$E13-SUM($S13:W13)),0) -> 0 | Y13: =IF(SUM($F13:L13)-$E13-SUM($S13:X13)>0,MAX($AF13,SUM($F13:L13)-$E13-SUM($S13:X13)),0) -> 0 | Z13: =IF(SUM($F13:M13)-$E13-SUM($S13:Y13)>0,MAX($AF13,SUM($F13:M13)-$E13-SUM($S13:Y13)),0) -> 0 | AA13: =IF(SUM($F13:N13)-$E13-SUM($S13:Z13)>0,MAX($AF13,SUM($F13:N13)-$E13-SUM($S13:Z13)),0) -> 0 | ... AD13: =IF(SUM($F13:Q13)-$E13-SUM($S13:AC13)>0,MAX($AF13,SUM($F13:Q13)-$E13-SUM($S13:AC13)),0) -> 0 | AE13: =SUM(S13:AD13) -> 0 | AF13: 0
A14: AR | B14: FINDET AR-52 | C14: Formulados | D14: kg | E14: 0 | F14: 476.12463 | G14: 649.62839 | H14: 1863.0304 | I14: 928.62117 | J14: 2849.025 | K14: 2059.6992 | L14: 1458.4914 | M14: 517.03386 | N14: 395.11568 | O14: 434.77509 | P14: 735.13768 | Q14: 1634.8149 | R14: =SUM(F14:Q14) -> 14001.497 | S14: =IF(SUM($F14:F14)-$E14-0>0,MAX($AF14,SUM($F14:F14)-$E14-0),0) -> 476.12463 | T14: =IF(SUM($F14:G14)-$E14-SUM($S14:S14)>0,MAX($AF14,SUM($F14:G14)-$E14-SUM($S14:S14)),0) -> 649.62839 | U14: =IF(SUM($F14:H14)-$E14-SUM($S14:T14)>0,MAX($AF14,SUM($F14:H14)-$E14-SUM($S14:T14)),0) -> 1863.0304 | V14: =IF(SUM($F14:I14)-$E14-SUM($S14:U14)>0,MAX($AF14,SUM($F14:I14)-$E14-SUM($S14:U14)),0) -> 928.62117 | W14: =IF(SUM($F14:J14)-$E14-SUM($S14:V14)>0,MAX($AF14,SUM($F14:J14)-$E14-SUM($S14:V14)),0) -> 2849.025 | X14: =IF(SUM($F14:K14)-$E14-SUM($S14:W14)>0,MAX($AF14,SUM($F14:K14)-$E14-SUM($S14:W14)),0) -> 2059.6992 | Y14: =IF(SUM($F14:L14)-$E14-SUM($S14:X14)>0,MAX($AF14,SUM($F14:L14)-$E14-SUM($S14:X14)),0) -> 1458.4914 | Z14: =IF(SUM($F14:M14)-$E14-SUM($S14:Y14)>0,MAX($AF14,SUM($F14:M14)-$E14-SUM($S14:Y14)),0) -> 517.03386 | AA14: =IF(SUM($F14:N14)-$E14-SUM($S14:Z14)>0,MAX($AF14,SUM($F14:N14)-$E14-SUM($S14:Z14)),0) -> 395.11568 | ... AD14: =IF(SUM($F14:Q14)-$E14-SUM($S14:AC14)>0,MAX($AF14,SUM($F14:Q14)-$E14-SUM($S14:AC14)),0) -> 1634.8149 | AE14: =SUM(S14:AD14) -> 14001.497 | AF14: 0
A15: ATC | B15: AATC | C15: Formulados | D15: kg | E15: 0 | F15: 7.844 | G15: 15.202 | H15: 2.545 | I15: 14.376 | J15: 4.385 | K15: 8.405 | L15: 3.183 | M15: 9.422 | N15: 7.023 | O15: 1.57 | P15: 3.21 | Q15: 11.326 | R15: =SUM(F15:Q15) -> 88.491 | S15: =IF(SUM($F15:F15)-$E15-0>0,MAX($AF15,SUM($F15:F15)-$E15-0),0) -> 7.844 | T15: =IF(SUM($F15:G15)-$E15-SUM($S15:S15)>0,MAX($AF15,SUM($F15:G15)-$E15-SUM($S15:S15)),0) -> 15.202 | U15: =IF(SUM($F15:H15)-$E15-SUM($S15:T15)>0,MAX($AF15,SUM($F15:H15)-$E15-SUM($S15:T15)),0) -> 2.545 | V15: =IF(SUM($F15:I15)-$E15-SUM($S15:U15)>0,MAX($AF15,SUM($F15:I15)-$E15-SUM($S15:U15)),0) -> 14.376 | W15: =IF(SUM($F15:J15)-$E15-SUM($S15:V15)>0,MAX($AF15,SUM($F15:J15)-$E15-SUM($S15:V15)),0) -> 4.385 | X15: =IF(SUM($F15:K15)-$E15-SUM($S15:W15)>0,MAX($AF15,SUM($F15:K15)-$E15-SUM($S15:W15)),0) -> 8.405 | Y15: =IF(SUM($F15:L15)-$E15-SUM($S15:X15)>0,MAX($AF15,SUM($F15:L15)-$E15-SUM($S15:X15)),0) -> 3.183 | Z15: =IF(SUM($F15:M15)-$E15-SUM($S15:Y15)>0,MAX($AF15,SUM($F15:M15)-$E15-SUM($S15:Y15)),0) -> 9.422 | AA15: =IF(SUM($F15:N15)-$E15-SUM($S15:Z15)>0,MAX($AF15,SUM($F15:N15)-$E15-SUM($S15:Z15)),0) -> 7.023 | ... AD15: =IF(SUM($F15:Q15)-$E15-SUM($S15:AC15)>0,MAX($AF15,SUM($F15:Q15)-$E15-SUM($S15:AC15)),0) -> 11.326 | AE15: =SUM(S15:AD15) -> 88.491 | AF15: 0
A16: AV24 | B16: AV24 | C16: Formulados | D16: kg | E16: 0 | F16: 0 | G16: 5100.613 | H16: 0 | I16: 11.55 | J16: 0 | K16: 214.85 | L16: 0 | M16: 153.825 | N16: 0 | O16: 0 | P16: 217.35 | Q16: 3087.346 | R16: =SUM(F16:Q16) -> 8785.534 | S16: =IF(SUM($F16:F16)-$E16-0>0,MAX($AF16,SUM($F16:F16)-$E16-0),0) -> 0 | T16: =IF(SUM($F16:G16)-$E16-SUM($S16:S16)>0,MAX($AF16,SUM($F16:G16)-$E16-SUM($S16:S16)),0) -> 5100.613 | U16: =IF(SUM($F16:H16)-$E16-SUM($S16:T16)>0,MAX($AF16,SUM($F16:H16)-$E16-SUM($S16:T16)),0) -> 0 | V16: =IF(SUM($F16:I16)-$E16-SUM($S16:U16)>0,MAX($AF16,SUM($F16:I16)-$E16-SUM($S16:U16)),0) -> 11.55 | W16: =IF(SUM($F16:J16)-$E16-SUM($S16:V16)>0,MAX($AF16,SUM($F16:J16)-$E16-SUM($S16:V16)),0) -> 0 | X16: =IF(SUM($F16:K16)-$E16-SUM($S16:W16)>0,MAX($AF16,SUM($F16:K16)-$E16-SUM($S16:W16)),0) -> 214.85 | Y16: =IF(SUM($F16:L16)-$E16-SUM($S16:X16)>0,MAX($AF16,SUM($F16:L16)-$E16-SUM($S16:X16)),0) -> 0 | Z16: =IF(SUM($F16:M16)-$E16-SUM($S16:Y16)>0,MAX($AF16,SUM($F16:M16)-$E16-SUM($S16:Y16)),0) -> 153.825 | AA16: =IF(SUM($F16:N16)-$E16-SUM($S16:Z16)>0,MAX($AF16,SUM($F16:N16)-$E16-SUM($S16:Z16)),0) -> 0 | ... AD16: =IF(SUM($F16:Q16)-$E16-SUM($S16:AC16)>0,MAX($AF16,SUM($F16:Q16)-$E16-SUM($S16:AC16)),0) -> 3087.346 | AE16: =SUM(S16:AD16) -> 8785.534 | AF16: 0
A17: BET | B17: BETAÍNA DE REMOLACHA | C17: Formulados | D17: kg | E17: 0 | F17: 595.984 | G17: 922.50579 | H17: 1017.13 | I17: 1657.9895 | J17: 1732.945 | K17: 3531.4085 | L17: 1370.472 | M17: 462.566 | N17: 174.171 | O17: 874.575 | P17: 1098.866 | Q17: 413.3995 | R17: =SUM(F17:Q17) -> 13852.012 | S17: =IF(SUM($F17:F17)-$E17-0>0,MAX($AF17,SUM($F17:F17)-$E17-0),0) -> 595.984 | T17: =IF(SUM($F17:G17)-$E17-SUM($S17:S17)>0,MAX($AF17,SUM($F17:G17)-$E17-SUM($S17:S17)),0) -> 922.50579 | U17: =IF(SUM($F17:H17)-$E17-SUM($S17:T17)>0,MAX($AF17,SUM($F17:H17)-$E17-SUM($S17:T17)),0) -> 1017.13 | V17: =IF(SUM($F17:I17)-$E17-SUM($S17:U17)>0,MAX($AF17,SUM($F17:I17)-$E17-SUM($S17:U17)),0) -> 1657.9895 | W17: =IF(SUM($F17:J17)-$E17-SUM($S17:V17)>0,MAX($AF17,SUM($F17:J17)-$E17-SUM($S17:V17)),0) -> 1732.945 | X17: =IF(SUM($F17:K17)-$E17-SUM($S17:W17)>0,MAX($AF17,SUM($F17:K17)-$E17-SUM($S17:W17)),0) -> 3531.4085 | Y17: =IF(SUM($F17:L17)-$E17-SUM($S17:X17)>0,MAX($AF17,SUM($F17:L17)-$E17-SUM($S17:X17)),0) -> 1370.472 | Z17: =IF(SUM($F17:M17)-$E17-SUM($S17:Y17)>0,MAX($AF17,SUM($F17:M17)-$E17-SUM($S17:Y17)),0) -> 462.566 | AA17: =IF(SUM($F17:N17)-$E17-SUM($S17:Z17)>0,MAX($AF17,SUM($F17:N17)-$E17-SUM($S17:Z17)),0) -> 174.171 | ... AD17: =IF(SUM($F17:Q17)-$E17-SUM($S17:AC17)>0,MAX($AF17,SUM($F17:Q17)-$E17-SUM($S17:AC17)),0) -> 413.3995 | AE17: =SUM(S17:AD17) -> 13852.012 | AF17: 0
A18: BICAR | B18: BICARBONATO SÓDICO ALIM. | C18: Formulados | D18: kg | E18: 3485 | F18: 0 | G18: 0 | H18: 0 | I18: 238.99807 | J18: 0 | K18: 105 | L18: 210 | M18: 425 | N18: 0 | O18: 510 | P18: 0 | Q18: 0 | R18: =SUM(F18:Q18) -> 1488.9981 | S18: =IF(SUM($F18:F18)-$E18-0>0,MAX($AF18,SUM($F18:F18)-$E18-0),0) -> 0 | T18: =IF(SUM($F18:G18)-$E18-SUM($S18:S18)>0,MAX($AF18,SUM($F18:G18)-$E18-SUM($S18:S18)),0) -> 0 | U18: =IF(SUM($F18:H18)-$E18-SUM($S18:T18)>0,MAX($AF18,SUM($F18:H18)-$E18-SUM($S18:T18)),0) -> 0 | V18: =IF(SUM($F18:I18)-$E18-SUM($S18:U18)>0,MAX($AF18,SUM($F18:I18)-$E18-SUM($S18:U18)),0) -> 0 | W18: =IF(SUM($F18:J18)-$E18-SUM($S18:V18)>0,MAX($AF18,SUM($F18:J18)-$E18-SUM($S18:V18)),0) -> 0 | X18: =IF(SUM($F18:K18)-$E18-SUM($S18:W18)>0,MAX($AF18,SUM($F18:K18)-$E18-SUM($S18:W18)),0) -> 0 | Y18: =IF(SUM($F18:L18)-$E18-SUM($S18:X18)>0,MAX($AF18,SUM($F18:L18)-$E18-SUM($S18:X18)),0) -> 0 | Z18: =IF(SUM($F18:M18)-$E18-SUM($S18:Y18)>0,MAX($AF18,SUM($F18:M18)-$E18-SUM($S18:Y18)),0) -> 0 | AA18: =IF(SUM($F18:N18)-$E18-SUM($S18:Z18)>0,MAX($AF18,SUM($F18:N18)-$E18-SUM($S18:Z18)),0) -> 0 | ... AD18: =IF(SUM($F18:Q18)-$E18-SUM($S18:AC18)>0,MAX($AF18,SUM($F18:Q18)-$E18-SUM($S18:AC18)),0) -> 0 | AE18: =SUM(S18:AD18) -> 0 | AF18: 0
A19: BOCAL | B19: BRETAX-CL | C19: Formulados | D19: kg | E19: 19980.673 | F19: 663.228 | G19: 2205.42 | H19: 1435.392 | I19: 1661.808 | J19: 1523.6468 | K19: 2057.235 | L19: 1749.733 | M19: 2600.58 | N19: 625.848 | O19: 1482.384 | P19: 1393.74 | Q19: 35.244 | R19: =SUM(F19:Q19) -> 17434.259 | S19: =IF(SUM($F19:F19)-$E19-0>0,MAX($AF19,SUM($F19:F19)-$E19-0),0) -> 0 | T19: =IF(SUM($F19:G19)-$E19-SUM($S19:S19)>0,MAX($AF19,SUM($F19:G19)-$E19-SUM($S19:S19)),0) -> 0 | U19: =IF(SUM($F19:H19)-$E19-SUM($S19:T19)>0,MAX($AF19,SUM($F19:H19)-$E19-SUM($S19:T19)),0) -> 0 | V19: =IF(SUM($F19:I19)-$E19-SUM($S19:U19)>0,MAX($AF19,SUM($F19:I19)-$E19-SUM($S19:U19)),0) -> 0 | W19: =IF(SUM($F19:J19)-$E19-SUM($S19:V19)>0,MAX($AF19,SUM($F19:J19)-$E19-SUM($S19:V19)),0) -> 0 | X19: =IF(SUM($F19:K19)-$E19-SUM($S19:W19)>0,MAX($AF19,SUM($F19:K19)-$E19-SUM($S19:W19)),0) -> 0 | Y19: =IF(SUM($F19:L19)-$E19-SUM($S19:X19)>0,MAX($AF19,SUM($F19:L19)-$E19-SUM($S19:X19)),0) -> 0 | Z19: =IF(SUM($F19:M19)-$E19-SUM($S19:Y19)>0,MAX($AF19,SUM($F19:M19)-$E19-SUM($S19:Y19)),0) -> 0 | AA19: =IF(SUM($F19:N19)-$E19-SUM($S19:Z19)>0,MAX($AF19,SUM($F19:N19)-$E19-SUM($S19:Z19)),0) -> 0 | ... AD19: =IF(SUM($F19:Q19)-$E19-SUM($S19:AC19)>0,MAX($AF19,SUM($F19:Q19)-$E19-SUM($S19:AC19)),0) -> 0 | AE19: =SUM(S19:AD19) -> 0 | AF19: 0
... A28: CLORPO | B28: CLORURO POTASICO | C28: Formulados | D28: kg | E28: 0 | F28: 753.08977 | G28: 247.11707 | H28: 1207.05 | I28: 34.32 | J28: 356.07 | K28: 1212.822 | L28: 169.26 | M28: 449.28 | N28: 0 | O28: 740.532 | P28: 934.128 | Q28: 128.544 | R28: =SUM(F28:Q28) -> 6232.2128 | S28: =IF(SUM($F28:F28)-$E28-0>0,MAX($AF28,SUM($F28:F28)-$E28-0),0) -> 753.08977 | T28: =IF(SUM($F28:G28)-$E28-SUM($S28:S28)>0,MAX($AF28,SUM($F28:G28)-$E28-SUM($S28:S28)),0) -> 247.11707 | U28: =IF(SUM($F28:H28)-$E28-SUM($S28:T28)>0,MAX($AF28,SUM($F28:H28)-$E28-SUM($S28:T28)),0) -> 1207.05 | V28: =IF(SUM($F28:I28)-$E28-SUM($S28:U28)>0,MAX($AF28,SUM($F28:I28)-$E28-SUM($S28:U28)),0) -> 34.32 | W28: =IF(SUM($F28:J28)-$E28-SUM($S28:V28)>0,MAX($AF28,SUM($F28:J28)-$E28-SUM($S28:V28)),0) -> 356.07 | X28: =IF(SUM($F28:K28)-$E28-SUM($S28:W28)>0,MAX($AF28,SUM($F28:K28)-$E28-SUM($S28:W28)),0) -> 1212.822 | Y28: =IF(SUM($F28:L28)-$E28-SUM($S28:X28)>0,MAX($AF28,SUM($F28:L28)-$E28-SUM($S28:X28)),0) -> 169.26 | Z28: =IF(SUM($F28:M28)-$E28-SUM($S28:Y28)>0,MAX($AF28,SUM($F28:M28)-$E28-SUM($S28:Y28)),0) -> 449.28 | AA28: =IF(SUM($F28:N28)-$E28-SUM($S28:Z28)>0,MAX($AF28,SUM($F28:N28)-$E28-SUM($S28:Z28)),0) -> 0 | ... AD28: =IF(SUM($F28:Q28)-$E28-SUM($S28:AC28)>0,MAX($AF28,SUM($F28:Q28)-$E28-SUM($S28:AC28)),0) -> 128.544 | AE28: =SUM(S28:AD28) -> 6232.2128 | AF28: 0
A29: CMG | B29: CARBONATO DE MAGNESIO - MAGNESITA | C29: Formulados | D29: kg | E29: 0 | F29: 0 | G29: 0 | H29: 3.1381869 | I29: 0 | J29: 11.135 | K29: 2.04 | L29: 0 | M29: 0 | N29: 0 | O29: 3.91 | P29: 0 | Q29: 0 | R29: =SUM(F29:Q29) -> 20.223187 | S29: =IF(SUM($F29:F29)-$E29-0>0,MAX($AF29,SUM($F29:F29)-$E29-0),0) -> 0 | T29: =IF(SUM($F29:G29)-$E29-SUM($S29:S29)>0,MAX($AF29,SUM($F29:G29)-$E29-SUM($S29:S29)),0) -> 0 | U29: =IF(SUM($F29:H29)-$E29-SUM($S29:T29)>0,MAX($AF29,SUM($F29:H29)-$E29-SUM($S29:T29)),0) -> 500 | V29: =IF(SUM($F29:I29)-$E29-SUM($S29:U29)>0,MAX($AF29,SUM($F29:I29)-$E29-SUM($S29:U29)),0) -> 0 | W29: =IF(SUM($F29:J29)-$E29-SUM($S29:V29)>0,MAX($AF29,SUM($F29:J29)-$E29-SUM($S29:V29)),0) -> 0 | X29: =IF(SUM($F29:K29)-$E29-SUM($S29:W29)>0,MAX($AF29,SUM($F29:K29)-$E29-SUM($S29:W29)),0) -> 0 | Y29: =IF(SUM($F29:L29)-$E29-SUM($S29:X29)>0,MAX($AF29,SUM($F29:L29)-$E29-SUM($S29:X29)),0) -> 0 | Z29: =IF(SUM($F29:M29)-$E29-SUM($S29:Y29)>0,MAX($AF29,SUM($F29:M29)-$E29-SUM($S29:Y29)),0) -> 0 | AA29: =IF(SUM($F29:N29)-$E29-SUM($S29:Z29)>0,MAX($AF29,SUM($F29:N29)-$E29-SUM($S29:Z29)),0) -> 0 | ... AD29: =IF(SUM($F29:Q29)-$E29-SUM($S29:AC29)>0,MAX($AF29,SUM($F29:Q29)-$E29-SUM($S29:AC29)),0) -> 0 | AE29: =SUM(S29:AD29) -> 500 | AF29: 500 | AG29: Lote mínimo indicado por el usuario.
A30: CMN | B30: CLORURO DE MANGANESO | C30: Formulados | D30: kg | E30: 166.51672 | F30: 38.016 | G30: 125.796 | H30: 33.88 | I30: 0 | J30: 107.712 | K30: 125.84 | L30: 44 | M30: 0 | N30: 0 | O30: 18.04 | P30: 133.1 | Q30: 0 | R30: =SUM(F30:Q30) -> 626.384 | S30: =IF(SUM($F30:F30)-$E30-0>0,MAX($AF30,SUM($F30:F30)-$E30-0),0) -> 0 | T30: =IF(SUM($F30:G30)-$E30-SUM($S30:S30)>0,MAX($AF30,SUM($F30:G30)-$E30-SUM($S30:S30)),0) -> 0 | U30: =IF(SUM($F30:H30)-$E30-SUM($S30:T30)>0,MAX($AF30,SUM($F30:H30)-$E30-SUM($S30:T30)),0) -> 31.175276 | V30: =IF(SUM($F30:I30)-$E30-SUM($S30:U30)>0,MAX($AF30,SUM($F30:I30)-$E30-SUM($S30:U30)),0) -> 0 | W30: =IF(SUM($F30:J30)-$E30-SUM($S30:V30)>0,MAX($AF30,SUM($F30:J30)-$E30-SUM($S30:V30)),0) -> 107.712 | X30: =IF(SUM($F30:K30)-$E30-SUM($S30:W30)>0,MAX($AF30,SUM($F30:K30)-$E30-SUM($S30:W30)),0) -> 125.84 | Y30: =IF(SUM($F30:L30)-$E30-SUM($S30:X30)>0,MAX($AF30,SUM($F30:L30)-$E30-SUM($S30:X30)),0) -> 44 | Z30: =IF(SUM($F30:M30)-$E30-SUM($S30:Y30)>0,MAX($AF30,SUM($F30:M30)-$E30-SUM($S30:Y30)),0) -> 0 | AA30: =IF(SUM($F30:N30)-$E30-SUM($S30:Z30)>0,MAX($AF30,SUM($F30:N30)-$E30-SUM($S30:Z30)),0) -> 0 | ... AD30: =IF(SUM($F30:Q30)-$E30-SUM($S30:AC30)>0,MAX($AF30,SUM($F30:Q30)-$E30-SUM($S30:AC30)),0) -> 0 | AE30: =SUM(S30:AD30) -> 459.86728 | AF30: 0
A31: CZN | B31: CLORURO DE ZINC | C31: Formulados | D31: kg | E31: 157.16897 | F31: 22.464 | G31: 74.334 | H31: 20.02 | I31: 0 | J31: 63.648 | K31: 74.36 | L31: 26 | M31: 0 | N31: 0 | O31: 10.66 | P31: 78.65 | Q31: 0 | R31: =SUM(F31:Q31) -> 370.136 | S31: =IF(SUM($F31:F31)-$E31-0>0,MAX($AF31,SUM($F31:F31)-$E31-0),0) -> 0 | T31: =IF(SUM($F31:G31)-$E31-SUM($S31:S31)>0,MAX($AF31,SUM($F31:G31)-$E31-SUM($S31:S31)),0) -> 0 | U31: =IF(SUM($F31:H31)-$E31-SUM($S31:T31)>0,MAX($AF31,SUM($F31:H31)-$E31-SUM($S31:T31)),0) -> 0 | V31: =IF(SUM($F31:I31)-$E31-SUM($S31:U31)>0,MAX($AF31,SUM($F31:I31)-$E31-SUM($S31:U31)),0) -> 0 | W31: =IF(SUM($F31:J31)-$E31-SUM($S31:V31)>0,MAX($AF31,SUM($F31:J31)-$E31-SUM($S31:V31)),0) -> 23.297027 | X31: =IF(SUM($F31:K31)-$E31-SUM($S31:W31)>0,MAX($AF31,SUM($F31:K31)-$E31-SUM($S31:W31)),0) -> 74.36 | Y31: =IF(SUM($F31:L31)-$E31-SUM($S31:X31)>0,MAX($AF31,SUM($F31:L31)-$E31-SUM($S31:X31)),0) -> 26 | Z31: =IF(SUM($F31:M31)-$E31-SUM($S31:Y31)>0,MAX($AF31,SUM($F31:M31)-$E31-SUM($S31:Y31)),0) -> 0 | AA31: =IF(SUM($F31:N31)-$E31-SUM($S31:Z31)>0,MAX($AF31,SUM($F31:N31)-$E31-SUM($S31:Z31)),0) -> 0 | ... AD31: =IF(SUM($F31:Q31)-$E31-SUM($S31:AC31)>0,MAX($AF31,SUM($F31:Q31)-$E31-SUM($S31:AC31)),0) -> 0 | AE31: =SUM(S31:AD31) -> 212.96703 | AF31: 0
A32: D55 | B32: DADMEL 55 | C32: Formulados | D32: kg | E32: 0 | F32: 1126 | G32: 1413.2375 | H32: 1578.5094 | I32: 1889.16 | J32: 1712.16 | K32: 2117 | L32: 1614.93 | M32: 1019 | N32: 623.28 | O32: 2503.96 | P32: 2793.08 | Q32: 925.68 | R32: =SUM(F32:Q32) -> 19315.997 | S32: =IF(SUM($F32:F32)-$E32-0>0,MAX($AF32,SUM($F32:F32)-$E32-0),0) -> 1126 | T32: =IF(SUM($F32:G32)-$E32-SUM($S32:S32)>0,MAX($AF32,SUM($F32:G32)-$E32-SUM($S32:S32)),0) -> 1413.2375 | U32: =IF(SUM($F32:H32)-$E32-SUM($S32:T32)>0,MAX($AF32,SUM($F32:H32)-$E32-SUM($S32:T32)),0) -> 1578.5094 | V32: =IF(SUM($F32:I32)-$E32-SUM($S32:U32)>0,MAX($AF32,SUM($F32:I32)-$E32-SUM($S32:U32)),0) -> 1889.16 | W32: =IF(SUM($F32:J32)-$E32-SUM($S32:V32)>0,MAX($AF32,SUM($F32:J32)-$E32-SUM($S32:V32)),0) -> 1712.16 | X32: =IF(SUM($F32:K32)-$E32-SUM($S32:W32)>0,MAX($AF32,SUM($F32:K32)-$E32-SUM($S32:W32)),0) -> 2117 | Y32: =IF(SUM($F32:L32)-$E32-SUM($S32:X32)>0,MAX($AF32,SUM($F32:L32)-$E32-SUM($S32:X32)),0) -> 1614.93 | Z32: =IF(SUM($F32:M32)-$E32-SUM($S32:Y32)>0,MAX($AF32,SUM($F32:M32)-$E32-SUM($S32:Y32)),0) -> 1019 | AA32: =IF(SUM($F32:N32)-$E32-SUM($S32:Z32)>0,MAX($AF32,SUM($F32:N32)-$E32-SUM($S32:Z32)),0) -> 623.28 | ... AD32: =IF(SUM($F32:Q32)-$E32-SUM($S32:AC32)>0,MAX($AF32,SUM($F32:Q32)-$E32-SUM($S32:AC32)),0) -> 925.68 | AE32: =SUM(S32:AD32) -> 19315.997 | AF32: 0
A33: DECL | B33: DESHCOFIX -108-(LÍQUIDO) | C33: Formulados | D33: kg | E33: 0 | F33: 16267.592 | G33: 22195.637 | H33: 63653.537 | I33: 31727.89 | J33: 97341.686 | K33: 70373.055 | L33: 49831.789 | M33: 17665.323 | N33: 13499.786 | O33: 14854.816 | P33: 25117.204 | Q33: 55856.175 | R33: =SUM(F33:Q33) -> 478384.49 | S33: =IF(SUM($F33:F33)-$E33-0>0,MAX($AF33,SUM($F33:F33)-$E33-0),0) -> 16267.592 | T33: =IF(SUM($F33:G33)-$E33-SUM($S33:S33)>0,MAX($AF33,SUM($F33:G33)-$E33-SUM($S33:S33)),0) -> 22195.637 | U33: =IF(SUM($F33:H33)-$E33-SUM($S33:T33)>0,MAX($AF33,SUM($F33:H33)-$E33-SUM($S33:T33)),0) -> 63653.537 | V33: =IF(SUM($F33:I33)-$E33-SUM($S33:U33)>0,MAX($AF33,SUM($F33:I33)-$E33-SUM($S33:U33)),0) -> 31727.89 | W33: =IF(SUM($F33:J33)-$E33-SUM($S33:V33)>0,MAX($AF33,SUM($F33:J33)-$E33-SUM($S33:V33)),0) -> 97341.686 | X33: =IF(SUM($F33:K33)-$E33-SUM($S33:W33)>0,MAX($AF33,SUM($F33:K33)-$E33-SUM($S33:W33)),0) -> 70373.055 | Y33: =IF(SUM($F33:L33)-$E33-SUM($S33:X33)>0,MAX($AF33,SUM($F33:L33)-$E33-SUM($S33:X33)),0) -> 49831.789 | Z33: =IF(SUM($F33:M33)-$E33-SUM($S33:Y33)>0,MAX($AF33,SUM($F33:M33)-$E33-SUM($S33:Y33)),0) -> 17665.323 | AA33: =IF(SUM($F33:N33)-$E33-SUM($S33:Z33)>0,MAX($AF33,SUM($F33:N33)-$E33-SUM($S33:Z33)),0) -> 13499.786 | ... AD33: =IF(SUM($F33:Q33)-$E33-SUM($S33:AC33)>0,MAX($AF33,SUM($F33:Q33)-$E33-SUM($S33:AC33)),0) -> 55856.175 | AE33: =SUM(S33:AD33) -> 478384.49 | AF33: 0
A34: EBRO | B34: EBROSIL | C34: Formulados | D34: kg | E34: 0 | F34: 68.55 | G34: 62.3 | H34: 42.903796 | I34: 111.99 | J34: 255.99 | K34: 50.5 | L34: 45.61 | M34: 37.75 | N34: 186.53 | O34: 8.82 | P34: 55.01 | Q34: 358.76 | R34: =SUM(F34:Q34) -> 1284.7138 | S34: =IF(SUM($F34:F34)-$E34-0>0,MAX($AF34,SUM($F34:F34)-$E34-0),0) -> 68.55 | T34: =IF(SUM($F34:G34)-$E34-SUM($S34:S34)>0,MAX($AF34,SUM($F34:G34)-$E34-SUM($S34:S34)),0) -> 62.3 | U34: =IF(SUM($F34:H34)-$E34-SUM($S34:T34)>0,MAX($AF34,SUM($F34:H34)-$E34-SUM($S34:T34)),0) -> 42.903796 | V34: =IF(SUM($F34:I34)-$E34-SUM($S34:U34)>0,MAX($AF34,SUM($F34:I34)-$E34-SUM($S34:U34)),0) -> 111.99 | W34: =IF(SUM($F34:J34)-$E34-SUM($S34:V34)>0,MAX($AF34,SUM($F34:J34)-$E34-SUM($S34:V34)),0) -> 255.99 | X34: =IF(SUM($F34:K34)-$E34-SUM($S34:W34)>0,MAX($AF34,SUM($F34:K34)-$E34-SUM($S34:W34)),0) -> 50.5 | Y34: =IF(SUM($F34:L34)-$E34-SUM($S34:X34)>0,MAX($AF34,SUM($F34:L34)-$E34-SUM($S34:X34)),0) -> 45.61 | Z34: =IF(SUM($F34:M34)-$E34-SUM($S34:Y34)>0,MAX($AF34,SUM($F34:M34)-$E34-SUM($S34:Y34)),0) -> 37.75 | AA34: =IF(SUM($F34:N34)-$E34-SUM($S34:Z34)>0,MAX($AF34,SUM($F34:N34)-$E34-SUM($S34:Z34)),0) -> 186.53 | ... AD34: =IF(SUM($F34:Q34)-$E34-SUM($S34:AC34)>0,MAX($AF34,SUM($F34:Q34)-$E34-SUM($S34:AC34)),0) -> 358.76 | AE34: =SUM(S34:AD34) -> 1284.7138 | AF34: 0
A35: EDT | B35: EDTA | C35: Formulados | D35: kg | E35: 0 | F35: 350.02856 | G35: 727.94118 | H35: 468.84456 | I35: 614.4725 | J35: 566.04278 | K35: 1059.7312 | L35: 608.5239 | M35: 400.68 | N35: 327.8881 | O35: 474.5331 | P35: 468.8626 | Q35: 1359.8344 | R35: =SUM(F35:Q35) -> 7427.3829 | S35: =IF(SUM($F35:F35)-$E35-0>0,MAX($AF35,SUM($F35:F35)-$E35-0),0) -> 350.02856 | T35: =IF(SUM($F35:G35)-$E35-SUM($S35:S35)>0,MAX($AF35,SUM($F35:G35)-$E35-SUM($S35:S35)),0) -> 727.94118 | U35: =IF(SUM($F35:H35)-$E35-SUM($S35:T35)>0,MAX($AF35,SUM($F35:H35)-$E35-SUM($S35:T35)),0) -> 468.84456 | V35: =IF(SUM($F35:I35)-$E35-SUM($S35:U35)>0,MAX($AF35,SUM($F35:I35)-$E35-SUM($S35:U35)),0) -> 614.4725 | W35: =IF(SUM($F35:J35)-$E35-SUM($S35:V35)>0,MAX($AF35,SUM($F35:J35)-$E35-SUM($S35:V35)),0) -> 566.04278 | X35: =IF(SUM($F35:K35)-$E35-SUM($S35:W35)>0,MAX($AF35,SUM($F35:K35)-$E35-SUM($S35:W35)),0) -> 1059.7312 | Y35: =IF(SUM($F35:L35)-$E35-SUM($S35:X35)>0,MAX($AF35,SUM($F35:L35)-$E35-SUM($S35:X35)),0) -> 608.5239 | Z35: =IF(SUM($F35:M35)-$E35-SUM($S35:Y35)>0,MAX($AF35,SUM($F35:M35)-$E35-SUM($S35:Y35)),0) -> 400.68 | AA35: =IF(SUM($F35:N35)-$E35-SUM($S35:Z35)>0,MAX($AF35,SUM($F35:N35)-$E35-SUM($S35:Z35)),0) -> 327.8881 | ... AD35: =IF(SUM($F35:Q35)-$E35-SUM($S35:AC35)>0,MAX($AF35,SUM($F35:Q35)-$E35-SUM($S35:AC35)),0) -> 1359.8344 | AE35: =SUM(S35:AD35) -> 7427.3829 | AF35: 0
A36: EDTACU | B36: DISSOLVINE - EDTA- CU-15 | C36: Formulados | D36: kg | E36: 64.498712 | F36: 0 | G36: 0 | H36: 0 | I36: 0 | J36: 80 | K36: 0 | L36: 2.438 | M36: 2.438 | N36: 0 | O36: 80 | P36: 300.586 | Q36: 80 | R36: =SUM(F36:Q36) -> 545.462 | S36: =IF(SUM($F36:F36)-$E36-0>0,MAX($AF36,SUM($F36:F36)-$E36-0),0) -> 0 | T36: =IF(SUM($F36:G36)-$E36-SUM($S36:S36)>0,MAX($AF36,SUM($F36:G36)-$E36-SUM($S36:S36)),0) -> 0 | U36: =IF(SUM($F36:H36)-$E36-SUM($S36:T36)>0,MAX($AF36,SUM($F36:H36)-$E36-SUM($S36:T36)),0) -> 0 | V36: =IF(SUM($F36:I36)-$E36-SUM($S36:U36)>0,MAX($AF36,SUM($F36:I36)-$E36-SUM($S36:U36)),0) -> 0 | W36: =IF(SUM($F36:J36)-$E36-SUM($S36:V36)>0,MAX($AF36,SUM($F36:J36)-$E36-SUM($S36:V36)),0) -> 15.501288 | X36: =IF(SUM($F36:K36)-$E36-SUM($S36:W36)>0,MAX($AF36,SUM($F36:K36)-$E36-SUM($S36:W36)),0) -> 0 | Y36: =IF(SUM($F36:L36)-$E36-SUM($S36:X36)>0,MAX($AF36,SUM($F36:L36)-$E36-SUM($S36:X36)),0) -> 2.438 | Z36: =IF(SUM($F36:M36)-$E36-SUM($S36:Y36)>0,MAX($AF36,SUM($F36:M36)-$E36-SUM($S36:Y36)),0) -> 2.438 | AA36: =IF(SUM($F36:N36)-$E36-SUM($S36:Z36)>0,MAX($AF36,SUM($F36:N36)-$E36-SUM($S36:Z36)),0) -> 0 | ... AD36: =IF(SUM($F36:Q36)-$E36-SUM($S36:AC36)>0,MAX($AF36,SUM($F36:Q36)-$E36-SUM($S36:AC36)),0) -> 80 | AE36: =SUM(S36:AD36) -> 480.96329 | AF36: 0
A37: EDTAFE | B37: DISSOLVINE - EDTA-FE 13 | C37: Formulados | D37: kg | E37: 37.819609 | F37: 0 | G37: 0 | H37: 0 | I37: 0 | J37: 0 | K37: 0 | L37: 2.438 | M37: 2.438 | N37: 0 | O37: 0 | P37: 2.346 | Q37: 0 | R37: =SUM(F37:Q37) -> 7.222 | S37: =IF(SUM($F37:F37)-$E37-0>0,MAX($AF37,SUM($F37:F37)-$E37-0),0) -> 0 | T37: =IF(SUM($F37:G37)-$E37-SUM($S37:S37)>0,MAX($AF37,SUM($F37:G37)-$E37-SUM($S37:S37)),0) -> 0 | U37: =IF(SUM($F37:H37)-$E37-SUM($S37:T37)>0,MAX($AF37,SUM($F37:H37)-$E37-SUM($S37:T37)),0) -> 0 | V37: =IF(SUM($F37:I37)-$E37-SUM($S37:U37)>0,MAX($AF37,SUM($F37:I37)-$E37-SUM($S37:U37)),0) -> 0 | W37: =IF(SUM($F37:J37)-$E37-SUM($S37:V37)>0,MAX($AF37,SUM($F37:J37)-$E37-SUM($S37:V37)),0) -> 0 | X37: =IF(SUM($F37:K37)-$E37-SUM($S37:W37)>0,MAX($AF37,SUM($F37:K37)-$E37-SUM($S37:W37)),0) -> 0 | Y37: =IF(SUM($F37:L37)-$E37-SUM($S37:X37)>0,MAX($AF37,SUM($F37:L37)-$E37-SUM($S37:X37)),0) -> 0 | Z37: =IF(SUM($F37:M37)-$E37-SUM($S37:Y37)>0,MAX($AF37,SUM($F37:M37)-$E37-SUM($S37:Y37)),0) -> 0 | AA37: =IF(SUM($F37:N37)-$E37-SUM($S37:Z37)>0,MAX($AF37,SUM($F37:N37)-$E37-SUM($S37:Z37)),0) -> 0 | ... AD37: =IF(SUM($F37:Q37)-$E37-SUM($S37:AC37)>0,MAX($AF37,SUM($F37:Q37)-$E37-SUM($S37:AC37)),0) -> 0 | AE37: =SUM(S37:AD37) -> 0 | AF37: 0
A38: EDTAMN | B38: DISSOLVINE - EDTA MN 13 | C38: Formulados | D38: kg | E38: 511.76761 | F38: 0 | G38: 0 | H38: 0 | I38: 0 | J38: 0 | K38: 0 | L38: 1.378 | M38: 1.378 | N38: 0 | O38: 0 | P38: 1.326 | Q38: 0 | R38: =SUM(F38:Q38) -> 4.082 | S38: =IF(SUM($F38:F38)-$E38-0>0,MAX($AF38,SUM($F38:F38)-$E38-0),0) -> 0 | T38: =IF(SUM($F38:G38)-$E38-SUM($S38:S38)>0,MAX($AF38,SUM($F38:G38)-$E38-SUM($S38:S38)),0) -> 0 | U38: =IF(SUM($F38:H38)-$E38-SUM($S38:T38)>0,MAX($AF38,SUM($F38:H38)-$E38-SUM($S38:T38)),0) -> 0 | V38: =IF(SUM($F38:I38)-$E38-SUM($S38:U38)>0,MAX($AF38,SUM($F38:I38)-$E38-SUM($S38:U38)),0) -> 0 | W38: =IF(SUM($F38:J38)-$E38-SUM($S38:V38)>0,MAX($AF38,SUM($F38:J38)-$E38-SUM($S38:V38)),0) -> 0 | X38: =IF(SUM($F38:K38)-$E38-SUM($S38:W38)>0,MAX($AF38,SUM($F38:K38)-$E38-SUM($S38:W38)),0) -> 0 | Y38: =IF(SUM($F38:L38)-$E38-SUM($S38:X38)>0,MAX($AF38,SUM($F38:L38)-$E38-SUM($S38:X38)),0) -> 0 | Z38: =IF(SUM($F38:M38)-$E38-SUM($S38:Y38)>0,MAX($AF38,SUM($F38:M38)-$E38-SUM($S38:Y38)),0) -> 0 | AA38: =IF(SUM($F38:N38)-$E38-SUM($S38:Z38)>0,MAX($AF38,SUM($F38:N38)-$E38-SUM($S38:Z38)),0) -> 0 | ... AD38: =IF(SUM($F38:Q38)-$E38-SUM($S38:AC38)>0,MAX($AF38,SUM($F38:Q38)-$E38-SUM($S38:AC38)),0) -> 0 | AE38: =SUM(S38:AD38) -> 0 | AF38: 0
A39: EDTAZN | B39: DISSOLVINE - EDTA ZN 15 | C39: Formulados | D39: kg | E39: 0 | F39: 0 | G39: 0 | H39: 0 | I39: 0 | J39: 80 | K39: 0 | L39: 1.378 | M39: 1.378 | N39: 0 | O39: 80 | P39: 299.566 | Q39: 80 | R39: =SUM(F39:Q39) -> 542.322 | S39: =IF(SUM($F39:F39)-$E39-0>0,MAX($AF39,SUM($F39:F39)-$E39-0),0) -> 0 | T39: =IF(SUM($F39:G39)-$E39-SUM($S39:S39)>0,MAX($AF39,SUM($F39:G39)-$E39-SUM($S39:S39)),0) -> 0 | U39: =IF(SUM($F39:H39)-$E39-SUM($S39:T39)>0,MAX($AF39,SUM($F39:H39)-$E39-SUM($S39:T39)),0) -> 0 | V39: =IF(SUM($F39:I39)-$E39-SUM($S39:U39)>0,MAX($AF39,SUM($F39:I39)-$E39-SUM($S39:U39)),0) -> 0 | W39: =IF(SUM($F39:J39)-$E39-SUM($S39:V39)>0,MAX($AF39,SUM($F39:J39)-$E39-SUM($S39:V39)),0) -> 80 | X39: =IF(SUM($F39:K39)-$E39-SUM($S39:W39)>0,MAX($AF39,SUM($F39:K39)-$E39-SUM($S39:W39)),0) -> 0 | Y39: =IF(SUM($F39:L39)-$E39-SUM($S39:X39)>0,MAX($AF39,SUM($F39:L39)-$E39-SUM($S39:X39)),0) -> 1.378 | Z39: =IF(SUM($F39:M39)-$E39-SUM($S39:Y39)>0,MAX($AF39,SUM($F39:M39)-$E39-SUM($S39:Y39)),0) -> 1.378 | AA39: =IF(SUM($F39:N39)-$E39-SUM($S39:Z39)>0,MAX($AF39,SUM($F39:N39)-$E39-SUM($S39:Z39)),0) -> 0 | ... AD39: =IF(SUM($F39:Q39)-$E39-SUM($S39:AC39)>0,MAX($AF39,SUM($F39:Q39)-$E39-SUM($S39:AC39)),0) -> 80 | AE39: =SUM(S39:AD39) -> 542.322 | AF39: 0
A40: FMA | B40: FOSFATO MONOAMONICO | C40: Formulados | D40: kg | E40: 725.84426 | F40: 657.6723 | G40: 1145.3147 | H40: 221.94394 | I40: 923.455 | J40: 1327.581 | K40: 1110.575 | L40: 648.475 | M40: 1169.571 | N40: 345.575 | O40: 446.375 | P40: 1233.802 | Q40: 882.9 | R40: =SUM(F40:Q40) -> 10113.24 | S40: =IF(SUM($F40:F40)-$E40-0>0,MAX($AF40,SUM($F40:F40)-$E40-0),0) -> 0 | T40: =IF(SUM($F40:G40)-$E40-SUM($S40:S40)>0,MAX($AF40,SUM($F40:G40)-$E40-SUM($S40:S40)),0) -> 1077.1427 | U40: =IF(SUM($F40:H40)-$E40-SUM($S40:T40)>0,MAX($AF40,SUM($F40:H40)-$E40-SUM($S40:T40)),0) -> 221.94394 | V40: =IF(SUM($F40:I40)-$E40-SUM($S40:U40)>0,MAX($AF40,SUM($F40:I40)-$E40-SUM($S40:U40)),0) -> 923.455 | W40: =IF(SUM($F40:J40)-$E40-SUM($S40:V40)>0,MAX($AF40,SUM($F40:J40)-$E40-SUM($S40:V40)),0) -> 1327.581 | X40: =IF(SUM($F40:K40)-$E40-SUM($S40:W40)>0,MAX($AF40,SUM($F40:K40)-$E40-SUM($S40:W40)),0) -> 1110.575 | Y40: =IF(SUM($F40:L40)-$E40-SUM($S40:X40)>0,MAX($AF40,SUM($F40:L40)-$E40-SUM($S40:X40)),0) -> 648.475 | Z40: =IF(SUM($F40:M40)-$E40-SUM($S40:Y40)>0,MAX($AF40,SUM($F40:M40)-$E40-SUM($S40:Y40)),0) -> 1169.571 | AA40: =IF(SUM($F40:N40)-$E40-SUM($S40:Z40)>0,MAX($AF40,SUM($F40:N40)-$E40-SUM($S40:Z40)),0) -> 345.575 | ... AD40: =IF(SUM($F40:Q40)-$E40-SUM($S40:AC40)>0,MAX($AF40,SUM($F40:Q40)-$E40-SUM($S40:AC40)),0) -> 882.9 | AE40: =SUM(S40:AD40) -> 9387.3956 | AF40: 0
A41: FMP | B41: FOSFATO MONOPOTASICO | C41: Formulados | D41: kg | E41: 0 | F41: 2701.733 | G41: 8618.3836 | H41: 3492.14 | I41: 3999.19 | J41: 10408.615 | K41: 9099.39 | L41: 3973.235 | M41: 5932.962 | N41: 1134.925 | O41: 3132.555 | P41: 3159.943 | Q41: 14337.35 | R41: =SUM(F41:Q41) -> 69990.422 | S41: =IF(SUM($F41:F41)-$E41-0>0,MAX($AF41,SUM($F41:F41)-$E41-0),0) -> 2701.733 | T41: =IF(SUM($F41:G41)-$E41-SUM($S41:S41)>0,MAX($AF41,SUM($F41:G41)-$E41-SUM($S41:S41)),0) -> 8618.3836 | U41: =IF(SUM($F41:H41)-$E41-SUM($S41:T41)>0,MAX($AF41,SUM($F41:H41)-$E41-SUM($S41:T41)),0) -> 3492.14 | V41: =IF(SUM($F41:I41)-$E41-SUM($S41:U41)>0,MAX($AF41,SUM($F41:I41)-$E41-SUM($S41:U41)),0) -> 3999.19 | W41: =IF(SUM($F41:J41)-$E41-SUM($S41:V41)>0,MAX($AF41,SUM($F41:J41)-$E41-SUM($S41:V41)),0) -> 10408.615 | X41: =IF(SUM($F41:K41)-$E41-SUM($S41:W41)>0,MAX($AF41,SUM($F41:K41)-$E41-SUM($S41:W41)),0) -> 9099.39 | Y41: =IF(SUM($F41:L41)-$E41-SUM($S41:X41)>0,MAX($AF41,SUM($F41:L41)-$E41-SUM($S41:X41)),0) -> 3973.235 | Z41: =IF(SUM($F41:M41)-$E41-SUM($S41:Y41)>0,MAX($AF41,SUM($F41:M41)-$E41-SUM($S41:Y41)),0) -> 5932.962 | AA41: =IF(SUM($F41:N41)-$E41-SUM($S41:Z41)>0,MAX($AF41,SUM($F41:N41)-$E41-SUM($S41:Z41)),0) -> 1134.925 | ... AD41: =IF(SUM($F41:Q41)-$E41-SUM($S41:AC41)>0,MAX($AF41,SUM($F41:Q41)-$E41-SUM($S41:AC41)),0) -> 14337.35 | AE41: =SUM(S41:AD41) -> 69990.422 | AF41: 0
... A53: HCA | B53: HIDROXIDO DE CAL | C53: Formulados | D53: kg | E53: 0 | F53: 44276.052 | G53: 63813.897 | H53: 189992.62 | I53: 91522.918 | J53: 276095.67 | K53: 206333.45 | L53: 146863.16 | M53: 50358.702 | N53: 32088.806 | O53: 43217.429 | P53: 72859.483 | Q53: 144059.71 | R53: =SUM(F53:Q53) -> 1361481.9 | S53: =IF(SUM($F53:F53)-$E53-0>0,MAX($AF53,SUM($F53:F53)-$E53-0),0) -> 44276.052 | T53: =IF(SUM($F53:G53)-$E53-SUM($S53:S53)>0,MAX($AF53,SUM($F53:G53)-$E53-SUM($S53:S53)),0) -> 63813.897 | U53: =IF(SUM($F53:H53)-$E53-SUM($S53:T53)>0,MAX($AF53,SUM($F53:H53)-$E53-SUM($S53:T53)),0) -> 189992.62 | V53: =IF(SUM($F53:I53)-$E53-SUM($S53:U53)>0,MAX($AF53,SUM($F53:I53)-$E53-SUM($S53:U53)),0) -> 91522.918 | W53: =IF(SUM($F53:J53)-$E53-SUM($S53:V53)>0,MAX($AF53,SUM($F53:J53)-$E53-SUM($S53:V53)),0) -> 276095.67 | X53: =IF(SUM($F53:K53)-$E53-SUM($S53:W53)>0,MAX($AF53,SUM($F53:K53)-$E53-SUM($S53:W53)),0) -> 206333.45 | Y53: =IF(SUM($F53:L53)-$E53-SUM($S53:X53)>0,MAX($AF53,SUM($F53:L53)-$E53-SUM($S53:X53)),0) -> 146863.16 | Z53: =IF(SUM($F53:M53)-$E53-SUM($S53:Y53)>0,MAX($AF53,SUM($F53:M53)-$E53-SUM($S53:Y53)),0) -> 50358.702 | AA53: =IF(SUM($F53:N53)-$E53-SUM($S53:Z53)>0,MAX($AF53,SUM($F53:N53)-$E53-SUM($S53:Z53)),0) -> 32088.806 | ... AD53: =IF(SUM($F53:Q53)-$E53-SUM($S53:AC53)>0,MAX($AF53,SUM($F53:Q53)-$E53-SUM($S53:AC53)),0) -> 144059.71 | AE53: =SUM(S53:AD53) -> 1361481.9 | AF53: 0
A54: HGA-FE | B54: HEPTAGLUCONATO DE HIERRO | C54: Formulados | D54: kg | E54: 315 | F54: 0 | G54: 0 | H54: 543 | I54: 103 | J54: 35 | K54: 0 | L54: 0 | M54: 0 | N54: 0 | O54: 0 | P54: 0 | Q54: 0 | R54: =SUM(F54:Q54) -> 681 | S54: =IF(SUM($F54:F54)-$E54-0>0,MAX($AF54,SUM($F54:F54)-$E54-0),0) -> 0 | T54: =IF(SUM($F54:G54)-$E54-SUM($S54:S54)>0,MAX($AF54,SUM($F54:G54)-$E54-SUM($S54:S54)),0) -> 0 | U54: =IF(SUM($F54:H54)-$E54-SUM($S54:T54)>0,MAX($AF54,SUM($F54:H54)-$E54-SUM($S54:T54)),0) -> 1200 | V54: =IF(SUM($F54:I54)-$E54-SUM($S54:U54)>0,MAX($AF54,SUM($F54:I54)-$E54-SUM($S54:U54)),0) -> 0 | W54: =IF(SUM($F54:J54)-$E54-SUM($S54:V54)>0,MAX($AF54,SUM($F54:J54)-$E54-SUM($S54:V54)),0) -> 0 | X54: =IF(SUM($F54:K54)-$E54-SUM($S54:W54)>0,MAX($AF54,SUM($F54:K54)-$E54-SUM($S54:W54)),0) -> 0 | Y54: =IF(SUM($F54:L54)-$E54-SUM($S54:X54)>0,MAX($AF54,SUM($F54:L54)-$E54-SUM($S54:X54)),0) -> 0 | Z54: =IF(SUM($F54:M54)-$E54-SUM($S54:Y54)>0,MAX($AF54,SUM($F54:M54)-$E54-SUM($S54:Y54)),0) -> 0 | AA54: =IF(SUM($F54:N54)-$E54-SUM($S54:Z54)>0,MAX($AF54,SUM($F54:N54)-$E54-SUM($S54:Z54)),0) -> 0 | ... AD54: =IF(SUM($F54:Q54)-$E54-SUM($S54:AC54)>0,MAX($AF54,SUM($F54:Q54)-$E54-SUM($S54:AC54)),0) -> 0 | AE54: =SUM(S54:AD54) -> 1200 | AF54: 1200 | AG54: Lote mínimo indicado por el usuario.
A55: HGA-FEL | B55: HEPTAGLUCONATO DE HIERRO LÍQUIDO | C55: Formulados | D55: kg | E55: 520.73107 | F55: 0 | G55: 0 | H55: 0 | I55: 0 | J55: 535.434 | K55: 77.5 | L55: 770 | M55: 35 | N55: 0 | O55: 0 | P55: 513.22 | Q55: 0 | R55: =SUM(F55:Q55) -> 1931.154 | S55: =IF(SUM($F55:F55)-$E55-0>0,MAX($AF55,SUM($F55:F55)-$E55-0),0) -> 0 | T55: =IF(SUM($F55:G55)-$E55-SUM($S55:S55)>0,MAX($AF55,SUM($F55:G55)-$E55-SUM($S55:S55)),0) -> 0 | U55: =IF(SUM($F55:H55)-$E55-SUM($S55:T55)>0,MAX($AF55,SUM($F55:H55)-$E55-SUM($S55:T55)),0) -> 0 | V55: =IF(SUM($F55:I55)-$E55-SUM($S55:U55)>0,MAX($AF55,SUM($F55:I55)-$E55-SUM($S55:U55)),0) -> 0 | W55: =IF(SUM($F55:J55)-$E55-SUM($S55:V55)>0,MAX($AF55,SUM($F55:J55)-$E55-SUM($S55:V55)),0) -> 14.702928 | X55: =IF(SUM($F55:K55)-$E55-SUM($S55:W55)>0,MAX($AF55,SUM($F55:K55)-$E55-SUM($S55:W55)),0) -> 77.5 | Y55: =IF(SUM($F55:L55)-$E55-SUM($S55:X55)>0,MAX($AF55,SUM($F55:L55)-$E55-SUM($S55:X55)),0) -> 770 | Z55: =IF(SUM($F55:M55)-$E55-SUM($S55:Y55)>0,MAX($AF55,SUM($F55:M55)-$E55-SUM($S55:Y55)),0) -> 35 | AA55: =IF(SUM($F55:N55)-$E55-SUM($S55:Z55)>0,MAX($AF55,SUM($F55:N55)-$E55-SUM($S55:Z55)),0) -> 0 | ... AD55: =IF(SUM($F55:Q55)-$E55-SUM($S55:AC55)>0,MAX($AF55,SUM($F55:Q55)-$E55-SUM($S55:AC55)),0) -> 0 | AE55: =SUM(S55:AD55) -> 1410.4229 | AF55: 0
A56: HGA-MGL | B56: HEPTAGLUCONATO DE MAGNESIO LÍQUIDO | C56: Formulados | D56: kg | E56: 0 | F56: 0 | G56: 0 | H56: 0 | I56: 0 | J56: 25.7 | K56: 0 | L56: 0 | M56: 0 | N56: 0 | O56: 0 | P56: 0 | Q56: 0 | R56: =SUM(F56:Q56) -> 25.7 | S56: =IF(SUM($F56:F56)-$E56-0>0,MAX($AF56,SUM($F56:F56)-$E56-0),0) -> 0 | T56: =IF(SUM($F56:G56)-$E56-SUM($S56:S56)>0,MAX($AF56,SUM($F56:G56)-$E56-SUM($S56:S56)),0) -> 0 | U56: =IF(SUM($F56:H56)-$E56-SUM($S56:T56)>0,MAX($AF56,SUM($F56:H56)-$E56-SUM($S56:T56)),0) -> 0 | V56: =IF(SUM($F56:I56)-$E56-SUM($S56:U56)>0,MAX($AF56,SUM($F56:I56)-$E56-SUM($S56:U56)),0) -> 0 | W56: =IF(SUM($F56:J56)-$E56-SUM($S56:V56)>0,MAX($AF56,SUM($F56:J56)-$E56-SUM($S56:V56)),0) -> 1250 | X56: =IF(SUM($F56:K56)-$E56-SUM($S56:W56)>0,MAX($AF56,SUM($F56:K56)-$E56-SUM($S56:W56)),0) -> 0 | Y56: =IF(SUM($F56:L56)-$E56-SUM($S56:X56)>0,MAX($AF56,SUM($F56:L56)-$E56-SUM($S56:X56)),0) -> 0 | Z56: =IF(SUM($F56:M56)-$E56-SUM($S56:Y56)>0,MAX($AF56,SUM($F56:M56)-$E56-SUM($S56:Y56)),0) -> 0 | AA56: =IF(SUM($F56:N56)-$E56-SUM($S56:Z56)>0,MAX($AF56,SUM($F56:N56)-$E56-SUM($S56:Z56)),0) -> 0 | ... AD56: =IF(SUM($F56:Q56)-$E56-SUM($S56:AC56)>0,MAX($AF56,SUM($F56:Q56)-$E56-SUM($S56:AC56)),0) -> 0 | AE56: =SUM(S56:AD56) -> 1250 | AF56: 1250 | AG56: Lote mínimo indicado por el usuario.
A57: HPO | B57: HIDROXIDO POTASICO | C57: Formulados | D57: kg | E57: 0 | F57: 0 | G57: 0 | H57: 460 | I57: 240 | J57: 0 | K57: 0 | L57: 473 | M57: 0 | N57: 0 | O57: 0 | P57: 1640 | Q57: 200 | R57: =SUM(F57:Q57) -> 3013 | S57: =IF(SUM($F57:F57)-$E57-0>0,MAX($AF57,SUM($F57:F57)-$E57-0),0) -> 0 | T57: =IF(SUM($F57:G57)-$E57-SUM($S57:S57)>0,MAX($AF57,SUM($F57:G57)-$E57-SUM($S57:S57)),0) -> 0 | U57: =IF(SUM($F57:H57)-$E57-SUM($S57:T57)>0,MAX($AF57,SUM($F57:H57)-$E57-SUM($S57:T57)),0) -> 460 | V57: =IF(SUM($F57:I57)-$E57-SUM($S57:U57)>0,MAX($AF57,SUM($F57:I57)-$E57-SUM($S57:U57)),0) -> 240 | W57: =IF(SUM($F57:J57)-$E57-SUM($S57:V57)>0,MAX($AF57,SUM($F57:J57)-$E57-SUM($S57:V57)),0) -> 0 | X57: =IF(SUM($F57:K57)-$E57-SUM($S57:W57)>0,MAX($AF57,SUM($F57:K57)-$E57-SUM($S57:W57)),0) -> 0 | Y57: =IF(SUM($F57:L57)-$E57-SUM($S57:X57)>0,MAX($AF57,SUM($F57:L57)-$E57-SUM($S57:X57)),0) -> 473 | Z57: =IF(SUM($F57:M57)-$E57-SUM($S57:Y57)>0,MAX($AF57,SUM($F57:M57)-$E57-SUM($S57:Y57)),0) -> 0 | AA57: =IF(SUM($F57:N57)-$E57-SUM($S57:Z57)>0,MAX($AF57,SUM($F57:N57)-$E57-SUM($S57:Z57)),0) -> 0 | ... AD57: =IF(SUM($F57:Q57)-$E57-SUM($S57:AC57)>0,MAX($AF57,SUM($F57:Q57)-$E57-SUM($S57:AC57)),0) -> 200 | AE57: =SUM(S57:AD57) -> 3013 | AF57: 0
A58: HPOL | B58: HIDROXIDO POTASICO LIQUIDO | C58: Formulados | D58: kg | E58: 0 | F58: 12776.524 | G58: 21867.866 | H58: 15562.862 | I58: 15338.7 | J58: 17999.347 | K58: 34278.403 | L58: 20871.632 | M58: 11157.699 | N58: 8799.475 | O58: 15348.885 | P58: 20460.916 | Q58: 20260.897 | R58: =SUM(F58:Q58) -> 214723.21 | S58: =IF(SUM($F58:F58)-$E58-0>0,MAX($AF58,SUM($F58:F58)-$E58-0),0) -> 12776.524 | T58: =IF(SUM($F58:G58)-$E58-SUM($S58:S58)>0,MAX($AF58,SUM($F58:G58)-$E58-SUM($S58:S58)),0) -> 21867.866 | U58: =IF(SUM($F58:H58)-$E58-SUM($S58:T58)>0,MAX($AF58,SUM($F58:H58)-$E58-SUM($S58:T58)),0) -> 15562.862 | V58: =IF(SUM($F58:I58)-$E58-SUM($S58:U58)>0,MAX($AF58,SUM($F58:I58)-$E58-SUM($S58:U58)),0) -> 15338.7 | W58: =IF(SUM($F58:J58)-$E58-SUM($S58:V58)>0,MAX($AF58,SUM($F58:J58)-$E58-SUM($S58:V58)),0) -> 17999.347 | X58: =IF(SUM($F58:K58)-$E58-SUM($S58:W58)>0,MAX($AF58,SUM($F58:K58)-$E58-SUM($S58:W58)),0) -> 34278.403 | Y58: =IF(SUM($F58:L58)-$E58-SUM($S58:X58)>0,MAX($AF58,SUM($F58:L58)-$E58-SUM($S58:X58)),0) -> 20871.632 | Z58: =IF(SUM($F58:M58)-$E58-SUM($S58:Y58)>0,MAX($AF58,SUM($F58:M58)-$E58-SUM($S58:Y58)),0) -> 11157.699 | AA58: =IF(SUM($F58:N58)-$E58-SUM($S58:Z58)>0,MAX($AF58,SUM($F58:N58)-$E58-SUM($S58:Z58)),0) -> 8799.475 | ... AD58: =IF(SUM($F58:Q58)-$E58-SUM($S58:AC58)>0,MAX($AF58,SUM($F58:Q58)-$E58-SUM($S58:AC58)),0) -> 20260.897 | AE58: =SUM(S58:AD58) -> 214723.21 | AF58: 0
A59: JB | B59: JABÓN POTÁSICO | C59: Formulados | D59: L | E59: 0 | F59: 0 | G59: 0 | H59: 0 | I59: 0 | J59: 0 | K59: 0 | L59: 0 | M59: 40 | N59: 0 | O59: 0 | P59: 2541 | Q59: 0 | R59: =SUM(F59:Q59) -> 2581 | S59: =IF(SUM($F59:F59)-$E59-0>0,MAX($AF59,SUM($F59:F59)-$E59-0),0) -> 0 | T59: =IF(SUM($F59:G59)-$E59-SUM($S59:S59)>0,MAX($AF59,SUM($F59:G59)-$E59-SUM($S59:S59)),0) -> 0 | U59: =IF(SUM($F59:H59)-$E59-SUM($S59:T59)>0,MAX($AF59,SUM($F59:H59)-$E59-SUM($S59:T59)),0) -> 0 | V59: =IF(SUM($F59:I59)-$E59-SUM($S59:U59)>0,MAX($AF59,SUM($F59:I59)-$E59-SUM($S59:U59)),0) -> 0 | W59: =IF(SUM($F59:J59)-$E59-SUM($S59:V59)>0,MAX($AF59,SUM($F59:J59)-$E59-SUM($S59:V59)),0) -> 0 | X59: =IF(SUM($F59:K59)-$E59-SUM($S59:W59)>0,MAX($AF59,SUM($F59:K59)-$E59-SUM($S59:W59)),0) -> 0 | Y59: =IF(SUM($F59:L59)-$E59-SUM($S59:X59)>0,MAX($AF59,SUM($F59:L59)-$E59-SUM($S59:X59)),0) -> 0 | Z59: =IF(SUM($F59:M59)-$E59-SUM($S59:Y59)>0,MAX($AF59,SUM($F59:M59)-$E59-SUM($S59:Y59)),0) -> 40 | AA59: =IF(SUM($F59:N59)-$E59-SUM($S59:Z59)>0,MAX($AF59,SUM($F59:N59)-$E59-SUM($S59:Z59)),0) -> 0 | ... AD59: =IF(SUM($F59:Q59)-$E59-SUM($S59:AC59)>0,MAX($AF59,SUM($F59:Q59)-$E59-SUM($S59:AC59)),0) -> 0 | AE59: =SUM(S59:AD59) -> 2581 | AF59: 0
A60: KF78 | B60: BIOPOL KF78 | C60: Formulados | D60: kg | E60: 243.81734 | F60: 192.72783 | G60: 387.36264 | H60: 336.84861 | I60: 348.468 | J60: 243.75405 | K60: 463.0985 | L60: 213.2775 | M60: 255.99895 | N60: 193.5305 | O60: 249.3805 | P60: 280.49945 | Q60: 375.8005 | R60: =SUM(F60:Q60) -> 3540.747 | S60: =IF(SUM($F60:F60)-$E60-0>0,MAX($AF60,SUM($F60:F60)-$E60-0),0) -> 0 | T60: =IF(SUM($F60:G60)-$E60-SUM($S60:S60)>0,MAX($AF60,SUM($F60:G60)-$E60-SUM($S60:S60)),0) -> 336.27313 | U60: =IF(SUM($F60:H60)-$E60-SUM($S60:T60)>0,MAX($AF60,SUM($F60:H60)-$E60-SUM($S60:T60)),0) -> 336.84861 | V60: =IF(SUM($F60:I60)-$E60-SUM($S60:U60)>0,MAX($AF60,SUM($F60:I60)-$E60-SUM($S60:U60)),0) -> 348.468 | W60: =IF(SUM($F60:J60)-$E60-SUM($S60:V60)>0,MAX($AF60,SUM($F60:J60)-$E60-SUM($S60:V60)),0) -> 243.75405 | X60: =IF(SUM($F60:K60)-$E60-SUM($S60:W60)>0,MAX($AF60,SUM($F60:K60)-$E60-SUM($S60:W60)),0) -> 463.0985 | Y60: =IF(SUM($F60:L60)-$E60-SUM($S60:X60)>0,MAX($AF60,SUM($F60:L60)-$E60-SUM($S60:X60)),0) -> 213.2775 | Z60: =IF(SUM($F60:M60)-$E60-SUM($S60:Y60)>0,MAX($AF60,SUM($F60:M60)-$E60-SUM($S60:Y60)),0) -> 255.99895 | AA60: =IF(SUM($F60:N60)-$E60-SUM($S60:Z60)>0,MAX($AF60,SUM($F60:N60)-$E60-SUM($S60:Z60)),0) -> 193.5305 | ... AD60: =IF(SUM($F60:Q60)-$E60-SUM($S60:AC60)>0,MAX($AF60,SUM($F60:Q60)-$E60-SUM($S60:AC60)),0) -> 375.8005 | AE60: =SUM(S60:AD60) -> 3296.9297 | AF60: 0
A61: KIN | B61: kinetina | C61: Formulados | D61: kg | E61: 0 | F61: 1.0900925 | G61: 5.9805 | H61: 3.67 | I61: 3.53 | J61: 5.5625 | K61: 5.425 | L61: 5.9415 | M61: 2.005 | N61: 1.9225 | O61: 3.7915 | P61: 1.3515 | Q61: 18.505 | R61: =SUM(F61:Q61) -> 58.775092 | S61: =IF(SUM($F61:F61)-$E61-0>0,MAX($AF61,SUM($F61:F61)-$E61-0),0) -> 1.0900925 | T61: =IF(SUM($F61:G61)-$E61-SUM($S61:S61)>0,MAX($AF61,SUM($F61:G61)-$E61-SUM($S61:S61)),0) -> 5.9805 | U61: =IF(SUM($F61:H61)-$E61-SUM($S61:T61)>0,MAX($AF61,SUM($F61:H61)-$E61-SUM($S61:T61)),0) -> 3.67 | V61: =IF(SUM($F61:I61)-$E61-SUM($S61:U61)>0,MAX($AF61,SUM($F61:I61)-$E61-SUM($S61:U61)),0) -> 3.53 | W61: =IF(SUM($F61:J61)-$E61-SUM($S61:V61)>0,MAX($AF61,SUM($F61:J61)-$E61-SUM($S61:V61)),0) -> 5.5625 | X61: =IF(SUM($F61:K61)-$E61-SUM($S61:W61)>0,MAX($AF61,SUM($F61:K61)-$E61-SUM($S61:W61)),0) -> 5.425 | Y61: =IF(SUM($F61:L61)-$E61-SUM($S61:X61)>0,MAX($AF61,SUM($F61:L61)-$E61-SUM($S61:X61)),0) -> 5.9415 | Z61: =IF(SUM($F61:M61)-$E61-SUM($S61:Y61)>0,MAX($AF61,SUM($F61:M61)-$E61-SUM($S61:Y61)),0) -> 2.005 | AA61: =IF(SUM($F61:N61)-$E61-SUM($S61:Z61)>0,MAX($AF61,SUM($F61:N61)-$E61-SUM($S61:Z61)),0) -> 1.9225 | ... AD61: =IF(SUM($F61:Q61)-$E61-SUM($S61:AC61)>0,MAX($AF61,SUM($F61:Q61)-$E61-SUM($S61:AC61)),0) -> 18.505 | AE61: =SUM(S61:AD61) -> 58.775092 | AF61: 0
A62: LIGNOAM | B62: LIGNOSULFONATO AMÓNICO LÍQUIDO | C62: Formulados | D62: kg | E62: 703.82649 | F62: 63.168 | G62: 268.917 | H62: 285.84 | I62: 413.435 | J62: 260.961 | K62: 481.33 | L62: 11.28 | M62: 434.734 | N62: 723.94 | O62: 468.58 | P62: 642.392 | Q62: 476.82 | R62: =SUM(F62:Q62) -> 4531.397 | S62: =IF(SUM($F62:F62)-$E62-0>0,MAX($AF62,SUM($F62:F62)-$E62-0),0) -> 0 | T62: =IF(SUM($F62:G62)-$E62-SUM($S62:S62)>0,MAX($AF62,SUM($F62:G62)-$E62-SUM($S62:S62)),0) -> 0 | U62: =IF(SUM($F62:H62)-$E62-SUM($S62:T62)>0,MAX($AF62,SUM($F62:H62)-$E62-SUM($S62:T62)),0) -> 0 | V62: =IF(SUM($F62:I62)-$E62-SUM($S62:U62)>0,MAX($AF62,SUM($F62:I62)-$E62-SUM($S62:U62)),0) -> 327.53351 | W62: =IF(SUM($F62:J62)-$E62-SUM($S62:V62)>0,MAX($AF62,SUM($F62:J62)-$E62-SUM($S62:V62)),0) -> 260.961 | X62: =IF(SUM($F62:K62)-$E62-SUM($S62:W62)>0,MAX($AF62,SUM($F62:K62)-$E62-SUM($S62:W62)),0) -> 481.33 | Y62: =IF(SUM($F62:L62)-$E62-SUM($S62:X62)>0,MAX($AF62,SUM($F62:L62)-$E62-SUM($S62:X62)),0) -> 11.28 | Z62: =IF(SUM($F62:M62)-$E62-SUM($S62:Y62)>0,MAX($AF62,SUM($F62:M62)-$E62-SUM($S62:Y62)),0) -> 434.734 | AA62: =IF(SUM($F62:N62)-$E62-SUM($S62:Z62)>0,MAX($AF62,SUM($F62:N62)-$E62-SUM($S62:Z62)),0) -> 723.94 | ... AD62: =IF(SUM($F62:Q62)-$E62-SUM($S62:AC62)>0,MAX($AF62,SUM($F62:Q62)-$E62-SUM($S62:AC62)),0) -> 476.82 | AE62: =SUM(S62:AD62) -> 3827.5705 | AF62: 0
A63: MAL | B63: ACIDO MALICO | C63: Formulados | D63: kg | E63: 0 | F63: 31100.503 | G63: 26935.981 | H63: 20090.649 | I63: 27195.17 | J63: 27161.87 | K63: 35907.457 | L63: 23726.172 | M63: 17369.731 | N63: 8891.315 | O63: 13173.529 | P63: 20605.851 | Q63: 7549.9821 | R63: =SUM(F63:Q63) -> 259708.21 | S63: =IF(SUM($F63:F63)-$E63-0>0,MAX($AF63,SUM($F63:F63)-$E63-0),0) -> 31100.503 | T63: =IF(SUM($F63:G63)-$E63-SUM($S63:S63)>0,MAX($AF63,SUM($F63:G63)-$E63-SUM($S63:S63)),0) -> 26935.981 | U63: =IF(SUM($F63:H63)-$E63-SUM($S63:T63)>0,MAX($AF63,SUM($F63:H63)-$E63-SUM($S63:T63)),0) -> 20090.649 | V63: =IF(SUM($F63:I63)-$E63-SUM($S63:U63)>0,MAX($AF63,SUM($F63:I63)-$E63-SUM($S63:U63)),0) -> 27195.17 | W63: =IF(SUM($F63:J63)-$E63-SUM($S63:V63)>0,MAX($AF63,SUM($F63:J63)-$E63-SUM($S63:V63)),0) -> 27161.87 | X63: =IF(SUM($F63:K63)-$E63-SUM($S63:W63)>0,MAX($AF63,SUM($F63:K63)-$E63-SUM($S63:W63)),0) -> 35907.457 | Y63: =IF(SUM($F63:L63)-$E63-SUM($S63:X63)>0,MAX($AF63,SUM($F63:L63)-$E63-SUM($S63:X63)),0) -> 23726.172 | Z63: =IF(SUM($F63:M63)-$E63-SUM($S63:Y63)>0,MAX($AF63,SUM($F63:M63)-$E63-SUM($S63:Y63)),0) -> 17369.731 | AA63: =IF(SUM($F63:N63)-$E63-SUM($S63:Z63)>0,MAX($AF63,SUM($F63:N63)-$E63-SUM($S63:Z63)),0) -> 8891.315 | ... AD63: =IF(SUM($F63:Q63)-$E63-SUM($S63:AC63)>0,MAX($AF63,SUM($F63:Q63)-$E63-SUM($S63:AC63)),0) -> 7549.982 | AE63: =SUM(S63:AD63) -> 259708.21 | AF63: 0
A64: MAN | B64: MANITOL | C64: Formulados | D64: kg | E64: 142.05307 | F64: 11.965 | G64: 23.395 | H64: 1.3229387 | I64: 23.955 | J64: 8.845 | K64: 2.2 | L64: 10.005 | M64: 20.045 | N64: 12.395 | O64: 2.61 | P64: 18.25 | Q64: 20.74 | R64: =SUM(F64:Q64) -> 155.72794 | S64: =IF(SUM($F64:F64)-$E64-0>0,MAX($AF64,SUM($F64:F64)-$E64-0),0) -> 0 | T64: =IF(SUM($F64:G64)-$E64-SUM($S64:S64)>0,MAX($AF64,SUM($F64:G64)-$E64-SUM($S64:S64)),0) -> 0 | U64: =IF(SUM($F64:H64)-$E64-SUM($S64:T64)>0,MAX($AF64,SUM($F64:H64)-$E64-SUM($S64:T64)),0) -> 0 | V64: =IF(SUM($F64:I64)-$E64-SUM($S64:U64)>0,MAX($AF64,SUM($F64:I64)-$E64-SUM($S64:U64)),0) -> 0 | W64: =IF(SUM($F64:J64)-$E64-SUM($S64:V64)>0,MAX($AF64,SUM($F64:J64)-$E64-SUM($S64:V64)),0) -> 0 | X64: =IF(SUM($F64:K64)-$E64-SUM($S64:W64)>0,MAX($AF64,SUM($F64:K64)-$E64-SUM($S64:W64)),0) -> 0 | Y64: =IF(SUM($F64:L64)-$E64-SUM($S64:X64)>0,MAX($AF64,SUM($F64:L64)-$E64-SUM($S64:X64)),0) -> 0 | Z64: =IF(SUM($F64:M64)-$E64-SUM($S64:Y64)>0,MAX($AF64,SUM($F64:M64)-$E64-SUM($S64:Y64)),0) -> 0 | AA64: =IF(SUM($F64:N64)-$E64-SUM($S64:Z64)>0,MAX($AF64,SUM($F64:N64)-$E64-SUM($S64:Z64)),0) -> 0 | ... AD64: =IF(SUM($F64:Q64)-$E64-SUM($S64:AC64)>0,MAX($AF64,SUM($F64:Q64)-$E64-SUM($S64:AC64)),0) -> 13.674865 | AE64: =SUM(S64:AD64) -> 13.674865 | AF64: 0
A65: MEA | B65: MONOETANOLAMINA | C65: Formulados | D65: kg | E65: 0 | F65: 454.635 | G65: 1765.9533 | H65: 1099.7606 | I65: 830.93419 | J65: 910.832 | K65: 2140.703 | L65: 638.902 | M65: 588.146 | N65: 35.138 | O65: 862.145 | P65: 1820.951 | Q65: 443.246 | R65: =SUM(F65:Q65) -> 11591.346 | S65: =IF(SUM($F65:F65)-$E65-0>0,MAX($AF65,SUM($F65:F65)-$E65-0),0) -> 454.635 | T65: =IF(SUM($F65:G65)-$E65-SUM($S65:S65)>0,MAX($AF65,SUM($F65:G65)-$E65-SUM($S65:S65)),0) -> 1765.9533 | U65: =IF(SUM($F65:H65)-$E65-SUM($S65:T65)>0,MAX($AF65,SUM($F65:H65)-$E65-SUM($S65:T65)),0) -> 1099.7606 | V65: =IF(SUM($F65:I65)-$E65-SUM($S65:U65)>0,MAX($AF65,SUM($F65:I65)-$E65-SUM($S65:U65)),0) -> 830.93419 | W65: =IF(SUM($F65:J65)-$E65-SUM($S65:V65)>0,MAX($AF65,SUM($F65:J65)-$E65-SUM($S65:V65)),0) -> 910.832 | X65: =IF(SUM($F65:K65)-$E65-SUM($S65:W65)>0,MAX($AF65,SUM($F65:K65)-$E65-SUM($S65:W65)),0) -> 2140.703 | Y65: =IF(SUM($F65:L65)-$E65-SUM($S65:X65)>0,MAX($AF65,SUM($F65:L65)-$E65-SUM($S65:X65)),0) -> 638.902 | Z65: =IF(SUM($F65:M65)-$E65-SUM($S65:Y65)>0,MAX($AF65,SUM($F65:M65)-$E65-SUM($S65:Y65)),0) -> 588.146 | AA65: =IF(SUM($F65:N65)-$E65-SUM($S65:Z65)>0,MAX($AF65,SUM($F65:N65)-$E65-SUM($S65:Z65)),0) -> 35.138 | ... AD65: =IF(SUM($F65:Q65)-$E65-SUM($S65:AC65)>0,MAX($AF65,SUM($F65:Q65)-$E65-SUM($S65:AC65)),0) -> 443.246 | AE65: =SUM(S65:AD65) -> 11591.346 | AF65: 0
A66: MGO | B66: OXIDO DE MAGNESIO | C66: Formulados | D66: kg | E66: 264.81337 | F66: 174.06462 | G66: 162.9859 | H66: 155.8126 | I66: 264.2825 | J66: 667.94993 | K66: 407.03278 | L66: 1065.8867 | M66: 71.169087 | N66: 96.44885 | O66: 125.6906 | P66: 221.41011 | Q66: 1614.172 | R66: =SUM(F66:Q66) -> 5026.9057 | S66: =IF(SUM($F66:F66)-$E66-0>0,MAX($AF66,SUM($F66:F66)-$E66-0),0) -> 0 | T66: =IF(SUM($F66:G66)-$E66-SUM($S66:S66)>0,MAX($AF66,SUM($F66:G66)-$E66-SUM($S66:S66)),0) -> 72.237147 | U66: =IF(SUM($F66:H66)-$E66-SUM($S66:T66)>0,MAX($AF66,SUM($F66:H66)-$E66-SUM($S66:T66)),0) -> 155.8126 | V66: =IF(SUM($F66:I66)-$E66-SUM($S66:U66)>0,MAX($AF66,SUM($F66:I66)-$E66-SUM($S66:U66)),0) -> 264.2825 | W66: =IF(SUM($F66:J66)-$E66-SUM($S66:V66)>0,MAX($AF66,SUM($F66:J66)-$E66-SUM($S66:V66)),0) -> 667.94993 | X66: =IF(SUM($F66:K66)-$E66-SUM($S66:W66)>0,MAX($AF66,SUM($F66:K66)-$E66-SUM($S66:W66)),0) -> 407.03278 | Y66: =IF(SUM($F66:L66)-$E66-SUM($S66:X66)>0,MAX($AF66,SUM($F66:L66)-$E66-SUM($S66:X66)),0) -> 1065.8867 | Z66: =IF(SUM($F66:M66)-$E66-SUM($S66:Y66)>0,MAX($AF66,SUM($F66:M66)-$E66-SUM($S66:Y66)),0) -> 71.169087 | AA66: =IF(SUM($F66:N66)-$E66-SUM($S66:Z66)>0,MAX($AF66,SUM($F66:N66)-$E66-SUM($S66:Z66)),0) -> 96.44885 | ... AD66: =IF(SUM($F66:Q66)-$E66-SUM($S66:AC66)>0,MAX($AF66,SUM($F66:Q66)-$E66-SUM($S66:AC66)),0) -> 1614.172 | AE66: =SUM(S66:AD66) -> 4762.0923 | AF66: 0
A67: MOSO | B67: MOLIBDATO SODICO | C67: Formulados | D67: kg | E67: 0 | F67: 57.686544 | G67: 329.1185 | H67: 623.54497 | I67: 250.964 | J67: 139.9225 | K67: 233.745 | L67: 361.5579 | M67: 379.1454 | N67: 140.1565 | O67: 130.6055 | P67: 48.8463 | Q67: 429.875 | R67: =SUM(F67:Q67) -> 3125.1681 | S67: =IF(SUM($F67:F67)-$E67-0>0,MAX($AF67,SUM($F67:F67)-$E67-0),0) -> 57.686544 | T67: =IF(SUM($F67:G67)-$E67-SUM($S67:S67)>0,MAX($AF67,SUM($F67:G67)-$E67-SUM($S67:S67)),0) -> 329.1185 | U67: =IF(SUM($F67:H67)-$E67-SUM($S67:T67)>0,MAX($AF67,SUM($F67:H67)-$E67-SUM($S67:T67)),0) -> 623.54497 | V67: =IF(SUM($F67:I67)-$E67-SUM($S67:U67)>0,MAX($AF67,SUM($F67:I67)-$E67-SUM($S67:U67)),0) -> 250.964 | W67: =IF(SUM($F67:J67)-$E67-SUM($S67:V67)>0,MAX($AF67,SUM($F67:J67)-$E67-SUM($S67:V67)),0) -> 139.9225 | X67: =IF(SUM($F67:K67)-$E67-SUM($S67:W67)>0,MAX($AF67,SUM($F67:K67)-$E67-SUM($S67:W67)),0) -> 233.745 | Y67: =IF(SUM($F67:L67)-$E67-SUM($S67:X67)>0,MAX($AF67,SUM($F67:L67)-$E67-SUM($S67:X67)),0) -> 361.5579 | Z67: =IF(SUM($F67:M67)-$E67-SUM($S67:Y67)>0,MAX($AF67,SUM($F67:M67)-$E67-SUM($S67:Y67)),0) -> 379.1454 | AA67: =IF(SUM($F67:N67)-$E67-SUM($S67:Z67)>0,MAX($AF67,SUM($F67:N67)-$E67-SUM($S67:Z67)),0) -> 140.1565 | ... AD67: =IF(SUM($F67:Q67)-$E67-SUM($S67:AC67)>0,MAX($AF67,SUM($F67:Q67)-$E67-SUM($S67:AC67)),0) -> 429.875 | AE67: =SUM(S67:AD67) -> 3125.1681 | AF67: 0
A68: NAM | B68: NITRATO AMONICO | C68: Formulados | D68: kg | E68: 0 | F68: 0 | G68: 52 | H68: 66 | I68: 32 | J68: 65 | K68: 10 | L68: 0 | M68: 204 | N68: 462 | O68: 264 | P68: 396 | Q68: 198 | R68: =SUM(F68:Q68) -> 1749 | S68: =IF(SUM($F68:F68)-$E68-0>0,MAX($AF68,SUM($F68:F68)-$E68-0),0) -> 0 | T68: =IF(SUM($F68:G68)-$E68-SUM($S68:S68)>0,MAX($AF68,SUM($F68:G68)-$E68-SUM($S68:S68)),0) -> 52 | U68: =IF(SUM($F68:H68)-$E68-SUM($S68:T68)>0,MAX($AF68,SUM($F68:H68)-$E68-SUM($S68:T68)),0) -> 66 | V68: =IF(SUM($F68:I68)-$E68-SUM($S68:U68)>0,MAX($AF68,SUM($F68:I68)-$E68-SUM($S68:U68)),0) -> 32 | W68: =IF(SUM($F68:J68)-$E68-SUM($S68:V68)>0,MAX($AF68,SUM($F68:J68)-$E68-SUM($S68:V68)),0) -> 65 | X68: =IF(SUM($F68:K68)-$E68-SUM($S68:W68)>0,MAX($AF68,SUM($F68:K68)-$E68-SUM($S68:W68)),0) -> 10 | Y68: =IF(SUM($F68:L68)-$E68-SUM($S68:X68)>0,MAX($AF68,SUM($F68:L68)-$E68-SUM($S68:X68)),0) -> 0 | Z68: =IF(SUM($F68:M68)-$E68-SUM($S68:Y68)>0,MAX($AF68,SUM($F68:M68)-$E68-SUM($S68:Y68)),0) -> 204 | AA68: =IF(SUM($F68:N68)-$E68-SUM($S68:Z68)>0,MAX($AF68,SUM($F68:N68)-$E68-SUM($S68:Z68)),0) -> 462 | ... AD68: =IF(SUM($F68:Q68)-$E68-SUM($S68:AC68)>0,MAX($AF68,SUM($F68:Q68)-$E68-SUM($S68:AC68)),0) -> 198 | AE68: =SUM(S68:AD68) -> 1749 | AF68: 0
... A129: ETQW33 | B129: ETIQUETA WALLSUN 33 CHILE | C129: Envasados | D129: ud | E129: 0 | F129: 0 | G129: 0 | H129: 0 | I129: 0 | J129: 0 | K129: 0 | L129: 0 | M129: 0 | N129: 0 | O129: 0 | P129: 0 | Q129: 23536 | R129: =SUM(F129:Q129) -> 23536 | S129: =IF(SUM($F129:F129)-$E129-0>0,MAX($AF129,SUM($F129:F129)-$E129-0),0) -> 0 | T129: =IF(SUM($F129:G129)-$E129-SUM($S129:S129)>0,MAX($AF129,SUM($F129:G129)-$E129-SUM($S129:S129)),0) -> 0 | U129: =IF(SUM($F129:H129)-$E129-SUM($S129:T129)>0,MAX($AF129,SUM($F129:H129)-$E129-SUM($S129:T129)),0) -> 0 | V129: =IF(SUM($F129:I129)-$E129-SUM($S129:U129)>0,MAX($AF129,SUM($F129:I129)-$E129-SUM($S129:U129)),0) -> 0 | W129: =IF(SUM($F129:J129)-$E129-SUM($S129:V129)>0,MAX($AF129,SUM($F129:J129)-$E129-SUM($S129:V129)),0) -> 0 | X129: =IF(SUM($F129:K129)-$E129-SUM($S129:W129)>0,MAX($AF129,SUM($F129:K129)-$E129-SUM($S129:W129)),0) -> 0 | Y129: =IF(SUM($F129:L129)-$E129-SUM($S129:X129)>0,MAX($AF129,SUM($F129:L129)-$E129-SUM($S129:X129)),0) -> 0 | Z129: =IF(SUM($F129:M129)-$E129-SUM($S129:Y129)>0,MAX($AF129,SUM($F129:M129)-$E129-SUM($S129:Y129)),0) -> 0 | AA129: =IF(SUM($F129:N129)-$E129-SUM($S129:Z129)>0,MAX($AF129,SUM($F129:N129)-$E129-SUM($S129:Z129)),0) -> 0 | ... AD129: =IF(SUM($F129:Q129)-$E129-SUM($S129:AC129)>0,MAX($AF129,SUM($F129:Q129)-$E129-SUM($S129:AC129)),0) -> 23536 | AE129: =SUM(S129:AD129) -> 23536 | AF129: 0
A130: FILM | B130: FILM ESTIRABLE 35 MM | C130: Envasados | D130: kg | E130: 0 | F130: 175.07201 | G130: 225.79679 | H130: 304.81997 | I130: 244.68402 | J130: 363.43863 | K130: 433.87198 | L130: 260.65998 | M130: 135.51121 | N130: 80.843219 | O130: 123.08674 | P130: 186.04651 | Q130: 266.862 | R130: =SUM(F130:Q130) -> 2800.6931 | S130: =IF(SUM($F130:F130)-$E130-0>0,MAX($AF130,SUM($F130:F130)-$E130-0),0) -> 175.07201 | T130: =IF(SUM($F130:G130)-$E130-SUM($S130:S130)>0,MAX($AF130,SUM($F130:G130)-$E130-SUM($S130:S130)),0) -> 225.79679 | U130: =IF(SUM($F130:H130)-$E130-SUM($S130:T130)>0,MAX($AF130,SUM($F130:H130)-$E130-SUM($S130:T130)),0) -> 304.81997 | V130: =IF(SUM($F130:I130)-$E130-SUM($S130:U130)>0,MAX($AF130,SUM($F130:I130)-$E130-SUM($S130:U130)),0) -> 244.68402 | W130: =IF(SUM($F130:J130)-$E130-SUM($S130:V130)>0,MAX($AF130,SUM($F130:J130)-$E130-SUM($S130:V130)),0) -> 363.43863 | X130: =IF(SUM($F130:K130)-$E130-SUM($S130:W130)>0,MAX($AF130,SUM($F130:K130)-$E130-SUM($S130:W130)),0) -> 433.87198 | Y130: =IF(SUM($F130:L130)-$E130-SUM($S130:X130)>0,MAX($AF130,SUM($F130:L130)-$E130-SUM($S130:X130)),0) -> 260.65998 | Z130: =IF(SUM($F130:M130)-$E130-SUM($S130:Y130)>0,MAX($AF130,SUM($F130:M130)-$E130-SUM($S130:Y130)),0) -> 135.51121 | AA130: =IF(SUM($F130:N130)-$E130-SUM($S130:Z130)>0,MAX($AF130,SUM($F130:N130)-$E130-SUM($S130:Z130)),0) -> 80.843219 | ... AD130: =IF(SUM($F130:Q130)-$E130-SUM($S130:AC130)>0,MAX($AF130,SUM($F130:Q130)-$E130-SUM($S130:AC130)),0) -> 266.862 | AE130: =SUM(S130:AD130) -> 2800.6931 | AF130: 0 | AG130: Incluye la necesidad mensual de FILMPR; ambos stocks al 31/12 son cero.
A131: KIA220 | B131: ETIQUETA KIARO 220 MM PP INY. | C131: Envasados | D131: ud | E131: 0 | F131: 17994.43 | G131: 80279.816 | H131: 21641.474 | I131: 9131.7437 | J131: 79776.58 | K131: 42866.288 | L131: 37296.697 | M131: 28967.548 | N131: 11265.85 | O131: 19840.29 | P131: 52171.547 | Q131: 49030.086 | R131: =SUM(F131:Q131) -> 450262.35 | S131: =IF(SUM($F131:F131)-$E131-0>0,MAX($AF131,SUM($F131:F131)-$E131-0),0) -> 17994.43 | T131: =IF(SUM($F131:G131)-$E131-SUM($S131:S131)>0,MAX($AF131,SUM($F131:G131)-$E131-SUM($S131:S131)),0) -> 80279.816 | U131: =IF(SUM($F131:H131)-$E131-SUM($S131:T131)>0,MAX($AF131,SUM($F131:H131)-$E131-SUM($S131:T131)),0) -> 21641.474 | V131: =IF(SUM($F131:I131)-$E131-SUM($S131:U131)>0,MAX($AF131,SUM($F131:I131)-$E131-SUM($S131:U131)),0) -> 9131.7437 | W131: =IF(SUM($F131:J131)-$E131-SUM($S131:V131)>0,MAX($AF131,SUM($F131:J131)-$E131-SUM($S131:V131)),0) -> 79776.58 | X131: =IF(SUM($F131:K131)-$E131-SUM($S131:W131)>0,MAX($AF131,SUM($F131:K131)-$E131-SUM($S131:W131)),0) -> 42866.288 | Y131: =IF(SUM($F131:L131)-$E131-SUM($S131:X131)>0,MAX($AF131,SUM($F131:L131)-$E131-SUM($S131:X131)),0) -> 37296.697 | Z131: =IF(SUM($F131:M131)-$E131-SUM($S131:Y131)>0,MAX($AF131,SUM($F131:M131)-$E131-SUM($S131:Y131)),0) -> 28967.548 | AA131: =IF(SUM($F131:N131)-$E131-SUM($S131:Z131)>0,MAX($AF131,SUM($F131:N131)-$E131-SUM($S131:Z131)),0) -> 11265.85 | ... AD131: =IF(SUM($F131:Q131)-$E131-SUM($S131:AC131)>0,MAX($AF131,SUM($F131:Q131)-$E131-SUM($S131:AC131)),0) -> 49030.086 | AE131: =SUM(S131:AD131) -> 450262.35 | AF131: 0
A132: KIA220P | B132: ETIQUETA 220 PAPEL INJECK | C132: Envasados | D132: ud | E132: 0 | F132: 226 | G132: 44.158379 | H132: 495 | I132: 22 | J132: 140 | K132: 546 | L132: 168 | M132: 46 | N132: 0 | O132: 368 | P132: 237 | Q132: 41 | R132: =SUM(F132:Q132) -> 2333.1584 | S132: =IF(SUM($F132:F132)-$E132-0>0,MAX($AF132,SUM($F132:F132)-$E132-0),0) -> 226 | T132: =IF(SUM($F132:G132)-$E132-SUM($S132:S132)>0,MAX($AF132,SUM($F132:G132)-$E132-SUM($S132:S132)),0) -> 44.158379 | U132: =IF(SUM($F132:H132)-$E132-SUM($S132:T132)>0,MAX($AF132,SUM($F132:H132)-$E132-SUM($S132:T132)),0) -> 495 | V132: =IF(SUM($F132:I132)-$E132-SUM($S132:U132)>0,MAX($AF132,SUM($F132:I132)-$E132-SUM($S132:U132)),0) -> 22 | W132: =IF(SUM($F132:J132)-$E132-SUM($S132:V132)>0,MAX($AF132,SUM($F132:J132)-$E132-SUM($S132:V132)),0) -> 140 | X132: =IF(SUM($F132:K132)-$E132-SUM($S132:W132)>0,MAX($AF132,SUM($F132:K132)-$E132-SUM($S132:W132)),0) -> 546 | Y132: =IF(SUM($F132:L132)-$E132-SUM($S132:X132)>0,MAX($AF132,SUM($F132:L132)-$E132-SUM($S132:X132)),0) -> 168 | Z132: =IF(SUM($F132:M132)-$E132-SUM($S132:Y132)>0,MAX($AF132,SUM($F132:M132)-$E132-SUM($S132:Y132)),0) -> 46 | AA132: =IF(SUM($F132:N132)-$E132-SUM($S132:Z132)>0,MAX($AF132,SUM($F132:N132)-$E132-SUM($S132:Z132)),0) -> 0 | ... AD132: =IF(SUM($F132:Q132)-$E132-SUM($S132:AC132)>0,MAX($AF132,SUM($F132:Q132)-$E132-SUM($S132:AC132)),0) -> 41 | AE132: =SUM(S132:AD132) -> 2333.1584 | AF132: 0
A133: KIA250 | B133: ETIQUETA KIARO 250 MM PP INY. | C133: Envasados | D133: ud | E133: 8223.7843 | F133: 11314.95 | G133: 18930.893 | H133: 7960.5049 | I133: 9660.6614 | J133: 10988.255 | K133: 32608.846 | L133: 12736.583 | M133: 9202.2949 | N133: 3682.5 | O133: 6157 | P133: 9523.9038 | Q133: 14186.5 | R133: =SUM(F133:Q133) -> 146952.89 | S133: =IF(SUM($F133:F133)-$E133-0>0,MAX($AF133,SUM($F133:F133)-$E133-0),0) -> 3091.1655 | T133: =IF(SUM($F133:G133)-$E133-SUM($S133:S133)>0,MAX($AF133,SUM($F133:G133)-$E133-SUM($S133:S133)),0) -> 18930.893 | U133: =IF(SUM($F133:H133)-$E133-SUM($S133:T133)>0,MAX($AF133,SUM($F133:H133)-$E133-SUM($S133:T133)),0) -> 7960.5049 | V133: =IF(SUM($F133:I133)-$E133-SUM($S133:U133)>0,MAX($AF133,SUM($F133:I133)-$E133-SUM($S133:U133)),0) -> 9660.6614 | W133: =IF(SUM($F133:J133)-$E133-SUM($S133:V133)>0,MAX($AF133,SUM($F133:J133)-$E133-SUM($S133:V133)),0) -> 10988.255 | X133: =IF(SUM($F133:K133)-$E133-SUM($S133:W133)>0,MAX($AF133,SUM($F133:K133)-$E133-SUM($S133:W133)),0) -> 32608.846 | Y133: =IF(SUM($F133:L133)-$E133-SUM($S133:X133)>0,MAX($AF133,SUM($F133:L133)-$E133-SUM($S133:X133)),0) -> 12736.583 | Z133: =IF(SUM($F133:M133)-$E133-SUM($S133:Y133)>0,MAX($AF133,SUM($F133:M133)-$E133-SUM($S133:Y133)),0) -> 9202.2949 | AA133: =IF(SUM($F133:N133)-$E133-SUM($S133:Z133)>0,MAX($AF133,SUM($F133:N133)-$E133-SUM($S133:Z133)),0) -> 3682.5 | ... AD133: =IF(SUM($F133:Q133)-$E133-SUM($S133:AC133)>0,MAX($AF133,SUM($F133:Q133)-$E133-SUM($S133:AC133)),0) -> 14186.5 | AE133: =SUM(S133:AD133) -> 138729.11 | AF133: 0
A134: LAM1 | B134: LAMINA 480 MM G 600, BOLSAS 1 KG | C134: Envasados | D134: kg | E134: 724.81332 | F134: 76.427557 | G134: 247.74517 | H134: 41.241798 | I134: 12.25133 | J134: 327.47562 | K134: 200.98996 | L134: 41.710322 | M134: 105.04119 | N134: 1.3852273 | O134: 70.058333 | P134: 124.72983 | Q134: 205.64858 | R134: =SUM(F134:Q134) -> 1454.7049 | S134: =IF(SUM($F134:F134)-$E134-0>0,MAX($AF134,SUM($F134:F134)-$E134-0),0) -> 0 | T134: =IF(SUM($F134:G134)-$E134-SUM($S134:S134)>0,MAX($AF134,SUM($F134:G134)-$E134-SUM($S134:S134)),0) -> 0 | U134: =IF(SUM($F134:H134)-$E134-SUM($S134:T134)>0,MAX($AF134,SUM($F134:H134)-$E134-SUM($S134:T134)),0) -> 0 | V134: =IF(SUM($F134:I134)-$E134-SUM($S134:U134)>0,MAX($AF134,SUM($F134:I134)-$E134-SUM($S134:U134)),0) -> 0 | W134: =IF(SUM($F134:J134)-$E134-SUM($S134:V134)>0,MAX($AF134,SUM($F134:J134)-$E134-SUM($S134:V134)),0) -> 0 | X134: =IF(SUM($F134:K134)-$E134-SUM($S134:W134)>0,MAX($AF134,SUM($F134:K134)-$E134-SUM($S134:W134)),0) -> 181.31812 | Y134: =IF(SUM($F134:L134)-$E134-SUM($S134:X134)>0,MAX($AF134,SUM($F134:L134)-$E134-SUM($S134:X134)),0) -> 41.710322 | Z134: =IF(SUM($F134:M134)-$E134-SUM($S134:Y134)>0,MAX($AF134,SUM($F134:M134)-$E134-SUM($S134:Y134)),0) -> 105.04119 | AA134: =IF(SUM($F134:N134)-$E134-SUM($S134:Z134)>0,MAX($AF134,SUM($F134:N134)-$E134-SUM($S134:Z134)),0) -> 1.3852273 | ... AD134: =IF(SUM($F134:Q134)-$E134-SUM($S134:AC134)>0,MAX($AF134,SUM($F134:Q134)-$E134-SUM($S134:AC134)),0) -> 205.64858 | AE134: =SUM(S134:AD134) -> 729.89161 | AF134: 0 | AG134: Solo necesidades y stock al 31/12 de envasados; se ignora la fila de formulados.
A135: LAM2 | B135: LAMINA 640 MM, 5 KG | C135: Envasados | D135: kg | E135: 3609.5165 | F135: 557.26438 | G135: 485.71893 | H135: 223.88845 | I135: 471.00259 | J135: 377.12834 | K135: 750.693 | L135: 463.684 | M135: 393.347 | N135: 177.674 | O135: 193.917 | P135: 299.848 | Q135: 220.15 | R135: =SUM(F135:Q135) -> 4614.3157 | S135: =IF(SUM($F135:F135)-$E135-0>0,MAX($AF135,SUM($F135:F135)-$E135-0),0) -> 0 | T135: =IF(SUM($F135:G135)-$E135-SUM($S135:S135)>0,MAX($AF135,SUM($F135:G135)-$E135-SUM($S135:S135)),0) -> 0 | U135: =IF(SUM($F135:H135)-$E135-SUM($S135:T135)>0,MAX($AF135,SUM($F135:H135)-$E135-SUM($S135:T135)),0) -> 0 | V135: =IF(SUM($F135:I135)-$E135-SUM($S135:U135)>0,MAX($AF135,SUM($F135:I135)-$E135-SUM($S135:U135)),0) -> 0 | W135: =IF(SUM($F135:J135)-$E135-SUM($S135:V135)>0,MAX($AF135,SUM($F135:J135)-$E135-SUM($S135:V135)),0) -> 0 | X135: =IF(SUM($F135:K135)-$E135-SUM($S135:W135)>0,MAX($AF135,SUM($F135:K135)-$E135-SUM($S135:W135)),0) -> 0 | Y135: =IF(SUM($F135:L135)-$E135-SUM($S135:X135)>0,MAX($AF135,SUM($F135:L135)-$E135-SUM($S135:X135)),0) -> 0 | Z135: =IF(SUM($F135:M135)-$E135-SUM($S135:Y135)>0,MAX($AF135,SUM($F135:M135)-$E135-SUM($S135:Y135)),0) -> 113.21019 | AA135: =IF(SUM($F135:N135)-$E135-SUM($S135:Z135)>0,MAX($AF135,SUM($F135:N135)-$E135-SUM($S135:Z135)),0) -> 177.674 | ... AD135: =IF(SUM($F135:Q135)-$E135-SUM($S135:AC135)>0,MAX($AF135,SUM($F135:Q135)-$E135-SUM($S135:AC135)),0) -> 220.15 | AE135: =SUM(S135:AD135) -> 1004.7992 | AF135: 0
A136: LAM3 | B136: LAMINA 1000 MM G 600, BOLSAS 20 KG | C136: Envasados | D136: kg | E136: 2002.6294 | F136: 110.485 | G136: 77.535046 | H136: 114.285 | I136: 53.865 | J136: 92.53 | K136: 61.275 | L136: 4.56 | M136: 10.545 | N136: 1.045 | O136: 40.375 | P136: 85.88 | Q136: 3.895 | R136: =SUM(F136:Q136) -> 656.27505 | S136: =IF(SUM($F136:F136)-$E136-0>0,MAX($AF136,SUM($F136:F136)-$E136-0),0) -> 0 | T136: =IF(SUM($F136:G136)-$E136-SUM($S136:S136)>0,MAX($AF136,SUM($F136:G136)-$E136-SUM($S136:S136)),0) -> 0 | U136: =IF(SUM($F136:H136)-$E136-SUM($S136:T136)>0,MAX($AF136,SUM($F136:H136)-$E136-SUM($S136:T136)),0) -> 0 | V136: =IF(SUM($F136:I136)-$E136-SUM($S136:U136)>0,MAX($AF136,SUM($F136:I136)-$E136-SUM($S136:U136)),0) -> 0 | W136: =IF(SUM($F136:J136)-$E136-SUM($S136:V136)>0,MAX($AF136,SUM($F136:J136)-$E136-SUM($S136:V136)),0) -> 0 | X136: =IF(SUM($F136:K136)-$E136-SUM($S136:W136)>0,MAX($AF136,SUM($F136:K136)-$E136-SUM($S136:W136)),0) -> 0 | Y136: =IF(SUM($F136:L136)-$E136-SUM($S136:X136)>0,MAX($AF136,SUM($F136:L136)-$E136-SUM($S136:X136)),0) -> 0 | Z136: =IF(SUM($F136:M136)-$E136-SUM($S136:Y136)>0,MAX($AF136,SUM($F136:M136)-$E136-SUM($S136:Y136)),0) -> 0 | AA136: =IF(SUM($F136:N136)-$E136-SUM($S136:Z136)>0,MAX($AF136,SUM($F136:N136)-$E136-SUM($S136:Z136)),0) -> 0 | ... AD136: =IF(SUM($F136:Q136)-$E136-SUM($S136:AC136)>0,MAX($AF136,SUM($F136:Q136)-$E136-SUM($S136:AC136)),0) -> 0 | AE136: =SUM(S136:AD136) -> 0 | AF136: 0
A137: PAL | B137: PALETS | C137: Envasados | D137: ud | E137: 0 | F137: 380.69921 | G137: 480.26261 | H137: 748.80184 | I137: 560.53007 | J137: 902.58214 | K137: 984.67962 | L137: 614.78591 | M137: 299.74799 | N137: 192.37628 | O137: 302.5313 | P137: 438.72007 | Q137: 646.7409 | R137: =SUM(F137:Q137) -> 6552.4579 | S137: =IF(SUM($F137:F137)-$E137-0>0,MAX($AF137,SUM($F137:F137)-$E137-0),0) -> 380.69921 | T137: =IF(SUM($F137:G137)-$E137-SUM($S137:S137)>0,MAX($AF137,SUM($F137:G137)-$E137-SUM($S137:S137)),0) -> 480.26261 | U137: =IF(SUM($F137:H137)-$E137-SUM($S137:T137)>0,MAX($AF137,SUM($F137:H137)-$E137-SUM($S137:T137)),0) -> 748.80184 | V137: =IF(SUM($F137:I137)-$E137-SUM($S137:U137)>0,MAX($AF137,SUM($F137:I137)-$E137-SUM($S137:U137)),0) -> 560.53007 | W137: =IF(SUM($F137:J137)-$E137-SUM($S137:V137)>0,MAX($AF137,SUM($F137:J137)-$E137-SUM($S137:V137)),0) -> 902.58214 | X137: =IF(SUM($F137:K137)-$E137-SUM($S137:W137)>0,MAX($AF137,SUM($F137:K137)-$E137-SUM($S137:W137)),0) -> 984.67962 | Y137: =IF(SUM($F137:L137)-$E137-SUM($S137:X137)>0,MAX($AF137,SUM($F137:L137)-$E137-SUM($S137:X137)),0) -> 614.78591 | Z137: =IF(SUM($F137:M137)-$E137-SUM($S137:Y137)>0,MAX($AF137,SUM($F137:M137)-$E137-SUM($S137:Y137)),0) -> 299.74799 | AA137: =IF(SUM($F137:N137)-$E137-SUM($S137:Z137)>0,MAX($AF137,SUM($F137:N137)-$E137-SUM($S137:Z137)),0) -> 192.37628 | ... AD137: =IF(SUM($F137:Q137)-$E137-SUM($S137:AC137)>0,MAX($AF137,SUM($F137:Q137)-$E137-SUM($S137:AC137)),0) -> 646.7409 | AE137: =SUM(S137:AD137) -> 6552.4579 | AF137: 0
A138: RIB | B138: RIBBON 155X450 RESINA IN | C138: Envasados | D138: ud | E138: 0 | F138: 4.5924269 | G138: 9.9902243 | H138: 11.809633 | I138: 6.7506834 | J138: 28.835311 | K138: 14.803492 | L138: 14.810329 | M138: 5.0170703 | N138: 5.0749318 | O138: 5.1884545 | P138: 8.9679784 | Q138: 15.062392 | R138: =SUM(F138:Q138) -> 130.90293 | S138: =IF(SUM($F138:F138)-$E138-0>0,MAX($AF138,SUM($F138:F138)-$E138-0),0) -> 4.5924269 | T138: =IF(SUM($F138:G138)-$E138-SUM($S138:S138)>0,MAX($AF138,SUM($F138:G138)-$E138-SUM($S138:S138)),0) -> 9.9902243 | U138: =IF(SUM($F138:H138)-$E138-SUM($S138:T138)>0,MAX($AF138,SUM($F138:H138)-$E138-SUM($S138:T138)),0) -> 11.809633 | V138: =IF(SUM($F138:I138)-$E138-SUM($S138:U138)>0,MAX($AF138,SUM($F138:I138)-$E138-SUM($S138:U138)),0) -> 6.7506834 | W138: =IF(SUM($F138:J138)-$E138-SUM($S138:V138)>0,MAX($AF138,SUM($F138:J138)-$E138-SUM($S138:V138)),0) -> 28.835311 | X138: =IF(SUM($F138:K138)-$E138-SUM($S138:W138)>0,MAX($AF138,SUM($F138:K138)-$E138-SUM($S138:W138)),0) -> 14.803492 | Y138: =IF(SUM($F138:L138)-$E138-SUM($S138:X138)>0,MAX($AF138,SUM($F138:L138)-$E138-SUM($S138:X138)),0) -> 14.810329 | Z138: =IF(SUM($F138:M138)-$E138-SUM($S138:Y138)>0,MAX($AF138,SUM($F138:M138)-$E138-SUM($S138:Y138)),0) -> 5.0170703 | AA138: =IF(SUM($F138:N138)-$E138-SUM($S138:Z138)>0,MAX($AF138,SUM($F138:N138)-$E138-SUM($S138:Z138)),0) -> 5.0749318 | ... AD138: =IF(SUM($F138:Q138)-$E138-SUM($S138:AC138)>0,MAX($AF138,SUM($F138:Q138)-$E138-SUM($S138:AC138)),0) -> 15.062392 | AE138: =SUM(S138:AD138) -> 130.90293 | AF138: 0
A139: RIB2 | B139: RIBBON 160X300 OUT | C139: Envasados | D139: ud | E139: 0 | F139: 26.485764 | G139: 32.59038 | H139: 21.324112 | I139: 26.835054 | J139: 23.654392 | K139: 55.964671 | L139: 25.331324 | M139: 19.900258 | N139: 8.52649 | O139: 12.15622 | P139: 18.422745 | Q139: 21.838098 | R139: =SUM(F139:Q139) -> 293.02951 | S139: =IF(SUM($F139:F139)-$E139-0>0,MAX($AF139,SUM($F139:F139)-$E139-0),0) -> 26.485764 | T139: =IF(SUM($F139:G139)-$E139-SUM($S139:S139)>0,MAX($AF139,SUM($F139:G139)-$E139-SUM($S139:S139)),0) -> 32.59038 | U139: =IF(SUM($F139:H139)-$E139-SUM($S139:T139)>0,MAX($AF139,SUM($F139:H139)-$E139-SUM($S139:T139)),0) -> 21.324112 | V139: =IF(SUM($F139:I139)-$E139-SUM($S139:U139)>0,MAX($AF139,SUM($F139:I139)-$E139-SUM($S139:U139)),0) -> 26.835054 | W139: =IF(SUM($F139:J139)-$E139-SUM($S139:V139)>0,MAX($AF139,SUM($F139:J139)-$E139-SUM($S139:V139)),0) -> 23.654392 | X139: =IF(SUM($F139:K139)-$E139-SUM($S139:W139)>0,MAX($AF139,SUM($F139:K139)-$E139-SUM($S139:W139)),0) -> 55.964671 | Y139: =IF(SUM($F139:L139)-$E139-SUM($S139:X139)>0,MAX($AF139,SUM($F139:L139)-$E139-SUM($S139:X139)),0) -> 25.331324 | Z139: =IF(SUM($F139:M139)-$E139-SUM($S139:Y139)>0,MAX($AF139,SUM($F139:M139)-$E139-SUM($S139:Y139)),0) -> 19.900259 | AA139: =IF(SUM($F139:N139)-$E139-SUM($S139:Z139)>0,MAX($AF139,SUM($F139:N139)-$E139-SUM($S139:Z139)),0) -> 8.52649 | ... AD139: =IF(SUM($F139:Q139)-$E139-SUM($S139:AC139)>0,MAX($AF139,SUM($F139:Q139)-$E139-SUM($S139:AC139)),0) -> 21.838098 | AE139: =SUM(S139:AD139) -> 293.02951 | AF139: 0
A140: RPT | B140: ROLLOS PRECINTOS TRASPARENTES 990 M -72 mm | C140: Envasados | D140: ud | E140: 0 | F140: 34.088135 | G140: 44.273179 | H140: 56.656073 | I140: 33.311571 | J140: 89.686494 | K140: 91.27484 | L140: 52.251615 | M140: 26.597326 | N140: 15.205668 | O140: 19.275035 | P140: 35.623771 | Q140: 61.003273 | R140: =SUM(F140:Q140) -> 559.24698 | S140: =IF(SUM($F140:F140)-$E140-0>0,MAX($AF140,SUM($F140:F140)-$E140-0),0) -> 34.088135 | T140: =IF(SUM($F140:G140)-$E140-SUM($S140:S140)>0,MAX($AF140,SUM($F140:G140)-$E140-SUM($S140:S140)),0) -> 44.273179 | U140: =IF(SUM($F140:H140)-$E140-SUM($S140:T140)>0,MAX($AF140,SUM($F140:H140)-$E140-SUM($S140:T140)),0) -> 56.656073 | V140: =IF(SUM($F140:I140)-$E140-SUM($S140:U140)>0,MAX($AF140,SUM($F140:I140)-$E140-SUM($S140:U140)),0) -> 33.311571 | W140: =IF(SUM($F140:J140)-$E140-SUM($S140:V140)>0,MAX($AF140,SUM($F140:J140)-$E140-SUM($S140:V140)),0) -> 89.686494 | X140: =IF(SUM($F140:K140)-$E140-SUM($S140:W140)>0,MAX($AF140,SUM($F140:K140)-$E140-SUM($S140:W140)),0) -> 91.27484 | Y140: =IF(SUM($F140:L140)-$E140-SUM($S140:X140)>0,MAX($AF140,SUM($F140:L140)-$E140-SUM($S140:X140)),0) -> 52.251615 | Z140: =IF(SUM($F140:M140)-$E140-SUM($S140:Y140)>0,MAX($AF140,SUM($F140:M140)-$E140-SUM($S140:Y140)),0) -> 26.597326 | AA140: =IF(SUM($F140:N140)-$E140-SUM($S140:Z140)>0,MAX($AF140,SUM($F140:N140)-$E140-SUM($S140:Z140)),0) -> 15.205668 | ... AD140: =IF(SUM($F140:Q140)-$E140-SUM($S140:AC140)>0,MAX($AF140,SUM($F140:Q140)-$E140-SUM($S140:AC140)),0) -> 61.003273 | AE140: =SUM(S140:AD140) -> 559.24698 | AF140: 0
A141: SEP | B141: LAMINA SEPARADORA CARTÓN PARA PALET | C141: Envasados | D141: ud | E141: 0 | F141: 531.08369 | G141: 660.81765 | H141: 951.2516 | I141: 793.71845 | J141: 1066.5673 | K141: 1285.9285 | L141: 787.05688 | M141: 407.73894 | N141: 247.64047 | O141: 389.77178 | P141: 561.29576 | Q141: 785.23902 | R141: =SUM(F141:Q141) -> 8468.11 | S141: =IF(SUM($F141:F141)-$E141-0>0,MAX($AF141,SUM($F141:F141)-$E141-0),0) -> 531.08369 | T141: =IF(SUM($F141:G141)-$E141-SUM($S141:S141)>0,MAX($AF141,SUM($F141:G141)-$E141-SUM($S141:S141)),0) -> 660.81765 | U141: =IF(SUM($F141:H141)-$E141-SUM($S141:T141)>0,MAX($AF141,SUM($F141:H141)-$E141-SUM($S141:T141)),0) -> 951.2516 | V141: =IF(SUM($F141:I141)-$E141-SUM($S141:U141)>0,MAX($AF141,SUM($F141:I141)-$E141-SUM($S141:U141)),0) -> 793.71845 | W141: =IF(SUM($F141:J141)-$E141-SUM($S141:V141)>0,MAX($AF141,SUM($F141:J141)-$E141-SUM($S141:V141)),0) -> 1066.5673 | X141: =IF(SUM($F141:K141)-$E141-SUM($S141:W141)>0,MAX($AF141,SUM($F141:K141)-$E141-SUM($S141:W141)),0) -> 1285.9285 | Y141: =IF(SUM($F141:L141)-$E141-SUM($S141:X141)>0,MAX($AF141,SUM($F141:L141)-$E141-SUM($S141:X141)),0) -> 787.05688 | Z141: =IF(SUM($F141:M141)-$E141-SUM($S141:Y141)>0,MAX($AF141,SUM($F141:M141)-$E141-SUM($S141:Y141)),0) -> 407.73894 | AA141: =IF(SUM($F141:N141)-$E141-SUM($S141:Z141)>0,MAX($AF141,SUM($F141:N141)-$E141-SUM($S141:Z141)),0) -> 247.64047 | ... AD141: =IF(SUM($F141:Q141)-$E141-SUM($S141:AC141)>0,MAX($AF141,SUM($F141:Q141)-$E141-SUM($S141:AC141)),0) -> 785.23902 | AE141: =SUM(S141:AD141) -> 8468.11 | AF141: 0
A142: TPD40I | B142: TAPÓN INDUCCIÓN D40 VERDE | C142: Envasados | D142: ud | E142: 0 | F142: 7522.7672 | G142: 44944 | H142: 13591.767 | I142: 958 | J142: 32262 | K142: 18586 | L142: 13993 | M142: 16414 | N142: 98 | O142: 7752 | P142: 34335 | Q142: 3920 | R142: =SUM(F142:Q142) -> 194376.53 | S142: =IF(SUM($F142:F142)-$E142-0>0,MAX($AF142,SUM($F142:F142)-$E142-0),0) -> 7522.7672 | T142: =IF(SUM($F142:G142)-$E142-SUM($S142:S142)>0,MAX($AF142,SUM($F142:G142)-$E142-SUM($S142:S142)),0) -> 44944 | U142: =IF(SUM($F142:H142)-$E142-SUM($S142:T142)>0,MAX($AF142,SUM($F142:H142)-$E142-SUM($S142:T142)),0) -> 13591.767 | V142: =IF(SUM($F142:I142)-$E142-SUM($S142:U142)>0,MAX($AF142,SUM($F142:I142)-$E142-SUM($S142:U142)),0) -> 958 | W142: =IF(SUM($F142:J142)-$E142-SUM($S142:V142)>0,MAX($AF142,SUM($F142:J142)-$E142-SUM($S142:V142)),0) -> 32262 | X142: =IF(SUM($F142:K142)-$E142-SUM($S142:W142)>0,MAX($AF142,SUM($F142:K142)-$E142-SUM($S142:W142)),0) -> 18586 | Y142: =IF(SUM($F142:L142)-$E142-SUM($S142:X142)>0,MAX($AF142,SUM($F142:L142)-$E142-SUM($S142:X142)),0) -> 13993 | Z142: =IF(SUM($F142:M142)-$E142-SUM($S142:Y142)>0,MAX($AF142,SUM($F142:M142)-$E142-SUM($S142:Y142)),0) -> 16414 | AA142: =IF(SUM($F142:N142)-$E142-SUM($S142:Z142)>0,MAX($AF142,SUM($F142:N142)-$E142-SUM($S142:Z142)),0) -> 98 | ... AD142: =IF(SUM($F142:Q142)-$E142-SUM($S142:AC142)>0,MAX($AF142,SUM($F142:Q142)-$E142-SUM($S142:AC142)),0) -> 3920 | AE142: =SUM(S142:AD142) -> 194376.53 | AF142: 0
A143: TPD40IV | B143: TAPÓN INDUCCIÓN D40 VÁLVULA | C143: Envasados | D143: ud | E143: 0 | F143: 3880 | G143: 16145 | H143: 6811 | I143: 987 | J143: 6132 | K143: 13938 | L143: 3843 | M143: 2255 | N143: 2341 | O143: 3433 | P143: 11705 | Q143: 25290 | R143: =SUM(F143:Q143) -> 96760 | S143: =IF(SUM($F143:F143)-$E143-0>0,MAX($AF143,SUM($F143:F143)-$E143-0),0) -> 3880 | T143: =IF(SUM($F143:G143)-$E143-SUM($S143:S143)>0,MAX($AF143,SUM($F143:G143)-$E143-SUM($S143:S143)),0) -> 16145 | U143: =IF(SUM($F143:H143)-$E143-SUM($S143:T143)>0,MAX($AF143,SUM($F143:H143)-$E143-SUM($S143:T143)),0) -> 6811 | V143: =IF(SUM($F143:I143)-$E143-SUM($S143:U143)>0,MAX($AF143,SUM($F143:I143)-$E143-SUM($S143:U143)),0) -> 987 | W143: =IF(SUM($F143:J143)-$E143-SUM($S143:V143)>0,MAX($AF143,SUM($F143:J143)-$E143-SUM($S143:V143)),0) -> 6132 | X143: =IF(SUM($F143:K143)-$E143-SUM($S143:W143)>0,MAX($AF143,SUM($F143:K143)-$E143-SUM($S143:W143)),0) -> 13938 | Y143: =IF(SUM($F143:L143)-$E143-SUM($S143:X143)>0,MAX($AF143,SUM($F143:L143)-$E143-SUM($S143:X143)),0) -> 3843 | Z143: =IF(SUM($F143:M143)-$E143-SUM($S143:Y143)>0,MAX($AF143,SUM($F143:M143)-$E143-SUM($S143:Y143)),0) -> 2255 | AA143: =IF(SUM($F143:N143)-$E143-SUM($S143:Z143)>0,MAX($AF143,SUM($F143:N143)-$E143-SUM($S143:Z143)),0) -> 2341 | ... AD143: =IF(SUM($F143:Q143)-$E143-SUM($S143:AC143)>0,MAX($AF143,SUM($F143:Q143)-$E143-SUM($S143:AC143)),0) -> 25290 | AE143: =SUM(S143:AD143) -> 96760 | AF143: 0
A144: TPD61I | B144: TAPÓN D61 INDUCCIÓN, NEGRO | C144: Envasados | D144: ud | E144: 612.4869 | F144: 1884 | G144: 1557.3359 | H144: 2943 | I144: 4440 | J144: 2972 | K144: 3604 | L144: 4910 | M144: 1347 | N144: 842 | O144: 2517 | P144: 2453 | Q144: 1344 | R144: =SUM(F144:Q144) -> 30813.336 | S144: =IF(SUM($F144:F144)-$E144-0>0,MAX($AF144,SUM($F144:F144)-$E144-0),0) -> 1271.5131 | T144: =IF(SUM($F144:G144)-$E144-SUM($S144:S144)>0,MAX($AF144,SUM($F144:G144)-$E144-SUM($S144:S144)),0) -> 1557.3359 | U144: =IF(SUM($F144:H144)-$E144-SUM($S144:T144)>0,MAX($AF144,SUM($F144:H144)-$E144-SUM($S144:T144)),0) -> 2943 | V144: =IF(SUM($F144:I144)-$E144-SUM($S144:U144)>0,MAX($AF144,SUM($F144:I144)-$E144-SUM($S144:U144)),0) -> 4440 | W144: =IF(SUM($F144:J144)-$E144-SUM($S144:V144)>0,MAX($AF144,SUM($F144:J144)-$E144-SUM($S144:V144)),0) -> 2972 | X144: =IF(SUM($F144:K144)-$E144-SUM($S144:W144)>0,MAX($AF144,SUM($F144:K144)-$E144-SUM($S144:W144)),0) -> 3604 | Y144: =IF(SUM($F144:L144)-$E144-SUM($S144:X144)>0,MAX($AF144,SUM($F144:L144)-$E144-SUM($S144:X144)),0) -> 4910 | Z144: =IF(SUM($F144:M144)-$E144-SUM($S144:Y144)>0,MAX($AF144,SUM($F144:M144)-$E144-SUM($S144:Y144)),0) -> 1347 | AA144: =IF(SUM($F144:N144)-$E144-SUM($S144:Z144)>0,MAX($AF144,SUM($F144:N144)-$E144-SUM($S144:Z144)),0) -> 842 | ... AD144: =IF(SUM($F144:Q144)-$E144-SUM($S144:AC144)>0,MAX($AF144,SUM($F144:Q144)-$E144-SUM($S144:AC144)),0) -> 1344 | AE144: =SUM(S144:AD144) -> 30200.849 | AF144: 0
A145: TPD61IV | B145: TAPÓN INDUCCIÓN 61 VÁLVULA VERDE | C145: Envasados | D145: ud | E145: 8965.2702 | F145: 893 | G145: 1480.7834 | H145: 8138 | I145: 5737 | J145: 3090 | K145: 2360 | L145: 1533 | M145: 773 | N145: 904 | O145: 715 | P145: 813 | Q145: 2980 | R145: =SUM(F145:Q145) -> 29416.783 | S145: =IF(SUM($F145:F145)-$E145-0>0,MAX($AF145,SUM($F145:F145)-$E145-0),0) -> 0 | T145: =IF(SUM($F145:G145)-$E145-SUM($S145:S145)>0,MAX($AF145,SUM($F145:G145)-$E145-SUM($S145:S145)),0) -> 0 | U145: =IF(SUM($F145:H145)-$E145-SUM($S145:T145)>0,MAX($AF145,SUM($F145:H145)-$E145-SUM($S145:T145)),0) -> 1546.5132 | V145: =IF(SUM($F145:I145)-$E145-SUM($S145:U145)>0,MAX($AF145,SUM($F145:I145)-$E145-SUM($S145:U145)),0) -> 5737 | W145: =IF(SUM($F145:J145)-$E145-SUM($S145:V145)>0,MAX($AF145,SUM($F145:J145)-$E145-SUM($S145:V145)),0) -> 3090 | X145: =IF(SUM($F145:K145)-$E145-SUM($S145:W145)>0,MAX($AF145,SUM($F145:K145)-$E145-SUM($S145:W145)),0) -> 2360 | Y145: =IF(SUM($F145:L145)-$E145-SUM($S145:X145)>0,MAX($AF145,SUM($F145:L145)-$E145-SUM($S145:X145)),0) -> 1533 | Z145: =IF(SUM($F145:M145)-$E145-SUM($S145:Y145)>0,MAX($AF145,SUM($F145:M145)-$E145-SUM($S145:Y145)),0) -> 773 | AA145: =IF(SUM($F145:N145)-$E145-SUM($S145:Z145)>0,MAX($AF145,SUM($F145:N145)-$E145-SUM($S145:Z145)),0) -> 904 | ... AD145: =IF(SUM($F145:Q145)-$E145-SUM($S145:AC145)>0,MAX($AF145,SUM($F145:Q145)-$E145-SUM($S145:AC145)),0) -> 2980 | AE145: =SUM(S145:AD145) -> 20451.513 | AF145: 0
A146: TPD61VS | B146: TAPÓN D61, VÁLVULA SETA NEGRO | C146: Envasados | D146: ud | E146: 2528.9233 | F146: 524.01526 | G146: 547.35114 | H146: 633.01526 | I146: 851 | J146: 873 | K146: 1751 | L146: 575 | M146: 356 | N146: 512 | O146: 979 | P146: 1035 | Q146: 558 | R146: =SUM(F146:Q146) -> 9194.3817 | S146: =IF(SUM($F146:F146)-$E146-0>0,MAX($AF146,SUM($F146:F146)-$E146-0),0) -> 0 | T146: =IF(SUM($F146:G146)-$E146-SUM($S146:S146)>0,MAX($AF146,SUM($F146:G146)-$E146-SUM($S146:S146)),0) -> 0 | U146: =IF(SUM($F146:H146)-$E146-SUM($S146:T146)>0,MAX($AF146,SUM($F146:H146)-$E146-SUM($S146:T146)),0) -> 0 | V146: =IF(SUM($F146:I146)-$E146-SUM($S146:U146)>0,MAX($AF146,SUM($F146:I146)-$E146-SUM($S146:U146)),0) -> 26.458383 | W146: =IF(SUM($F146:J146)-$E146-SUM($S146:V146)>0,MAX($AF146,SUM($F146:J146)-$E146-SUM($S146:V146)),0) -> 873 | X146: =IF(SUM($F146:K146)-$E146-SUM($S146:W146)>0,MAX($AF146,SUM($F146:K146)-$E146-SUM($S146:W146)),0) -> 1751 | Y146: =IF(SUM($F146:L146)-$E146-SUM($S146:X146)>0,MAX($AF146,SUM($F146:L146)-$E146-SUM($S146:X146)),0) -> 575 | Z146: =IF(SUM($F146:M146)-$E146-SUM($S146:Y146)>0,MAX($AF146,SUM($F146:M146)-$E146-SUM($S146:Y146)),0) -> 356 | AA146: =IF(SUM($F146:N146)-$E146-SUM($S146:Z146)>0,MAX($AF146,SUM($F146:N146)-$E146-SUM($S146:Z146)),0) -> 512 | ... AD146: =IF(SUM($F146:Q146)-$E146-SUM($S146:AC146)>0,MAX($AF146,SUM($F146:Q146)-$E146-SUM($S146:AC146)),0) -> 558 | AE146: =SUM(S146:AD146) -> 6665.4584 | AF146: 0
... A149: TPD63VS | B149: TAPÓN D63 VALVULA SETA, BLANCO | C149: Envasados | D149: ud | E149: 0 | F149: 1917.2 | G149: 1715 | H149: 396.95992 | I149: 778 | J149: 1077 | K149: 859 | L149: 813 | M149: 1023 | N149: 230 | O149: 339 | P149: 420 | Q149: 1569 | R149: =SUM(F149:Q149) -> 11137.16 | S149: =IF(SUM($F149:F149)-$E149-0>0,MAX($AF149,SUM($F149:F149)-$E149-0),0) -> 1917.2 | T149: =IF(SUM($F149:G149)-$E149-SUM($S149:S149)>0,MAX($AF149,SUM($F149:G149)-$E149-SUM($S149:S149)),0) -> 1715 | U149: =IF(SUM($F149:H149)-$E149-SUM($S149:T149)>0,MAX($AF149,SUM($F149:H149)-$E149-SUM($S149:T149)),0) -> 396.95992 | V149: =IF(SUM($F149:I149)-$E149-SUM($S149:U149)>0,MAX($AF149,SUM($F149:I149)-$E149-SUM($S149:U149)),0) -> 778 | W149: =IF(SUM($F149:J149)-$E149-SUM($S149:V149)>0,MAX($AF149,SUM($F149:J149)-$E149-SUM($S149:V149)),0) -> 1077 | X149: =IF(SUM($F149:K149)-$E149-SUM($S149:W149)>0,MAX($AF149,SUM($F149:K149)-$E149-SUM($S149:W149)),0) -> 859 | Y149: =IF(SUM($F149:L149)-$E149-SUM($S149:X149)>0,MAX($AF149,SUM($F149:L149)-$E149-SUM($S149:X149)),0) -> 813 | Z149: =IF(SUM($F149:M149)-$E149-SUM($S149:Y149)>0,MAX($AF149,SUM($F149:M149)-$E149-SUM($S149:Y149)),0) -> 1023 | AA149: =IF(SUM($F149:N149)-$E149-SUM($S149:Z149)>0,MAX($AF149,SUM($F149:N149)-$E149-SUM($S149:Z149)),0) -> 230 | ... AD149: =IF(SUM($F149:Q149)-$E149-SUM($S149:AC149)>0,MAX($AF149,SUM($F149:Q149)-$E149-SUM($S149:AC149)),0) -> 1569 | AE149: =SUM(S149:AD149) -> 11137.16 | AF149: 0

Sheet Precios
A2: Precios de compra aplicados en 2027
B4: Incremento previsto | C4: =Supuestos!B5 -> 0.1
A6: Precio manual (amarillo): base antes del 10 %. Los artículos sin precio quedan pendientes.
A7: Artículo | B7: Descripción | C7: Grupo | D7: Código histórico | E7: Mes base | F7: Precio base | G7: Precio manual | H7: Precio 2027 | I7: Estado | J7: Fuente
A8: ACE | B8: ACETAMIDA | C8: Formulados | D8: ACE | E8: 07/2026 | F8: 37.2 | H8: =IF(ISNUMBER(G8),G8*(1+$C$4),IF(ISNUMBER(F8),F8*(1+$C$4),"")) -> 40.92 | I8: =IF(Unidades!AE8=0,"SIN COMPRA",IF(ISNUMBER(H8),"VALORADO","FALTA PRECIO")) -> VALORADO | J8: Presupuesto anterior
A9: ACIT | B9: ACIDO CÍTRICO MONOHIDRATADO | C9: Formulados | D9: ACIT | E9: 06/2026 | F9: 1.3 | H9: =IF(ISNUMBER(G9),G9*(1+$C$4),IF(ISNUMBER(F9),F9*(1+$C$4),"")) -> 1.43 | I9: =IF(Unidades!AE9=0,"SIN COMPRA",IF(ISNUMBER(H9),"VALORADO","FALTA PRECIO")) -> VALORADO | J9: Presupuesto anterior
A10: ADI | B10: ACIDO ADIPICO | C10: Formulados | D10: ADI | E10: 05/2026 | F10: 2.46 | H10: =IF(ISNUMBER(G10),G10*(1+$C$4),IF(ISNUMBER(F10),F10*(1+$C$4),"")) -> 2.706 | I10: =IF(Unidades!AE10=0,"SIN COMPRA",IF(ISNUMBER(H10),"VALORADO","FALTA PRECIO")) -> VALORADO | J10: Presupuesto anterior
A11: AMARILLO | B11: COLOR AMARILLO | C11: Formulados | D11: AMARILLO | H11: =IF(ISNUMBER(G11),G11*(1+$C$4),IF(ISNUMBER(F11),F11*(1+$C$4),"")) | I11: =IF(Unidades!AE11=0,"SIN COMPRA",IF(ISNUMBER(H11),"VALORADO","FALTA PRECIO")) -> SIN COMPRA | J11: Sin precio histórico
A12: AMO | B12: AMONÍACO | C12: Formulados | D12: AMO | E12: 06/2026 | F12: 0.38 | H12: =IF(ISNUMBER(G12),G12*(1+$C$4),IF(ISNUMBER(F12),F12*(1+$C$4),"")) -> 0.418 | I12: =IF(Unidades!AE12=0,"SIN COMPRA",IF(ISNUMBER(H12),"VALORADO","FALTA PRECIO")) -> VALORADO | J12: Presupuesto anterior
A13: ANTI | B13: ANTIESPUMANTE ANTISCHIUMA GEN | C13: Formulados | D13: ANTI | E13: 03/2024 | F13: 7.75 | H13: =IF(ISNUMBER(G13),G13*(1+$C$4),IF(ISNUMBER(F13),F13*(1+$C$4),"")) -> 8.525 | I13: =IF(Unidades!AE13=0,"SIN COMPRA",IF(ISNUMBER(H13),"VALORADO","FALTA PRECIO")) -> SIN COMPRA | J13: Presupuesto anterior
A14: AR | B14: FINDET AR-52 | C14: Formulados | D14: AR | E14: 03/2026 | F14: 2.9 | H14: =IF(ISNUMBER(G14),G14*(1+$C$4),IF(ISNUMBER(F14),F14*(1+$C$4),"")) -> 3.19 | I14: =IF(Unidades!AE14=0,"SIN COMPRA",IF(ISNUMBER(H14),"VALORADO","FALTA PRECIO")) -> VALORADO | J14: Último mes de histórico
A15: ATC | B15: AATC | C15: Formulados | D15: ATC | E15: 05/2026 | F15: 31.9 | H15: =IF(ISNUMBER(G15),G15*(1+$C$4),IF(ISNUMBER(F15),F15*(1+$C$4),"")) -> 35.09 | I15: =IF(Unidades!AE15=0,"SIN COMPRA",IF(ISNUMBER(H15),"VALORADO","FALTA PRECIO")) -> VALORADO | J15: Presupuesto anterior
A16: AV24 | B16: AV24 | C16: Formulados | D16: AV24 | E16: 01/2026 | F16: 1.55 | H16: =IF(ISNUMBER(G16),G16*(1+$C$4),IF(ISNUMBER(F16),F16*(1+$C$4),"")) -> 1.705 | I16: =IF(Unidades!AE16=0,"SIN COMPRA",IF(ISNUMBER(H16),"VALORADO","FALTA PRECIO")) -> VALORADO | J16: Presupuesto anterior
A17: BET | B17: BETAÍNA DE REMOLACHA | C17: Formulados | D17: BET | E17: 07/2026 | F17: 5.15 | H17: =IF(ISNUMBER(G17),G17*(1+$C$4),IF(ISNUMBER(F17),F17*(1+$C$4),"")) -> 5.665 | I17: =IF(Unidades!AE17=0,"SIN COMPRA",IF(ISNUMBER(H17),"VALORADO","FALTA PRECIO")) -> VALORADO | J17: Presupuesto anterior
A18: BICAR | B18: BICARBONATO SÓDICO ALIM. | C18: Formulados | D18: BICAR | E18: 06/2025 | F18: 0.47 | H18: =IF(ISNUMBER(G18),G18*(1+$C$4),IF(ISNUMBER(F18),F18*(1+$C$4),"")) -> 0.517 | I18: =IF(Unidades!AE18=0,"SIN COMPRA",IF(ISNUMBER(H18),"VALORADO","FALTA PRECIO")) -> SIN COMPRA | J18: Presupuesto anterior
A19: BOCAL | B19: BRETAX-CL | C19: Formulados | D19: BOCAL | E19: 06/2026 | F19: 0.4 | H19: =IF(ISNUMBER(G19),G19*(1+$C$4),IF(ISNUMBER(F19),F19*(1+$C$4),"")) -> 0.44 | I19: =IF(Unidades!AE19=0,"SIN COMPRA",IF(ISNUMBER(H19),"VALORADO","FALTA PRECIO")) -> SIN COMPRA | J19: Presupuesto anterior
A20: BOR | B20: ACIDO BORICO | C20: Formulados | D20: BOR | E20: 04/2025 | F20: 1.07 | H20: =IF(ISNUMBER(G20),G20*(1+$C$4),IF(ISNUMBER(F20),F20*(1+$C$4),"")) -> 1.177 | I20: =IF(Unidades!AE20=0,"SIN COMPRA",IF(ISNUMBER(H20),"VALORADO","FALTA PRECIO")) -> VALORADO | J20: Presupuesto anterior
A21: BORL | B21: BORO LÍQUIDO(BORO ETANOLAMINA) | C21: Formulados | D21: BORL | E21: 03/2026 | F21: 1.0445 | H21: =IF(ISNUMBER(G21),G21*(1+$C$4),IF(ISNUMBER(F21),F21*(1+$C$4),"")) -> 1.14895 | I21: =IF(Unidades!AE21=0,"SIN COMPRA",IF(ISNUMBER(H21),"VALORADO","FALTA PRECIO")) -> VALORADO | J21: Presupuesto anterior
A22: BP | B22: BORAX PENTA | C22: Formulados | D22: BP | H22: =IF(ISNUMBER(G22),G22*(1+$C$4),IF(ISNUMBER(F22),F22*(1+$C$4),"")) | I22: =IF(Unidades!AE22=0,"SIN COMPRA",IF(ISNUMBER(H22),"VALORADO","FALTA PRECIO")) -> SIN COMPRA | J22: Sin precio histórico
A23: CAMN | B23: CARBONATO DE MANGANESO | C23: Formulados | D23: CAMN | E23: 04/2024 | F23: 1.2 | H23: =IF(ISNUMBER(G23),G23*(1+$C$4),IF(ISNUMBER(F23),F23*(1+$C$4),"")) -> 1.32 | I23: =IF(Unidades!AE23=0,"SIN COMPRA",IF(ISNUMBER(H23),"VALORADO","FALTA PRECIO")) -> VALORADO | J23: Presupuesto anterior
A24: CCA2 | B24: CALPREC PA | C24: Formulados | D24: CCA2 | E24: 04/2026 | F24: 0.60272063 | H24: =IF(ISNUMBER(G24),G24*(1+$C$4),IF(ISNUMBER(F24),F24*(1+$C$4),"")) -> 0.6629927 | I24: =IF(Unidades!AE24=0,"SIN COMPRA",IF(ISNUMBER(H24),"VALORADO","FALTA PRECIO")) -> VALORADO | J24: Presupuesto anterior
A25: CCB | B25: CARBONATO CÁLCICO LR-A | C25: Formulados | D25: CCB | E25: 07/2026 | F25: 0.124 | H25: =IF(ISNUMBER(G25),G25*(1+$C$4),IF(ISNUMBER(F25),F25*(1+$C$4),"")) -> 0.1364 | I25: =IF(Unidades!AE25=0,"SIN COMPRA",IF(ISNUMBER(H25),"VALORADO","FALTA PRECIO")) -> VALORADO | J25: Presupuesto anterior
A26: CCB2 | B26: CARBONATO CÁLCICO 2 MC | C26: Formulados | D26: CCB2 | E26: 06/2026 | F26: 0.128 | H26: =IF(ISNUMBER(G26),G26*(1+$C$4),IF(ISNUMBER(F26),F26*(1+$C$4),"")) -> 0.1408 | I26: =IF(Unidades!AE26=0,"SIN COMPRA",IF(ISNUMBER(H26),"VALORADO","FALTA PRECIO")) -> VALORADO | J26: Presupuesto anterior
A27: CLCAL | B27: CLORURO CÁLCICO LIQ. 36% | C27: Formulados | D27: CLCAL | E27: 04/2026 | F27: 0.25593166 | H27: =IF(ISNUMBER(G27),G27*(1+$C$4),IF(ISNUMBER(F27),F27*(1+$C$4),"")) -> 0.28152482 | I27: =IF(Unidades!AE27=0,"SIN COMPRA",IF(ISNUMBER(H27),"VALORADO","FALTA PRECIO")) -> VALORADO | J27: Último mes de histórico
A28: CLORPO | B28: CLORURO POTASICO | C28: Formulados | D28: CLORPO | E28: 03/2026 | F28: 0.52 | H28: =IF(ISNUMBER(G28),G28*(1+$C$4),IF(ISNUMBER(F28),F28*(1+$C$4),"")) -> 0.572 | I28: =IF(Unidades!AE28=0,"SIN COMPRA",IF(ISNUMBER(H28),"VALORADO","FALTA PRECIO")) -> VALORADO | J28: Presupuesto anterior
A29: CMG | B29: CARBONATO DE MAGNESIO - MAGNESITA | C29: Formulados | D29: CMG | F29: 0.26 | H29: =IF(ISNUMBER(G29),G29*(1+$C$4),IF(ISNUMBER(F29),F29*(1+$C$4),"")) -> 0.286 | I29: =IF(Unidades!AE29=0,"SIN COMPRA",IF(ISNUMBER(H29),"VALORADO","FALTA PRECIO")) -> VALORADO | J29: Precio comunicado ayer
A30: CMN | B30: CLORURO DE MANGANESO | C30: Formulados | D30: CMN | E30: 06/2026 | F30: 5.95 | H30: =IF(ISNUMBER(G30),G30*(1+$C$4),IF(ISNUMBER(F30),F30*(1+$C$4),"")) -> 6.545 | I30: =IF(Unidades!AE30=0,"SIN COMPRA",IF(ISNUMBER(H30),"VALORADO","FALTA PRECIO")) -> VALORADO | J30: Presupuesto anterior
A31: CZN | B31: CLORURO DE ZINC | C31: Formulados | D31: CZN | E31: 06/2026 | F31: 2.65 | H31: =IF(ISNUMBER(G31),G31*(1+$C$4),IF(ISNUMBER(F31),F31*(1+$C$4),"")) -> 2.915 | I31: =IF(Unidades!AE31=0,"SIN COMPRA",IF(ISNUMBER(H31),"VALORADO","FALTA PRECIO")) -> VALORADO | J31: Presupuesto anterior
A32: D55 | B32: DADMEL 55 | C32: Formulados | D32: D55 | E32: 05/2026 | F32: 0.57 | H32: =IF(ISNUMBER(G32),G32*(1+$C$4),IF(ISNUMBER(F32),F32*(1+$C$4),"")) -> 0.627 | I32: =IF(Unidades!AE32=0,"SIN COMPRA",IF(ISNUMBER(H32),"VALORADO","FALTA PRECIO")) -> VALORADO | J32: Presupuesto anterior
A33: DECL | B33: DESHCOFIX -108-(LÍQUIDO) | C33: Formulados | D33: DECL | E33: 07/2026 | F33: 0.895 | H33: =IF(ISNUMBER(G33),G33*(1+$C$4),IF(ISNUMBER(F33),F33*(1+$C$4),"")) -> 0.9845 | I33: =IF(Unidades!AE33=0,"SIN COMPRA",IF(ISNUMBER(H33),"VALORADO","FALTA PRECIO")) -> VALORADO | J33: Presupuesto anterior
A34: EBRO | B34: EBROSIL | C34: Formulados | D34: EBRO | E34: 02/2026 | F34: 1.75 | H34: =IF(ISNUMBER(G34),G34*(1+$C$4),IF(ISNUMBER(F34),F34*(1+$C$4),"")) -> 1.925 | I34: =IF(Unidades!AE34=0,"SIN COMPRA",IF(ISNUMBER(H34),"VALORADO","FALTA PRECIO")) -> VALORADO | J34: Presupuesto anterior
A35: EDT | B35: EDTA | C35: Formulados | D35: EDT | E35: 05/2026 | F35: 1.1 | H35: =IF(ISNUMBER(G35),G35*(1+$C$4),IF(ISNUMBER(F35),F35*(1+$C$4),"")) -> 1.21 | I35: =IF(Unidades!AE35=0,"SIN COMPRA",IF(ISNUMBER(H35),"VALORADO","FALTA PRECIO")) -> VALORADO | J35: Presupuesto anterior
A36: EDTACU | B36: DISSOLVINE - EDTA- CU-15 | C36: Formulados | D36: EDTACU | E36: 04/2026 | F36: 3.95 | H36: =IF(ISNUMBER(G36),G36*(1+$C$4),IF(ISNUMBER(F36),F36*(1+$C$4),"")) -> 4.345 | I36: =IF(Unidades!AE36=0,"SIN COMPRA",IF(ISNUMBER(H36),"VALORADO","FALTA PRECIO")) -> VALORADO | J36: Presupuesto anterior
A37: EDTAFE | B37: DISSOLVINE - EDTA-FE 13 | C37: Formulados | D37: EDTAFE | H37: =IF(ISNUMBER(G37),G37*(1+$C$4),IF(ISNUMBER(F37),F37*(1+$C$4),"")) | I37: =IF(Unidades!AE37=0,"SIN COMPRA",IF(ISNUMBER(H37),"VALORADO","FALTA PRECIO")) -> SIN COMPRA | J37: Sin precio histórico
A38: EDTAMN | B38: DISSOLVINE - EDTA MN 13 | C38: Formulados | D38: EDTAMN | H38: =IF(ISNUMBER(G38),G38*(1+$C$4),IF(ISNUMBER(F38),F38*(1+$C$4),"")) | I38: =IF(Unidades!AE38=0,"SIN COMPRA",IF(ISNUMBER(H38),"VALORADO","FALTA PRECIO")) -> SIN COMPRA | J38: Sin precio histórico
A39: EDTAZN | B39: DISSOLVINE - EDTA ZN 15 | C39: Formulados | D39: EDTAZN | E39: 03/2026 | F39: 5.35 | H39: =IF(ISNUMBER(G39),G39*(1+$C$4),IF(ISNUMBER(F39),F39*(1+$C$4),"")) -> 5.885 | I39: =IF(Unidades!AE39=0,"SIN COMPRA",IF(ISNUMBER(H39),"VALORADO","FALTA PRECIO")) -> VALORADO | J39: Presupuesto anterior
A40: FMA | B40: FOSFATO MONOAMONICO | C40: Formulados | D40: FMA | E40: 06/2026 | F40: 1.25 | H40: =IF(ISNUMBER(G40),G40*(1+$C$4),IF(ISNUMBER(F40),F40*(1+$C$4),"")) -> 1.375 | I40: =IF(Unidades!AE40=0,"SIN COMPRA",IF(ISNUMBER(H40),"VALORADO","FALTA PRECIO")) -> VALORADO | J40: Presupuesto anterior
A41: FMP | B41: FOSFATO MONOPOTASICO | C41: Formulados | D41: FMP | E41: 07/2026 | F41: 1.78 | H41: =IF(ISNUMBER(G41),G41*(1+$C$4),IF(ISNUMBER(F41),F41*(1+$C$4),"")) -> 1.958 | I41: =IF(Unidades!AE41=0,"SIN COMPRA",IF(ISNUMBER(H41),"VALORADO","FALTA PRECIO")) -> VALORADO | J41: Presupuesto anterior
A42: FOCA | B42: FORMIATO CÁLCICO | C42: Formulados | D42: FOCA | E42: 12/2025 | F42: 0.695 | H42: =IF(ISNUMBER(G42),G42*(1+$C$4),IF(ISNUMBER(F42),F42*(1+$C$4),"")) -> 0.7645 | I42: =IF(Unidades!AE42=0,"SIN COMPRA",IF(ISNUMBER(H42),"VALORADO","FALTA PRECIO")) -> VALORADO | J42: Presupuesto anterior
A43: FOF | B43: ACIDO FOSFOROSO | C43: Formulados | D43: FOF | E43: 02/2026 | F43: 3.24 | H43: =IF(ISNUMBER(G43),G43*(1+$C$4),IF(ISNUMBER(F43),F43*(1+$C$4),"")) -> 3.564 | I43: =IF(Unidades!AE43=0,"SIN COMPRA",IF(ISNUMBER(H43),"VALORADO","FALTA PRECIO")) -> VALORADO | J43: Último mes de histórico
A44: FOI | B44: ACIDO FOSFORICO | C44: Formulados | D44: FOI | E44: 07/2026 | F44: 1.51 | H44: =IF(ISNUMBER(G44),G44*(1+$C$4),IF(ISNUMBER(F44),F44*(1+$C$4),"")) -> 1.661 | I44: =IF(Unidades!AE44=0,"SIN COMPRA",IF(ISNUMBER(H44),"VALORADO","FALTA PRECIO")) -> VALORADO | J44: Presupuesto anterior
A45: FOP | B45: FORMIATO POTÁSICO LÍQUIDO 75% | C45: Formulados | D45: FOP | E45: 07/2026 | F45: 1.0617391 | H45: =IF(ISNUMBER(G45),G45*(1+$C$4),IF(ISNUMBER(F45),F45*(1+$C$4),"")) -> 1.167913 | I45: =IF(Unidades!AE45=0,"SIN COMPRA",IF(ISNUMBER(H45),"VALORADO","FALTA PRECIO")) -> VALORADO | J45: Presupuesto anterior
A46: FORTE | B46: FORTEHUM | C46: Formulados | D46: FORTE | E46: 02/2026 | F46: 2.164 | H46: =IF(ISNUMBER(G46),G46*(1+$C$4),IF(ISNUMBER(F46),F46*(1+$C$4),"")) -> 2.3804 | I46: =IF(Unidades!AE46=0,"SIN COMPRA",IF(ISNUMBER(H46),"VALORADO","FALTA PRECIO")) -> VALORADO | J46: Presupuesto anterior
A47: GLBE | B47: GLICINA BETAINA | C47: Formulados | D47: GLBE | E47: 07/2026 | F47: 3.33 | H47: =IF(ISNUMBER(G47),G47*(1+$C$4),IF(ISNUMBER(F47),F47*(1+$C$4),"")) -> 3.663 | I47: =IF(Unidades!AE47=0,"SIN COMPRA",IF(ISNUMBER(H47),"VALORADO","FALTA PRECIO")) -> VALORADO | J47: Presupuesto anterior
A48: GLI | B48: GLICINA | C48: Formulados | D48: GLI | E48: 07/2026 | F48: 1.612973 | H48: =IF(ISNUMBER(G48),G48*(1+$C$4),IF(ISNUMBER(F48),F48*(1+$C$4),"")) -> 1.7742703 | I48: =IF(Unidades!AE48=0,"SIN COMPRA",IF(ISNUMBER(H48),"VALORADO","FALTA PRECIO")) -> VALORADO | J48: Presupuesto anterior
A49: GLINA | B49: GLICERINA USP | C49: Formulados | D49: GLINA | E49: 03/2026 | F49: 1.72 | H49: =IF(ISNUMBER(G49),G49*(1+$C$4),IF(ISNUMBER(F49),F49*(1+$C$4),"")) -> 1.892 | I49: =IF(Unidades!AE49=0,"SIN COMPRA",IF(ISNUMBER(H49),"VALORADO","FALTA PRECIO")) -> VALORADO | J49: Presupuesto anterior
A50: GLUCONIC | B50: ACIDO GLUCONICO | C50: Formulados | D50: GLUCONIC | E50: 05/2026 | F50: 1.15 | H50: =IF(ISNUMBER(G50),G50*(1+$C$4),IF(ISNUMBER(F50),F50*(1+$C$4),"")) -> 1.265 | I50: =IF(Unidades!AE50=0,"SIN COMPRA",IF(ISNUMBER(H50),"VALORADO","FALTA PRECIO")) -> VALORADO | J50: Presupuesto anterior
... A53: HCA | B53: HIDROXIDO DE CAL | C53: Formulados | D53: HCA | E53: 07/2026 | F53: 0.165 | H53: =IF(ISNUMBER(G53),G53*(1+$C$4),IF(ISNUMBER(F53),F53*(1+$C$4),"")) -> 0.1815 | I53: =IF(Unidades!AE53=0,"SIN COMPRA",IF(ISNUMBER(H53),"VALORADO","FALTA PRECIO")) -> VALORADO | J53: Presupuesto anterior
A54: HGA-FE | B54: HEPTAGLUCONATO DE HIERRO | C54: Formulados | D54: HGA-FE | F54: 3.69 | H54: =IF(ISNUMBER(G54),G54*(1+$C$4),IF(ISNUMBER(F54),F54*(1+$C$4),"")) -> 4.059 | I54: =IF(Unidades!AE54=0,"SIN COMPRA",IF(ISNUMBER(H54),"VALORADO","FALTA PRECIO")) -> VALORADO | J54: Precio comunicado ayer
A55: HGA-FEL | B55: HEPTAGLUCONATO DE HIERRO LÍQUIDO | C55: Formulados | D55: HGA-FEL | E55: 05/2026 | F55: 1.15 | H55: =IF(ISNUMBER(G55),G55*(1+$C$4),IF(ISNUMBER(F55),F55*(1+$C$4),"")) -> 1.265 | I55: =IF(Unidades!AE55=0,"SIN COMPRA",IF(ISNUMBER(H55),"VALORADO","FALTA PRECIO")) -> VALORADO | J55: Presupuesto anterior
A56: HGA-MGL | B56: HEPTAGLUCONATO DE MAGNESIO LÍQUIDO | C56: Formulados | D56: HGA-MGL | F56: 1.43 | H56: =IF(ISNUMBER(G56),G56*(1+$C$4),IF(ISNUMBER(F56),F56*(1+$C$4),"")) -> 1.573 | I56: =IF(Unidades!AE56=0,"SIN COMPRA",IF(ISNUMBER(H56),"VALORADO","FALTA PRECIO")) -> VALORADO | J56: Precio comunicado ayer
A57: HPO | B57: HIDROXIDO POTASICO | C57: Formulados | D57: HPO | E57: 07/2026 | F57: 1.68 | H57: =IF(ISNUMBER(G57),G57*(1+$C$4),IF(ISNUMBER(F57),F57*(1+$C$4),"")) -> 1.848 | I57: =IF(Unidades!AE57=0,"SIN COMPRA",IF(ISNUMBER(H57),"VALORADO","FALTA PRECIO")) -> VALORADO | J57: Presupuesto anterior
A58: HPOL | B58: HIDROXIDO POTASICO LIQUIDO | C58: Formulados | D58: HPOL | E58: 07/2026 | F58: 0.41532419 | H58: =IF(ISNUMBER(G58),G58*(1+$C$4),IF(ISNUMBER(F58),F58*(1+$C$4),"")) -> 0.45685661 | I58: =IF(Unidades!AE58=0,"SIN COMPRA",IF(ISNUMBER(H58),"VALORADO","FALTA PRECIO")) -> VALORADO | J58: Presupuesto anterior
A59: JB | B59: JABÓN POTÁSICO | C59: Formulados | D59: JB | E59: 10/2025 | F59: 1.26 | H59: =IF(ISNUMBER(G59),G59*(1+$C$4),IF(ISNUMBER(F59),F59*(1+$C$4),"")) -> 1.386 | I59: =IF(Unidades!AE59=0,"SIN COMPRA",IF(ISNUMBER(H59),"VALORADO","FALTA PRECIO")) -> VALORADO | J59: Presupuesto anterior
A60: KF78 | B60: BIOPOL KF78 | C60: Formulados | D60: KF78 | E60: 07/2026 | F60: 4.88 | H60: =IF(ISNUMBER(G60),G60*(1+$C$4),IF(ISNUMBER(F60),F60*(1+$C$4),"")) -> 5.368 | I60: =IF(Unidades!AE60=0,"SIN COMPRA",IF(ISNUMBER(H60),"VALORADO","FALTA PRECIO")) -> VALORADO | J60: Presupuesto anterior
A61: KIN | B61: kinetina | C61: Formulados | D61: KIN | E61: 05/2026 | F61: 145 | H61: =IF(ISNUMBER(G61),G61*(1+$C$4),IF(ISNUMBER(F61),F61*(1+$C$4),"")) -> 159.5 | I61: =IF(Unidades!AE61=0,"SIN COMPRA",IF(ISNUMBER(H61),"VALORADO","FALTA PRECIO")) -> VALORADO | J61: Presupuesto anterior
A62: LIGNOAM | B62: LIGNOSULFONATO AMÓNICO LÍQUIDO | C62: Formulados | D62: LIGNOAM | E62: 06/2026 | F62: 0.735 | H62: =IF(ISNUMBER(G62),G62*(1+$C$4),IF(ISNUMBER(F62),F62*(1+$C$4),"")) -> 0.8085 | I62: =IF(Unidades!AE62=0,"SIN COMPRA",IF(ISNUMBER(H62),"VALORADO","FALTA PRECIO")) -> VALORADO | J62: Presupuesto anterior
A63: MAL | B63: ACIDO MALICO | C63: Formulados | D63: MAL | E63: 07/2026 | F63: 2.2835791 | H63: =IF(ISNUMBER(G63),G63*(1+$C$4),IF(ISNUMBER(F63),F63*(1+$C$4),"")) -> 2.511937 | I63: =IF(Unidades!AE63=0,"SIN COMPRA",IF(ISNUMBER(H63),"VALORADO","FALTA PRECIO")) -> VALORADO | J63: Presupuesto anterior
A64: MAN | B64: MANITOL | C64: Formulados | D64: MAN | E64: 05/2025 | F64: 6.4 | H64: =IF(ISNUMBER(G64),G64*(1+$C$4),IF(ISNUMBER(F64),F64*(1+$C$4),"")) -> 7.04 | I64: =IF(Unidades!AE64=0,"SIN COMPRA",IF(ISNUMBER(H64),"VALORADO","FALTA PRECIO")) -> VALORADO | J64: Presupuesto anterior
A65: MEA | B65: MONOETANOLAMINA | C65: Formulados | D65: MEA | E65: 06/2026 | F65: 2.32 | H65: =IF(ISNUMBER(G65),G65*(1+$C$4),IF(ISNUMBER(F65),F65*(1+$C$4),"")) -> 2.552 | I65: =IF(Unidades!AE65=0,"SIN COMPRA",IF(ISNUMBER(H65),"VALORADO","FALTA PRECIO")) -> VALORADO | J65: Presupuesto anterior
A66: MGO | B66: OXIDO DE MAGNESIO | C66: Formulados | D66: MGO | E66: 02/2026 | F66: 1.73 | H66: =IF(ISNUMBER(G66),G66*(1+$C$4),IF(ISNUMBER(F66),F66*(1+$C$4),"")) -> 1.903 | I66: =IF(Unidades!AE66=0,"SIN COMPRA",IF(ISNUMBER(H66),"VALORADO","FALTA PRECIO")) -> VALORADO | J66: Presupuesto anterior
A67: MOSO | B67: MOLIBDATO SODICO | C67: Formulados | D67: MOSO | E67: 07/2026 | F67: 28.5 | H67: =IF(ISNUMBER(G67),G67*(1+$C$4),IF(ISNUMBER(F67),F67*(1+$C$4),"")) -> 31.35 | I67: =IF(Unidades!AE67=0,"SIN COMPRA",IF(ISNUMBER(H67),"VALORADO","FALTA PRECIO")) -> VALORADO | J67: Presupuesto anterior
A68: NAM | B68: NITRATO AMONICO | C68: Formulados | D68: NAM | E68: 01/2025 | F68: 0.53 | H68: =IF(ISNUMBER(G68),G68*(1+$C$4),IF(ISNUMBER(F68),F68*(1+$C$4),"")) -> 0.583 | I68: =IF(Unidades!AE68=0,"SIN COMPRA",IF(ISNUMBER(H68),"VALORADO","FALTA PRECIO")) -> VALORADO | J68: Presupuesto anterior
... A149: TPD63VS | B149: TAPÓN D63 VALVULA SETA, BLANCO | C149: Envasados | D149: TPD63VS | E149: 04/2026 | F149: 0.289 | H149: =IF(ISNUMBER(G149),G149*(1+$C$4),IF(ISNUMBER(F149),F149*(1+$C$4),"")) -> 0.3179 | I149: =IF(Unidades!AE149=0,"SIN COMPRA",IF(ISNUMBER(H149),"VALORADO","FALTA PRECIO")) -> VALORADO | J149: Presupuesto anterior

Sheet Origen
A2: Necesidades y stock del archivo actualizado
A4: Los valores originales se conservan; para LAM1 solo se usa la fila de envasados en Unidades.
A6: Pestaña origen | B6: Fila | C6: Artículo | D6: Descripción | E6: Unidad | F6: Stock 30/09 | G6: Consumo oct–dic | H6: Stock 31/12 | I6: Necesidad 2027 | J6: Tratamiento
A7: Formulados | B7: 2 | C7: ACE | D7: ACETAMIDA | E7: kg | F7: 370 | G7: 131.44346 | H7: 238.55654 | I7: 447.23518 | J7: Incluido
A8: Formulados | B8: 3 | C8: ACIT | D8: ACIDO CÍTRICO MONOHIDRATADO | E8: kg | F8: 3406 | G8: 5991.0796 | H8: 0 | I8: 22406.94 | J8: Incluido
A9: Formulados | B9: 4 | C9: ADI | D9: ACIDO ADIPICO | E9: kg | F9: 5900 | G9: 947.99614 | H9: 4952.0039 | I9: 8825.0523 | J9: Incluido
A10: Formulados | B10: 5 | C10: AMARILLO | D10: COLOR AMARILLO | E10: kg | F10: 3 | G10: 0.069203718 | H10: 2.9307963 | I10: 0.54837 | J10: Incluido
A11: Formulados | B11: 6 | C11: AMO | D11: AMONÍACO | E11: kg | F11: 3200 | G11: 2147.689 | H11: 1052.311 | I11: 20113.937 | J11: Incluido
A12: Formulados | B12: 7 | C12: ANTI | D12: ANTIESPUMANTE ANTISCHIUMA GEN | E12: kg | F12: 90 | G12: 11.36837 | H12: 78.63163 | I12: 24.964915 | J12: Incluido
A13: Formulados | B13: 8 | C13: AR | D13: FINDET AR-52 | E13: kg | F13: 0 | G13: 2230.7547 | H13: 0 | I13: 14001.497 | J13: Incluido
A14: Formulados | B14: 9 | C14: ATC | D14: AATC | E14: kg | F14: 0 | G14: 12.627309 | H14: 0 | I14: 88.491 | J14: Incluido
A15: Formulados | B15: 10 | C15: AV24 | D15: AV24 | E15: kg | F15: 0 | G15: 3407.0981 | H15: 0 | I15: 8785.534 | J15: Incluido
A16: Formulados | B16: 11 | C16: BET | D16: BETAÍNA DE REMOLACHA | E16: kg | F16: 750 | G16: 1980.8607 | H16: 0 | I16: 13852.012 | J16: Incluido
A17: Formulados | B17: 12 | C17: BICAR | D17: BICARBONATO SÓDICO ALIM. | E17: kg | F17: 3485 | G17: 0 | H17: 3485 | I17: 1488.9981 | J17: Incluido
A18: Formulados | B18: 13 | C18: BOCAL | D18: BRETAX-CL | E18: kg | F18: 22445 | G18: 2464.3273 | H18: 19980.673 | I18: 17434.259 | J18: Incluido
... A105: Formulados | B105: 100 | C105: XT | D105: EXTRACTO ALGAS POLVO XT | E105: kg | F105: 158 | G105: 3404.6038 | H105: 0 | I105: 10197.89 | J105: Incluido
A106: Formulados | B106: 101 | C106: XT48 | D106: EXTRACTO DE ALGAS LÍQUIDO 48% | E106: kg | G106: 1993.0671 | H106: 0 | I106: 15005.52 | J106: Incluido
A107: Envasados | B107: 2 | C107: B200 | D107: BIDON 200 LITROS | E107: ud | F107: 61 | G107: 115.65553 | H107: 0 | I107: 519.54389 | J107: Incluido
A108: Envasados | B108: 3 | C108: B200GRIF | D108: GRIFO BIDÓN 200 L | E108: ud | F108: 0 | G108: 115.65553 | H108: 0 | I108: 519.54389 | J108: Incluido
A109: Envasados | B109: 4 | C109: B200TP | D109: TAPÓN 2" PARA GRIFO DE BIDÓN 200 L | E109: sin unidad | F109: 0 | G109: 100.48759 | H109: 0 | I109: 477.94389 | J109: Incluido
A110: Envasados | B110: 5 | C110: B20L | D110: BOLSA 20 L METALIZADA CON TAPÓN | E110: ud | F110: 34148 | G110: 18504.885 | H110: 15643.115 | I110: 112426.85 | J110: Incluido
A111: Envasados | B111: 6 | C111: B5ALC | D111: BOLSA ALCAPLANT 5 KG | E111: ud | F111: 33753 | G111: 15547.137 | H111: 18205.863 | I111: 97726.158 | J111: Incluido
A112: Envasados | B112: 7 | C112: BAG | D112: BOLSA INTERNA CONVERT KIT | E112: ud | F112: 0 | G112: 0 | H112: 0 | I112: 13.846154 | J112: Excluido por criterio previo
A113: Envasados | B113: 8 | C113: C1000 | D113: CONTENEDOR 1000 | E113: ud | F113: 61 | G113: 105.70157 | H113: 0 | I113: 408 | J113: Incluido
A114: Envasados | B114: 9 | C114: C1000R | D114: CONTENEDOR 1000 RECICLADO | E114: ud | F114: 0 | G114: 20.855915 | H114: 0 | I114: 127 | J114: Incluido
A115: Envasados | B115: 10 | C115: C1000R3P | D115: CONTENEDOR RECICLADO BOCA 3" ALCAPLANT | E115: ud | F115: 0 | G115: 14.584556 | H115: 0 | I115: 126.92308 | J115: Incluido
A116: Envasados | B116: 11 | C116: C1L | D116: CAJA 1 LITRO | E116: ud | F116: 8697 | G116: 7709.7366 | H116: 987.2634 | I116: 29197.968 | J116: Incluido
A117: Envasados | B117: 12 | C117: CAG | D117: CAJAS "CODIAGRO NUEVA CALIDAD" | E117: ud | F117: 9158 | G117: 6396.13 | H117: 2761.87 | I117: 50136.491 | J117: Incluido
A118: Envasados | B118: 13 | C118: CANT1 | D118: Cantonera Blanca 35x35x2,5x1280 | E118: ud | F118: 10392 | G118: 5023.1203 | H118: 5368.8797 | I118: 30465.83 | J118: Incluido
... A161: Envasados | B161: 56 | C161: TPD63VS | D161: TAPÓN D63 VALVULA SETA, BLANCO | E161: ud | F161: 1550 | G161: 1691.2251 | H161: 0 | I161: 11137.16 | J161: Incluido
